Workbook

Sheet README
B2: ASPIRE COMBINED UNDERWRITING MODEL v2 - DEMO: 8 sample deals, Deal sheet populated
B4: HOW TO RUN A DEAL
B5: Deal sheet: sections A, B and existing positions as always; DEAL PROFILE (right of the bank data): ISO, industry, new/renewal, credit score. State is optional and only informational. Position comes from C42.
B6: Read section C (cash flow), C2 (house-book indicators, same colour code), D (decision on the requested offer), E (max offer at the sizing line), F (final offer). Decision Summary has the full read-out; Comparable Deals lists the deals behind it.
B8: HOW THE HOUSE BOOK CHANGES THE OFFER
B9: 1. Historical Score matches the deal to seven cohorts (new/renewal + industry + position ... down to the whole seasoned book) and picks the first one with enough seasoned deals and dollars.
B10: 2. Its principal lost rate is blended toward the book by credibility Z = n/(n+K) and divided by the book rate -> relative index (1.00 = book).
B11: 3. The index lands on a row of the modifier table (Controls section 5). Supportive book -> SIZING FLEX moves the sizing lines toward the red lines (recommended 90% for Strong positive, 45% for Mild positive), so the max offer is larger and metrics may show YELLOW. Neutral -> flex 0 = the tool exactly as built. Negative -> green lines plus a fund multiplier, shorter band, higher factor tier, weekly.
B12: 4. Section E sizes the max offer at the sizing lines (column H of section C). Offer Engine shows green-line base vs sized vs final side by side and re-checks every metric at the final offer: yellow is allowed, red never.
B14: HARD RULES
B15: History never removes a knockout, never turns a metric red (flex is capped below 100%), never exceeds the sized max, and is Neutral whenever no cohort meets the minimums.
B17: COLOUR KEY
B18: Blue on yellow = input. Green font = link to Controls. Purple bold (column H, section C) = sizing line in use. Same GREEN / YELLOW / RED cells in C2 as in C.

Sheet Deal
B1: UNDERWRITING TOOL
B2: DECISION | C2: =C62 -> CONDITIONAL | D2: =IF(C62="","",C60&" red flag(s) vs limit "&C61&" | "&COUNTIF(F38:F45,"GREEN")&"G / "&COUNTIF(F38:F45,"YELLOW")&"Y / "&COUNTIF(F38:F45,"RED")&"R | score "&TEXT(C65,"0.0")&"/"&D65&" = "&C66&" | FINAL: "&IF(C77="","-",C77)) -> 0 red flag(s) vs limit 2 | 7G / 1Y / 0R | score 7.5/8 = Strong | FINAL: CONDITIONAL
B4: A. OFFER | J4: MONEYBADGER CROSS-CHECK
B5: Fund $ | C5: Factor | D5: =IF($E$6="Weekly","Term (weeks)","Term (daily pmts)") -> Term (weeks) | E5: Freq | F5: Fee % | J5: Metric | K5: This tool | L5: MoneyBadger | M5: Diff
B6: 40000 | C6: 1.45 | D6: 24 | E6: Weekly | F6: =Controls!$B$15 -> 0.05 | J6: =IF($E$6="Weekly","Weekly remittance","Daily remittance") -> Weekly remittance | K6: =IF(OR($E$6="",C8="",C24=0),"",IF($E$6="Weekly",D8,C8)) -> 2416.6667 | L6: =IF(OR(L7="",C24=0),"",L7*C24/IF($E$6="Weekly",$L$8,$L$9)) -> 2417.1562 | M6: =IF(OR(K6="",L6=""),"",L6-K6) -> 0.48958333
B7: Payback | C7: Daily $ | D7: Weekly $ | E7: Monthly $ | F7: Term (mo) | G7: Net $ | J7: Holdback % | K7: =IF(OR(D8="",C24=0),"",E8/C24) -> 0.12135169 | L7: =IF(OR($E$6="",C8="",C24=0),"",ROUND(IF($E$6="Weekly",D8*$L$8,C8*$L$9)/C24*100,2)/100) -> 0.1121 | M7: =IF(OR(K7="",L7=""),"",L7-K7) -> -0.0092516908
B8: =IF(OR(B6="",C6=""),"",B6*C6) -> 58000 | C8: =IF(OR(B8="",D6="",D6=0),"",IF(E6="Weekly",(B8/D6)/5,B8/D6)) -> 483.33333 | D8: =IF(C8="","",C8*5) -> 2416.6667 | E8: =IF(C8="","",C8*$K$9) -> 10466.583 | F8: =IF(OR(D6="",D6=0),"",IF(E6="Weekly",D6,D6/5)/($K$9/5)) -> 5.5414454 | G8: =IF(B6="","",B6-(B6*F6)) -> 38000 | J8: Weeks / month | K8: =Controls!$B$28 -> 4.331 | L8: =Controls!$B$30 -> 4 | M8: =IF(OR(K8="",L8=""),"",L8-K8) -> -0.331
J9: Days / month | K9: =Controls!$B$29 -> 21.655 | L9: =Controls!$B$31 -> 21 | M9: =IF(OR(K9="",L9=""),"",L9-K9) -> -0.655
B10: B. BANK DATA (up to 12 months)
B11: Month - NEWEST FIRST | C11: True rev $ | D11: Avg daily bal $ | E11: Neg days | F11: NSFs | G11: MoM % | J11: DEAL PROFILE (house-book match inputs)
B12: Aug | C12: 88000 | D12: 7400 | E12: 0 | F12: 0 | G12: =IF(OR(C12="",C13=""),"",(C12-C13)/C13) -> 0.047619048 | J12: ISO | K12: Fundwell | L12: =IF(K12="","",COUNTIF('Historical Data'!$K$2:$K$9,K12)&" deals in book") -> 4 deals in book
B13: Jul | C13: 84000 | D13: 6900 | E13: 0 | F13: 1 | G13: =IF(OR(C13="",C14=""),"",(C13-C14)/C14) -> -0.076923077 | J13: Industry (SIC major group) | K13: Eating & Drinking Places | L13: =IF(K13="","",COUNTIF('Historical Data'!$Y$2:$Y$9,K13)&" deals in book") -> 1 deals in book
B14: Jun | C14: 91000 | D14: 8100 | E14: 0 | F14: 0 | G14: =IF(OR(C14="",C15=""),"",(C14-C15)/C15) -> 0.1097561 | J14: State (optional - informational only) | K14: NJ | L14: =IF(K14="","not needed for an offer",COUNTIF('Historical Data'!$J$2:$J$9,K14)&" deals in book") -> 4 deals in book
B15: May | C15: 82000 | D15: 6500 | E15: 1 | F15: 0 | G15: =IF(OR(C15="",C16=""),"",(C15-C16)/C16) | J15: New deal or renewal | K15: New Deal | L15: =IF(K15="","required for history match","")
G16: =IF(OR(C16="",C17=""),"",(C16-C17)/C17) | J16: Credit score (FICO) | K16: 672 | L16: =IF(K16="","not scored",IF(K16>=Controls!$B$12,"GREEN",IF(K16>=Controls!$C$12,"YELLOW","RED"))) -> GREEN
G17: =IF(OR(C17="",C18=""),"",(C17-C18)/C18) | J17: Position for matching = C42 (existing positions + 1). Bands and thresholds: Controls.
G18: =IF(OR(C18="",C19=""),"",(C18-C19)/C19)
G19: =IF(OR(C19="",C20=""),"",(C19-C20)/C20)
G20: =IF(OR(C20="",C21=""),"",(C20-C21)/C21)
G21: =IF(OR(C21="",C22=""),"",(C21-C22)/C22)
G22: =IF(OR(C22="",C23=""),"",(C22-C23)/C23)
B24: AVG / TOTAL (months entered) | C24: =IF(COUNT(C12:C23)=0,0,AVERAGE(C12:C23)) -> 86250 | D24: =IF(COUNT(D12:D23)=0,0,AVERAGE(D12:D23)) -> 7225 | E24: =SUM(E12:E23) -> 1 | F24: =SUM(F12:F23) -> 1 | G24: =IFERROR(AVERAGE(G12:G22),"") -> 0.026817356
B26: EXISTING POSITIONS (freq Monthly = leverage only, NOT a position)
B27: Funder | C27: Funded $ | D27: Payment | E27: Freq | F27: Daily equiv | G27: Start Date | H27: Est Term | I27: Est term (mo) | J27: Mo. remaining
E28: Weekly | F28: =IF(D28<>"",IF(E28="Daily",D28,IF(E28="Weekly",D28/5,D28/$K$9)),IF(C28="","",C28*Controls!$B$33/(Controls!$B$23*$K$9))) | H28: =IF(OR(C28="",D28=""),"",ROUND(C28*Controls!$B$33/D28,0)) | I28: =IF(H28="","",H28/IF(E28="Daily",$K$9,IF(E28="Weekly",$K$9/5,1))) | J28: =IF(OR(I28="",G28=""),"",MAX(0,I28-(TODAY()-G28)/Controls!$B$32))
E29: Weekly | F29: =IF(D29<>"",IF(E29="Daily",D29,IF(E29="Weekly",D29/5,D29/$K$9)),IF(C29="","",C29*Controls!$B$33/(Controls!$B$23*$K$9))) | H29: =IF(OR(C29="",D29=""),"",ROUND(C29*Controls!$B$33/D29,0)) | I29: =IF(H29="","",H29/IF(E29="Daily",$K$9,IF(E29="Weekly",$K$9/5,1))) | J29: =IF(OR(I29="",G29=""),"",MAX(0,I29-(TODAY()-G29)/Controls!$B$32))
E30: Weekly | F30: =IF(D30<>"",IF(E30="Daily",D30,IF(E30="Weekly",D30/5,D30/$K$9)),IF(C30="","",C30*Controls!$B$33/(Controls!$B$23*$K$9))) | H30: =IF(OR(C30="",D30=""),"",ROUND(C30*Controls!$B$33/D30,0)) | I30: =IF(H30="","",H30/IF(E30="Daily",$K$9,IF(E30="Weekly",$K$9/5,1))) | J30: =IF(OR(I30="",G30=""),"",MAX(0,I30-(TODAY()-G30)/Controls!$B$32))
E31: Weekly | F31: =IF(D31<>"",IF(E31="Daily",D31,IF(E31="Weekly",D31/5,D31/$K$9)),IF(C31="","",C31*Controls!$B$33/(Controls!$B$23*$K$9))) | H31: =IF(OR(C31="",D31=""),"",ROUND(C31*Controls!$B$33/D31,0)) | I31: =IF(H31="","",H31/IF(E31="Daily",$K$9,IF(E31="Weekly",$K$9/5,1))) | J31: =IF(OR(I31="",G31=""),"",MAX(0,I31-(TODAY()-G31)/Controls!$B$32))
E32: Weekly | F32: =IF(D32<>"",IF(E32="Daily",D32,IF(E32="Weekly",D32/5,D32/$K$9)),IF(C32="","",C32*Controls!$B$33/(Controls!$B$23*$K$9))) | H32: =IF(OR(C32="",D32=""),"",ROUND(C32*Controls!$B$33/D32,0)) | I32: =IF(H32="","",H32/IF(E32="Daily",$K$9,IF(E32="Weekly",$K$9/5,1))) | J32: =IF(OR(I32="",G32=""),"",MAX(0,I32-(TODAY()-G32)/Controls!$B$32))
E33: Weekly | F33: =IF(D33<>"",IF(E33="Daily",D33,IF(E33="Weekly",D33/5,D33/$K$9)),IF(C33="","",C33*Controls!$B$33/(Controls!$B$23*$K$9))) | H33: =IF(OR(C33="",D33=""),"",ROUND(C33*Controls!$B$33/D33,0)) | I33: =IF(H33="","",H33/IF(E33="Daily",$K$9,IF(E33="Weekly",$K$9/5,1))) | J33: =IF(OR(I33="",G33=""),"",MAX(0,I33-(TODAY()-G33)/Controls!$B$32))
B34: Positions (excl. Monthly) | C34: =SUMPRODUCT(((C28:C33<>"")+(D28:D33<>"")>0)*(E28:E33<>"Monthly")) -> 0 | D34: Total existing daily | E34: =SUM(F28:F33) -> 0 | F34: =E34*$K$9 -> 0 | G34: /month
B36: C. METRICS
B37: Metric | C37: Value | D37: Green | E37: Red | F37: Status | G37: Knockout | H37: Sizing line
B38: Total LVG (all debt / rev) | C38: =IF(C24=0,"",(E34+IF(C8="",0,C8))*$K$9/C24) -> 0.12135169 | D38: =Controls!$B$5 -> 0.3 | E38: =Controls!$C$5 -> 0.45 | F38: =IF(C38="","",IF(C38>=G38,"KNOCKOUT",IF(C38<=D38,"GREEN",IF(C38>=E38,"RED","YELLOW")))) -> GREEN | G38: =Controls!$D$5 -> 0.55 | H38: =D38+'Historical Score'!$C$42*(E38-D38) -> 0.3
B39: New holdback SP% | C39: =IF(OR(C24=0,E8=""),"",E8/C24) -> 0.12135169 | D39: =Controls!$B$6 -> 0.18 | E39: =Controls!$C$6 -> 0.25 | F39: =IF(C39="","",IF(C39>=G39,"KNOCKOUT",IF(C39<=D39,"GREEN",IF(C39>=E39,"RED","YELLOW")))) -> GREEN | G39: =Controls!$D$6 -> 0.35 | H39: =D39+'Historical Score'!$C$42*(E39-D39) -> 0.18
B40: Daily debt / balance | C40: =IF(D24=0,"",(E34+IF(C8="",0,C8))/D24) -> 0.066897347 | D40: =Controls!$B$7 -> 0.18 | E40: =Controls!$C$7 -> 0.3 | F40: =IF(C40="","",IF(C40>=G40,"KNOCKOUT",IF(C40<=D40,"GREEN",IF(C40>=E40,"RED","YELLOW")))) -> GREEN | G40: =Controls!$D$7 -> 0.35 | H40: =D40+'Historical Score'!$C$42*(E40-D40) -> 0.18
B41: Fund / revenue | C41: =IF(OR(C24=0,B6=""),"",B6/C24) -> 0.46376812 | D41: =Controls!$B$8 -> 0.6 | E41: =Controls!$C$8 -> 0.9 | F41: =IF(C41="","",IF(C41>=G41,"KNOCKOUT",IF(C41<=D41,"GREEN",IF(C41>=E41,"RED","YELLOW")))) -> GREEN | G41: =Controls!$D$8 -> 1.25 | H41: =D41+'Historical Score'!$C$42*(E41-D41) -> 0.6
B42: # positions (incl. new) | C42: =IF(C24=0,"",C34+1) -> 1 | D42: =Controls!$B$9 -> 2 | E42: =Controls!$C$9 -> 5 | F42: =IF(C42="","",IF(C42>=G42,"KNOCKOUT",IF(C42<=D42,"GREEN",IF(C42>=E42,"RED","YELLOW")))) -> GREEN | G42: =Controls!$D$9 -> 6
B43: Revenue trend (avg MoM) | C43: =G24 -> 0.026817356 | D43: =Controls!$B$10 -> -0.05 | E43: =Controls!$C$10 -> -0.15 | F43: =IF(C24=0,"",IF(NOT(ISNUMBER(C43)),"YELLOW",IF(C43<=G43,"KNOCKOUT",IF(C43>=D43,"GREEN",IF(C43<=E43,"RED","YELLOW"))))) -> GREEN | G43: =Controls!$D$10 -> -0.3
B44: Neg days + NSFs (total) | C44: =E24+F24 -> 2 | D44: =Controls!$B$11 -> 1 | E44: =Controls!$C$11 -> 6 | F44: =IF(C44="","",IF(C44>=G44,"KNOCKOUT",IF(C44<=D44,"GREEN",IF(C44>=E44,"RED","YELLOW")))) -> YELLOW | G44: =Controls!$D$11 -> 10
B45: Credit score (FICO) | C45: =IF(K16="","",K16) -> 672 | D45: =Controls!$B$12 -> 650 | E45: =Controls!$C$12 -> 630 | F45: =IF(C45="","",IF(AND(G45<>0,C45<=G45),"KNOCKOUT",IF(C45>=D45,"GREEN",IF(C45<E45,"RED","YELLOW")))) -> GREEN | G45: =Controls!$D$12 -> 0
B46: Existing leverage (before new) | C46: =IF(C24=0,"",F34/C24) -> 0 | D46: - | E46: - | F46: INFO
B47: Balance / revenue | C47: =IF(C24=0,"",D24/C24) -> 0.083768116 | D47: - | E47: - | F47: INFO
B49: C2. HOUSE-BOOK INDICATORS (set the sizing line + modifier; NOT counted in the cash-flow score)
B50: Cohort | C50: Blended lost rate | D50: Green <= | E50: Red > | F50: Status | G50: Seasoned n
B51: ="Primary cohort: "&'Historical Score'!$C$30 -> Primary cohort: T6: new/renewal only | C51: =IF('Historical Score'!$C$29=7,"",'Historical Score'!$C$38) -> 0.42404762 | D51: ='Historical Score'!$C$10*Controls!$A$50 -> 0.3485 | E51: ='Historical Score'!$C$10*Controls!$A$51 -> 0.4715 | F51: =IF('Historical Score'!$C$29=7,"NO EVIDENCE",IF('Historical Score'!$C$39<=Controls!$A$50,"GREEN",IF('Historical Score'!$C$39<=Controls!$A$51,"YELLOW","RED"))) -> YELLOW | G51: ='Historical Score'!$C$31 -> 5 / 6
B52: ISO | C52: =IF('Historical Score'!$L$25="","",'Historical Score'!$W$25) -> 0.41181818 | D52: ='Historical Score'!$C$10*Controls!$A$50 -> 0.3485 | E52: ='Historical Score'!$C$10*Controls!$A$51 -> 0.4715 | F52: =IF('Historical Score'!$E$25=0,"NO DEALS",IF('Historical Score'!$L$25="","TOO FEW",IF('Historical Score'!$X$25<=Controls!$A$50,"GREEN",IF('Historical Score'!$X$25<=Controls!$A$51,"YELLOW","RED")))) -> YELLOW | G52: ='Historical Score'!$E$25 -> 3
B53: Industry | C53: =IF('Historical Score'!$L$24="","",'Historical Score'!$W$24) | D53: ='Historical Score'!$C$10*Controls!$A$50 -> 0.3485 | E53: ='Historical Score'!$C$10*Controls!$A$51 -> 0.4715 | F53: =IF('Historical Score'!$E$24=0,"NO DEALS",IF('Historical Score'!$L$24="","TOO FEW",IF('Historical Score'!$X$24<=Controls!$A$50,"GREEN",IF('Historical Score'!$X$24<=Controls!$A$51,"YELLOW","RED")))) -> TOO FEW | G53: ='Historical Score'!$E$24 -> 1
B54: New deal / renewal | C54: =IF('Historical Score'!$L$23="","",'Historical Score'!$W$23) -> 0.42404762 | D54: ='Historical Score'!$C$10*Controls!$A$50 -> 0.3485 | E54: ='Historical Score'!$C$10*Controls!$A$51 -> 0.4715 | F54: =IF('Historical Score'!$E$23=0,"NO DEALS",IF('Historical Score'!$L$23="","TOO FEW",IF('Historical Score'!$X$23<=Controls!$A$50,"GREEN",IF('Historical Score'!$X$23<=Controls!$A$51,"YELLOW","RED")))) -> YELLOW | G54: ='Historical Score'!$E$23 -> 5
B55: Position | C55: =IF('Historical Score'!$L$22="","",'Historical Score'!$W$22) | D55: ='Historical Score'!$C$10*Controls!$A$50 -> 0.3485 | E55: ='Historical Score'!$C$10*Controls!$A$51 -> 0.4715 | F55: =IF('Historical Score'!$E$22=0,"NO DEALS",IF('Historical Score'!$L$22="","TOO FEW",IF('Historical Score'!$X$22<=Controls!$A$50,"GREEN",IF('Historical Score'!$X$22<=Controls!$A$51,"YELLOW","RED")))) -> TOO FEW | G55: ='Historical Score'!$E$22 -> 1
B56: State (informational - never sizes the offer) | C56: =IF('Historical Score'!$L$26="","",'Historical Score'!$W$26) -> 0.41181818 | D56: ='Historical Score'!$C$10*Controls!$A$50 -> 0.3485 | E56: ='Historical Score'!$C$10*Controls!$A$51 -> 0.4715 | F56: =IF('Historical Score'!$E$26=0,"NO DEALS",IF('Historical Score'!$L$26="","TOO FEW",IF('Historical Score'!$X$26<=Controls!$A$50,"GREEN",IF('Historical Score'!$X$26<=Controls!$A$51,"YELLOW","RED")))) -> YELLOW | G56: ='Historical Score'!$E$26 -> 3
B57: Seasoned deals behind the primary cohort | C57: =IF('Historical Score'!$C$29=7,0,INDEX('Historical Score'!$E$14:$E$20,'Historical Score'!$C$29)) -> 5 | D57: =Controls!$B$44 -> 5 | E57: =Controls!$B$40 -> 3 | F57: =IF(C57>=D57,"GREEN",IF(C57>=E57,"YELLOW","RED")) -> GREEN | G57: ="modifier: "&'Historical Score'!$C$41&" | sizing flex "&TEXT('Historical Score'!$C$42,"0%") -> modifier: Neutral | sizing flex 0%
B59: D. DECISION (cash-flow layer, on the requested offer)
B60: Red flags | C60: =COUNTIF(F38:F45,"RED")+COUNTIF(F38:F45,"KNOCKOUT") -> 0 | D60: Knockouts | E60: =COUNTIF(F38:F45,"KNOCKOUT") -> 0
B61: Decline if red flags >= (Controls) | C61: =Controls!$B$13 -> 2 | D61: Minimum fund $ | E61: =Controls!$B$14 -> 10000
B62: DECISION | C62: =IF(C24=0,"",IF(OR(E60>0,IF(ISNUMBER(C73),C73,0)<E61),"DECLINE",IF(OR(B6="",B6=0),"",IF(C60>=C61,"DECLINE",IF(COUNTIF(F38:F45,"GREEN")=D65,"APPROVE","CONDITIONAL"))))) -> CONDITIONAL | D62: =IF(C62="DECLINE",IF(E60>0,"KNOCKOUT: "&INDEX(B38:B45,MATCH("KNOCKOUT",F38:F45,0))&" is past its knockout line.",IF(C60>=C61,"Red flags reached the threshold.","Max fund "&IF(ISNUMBER(C73),TEXT(C73,"$#,##0"),"$0")&" is below your minimum "&TEXT(E61,"$#,##0")&".")),IF(C62="APPROVE","All "&D65&" decision metrics green.",IF(C62="","Enter offer + bank data.","Fundable but not clean - review yellows/reds above."))) -> Fundable but not clean - review yellows/reds above.
B64: E. DEAL QUALITY & MAXIMUM OFFER at the sizing line (green line unless the house book is supportive)
B65: Score (G=1, Y=0.5, R=0) | C65: =COUNTIF(F38:F45,"GREEN")+0.5*COUNTIF(F38:F45,"YELLOW") -> 7.5 | D65: =SUMPRODUCT(--(F38:F45<>"")) -> 8 | E65: scored metrics
B66: Tier (score scaled to 7 for the bands) | C66: =IF(C24=0,"",IF(D67>=Controls!$B$25,"Strong",IF(D67>=Controls!$C$25,"Solid",IF(D67>=Controls!$D$25,"Moderate","Weak")))) -> Strong
B67: Max daily by SP% sizing line | C67: =IF(C24=0,"",H39*C24/$K$9) -> 716.9245 | D67: =IF(D65=0,0,C65*7/D65) -> 6.5625 | E67: scaled score /7
B68: Max daily by Total LVG sizing line | C68: =IF(C24=0,"",(H38*C24-F34)/$K$9) -> 1194.8742
B69: Max daily by Daily/Balance sizing line | C69: =IF(OR(C24=0,D24=0),"",H40*D24-E34) -> 1300.5
B70: MAX DAILY (weakest link) | C70: =IF(C24=0,"",MAX(0,MIN(C67:C69))) -> 716.9245 | D70: =IF(C70="","",IF(C70=0,"no clean room - existing debt is over the sizing line",INDEX({"SP% holdback";"Total LVG";"Daily/Balance"},MATCH(C70,C67:C69,0))&" is the limit")) -> SP% holdback is the limit
B71: Weekly / monthly equivalent | C71: =IF(OR(C70="",C70=0),"",C70*5) -> 3584.6225 | D71: =IF(OR(C70="",C70=0),"",C70*$K$9) -> 15525
B72: Term (daily pmts) / factor from bands | C72: =IF(OR(C70="",C70=0,C65=""),"",MAX(20,MIN(INDEX(Controls!$B$19:$B$22,MATCH(D67,Controls!$A$19:$A$22,1)),FLOOR(Controls!$B$23*$K$9,5),FLOOR(H41*C24*D72/C70,5)))) -> 100 | D72: =IF(OR(C65="",C24=0),"",INDEX(Controls!$C$19:$C$22,MATCH(D67,Controls!$A$19:$A$22,1))) -> 1.45
B73: MAX FUND at the sizing line | C73: =IF(COUNTIF(F42:F45,"KNOCKOUT")>0,"-",IF(OR(C70="",C70=0,C72="",D72=""),"",FLOOR(C70*C72/D72,500))) -> 49000 | D73: =IF(C73="-","KNOCKOUT on the merchant - do not fund.",IF(C73="","","payback "&TEXT(C73*D72,"$#,##0")&" over "&C72&" daily pmts ("&TEXT(C72/5,"0")&" wks) | green-line max "&IF(ISNUMBER('Offer Engine'!$C$8),TEXT('Offer Engine'!$C$8,"$#,##0"),"-"))) -> payback $71,050 over 100 daily pmts (20 wks) | green-line max $49,000
B75: F. FINAL OFFER (max at the sizing line, then the modifier) - full detail on Decision Summary
B76: Item | C76: Value | D76: Detail
B77: FINAL DECISION | C77: ='Decision Summary'!$C$5 -> CONDITIONAL | D77: ='Decision Summary'!$D$5 -> Yellows remain at the final offer or the evidence is negative - see the metric rows.
B78: Recommended fund | C78: ='Decision Summary'!$C$6 -> 49000 | D78: ='Decision Summary'!$D$6 -> green-line max $49,000 | sized max $49,000 | final = 100% of sized (requested $40,000)
B79: Factor | C79: ='Decision Summary'!$C$7 -> 1.45 | D79: ='Decision Summary'!$D$7 -> band 1.45
B80: Term | C80: ='Decision Summary'!$C$8 -> 20 | D80: ='Decision Summary'!$D$8 -> weeks (4.6 months; sized 100 daily pmts)
B81: Payment | C81: ='Decision Summary'!$C$9 -> 3552.5 | D81: ='Decision Summary'!$D$9 -> per week; daily-equivalent $710.50, monthly $15,386; payback $71,050, net $46,550
B82: Frequency | C82: ='Decision Summary'!$C$10 -> Weekly | D82: ='Decision Summary'!$D$10 -> As proposed on the Deal sheet
B83: Sizing line used | C83: ='Decision Summary'!$C$11 -> 0 | D83: ='Decision Summary'!$D$11 -> green lines (the cash-flow tool as built)
B84: Holdback % at final offer | C84: ='Decision Summary'!$C$12 -> 0.17838699 | D84: ='Decision Summary'!$D$12 -> GREEN (green 18% / red 25%)
B85: Historical modifier | C85: ='Decision Summary'!$C$17 -> Neutral | D85: ='Decision Summary'!$D$17 -> index 1.03 (1.00 = seasoned book); sizing flex 0%, fund x 1.00, term step 0, factor step 0
B86: Comparable deals (seasoned / all) | C86: ='Decision Summary'!$C$19 -> 5 / 6 | D86: ='Decision Summary'!$D$19 -> T6: new/renewal only
B87: Cohort principal lost rate | C87: ='Decision Summary'!$C$21 -> 0.50833333 | D87: ='Decision Summary'!$D$21 -> vs seasoned book 41.0%; blended 42.4%; collected on defaults 32%
B88: Manual-review triggers | C88: ='Decision Summary'!$C$25 | D88: ='Decision Summary'!$D$25 -> blank = none
B89: Layer 1 stays the ceiling: the sizing line never reaches the red line, knockouts are never removed, the final fund never exceeds the max at the sizing line. See Checks.

Sheet Decision Summary
B1: DECISION SUMMARY
B4: Item | C4: Value | D4: Detail
B5: DECISION | C5: =IF(Deal!$C$24=0,"",IF(OR(Deal!$C$73="-",Deal!$C$73="",'Offer Engine'!$E$8="",'Offer Engine'!$E$8=0,'Offer Engine'!$E$8<Controls!$B$14,'Offer Engine'!$E$41>=Controls!$B$13),"DECLINE",IF(C25<>"","MANUAL REVIEW",IF(OR(COUNTIF('Offer Engine'!$F$26:$F$33,"YELLOW")+COUNTIF('Offer Engine'!$F$26:$F$33,"RED")>0,'Historical Score'!$C$40>=4),"CONDITIONAL","APPROVE")))) -> CONDITIONAL | D5: =IF(C5="","Enter bank data + deal profile.",IF(C5="DECLINE",IF(COUNTIF(Deal!$F$42:$F$45,"KNOCKOUT")>0,"Merchant knockout: "&INDEX(Deal!$B$42:$B$45,MATCH("KNOCKOUT",Deal!$F$42:$F$45,0))&".",IF(OR('Offer Engine'!$E$8="",'Offer Engine'!$E$8=0),"No clean room under the sizing line.",IF('Offer Engine'!$E$8<Controls!$B$14,"Final fund "&TEXT('Offer Engine'!$E$8,"$#,##0")&" is below the minimum "&TEXT(Controls!$B$14,"$#,##0")&".","Red flags at the final offer reached the limit."))),IF(C5="MANUAL REVIEW","Triggers: "&C25,IF(C5="APPROVE","All metrics green at the final offer; evidence neutral or better.","Yellows remain at the final offer or the evidence is negative - see the metric rows.")))) -> Yellows remain at the final offer or the evidence is negative - see the metric rows.
B6: Recommended funding amount | C6: ='Offer Engine'!$E$8 -> 49000 | D6: =IF(OR(C6="",C6="-"),"","green-line max "&IF(ISNUMBER('Offer Engine'!$C$8),TEXT('Offer Engine'!$C$8,"$#,##0"),"-")&" | sized max "&IF(ISNUMBER('Offer Engine'!$D$8),TEXT('Offer Engine'!$D$8,"$#,##0"),"-")&" | final = "&TEXT(C6/'Offer Engine'!$D$8,"0%")&" of sized (requested "&IF(Deal!$B$6="","n/a",TEXT(Deal!$B$6,"$#,##0"))&")") -> green-line max $49,000 | sized max $49,000 | final = 100% of sized (requested $40,000)
B7: Recommended factor rate | C7: ='Offer Engine'!$E$7 -> 1.45 | D7: =IF(C7="","","band "&TEXT('Offer Engine'!$D$7,"0.00")&IF('Offer Engine'!$E$7>'Offer Engine'!$D$7," -> raised one tier by the modifier","")) -> band 1.45
B8: Recommended term | C8: ='Offer Engine'!$E$17 -> 20 | D8: =IF(C8="","",IF('Offer Engine'!$E$16="Weekly","weeks","daily payments")&" ("&TEXT('Offer Engine'!$E$22,"0.0")&" months; sized "&'Offer Engine'!$D$6&" daily pmts"&IF('Offer Engine'!$E$6<'Offer Engine'!$D$6,", shortened by the modifier","")&")") -> weeks (4.6 months; sized 100 daily pmts)
B9: Payment | C9: ='Offer Engine'!$E$18 -> 3552.5 | D9: =IF(C9="","","per "&IF('Offer Engine'!$E$16="Weekly","week","business day")&"; daily-equivalent "&TEXT('Offer Engine'!$E$9,"$#,##0.00")&", monthly "&TEXT('Offer Engine'!$E$19,"$#,##0")&"; payback "&TEXT('Offer Engine'!$E$20,"$#,##0")&", net "&TEXT('Offer Engine'!$E$21,"$#,##0")) -> per week; daily-equivalent $710.50, monthly $15,386; payback $71,050, net $46,550
B10: Daily or weekly | C10: ='Offer Engine'!$E$16 -> Weekly | D10: =IF('Offer Engine'!$C$13="Weekly","Weekly required by the modifier","As proposed on the Deal sheet") -> As proposed on the Deal sheet
B11: Sizing line used | C11: ='Offer Engine'!$C$15 -> 0 | D11: =IF(C11=0,"green lines (the cash-flow tool as built)",TEXT(C11,"0%")&" of the way from the green line to the red line - the book is supportive, yellows allowed") -> green lines (the cash-flow tool as built)
B12: Holdback % | C12: ='Offer Engine'!$E$27 -> 0.17838699 | D12: =IF(C12="","",'Offer Engine'!$F$27&" (green "&TEXT(Controls!$B$6,"0%")&" / red "&TEXT(Controls!$C$6,"0%")&")") -> GREEN (green 18% / red 25%)
B13: Total leverage (all debt / revenue) | C13: ='Offer Engine'!$E$26 -> 0.17838699 | D13: =IF(C13="","",'Offer Engine'!$F$26&" (green "&TEXT(Controls!$B$5,"0%")&" / red "&TEXT(Controls!$C$5,"0%")&")") -> GREEN (green 30% / red 45%)
B14: Funding-to-revenue | C14: ='Offer Engine'!$E$29 -> 0.56811594 | D14: =IF(C14="","",'Offer Engine'!$F$29&" (green "&TEXT(Controls!$B$8,"0.00")&" / red "&TEXT(Controls!$C$8,"0.00")&")") -> GREEN (green 0.60 / red 0.90)
B15: Daily debt-to-balance | C15: ='Offer Engine'!$E$28 -> 0.0983391 | D15: =IF(C15="","",'Offer Engine'!$F$28&" (green "&TEXT(Controls!$B$7,"0%")&" / red "&TEXT(Controls!$C$7,"0%")&")") -> GREEN (green 18% / red 30%)
B16: Number of positions (incl. new) | C16: =Deal!$C$42 -> 1 | D16: =IF(C16="","",Deal!$F$42) -> GREEN
B17: Historical modifier | C17: ='Historical Score'!$C$41 -> Neutral | D17: =IF(C17="","","index "&TEXT('Historical Score'!$C$39,"0.00")&" (1.00 = seasoned book); sizing flex "&TEXT('Historical Score'!$C$42,"0%")&", fund x "&TEXT('Historical Score'!$C$43,"0.00")&", term step "&'Historical Score'!$C$44&", factor step "&'Historical Score'!$C$45) -> index 1.03 (1.00 = seasoned book); sizing flex 0%, fund x 1.00, term step 0, factor step 0
B18: Cash-flow risk score | C18: =Deal!$C$65 -> 7.5 | D18: =IF(C18="","","of "&Deal!$D$65&" scored metrics = "&Deal!$C$66&" (scaled "&TEXT(Deal!$D$67,"0.0")&"/7 for the bands)") -> of 8 scored metrics = Strong (scaled 6.6/7 for the bands)
B19: Number of comparable deals (seasoned / all) | C19: ='Historical Score'!$C$31 -> 5 / 6 | D19: ='Historical Score'!$C$30 -> T6: new/renewal only
B20: Percentage of comparable deals seasoned | C20: ='Historical Score'!$C$32 -> 0.83333333 | D20: ="credibility Z "&TEXT('Historical Score'!$C$37,"0.00")&" (n / (n + K))" -> credibility Z 0.14 (n / (n + K))
B21: Comparable-cohort principal lost rate | C21: ='Historical Score'!$C$33 -> 0.50833333 | D21: =IF(C21="","too few seasoned deals to show a rate","vs seasoned book "&TEXT('Historical Score'!$C$10,"0.0%")&"; blended "&TEXT('Historical Score'!$C$38,"0.0%")&"; collected on defaults "&IF('Historical Score'!$C$36="","n/a",TEXT('Historical Score'!$C$36,"0%"))) -> vs seasoned book 41.0%; blended 42.4%; collected on defaults 32%
B22: Comparable-cohort return on funded capital | C22: ='Historical Score'!$C$35 -> -0.38333333 | D22: ="seasoned deals only" -> seasoned deals only
B23: Largest historical impact | C23: ='Historical Score'!$C$48 -> New/renewal only | D23: ='Historical Score'!$C$49 -> 42.4% vs 41.0% book (5 seasoned deals)
B24: Metric that limited the offer | C24: =IF(Deal!$D$70="","",Deal!$D$70) -> SP% holdback is the limit | D24: =IF(Deal!$C$70="","",IF(Deal!$C$70=0,"existing debt already exceeds the sizing line",IF(Deal!$C$72=FLOOR(Deal!$H$41*Deal!$C$24*Deal!$D$72/Deal!$C$70,5),"term also capped by the fund/revenue sizing line","term set by the score band"))) -> term also capped by the fund/revenue sizing line
B25: Manual-review triggers fired | C25: =IF(AND(Controls!$B$74="Y",'Offer Engine'!$C$14="Y"),"Severe historical modifier; ","")&IF(AND(Controls!$B$75="Y",Deal!$F$45="RED",COUNTIF('Offer Engine'!$F$26:$F$32,"RED")>0),"Credit RED plus another RED; ","")&IF(AND(Controls!$B$76="Y",ISNUMBER(Deal!$C$42),IF(ISNUMBER(Deal!$C$42),Deal!$C$42,0)>=Controls!$C$76),"Positions incl. new at/above "&Controls!$C$76&"; ","")&IF(AND(Controls!$B$77="Y",Deal!$K$15="New Deal",ISNUMBER(Deal!$C$42),IF(ISNUMBER(Deal!$C$42),Deal!$C$42,0)>=Controls!$C$77,OR(Deal!$K$13="General Building Contractors",Deal!$K$13="Special Trade Contractors",Deal!$K$13="Heavy Construction")),"New "&Controls!$C$77&"rd+ position construction deal; ","")&IF(AND(Controls!$B$78="Y",OR(AND(Deal!$K$12<>"",COUNTIF('Historical Data'!$K$2:$K$9,Deal!$K$12)=0),AND(Deal!$K$13<>"",COUNTIF('Historical Data'!$Y$2:$Y$9,Deal!$K$13)=0))),"ISO or industry not in house book; ","")&IF(AND(Controls!$B$79="Y",ISNUMBER('Offer Engine'!$E$8),IF(ISNUMBER('Offer Engine'!$E$8),'Offer Engine'!$E$8,0)<Controls!$B$14,IF(ISNUMBER('Offer Engine'!$E$8),'Offer Engine'!$E$8,0)>0),"Final fund below minimum; ","")&IF(AND(Controls!$B$80="Y",'Historical Score'!$C$29=7),"No cohort met the minimums; ","") | D25: ="blank = none" -> blank = none
B26: Evidence: ISO | C26: ='Historical Score'!$C$50 -> Fundwell: 3 seasoned deals, lost 43.0% vs 41.0% book, Z 0.09 -> neutral
B27: Evidence: industry | C27: ='Historical Score'!$C$51 -> Eating & Drinking Places: 1 seasoned deals - too few to rate
B28: Evidence: new deal / renewal | C28: ='Historical Score'!$C$52 -> New Deal: 5 seasoned deals, lost 50.8% vs 41.0% book -> neutral
B29: Evidence: position | C29: ='Historical Score'!$C$53 -> position 1: 1 seasoned deals - too few to rate
B30: Evidence: state (informational) | C30: ='Historical Score'!$C$54 -> NJ: 3 seasoned deals, lost 43.0% vs 41.0% book - informational only
B31: Warnings | C31: ='Historical Score'!$C$56 -> Tighter tiers 1-5 too small;
B32: Reds at the requested offer | C32: =IF(COUNTIF(Deal!$F$38:$F$45,"RED")+COUNTIF(Deal!$F$38:$F$45,"KNOCKOUT")=0,"none",IF(Deal!$F$38="RED","total leverage; ","")&IF(Deal!$F$39="RED","holdback; ","")&IF(Deal!$F$40="RED","daily debt/balance; ","")&IF(Deal!$F$41="RED","fund/revenue; ","")&IF(Deal!$F$42="RED","positions; ","")&IF(Deal!$F$43="RED","revenue trend; ","")&IF(Deal!$F$44="RED","neg days/NSFs; ","")&IF(Deal!$F$45="RED","credit; ","")&IF(COUNTIF(Deal!$F$38:$F$45,"KNOCKOUT")>0,"KNOCKOUT present","")) -> none
B33: Greens at the requested offer | C33: =IF(COUNTIF(Deal!$F$38:$F$45,"GREEN")=0,"none",IF(Deal!$F$38="GREEN","leverage; ","")&IF(Deal!$F$39="GREEN","holdback; ","")&IF(Deal!$F$40="GREEN","daily debt/balance; ","")&IF(Deal!$F$41="GREEN","fund/revenue; ","")&IF(Deal!$F$42="GREEN","positions; ","")&IF(Deal!$F$43="GREEN","revenue trend; ","")&IF(Deal!$F$44="GREEN","clean neg days/NSFs; ","")&IF(Deal!$F$45="GREEN","credit; ","")) -> leverage; holdback; daily debt/balance; fund/revenue; positions; revenue trend; credit;

Sheet Offer Engine
B1: OFFER ENGINE - green-line base -> sized at the house-book sizing line -> final after the modifier
B2: Base = the cash-flow tool exactly as built (green lines). Sized = Deal section E (sizing line, moved toward the red line only when the book is supportive). Final = sized x multiplier, term / factor steps. Final daily payment never exceeds the sized max daily.
B4: Item | C4: Base (green line) | D4: Sized (sizing line) | E4: Final (modifier) | F4: Status | G4: How
B5: Max daily payment | C5: =IF(Deal!$C$24=0,"",MAX(0,MIN(Deal!$D$39*Deal!$C$24/Deal!$K$9,(Deal!$D$38*Deal!$C$24-Deal!$F$34)/Deal!$K$9,IF(Deal!$D$24=0,0,Deal!$D$40*Deal!$D$24-Deal!$E$34)))) -> 716.9245 | D5: =Deal!$C$70 -> 716.9245 | E5: =Deal!$C$70 -> 716.9245 | G5: weakest of holdback / total LVG / daily-debt-to-balance at that line
B6: Term (daily payments) | C6: =IF(OR(C5="",C5=0),"",MAX(20,MIN(INDEX(Controls!$B$19:$B$22,MATCH(Deal!$D$67,Controls!$A$19:$A$22,1)),FLOOR(Controls!$B$23*Deal!$K$9,5),FLOOR(Deal!$D$41*Deal!$C$24*C7/C5,5)))) -> 100 | D6: =Deal!$C$72 -> 100 | E6: =IF(OR(D6="",D8="-"),"",MAX(20,MIN(D6,INDEX(Controls!$B$19:$B$22,MAX(1,MATCH(Deal!$D$67,Controls!$A$19:$A$22,1)+C11))))) -> 100 | G6: band term; final steps down the band table
B7: Factor | C7: =Deal!$D$72 -> 1.45 | D7: =Deal!$D$72 -> 1.45 | E7: =IF(D7="","",INDEX(Controls!$B$24:$D$24,MIN(3,MAX(1,MATCH(D7,Controls!$B$24:$D$24,0)+C12)))) -> 1.45 | G7: next approved tier when stepped; never above 1.49
B8: Fund $ | C8: =IF(COUNTIF(Deal!$F$42:$F$45,"KNOCKOUT")>0,"-",IF(OR(C5="",C5=0,C6="",C7=""),"",FLOOR(C5*C6/C7,500))) -> 49000 | D8: =Deal!$C$73 -> 49000 | E8: =IF(D8="-","-",IF(OR(D8="",E6="",E7=""),"",MAX(0,FLOOR(MIN(D8*C10,D5*E6/E7),500)))) -> 49000 | G8: final = MIN(sized x multiplier, sized max daily x final term / final factor)
B9: Daily payment | C9: =IF(OR(C8="",C8="-"),"",C8*C7/C6) -> 710.5 | D9: =IF(OR(D8="",D8="-"),"",D8*D7/D6) -> 710.5 | E9: =IF(OR(E8="",E8="-",E8=0),"",E8*E7/E6) -> 710.5 | G9: fund x factor / term
B10: Fund multiplier (Controls) | C10: ='Historical Score'!$C$43 -> 1
B11: Term step | C11: ='Historical Score'!$C$44 -> 0
B12: Factor step | C12: ='Historical Score'!$C$45 -> 0
B13: Frequency rule | C13: ='Historical Score'!$C$46 -> As proposed
B14: Manual review flag | C14: ='Historical Score'!$C$47 -> N
B15: Sizing flex | C15: ='Historical Score'!$C$42 -> 0 | G15: share of the way from the green line to the red line used for sizing
B16: Frequency (final) | C16: =IF(Deal!$E$6="","Daily",Deal!$E$6) -> Weekly | D16: =IF(Deal!$E$6="","Daily",Deal!$E$6) -> Weekly | E16: =IF(C13="Weekly","Weekly",IF(Deal!$E$6="","Daily",Deal!$E$6)) -> Weekly
B17: Term in final units | C17: =IF(OR(C6="",C8="-"),"",IF(C16="Weekly",C6/5,C6)) -> 20 | D17: =IF(OR(D6="",D8="-"),"",IF(D16="Weekly",D6/5,D6)) -> 20 | E17: =IF(OR(E6="",E8="-"),"",IF(E16="Weekly",E6/5,E6)) -> 20 | G17: weeks or daily payments
B18: Payment in final units | C18: =IF(C9="","",IF(C16="Weekly",C9*5,C9)) -> 3552.5 | D18: =IF(D9="","",IF(D16="Weekly",D9*5,D9)) -> 3552.5 | E18: =IF(E9="","",IF(E16="Weekly",E9*5,E9)) -> 3552.5
B19: Monthly payment | C19: =IF(C9="","",C9*Controls!$B$29) -> 15385.878 | D19: =IF(D9="","",D9*Controls!$B$29) -> 15385.878 | E19: =IF(E9="","",E9*Controls!$B$29) -> 15385.878
B20: Payback | C20: =IF(OR(C8="",C8="-"),"",C8*C7) -> 71050 | D20: =IF(OR(D8="",D8="-"),"",D8*D7) -> 71050 | E20: =IF(OR(E8="",E8="-"),"",E8*E7) -> 71050
B21: Net disbursed | C21: =IF(OR(C8="",C8="-"),"",C8*(1-Controls!$B$15)) -> 46550 | D21: =IF(OR(D8="",D8="-"),"",D8*(1-Controls!$B$15)) -> 46550 | E21: =IF(OR(E8="",E8="-"),"",E8*(1-Controls!$B$15)) -> 46550
B22: Term (months) | C22: =IF(C6="","",C6/Controls!$B$29) -> 4.6178712 | D22: =IF(D6="","",D6/Controls!$B$29) -> 4.6178712 | E22: =IF(E6="","",E6/Controls!$B$29) -> 4.6178712
B24: METRICS AT THE FINAL OFFER (yellow allowed when the book is supportive; RED / KNOCKOUT never)
B25: Metric | C25: Base | D25: Sized | E25: Final | F25: Status (final) | G25: Green / Red / Knockout
B26: Total LVG (all debt / rev) | C26: =IF(OR(Deal!$C$24=0,C9=""),"",(Deal!$E$34+C9)*Controls!$B$29/Deal!$C$24) -> 0.17838699 | D26: =IF(OR(Deal!$C$24=0,D9=""),"",(Deal!$E$34+D9)*Controls!$B$29/Deal!$C$24) -> 0.17838699 | E26: =IF(OR(Deal!$C$24=0,E9=""),"",(Deal!$E$34+E9)*Controls!$B$29/Deal!$C$24) -> 0.17838699 | F26: =IF(E26="","",IF(E26>=Controls!$D$5,"KNOCKOUT",IF(E26<=Controls!$B$5,"GREEN",IF(E26>=Controls!$C$5,"RED","YELLOW")))) -> GREEN | G26: =TEXT(Controls!$B$5,"0.0%")&" / "&TEXT(Controls!$C$5,"0.0%")&" / "&TEXT(Controls!$D$5,"0.0%") -> 30.0% / 45.0% / 55.0%
B27: New holdback SP% | C27: =IF(OR(Deal!$C$24=0,C9=""),"",C9*Controls!$B$29/Deal!$C$24) -> 0.17838699 | D27: =IF(OR(Deal!$C$24=0,D9=""),"",D9*Controls!$B$29/Deal!$C$24) -> 0.17838699 | E27: =IF(OR(Deal!$C$24=0,E9=""),"",E9*Controls!$B$29/Deal!$C$24) -> 0.17838699 | F27: =IF(E27="","",IF(E27>=Controls!$D$6,"KNOCKOUT",IF(E27<=Controls!$B$6,"GREEN",IF(E27>=Controls!$C$6,"RED","YELLOW")))) -> GREEN | G27: =TEXT(Controls!$B$6,"0.0%")&" / "&TEXT(Controls!$C$6,"0.0%")&" / "&TEXT(Controls!$D$6,"0.0%") -> 18.0% / 25.0% / 35.0%
B28: Daily debt / balance | C28: =IF(OR(Deal!$D$24=0,C9=""),"",(Deal!$E$34+C9)/Deal!$D$24) -> 0.0983391 | D28: =IF(OR(Deal!$D$24=0,D9=""),"",(Deal!$E$34+D9)/Deal!$D$24) -> 0.0983391 | E28: =IF(OR(Deal!$D$24=0,E9=""),"",(Deal!$E$34+E9)/Deal!$D$24) -> 0.0983391 | F28: =IF(E28="","",IF(E28>=Controls!$D$7,"KNOCKOUT",IF(E28<=Controls!$B$7,"GREEN",IF(E28>=Controls!$C$7,"RED","YELLOW")))) -> GREEN | G28: =TEXT(Controls!$B$7,"0.0%")&" / "&TEXT(Controls!$C$7,"0.0%")&" / "&TEXT(Controls!$D$7,"0.0%") -> 18.0% / 30.0% / 35.0%
B29: Fund / revenue | C29: =IF(OR(Deal!$C$24=0,C8="",C8="-"),"",C8/Deal!$C$24) -> 0.56811594 | D29: =IF(OR(Deal!$C$24=0,D8="",D8="-"),"",D8/Deal!$C$24) -> 0.56811594 | E29: =IF(OR(Deal!$C$24=0,E8="",E8="-"),"",E8/Deal!$C$24) -> 0.56811594 | F29: =IF(E29="","",IF(E29>=Controls!$D$8,"KNOCKOUT",IF(E29<=Controls!$B$8,"GREEN",IF(E29>=Controls!$C$8,"RED","YELLOW")))) -> GREEN | G29: =TEXT(Controls!$B$8,"0.00")&" / "&TEXT(Controls!$C$8,"0.00")&" / "&TEXT(Controls!$D$8,"0.00") -> 0.60 / 0.90 / 1.25
B30: # positions (incl. new) | E30: =Deal!$C$42 -> 1 | F30: =Deal!$F$42 -> GREEN | G30: merchant-side, unchanged by the offer
B31: Revenue trend (avg MoM) | E31: =Deal!$C$43 -> 0.026817356 | F31: =Deal!$F$43 -> GREEN | G31: merchant-side, unchanged by the offer
B32: Neg days + NSFs (total) | E32: =Deal!$C$44 -> 2 | F32: =Deal!$F$44 -> YELLOW | G32: merchant-side, unchanged by the offer
B33: Credit score (FICO) | E33: =Deal!$C$45 -> 672 | F33: =Deal!$F$45 -> GREEN | G33: merchant-side, unchanged by the offer
B35: SAFETY PROOF
B36: Final fund <= sized max fund | E36: =IF(OR(E8="",E8="-",D8="",D8="-"),"OK",IF(E8<=D8,"OK","FAIL")) -> OK
B37: Final daily payment <= sized max daily | E37: =IF(OR(E9="",D5=""),"OK",IF(E9<=D5+0.005,"OK","FAIL")) -> OK
B38: No offer-side metric RED / KNOCKOUT at the final offer | E38: =IF(COUNTIF(F26:F29,"RED")+COUNTIF(F26:F29,"KNOCKOUT")=0,"OK","FAIL") -> OK
B39: Merchant knockouts untouched | E39: =IF(COUNTIF(Deal!$F$42:$F$45,"KNOCKOUT")>0,IF(E8="-","OK","FAIL"),"OK") -> OK
B40: Sizing flex below 100% (sizing line never reaches the red line) | E40: =IF(C15<1,"OK","FAIL") -> OK
B41: Red flags at the final offer (offer-side + merchant-side) | E41: =COUNTIF(F26:F33,"RED")+COUNTIF(F26:F33,"KNOCKOUT") -> 0

Sheet Historical Score
A1: HISTORICAL SCORE - comparable cohorts, credibility and the modifier
A2: Rates use SEASONED deals only (age >= multiple x contracted term). Blended = Z x cohort + (1-Z) x seasoned book, Z = n/(n+K). Index = blended / book.
A4: DEAL BEING MATCHED
B5: New deal or renewal | C5: =IF(Deal!$K$15="","",Deal!$K$15) -> New Deal
B6: Position (Deal C42) | C6: =IF(Deal!$C$42="","",Deal!$C$42) -> 1
B7: Industry | C7: =IF(Deal!$K$13="","",Deal!$K$13) -> Eating & Drinking Places
B8: ISO | C8: =IF(Deal!$K$12="","",Deal!$K$12) -> Fundwell
B9: State (informational) | C9: =IF(Deal!$K$14="","",Deal!$K$14) -> NJ
B10: Seasoned-book principal lost rate (baseline) | C10: =IF($L$20="",0,$L$20) -> 0.41
B11: Seasoned-book deals / funded | C11: =TEXT($E$20,"#,##0")&" / "&TEXT($G$20,"$#,##0") -> 7 / $150,000
A13: Tier | B13: Cohort | C13: Keys | D13: Deals (all) | E13: Seasoned | F13: % seasoned | G13: Funded $ (seasoned) | H13: Open n | I13: Open % | J13: Default n | K13: Default % | L13: Principal lost rate | M13: Collected on defaults | N13: Return on funded | O13: Avg adv/rev | P13: Avg term (bd) | Q13: Avg factor | R13: Avg deal size | S13: Avg days on book | T13: Renewal share | U13: Meets minimums? | V13: Credibility Z | W13: Blended lost rate | X13: Relative index | Y13: Meets min (1/0) | Z13: Impact vs book | AA13: Rate shown?
A14: 1 | B14: T1: new/renewal + industry + position | C14: NR + industry + position | D14: =SUMPRODUCT('Historical Data'!$AV$2:$AV$9*'Historical Data'!$AD$2:$AD$9) -> 1 | E14: =SUMPRODUCT('Historical Data'!$AV$2:$AV$9*'Historical Data'!$AP$2:$AP$9) -> 1 | F14: =IF(D14=0,"",E14/D14) -> 1 | G14: =SUMPRODUCT('Historical Data'!$AV$2:$AV$9*'Historical Data'!$AP$2:$AP$9*'Historical Data'!$N$2:$N$9) -> 10000 | H14: =SUMPRODUCT('Historical Data'!$AV$2:$AV$9*'Historical Data'!$AP$2:$AP$9*'Historical Data'!$AH$2:$AH$9) -> 0 | I14: =IF(E14=0,"",H14/E14) -> 0 | J14: =SUMPRODUCT('Historical Data'!$AV$2:$AV$9*'Historical Data'!$AP$2:$AP$9*'Historical Data'!$AE$2:$AE$9) -> 0 | K14: =IF(E14=0,"",J14/E14) -> 0 | L14: =IF(OR(E14<Controls!$B$43,G14=0),"",SUMPRODUCT('Historical Data'!$AV$2:$AV$9*'Historical Data'!$AP$2:$AP$9*'Historical Data'!$AK$2:$AK$9)/G14) | M14: =IF(OR(E14<Controls!$B$43,SUMPRODUCT('Historical Data'!$AV$2:$AV$9*'Historical Data'!$AP$2:$AP$9*'Historical Data'!$AE$2:$AE$9*'Historical Data'!$N$2:$N$9)=0),"",SUMPRODUCT('Historical Data'!$AV$2:$AV$9*'Historical Data'!$AP$2:$AP$9*'Historical Data'!$AE$2:$AE$9*'Historical Data'!$Q$2:$Q$9)/SUMPRODUCT('Historical Data'!$AV$2:$AV$9*'Historical Data'!$AP$2:$AP$9*'Historical Data'!$AE$2:$AE$9*'Historical Data'!$N$2:$N$9)) | N14: =IF(OR(E14<Controls!$B$43,G14=0),"",SUMPRODUCT('Historical Data'!$AV$2:$AV$9*'Historical Data'!$AP$2:$AP$9*'Historical Data'!$AJ$2:$AJ$9)/G14) | O14: =IF(SUMPRODUCT('Historical Data'!$AV$2:$AV$9*'Historical Data'!$AP$2:$AP$9*'Historical Data'!$AM$2:$AM$9)=0,"",SUMPRODUCT('Historical Data'!$AV$2:$AV$9*'Historical Data'!$AP$2:$AP$9*'Historical Data'!$AM$2:$AM$9*'Historical Data'!$AL$2:$AL$9)/SUMPRODUCT('Historical Data'!$AV$2:$AV$9*'Historical Data'!$AP$2:$AP$9*'Historical Data'!$AM$2:$AM$9)) -> 0.2 | P14: =IF(E14=0,"",SUMPRODUCT('Historical Data'!$AV$2:$AV$9*'Historical Data'!$AP$2:$AP$9*'Historical Data'!$AA$2:$AA$9)/E14) -> 108.275 | Q14: =IF(E14=0,"",SUMPRODUCT('Historical Data'!$AV$2:$AV$9*'Historical Data'!$AP$2:$AP$9*'Historical Data'!$M$2:$M$9)/E14) -> 1.5 | R14: =IF(E14=0,"",G14/E14) -> 10000 | S14: =IF(E14=0,"",SUMPRODUCT('Historical Data'!$AV$2:$AV$9*'Historical Data'!$AP$2:$AP$9*'Historical Data'!$AN$2:$AN$9)/E14) -> 105 | T14: =IF(E14=0,"",SUMPRODUCT('Historical Data'!$AV$2:$AV$9*'Historical Data'!$AP$2:$AP$9*'Historical Data'!$AO$2:$AO$9)/E14) -> 0 | U14: =IF(AND(E14>=Controls!$B$40,G14>=Controls!$B$41),"Yes","No") -> No | V14: =IF(E14+Controls!$B$42=0,0,E14/(E14+Controls!$B$42)) -> 0.032258065 | W14: =IF(L14="",$C$10,V14*L14+(1-V14)*$C$10) -> 0.41 | X14: =IF(OR($C$10="",$C$10=0),"",W14/$C$10) -> 1 | Y14: =IF(U14="Yes",1,0) -> 0 | Z14: =IF(L14="",0,ABS(W14-$C$10)) -> 0 | AA14: =IF(L14="","No","Yes") -> No
A15: 2 | B15: T2: new/renewal + ISO + position | C15: NR + ISO + position | D15: =SUMPRODUCT('Historical Data'!$AW$2:$AW$9*'Historical Data'!$AD$2:$AD$9) -> 2 | E15: =SUMPRODUCT('Historical Data'!$AW$2:$AW$9*'Historical Data'!$AP$2:$AP$9) -> 1 | F15: =IF(D15=0,"",E15/D15) -> 0.5 | G15: =SUMPRODUCT('Historical Data'!$AW$2:$AW$9*'Historical Data'!$AP$2:$AP$9*'Historical Data'!$N$2:$N$9) -> 10000 | H15: =SUMPRODUCT('Historical Data'!$AW$2:$AW$9*'Historical Data'!$AP$2:$AP$9*'Historical Data'!$AH$2:$AH$9) -> 0 | I15: =IF(E15=0,"",H15/E15) -> 0 | J15: =SUMPRODUCT('Historical Data'!$AW$2:$AW$9*'Historical Data'!$AP$2:$AP$9*'Historical Data'!$AE$2:$AE$9) -> 0 | K15: =IF(E15=0,"",J15/E15) -> 0 | L15: =IF(OR(E15<Controls!$B$43,G15=0),"",SUMPRODUCT('Historical Data'!$AW$2:$AW$9*'Historical Data'!$AP$2:$AP$9*'Historical Data'!$AK$2:$AK$9)/G15) | M15: =IF(OR(E15<Controls!$B$43,SUMPRODUCT('Historical Data'!$AW$2:$AW$9*'Historical Data'!$AP$2:$AP$9*'Historical Data'!$AE$2:$AE$9*'Historical Data'!$N$2:$N$9)=0),"",SUMPRODUCT('Historical Data'!$AW$2:$AW$9*'Historical Data'!$AP$2:$AP$9*'Historical Data'!$AE$2:$AE$9*'Historical Data'!$Q$2:$Q$9)/SUMPRODUCT('Historical Data'!$AW$2:$AW$9*'Historical Data'!$AP$2:$AP$9*'Historical Data'!$AE$2:$AE$9*'Historical Data'!$N$2:$N$9)) | N15: =IF(OR(E15<Controls!$B$43,G15=0),"",SUMPRODUCT('Historical Data'!$AW$2:$AW$9*'Historical Data'!$AP$2:$AP$9*'Historical Data'!$AJ$2:$AJ$9)/G15) | O15: =IF(SUMPRODUCT('Historical Data'!$AW$2:$AW$9*'Historical Data'!$AP$2:$AP$9*'Historical Data'!$AM$2:$AM$9)=0,"",SUMPRODUCT('Historical Data'!$AW$2:$AW$9*'Historical Data'!$AP$2:$AP$9*'Historical Data'!$AM$2:$AM$9*'Historical Data'!$AL$2:$AL$9)/SUMPRODUCT('Historical Data'!$AW$2:$AW$9*'Historical Data'!$AP$2:$AP$9*'Historical Data'!$AM$2:$AM$9)) -> 0.2 | P15: =IF(E15=0,"",SUMPRODUCT('Historical Data'!$AW$2:$AW$9*'Historical Data'!$AP$2:$AP$9*'Historical Data'!$AA$2:$AA$9)/E15) -> 108.275 | Q15: =IF(E15=0,"",SUMPRODUCT('Historical Data'!$AW$2:$AW$9*'Historical Data'!$AP$2:$AP$9*'Historical Data'!$M$2:$M$9)/E15) -> 1.5 | R15: =IF(E15=0,"",G15/E15) -> 10000 | S15: =IF(E15=0,"",SUMPRODUCT('Historical Data'!$AW$2:$AW$9*'Historical Data'!$AP$2:$AP$9*'Historical Data'!$AN$2:$AN$9)/E15) -> 105 | T15: =IF(E15=0,"",SUMPRODUCT('Historical Data'!$AW$2:$AW$9*'Historical Data'!$AP$2:$AP$9*'Historical Data'!$AO$2:$AO$9)/E15) -> 0 | U15: =IF(AND(E15>=Controls!$B$40,G15>=Controls!$B$41),"Yes","No") -> No | V15: =IF(E15+Controls!$B$42=0,0,E15/(E15+Controls!$B$42)) -> 0.032258065 | W15: =IF(L15="",$C$10,V15*L15+(1-V15)*$C$10) -> 0.41 | X15: =IF(OR($C$10="",$C$10=0),"",W15/$C$10) -> 1 | Y15: =IF(U15="Yes",1,0) -> 0 | Z15: =IF(L15="",0,ABS(W15-$C$10)) -> 0 | AA15: =IF(L15="","No","Yes") -> No
A16: 3 | B16: T3: new/renewal + industry | C16: NR + industry | D16: =SUMPRODUCT('Historical Data'!$AX$2:$AX$9*'Historical Data'!$AD$2:$AD$9) -> 1 | E16: =SUMPRODUCT('Historical Data'!$AX$2:$AX$9*'Historical Data'!$AP$2:$AP$9) -> 1 | F16: =IF(D16=0,"",E16/D16) -> 1 | G16: =SUMPRODUCT('Historical Data'!$AX$2:$AX$9*'Historical Data'!$AP$2:$AP$9*'Historical Data'!$N$2:$N$9) -> 10000 | H16: =SUMPRODUCT('Historical Data'!$AX$2:$AX$9*'Historical Data'!$AP$2:$AP$9*'Historical Data'!$AH$2:$AH$9) -> 0 | I16: =IF(E16=0,"",H16/E16) -> 0 | J16: =SUMPRODUCT('Historical Data'!$AX$2:$AX$9*'Historical Data'!$AP$2:$AP$9*'Historical Data'!$AE$2:$AE$9) -> 0 | K16: =IF(E16=0,"",J16/E16) -> 0 | L16: =IF(OR(E16<Controls!$B$43,G16=0),"",SUMPRODUCT('Historical Data'!$AX$2:$AX$9*'Historical Data'!$AP$2:$AP$9*'Historical Data'!$AK$2:$AK$9)/G16) | M16: =IF(OR(E16<Controls!$B$43,SUMPRODUCT('Historical Data'!$AX$2:$AX$9*'Historical Data'!$AP$2:$AP$9*'Historical Data'!$AE$2:$AE$9*'Historical Data'!$N$2:$N$9)=0),"",SUMPRODUCT('Historical Data'!$AX$2:$AX$9*'Historical Data'!$AP$2:$AP$9*'Historical Data'!$AE$2:$AE$9*'Historical Data'!$Q$2:$Q$9)/SUMPRODUCT('Historical Data'!$AX$2:$AX$9*'Historical Data'!$AP$2:$AP$9*'Historical Data'!$AE$2:$AE$9*'Historical Data'!$N$2:$N$9)) | N16: =IF(OR(E16<Controls!$B$43,G16=0),"",SUMPRODUCT('Historical Data'!$AX$2:$AX$9*'Historical Data'!$AP$2:$AP$9*'Historical Data'!$AJ$2:$AJ$9)/G16) | O16: =IF(SUMPRODUCT('Historical Data'!$AX$2:$AX$9*'Historical Data'!$AP$2:$AP$9*'Historical Data'!$AM$2:$AM$9)=0,"",SUMPRODUCT('Historical Data'!$AX$2:$AX$9*'Historical Data'!$AP$2:$AP$9*'Historical Data'!$AM$2:$AM$9*'Historical Data'!$AL$2:$AL$9)/SUMPRODUCT('Historical Data'!$AX$2:$AX$9*'Historical Data'!$AP$2:$AP$9*'Historical Data'!$AM$2:$AM$9)) -> 0.2 | P16: =IF(E16=0,"",SUMPRODUCT('Historical Data'!$AX$2:$AX$9*'Historical Data'!$AP$2:$AP$9*'Historical Data'!$AA$2:$AA$9)/E16) -> 108.275 | Q16: =IF(E16=0,"",SUMPRODUCT('Historical Data'!$AX$2:$AX$9*'Historical Data'!$AP$2:$AP$9*'Historical Data'!$M$2:$M$9)/E16) -> 1.5 | R16: =IF(E16=0,"",G16/E16) -> 10000 | S16: =IF(E16=0,"",SUMPRODUCT('Historical Data'!$AX$2:$AX$9*'Historical Data'!$AP$2:$AP$9*'Historical Data'!$AN$2:$AN$9)/E16) -> 105 | T16: =IF(E16=0,"",SUMPRODUCT('Historical Data'!$AX$2:$AX$9*'Historical Data'!$AP$2:$AP$9*'Historical Data'!$AO$2:$AO$9)/E16) -> 0 | U16: =IF(AND(E16>=Controls!$B$40,G16>=Controls!$B$41),"Yes","No") -> No | V16: =IF(E16+Controls!$B$42=0,0,E16/(E16+Controls!$B$42)) -> 0.032258065 | W16: =IF(L16="",$C$10,V16*L16+(1-V16)*$C$10) -> 0.41 | X16: =IF(OR($C$10="",$C$10=0),"",W16/$C$10) -> 1 | Y16: =IF(U16="Yes",1,0) -> 0 | Z16: =IF(L16="",0,ABS(W16-$C$10)) -> 0 | AA16: =IF(L16="","No","Yes") -> No
A17: 4 | B17: T4: new/renewal + ISO | C17: NR + ISO | D17: =SUMPRODUCT('Historical Data'!$AY$2:$AY$9*'Historical Data'!$AD$2:$AD$9) -> 3 | E17: =SUMPRODUCT('Historical Data'!$AY$2:$AY$9*'Historical Data'!$AP$2:$AP$9) -> 2 | F17: =IF(D17=0,"",E17/D17) -> 0.66666667 | G17: =SUMPRODUCT('Historical Data'!$AY$2:$AY$9*'Historical Data'!$AP$2:$AP$9*'Historical Data'!$N$2:$N$9) -> 40000 | H17: =SUMPRODUCT('Historical Data'!$AY$2:$AY$9*'Historical Data'!$AP$2:$AP$9*'Historical Data'!$AH$2:$AH$9) -> 0 | I17: =IF(E17=0,"",H17/E17) -> 0 | J17: =SUMPRODUCT('Historical Data'!$AY$2:$AY$9*'Historical Data'!$AP$2:$AP$9*'Historical Data'!$AE$2:$AE$9) -> 1 | K17: =IF(E17=0,"",J17/E17) -> 0.5 | L17: =IF(OR(E17<Controls!$B$43,G17=0),"",SUMPRODUCT('Historical Data'!$AY$2:$AY$9*'Historical Data'!$AP$2:$AP$9*'Historical Data'!$AK$2:$AK$9)/G17) -> 0.525 | M17: =IF(OR(E17<Controls!$B$43,SUMPRODUCT('Historical Data'!$AY$2:$AY$9*'Historical Data'!$AP$2:$AP$9*'Historical Data'!$AE$2:$AE$9*'Historical Data'!$N$2:$N$9)=0),"",SUMPRODUCT('Historical Data'!$AY$2:$AY$9*'Historical Data'!$AP$2:$AP$9*'Historical Data'!$AE$2:$AE$9*'Historical Data'!$Q$2:$Q$9)/SUMPRODUCT('Historical Data'!$AY$2:$AY$9*'Historical Data'!$AP$2:$AP$9*'Historical Data'!$AE$2:$AE$9*'Historical Data'!$N$2:$N$9)) -> 0.3 | N17: =IF(OR(E17<Controls!$B$43,G17=0),"",SUMPRODUCT('Historical Data'!$AY$2:$AY$9*'Historical Data'!$AP$2:$AP$9*'Historical Data'!$AJ$2:$AJ$9)/G17) -> -0.4 | O17: =IF(SUMPRODUCT('Historical Data'!$AY$2:$AY$9*'Historical Data'!$AP$2:$AP$9*'Historical Data'!$AM$2:$AM$9)=0,"",SUMPRODUCT('Historical Data'!$AY$2:$AY$9*'Historical Data'!$AP$2:$AP$9*'Historical Data'!$AM$2:$AM$9*'Historical Data'!$AL$2:$AL$9)/SUMPRODUCT('Historical Data'!$AY$2:$AY$9*'Historical Data'!$AP$2:$AP$9*'Historical Data'!$AM$2:$AM$9)) -> 0.35 | P17: =IF(E17=0,"",SUMPRODUCT('Historical Data'!$AY$2:$AY$9*'Historical Data'!$AP$2:$AP$9*'Historical Data'!$AA$2:$AA$9)/E17) -> 119.1025 | Q17: =IF(E17=0,"",SUMPRODUCT('Historical Data'!$AY$2:$AY$9*'Historical Data'!$AP$2:$AP$9*'Historical Data'!$M$2:$M$9)/E17) -> 1.5 | R17: =IF(E17=0,"",G17/E17) -> 20000 | S17: =IF(E17=0,"",SUMPRODUCT('Historical Data'!$AY$2:$AY$9*'Historical Data'!$AP$2:$AP$9*'Historical Data'!$AN$2:$AN$9)/E17) -> 85.5 | T17: =IF(E17=0,"",SUMPRODUCT('Historical Data'!$AY$2:$AY$9*'Historical Data'!$AP$2:$AP$9*'Historical Data'!$AO$2:$AO$9)/E17) -> 0 | U17: =IF(AND(E17>=Controls!$B$40,G17>=Controls!$B$41),"Yes","No") -> No | V17: =IF(E17+Controls!$B$42=0,0,E17/(E17+Controls!$B$42)) -> 0.0625 | W17: =IF(L17="",$C$10,V17*L17+(1-V17)*$C$10) -> 0.4171875 | X17: =IF(OR($C$10="",$C$10=0),"",W17/$C$10) -> 1.0175305 | Y17: =IF(U17="Yes",1,0) -> 0 | Z17: =IF(L17="",0,ABS(W17-$C$10)) -> 0.0071875 | AA17: =IF(L17="","No","Yes") -> Yes
A18: 5 | B18: T5: new/renewal + position | C18: NR + position | D18: =SUMPRODUCT('Historical Data'!$AZ$2:$AZ$9*'Historical Data'!$AD$2:$AD$9) -> 2 | E18: =SUMPRODUCT('Historical Data'!$AZ$2:$AZ$9*'Historical Data'!$AP$2:$AP$9) -> 1 | F18: =IF(D18=0,"",E18/D18) -> 0.5 | G18: =SUMPRODUCT('Historical Data'!$AZ$2:$AZ$9*'Historical Data'!$AP$2:$AP$9*'Historical Data'!$N$2:$N$9) -> 10000 | H18: =SUMPRODUCT('Historical Data'!$AZ$2:$AZ$9*'Historical Data'!$AP$2:$AP$9*'Historical Data'!$AH$2:$AH$9) -> 0 | I18: =IF(E18=0,"",H18/E18) -> 0 | J18: =SUMPRODUCT('Historical Data'!$AZ$2:$AZ$9*'Historical Data'!$AP$2:$AP$9*'Historical Data'!$AE$2:$AE$9) -> 0 | K18: =IF(E18=0,"",J18/E18) -> 0 | L18: =IF(OR(E18<Controls!$B$43,G18=0),"",SUMPRODUCT('Historical Data'!$AZ$2:$AZ$9*'Historical Data'!$AP$2:$AP$9*'Historical Data'!$AK$2:$AK$9)/G18) | M18: =IF(OR(E18<Controls!$B$43,SUMPRODUCT('Historical Data'!$AZ$2:$AZ$9*'Historical Data'!$AP$2:$AP$9*'Historical Data'!$AE$2:$AE$9*'Historical Data'!$N$2:$N$9)=0),"",SUMPRODUCT('Historical Data'!$AZ$2:$AZ$9*'Historical Data'!$AP$2:$AP$9*'Historical Data'!$AE$2:$AE$9*'Historical Data'!$Q$2:$Q$9)/SUMPRODUCT('Historical Data'!$AZ$2:$AZ$9*'Historical Data'!$AP$2:$AP$9*'Historical Data'!$AE$2:$AE$9*'Historical Data'!$N$2:$N$9)) | N18: =IF(OR(E18<Controls!$B$43,G18=0),"",SUMPRODUCT('Historical Data'!$AZ$2:$AZ$9*'Historical Data'!$AP$2:$AP$9*'Historical Data'!$AJ$2:$AJ$9)/G18) | O18: =IF(SUMPRODUCT('Historical Data'!$AZ$2:$AZ$9*'Historical Data'!$AP$2:$AP$9*'Historical Data'!$AM$2:$AM$9)=0,"",SUMPRODUCT('Historical Data'!$AZ$2:$AZ$9*'Historical Data'!$AP$2:$AP$9*'Historical Data'!$AM$2:$AM$9*'Historical Data'!$AL$2:$AL$9)/SUMPRODUCT('Historical Data'!$AZ$2:$AZ$9*'Historical Data'!$AP$2:$AP$9*'Historical Data'!$AM$2:$AM$9)) -> 0.2 | P18: =IF(E18=0,"",SUMPRODUCT('Historical Data'!$AZ$2:$AZ$9*'Historical Data'!$AP$2:$AP$9*'Historical Data'!$AA$2:$AA$9)/E18) -> 108.275 | Q18: =IF(E18=0,"",SUMPRODUCT('Historical Data'!$AZ$2:$AZ$9*'Historical Data'!$AP$2:$AP$9*'Historical Data'!$M$2:$M$9)/E18) -> 1.5 | R18: =IF(E18=0,"",G18/E18) -> 10000 | S18: =IF(E18=0,"",SUMPRODUCT('Historical Data'!$AZ$2:$AZ$9*'Historical Data'!$AP$2:$AP$9*'Historical Data'!$AN$2:$AN$9)/E18) -> 105 | T18: =IF(E18=0,"",SUMPRODUCT('Historical Data'!$AZ$2:$AZ$9*'Historical Data'!$AP$2:$AP$9*'Historical Data'!$AO$2:$AO$9)/E18) -> 0 | U18: =IF(AND(E18>=Controls!$B$40,G18>=Controls!$B$41),"Yes","No") -> No | V18: =IF(E18+Controls!$B$42=0,0,E18/(E18+Controls!$B$42)) -> 0.032258065 | W18: =IF(L18="",$C$10,V18*L18+(1-V18)*$C$10) -> 0.41 | X18: =IF(OR($C$10="",$C$10=0),"",W18/$C$10) -> 1 | Y18: =IF(U18="Yes",1,0) -> 0 | Z18: =IF(L18="",0,ABS(W18-$C$10)) -> 0 | AA18: =IF(L18="","No","Yes") -> No
A19: 6 | B19: T6: new/renewal only | C19: NR | D19: =SUMPRODUCT('Historical Data'!$BA$2:$BA$9*'Historical Data'!$AD$2:$AD$9) -> 6 | E19: =SUMPRODUCT('Historical Data'!$BA$2:$BA$9*'Historical Data'!$AP$2:$AP$9) -> 5 | F19: =IF(D19=0,"",E19/D19) -> 0.83333333 | G19: =SUMPRODUCT('Historical Data'!$BA$2:$BA$9*'Historical Data'!$AP$2:$AP$9*'Historical Data'!$N$2:$N$9) -> 120000 | H19: =SUMPRODUCT('Historical Data'!$BA$2:$BA$9*'Historical Data'!$AP$2:$AP$9*'Historical Data'!$AH$2:$AH$9) -> 0 | I19: =IF(E19=0,"",H19/E19) -> 0 | J19: =SUMPRODUCT('Historical Data'!$BA$2:$BA$9*'Historical Data'!$AP$2:$AP$9*'Historical Data'!$AE$2:$AE$9) -> 3 | K19: =IF(E19=0,"",J19/E19) -> 0.6 | L19: =IF(OR(E19<Controls!$B$43,G19=0),"",SUMPRODUCT('Historical Data'!$BA$2:$BA$9*'Historical Data'!$AP$2:$AP$9*'Historical Data'!$AK$2:$AK$9)/G19) -> 0.50833333 | M19: =IF(OR(E19<Controls!$B$43,SUMPRODUCT('Historical Data'!$BA$2:$BA$9*'Historical Data'!$AP$2:$AP$9*'Historical Data'!$AE$2:$AE$9*'Historical Data'!$N$2:$N$9)=0),"",SUMPRODUCT('Historical Data'!$BA$2:$BA$9*'Historical Data'!$AP$2:$AP$9*'Historical Data'!$AE$2:$AE$9*'Historical Data'!$Q$2:$Q$9)/SUMPRODUCT('Historical Data'!$BA$2:$BA$9*'Historical Data'!$AP$2:$AP$9*'Historical Data'!$AE$2:$AE$9*'Historical Data'!$N$2:$N$9)) -> 0.32222222 | N19: =IF(OR(E19<Controls!$B$43,G19=0),"",SUMPRODUCT('Historical Data'!$BA$2:$BA$9*'Historical Data'!$AP$2:$AP$9*'Historical Data'!$AJ$2:$AJ$9)/G19) -> -0.38333333 | O19: =IF(SUMPRODUCT('Historical Data'!$BA$2:$BA$9*'Historical Data'!$AP$2:$AP$9*'Historical Data'!$AM$2:$AM$9)=0,"",SUMPRODUCT('Historical Data'!$BA$2:$BA$9*'Historical Data'!$AP$2:$AP$9*'Historical Data'!$AM$2:$AM$9*'Historical Data'!$AL$2:$AL$9)/SUMPRODUCT('Historical Data'!$BA$2:$BA$9*'Historical Data'!$AP$2:$AP$9*'Historical Data'!$AM$2:$AM$9)) -> 0.35 | P19: =IF(E19=0,"",SUMPRODUCT('Historical Data'!$BA$2:$BA$9*'Historical Data'!$AP$2:$AP$9*'Historical Data'!$AA$2:$AA$9)/E19) -> 107.641 | Q19: =IF(E19=0,"",SUMPRODUCT('Historical Data'!$BA$2:$BA$9*'Historical Data'!$AP$2:$AP$9*'Historical Data'!$M$2:$M$9)/E19) -> 1.5 | R19: =IF(E19=0,"",G19/E19) -> 24000 | S19: =IF(E19=0,"",SUMPRODUCT('Historical Data'!$BA$2:$BA$9*'Historical Data'!$AP$2:$AP$9*'Historical Data'!$AN$2:$AN$9)/E19) -> 85.4 | T19: =IF(E19=0,"",SUMPRODUCT('Historical Data'!$BA$2:$BA$9*'Historical Data'!$AP$2:$AP$9*'Historical Data'!$AO$2:$AO$9)/E19) -> 0 | U19: =IF(AND(E19>=Controls!$B$40,G19>=Controls!$B$41),"Yes","No") -> Yes | V19: =IF(E19+Controls!$B$42=0,0,E19/(E19+Controls!$B$42)) -> 0.14285714 | W19: =IF(L19="",$C$10,V19*L19+(1-V19)*$C$10) -> 0.42404762 | X19: =IF(OR($C$10="",$C$10=0),"",W19/$C$10) -> 1.0342625 | Y19: =IF(U19="Yes",1,0) -> 1 | Z19: =IF(L19="",0,ABS(W19-$C$10)) -> 0.014047619 | AA19: =IF(L19="","No","Yes") -> Yes
A20: 7 | B20: T7: seasoned book (baseline) | C20: all seasoned deals in window | D20: =SUMPRODUCT('Historical Data'!$BB$2:$BB$9*'Historical Data'!$AD$2:$AD$9) -> 8 | E20: =SUMPRODUCT('Historical Data'!$BB$2:$BB$9*'Historical Data'!$AP$2:$AP$9) -> 7 | F20: =IF(D20=0,"",E20/D20) -> 0.875 | G20: =SUMPRODUCT('Historical Data'!$BB$2:$BB$9*'Historical Data'!$AP$2:$AP$9*'Historical Data'!$N$2:$N$9) -> 150000 | H20: =SUMPRODUCT('Historical Data'!$BB$2:$BB$9*'Historical Data'!$AP$2:$AP$9*'Historical Data'!$AH$2:$AH$9) -> 0 | I20: =IF(E20=0,"",H20/E20) -> 0 | J20: =SUMPRODUCT('Historical Data'!$BB$2:$BB$9*'Historical Data'!$AP$2:$AP$9*'Historical Data'!$AE$2:$AE$9) -> 4 | K20: =IF(E20=0,"",J20/E20) -> 0.57142857 | L20: =IF(OR(E20<Controls!$B$43,G20=0),"",SUMPRODUCT('Historical Data'!$BB$2:$BB$9*'Historical Data'!$AP$2:$AP$9*'Historical Data'!$AK$2:$AK$9)/G20) -> 0.41 | M20: =IF(OR(E20<Controls!$B$43,SUMPRODUCT('Historical Data'!$BB$2:$BB$9*'Historical Data'!$AP$2:$AP$9*'Historical Data'!$AE$2:$AE$9*'Historical Data'!$N$2:$N$9)=0),"",SUMPRODUCT('Historical Data'!$BB$2:$BB$9*'Historical Data'!$AP$2:$AP$9*'Historical Data'!$AE$2:$AE$9*'Historical Data'!$Q$2:$Q$9)/SUMPRODUCT('Historical Data'!$BB$2:$BB$9*'Historical Data'!$AP$2:$AP$9*'Historical Data'!$AE$2:$AE$9*'Historical Data'!$N$2:$N$9)) -> 0.385 | N20: =IF(OR(E20<Controls!$B$43,G20=0),"",SUMPRODUCT('Historical Data'!$BB$2:$BB$9*'Historical Data'!$AP$2:$AP$9*'Historical Data'!$AJ$2:$AJ$9)/G20) -> -0.24333333 | O20: =IF(SUMPRODUCT('Historical Data'!$BB$2:$BB$9*'Historical Data'!$AP$2:$AP$9*'Historical Data'!$AM$2:$AM$9)=0,"",SUMPRODUCT('Historical Data'!$BB$2:$BB$9*'Historical Data'!$AP$2:$AP$9*'Historical Data'!$AM$2:$AM$9*'Historical Data'!$AL$2:$AL$9)/SUMPRODUCT('Historical Data'!$BB$2:$BB$9*'Historical Data'!$AP$2:$AP$9*'Historical Data'!$AM$2:$AM$9)) -> 0.35 | P20: =IF(E20=0,"",SUMPRODUCT('Historical Data'!$BB$2:$BB$9*'Historical Data'!$AP$2:$AP$9*'Historical Data'!$AA$2:$AA$9)/E20) -> 103.54643 | Q20: =IF(E20=0,"",SUMPRODUCT('Historical Data'!$BB$2:$BB$9*'Historical Data'!$AP$2:$AP$9*'Historical Data'!$M$2:$M$9)/E20) -> 1.5 | R20: =IF(E20=0,"",G20/E20) -> 21428.571 | S20: =IF(E20=0,"",SUMPRODUCT('Historical Data'!$BB$2:$BB$9*'Historical Data'!$AP$2:$AP$9*'Historical Data'!$AN$2:$AN$9)/E20) -> 94.142857 | T20: =IF(E20=0,"",SUMPRODUCT('Historical Data'!$BB$2:$BB$9*'Historical Data'!$AP$2:$AP$9*'Historical Data'!$AO$2:$AO$9)/E20) -> 0.28571429 | U20: =IF(AND(E20>=Controls!$B$40,G20>=Controls!$B$41),"Yes","No") -> Yes | V20: =IF(E20+Controls!$B$42=0,0,E20/(E20+Controls!$B$42)) -> 0.18918919 | W20: =IF(L20="",$C$10,V20*L20+(1-V20)*$C$10) -> 0.41 | X20: =IF(OR($C$10="",$C$10=0),"",W20/$C$10) -> 1 | Y20: =IF(U20="Yes",1,0) -> 1 | Z20: =IF(L20="",0,ABS(W20-$C$10)) -> 0 | AA20: =IF(L20="","No","Yes") -> Yes
B21: SINGLE-DIMENSION EVIDENCE (C2 block on Deal; largest-impact test)
A22: S1 | B22: Position only | C22: Position only | D22: =SUMPRODUCT('Historical Data'!$AQ$2:$AQ$9*'Historical Data'!$AD$2:$AD$9) -> 2 | E22: =SUMPRODUCT('Historical Data'!$AQ$2:$AQ$9*'Historical Data'!$AP$2:$AP$9) -> 1 | F22: =IF(D22=0,"",E22/D22) -> 0.5 | G22: =SUMPRODUCT('Historical Data'!$AQ$2:$AQ$9*'Historical Data'!$AP$2:$AP$9*'Historical Data'!$N$2:$N$9) -> 10000 | H22: =SUMPRODUCT('Historical Data'!$AQ$2:$AQ$9*'Historical Data'!$AP$2:$AP$9*'Historical Data'!$AH$2:$AH$9) -> 0 | I22: =IF(E22=0,"",H22/E22) -> 0 | J22: =SUMPRODUCT('Historical Data'!$AQ$2:$AQ$9*'Historical Data'!$AP$2:$AP$9*'Historical Data'!$AE$2:$AE$9) -> 0 | K22: =IF(E22=0,"",J22/E22) -> 0 | L22: =IF(OR(E22<Controls!$B$43,G22=0),"",SUMPRODUCT('Historical Data'!$AQ$2:$AQ$9*'Historical Data'!$AP$2:$AP$9*'Historical Data'!$AK$2:$AK$9)/G22) | M22: =IF(OR(E22<Controls!$B$43,SUMPRODUCT('Historical Data'!$AQ$2:$AQ$9*'Historical Data'!$AP$2:$AP$9*'Historical Data'!$AE$2:$AE$9*'Historical Data'!$N$2:$N$9)=0),"",SUMPRODUCT('Historical Data'!$AQ$2:$AQ$9*'Historical Data'!$AP$2:$AP$9*'Historical Data'!$AE$2:$AE$9*'Historical Data'!$Q$2:$Q$9)/SUMPRODUCT('Historical Data'!$AQ$2:$AQ$9*'Historical Data'!$AP$2:$AP$9*'Historical Data'!$AE$2:$AE$9*'Historical Data'!$N$2:$N$9)) | N22: =IF(OR(E22<Controls!$B$43,G22=0),"",SUMPRODUCT('Historical Data'!$AQ$2:$AQ$9*'Historical Data'!$AP$2:$AP$9*'Historical Data'!$AJ$2:$AJ$9)/G22) | O22: =IF(SUMPRODUCT('Historical Data'!$AQ$2:$AQ$9*'Historical Data'!$AP$2:$AP$9*'Historical Data'!$AM$2:$AM$9)=0,"",SUMPRODUCT('Historical Data'!$AQ$2:$AQ$9*'Historical Data'!$AP$2:$AP$9*'Historical Data'!$AM$2:$AM$9*'Historical Data'!$AL$2:$AL$9)/SUMPRODUCT('Historical Data'!$AQ$2:$AQ$9*'Historical Data'!$AP$2:$AP$9*'Historical Data'!$AM$2:$AM$9)) -> 0.2 | P22: =IF(E22=0,"",SUMPRODUCT('Historical Data'!$AQ$2:$AQ$9*'Historical Data'!$AP$2:$AP$9*'Historical Data'!$AA$2:$AA$9)/E22) -> 108.275 | Q22: =IF(E22=0,"",SUMPRODUCT('Historical Data'!$AQ$2:$AQ$9*'Historical Data'!$AP$2:$AP$9*'Historical Data'!$M$2:$M$9)/E22) -> 1.5 | R22: =IF(E22=0,"",G22/E22) -> 10000 | S22: =IF(E22=0,"",SUMPRODUCT('Historical Data'!$AQ$2:$AQ$9*'Historical Data'!$AP$2:$AP$9*'Historical Data'!$AN$2:$AN$9)/E22) -> 105 | T22: =IF(E22=0,"",SUMPRODUCT('Historical Data'!$AQ$2:$AQ$9*'Historical Data'!$AP$2:$AP$9*'Historical Data'!$AO$2:$AO$9)/E22) -> 0 | U22: =IF(AND(E22>=Controls!$B$40,G22>=Controls!$B$41),"Yes","No") -> No | V22: =IF(E22+Controls!$B$42=0,0,E22/(E22+Controls!$B$42)) -> 0.032258065 | W22: =IF(L22="",$C$10,V22*L22+(1-V22)*$C$10) -> 0.41 | X22: =IF(OR($C$10="",$C$10=0),"",W22/$C$10) -> 1 | Y22: =IF(U22="Yes",1,0) -> 0 | Z22: =IF(L22="",0,ABS(W22-$C$10)) -> 0 | AA22: =IF(L22="","No","Yes") -> No
A23: S2 | B23: New/renewal only | C23: New/renewal only | D23: =SUMPRODUCT('Historical Data'!$AR$2:$AR$9*'Historical Data'!$AD$2:$AD$9) -> 6 | E23: =SUMPRODUCT('Historical Data'!$AR$2:$AR$9*'Historical Data'!$AP$2:$AP$9) -> 5 | F23: =IF(D23=0,"",E23/D23) -> 0.83333333 | G23: =SUMPRODUCT('Historical Data'!$AR$2:$AR$9*'Historical Data'!$AP$2:$AP$9*'Historical Data'!$N$2:$N$9) -> 120000 | H23: =SUMPRODUCT('Historical Data'!$AR$2:$AR$9*'Historical Data'!$AP$2:$AP$9*'Historical Data'!$AH$2:$AH$9) -> 0 | I23: =IF(E23=0,"",H23/E23) -> 0 | J23: =SUMPRODUCT('Historical Data'!$AR$2:$AR$9*'Historical Data'!$AP$2:$AP$9*'Historical Data'!$AE$2:$AE$9) -> 3 | K23: =IF(E23=0,"",J23/E23) -> 0.6 | L23: =IF(OR(E23<Controls!$B$43,G23=0),"",SUMPRODUCT('Historical Data'!$AR$2:$AR$9*'Historical Data'!$AP$2:$AP$9*'Historical Data'!$AK$2:$AK$9)/G23) -> 0.50833333 | M23: =IF(OR(E23<Controls!$B$43,SUMPRODUCT('Historical Data'!$AR$2:$AR$9*'Historical Data'!$AP$2:$AP$9*'Historical Data'!$AE$2:$AE$9*'Historical Data'!$N$2:$N$9)=0),"",SUMPRODUCT('Historical Data'!$AR$2:$AR$9*'Historical Data'!$AP$2:$AP$9*'Historical Data'!$AE$2:$AE$9*'Historical Data'!$Q$2:$Q$9)/SUMPRODUCT('Historical Data'!$AR$2:$AR$9*'Historical Data'!$AP$2:$AP$9*'Historical Data'!$AE$2:$AE$9*'Historical Data'!$N$2:$N$9)) -> 0.32222222 | N23: =IF(OR(E23<Controls!$B$43,G23=0),"",SUMPRODUCT('Historical Data'!$AR$2:$AR$9*'Historical Data'!$AP$2:$AP$9*'Historical Data'!$AJ$2:$AJ$9)/G23) -> -0.38333333 | O23: =IF(SUMPRODUCT('Historical Data'!$AR$2:$AR$9*'Historical Data'!$AP$2:$AP$9*'Historical Data'!$AM$2:$AM$9)=0,"",SUMPRODUCT('Historical Data'!$AR$2:$AR$9*'Historical Data'!$AP$2:$AP$9*'Historical Data'!$AM$2:$AM$9*'Historical Data'!$AL$2:$AL$9)/SUMPRODUCT('Historical Data'!$AR$2:$AR$9*'Historical Data'!$AP$2:$AP$9*'Historical Data'!$AM$2:$AM$9)) -> 0.35 | P23: =IF(E23=0,"",SUMPRODUCT('Historical Data'!$AR$2:$AR$9*'Historical Data'!$AP$2:$AP$9*'Historical Data'!$AA$2:$AA$9)/E23) -> 107.641 | Q23: =IF(E23=0,"",SUMPRODUCT('Historical Data'!$AR$2:$AR$9*'Historical Data'!$AP$2:$AP$9*'Historical Data'!$M$2:$M$9)/E23) -> 1.5 | R23: =IF(E23=0,"",G23/E23) -> 24000 | S23: =IF(E23=0,"",SUMPRODUCT('Historical Data'!$AR$2:$AR$9*'Historical Data'!$AP$2:$AP$9*'Historical Data'!$AN$2:$AN$9)/E23) -> 85.4 | T23: =IF(E23=0,"",SUMPRODUCT('Historical Data'!$AR$2:$AR$9*'Historical Data'!$AP$2:$AP$9*'Historical Data'!$AO$2:$AO$9)/E23) -> 0 | U23: =IF(AND(E23>=Controls!$B$40,G23>=Controls!$B$41),"Yes","No") -> Yes | V23: =IF(E23+Controls!$B$42=0,0,E23/(E23+Controls!$B$42)) -> 0.14285714 | W23: =IF(L23="",$C$10,V23*L23+(1-V23)*$C$10) -> 0.42404762 | X23: =IF(OR($C$10="",$C$10=0),"",W23/$C$10) -> 1.0342625 | Y23: =IF(U23="Yes",1,0) -> 1 | Z23: =IF(L23="",0,ABS(W23-$C$10)) -> 0.014047619 | AA23: =IF(L23="","No","Yes") -> Yes
A24: S3 | B24: Industry only | C24: Industry only | D24: =SUMPRODUCT('Historical Data'!$AS$2:$AS$9*'Historical Data'!$AD$2:$AD$9) -> 1 | E24: =SUMPRODUCT('Historical Data'!$AS$2:$AS$9*'Historical Data'!$AP$2:$AP$9) -> 1 | F24: =IF(D24=0,"",E24/D24) -> 1 | G24: =SUMPRODUCT('Historical Data'!$AS$2:$AS$9*'Historical Data'!$AP$2:$AP$9*'Historical Data'!$N$2:$N$9) -> 10000 | H24: =SUMPRODUCT('Historical Data'!$AS$2:$AS$9*'Historical Data'!$AP$2:$AP$9*'Historical Data'!$AH$2:$AH$9) -> 0 | I24: =IF(E24=0,"",H24/E24) -> 0 | J24: =SUMPRODUCT('Historical Data'!$AS$2:$AS$9*'Historical Data'!$AP$2:$AP$9*'Historical Data'!$AE$2:$AE$9) -> 0 | K24: =IF(E24=0,"",J24/E24) -> 0 | L24: =IF(OR(E24<Controls!$B$43,G24=0),"",SUMPRODUCT('Historical Data'!$AS$2:$AS$9*'Historical Data'!$AP$2:$AP$9*'Historical Data'!$AK$2:$AK$9)/G24) | M24: =IF(OR(E24<Controls!$B$43,SUMPRODUCT('Historical Data'!$AS$2:$AS$9*'Historical Data'!$AP$2:$AP$9*'Historical Data'!$AE$2:$AE$9*'Historical Data'!$N$2:$N$9)=0),"",SUMPRODUCT('Historical Data'!$AS$2:$AS$9*'Historical Data'!$AP$2:$AP$9*'Historical Data'!$AE$2:$AE$9*'Historical Data'!$Q$2:$Q$9)/SUMPRODUCT('Historical Data'!$AS$2:$AS$9*'Historical Data'!$AP$2:$AP$9*'Historical Data'!$AE$2:$AE$9*'Historical Data'!$N$2:$N$9)) | N24: =IF(OR(E24<Controls!$B$43,G24=0),"",SUMPRODUCT('Historical Data'!$AS$2:$AS$9*'Historical Data'!$AP$2:$AP$9*'Historical Data'!$AJ$2:$AJ$9)/G24) | O24: =IF(SUMPRODUCT('Historical Data'!$AS$2:$AS$9*'Historical Data'!$AP$2:$AP$9*'Historical Data'!$AM$2:$AM$9)=0,"",SUMPRODUCT('Historical Data'!$AS$2:$AS$9*'Historical Data'!$AP$2:$AP$9*'Historical Data'!$AM$2:$AM$9*'Historical Data'!$AL$2:$AL$9)/SUMPRODUCT('Historical Data'!$AS$2:$AS$9*'Historical Data'!$AP$2:$AP$9*'Historical Data'!$AM$2:$AM$9)) -> 0.2 | P24: =IF(E24=0,"",SUMPRODUCT('Historical Data'!$AS$2:$AS$9*'Historical Data'!$AP$2:$AP$9*'Historical Data'!$AA$2:$AA$9)/E24) -> 108.275 | Q24: =IF(E24=0,"",SUMPRODUCT('Historical Data'!$AS$2:$AS$9*'Historical Data'!$AP$2:$AP$9*'Historical Data'!$M$2:$M$9)/E24) -> 1.5 | R24: =IF(E24=0,"",G24/E24) -> 10000 | S24: =IF(E24=0,"",SUMPRODUCT('Historical Data'!$AS$2:$AS$9*'Historical Data'!$AP$2:$AP$9*'Historical Data'!$AN$2:$AN$9)/E24) -> 105 | T24: =IF(E24=0,"",SUMPRODUCT('Historical Data'!$AS$2:$AS$9*'Historical Data'!$AP$2:$AP$9*'Historical Data'!$AO$2:$AO$9)/E24) -> 0 | U24: =IF(AND(E24>=Controls!$B$40,G24>=Controls!$B$41),"Yes","No") -> No | V24: =IF(E24+Controls!$B$42=0,0,E24/(E24+Controls!$B$42)) -> 0.032258065 | W24: =IF(L24="",$C$10,V24*L24+(1-V24)*$C$10) -> 0.41 | X24: =IF(OR($C$10="",$C$10=0),"",W24/$C$10) -> 1 | Y24: =IF(U24="Yes",1,0) -> 0 | Z24: =IF(L24="",0,ABS(W24-$C$10)) -> 0 | AA24: =IF(L24="","No","Yes") -> No
A25: S4 | B25: ISO only | C25: ISO only | D25: =SUMPRODUCT('Historical Data'!$AT$2:$AT$9*'Historical Data'!$AD$2:$AD$9) -> 4 | E25: =SUMPRODUCT('Historical Data'!$AT$2:$AT$9*'Historical Data'!$AP$2:$AP$9) -> 3 | F25: =IF(D25=0,"",E25/D25) -> 0.75 | G25: =SUMPRODUCT('Historical Data'!$AT$2:$AT$9*'Historical Data'!$AP$2:$AP$9*'Historical Data'!$N$2:$N$9) -> 50000 | H25: =SUMPRODUCT('Historical Data'!$AT$2:$AT$9*'Historical Data'!$AP$2:$AP$9*'Historical Data'!$AH$2:$AH$9) -> 0 | I25: =IF(E25=0,"",H25/E25) -> 0 | J25: =SUMPRODUCT('Historical Data'!$AT$2:$AT$9*'Historical Data'!$AP$2:$AP$9*'Historical Data'!$AE$2:$AE$9) -> 2 | K25: =IF(E25=0,"",J25/E25) -> 0.66666667 | L25: =IF(OR(E25<Controls!$B$43,G25=0),"",SUMPRODUCT('Historical Data'!$AT$2:$AT$9*'Historical Data'!$AP$2:$AP$9*'Historical Data'!$AK$2:$AK$9)/G25) -> 0.43 | M25: =IF(OR(E25<Controls!$B$43,SUMPRODUCT('Historical Data'!$AT$2:$AT$9*'Historical Data'!$AP$2:$AP$9*'Historical Data'!$AE$2:$AE$9*'Historical Data'!$N$2:$N$9)=0),"",SUMPRODUCT('Historical Data'!$AT$2:$AT$9*'Historical Data'!$AP$2:$AP$9*'Historical Data'!$AE$2:$AE$9*'Historical Data'!$Q$2:$Q$9)/SUMPRODUCT('Historical Data'!$AT$2:$AT$9*'Historical Data'!$AP$2:$AP$9*'Historical Data'!$AE$2:$AE$9*'Historical Data'!$N$2:$N$9)) -> 0.4625 | N25: =IF(OR(E25<Controls!$B$43,G25=0),"",SUMPRODUCT('Historical Data'!$AT$2:$AT$9*'Historical Data'!$AP$2:$AP$9*'Historical Data'!$AJ$2:$AJ$9)/G25) -> -0.33 | O25: =IF(SUMPRODUCT('Historical Data'!$AT$2:$AT$9*'Historical Data'!$AP$2:$AP$9*'Historical Data'!$AM$2:$AM$9)=0,"",SUMPRODUCT('Historical Data'!$AT$2:$AT$9*'Historical Data'!$AP$2:$AP$9*'Historical Data'!$AM$2:$AM$9*'Historical Data'!$AL$2:$AL$9)/SUMPRODUCT('Historical Data'!$AT$2:$AT$9*'Historical Data'!$AP$2:$AP$9*'Historical Data'!$AM$2:$AM$9)) -> 0.4 | P25: =IF(E25=0,"",SUMPRODUCT('Historical Data'!$AT$2:$AT$9*'Historical Data'!$AP$2:$AP$9*'Historical Data'!$AA$2:$AA$9)/E25) -> 108.275 | Q25: =IF(E25=0,"",SUMPRODUCT('Historical Data'!$AT$2:$AT$9*'Historical Data'!$AP$2:$AP$9*'Historical Data'!$M$2:$M$9)/E25) -> 1.5 | R25: =IF(E25=0,"",G25/E25) -> 16666.667 | S25: =IF(E25=0,"",SUMPRODUCT('Historical Data'!$AT$2:$AT$9*'Historical Data'!$AP$2:$AP$9*'Historical Data'!$AN$2:$AN$9)/E25) -> 99.333333 | T25: =IF(E25=0,"",SUMPRODUCT('Historical Data'!$AT$2:$AT$9*'Historical Data'!$AP$2:$AP$9*'Historical Data'!$AO$2:$AO$9)/E25) -> 0.33333333 | U25: =IF(AND(E25>=Controls!$B$40,G25>=Controls!$B$41),"Yes","No") -> Yes | V25: =IF(E25+Controls!$B$42=0,0,E25/(E25+Controls!$B$42)) -> 0.090909091 | W25: =IF(L25="",$C$10,V25*L25+(1-V25)*$C$10) -> 0.41181818 | X25: =IF(OR($C$10="",$C$10=0),"",W25/$C$10) -> 1.0044346 | Y25: =IF(U25="Yes",1,0) -> 1 | Z25: =IF(L25="",0,ABS(W25-$C$10)) -> 0.0018181818 | AA25: =IF(L25="","No","Yes") -> Yes
A26: S5 | B26: State only (INFORMATIONAL) | C26: State only (INFORMATIONAL) | D26: =SUMPRODUCT('Historical Data'!$AU$2:$AU$9*'Historical Data'!$AD$2:$AD$9) -> 4 | E26: =SUMPRODUCT('Historical Data'!$AU$2:$AU$9*'Historical Data'!$AP$2:$AP$9) -> 3 | F26: =IF(D26=0,"",E26/D26) -> 0.75 | G26: =SUMPRODUCT('Historical Data'!$AU$2:$AU$9*'Historical Data'!$AP$2:$AP$9*'Historical Data'!$N$2:$N$9) -> 50000 | H26: =SUMPRODUCT('Historical Data'!$AU$2:$AU$9*'Historical Data'!$AP$2:$AP$9*'Historical Data'!$AH$2:$AH$9) -> 0 | I26: =IF(E26=0,"",H26/E26) -> 0 | J26: =SUMPRODUCT('Historical Data'!$AU$2:$AU$9*'Historical Data'!$AP$2:$AP$9*'Historical Data'!$AE$2:$AE$9) -> 2 | K26: =IF(E26=0,"",J26/E26) -> 0.66666667 | L26: =IF(OR(E26<Controls!$B$43,G26=0),"",SUMPRODUCT('Historical Data'!$AU$2:$AU$9*'Historical Data'!$AP$2:$AP$9*'Historical Data'!$AK$2:$AK$9)/G26) -> 0.43 | M26: =IF(OR(E26<Controls!$B$43,SUMPRODUCT('Historical Data'!$AU$2:$AU$9*'Historical Data'!$AP$2:$AP$9*'Historical Data'!$AE$2:$AE$9*'Historical Data'!$N$2:$N$9)=0),"",SUMPRODUCT('Historical Data'!$AU$2:$AU$9*'Historical Data'!$AP$2:$AP$9*'Historical Data'!$AE$2:$AE$9*'Historical Data'!$Q$2:$Q$9)/SUMPRODUCT('Historical Data'!$AU$2:$AU$9*'Historical Data'!$AP$2:$AP$9*'Historical Data'!$AE$2:$AE$9*'Historical Data'!$N$2:$N$9)) -> 0.4625 | N26: =IF(OR(E26<Controls!$B$43,G26=0),"",SUMPRODUCT('Historical Data'!$AU$2:$AU$9*'Historical Data'!$AP$2:$AP$9*'Historical Data'!$AJ$2:$AJ$9)/G26) -> -0.33 | O26: =IF(SUMPRODUCT('Historical Data'!$AU$2:$AU$9*'Historical Data'!$AP$2:$AP$9*'Historical Data'!$AM$2:$AM$9)=0,"",SUMPRODUCT('Historical Data'!$AU$2:$AU$9*'Historical Data'!$AP$2:$AP$9*'Historical Data'!$AM$2:$AM$9*'Historical Data'!$AL$2:$AL$9)/SUMPRODUCT('Historical Data'!$AU$2:$AU$9*'Historical Data'!$AP$2:$AP$9*'Historical Data'!$AM$2:$AM$9)) -> 0.4 | P26: =IF(E26=0,"",SUMPRODUCT('Historical Data'!$AU$2:$AU$9*'Historical Data'!$AP$2:$AP$9*'Historical Data'!$AA$2:$AA$9)/E26) -> 108.275 | Q26: =IF(E26=0,"",SUMPRODUCT('Historical Data'!$AU$2:$AU$9*'Historical Data'!$AP$2:$AP$9*'Historical Data'!$M$2:$M$9)/E26) -> 1.5 | R26: =IF(E26=0,"",G26/E26) -> 16666.667 | S26: =IF(E26=0,"",SUMPRODUCT('Historical Data'!$AU$2:$AU$9*'Historical Data'!$AP$2:$AP$9*'Historical Data'!$AN$2:$AN$9)/E26) -> 99.333333 | T26: =IF(E26=0,"",SUMPRODUCT('Historical Data'!$AU$2:$AU$9*'Historical Data'!$AP$2:$AP$9*'Historical Data'!$AO$2:$AO$9)/E26) -> 0.33333333 | U26: =IF(AND(E26>=Controls!$B$40,G26>=Controls!$B$41),"Yes","No") -> Yes | V26: =IF(E26+Controls!$B$42=0,0,E26/(E26+Controls!$B$42)) -> 0.090909091 | W26: =IF(L26="",$C$10,V26*L26+(1-V26)*$C$10) -> 0.41181818 | X26: =IF(OR($C$10="",$C$10=0),"",W26/$C$10) -> 1.0044346 | Y26: =IF(U26="Yes",1,0) -> 1 | Z26: =IF(L26="",0,ABS(W26-$C$10)) -> 0.0018181818 | AA26: =IF(L26="","No","Yes") -> Yes
A28: RESULT
B29: Primary tier (first tier meeting the minimums) | C29: =IFERROR(MATCH(1,$Y$14:$Y$20,0),7) -> 6
B30: Primary cohort | C30: =INDEX($B$14:$B$20,$C$29) -> T6: new/renewal only
B31: Seasoned deals / all matches | C31: =TEXT(INDEX($E$14:$E$20,$C$29),"#,##0")&" / "&TEXT(INDEX($D$14:$D$20,$C$29),"#,##0") -> 5 / 6
B32: % of comparable deals seasoned | C32: =INDEX($F$14:$F$20,$C$29) -> 0.83333333
B33: Cohort principal lost rate (seasoned) | C33: =INDEX($L$14:$L$20,$C$29) -> 0.50833333
B34: Cohort open share | C34: =INDEX($I$14:$I$20,$C$29) -> 0
B35: Cohort return on funded capital | C35: =INDEX($N$14:$N$20,$C$29) -> -0.38333333
B36: Cohort collected on defaults | C36: =INDEX($M$14:$M$20,$C$29) -> 0.32222222
B37: Credibility Z | C37: =INDEX($V$14:$V$20,$C$29) -> 0.14285714
B38: Blended lost rate | C38: =INDEX($W$14:$W$20,$C$29) -> 0.42404762
B39: Relative index (blended / book) | C39: =INDEX($X$14:$X$20,$C$29) -> 1.0342625
B40: Modifier level (1 strong positive .. 3 neutral .. 6 severe) | C40: =IF(OR(C29=7,C39=""),3,COUNTIF(Controls!$A$49:$A$54,"<"&C39)+1) -> 3
B41: Modifier level name | C41: =INDEX(Controls!$B$49:$B$54,C40) -> Neutral
B42: Sizing flex (0 = green line, 1 = red line) | C42: =INDEX(Controls!$C$49:$C$54,C40) -> 0
B43: Fund multiplier | C43: =INDEX(Controls!$D$49:$D$54,C40) -> 1
B44: Term step (bands) | C44: =INDEX(Controls!$E$49:$E$54,C40) -> 0
B45: Factor step (tiers) | C45: =INDEX(Controls!$F$49:$F$54,C40) -> 0
B46: Frequency rule | C46: =INDEX(Controls!$G$49:$G$54,C40) -> As proposed
B47: Manual review flag from modifier | C47: =INDEX(Controls!$H$49:$H$54,C40) -> N
B48: Largest-impact variable (position / NR / industry / ISO) | C48: =IF(MAX($Z$22:$Z$25)=0,"none rated",INDEX($B$22:$B$25,MATCH(MAX($Z$22:$Z$25),$Z$22:$Z$25,0))) -> New/renewal only
B49: its blended lost rate vs book | C49: =IF(MAX($Z$22:$Z$25)=0,"",TEXT(INDEX($W$22:$W$25,MATCH(MAX($Z$22:$Z$25),$Z$22:$Z$25,0)),"0.0%")&" vs "&TEXT($C$10,"0.0%")&" book ("&TEXT(INDEX($E$22:$E$25,MATCH(MAX($Z$22:$Z$25),$Z$22:$Z$25,0)),"0")&" seasoned deals)") -> 42.4% vs 41.0% book (5 seasoned deals)
B50: ISO | C50: =IF($C$8="","not entered",IF($E$25=0,$C$8&": no seasoned deals in the book",IF($L$25="",$C$8&": "&$E$25&" seasoned deals - too few to rate",$C$8&": "&$E$25&" seasoned deals, lost "&TEXT($L$25,"0.0%")&" vs "&TEXT($C$10,"0.0%")&" book, Z "&TEXT($V$25,"0.00")&" -> "&IF($X$25<=Controls!$A$50,"stronger than book",IF($X$25<=Controls!$A$51,"neutral","weaker than book"))))) -> Fundwell: 3 seasoned deals, lost 43.0% vs 41.0% book, Z 0.09 -> neutral
B51: Industry | C51: =IF($C$7="","not entered",IF($E$24=0,$C$7&": no seasoned deals in the book",IF($L$24="",$C$7&": "&$E$24&" seasoned deals - too few to rate",$C$7&": "&$E$24&" seasoned deals, lost "&TEXT($L$24,"0.0%")&" vs "&TEXT($C$10,"0.0%")&" book, Z "&TEXT($V$24,"0.00")&" -> "&IF($X$24<=Controls!$A$50,"stronger than book",IF($X$24<=Controls!$A$51,"neutral","weaker than book"))))) -> Eating & Drinking Places: 1 seasoned deals - too few to rate
B52: New deal / renewal | C52: =IF($C$5="","not entered",IF($L$23="",$C$5&": "&$E$23&" seasoned deals - too few to rate",$C$5&": "&$E$23&" seasoned deals, lost "&TEXT($L$23,"0.0%")&" vs "&TEXT($C$10,"0.0%")&" book -> "&IF($X$23<=Controls!$A$50,"stronger than book",IF($X$23<=Controls!$A$51,"neutral","weaker than book")))) -> New Deal: 5 seasoned deals, lost 50.8% vs 41.0% book -> neutral
B53: Position | C53: =IF($C$6="","not entered",IF($L$22="","position "&$C$6&": "&$E$22&" seasoned deals - too few to rate","position "&$C$6&": "&$E$22&" seasoned deals, lost "&TEXT($L$22,"0.0%")&" vs "&TEXT($C$10,"0.0%")&" book -> "&IF($X$22<=Controls!$A$50,"stronger than book",IF($X$22<=Controls!$A$51,"neutral","weaker than book")))) -> position 1: 1 seasoned deals - too few to rate
B54: State (informational only) | C54: =IF($C$9="","not entered - not needed",IF($E$26=0,$C$9&": no seasoned deals",IF($L$26="",$C$9&": "&$E$26&" seasoned deals - too few to rate",$C$9&": "&$E$26&" seasoned deals, lost "&TEXT($L$26,"0.0%")&" vs "&TEXT($C$10,"0.0%")&" book - informational only"))) -> NJ: 3 seasoned deals, lost 43.0% vs 41.0% book - informational only
B55: Conflicting signals? (ISO vs industry on opposite sides) | C55: =IF(OR($L$24="",$L$25=""),"No",IF(OR(AND($X$24<Controls!$A$50,$X$25>Controls!$A$51),AND($X$25<Controls!$A$50,$X$24>Controls!$A$51)),"YES - review both cohorts","No")) -> No
B56: Warnings | C56: =IF($C$29=7,"No cohort met the minimums - book baseline, modifier Neutral; ","")&IF(C29<>1,"Tighter tiers 1-"&(C29-1)&" too small; ","")&IF(C55<>"No","Conflicting ISO / industry signals; ","") -> Tighter tiers 1-5 too small;

Sheet Comparable Deals
A1: COMPARABLE DEALS - every house-book deal in the primary cohort
A2: ="Primary cohort: "&'Historical Score'!$C$30&" | "&'Historical Score'!$C$31&" seasoned / all | first 400 listed" -> Primary cohort: T6: new/renewal only | 5 / 6 seasoned / all | first 400 listed
A4: # | B4: Contract ID | C4: DBA | D4: Status | E4: Funded | F4: Position | G4: Industry | H4: ISO | I4: State | J4: New/renewal | K4: Factor | L4: Advance | M4: Collected | N4: % paid | O4: Net cash | P4: Principal lost | Q4: Term (bd) | R4: Age (bd) | S4: Days on book | T4: Seasoned | U4: Default | V4: Open | W4: Similarity tier | X4: Why included
A5: 1 | B5: =IFERROR(INDEX('Historical Data'!$A$2:$A$9,MATCH($A5,'Historical Data'!$BE$2:$BE$9,0)),"") -> A-001 | C5: =IFERROR(INDEX('Historical Data'!$B$2:$B$9,MATCH($A5,'Historical Data'!$BE$2:$BE$9,0)),"") -> Ridgeline Cafe | D5: =IFERROR(INDEX('Historical Data'!$D$2:$D$9,MATCH($A5,'Historical Data'!$BE$2:$BE$9,0)),"") -> Closed | E5: =IFERROR(INDEX('Historical Data'!$E$2:$E$9,MATCH($A5,'Historical Data'!$BE$2:$BE$9,0)),"") -> 45672 | F5: =IFERROR(INDEX('Historical Data'!$G$2:$G$9,MATCH($A5,'Historical Data'!$BE$2:$BE$9,0)),"") -> 1 | G5: =IFERROR(INDEX('Historical Data'!$Y$2:$Y$9,MATCH($A5,'Historical Data'!$BE$2:$BE$9,0)),"") -> Eating & Drinking Places | H5: =IFERROR(INDEX('Historical Data'!$K$2:$K$9,MATCH($A5,'Historical Data'!$BE$2:$BE$9,0)),"") -> Fundwell | I5: =IFERROR(INDEX('Historical Data'!$J$2:$J$9,MATCH($A5,'Historical Data'!$BE$2:$BE$9,0)),"") -> NJ | J5: =IFERROR(INDEX('Historical Data'!$L$2:$L$9,MATCH($A5,'Historical Data'!$BE$2:$BE$9,0)),"") -> New Deal | K5: =IFERROR(INDEX('Historical Data'!$M$2:$M$9,MATCH($A5,'Historical Data'!$BE$2:$BE$9,0)),"") -> 1.5 | L5: =IFERROR(INDEX('Historical Data'!$N$2:$N$9,MATCH($A5,'Historical Data'!$BE$2:$BE$9,0)),"") -> 10000 | M5: =IFERROR(INDEX('Historical Data'!$Q$2:$Q$9,MATCH($A5,'Historical Data'!$BE$2:$BE$9,0)),"") -> 15000 | N5: =IFERROR(INDEX('Historical Data'!$S$2:$S$9,MATCH($A5,'Historical Data'!$BE$2:$BE$9,0)),"") -> 1 | O5: =IFERROR(INDEX('Historical Data'!$AJ$2:$AJ$9,MATCH($A5,'Historical Data'!$BE$2:$BE$9,0)),"") -> 5000 | P5: =IFERROR(INDEX('Historical Data'!$AK$2:$AK$9,MATCH($A5,'Historical Data'!$BE$2:$BE$9,0)),"") -> 0 | Q5: =IFERROR(INDEX('Historical Data'!$AA$2:$AA$9,MATCH($A5,'Historical Data'!$BE$2:$BE$9,0)),"") -> 108.275 | R5: =IFERROR(INDEX('Historical Data'!$AB$2:$AB$9,MATCH($A5,'Historical Data'!$BE$2:$BE$9,0)),"") -> 405 | S5: =IFERROR(INDEX('Historical Data'!$AN$2:$AN$9,MATCH($A5,'Historical Data'!$BE$2:$BE$9,0)),"") -> 105 | T5: =IFERROR(INDEX('Historical Data'!$AC$2:$AC$9,MATCH($A5,'Historical Data'!$BE$2:$BE$9,0)),"") -> 1 | U5: =IFERROR(INDEX('Historical Data'!$AE$2:$AE$9,MATCH($A5,'Historical Data'!$BE$2:$BE$9,0)),"") -> 0 | V5: =IFERROR(INDEX('Historical Data'!$AH$2:$AH$9,MATCH($A5,'Historical Data'!$BE$2:$BE$9,0)),"") -> 0 | W5: =IFERROR(INDEX('Historical Data'!$BC$2:$BC$9,MATCH($A5,'Historical Data'!$BE$2:$BE$9,0)),"") -> 1 | X5: =IF(B5="","",IF(W5=1,"NR + industry + position",IF(W5=2,"NR + ISO + position",IF(W5=3,"NR + industry",IF(W5=4,"NR + ISO",IF(W5=5,"NR + position",IF(W5=6,"NR only","book baseline"))))))&" ["&IF(T5=1,"seasoned","unseasoned")&IF(U5=1,", defaulted","")&IF(V5=1,", open","")&"]") -> NR + industry + position [seasoned]
A6: 2 | B6: =IFERROR(INDEX('Historical Data'!$A$2:$A$9,MATCH($A6,'Historical Data'!$BE$2:$BE$9,0)),"") -> A-003 | C6: =IFERROR(INDEX('Historical Data'!$B$2:$B$9,MATCH($A6,'Historical Data'!$BE$2:$BE$9,0)),"") -> Kane Construction | D6: =IFERROR(INDEX('Historical Data'!$D$2:$D$9,MATCH($A6,'Historical Data'!$BE$2:$BE$9,0)),"") -> Legal | E6: =IFERROR(INDEX('Historical Data'!$E$2:$E$9,MATCH($A6,'Historical Data'!$BE$2:$BE$9,0)),"") -> 45721 | F6: =IFERROR(INDEX('Historical Data'!$G$2:$G$9,MATCH($A6,'Historical Data'!$BE$2:$BE$9,0)),"") -> 3 | G6: =IFERROR(INDEX('Historical Data'!$Y$2:$Y$9,MATCH($A6,'Historical Data'!$BE$2:$BE$9,0)),"") -> General Building Contractors | H6: =IFERROR(INDEX('Historical Data'!$K$2:$K$9,MATCH($A6,'Historical Data'!$BE$2:$BE$9,0)),"") -> Fundwell | I6: =IFERROR(INDEX('Historical Data'!$J$2:$J$9,MATCH($A6,'Historical Data'!$BE$2:$BE$9,0)),"") -> NJ | J6: =IFERROR(INDEX('Historical Data'!$L$2:$L$9,MATCH($A6,'Historical Data'!$BE$2:$BE$9,0)),"") -> New Deal | K6: =IFERROR(INDEX('Historical Data'!$M$2:$M$9,MATCH($A6,'Historical Data'!$BE$2:$BE$9,0)),"") -> 1.5 | L6: =IFERROR(INDEX('Historical Data'!$N$2:$N$9,MATCH($A6,'Historical Data'!$BE$2:$BE$9,0)),"") -> 30000 | M6: =IFERROR(INDEX('Historical Data'!$Q$2:$Q$9,MATCH($A6,'Historical Data'!$BE$2:$BE$9,0)),"") -> 9000 | N6: =IFERROR(INDEX('Historical Data'!$S$2:$S$9,MATCH($A6,'Historical Data'!$BE$2:$BE$9,0)),"") -> 0.2 | O6: =IFERROR(INDEX('Historical Data'!$AJ$2:$AJ$9,MATCH($A6,'Historical Data'!$BE$2:$BE$9,0)),"") -> -21000 | P6: =IFERROR(INDEX('Historical Data'!$AK$2:$AK$9,MATCH($A6,'Historical Data'!$BE$2:$BE$9,0)),"") -> 21000 | Q6: =IFERROR(INDEX('Historical Data'!$AA$2:$AA$9,MATCH($A6,'Historical Data'!$BE$2:$BE$9,0)),"") -> 129.93 | R6: =IFERROR(INDEX('Historical Data'!$AB$2:$AB$9,MATCH($A6,'Historical Data'!$BE$2:$BE$9,0)),"") -> 372 | S6: =IFERROR(INDEX('Historical Data'!$AN$2:$AN$9,MATCH($A6,'Historical Data'!$BE$2:$BE$9,0)),"") -> 66 | T6: =IFERROR(INDEX('Historical Data'!$AC$2:$AC$9,MATCH($A6,'Historical Data'!$BE$2:$BE$9,0)),"") -> 1 | U6: =IFERROR(INDEX('Historical Data'!$AE$2:$AE$9,MATCH($A6,'Historical Data'!$BE$2:$BE$9,0)),"") -> 1 | V6: =IFERROR(INDEX('Historical Data'!$AH$2:$AH$9,MATCH($A6,'Historical Data'!$BE$2:$BE$9,0)),"") -> 0 | W6: =IFERROR(INDEX('Historical Data'!$BC$2:$BC$9,MATCH($A6,'Historical Data'!$BE$2:$BE$9,0)),"") -> 4 | X6: =IF(B6="","",IF(W6=1,"NR + industry + position",IF(W6=2,"NR + ISO + position",IF(W6=3,"NR + industry",IF(W6=4,"NR + ISO",IF(W6=5,"NR + position",IF(W6=6,"NR only","book baseline"))))))&" ["&IF(T6=1,"seasoned","unseasoned")&IF(U6=1,", defaulted","")&IF(V6=1,", open","")&"]") -> NR + ISO [seasoned, defaulted]
A7: 3 | B7: =IFERROR(INDEX('Historical Data'!$A$2:$A$9,MATCH($A7,'Historical Data'!$BE$2:$BE$9,0)),"") -> A-004 | C7: =IFERROR(INDEX('Historical Data'!$B$2:$B$9,MATCH($A7,'Historical Data'!$BE$2:$BE$9,0)),"") -> Baymont Auto Body | D7: =IFERROR(INDEX('Historical Data'!$D$2:$D$9,MATCH($A7,'Historical Data'!$BE$2:$BE$9,0)),"") -> In House Collection | E7: =IFERROR(INDEX('Historical Data'!$E$2:$E$9,MATCH($A7,'Historical Data'!$BE$2:$BE$9,0)),"") -> 45768 | F7: =IFERROR(INDEX('Historical Data'!$G$2:$G$9,MATCH($A7,'Historical Data'!$BE$2:$BE$9,0)),"") -> 3 | G7: =IFERROR(INDEX('Historical Data'!$Y$2:$Y$9,MATCH($A7,'Historical Data'!$BE$2:$BE$9,0)),"") -> Auto Repair & Services | H7: =IFERROR(INDEX('Historical Data'!$K$2:$K$9,MATCH($A7,'Historical Data'!$BE$2:$BE$9,0)),"") -> Westwood | I7: =IFERROR(INDEX('Historical Data'!$J$2:$J$9,MATCH($A7,'Historical Data'!$BE$2:$BE$9,0)),"") -> TX | J7: =IFERROR(INDEX('Historical Data'!$L$2:$L$9,MATCH($A7,'Historical Data'!$BE$2:$BE$9,0)),"") -> New Deal | K7: =IFERROR(INDEX('Historical Data'!$M$2:$M$9,MATCH($A7,'Historical Data'!$BE$2:$BE$9,0)),"") -> 1.5 | L7: =IFERROR(INDEX('Historical Data'!$N$2:$N$9,MATCH($A7,'Historical Data'!$BE$2:$BE$9,0)),"") -> 40000 | M7: =IFERROR(INDEX('Historical Data'!$Q$2:$Q$9,MATCH($A7,'Historical Data'!$BE$2:$BE$9,0)),"") -> 20000 | N7: =IFERROR(INDEX('Historical Data'!$S$2:$S$9,MATCH($A7,'Historical Data'!$BE$2:$BE$9,0)),"") -> 0.33333333 | O7: =IFERROR(INDEX('Historical Data'!$AJ$2:$AJ$9,MATCH($A7,'Historical Data'!$BE$2:$BE$9,0)),"") -> -20000 | P7: =IFERROR(INDEX('Historical Data'!$AK$2:$AK$9,MATCH($A7,'Historical Data'!$BE$2:$BE$9,0)),"") -> 20000 | Q7: =IFERROR(INDEX('Historical Data'!$AA$2:$AA$9,MATCH($A7,'Historical Data'!$BE$2:$BE$9,0)),"") -> 120 | R7: =IFERROR(INDEX('Historical Data'!$AB$2:$AB$9,MATCH($A7,'Historical Data'!$BE$2:$BE$9,0)),"") -> 339 | S7: =IFERROR(INDEX('Historical Data'!$AN$2:$AN$9,MATCH($A7,'Historical Data'!$BE$2:$BE$9,0)),"") -> 85 | T7: =IFERROR(INDEX('Historical Data'!$AC$2:$AC$9,MATCH($A7,'Historical Data'!$BE$2:$BE$9,0)),"") -> 1 | U7: =IFERROR(INDEX('Historical Data'!$AE$2:$AE$9,MATCH($A7,'Historical Data'!$BE$2:$BE$9,0)),"") -> 1 | V7: =IFERROR(INDEX('Historical Data'!$AH$2:$AH$9,MATCH($A7,'Historical Data'!$BE$2:$BE$9,0)),"") -> 0 | W7: =IFERROR(INDEX('Historical Data'!$BC$2:$BC$9,MATCH($A7,'Historical Data'!$BE$2:$BE$9,0)),"") -> 6 | X7: =IF(B7="","",IF(W7=1,"NR + industry + position",IF(W7=2,"NR + ISO + position",IF(W7=3,"NR + industry",IF(W7=4,"NR + ISO",IF(W7=5,"NR + position",IF(W7=6,"NR only","book baseline"))))))&" ["&IF(T7=1,"seasoned","unseasoned")&IF(U7=1,", defaulted","")&IF(V7=1,", open","")&"]") -> NR only [seasoned, defaulted]
A8: 4 | B8: =IFERROR(INDEX('Historical Data'!$A$2:$A$9,MATCH($A8,'Historical Data'!$BE$2:$BE$9,0)),"") -> A-006 | C8: =IFERROR(INDEX('Historical Data'!$B$2:$B$9,MATCH($A8,'Historical Data'!$BE$2:$BE$9,0)),"") -> Orchard Supply | D8: =IFERROR(INDEX('Historical Data'!$D$2:$D$9,MATCH($A8,'Historical Data'!$BE$2:$BE$9,0)),"") -> Bankruptcy | E8: =IFERROR(INDEX('Historical Data'!$E$2:$E$9,MATCH($A8,'Historical Data'!$BE$2:$BE$9,0)),"") -> 45826 | F8: =IFERROR(INDEX('Historical Data'!$G$2:$G$9,MATCH($A8,'Historical Data'!$BE$2:$BE$9,0)),"") -> 4 | G8: =IFERROR(INDEX('Historical Data'!$Y$2:$Y$9,MATCH($A8,'Historical Data'!$BE$2:$BE$9,0)),"") -> No SIC | H8: =IFERROR(INDEX('Historical Data'!$K$2:$K$9,MATCH($A8,'Historical Data'!$BE$2:$BE$9,0)),"") -> Westwood | I8: =IFERROR(INDEX('Historical Data'!$J$2:$J$9,MATCH($A8,'Historical Data'!$BE$2:$BE$9,0)),"") -> TX | J8: =IFERROR(INDEX('Historical Data'!$L$2:$L$9,MATCH($A8,'Historical Data'!$BE$2:$BE$9,0)),"") -> New Deal | K8: =IFERROR(INDEX('Historical Data'!$M$2:$M$9,MATCH($A8,'Historical Data'!$BE$2:$BE$9,0)),"") -> 1.5 | L8: =IFERROR(INDEX('Historical Data'!$N$2:$N$9,MATCH($A8,'Historical Data'!$BE$2:$BE$9,0)),"") -> 20000 | M8: =IFERROR(INDEX('Historical Data'!$Q$2:$Q$9,MATCH($A8,'Historical Data'!$BE$2:$BE$9,0)),"") -> 0 | N8: =IFERROR(INDEX('Historical Data'!$S$2:$S$9,MATCH($A8,'Historical Data'!$BE$2:$BE$9,0)),"") -> 0 | O8: =IFERROR(INDEX('Historical Data'!$AJ$2:$AJ$9,MATCH($A8,'Historical Data'!$BE$2:$BE$9,0)),"") -> -20000 | P8: =IFERROR(INDEX('Historical Data'!$AK$2:$AK$9,MATCH($A8,'Historical Data'!$BE$2:$BE$9,0)),"") -> 20000 | Q8: =IFERROR(INDEX('Historical Data'!$AA$2:$AA$9,MATCH($A8,'Historical Data'!$BE$2:$BE$9,0)),"") -> 80 | R8: =IFERROR(INDEX('Historical Data'!$AB$2:$AB$9,MATCH($A8,'Historical Data'!$BE$2:$BE$9,0)),"") -> 298 | S8: =IFERROR(INDEX('Historical Data'!$AN$2:$AN$9,MATCH($A8,'Historical Data'!$BE$2:$BE$9,0)),"") -> 64 | T8: =IFERROR(INDEX('Historical Data'!$AC$2:$AC$9,MATCH($A8,'Historical Data'!$BE$2:$BE$9,0)),"") -> 1 | U8: =IFERROR(INDEX('Historical Data'!$AE$2:$AE$9,MATCH($A8,'Historical Data'!$BE$2:$BE$9,0)),"") -> 1 | V8: =IFERROR(INDEX('Historical Data'!$AH$2:$AH$9,MATCH($A8,'Historical Data'!$BE$2:$BE$9,0)),"") -> 0 | W8: =IFERROR(INDEX('Historical Data'!$BC$2:$BC$9,MATCH($A8,'Historical Data'!$BE$2:$BE$9,0)),"") -> 6 | X8: =IF(B8="","",IF(W8=1,"NR + industry + position",IF(W8=2,"NR + ISO + position",IF(W8=3,"NR + industry",IF(W8=4,"NR + ISO",IF(W8=5,"NR + position",IF(W8=6,"NR only","book baseline"))))))&" ["&IF(T8=1,"seasoned","unseasoned")&IF(U8=1,", defaulted","")&IF(V8=1,", open","")&"]") -> NR only [seasoned, defaulted]
A9: 5 | B9: =IFERROR(INDEX('Historical Data'!$A$2:$A$9,MATCH($A9,'Historical Data'!$BE$2:$BE$9,0)),"") -> A-007 | C9: =IFERROR(INDEX('Historical Data'!$B$2:$B$9,MATCH($A9,'Historical Data'!$BE$2:$BE$9,0)),"") -> Pinewood Dental | D9: =IFERROR(INDEX('Historical Data'!$D$2:$D$9,MATCH($A9,'Historical Data'!$BE$2:$BE$9,0)),"") -> Open | E9: =IFERROR(INDEX('Historical Data'!$E$2:$E$9,MATCH($A9,'Historical Data'!$BE$2:$BE$9,0)),"") -> 46030 | F9: =IFERROR(INDEX('Historical Data'!$G$2:$G$9,MATCH($A9,'Historical Data'!$BE$2:$BE$9,0)),"") -> 1 | G9: =IFERROR(INDEX('Historical Data'!$Y$2:$Y$9,MATCH($A9,'Historical Data'!$BE$2:$BE$9,0)),"") -> Health Services | H9: =IFERROR(INDEX('Historical Data'!$K$2:$K$9,MATCH($A9,'Historical Data'!$BE$2:$BE$9,0)),"") -> Fundwell | I9: =IFERROR(INDEX('Historical Data'!$J$2:$J$9,MATCH($A9,'Historical Data'!$BE$2:$BE$9,0)),"") -> NJ | J9: =IFERROR(INDEX('Historical Data'!$L$2:$L$9,MATCH($A9,'Historical Data'!$BE$2:$BE$9,0)),"") -> New Deal | K9: =IFERROR(INDEX('Historical Data'!$M$2:$M$9,MATCH($A9,'Historical Data'!$BE$2:$BE$9,0)),"") -> 1.5 | L9: =IFERROR(INDEX('Historical Data'!$N$2:$N$9,MATCH($A9,'Historical Data'!$BE$2:$BE$9,0)),"") -> 50000 | M9: =IFERROR(INDEX('Historical Data'!$Q$2:$Q$9,MATCH($A9,'Historical Data'!$BE$2:$BE$9,0)),"") -> 30000 | N9: =IFERROR(INDEX('Historical Data'!$S$2:$S$9,MATCH($A9,'Historical Data'!$BE$2:$BE$9,0)),"") -> 0.4 | O9: =IFERROR(INDEX('Historical Data'!$AJ$2:$AJ$9,MATCH($A9,'Historical Data'!$BE$2:$BE$9,0)),"") -> -20000 | P9: =IFERROR(INDEX('Historical Data'!$AK$2:$AK$9,MATCH($A9,'Historical Data'!$BE$2:$BE$9,0)),"") -> 0 | Q9: =IFERROR(INDEX('Historical Data'!$AA$2:$AA$9,MATCH($A9,'Historical Data'!$BE$2:$BE$9,0)),"") -> 129.93 | R9: =IFERROR(INDEX('Historical Data'!$AB$2:$AB$9,MATCH($A9,'Historical Data'!$BE$2:$BE$9,0)),"") -> 160 | S9: =IFERROR(INDEX('Historical Data'!$AN$2:$AN$9,MATCH($A9,'Historical Data'!$BE$2:$BE$9,0)),"") -> 144 | T9: =IFERROR(INDEX('Historical Data'!$AC$2:$AC$9,MATCH($A9,'Historical Data'!$BE$2:$BE$9,0)),"") -> 0 | U9: =IFERROR(INDEX('Historical Data'!$AE$2:$AE$9,MATCH($A9,'Historical Data'!$BE$2:$BE$9,0)),"") -> 0 | V9: =IFERROR(INDEX('Historical Data'!$AH$2:$AH$9,MATCH($A9,'Historical Data'!$BE$2:$BE$9,0)),"") -> 1 | W9: =IFERROR(INDEX('Historical Data'!$BC$2:$BC$9,MATCH($A9,'Historical Data'!$BE$2:$BE$9,0)),"") -> 2 | X9: =IF(B9="","",IF(W9=1,"NR + industry + position",IF(W9=2,"NR + ISO + position",IF(W9=3,"NR + industry",IF(W9=4,"NR + ISO",IF(W9=5,"NR + position",IF(W9=6,"NR only","book baseline"))))))&" ["&IF(T9=1,"seasoned","unseasoned")&IF(U9=1,", defaulted","")&IF(V9=1,", open","")&"]") -> NR + ISO + position [unseasoned, open]
A10: 6 | B10: =IFERROR(INDEX('Historical Data'!$A$2:$A$9,MATCH($A10,'Historical Data'!$BE$2:$BE$9,0)),"") -> A-008 | C10: =IFERROR(INDEX('Historical Data'!$B$2:$B$9,MATCH($A10,'Historical Data'!$BE$2:$BE$9,0)),"") -> Harbor Cleaning | D10: =IFERROR(INDEX('Historical Data'!$D$2:$D$9,MATCH($A10,'Historical Data'!$BE$2:$BE$9,0)),"") -> Closed/NSF Unpaid | E10: =IFERROR(INDEX('Historical Data'!$E$2:$E$9,MATCH($A10,'Historical Data'!$BE$2:$BE$9,0)),"") -> 45852 | F10: =IFERROR(INDEX('Historical Data'!$G$2:$G$9,MATCH($A10,'Historical Data'!$BE$2:$BE$9,0)),"") -> 3 | G10: =IFERROR(INDEX('Historical Data'!$Y$2:$Y$9,MATCH($A10,'Historical Data'!$BE$2:$BE$9,0)),"") -> Business Services | H10: =IFERROR(INDEX('Historical Data'!$K$2:$K$9,MATCH($A10,'Historical Data'!$BE$2:$BE$9,0)),"") -> Westwood | I10: =IFERROR(INDEX('Historical Data'!$J$2:$J$9,MATCH($A10,'Historical Data'!$BE$2:$BE$9,0)),"") -> TX | J10: =IFERROR(INDEX('Historical Data'!$L$2:$L$9,MATCH($A10,'Historical Data'!$BE$2:$BE$9,0)),"") -> New Deal | K10: =IFERROR(INDEX('Historical Data'!$M$2:$M$9,MATCH($A10,'Historical Data'!$BE$2:$BE$9,0)),"") -> 1.5 | L10: =IFERROR(INDEX('Historical Data'!$N$2:$N$9,MATCH($A10,'Historical Data'!$BE$2:$BE$9,0)),"") -> 20000 | M10: =IFERROR(INDEX('Historical Data'!$Q$2:$Q$9,MATCH($A10,'Historical Data'!$BE$2:$BE$9,0)),"") -> 30000 | N10: =IFERROR(INDEX('Historical Data'!$S$2:$S$9,MATCH($A10,'Historical Data'!$BE$2:$BE$9,0)),"") -> 1 | O10: =IFERROR(INDEX('Historical Data'!$AJ$2:$AJ$9,MATCH($A10,'Historical Data'!$BE$2:$BE$9,0)),"") -> 10000 | P10: =IFERROR(INDEX('Historical Data'!$AK$2:$AK$9,MATCH($A10,'Historical Data'!$BE$2:$BE$9,0)),"") -> 0 | Q10: =IFERROR(INDEX('Historical Data'!$AA$2:$AA$9,MATCH($A10,'Historical Data'!$BE$2:$BE$9,0)),"") -> 100 | R10: =IFERROR(INDEX('Historical Data'!$AB$2:$AB$9,MATCH($A10,'Historical Data'!$BE$2:$BE$9,0)),"") -> 282 | S10: =IFERROR(INDEX('Historical Data'!$AN$2:$AN$9,MATCH($A10,'Historical Data'!$BE$2:$BE$9,0)),"") -> 107 | T10: =IFERROR(INDEX('Historical Data'!$AC$2:$AC$9,MATCH($A10,'Historical Data'!$BE$2:$BE$9,0)),"") -> 1 | U10: =IFERROR(INDEX('Historical Data'!$AE$2:$AE$9,MATCH($A10,'Historical Data'!$BE$2:$BE$9,0)),"") -> 0 | V10: =IFERROR(INDEX('Historical Data'!$AH$2:$AH$9,MATCH($A10,'Historical Data'!$BE$2:$BE$9,0)),"") -> 0 | W10: =IFERROR(INDEX('Historical Data'!$BC$2:$BC$9,MATCH($A10,'Historical Data'!$BE$2:$BE$9,0)),"") -> 6 | X10: =IF(B10="","",IF(W10=1,"NR + industry + position",IF(W10=2,"NR + ISO + position",IF(W10=3,"NR + industry",IF(W10=4,"NR + ISO",IF(W10=5,"NR + position",IF(W10=6,"NR only","book baseline"))))))&" ["&IF(T10=1,"seasoned","unseasoned")&IF(U10=1,", defaulted","")&IF(V10=1,", open","")&"]") -> NR only [seasoned]
A11: 7 | B11: =IFERROR(INDEX('Historical Data'!$A$2:$A$9,MATCH($A11,'Historical Data'!$BE$2:$BE$9,0)),"") | C11: =IFERROR(INDEX('Historical Data'!$B$2:$B$9,MATCH($A11,'Historical Data'!$BE$2:$BE$9,0)),"") | D11: =IFERROR(INDEX('Historical Data'!$D$2:$D$9,MATCH($A11,'Historical Data'!$BE$2:$BE$9,0)),"") | E11: =IFERROR(INDEX('Historical Data'!$E$2:$E$9,MATCH($A11,'Historical Data'!$BE$2:$BE$9,0)),"") | F11: =IFERROR(INDEX('Historical Data'!$G$2:$G$9,MATCH($A11,'Historical Data'!$BE$2:$BE$9,0)),"") | G11: =IFERROR(INDEX('Historical Data'!$Y$2:$Y$9,MATCH($A11,'Historical Data'!$BE$2:$BE$9,0)),"") | H11: =IFERROR(INDEX('Historical Data'!$K$2:$K$9,MATCH($A11,'Historical Data'!$BE$2:$BE$9,0)),"") | I11: =IFERROR(INDEX('Historical Data'!$J$2:$J$9,MATCH($A11,'Historical Data'!$BE$2:$BE$9,0)),"") | J11: =IFERROR(INDEX('Historical Data'!$L$2:$L$9,MATCH($A11,'Historical Data'!$BE$2:$BE$9,0)),"") | K11: =IFERROR(INDEX('Historical Data'!$M$2:$M$9,MATCH($A11,'Historical Data'!$BE$2:$BE$9,0)),"") | L11: =IFERROR(INDEX('Historical Data'!$N$2:$N$9,MATCH($A11,'Historical Data'!$BE$2:$BE$9,0)),"") | M11: =IFERROR(INDEX('Historical Data'!$Q$2:$Q$9,MATCH($A11,'Historical Data'!$BE$2:$BE$9,0)),"") | N11: =IFERROR(INDEX('Historical Data'!$S$2:$S$9,MATCH($A11,'Historical Data'!$BE$2:$BE$9,0)),"") | O11: =IFERROR(INDEX('Historical Data'!$AJ$2:$AJ$9,MATCH($A11,'Historical Data'!$BE$2:$BE$9,0)),"") | P11: =IFERROR(INDEX('Historical Data'!$AK$2:$AK$9,MATCH($A11,'Historical Data'!$BE$2:$BE$9,0)),"") | Q11: =IFERROR(INDEX('Historical Data'!$AA$2:$AA$9,MATCH($A11,'Historical Data'!$BE$2:$BE$9,0)),"") | R11: =IFERROR(INDEX('Historical Data'!$AB$2:$AB$9,MATCH($A11,'Historical Data'!$BE$2:$BE$9,0)),"") | S11: =IFERROR(INDEX('Historical Data'!$AN$2:$AN$9,MATCH($A11,'Historical Data'!$BE$2:$BE$9,0)),"") | T11: =IFERROR(INDEX('Historical Data'!$AC$2:$AC$9,MATCH($A11,'Historical Data'!$BE$2:$BE$9,0)),"") | U11: =IFERROR(INDEX('Historical Data'!$AE$2:$AE$9,MATCH($A11,'Historical Data'!$BE$2:$BE$9,0)),"") | V11: =IFERROR(INDEX('Historical Data'!$AH$2:$AH$9,MATCH($A11,'Historical Data'!$BE$2:$BE$9,0)),"") | W11: =IFERROR(INDEX('Historical Data'!$BC$2:$BC$9,MATCH($A11,'Historical Data'!$BE$2:$BE$9,0)),"") | X11: =IF(B11="","",IF(W11=1,"NR + industry + position",IF(W11=2,"NR + ISO + position",IF(W11=3,"NR + industry",IF(W11=4,"NR + ISO",IF(W11=5,"NR + position",IF(W11=6,"NR only","book baseline"))))))&" ["&IF(T11=1,"seasoned","unseasoned")&IF(U11=1,", defaulted","")&IF(V11=1,", open","")&"]")
A12: 8 | B12: =IFERROR(INDEX('Historical Data'!$A$2:$A$9,MATCH($A12,'Historical Data'!$BE$2:$BE$9,0)),"") | C12: =IFERROR(INDEX('Historical Data'!$B$2:$B$9,MATCH($A12,'Historical Data'!$BE$2:$BE$9,0)),"") | D12: =IFERROR(INDEX('Historical Data'!$D$2:$D$9,MATCH($A12,'Historical Data'!$BE$2:$BE$9,0)),"") | E12: =IFERROR(INDEX('Historical Data'!$E$2:$E$9,MATCH($A12,'Historical Data'!$BE$2:$BE$9,0)),"") | F12: =IFERROR(INDEX('Historical Data'!$G$2:$G$9,MATCH($A12,'Historical Data'!$BE$2:$BE$9,0)),"") | G12: =IFERROR(INDEX('Historical Data'!$Y$2:$Y$9,MATCH($A12,'Historical Data'!$BE$2:$BE$9,0)),"") | H12: =IFERROR(INDEX('Historical Data'!$K$2:$K$9,MATCH($A12,'Historical Data'!$BE$2:$BE$9,0)),"") | I12: =IFERROR(INDEX('Historical Data'!$J$2:$J$9,MATCH($A12,'Historical Data'!$BE$2:$BE$9,0)),"") | J12: =IFERROR(INDEX('Historical Data'!$L$2:$L$9,MATCH($A12,'Historical Data'!$BE$2:$BE$9,0)),"") | K12: =IFERROR(INDEX('Historical Data'!$M$2:$M$9,MATCH($A12,'Historical Data'!$BE$2:$BE$9,0)),"") | L12: =IFERROR(INDEX('Historical Data'!$N$2:$N$9,MATCH($A12,'Historical Data'!$BE$2:$BE$9,0)),"") | M12: =IFERROR(INDEX('Historical Data'!$Q$2:$Q$9,MATCH($A12,'Historical Data'!$BE$2:$BE$9,0)),"") | N12: =IFERROR(INDEX('Historical Data'!$S$2:$S$9,MATCH($A12,'Historical Data'!$BE$2:$BE$9,0)),"") | O12: =IFERROR(INDEX('Historical Data'!$AJ$2:$AJ$9,MATCH($A12,'Historical Data'!$BE$2:$BE$9,0)),"") | P12: =IFERROR(INDEX('Historical Data'!$AK$2:$AK$9,MATCH($A12,'Historical Data'!$BE$2:$BE$9,0)),"") | Q12: =IFERROR(INDEX('Historical Data'!$AA$2:$AA$9,MATCH($A12,'Historical Data'!$BE$2:$BE$9,0)),"") | R12: =IFERROR(INDEX('Historical Data'!$AB$2:$AB$9,MATCH($A12,'Historical Data'!$BE$2:$BE$9,0)),"") | S12: =IFERROR(INDEX('Historical Data'!$AN$2:$AN$9,MATCH($A12,'Historical Data'!$BE$2:$BE$9,0)),"") | T12: =IFERROR(INDEX('Historical Data'!$AC$2:$AC$9,MATCH($A12,'Historical Data'!$BE$2:$BE$9,0)),"") | U12: =IFERROR(INDEX('Historical Data'!$AE$2:$AE$9,MATCH($A12,'Historical Data'!$BE$2:$BE$9,0)),"") | V12: =IFERROR(INDEX('Historical Data'!$AH$2:$AH$9,MATCH($A12,'Historical Data'!$BE$2:$BE$9,0)),"") | W12: =IFERROR(INDEX('Historical Data'!$BC$2:$BC$9,MATCH($A12,'Historical Data'!$BE$2:$BE$9,0)),"") | X12: =IF(B12="","",IF(W12=1,"NR + industry + position",IF(W12=2,"NR + ISO + position",IF(W12=3,"NR + industry",IF(W12=4,"NR + ISO",IF(W12=5,"NR + position",IF(W12=6,"NR only","book baseline"))))))&" ["&IF(T12=1,"seasoned","unseasoned")&IF(U12=1,", defaulted","")&IF(V12=1,", open","")&"]")
A13: 9 | B13: =IFERROR(INDEX('Historical Data'!$A$2:$A$9,MATCH($A13,'Historical Data'!$BE$2:$BE$9,0)),"") | C13: =IFERROR(INDEX('Historical Data'!$B$2:$B$9,MATCH($A13,'Historical Data'!$BE$2:$BE$9,0)),"") | D13: =IFERROR(INDEX('Historical Data'!$D$2:$D$9,MATCH($A13,'Historical Data'!$BE$2:$BE$9,0)),"") | E13: =IFERROR(INDEX('Historical Data'!$E$2:$E$9,MATCH($A13,'Historical Data'!$BE$2:$BE$9,0)),"") | F13: =IFERROR(INDEX('Historical Data'!$G$2:$G$9,MATCH($A13,'Historical Data'!$BE$2:$BE$9,0)),"") | G13: =IFERROR(INDEX('Historical Data'!$Y$2:$Y$9,MATCH($A13,'Historical Data'!$BE$2:$BE$9,0)),"") | H13: =IFERROR(INDEX('Historical Data'!$K$2:$K$9,MATCH($A13,'Historical Data'!$BE$2:$BE$9,0)),"") | I13: =IFERROR(INDEX('Historical Data'!$J$2:$J$9,MATCH($A13,'Historical Data'!$BE$2:$BE$9,0)),"") | J13: =IFERROR(INDEX('Historical Data'!$L$2:$L$9,MATCH($A13,'Historical Data'!$BE$2:$BE$9,0)),"") | K13: =IFERROR(INDEX('Historical Data'!$M$2:$M$9,MATCH($A13,'Historical Data'!$BE$2:$BE$9,0)),"") | L13: =IFERROR(INDEX('Historical Data'!$N$2:$N$9,MATCH($A13,'Historical Data'!$BE$2:$BE$9,0)),"") | M13: =IFERROR(INDEX('Historical Data'!$Q$2:$Q$9,MATCH($A13,'Historical Data'!$BE$2:$BE$9,0)),"") | N13: =IFERROR(INDEX('Historical Data'!$S$2:$S$9,MATCH($A13,'Historical Data'!$BE$2:$BE$9,0)),"") | O13: =IFERROR(INDEX('Historical Data'!$AJ$2:$AJ$9,MATCH($A13,'Historical Data'!$BE$2:$BE$9,0)),"") | P13: =IFERROR(INDEX('Historical Data'!$AK$2:$AK$9,MATCH($A13,'Historical Data'!$BE$2:$BE$9,0)),"") | Q13: =IFERROR(INDEX('Historical Data'!$AA$2:$AA$9,MATCH($A13,'Historical Data'!$BE$2:$BE$9,0)),"") | R13: =IFERROR(INDEX('Historical Data'!$AB$2:$AB$9,MATCH($A13,'Historical Data'!$BE$2:$BE$9,0)),"") | S13: =IFERROR(INDEX('Historical Data'!$AN$2:$AN$9,MATCH($A13,'Historical Data'!$BE$2:$BE$9,0)),"") | T13: =IFERROR(INDEX('Historical Data'!$AC$2:$AC$9,MATCH($A13,'Historical Data'!$BE$2:$BE$9,0)),"") | U13: =IFERROR(INDEX('Historical Data'!$AE$2:$AE$9,MATCH($A13,'Historical Data'!$BE$2:$BE$9,0)),"") | V13: =IFERROR(INDEX('Historical Data'!$AH$2:$AH$9,MATCH($A13,'Historical Data'!$BE$2:$BE$9,0)),"") | W13: =IFERROR(INDEX('Historical Data'!$BC$2:$BC$9,MATCH($A13,'Historical Data'!$BE$2:$BE$9,0)),"") | X13: =IF(B13="","",IF(W13=1,"NR + industry + position",IF(W13=2,"NR + ISO + position",IF(W13=3,"NR + industry",IF(W13=4,"NR + ISO",IF(W13=5,"NR + position",IF(W13=6,"NR only","book baseline"))))))&" ["&IF(T13=1,"seasoned","unseasoned")&IF(U13=1,", defaulted","")&IF(V13=1,", open","")&"]")
A14: 10 | B14: =IFERROR(INDEX('Historical Data'!$A$2:$A$9,MATCH($A14,'Historical Data'!$BE$2:$BE$9,0)),"") | C14: =IFERROR(INDEX('Historical Data'!$B$2:$B$9,MATCH($A14,'Historical Data'!$BE$2:$BE$9,0)),"") | D14: =IFERROR(INDEX('Historical Data'!$D$2:$D$9,MATCH($A14,'Historical Data'!$BE$2:$BE$9,0)),"") | E14: =IFERROR(INDEX('Historical Data'!$E$2:$E$9,MATCH($A14,'Historical Data'!$BE$2:$BE$9,0)),"") | F14: =IFERROR(INDEX('Historical Data'!$G$2:$G$9,MATCH($A14,'Historical Data'!$BE$2:$BE$9,0)),"") | G14: =IFERROR(INDEX('Historical Data'!$Y$2:$Y$9,MATCH($A14,'Historical Data'!$BE$2:$BE$9,0)),"") | H14: =IFERROR(INDEX('Historical Data'!$K$2:$K$9,MATCH($A14,'Historical Data'!$BE$2:$BE$9,0)),"") | I14: =IFERROR(INDEX('Historical Data'!$J$2:$J$9,MATCH($A14,'Historical Data'!$BE$2:$BE$9,0)),"") | J14: =IFERROR(INDEX('Historical Data'!$L$2:$L$9,MATCH($A14,'Historical Data'!$BE$2:$BE$9,0)),"") | K14: =IFERROR(INDEX('Historical Data'!$M$2:$M$9,MATCH($A14,'Historical Data'!$BE$2:$BE$9,0)),"") | L14: =IFERROR(INDEX('Historical Data'!$N$2:$N$9,MATCH($A14,'Historical Data'!$BE$2:$BE$9,0)),"") | M14: =IFERROR(INDEX('Historical Data'!$Q$2:$Q$9,MATCH($A14,'Historical Data'!$BE$2:$BE$9,0)),"") | N14: =IFERROR(INDEX('Historical Data'!$S$2:$S$9,MATCH($A14,'Historical Data'!$BE$2:$BE$9,0)),"") | O14: =IFERROR(INDEX('Historical Data'!$AJ$2:$AJ$9,MATCH($A14,'Historical Data'!$BE$2:$BE$9,0)),"") | P14: =IFERROR(INDEX('Historical Data'!$AK$2:$AK$9,MATCH($A14,'Historical Data'!$BE$2:$BE$9,0)),"") | Q14: =IFERROR(INDEX('Historical Data'!$AA$2:$AA$9,MATCH($A14,'Historical Data'!$BE$2:$BE$9,0)),"") | R14: =IFERROR(INDEX('Historical Data'!$AB$2:$AB$9,MATCH($A14,'Historical Data'!$BE$2:$BE$9,0)),"") | S14: =IFERROR(INDEX('Historical Data'!$AN$2:$AN$9,MATCH($A14,'Historical Data'!$BE$2:$BE$9,0)),"") | T14: =IFERROR(INDEX('Historical Data'!$AC$2:$AC$9,MATCH($A14,'Historical Data'!$BE$2:$BE$9,0)),"") | U14: =IFERROR(INDEX('Historical Data'!$AE$2:$AE$9,MATCH($A14,'Historical Data'!$BE$2:$BE$9,0)),"") | V14: =IFERROR(INDEX('Historical Data'!$AH$2:$AH$9,MATCH($A14,'Historical Data'!$BE$2:$BE$9,0)),"") | W14: =IFERROR(INDEX('Historical Data'!$BC$2:$BC$9,MATCH($A14,'Historical Data'!$BE$2:$BE$9,0)),"") | X14: =IF(B14="","",IF(W14=1,"NR + industry + position",IF(W14=2,"NR + ISO + position",IF(W14=3,"NR + industry",IF(W14=4,"NR + ISO",IF(W14=5,"NR + position",IF(W14=6,"NR only","book baseline"))))))&" ["&IF(T14=1,"seasoned","unseasoned")&IF(U14=1,", defaulted","")&IF(V14=1,", open","")&"]")
A15: 11 | B15: =IFERROR(INDEX('Historical Data'!$A$2:$A$9,MATCH($A15,'Historical Data'!$BE$2:$BE$9,0)),"") | C15: =IFERROR(INDEX('Historical Data'!$B$2:$B$9,MATCH($A15,'Historical Data'!$BE$2:$BE$9,0)),"") | D15: =IFERROR(INDEX('Historical Data'!$D$2:$D$9,MATCH($A15,'Historical Data'!$BE$2:$BE$9,0)),"") | E15: =IFERROR(INDEX('Historical Data'!$E$2:$E$9,MATCH($A15,'Historical Data'!$BE$2:$BE$9,0)),"") | F15: =IFERROR(INDEX('Historical Data'!$G$2:$G$9,MATCH($A15,'Historical Data'!$BE$2:$BE$9,0)),"") | G15: =IFERROR(INDEX('Historical Data'!$Y$2:$Y$9,MATCH($A15,'Historical Data'!$BE$2:$BE$9,0)),"") | H15: =IFERROR(INDEX('Historical Data'!$K$2:$K$9,MATCH($A15,'Historical Data'!$BE$2:$BE$9,0)),"") | I15: =IFERROR(INDEX('Historical Data'!$J$2:$J$9,MATCH($A15,'Historical Data'!$BE$2:$BE$9,0)),"") | J15: =IFERROR(INDEX('Historical Data'!$L$2:$L$9,MATCH($A15,'Historical Data'!$BE$2:$BE$9,0)),"") | K15: =IFERROR(INDEX('Historical Data'!$M$2:$M$9,MATCH($A15,'Historical Data'!$BE$2:$BE$9,0)),"") | L15: =IFERROR(INDEX('Historical Data'!$N$2:$N$9,MATCH($A15,'Historical Data'!$BE$2:$BE$9,0)),"") | M15: =IFERROR(INDEX('Historical Data'!$Q$2:$Q$9,MATCH($A15,'Historical Data'!$BE$2:$BE$9,0)),"") | N15: =IFERROR(INDEX('Historical Data'!$S$2:$S$9,MATCH($A15,'Historical Data'!$BE$2:$BE$9,0)),"") | O15: =IFERROR(INDEX('Historical Data'!$AJ$2:$AJ$9,MATCH($A15,'Historical Data'!$BE$2:$BE$9,0)),"") | P15: =IFERROR(INDEX('Historical Data'!$AK$2:$AK$9,MATCH($A15,'Historical Data'!$BE$2:$BE$9,0)),"") | Q15: =IFERROR(INDEX('Historical Data'!$AA$2:$AA$9,MATCH($A15,'Historical Data'!$BE$2:$BE$9,0)),"") | R15: =IFERROR(INDEX('Historical Data'!$AB$2:$AB$9,MATCH($A15,'Historical Data'!$BE$2:$BE$9,0)),"") | S15: =IFERROR(INDEX('Historical Data'!$AN$2:$AN$9,MATCH($A15,'Historical Data'!$BE$2:$BE$9,0)),"") | T15: =IFERROR(INDEX('Historical Data'!$AC$2:$AC$9,MATCH($A15,'Historical Data'!$BE$2:$BE$9,0)),"") | U15: =IFERROR(INDEX('Historical Data'!$AE$2:$AE$9,MATCH($A15,'Historical Data'!$BE$2:$BE$9,0)),"") | V15: =IFERROR(INDEX('Historical Data'!$AH$2:$AH$9,MATCH($A15,'Historical Data'!$BE$2:$BE$9,0)),"") | W15: =IFERROR(INDEX('Historical Data'!$BC$2:$BC$9,MATCH($A15,'Historical Data'!$BE$2:$BE$9,0)),"") | X15: =IF(B15="","",IF(W15=1,"NR + industry + position",IF(W15=2,"NR + ISO + position",IF(W15=3,"NR + industry",IF(W15=4,"NR + ISO",IF(W15=5,"NR + position",IF(W15=6,"NR only","book baseline"))))))&" ["&IF(T15=1,"seasoned","unseasoned")&IF(U15=1,", defaulted","")&IF(V15=1,", open","")&"]")
A16: 12 | B16: =IFERROR(INDEX('Historical Data'!$A$2:$A$9,MATCH($A16,'Historical Data'!$BE$2:$BE$9,0)),"") | C16: =IFERROR(INDEX('Historical Data'!$B$2:$B$9,MATCH($A16,'Historical Data'!$BE$2:$BE$9,0)),"") | D16: =IFERROR(INDEX('Historical Data'!$D$2:$D$9,MATCH($A16,'Historical Data'!$BE$2:$BE$9,0)),"") | E16: =IFERROR(INDEX('Historical Data'!$E$2:$E$9,MATCH($A16,'Historical Data'!$BE$2:$BE$9,0)),"") | F16: =IFERROR(INDEX('Historical Data'!$G$2:$G$9,MATCH($A16,'Historical Data'!$BE$2:$BE$9,0)),"") | G16: =IFERROR(INDEX('Historical Data'!$Y$2:$Y$9,MATCH($A16,'Historical Data'!$BE$2:$BE$9,0)),"") | H16: =IFERROR(INDEX('Historical Data'!$K$2:$K$9,MATCH($A16,'Historical Data'!$BE$2:$BE$9,0)),"") | I16: =IFERROR(INDEX('Historical Data'!$J$2:$J$9,MATCH($A16,'Historical Data'!$BE$2:$BE$9,0)),"") | J16: =IFERROR(INDEX('Historical Data'!$L$2:$L$9,MATCH($A16,'Historical Data'!$BE$2:$BE$9,0)),"") | K16: =IFERROR(INDEX('Historical Data'!$M$2:$M$9,MATCH($A16,'Historical Data'!$BE$2:$BE$9,0)),"") | L16: =IFERROR(INDEX('Historical Data'!$N$2:$N$9,MATCH($A16,'Historical Data'!$BE$2:$BE$9,0)),"") | M16: =IFERROR(INDEX('Historical Data'!$Q$2:$Q$9,MATCH($A16,'Historical Data'!$BE$2:$BE$9,0)),"") | N16: =IFERROR(INDEX('Historical Data'!$S$2:$S$9,MATCH($A16,'Historical Data'!$BE$2:$BE$9,0)),"") | O16: =IFERROR(INDEX('Historical Data'!$AJ$2:$AJ$9,MATCH($A16,'Historical Data'!$BE$2:$BE$9,0)),"") | P16: =IFERROR(INDEX('Historical Data'!$AK$2:$AK$9,MATCH($A16,'Historical Data'!$BE$2:$BE$9,0)),"") | Q16: =IFERROR(INDEX('Historical Data'!$AA$2:$AA$9,MATCH($A16,'Historical Data'!$BE$2:$BE$9,0)),"") | R16: =IFERROR(INDEX('Historical Data'!$AB$2:$AB$9,MATCH($A16,'Historical Data'!$BE$2:$BE$9,0)),"") | S16: =IFERROR(INDEX('Historical Data'!$AN$2:$AN$9,MATCH($A16,'Historical Data'!$BE$2:$BE$9,0)),"") | T16: =IFERROR(INDEX('Historical Data'!$AC$2:$AC$9,MATCH($A16,'Historical Data'!$BE$2:$BE$9,0)),"") | U16: =IFERROR(INDEX('Historical Data'!$AE$2:$AE$9,MATCH($A16,'Historical Data'!$BE$2:$BE$9,0)),"") | V16: =IFERROR(INDEX('Historical Data'!$AH$2:$AH$9,MATCH($A16,'Historical Data'!$BE$2:$BE$9,0)),"") | W16: =IFERROR(INDEX('Historical Data'!$BC$2:$BC$9,MATCH($A16,'Historical Data'!$BE$2:$BE$9,0)),"") | X16: =IF(B16="","",IF(W16=1,"NR + industry + position",IF(W16=2,"NR + ISO + position",IF(W16=3,"NR + industry",IF(W16=4,"NR + ISO",IF(W16=5,"NR + position",IF(W16=6,"NR only","book baseline"))))))&" ["&IF(T16=1,"seasoned","unseasoned")&IF(U16=1,", defaulted","")&IF(V16=1,", open","")&"]")
... A404: 400 | B404: =IFERROR(INDEX('Historical Data'!$A$2:$A$9,MATCH($A404,'Historical Data'!$BE$2:$BE$9,0)),"") | C404: =IFERROR(INDEX('Historical Data'!$B$2:$B$9,MATCH($A404,'Historical Data'!$BE$2:$BE$9,0)),"") | D404: =IFERROR(INDEX('Historical Data'!$D$2:$D$9,MATCH($A404,'Historical Data'!$BE$2:$BE$9,0)),"") | E404: =IFERROR(INDEX('Historical Data'!$E$2:$E$9,MATCH($A404,'Historical Data'!$BE$2:$BE$9,0)),"") | F404: =IFERROR(INDEX('Historical Data'!$G$2:$G$9,MATCH($A404,'Historical Data'!$BE$2:$BE$9,0)),"") | G404: =IFERROR(INDEX('Historical Data'!$Y$2:$Y$9,MATCH($A404,'Historical Data'!$BE$2:$BE$9,0)),"") | H404: =IFERROR(INDEX('Historical Data'!$K$2:$K$9,MATCH($A404,'Historical Data'!$BE$2:$BE$9,0)),"") | I404: =IFERROR(INDEX('Historical Data'!$J$2:$J$9,MATCH($A404,'Historical Data'!$BE$2:$BE$9,0)),"") | J404: =IFERROR(INDEX('Historical Data'!$L$2:$L$9,MATCH($A404,'Historical Data'!$BE$2:$BE$9,0)),"") | K404: =IFERROR(INDEX('Historical Data'!$M$2:$M$9,MATCH($A404,'Historical Data'!$BE$2:$BE$9,0)),"") | L404: =IFERROR(INDEX('Historical Data'!$N$2:$N$9,MATCH($A404,'Historical Data'!$BE$2:$BE$9,0)),"") | M404: =IFERROR(INDEX('Historical Data'!$Q$2:$Q$9,MATCH($A404,'Historical Data'!$BE$2:$BE$9,0)),"") | N404: =IFERROR(INDEX('Historical Data'!$S$2:$S$9,MATCH($A404,'Historical Data'!$BE$2:$BE$9,0)),"") | O404: =IFERROR(INDEX('Historical Data'!$AJ$2:$AJ$9,MATCH($A404,'Historical Data'!$BE$2:$BE$9,0)),"") | P404: =IFERROR(INDEX('Historical Data'!$AK$2:$AK$9,MATCH($A404,'Historical Data'!$BE$2:$BE$9,0)),"") | Q404: =IFERROR(INDEX('Historical Data'!$AA$2:$AA$9,MATCH($A404,'Historical Data'!$BE$2:$BE$9,0)),"") | R404: =IFERROR(INDEX('Historical Data'!$AB$2:$AB$9,MATCH($A404,'Historical Data'!$BE$2:$BE$9,0)),"") | S404: =IFERROR(INDEX('Historical Data'!$AN$2:$AN$9,MATCH($A404,'Historical Data'!$BE$2:$BE$9,0)),"") | T404: =IFERROR(INDEX('Historical Data'!$AC$2:$AC$9,MATCH($A404,'Historical Data'!$BE$2:$BE$9,0)),"") | U404: =IFERROR(INDEX('Historical Data'!$AE$2:$AE$9,MATCH($A404,'Historical Data'!$BE$2:$BE$9,0)),"") | V404: =IFERROR(INDEX('Historical Data'!$AH$2:$AH$9,MATCH($A404,'Historical Data'!$BE$2:$BE$9,0)),"") | W404: =IFERROR(INDEX('Historical Data'!$BC$2:$BC$9,MATCH($A404,'Historical Data'!$BE$2:$BE$9,0)),"") | X404: =IF(B404="","",IF(W404=1,"NR + industry + position",IF(W404=2,"NR + ISO + position",IF(W404=3,"NR + industry",IF(W404=4,"NR + ISO",IF(W404=5,"NR + position",IF(W404=6,"NR only","book baseline"))))))&" ["&IF(T404=1,"seasoned","unseasoned")&IF(U404=1,", defaulted","")&IF(V404=1,", open","")&"]")

Sheet Historical Data
A1: Contract ID | B1: DBA | C1: Legal name | D1: Status | E1: Start date | F1: Last active | G1: Position | H1: SIC | I1: SIC2 | J1: State | K1: ISO | L1: New or renewal | M1: Factor | N1: Advance | O1: Commission | P1: Payback | Q1: Collected | R1: Balance | S1: % paid | T1: Exp dur (raw) | U1: NSF count | V1: Avg rev/mo | W1: Holdback % | X1: Biz start | Y1: Industry | Z1: Pay frequency | AA1: Term (bus. days) | AB1: Age at as-of (bus. days) | AC1: Seasoned | AD1: In window | AE1: Default | AF1: Resolved | AG1: Closed family | AH1: Open | AI1: Status valid | AJ1: Net cash | AK1: Principal lost | AL1: Adv / revenue | AM1: Has revenue | AN1: Days on book (bus.) | AO1: Renewal | AP1: Eligible (seasoned & in window) | AQ1: m: position | AR1: m: new/renewal | AS1: m: industry | AT1: m: ISO | AU1: m: state | AV1: T1 NR+Ind+Pos | AW1: T2 NR+ISO+Pos | AX1: T3 NR+Ind | AY1: T4 NR+ISO | AZ1: T5 NR+Pos | BA1: T6 NR | BB1: T7 Book | BC1: Best tier | BD1: In primary cohort | BE1: Seq
A2: A-001 | B2: Ridgeline Cafe | C2: Ridgeline Cafe LLC | D2: Closed | E2: 45672 | F2: 45821 | G2: 1 | H2: 5812 | I2: 58 | J2: NJ | K2: Fundwell | L2: New Deal | M2: 1.5 | N2: 10000 | O2: 1000 | P2: 15000 | Q2: 15000 | R2: 0 | S2: 1 | T2: 5 | U2: 0 | V2: 50000 | W2: 0.12 | X2: 43160 | Y2: =IF(I2="","No SIC",IFERROR(VLOOKUP(I2,Ref!$A$2:$B$65,2,FALSE()),"Unclassified")) -> Eating & Drinking Places | Z2: =IF(T2="","",IF(T2<12,"Daily","Weekly")) -> Daily | AA2: =IF(T2="",0,IF(T2<12,T2*Controls!$B$29,T2*5)) -> 108.275 | AB2: =IF(E2="",0,NETWORKDAYS(E2,Controls!$B$36,Ref!$K$2:$K$42)) -> 405 | AC2: =IF(AND(AA2>0,AB2>=Controls!$B$39*AA2),1,0) -> 1 | AD2: =IF(AND(E2<>"",E2>=Controls!$B$37,E2<=Controls!$B$38),1,0) -> 1 | AE2: =IF(IFERROR(VLOOKUP(D2,Controls!$A$59:$E$69,2,FALSE()),"No")="Yes",1,0) -> 0 | AF2: =IF(IFERROR(VLOOKUP(D2,Controls!$A$59:$E$69,3,FALSE()),"No")="Yes",1,0) -> 1 | AG2: =IF(IFERROR(VLOOKUP(D2,Controls!$A$59:$E$69,4,FALSE()),"No")="Yes",1,0) -> 1 | AH2: =IF(IFERROR(VLOOKUP(D2,Controls!$A$59:$E$69,5,FALSE()),"No")="Yes",1,0) -> 0 | AI2: =IF(ISNUMBER(MATCH(D2,Controls!$A$59:$A$69,0)),1,0) -> 1 | AJ2: =Q2-N2 -> 5000 | AK2: =IF(AE2=1,MAX(0,N2-Q2),0) -> 0 | AL2: =IF(OR(V2="",V2=0),0,N2/V2) -> 0.2 | AM2: =IF(OR(V2="",V2=0),0,1) -> 1 | AN2: =IF(OR(E2="",F2=""),0,NETWORKDAYS(E2,F2,Ref!$K$2:$K$42)) -> 105 | AO2: =IF(L2="Renewal",1,0) -> 0 | AP2: =AC2*AD2 -> 1 | AQ2: =IF(AND(G2<>"",'Historical Score'!$C$6<>""),IF(G2='Historical Score'!$C$6,1,0),0) -> 1 | AR2: =IF(AND(L2<>"",'Historical Score'!$C$5<>""),IF(L2='Historical Score'!$C$5,1,0),0) -> 1 | AS2: =IF(AND(Y2<>"",'Historical Score'!$C$7<>""),IF(Y2='Historical Score'!$C$7,1,0),0) -> 1 | AT2: =IF(AND(K2<>"",'Historical Score'!$C$8<>""),IF(K2='Historical Score'!$C$8,1,0),0) -> 1 | AU2: =IF(AND(J2<>"",'Historical Score'!$C$9<>""),IF(J2='Historical Score'!$C$9,1,0),0) -> 1 | AV2: =AR2*AS2*AQ2 -> 1 | AW2: =AR2*AT2*AQ2 -> 1 | AX2: =AR2*AS2 -> 1 | AY2: =AR2*AT2 -> 1 | AZ2: =AR2*AQ2 -> 1 | BA2: =AR2 -> 1 | BB2: =1 -> 1 | BC2: =IF(AV2=1,1,IF(AW2=1,2,IF(AX2=1,3,IF(AY2=1,4,IF(AZ2=1,5,IF(BA2=1,6,7)))))) -> 1 | BD2: =IF(AD2=1,CHOOSE('Historical Score'!$C$29,AV2,AW2,AX2,AY2,AZ2,BA2,BB2),0) -> 1 | BE2: =IF(BD2=1,COUNTIF($BD$2:BD2,1),"") -> 1
A3: A-002 | B3: Delta Freight | C3: Delta Freight Group LLC | D3: Closed | E3: 45698 | F3: 45848 | G3: 2 | H3: 4213 | I3: 42 | J3: TX | K3: Westwood | L3: Renewal | M3: 1.5 | N3: 20000 | O3: 2000 | P3: 30000 | Q3: 30000 | R3: 0 | S3: 1 | T3: 20 | U3: 0 | V3: 100000 | W3: 0.09 | X3: 42170 | Y3: =IF(I3="","No SIC",IFERROR(VLOOKUP(I3,Ref!$A$2:$B$65,2,FALSE()),"Unclassified")) -> Trucking & Warehousing | Z3: =IF(T3="","",IF(T3<12,"Daily","Weekly")) -> Weekly | AA3: =IF(T3="",0,IF(T3<12,T3*Controls!$B$29,T3*5)) -> 100 | AB3: =IF(E3="",0,NETWORKDAYS(E3,Controls!$B$36,Ref!$K$2:$K$42)) -> 388 | AC3: =IF(AND(AA3>0,AB3>=Controls!$B$39*AA3),1,0) -> 1 | AD3: =IF(AND(E3<>"",E3>=Controls!$B$37,E3<=Controls!$B$38),1,0) -> 1 | AE3: =IF(IFERROR(VLOOKUP(D3,Controls!$A$59:$E$69,2,FALSE()),"No")="Yes",1,0) -> 0 | AF3: =IF(IFERROR(VLOOKUP(D3,Controls!$A$59:$E$69,3,FALSE()),"No")="Yes",1,0) -> 1 | AG3: =IF(IFERROR(VLOOKUP(D3,Controls!$A$59:$E$69,4,FALSE()),"No")="Yes",1,0) -> 1 | AH3: =IF(IFERROR(VLOOKUP(D3,Controls!$A$59:$E$69,5,FALSE()),"No")="Yes",1,0) -> 0 | AI3: =IF(ISNUMBER(MATCH(D3,Controls!$A$59:$A$69,0)),1,0) -> 1 | AJ3: =Q3-N3 -> 10000 | AK3: =IF(AE3=1,MAX(0,N3-Q3),0) -> 0 | AL3: =IF(OR(V3="",V3=0),0,N3/V3) -> 0.2 | AM3: =IF(OR(V3="",V3=0),0,1) -> 1 | AN3: =IF(OR(E3="",F3=""),0,NETWORKDAYS(E3,F3,Ref!$K$2:$K$42)) -> 105 | AO3: =IF(L3="Renewal",1,0) -> 1 | AP3: =AC3*AD3 -> 1 | AQ3: =IF(AND(G3<>"",'Historical Score'!$C$6<>""),IF(G3='Historical Score'!$C$6,1,0),0) -> 0 | AR3: =IF(AND(L3<>"",'Historical Score'!$C$5<>""),IF(L3='Historical Score'!$C$5,1,0),0) -> 0 | AS3: =IF(AND(Y3<>"",'Historical Score'!$C$7<>""),IF(Y3='Historical Score'!$C$7,1,0),0) -> 0 | AT3: =IF(AND(K3<>"",'Historical Score'!$C$8<>""),IF(K3='Historical Score'!$C$8,1,0),0) -> 0 | AU3: =IF(AND(J3<>"",'Historical Score'!$C$9<>""),IF(J3='Historical Score'!$C$9,1,0),0) -> 0 | AV3: =AR3*AS3*AQ3 -> 0 | AW3: =AR3*AT3*AQ3 -> 0 | AX3: =AR3*AS3 -> 0 | AY3: =AR3*AT3 -> 0 | AZ3: =AR3*AQ3 -> 0 | BA3: =AR3 -> 0 | BB3: =1 -> 1 | BC3: =IF(AV3=1,1,IF(AW3=1,2,IF(AX3=1,3,IF(AY3=1,4,IF(AZ3=1,5,IF(BA3=1,6,7)))))) -> 7 | BD3: =IF(AD3=1,CHOOSE('Historical Score'!$C$29,AV3,AW3,AX3,AY3,AZ3,BA3,BB3),0) -> 0 | BE3: =IF(BD3=1,COUNTIF($BD$2:BD3,1),"")
A4: A-003 | B4: Kane Construction | C4: Kane Construction Inc | D4: Legal | E4: 45721 | F4: 45813 | G4: 3 | H4: 1542 | I4: 15 | J4: NJ | K4: Fundwell | L4: New Deal | M4: 1.5 | N4: 30000 | O4: 3000 | P4: 45000 | Q4: 9000 | R4: 36000 | S4: 0.2 | T4: 6 | U4: 4 | V4: 60000 | W4: 0.15 | X4: 43840 | Y4: =IF(I4="","No SIC",IFERROR(VLOOKUP(I4,Ref!$A$2:$B$65,2,FALSE()),"Unclassified")) -> General Building Contractors | Z4: =IF(T4="","",IF(T4<12,"Daily","Weekly")) -> Daily | AA4: =IF(T4="",0,IF(T4<12,T4*Controls!$B$29,T4*5)) -> 129.93 | AB4: =IF(E4="",0,NETWORKDAYS(E4,Controls!$B$36,Ref!$K$2:$K$42)) -> 372 | AC4: =IF(AND(AA4>0,AB4>=Controls!$B$39*AA4),1,0) -> 1 | AD4: =IF(AND(E4<>"",E4>=Controls!$B$37,E4<=Controls!$B$38),1,0) -> 1 | AE4: =IF(IFERROR(VLOOKUP(D4,Controls!$A$59:$E$69,2,FALSE()),"No")="Yes",1,0) -> 1 | AF4: =IF(IFERROR(VLOOKUP(D4,Controls!$A$59:$E$69,3,FALSE()),"No")="Yes",1,0) -> 0 | AG4: =IF(IFERROR(VLOOKUP(D4,Controls!$A$59:$E$69,4,FALSE()),"No")="Yes",1,0) -> 0 | AH4: =IF(IFERROR(VLOOKUP(D4,Controls!$A$59:$E$69,5,FALSE()),"No")="Yes",1,0) -> 0 | AI4: =IF(ISNUMBER(MATCH(D4,Controls!$A$59:$A$69,0)),1,0) -> 1 | AJ4: =Q4-N4 -> -21000 | AK4: =IF(AE4=1,MAX(0,N4-Q4),0) -> 21000 | AL4: =IF(OR(V4="",V4=0),0,N4/V4) -> 0.5 | AM4: =IF(OR(V4="",V4=0),0,1) -> 1 | AN4: =IF(OR(E4="",F4=""),0,NETWORKDAYS(E4,F4,Ref!$K$2:$K$42)) -> 66 | AO4: =IF(L4="Renewal",1,0) -> 0 | AP4: =AC4*AD4 -> 1 | AQ4: =IF(AND(G4<>"",'Historical Score'!$C$6<>""),IF(G4='Historical Score'!$C$6,1,0),0) -> 0 | AR4: =IF(AND(L4<>"",'Historical Score'!$C$5<>""),IF(L4='Historical Score'!$C$5,1,0),0) -> 1 | AS4: =IF(AND(Y4<>"",'Historical Score'!$C$7<>""),IF(Y4='Historical Score'!$C$7,1,0),0) -> 0 | AT4: =IF(AND(K4<>"",'Historical Score'!$C$8<>""),IF(K4='Historical Score'!$C$8,1,0),0) -> 1 | AU4: =IF(AND(J4<>"",'Historical Score'!$C$9<>""),IF(J4='Historical Score'!$C$9,1,0),0) -> 1 | AV4: =AR4*AS4*AQ4 -> 0 | AW4: =AR4*AT4*AQ4 -> 0 | AX4: =AR4*AS4 -> 0 | AY4: =AR4*AT4 -> 1 | AZ4: =AR4*AQ4 -> 0 | BA4: =AR4 -> 1 | BB4: =1 -> 1 | BC4: =IF(AV4=1,1,IF(AW4=1,2,IF(AX4=1,3,IF(AY4=1,4,IF(AZ4=1,5,IF(BA4=1,6,7)))))) -> 4 | BD4: =IF(AD4=1,CHOOSE('Historical Score'!$C$29,AV4,AW4,AX4,AY4,AZ4,BA4,BB4),0) -> 1 | BE4: =IF(BD4=1,COUNTIF($BD$2:BD4,1),"") -> 2
A5: A-004 | B5: Baymont Auto Body | C5: Baymont Auto Body LLC | D5: In House Collection | E5: 45768 | F5: 45889 | G5: 3 | H5: 7538 | I5: 75 | J5: TX | K5: Westwood | L5: New Deal | M5: 1.5 | N5: 40000 | O5: 4000 | P5: 60000 | Q5: 20000 | R5: 40000 | S5: 0.33333333 | T5: 24 | U5: 7 | V5: 80000 | W5: 0.11 | X5: 41182 | Y5: =IF(I5="","No SIC",IFERROR(VLOOKUP(I5,Ref!$A$2:$B$65,2,FALSE()),"Unclassified")) -> Auto Repair & Services | Z5: =IF(T5="","",IF(T5<12,"Daily","Weekly")) -> Weekly | AA5: =IF(T5="",0,IF(T5<12,T5*Controls!$B$29,T5*5)) -> 120 | AB5: =IF(E5="",0,NETWORKDAYS(E5,Controls!$B$36,Ref!$K$2:$K$42)) -> 339 | AC5: =IF(AND(AA5>0,AB5>=Controls!$B$39*AA5),1,0) -> 1 | AD5: =IF(AND(E5<>"",E5>=Controls!$B$37,E5<=Controls!$B$38),1,0) -> 1 | AE5: =IF(IFERROR(VLOOKUP(D5,Controls!$A$59:$E$69,2,FALSE()),"No")="Yes",1,0) -> 1 | AF5: =IF(IFERROR(VLOOKUP(D5,Controls!$A$59:$E$69,3,FALSE()),"No")="Yes",1,0) -> 0 | AG5: =IF(IFERROR(VLOOKUP(D5,Controls!$A$59:$E$69,4,FALSE()),"No")="Yes",1,0) -> 0 | AH5: =IF(IFERROR(VLOOKUP(D5,Controls!$A$59:$E$69,5,FALSE()),"No")="Yes",1,0) -> 0 | AI5: =IF(ISNUMBER(MATCH(D5,Controls!$A$59:$A$69,0)),1,0) -> 1 | AJ5: =Q5-N5 -> -20000 | AK5: =IF(AE5=1,MAX(0,N5-Q5),0) -> 20000 | AL5: =IF(OR(V5="",V5=0),0,N5/V5) -> 0.5 | AM5: =IF(OR(V5="",V5=0),0,1) -> 1 | AN5: =IF(OR(E5="",F5=""),0,NETWORKDAYS(E5,F5,Ref!$K$2:$K$42)) -> 85 | AO5: =IF(L5="Renewal",1,0) -> 0 | AP5: =AC5*AD5 -> 1 | AQ5: =IF(AND(G5<>"",'Historical Score'!$C$6<>""),IF(G5='Historical Score'!$C$6,1,0),0) -> 0 | AR5: =IF(AND(L5<>"",'Historical Score'!$C$5<>""),IF(L5='Historical Score'!$C$5,1,0),0) -> 1 | AS5: =IF(AND(Y5<>"",'Historical Score'!$C$7<>""),IF(Y5='Historical Score'!$C$7,1,0),0) -> 0 | AT5: =IF(AND(K5<>"",'Historical Score'!$C$8<>""),IF(K5='Historical Score'!$C$8,1,0),0) -> 0 | AU5: =IF(AND(J5<>"",'Historical Score'!$C$9<>""),IF(J5='Historical Score'!$C$9,1,0),0) -> 0 | AV5: =AR5*AS5*AQ5 -> 0 | AW5: =AR5*AT5*AQ5 -> 0 | AX5: =AR5*AS5 -> 0 | AY5: =AR5*AT5 -> 0 | AZ5: =AR5*AQ5 -> 0 | BA5: =AR5 -> 1 | BB5: =1 -> 1 | BC5: =IF(AV5=1,1,IF(AW5=1,2,IF(AX5=1,3,IF(AY5=1,4,IF(AZ5=1,5,IF(BA5=1,6,7)))))) -> 6 | BD5: =IF(AD5=1,CHOOSE('Historical Score'!$C$29,AV5,AW5,AX5,AY5,AZ5,BA5,BB5),0) -> 1 | BE5: =IF(BD5=1,COUNTIF($BD$2:BD5,1),"") -> 3
A6: A-005 | B6: Sunset Nails | C6: Sunset Nails Corp | D6: Written-Off | E6: 45789 | F6: 45973 | G6: 2 | H6: 7231 | I6: 72 | J6: NJ | K6: Fundwell | L6: Renewal | M6: 1.5 | N6: 10000 | O6: 1000 | P6: 15000 | Q6: 9500 | R6: 5500 | S6: 0.63333333 | T6: 4 | U6: 2 | V6: 20000 | W6: 0.14 | X6: 43774 | Y6: =IF(I6="","No SIC",IFERROR(VLOOKUP(I6,Ref!$A$2:$B$65,2,FALSE()),"Unclassified")) -> Personal Services | Z6: =IF(T6="","",IF(T6<12,"Daily","Weekly")) -> Daily | AA6: =IF(T6="",0,IF(T6<12,T6*Controls!$B$29,T6*5)) -> 86.62 | AB6: =IF(E6="",0,NETWORKDAYS(E6,Controls!$B$36,Ref!$K$2:$K$42)) -> 324 | AC6: =IF(AND(AA6>0,AB6>=Controls!$B$39*AA6),1,0) -> 1 | AD6: =IF(AND(E6<>"",E6>=Controls!$B$37,E6<=Controls!$B$38),1,0) -> 1 | AE6: =IF(IFERROR(VLOOKUP(D6,Controls!$A$59:$E$69,2,FALSE()),"No")="Yes",1,0) -> 1 | AF6: =IF(IFERROR(VLOOKUP(D6,Controls!$A$59:$E$69,3,FALSE()),"No")="Yes",1,0) -> 1 | AG6: =IF(IFERROR(VLOOKUP(D6,Controls!$A$59:$E$69,4,FALSE()),"No")="Yes",1,0) -> 0 | AH6: =IF(IFERROR(VLOOKUP(D6,Controls!$A$59:$E$69,5,FALSE()),"No")="Yes",1,0) -> 0 | AI6: =IF(ISNUMBER(MATCH(D6,Controls!$A$59:$A$69,0)),1,0) -> 1 | AJ6: =Q6-N6 -> -500 | AK6: =IF(AE6=1,MAX(0,N6-Q6),0) -> 500 | AL6: =IF(OR(V6="",V6=0),0,N6/V6) -> 0.5 | AM6: =IF(OR(V6="",V6=0),0,1) -> 1 | AN6: =IF(OR(E6="",F6=""),0,NETWORKDAYS(E6,F6,Ref!$K$2:$K$42)) -> 127 | AO6: =IF(L6="Renewal",1,0) -> 1 | AP6: =AC6*AD6 -> 1 | AQ6: =IF(AND(G6<>"",'Historical Score'!$C$6<>""),IF(G6='Historical Score'!$C$6,1,0),0) -> 0 | AR6: =IF(AND(L6<>"",'Historical Score'!$C$5<>""),IF(L6='Historical Score'!$C$5,1,0),0) -> 0 | AS6: =IF(AND(Y6<>"",'Historical Score'!$C$7<>""),IF(Y6='Historical Score'!$C$7,1,0),0) -> 0 | AT6: =IF(AND(K6<>"",'Historical Score'!$C$8<>""),IF(K6='Historical Score'!$C$8,1,0),0) -> 1 | AU6: =IF(AND(J6<>"",'Historical Score'!$C$9<>""),IF(J6='Historical Score'!$C$9,1,0),0) -> 1 | AV6: =AR6*AS6*AQ6 -> 0 | AW6: =AR6*AT6*AQ6 -> 0 | AX6: =AR6*AS6 -> 0 | AY6: =AR6*AT6 -> 0 | AZ6: =AR6*AQ6 -> 0 | BA6: =AR6 -> 0 | BB6: =1 -> 1 | BC6: =IF(AV6=1,1,IF(AW6=1,2,IF(AX6=1,3,IF(AY6=1,4,IF(AZ6=1,5,IF(BA6=1,6,7)))))) -> 7 | BD6: =IF(AD6=1,CHOOSE('Historical Score'!$C$29,AV6,AW6,AX6,AY6,AZ6,BA6,BB6),0) -> 0 | BE6: =IF(BD6=1,COUNTIF($BD$2:BD6,1),"")
A7: A-006 | B7: Orchard Supply | C7: Orchard Supply Co LLC | D7: Bankruptcy | E7: 45826 | F7: 45918 | G7: 4 | J7: TX | K7: Westwood | L7: New Deal | M7: 1.5 | N7: 20000 | O7: 2000 | P7: 30000 | Q7: 0 | R7: 30000 | S7: 0 | T7: 16 | U7: 9 | V7: 100000 | W7: 0.1 | X7: 44305 | Y7: =IF(I7="","No SIC",IFERROR(VLOOKUP(I7,Ref!$A$2:$B$65,2,FALSE()),"Unclassified")) -> No SIC | Z7: =IF(T7="","",IF(T7<12,"Daily","Weekly")) -> Weekly | AA7: =IF(T7="",0,IF(T7<12,T7*Controls!$B$29,T7*5)) -> 80 | AB7: =IF(E7="",0,NETWORKDAYS(E7,Controls!$B$36,Ref!$K$2:$K$42)) -> 298 | AC7: =IF(AND(AA7>0,AB7>=Controls!$B$39*AA7),1,0) -> 1 | AD7: =IF(AND(E7<>"",E7>=Controls!$B$37,E7<=Controls!$B$38),1,0) -> 1 | AE7: =IF(IFERROR(VLOOKUP(D7,Controls!$A$59:$E$69,2,FALSE()),"No")="Yes",1,0) -> 1 | AF7: =IF(IFERROR(VLOOKUP(D7,Controls!$A$59:$E$69,3,FALSE()),"No")="Yes",1,0) -> 1 | AG7: =IF(IFERROR(VLOOKUP(D7,Controls!$A$59:$E$69,4,FALSE()),"No")="Yes",1,0) -> 0 | AH7: =IF(IFERROR(VLOOKUP(D7,Controls!$A$59:$E$69,5,FALSE()),"No")="Yes",1,0) -> 0 | AI7: =IF(ISNUMBER(MATCH(D7,Controls!$A$59:$A$69,0)),1,0) -> 1 | AJ7: =Q7-N7 -> -20000 | AK7: =IF(AE7=1,MAX(0,N7-Q7),0) -> 20000 | AL7: =IF(OR(V7="",V7=0),0,N7/V7) -> 0.2 | AM7: =IF(OR(V7="",V7=0),0,1) -> 1 | AN7: =IF(OR(E7="",F7=""),0,NETWORKDAYS(E7,F7,Ref!$K$2:$K$42)) -> 64 | AO7: =IF(L7="Renewal",1,0) -> 0 | AP7: =AC7*AD7 -> 1 | AQ7: =IF(AND(G7<>"",'Historical Score'!$C$6<>""),IF(G7='Historical Score'!$C$6,1,0),0) -> 0 | AR7: =IF(AND(L7<>"",'Historical Score'!$C$5<>""),IF(L7='Historical Score'!$C$5,1,0),0) -> 1 | AS7: =IF(AND(Y7<>"",'Historical Score'!$C$7<>""),IF(Y7='Historical Score'!$C$7,1,0),0) -> 0 | AT7: =IF(AND(K7<>"",'Historical Score'!$C$8<>""),IF(K7='Historical Score'!$C$8,1,0),0) -> 0 | AU7: =IF(AND(J7<>"",'Historical Score'!$C$9<>""),IF(J7='Historical Score'!$C$9,1,0),0) -> 0 | AV7: =AR7*AS7*AQ7 -> 0 | AW7: =AR7*AT7*AQ7 -> 0 | AX7: =AR7*AS7 -> 0 | AY7: =AR7*AT7 -> 0 | AZ7: =AR7*AQ7 -> 0 | BA7: =AR7 -> 1 | BB7: =1 -> 1 | BC7: =IF(AV7=1,1,IF(AW7=1,2,IF(AX7=1,3,IF(AY7=1,4,IF(AZ7=1,5,IF(BA7=1,6,7)))))) -> 6 | BD7: =IF(AD7=1,CHOOSE('Historical Score'!$C$29,AV7,AW7,AX7,AY7,AZ7,BA7,BB7),0) -> 1 | BE7: =IF(BD7=1,COUNTIF($BD$2:BD7,1),"") -> 4
A8: A-007 | B8: Pinewood Dental | C8: Pinewood Dental PC | D8: Open | E8: 46030 | F8: 46237 | G8: 1 | H8: 8021 | I8: 80 | J8: NJ | K8: Fundwell | L8: New Deal | M8: 1.5 | N8: 50000 | O8: 5000 | P8: 75000 | Q8: 30000 | R8: 45000 | S8: 0.4 | T8: 6 | U8: 0 | V8: 250000 | W8: 0.08 | X8: 40211 | Y8: =IF(I8="","No SIC",IFERROR(VLOOKUP(I8,Ref!$A$2:$B$65,2,FALSE()),"Unclassified")) -> Health Services | Z8: =IF(T8="","",IF(T8<12,"Daily","Weekly")) -> Daily | AA8: =IF(T8="",0,IF(T8<12,T8*Controls!$B$29,T8*5)) -> 129.93 | AB8: =IF(E8="",0,NETWORKDAYS(E8,Controls!$B$36,Ref!$K$2:$K$42)) -> 160 | AC8: =IF(AND(AA8>0,AB8>=Controls!$B$39*AA8),1,0) -> 0 | AD8: =IF(AND(E8<>"",E8>=Controls!$B$37,E8<=Controls!$B$38),1,0) -> 1 | AE8: =IF(IFERROR(VLOOKUP(D8,Controls!$A$59:$E$69,2,FALSE()),"No")="Yes",1,0) -> 0 | AF8: =IF(IFERROR(VLOOKUP(D8,Controls!$A$59:$E$69,3,FALSE()),"No")="Yes",1,0) -> 0 | AG8: =IF(IFERROR(VLOOKUP(D8,Controls!$A$59:$E$69,4,FALSE()),"No")="Yes",1,0) -> 0 | AH8: =IF(IFERROR(VLOOKUP(D8,Controls!$A$59:$E$69,5,FALSE()),"No")="Yes",1,0) -> 1 | AI8: =IF(ISNUMBER(MATCH(D8,Controls!$A$59:$A$69,0)),1,0) -> 1 | AJ8: =Q8-N8 -> -20000 | AK8: =IF(AE8=1,MAX(0,N8-Q8),0) -> 0 | AL8: =IF(OR(V8="",V8=0),0,N8/V8) -> 0.2 | AM8: =IF(OR(V8="",V8=0),0,1) -> 1 | AN8: =IF(OR(E8="",F8=""),0,NETWORKDAYS(E8,F8,Ref!$K$2:$K$42)) -> 144 | AO8: =IF(L8="Renewal",1,0) -> 0 | AP8: =AC8*AD8 -> 0 | AQ8: =IF(AND(G8<>"",'Historical Score'!$C$6<>""),IF(G8='Historical Score'!$C$6,1,0),0) -> 1 | AR8: =IF(AND(L8<>"",'Historical Score'!$C$5<>""),IF(L8='Historical Score'!$C$5,1,0),0) -> 1 | AS8: =IF(AND(Y8<>"",'Historical Score'!$C$7<>""),IF(Y8='Historical Score'!$C$7,1,0),0) -> 0 | AT8: =IF(AND(K8<>"",'Historical Score'!$C$8<>""),IF(K8='Historical Score'!$C$8,1,0),0) -> 1 | AU8: =IF(AND(J8<>"",'Historical Score'!$C$9<>""),IF(J8='Historical Score'!$C$9,1,0),0) -> 1 | AV8: =AR8*AS8*AQ8 -> 0 | AW8: =AR8*AT8*AQ8 -> 1 | AX8: =AR8*AS8 -> 0 | AY8: =AR8*AT8 -> 1 | AZ8: =AR8*AQ8 -> 1 | BA8: =AR8 -> 1 | BB8: =1 -> 1 | BC8: =IF(AV8=1,1,IF(AW8=1,2,IF(AX8=1,3,IF(AY8=1,4,IF(AZ8=1,5,IF(BA8=1,6,7)))))) -> 2 | BD8: =IF(AD8=1,CHOOSE('Historical Score'!$C$29,AV8,AW8,AX8,AY8,AZ8,BA8,BB8),0) -> 1 | BE8: =IF(BD8=1,COUNTIF($BD$2:BD8,1),"") -> 5
A9: A-008 | B9: Harbor Cleaning | C9: Harbor Cleaning Services LLC | D9: Closed/NSF Unpaid | E9: 45852 | F9: 46006 | G9: 3 | H9: 7349 | I9: 73 | J9: TX | K9: Westwood | L9: New Deal | M9: 1.5 | N9: 20000 | O9: 2000 | P9: 30000 | Q9: 30000 | R9: 0 | S9: 1 | T9: 20 | U9: 11 | W9: 0.13 | X9: 44781 | Y9: =IF(I9="","No SIC",IFERROR(VLOOKUP(I9,Ref!$A$2:$B$65,2,FALSE()),"Unclassified")) -> Business Services | Z9: =IF(T9="","",IF(T9<12,"Daily","Weekly")) -> Weekly | AA9: =IF(T9="",0,IF(T9<12,T9*Controls!$B$29,T9*5)) -> 100 | AB9: =IF(E9="",0,NETWORKDAYS(E9,Controls!$B$36,Ref!$K$2:$K$42)) -> 282 | AC9: =IF(AND(AA9>0,AB9>=Controls!$B$39*AA9),1,0) -> 1 | AD9: =IF(AND(E9<>"",E9>=Controls!$B$37,E9<=Controls!$B$38),1,0) -> 1 | AE9: =IF(IFERROR(VLOOKUP(D9,Controls!$A$59:$E$69,2,FALSE()),"No")="Yes",1,0) -> 0 | AF9: =IF(IFERROR(VLOOKUP(D9,Controls!$A$59:$E$69,3,FALSE()),"No")="Yes",1,0) -> 1 | AG9: =IF(IFERROR(VLOOKUP(D9,Controls!$A$59:$E$69,4,FALSE()),"No")="Yes",1,0) -> 1 | AH9: =IF(IFERROR(VLOOKUP(D9,Controls!$A$59:$E$69,5,FALSE()),"No")="Yes",1,0) -> 0 | AI9: =IF(ISNUMBER(MATCH(D9,Controls!$A$59:$A$69,0)),1,0) -> 1 | AJ9: =Q9-N9 -> 10000 | AK9: =IF(AE9=1,MAX(0,N9-Q9),0) -> 0 | AL9: =IF(OR(V9="",V9=0),0,N9/V9) -> 0 | AM9: =IF(OR(V9="",V9=0),0,1) -> 0 | AN9: =IF(OR(E9="",F9=""),0,NETWORKDAYS(E9,F9,Ref!$K$2:$K$42)) -> 107 | AO9: =IF(L9="Renewal",1,0) -> 0 | AP9: =AC9*AD9 -> 1 | AQ9: =IF(AND(G9<>"",'Historical Score'!$C$6<>""),IF(G9='Historical Score'!$C$6,1,0),0) -> 0 | AR9: =IF(AND(L9<>"",'Historical Score'!$C$5<>""),IF(L9='Historical Score'!$C$5,1,0),0) -> 1 | AS9: =IF(AND(Y9<>"",'Historical Score'!$C$7<>""),IF(Y9='Historical Score'!$C$7,1,0),0) -> 0 | AT9: =IF(AND(K9<>"",'Historical Score'!$C$8<>""),IF(K9='Historical Score'!$C$8,1,0),0) -> 0 | AU9: =IF(AND(J9<>"",'Historical Score'!$C$9<>""),IF(J9='Historical Score'!$C$9,1,0),0) -> 0 | AV9: =AR9*AS9*AQ9 -> 0 | AW9: =AR9*AT9*AQ9 -> 0 | AX9: =AR9*AS9 -> 0 | AY9: =AR9*AT9 -> 0 | AZ9: =AR9*AQ9 -> 0 | BA9: =AR9 -> 1 | BB9: =1 -> 1 | BC9: =IF(AV9=1,1,IF(AW9=1,2,IF(AX9=1,3,IF(AY9=1,4,IF(AZ9=1,5,IF(BA9=1,6,7)))))) -> 6 | BD9: =IF(AD9=1,CHOOSE('Historical Score'!$C$29,AV9,AW9,AX9,AY9,AZ9,BA9,BB9),0) -> 1 | BE9: =IF(BD9=1,COUNTIF($BD$2:BD9,1),"") -> 6

Sheet Controls
A1: CONTROLS - every editable threshold, tier, historical weight and rule
A2: Blue = editable. Do not insert or delete rows; formulas reference fixed cells.
A3: 1. CASH-FLOW THRESHOLDS
A4: Metric | B4: Green (at or better) | C4: Red (at or worse) | D4: Knockout | E4: Direction | I4: Note
A5: Total LVG (all debt / rev) | B5: 0.3 | C5: 0.45 | D5: 0.55 | E5: higher is worse
A6: New holdback SP% | B6: 0.18 | C6: 0.25 | D6: 0.35 | E6: higher is worse
A7: Daily debt / balance | B7: 0.18 | C7: 0.3 | D7: 0.35 | E7: higher is worse
A8: Fund / revenue | B8: 0.6 | C8: 0.9 | D8: 1.25 | E8: higher is worse
A9: # positions (incl. new) | B9: 2 | C9: 5 | D9: 6 | E9: higher is worse
A10: Revenue trend (avg MoM) | B10: -0.05 | C10: -0.15 | D10: -0.3 | E10: lower is worse
A11: Neg days + NSFs (total) | B11: 1 | C11: 6 | D11: 10 | E11: higher is worse | I11: total across all months entered
A12: Credit score (FICO) | B12: 650 | C12: 630 | D12: 0 | E12: lower is worse | I12: 650+ green, 630-649 yellow, below 630 red; knockout 0 = off
A13: Decline if red flags (RED + KNOCKOUT) >= | B13: 2
A14: Minimum fund $ | B14: 10000
A15: Underwriting fee % | B15: 0.05
A17: 2. PRICING BANDS
A18: Score >= | B18: Term cap (daily pmts) | C18: Factor | I18: Note
A19: 0 | B19: 100 | C19: 1.49
A20: 5 | B20: 130 | C20: 1.45
A21: 6 | B21: 150 | C21: 1.45
A22: 7 | B22: 195 | C22: 1.4
A23: Max term (months) | B23: 9
A24: Approved factor tiers (low -> high) | B24: 1.4 | C24: 1.45 | D24: 1.49
A25: Tier cut-offs on 7-point scale: Strong / Solid / Moderate | B25: 6.5 | C25: 5 | D25: 3.5
A27: 3. CONVERSION CONSTANTS
A28: Weeks per month (ours) | B28: 4.331
A29: Business days per month (ours) | B29: 21.655
A30: MoneyBadger weeks per month | B30: 4
A31: MoneyBadger business days per month | B31: 21
A32: Calendar days per month | B32: 30.4375
A33: Assumed factor on existing positions | B33: 1.45
A35: 4. HISTORICAL EVIDENCE SETTINGS
A36: As-of date for seasoning (date of the CRM export) | B36: 46259
A37: Window: funded on or after | B37: 45597
A38: Window: funded on or before | B38: 46259 | I38: 12/31/2025 = settled book
A39: Seasoning multiple (age >= multiple x contracted term) | B39: 1.25
A40: Minimum seasoned deals for a cohort to be PRIMARY | B40: 3 | I40: RECOMMENDED for the full book: 10
A41: Minimum seasoned funded $ for a cohort to be PRIMARY | B41: 30000 | I41: RECOMMENDED for the full book: $150,000
A42: Credibility constant K (seasoned deals for half weight) | B42: 30 | I42: Z = n / (n + K); small cohorts are pulled toward the book
A43: Minimum seasoned deals before a rate is shown | B43: 2 | I43: RECOMMENDED for the full book: 5
A44: Seasoned deals for the sample-size indicator to be GREEN | B44: 5 | I44: RECOMMENDED for the full book: 30
A47: 5. HISTORICAL MODIFIER TABLE index = blended cohort lost rate / seasoned-book lost rate (1.00 = book)
A48: Index at or below | B48: Level | C48: Sizing flex (0 = green line, 1 = red line) | D48: Fund multiplier | E48: Term step (bands) | F48: Factor step (tiers) | G48: Frequency | H48: Manual review? | I48: Note
A49: 0.6 | B49: Strong positive | C49: 0.9 | D49: 1 | E49: 0 | F49: 0 | G49: As proposed | H49: N | I49: RECOMMENDED: size 90% of the way to the red line - metrics may go yellow, never red
A50: 0.85 | B50: Mild positive | C50: 0.45 | D50: 1 | E50: 0 | F50: 0 | G50: As proposed | H50: N | I50: half-way to the red line
A51: 1.15 | B51: Neutral | C51: 0 | D51: 1 | E51: 0 | F51: 0 | G51: As proposed | H51: N | I51: equals the cash-flow tool exactly as built
A52: 1.4 | B52: Mild negative | C52: 0 | D52: 0.85 | E52: -1 | F52: 1 | G52: As proposed | H52: N
A53: 1.75 | B53: Negative | C53: 0 | D53: 0.7 | E53: -1 | F53: 1 | G53: Weekly | H53: N
A54: 999 | B54: Severe | C54: 0 | D54: 0.55 | E54: -2 | F54: 1 | G54: Weekly | H54: Y | I54: sent to manual review
A55: The C2 block on the Deal sheet uses A50 (0.85) and A51 (1.15) as its GREEN / RED lines for every house-book indicator. Modifier = Neutral whenever no cohort meets the minimums.
A57: 6. STATUS MAPPING
A58: Status | B58: Default? | C58: Resolved? | D58: Closed? | E58: Open? | F58: Deals in file
A59: Closed | B59: No | C59: Yes | D59: Yes | E59: No | F59: =COUNTIF('Historical Data'!$D$2:$D$9,A59) -> 2
A60: Open | B60: No | C60: No | D60: No | E60: Yes | F60: =COUNTIF('Historical Data'!$D$2:$D$9,A60) -> 1
A61: Legal | B61: Yes | C61: No | D61: No | E61: No | F61: =COUNTIF('Historical Data'!$D$2:$D$9,A61) -> 1
A62: In House Collection | B62: Yes | C62: No | D62: No | E62: No | F62: =COUNTIF('Historical Data'!$D$2:$D$9,A62) -> 1
A63: Lowered Payments | B63: No | C63: No | D63: No | E63: No | F63: =COUNTIF('Historical Data'!$D$2:$D$9,A63) -> 0
A64: Written-Off | B64: Yes | C64: Yes | D64: No | E64: No | F64: =COUNTIF('Historical Data'!$D$2:$D$9,A64) -> 1
A65: Bankruptcy | B65: Yes | C65: Yes | D65: No | E65: No | F65: =COUNTIF('Historical Data'!$D$2:$D$9,A65) -> 1
A66: Settlement Agreement | B66: Yes | C66: Yes | D66: No | E66: No | F66: =COUNTIF('Historical Data'!$D$2:$D$9,A66) -> 0
A67: Closed/NSF | B67: No | C67: Yes | D67: Yes | E67: No | F67: =COUNTIF('Historical Data'!$D$2:$D$9,A67) -> 0
A68: Closed/NSF Unpaid | B68: No | C68: Yes | D68: Yes | E68: No | F68: =COUNTIF('Historical Data'!$D$2:$D$9,A68) -> 1
A69: At-Risk | B69: Yes | C69: No | D69: No | E69: No | F69: =COUNTIF('Historical Data'!$D$2:$D$9,A69) -> 0
A72: 7. MANUAL-REVIEW TRIGGERS (Y = active)
A73: Trigger | B73: Active? | C73: Parameter | I73: Note
A74: Historical modifier is Severe | B74: Y
A75: Credit score RED AND another metric RED | B75: Y
A76: Positions incl. new at or above | B76: Y | C76: 4 | I76: fund up to a 4th
A77: New deal, position at/above parameter, construction industry | B77: Y | C77: 3
A78: ISO or industry has no deals in the house book | B78: Y
A79: Final fund below minimum fund $ | B79: Y
A80: No cohort met the minimums (book baseline in use) | B80: N | I80: off by default

Sheet Checks
B1: CHECKS / AUDIT
B2: =COUNTIF(C4:C43,"FAIL")&" FAIL | "&COUNTIF(C4:C43,"WARN")&" WARN | "&COUNTIF(C4:C43,"OK")&" OK" -> 0 FAIL | 5 WARN | 27 OK
B3: Check | C3: Result | D3: Detail
B4: MISSING INPUTS
B5: Bank data entered | C5: =IF(Deal!$C$24=0,"WARN","OK") -> OK | D5: ="months entered: "&COUNT(Deal!$C$12:$C$23) -> months entered: 4
B6: Average daily balance entered | C6: =IF(Deal!$D$24=0,"WARN","OK") -> OK
B7: New deal or renewal entered | C7: =IF(Deal!$K$15="","WARN","OK") -> OK | D7: ="required for any cohort tighter than the book" -> required for any cohort tighter than the book
B8: ISO entered and found in the house book | C8: =IF(Deal!$K$12="","WARN",IF(COUNTIF('Historical Data'!$K$2:$K$9,Deal!$K$12)=0,"WARN","OK")) -> OK
B9: Industry entered and found in the house book | C9: =IF(Deal!$K$13="","WARN",IF(COUNTIF('Historical Data'!$Y$2:$Y$9,Deal!$K$13)=0,"WARN","OK")) -> OK
B10: Credit score entered | C10: =IF(Deal!$K$16="","WARN","OK") -> OK | D10: ="blank = not scored" -> blank = not scored
B11: Requested factor is an approved tier | C11: =IF(Deal!$C$6="","OK",IF(ISNUMBER(MATCH(Deal!$C$6,Controls!$B$24:$D$24,0)),"OK","WARN")) -> OK
B12: FORMULA ERRORS
B13: Deal sheet | C13: =IF(SUMPRODUCT(--ISERROR(Deal!$B$1:$M$92))=0,"OK","FAIL") -> OK | D13: =SUMPRODUCT(--ISERROR(Deal!$B$1:$M$92))&" error cells" -> 0 error cells
B14: Historical Data | C14: =IF(SUMPRODUCT(--ISERROR('Historical Data'!$Y$2:$Y$9))+SUMPRODUCT(--ISERROR('Historical Data'!$AA$2:$AA$9))+SUMPRODUCT(--ISERROR('Historical Data'!$BC$2:$BC$9))+SUMPRODUCT(--ISERROR('Historical Data'!$BE$2:$BE$9))=0,"OK","FAIL") -> OK
B15: Historical Score | C15: =IF(SUMPRODUCT(--ISERROR('Historical Score'!$A$1:$AA$56))=0,"OK","FAIL") -> OK
B16: Offer Engine / Decision Summary | C16: =IF(SUMPRODUCT(--ISERROR('Offer Engine'!$B$1:$G$41))+SUMPRODUCT(--ISERROR('Decision Summary'!$B$1:$D$33))=0,"OK","FAIL") -> OK
B17: SAFETY
B18: Final fund <= sized max fund | C18: ='Offer Engine'!$E$36 -> OK
B19: Final daily <= sized max daily | C19: ='Offer Engine'!$E$37 -> OK
B20: No offer-side metric red/knockout at the final offer | C20: ='Offer Engine'!$E$38 -> OK
B21: Merchant knockouts untouched | C21: ='Offer Engine'!$E$39 -> OK
B22: Sizing flex below 100% | C22: ='Offer Engine'!$E$40 -> OK
B23: COHORT QUALITY
B24: Primary cohort met the minimums | C24: =IF('Historical Score'!$C$29=7,"WARN","OK") -> OK | D24: =IF('Historical Score'!$C$29=7,"book baseline - modifier Neutral",'Historical Score'!$C$30) -> T6: new/renewal only
B25: Seasoned deals behind the primary cohort | C25: =Deal!$F$57 -> GREEN | D25: =Deal!$C$57&" seasoned deals" -> 5 seasoned deals
B26: Conflicting ISO vs industry signals | C26: =IF('Historical Score'!$C$55="No","OK","WARN") -> OK | D26: ='Historical Score'!$C$55 -> No
B27: Tighter cohorts skipped for being too small | C27: =IF('Historical Score'!$C$29=1,"OK","WARN") -> WARN | D27: ='Historical Score'!$C$56 -> Tighter tiers 1-5 too small;
B28: DATA QUALITY (house book)
B29: Deals loaded | C29: ="OK" -> OK | D29: =COUNTA('Historical Data'!$A$2:$A$9)&" deals" -> 8 deals
B30: Statuses not in the Controls mapping | C30: =IF(SUMPRODUCT(1-'Historical Data'!$AI$2:$AI$9)=0,"OK","FAIL") -> OK | D30: =SUMPRODUCT(1-'Historical Data'!$AI$2:$AI$9)&" deals" -> 0 deals
B31: Deals with no revenue figure | C31: =IF(SUMPRODUCT(1-'Historical Data'!$AM$2:$AM$9)>0,"WARN","OK") -> WARN | D31: =SUMPRODUCT(1-'Historical Data'!$AM$2:$AM$9)&" deals - excluded from adv/rev averages" -> 1 deals - excluded from adv/rev averages
B32: Never-paid deals (collected <= 0) | C32: ="WARN" -> WARN | D32: =COUNTIF('Historical Data'!$Q$2:$Q$9,"<=0")&" deals" -> 1 deals
B33: Open status but 99.9%+ paid | C33: =IF(SUMPRODUCT('Historical Data'!$AH$2:$AH$9*('Historical Data'!$S$2:$S$9>=0.999))=0,"OK","WARN") -> OK | D33: =SUMPRODUCT('Historical Data'!$AH$2:$AH$9*('Historical Data'!$S$2:$S$9>=0.999))&" deals" -> 0 deals
B34: Open deals older than 1.5x contracted term | C34: ="WARN" -> WARN | D34: =SUMPRODUCT('Historical Data'!$AH$2:$AH$9*('Historical Data'!$AB$2:$AB$9>1.5*'Historical Data'!$AA$2:$AA$9))&" deals" -> 0 deals
B35: Weekly term above 39 weeks (9-month box) | C35: ="WARN" -> WARN | D35: =SUMPRODUCT(('Historical Data'!$T$2:$T$9>=12)*('Historical Data'!$T$2:$T$9>39))&" deals" -> 0 deals
B36: Payback = advance x factor on every deal | C36: =IF(SUMPRODUCT(--(ABS('Historical Data'!$P$2:$P$9-'Historical Data'!$N$2:$N$9*'Historical Data'!$M$2:$M$9)>1))=0,"OK","WARN") -> OK | D36: =SUMPRODUCT(--(ABS('Historical Data'!$P$2:$P$9-'Historical Data'!$N$2:$N$9*'Historical Data'!$M$2:$M$9)>1))&" mismatches" -> 0 mismatches
B37: RECONCILIATION
B38: Total funded | C38: ="OK" -> OK | D38: =TEXT(SUM('Historical Data'!$N$2:$N$9),"$#,##0")&" (full book: $34,481,626)" -> $200,000 (full book: $34,481,626)
B39: Total collected | C39: ="OK" -> OK | D39: =TEXT(SUM('Historical Data'!$Q$2:$Q$9),"$#,##0")&" (full book: $27,438,510)" -> $143,500 (full book: $27,438,510)
B40: Principal lost | C40: ="OK" -> OK | D40: =TEXT(SUMPRODUCT('Historical Data'!$AK$2:$AK$9),"$#,##0")&" (full book: $5,270,163)" -> $61,500 (full book: $5,270,163)
B41: Tier-7 seasoned funded = in-window seasoned funded | C41: =IF(ABS('Historical Score'!$G$20-SUMPRODUCT('Historical Data'!$AP$2:$AP$9*'Historical Data'!$N$2:$N$9))<1,"OK","FAIL") -> OK
B42: Comparable list count = primary cohort matches | C42: =IF(MIN(400,INDEX('Historical Score'!$D$14:$D$20,'Historical Score'!$C$29))=SUMPRODUCT(--('Comparable Deals'!$B$5:$B$404<>"")),"OK","FAIL") -> OK | D42: =SUMPRODUCT(--('Comparable Deals'!$B$5:$B$404<>""))&" listed" -> 6 listed

Sheet Ref
A1: SIC2 | B1: Industry (SIC major group) | C1: Division | E1: ISO (house-book spelling) | G1: Industry list | I1: State | K1: Fed holiday | M1: Status list
A2: 01 | B2: Agricultural Production - Crops | C2: Agriculture, Forestry & Fishing | E2: Ace Partners | G2: Administration of Economic Programs | I2: AL | K2: 45292 | M2: Closed
A3: 02 | B3: Agricultural Production - Livestock | C3: Agriculture, Forestry & Fishing | E3: Advance Consolidations | G3: Agricultural Production - Crops | I3: AR | K3: 45306 | M3: Open
A4: 07 | B4: Agricultural Services | C4: Agriculture, Forestry & Fishing | E4: ALLSTATE FUND PROS LLC | G4: Agricultural Production - Livestock | I4: AZ | K4: 45341 | M4: Legal
A5: 08 | B5: Forestry | C5: Agriculture, Forestry & Fishing | E5: Alternative Solutions Funding | G5: Agricultural Services | I5: CA | K5: 45439 | M5: In House Collection
A6: 13 | B6: Oil & Gas Extraction | C6: Mining | E6: alvara capital | G6: Air Transportation | I6: CO | K6: 45462 | M6: Lowered Payments
A7: 14 | B7: Nonmetallic Minerals Mining | C7: Mining | E7: American Funding Association 1 | G7: Amusement & Recreation Services | I7: CT | K7: 45477 | M7: Written-Off
A8: 15 | B8: General Building Contractors | C8: Construction | E8: Amerishop Financial services | G8: Apparel & Accessory Stores | I8: DC | K8: 45537 | M8: Bankruptcy
A9: 16 | B9: Heavy Construction | C9: Construction | E9: Aspire Funding | G9: Apparel & Textile Products | I9: DE | K9: 45579 | M9: Settlement Agreement
A10: 17 | B10: Special Trade Contractors | C10: Construction | E10: Atla Finance | G10: Auto Dealers & Gas Stations | I10: FL | K10: 45607 | M10: Closed/NSF
A11: 20 | B11: Food & Kindred Products | C11: Manufacturing | E11: AVON ADVANCE | G11: Auto Repair & Services | I11: GA | K11: 45624 | M11: Closed/NSF Unpaid
A12: 23 | B12: Apparel & Textile Products | C12: Manufacturing | E12: Ballicci | G12: Building Materials & Garden Supply | I12: HI | K12: 45651 | M12: At-Risk
A13: 24 | B13: Lumber & Wood Products | C13: Manufacturing | E13: BFA 3 | G13: Business Services | I13: IA | K13: 45658
A14: 25 | B14: Furniture & Fixtures | C14: Manufacturing | E14: Bingo advance LLC | G14: Chemicals & Allied Products | I14: ID | K14: 45677
A15: 27 | B15: Printing & Publishing | C15: Manufacturing | E15: Birkin Capital Inc | G15: Communications | I15: IL | K15: 45705
A16: 28 | B16: Chemicals & Allied Products | C16: Manufacturing | E16: biz advance now | G16: Eating & Drinking Places | I16: IN | K16: 45803
A17: 30 | B17: Rubber & Plastics | C17: Manufacturing | E17: Biz fuel | G17: Educational Services | I17: KS | K17: 45827
A18: 32 | B18: Stone, Clay, Glass & Concrete | C18: Manufacturing | E18: BizFin LLC | G18: Electric, Gas & Sanitary Services | I18: KY | K18: 45842
A19: 33 | B19: Primary Metal Industries | C19: Manufacturing | E19: black flag funding | G19: Electronic & Electrical Equipment | I19: LA | K19: 45901
A20: 34 | B20: Fabricated Metal Products | C20: Manufacturing | E20: Black Tie Funding | G20: Engineering, Accounting & Management | I20: MA | K20: 45943
A21: 35 | B21: Industrial Machinery & Equipment | C21: Manufacturing | E21: Blue Oak Advance | G21: Environmental Quality & Housing | I21: MD | K21: 45972
A22: 36 | B22: Electronic & Electrical Equipment | C22: Manufacturing | E22: bridge consolidation | G22: Fabricated Metal Products | I22: ME | K22: 45988
A23: 37 | B23: Transportation Equipment | C23: Manufacturing | E23: Broadway Advance LLC | G23: Food & Kindred Products | I23: MI | K23: 46016
A24: 38 | B24: Instruments & Related Products | C24: Manufacturing | E24: Business Fund USA 4 | G24: Food Stores | I24: MN | K24: 46023
... A42: 59 | B42: Miscellaneous Retail | C42: Retail Trade | E42: ecp business capital | G42: Miscellaneous Manufacturing | I42: SC | K42: 46716
A43: 62 | B43: Security & Commodity Brokers | C43: Finance, Insurance & Real Estate | E43: Elite Advance 5 | G43: Miscellaneous Repair Services | I43: SD
A44: 63 | B44: Insurance Carriers | C44: Finance, Insurance & Real Estate | E44: elite finance team | G44: Miscellaneous Retail | I44: TN
A45: 64 | B45: Insurance Agents & Brokers | C45: Finance, Insurance & Real Estate | E45: ELITE FUNDING PARTNERS LLC 6 | G45: Motion Pictures | I45: TX
A46: 65 | B46: Real Estate | C46: Finance, Insurance & Real Estate | E46: EVR GREEN LLC | G46: Museums & Botanical Gardens | I46: UT
A47: 70 | B47: Hotels & Lodging | C47: Services | E47: EZ ADVANCE LLC | G47: National Security & Intl Affairs | I47: VA
A48: 72 | B48: Personal Services | C48: Services | E48: ez alternative solutions | G48: Nonmetallic Minerals Mining | I48: VT
A49: 73 | B49: Business Services | C49: Services | E49: FC ADVANCE | G49: Oil & Gas Extraction | I49: WA
A50: 75 | B50: Auto Repair & Services | C50: Services | E50: Fidelity Funding | G50: Personal Services | I50: WI
A51: 76 | B51: Miscellaneous Repair Services | C51: Services | E51: FIFTH VENTURE | G51: Primary Metal Industries | I51: WV
A52: 78 | B52: Motion Pictures | C52: Services | E52: FIMACAP INC | G52: Printing & Publishing
A53: 79 | B53: Amusement & Recreation Services | C53: Services | E53: Financial Express LLC | G53: Real Estate
A54: 80 | B54: Health Services | C54: Services | E54: Financity | G54: Rubber & Plastics
A55: 81 | B55: Legal Services | C55: Services | E55: FireLine Funding | G55: Security & Commodity Brokers
A56: 82 | B56: Educational Services | C56: Services | E56: First Path Capital | G56: Services - Miscellaneous
A57: 83 | B57: Social Services | C57: Services | E57: Fund Kite | G57: Social Services
A58: 84 | B58: Museums & Botanical Gardens | C58: Services | E58: Fund Max | G58: Special Trade Contractors
A59: 86 | B59: Membership Organizations | C59: Services | E59: Fund Simple | G59: Stone, Clay, Glass & Concrete
A60: 87 | B60: Engineering, Accounting & Management | C60: Services | E60: Fund Your Bizz | G60: Transportation Equipment
A61: 89 | B61: Services - Miscellaneous | C61: Services | E61: FundFlex | G61: Transportation Services
A62: 92 | B62: Justice, Public Order & Safety | C62: Public Administration | E62: Fundible | G62: Trucking & Warehousing
A63: 95 | B63: Environmental Quality & Housing | C63: Public Administration | E63: Fundward | G63: Water Transportation
... A65: 97 | B65: National Security & Intl Affairs | C65: Public Administration | E65: Go Ai Ez LLC Dba:Gova Funding | G65: Wholesale Trade - Nondurable Goods
E66: GREYSTONE | G66: No SIC
E67: GROWTH RATE CAPITAL INC | G67: Unclassified
E68: Hero Advance Group
E69: I burst funding
E70: ICB FUNDING
E71: ICG Funding
E72: J Capital Solutions
E73: JABSCAP
E74: Kelly Kapital
E75: Key Capital Funding
E76: Klendify
E77: langtech
E78: legacy funding llc
E79: Lemonaid
... E157: YM ventures
