Workbook
Name D26D33: #REF!

Sheet README
A3: PURPOSE OF THIS SHEET
A4: The purpose of this sheet is to combine cashflow-analysis with historical data to automatically generate a recommended offer
A6: METHODOLOGY
A7: In-order to easily make future adjustments, all assumptions and parameters are editable in "Controls"
A9: WORK FLOW
A10: Firstly you input deal data(Revenue, Balances, Existing positions, ISO, Industry, etc.)
A11: Then

Sheet Deal
B1: UNDERWRITING TOOL | G1: PINK = MANUAL INPUT
B2: DECISION | C2: =C62
B4: A. OFFER | J4: MONEYBADGER Discrepancies
B5: Fund $ | C5: Factor | D5: =IF($E$6="Weekly","Term (weeks)","Term (daily pmts)") | E5: Freq | F5: Fee % | J5: Metric | K5: This tool | L5: MoneyBadger | M5: Difference
F6: 0.05 | J6: =IF($E$6="Weekly","Weekly remittance","Daily remittance") | K6: =IF(OR($E$6="",C8="",C24=0),"",IF($E$6="Weekly",D8,C8)) | L6: =IF(OR(L7="",C24=0),"",L7*C24/IF($E$6="Weekly",$L$8,$L$9)) | M6: =IF(OR(K6="",L6=""),"",L6-K6)
B7: Payback | C7: Daily $ | D7: Weekly $ | E7: Monthly $ | F7: Term (month) | G7: Net $ to Merchant | J7: Holdback % | K7: =IF(OR(D8="",C24=0),"",E8/C24) | L7: =IF(OR($E$6="",C8="",C24=0),"",ROUND(IF($E$6="Weekly",D8*$L$8,C8*$L$9)/C24*100,2)/100) | M7: =IF(OR(K7="",L7=""),"",L7-K7)
B8: =IF(OR(B6="",C6=""),"",B6*C6) | C8: =IF(OR(B8="",D6="",D6=0),"",IF(E6="Weekly",(B8/D6)/5,B8/D6)) | D8: =IF(C8="","",C8*5) | E8: =IF(C8="","",C8*$K$9) | F8: =IF(OR(D6="",D6=0),"",IF(E6="Weekly",D6,D6/5)/($K$9/5)) | G8: =IF(B6="","",B6-(B6*F6)) | J8: Weeks / month | K8: 4.331 | L8: 4 | M8: =IF(OR(K8="",L8=""),"",L8-K8)
J9: Days / month | K9: 21.655 | L9: 21 | M9: =IF(OR(K9="",L9=""),"",L9-K9)
B10: B. BANK DATA
B11: Month - MOST RECENT FIRST | C11: True rev $ | D11: Avg daily bal $ | E11: Neg days | F11: NSFs | G11: MoM %(Revenue Trend) | J11: DEAL PROFILE
B12: Aug | C12: 60000 | D12: 2000 | E12: 0 | F12: 0 | G12: =IF(OR(C12="",C13=""),"",(C12-C13)/C13) | J12: ISO | K12: United Secured Capital 8 | L12: =IF(K12="","",COUNTIF('Historical Data'!$K$2:$K$1100,K12)&" deals in book")
B13: Jul | C13: 60000 | D13: 2000 | E13: 0 | F13: 0 | G13: =IF(OR(C13="",C14=""),"",(C13-C14)/C14) | J13: Industry | K13: Real Estate | L13: =IF(K13="","",COUNTIF('Historical Data'!$Y$2:$Y$1100,K13)&" deals in book")
B14: Jun | C14: 60000 | D14: 2000 | E14: 0 | F14: 0 | G14: =IF(OR(C14="",C15=""),"",(C14-C15)/C15) | J14: New deal or renewal | K14: Renewal | L14: =IF(K14="","",COUNTIF('Historical Data'!$L$2:$L$1100,K14)&" deals in book")
B15: May | C15: 60000 | D15: 2000 | E15: 0 | F15: 0 | G15: =IF(OR(C15="",C16=""),"",(C15-C16)/C16) | J15: Credit score | K15: 600
G16: =IF(OR(C16="",C17=""),"",(C16-C17)/C17)
G17: =IF(OR(C17="",C18=""),"",(C17-C18)/C18)
G18: =IF(OR(C18="",C19=""),"",(C18-C19)/C19)
G19: =IF(OR(C19="",C20=""),"",(C19-C20)/C20)
G20: =IF(OR(C20="",C21=""),"",(C20-C21)/C21)
G21: =IF(OR(C21="",C22=""),"",(C21-C22)/C22)
G22: =IF(OR(C22="",C23=""),"",(C22-C23)/C23)
B24: AVG / TOTAL | C24: 60000 | D24: =IF(COUNT(D12:D23)=0,0,AVERAGE(D12:D23)) | E24: =SUM(E12:E23) | F24: =SUM(F12:F23) | G24: =IFERROR(AVERAGE(G12:G22),"")
B26: EXISTING POSITIONS
B27: Funder | C27: Funded $ | D27: Payment | E27: Freq | F27: Daily equiv | G27: Start Date | H27: Est Term | I27: Est term (mo) | J27: Mo. remaining
B28: lendr | C28: 50000 | D28: 1000 | E28: Weekly | F28: =IF(D28<>"",IF(E28="Daily",D28,IF(E28="Weekly",D28/5,D28/$K$9)),IF(C28="","",C28*Controls!$B$17/(Controls!$B$9*$K$9))) | H28: =IF(OR(C28="",D28=""),"",ROUND(C28*Controls!$B$17/D28,0)) | I28: =IF(H28="","",H28/IF(E28="Daily",$K$9,IF(E28="Weekly",$K$9/5,1))) | J28: =IF(OR(I28="",G28=""),"",MAX(0,I28-(TODAY()-G28)/Controls!$B$16))
E29: Weekly | F29: =IF(D29<>"",IF(E29="Daily",D29,IF(E29="Weekly",D29/5,D29/$K$9)),IF(C29="","",C29*Controls!$B$17/(Controls!$B$9*$K$9))) | H29: =IF(OR(C29="",D29=""),"",ROUND(C29*Controls!$B$17/D29,0)) | I29: =IF(H29="","",H29/IF(E29="Daily",$K$9,IF(E29="Weekly",$K$9/5,1))) | J29: =IF(OR(I29="",G29=""),"",MAX(0,I29-(TODAY()-G29)/Controls!$B$16))
E30: Weekly | F30: =IF(D30<>"",IF(E30="Daily",D30,IF(E30="Weekly",D30/5,D30/$K$9)),IF(C30="","",C30*Controls!$B$17/(Controls!$B$9*$K$9))) | H30: =IF(OR(C30="",D30=""),"",ROUND(C30*Controls!$B$17/D30,0)) | I30: =IF(H30="","",H30/IF(E30="Daily",$K$9,IF(E30="Weekly",$K$9/5,1))) | J30: =IF(OR(I30="",G30=""),"",MAX(0,I30-(TODAY()-G30)/Controls!$B$16))
E31: Weekly | F31: =IF(D31<>"",IF(E31="Daily",D31,IF(E31="Weekly",D31/5,D31/$K$9)),IF(C31="","",C31*Controls!$B$17/(Controls!$B$9*$K$9))) | H31: =IF(OR(C31="",D31=""),"",ROUND(C31*Controls!$B$17/D31,0)) | I31: =IF(H31="","",H31/IF(E31="Daily",$K$9,IF(E31="Weekly",$K$9/5,1))) | J31: =IF(OR(I31="",G31=""),"",MAX(0,I31-(TODAY()-G31)/Controls!$B$16))
E32: Weekly | F32: =IF(D32<>"",IF(E32="Daily",D32,IF(E32="Weekly",D32/5,D32/$K$9)),IF(C32="","",C32*Controls!$B$17/(Controls!$B$9*$K$9))) | H32: =IF(OR(C32="",D32=""),"",ROUND(C32*Controls!$B$17/D32,0)) | I32: =IF(H32="","",H32/IF(E32="Daily",$K$9,IF(E32="Weekly",$K$9/5,1))) | J32: =IF(OR(I32="",G32=""),"",MAX(0,I32-(TODAY()-G32)/Controls!$B$16))
E33: Weekly | F33: =IF(D33<>"",IF(E33="Daily",D33,IF(E33="Weekly",D33/5,D33/$K$9)),IF(C33="","",C33*Controls!$B$17/(Controls!$B$9*$K$9))) | H33: =IF(OR(C33="",D33=""),"",ROUND(C33*Controls!$B$17/D33,0)) | I33: =IF(H33="","",H33/IF(E33="Daily",$K$9,IF(E33="Weekly",$K$9/5,1))) | J33: =IF(OR(I33="",G33=""),"",MAX(0,I33-(TODAY()-G33)/Controls!$B$16))
B34: Positions (excl. Monthly) | C34: =SUMPRODUCT(((C28:C33<>"")+(D28:D33<>"")>0)*(E28:E33<>"Monthly")) | D34: Total existing daily | E34: =SUM(F28:F33) | F34: =E34*$K$9 | G34: /month
B36: C. METRICS
B37: Metric | C37: Value | D37: Green | E37: Red | F37: Status | G37: Knockout | H37: Sizing line
B38: Total LVG (all debt / rev) | C38: =IF(C24=0,"",(E34+IF(C8="",0,C8))*$K$9/C24) | D38: 0.3 | E38: 0.45 | F38: =IF(C38="","",IF(C38>=G38,"KNOCKOUT",IF(C38<=D38,"GREEN",IF(C38>=E38,"RED","YELLOW")))) | G38: 0.55 | H38: =D38+'Historical Score'!$C$35*(E38-D38)
B39: New holdback SP% | C39: =IF(OR(C24=0,E8=""),"",E8/C24) | D39: 0.18 | E39: 0.25 | F39: =IF(C39="","",IF(C39>=G39,"KNOCKOUT",IF(C39<=D39,"GREEN",IF(C39>=E39,"RED","YELLOW")))) | G39: 0.35 | H39: =D39+'Historical Score'!$C$35*(E39-D39)
B40: Daily debt / balance | C40: =IF(D24=0,"",(E34+IF(C8="",0,C8))/D24) | D40: 0.18 | E40: 0.3 | F40: =IF(C40="","",IF(C40>=G40,"KNOCKOUT",IF(C40<=D40,"GREEN",IF(C40>=E40,"RED","YELLOW")))) | G40: 0.35 | H40: =D40+'Historical Score'!$C$35*(E40-D40)
B41: Fund / revenue | C41: =IF(OR(C24=0,B6=""),"",B6/C24) | D41: 0.6 | E41: 0.9 | F41: =IF(C41="","",IF(C41>=G41,"KNOCKOUT",IF(C41<=D41,"GREEN",IF(C41>=E41,"RED","YELLOW")))) | G41: 1.25 | H41: =D41+'Historical Score'!$C$35*(E41-D41)
B42: # positions (incl. new) | C42: =IF(C24=0,"",C34+1) | D42: 2 | E42: 5 | F42: =IF(C42="","",IF(C42>=G42,"KNOCKOUT",IF(C42<=D42,"GREEN",IF(C42>=E42,"RED","YELLOW")))) | G42: 6
B43: Revenue trend (avg MoM) | C43: =G24 | D43: -0.05 | E43: -0.15 | F43: =IF(C24=0,"",IF(NOT(ISNUMBER(C43)),"YELLOW",IF(C43<=G43,"KNOCKOUT",IF(C43>=D43,"GREEN",IF(C43<=E43,"RED","YELLOW"))))) | G43: -0.3
B44: Neg days + NSFs (total) | C44: =E24+F24 | D44: 1 | E44: 6 | F44: =IF(C44="","",IF(C44>=G44,"KNOCKOUT",IF(C44<=D44,"GREEN",IF(C44>=E44,"RED","YELLOW")))) | G44: 10
B45: Credit score (FICO) | C45: =IF(K15="","",K15) | D45: 650 | E45: 630 | F45: =IF(C45="","",IF(AND(G45<>0,C45<=G45),"KNOCKOUT",IF(C45>=D45,"GREEN",IF(C45<E45,"RED","YELLOW")))) | G45: 0
B46: Existing leverage (before new) | C46: =IF(C24=0,"",F34/C24) | D46: - | E46: - | F46: INFO
B47: Balance / revenue | C47: =IF(C24=0,"",D24/C24) | D47: - | E47: - | F47: INFO
B49: C2. HOUSE-BOOK INDICATORS (set the sizing line + modifier; NOT counted in the cash-flow score)
B50: Cohort | C50: Principal lost rate | D50: Green <= | E50: Red > | F50: Status | G50: Seasoned Deals | H50: Return on funded
B51: ="Primary cohort: "&'Historical Score'!$C$29 | C51: ='Historical Score'!$C$31 | D51: ='Historical Score'!$C$10*Controls!$B$29 | E51: ='Historical Score'!$C$10*Controls!$B$30 | F51: =IF('Historical Score'!$C$37="NO","NO DEALS",IF('Historical Score'!$C$33<=Controls!$B$29,"GREEN",IF('Historical Score'!$C$33>Controls!$B$30,"RED","YELLOW"))) | G51: ='Historical Score'!$C$30 | H51: ='Historical Score'!$C$32
B52: ISO | C52: ='Historical Score'!$F$26 | D52: ='Historical Score'!$C$10*Controls!$B$29 | E52: ='Historical Score'!$C$10*Controls!$B$30 | F52: =IF('Historical Score'!$C$26=0,"NO DEALS",IF('Historical Score'!$F$26="","NO RATE",IF('Historical Score'!$H$26<=Controls!$B$29,"GREEN",IF('Historical Score'!$H$26>Controls!$B$30,"RED","YELLOW")))) | G52: ='Historical Score'!$C$26 | H52: ='Historical Score'!$G$26
B53: Industry | C53: ='Historical Score'!$F$25 | D53: ='Historical Score'!$C$10*Controls!$B$29 | E53: ='Historical Score'!$C$10*Controls!$B$30 | F53: =IF('Historical Score'!$C$25=0,"NO DEALS",IF('Historical Score'!$F$25="","NO RATE",IF('Historical Score'!$H$25<=Controls!$B$29,"GREEN",IF('Historical Score'!$H$25>Controls!$B$30,"RED","YELLOW")))) | G53: ='Historical Score'!$C$25 | H53: ='Historical Score'!$G$25
B54: New deal / renewal | C54: ='Historical Score'!$F$24 | D54: ='Historical Score'!$C$10*Controls!$B$29 | E54: ='Historical Score'!$C$10*Controls!$B$30 | F54: =IF('Historical Score'!$C$24=0,"NO DEALS",IF('Historical Score'!$F$24="","NO RATE",IF('Historical Score'!$H$24<=Controls!$B$29,"GREEN",IF('Historical Score'!$H$24>Controls!$B$30,"RED","YELLOW")))) | G54: ='Historical Score'!$C$24 | H54: ='Historical Score'!$G$24
B55: Position | C55: ='Historical Score'!$F$23 | D55: ='Historical Score'!$C$10*Controls!$B$29 | E55: ='Historical Score'!$C$10*Controls!$B$30 | F55: =IF('Historical Score'!$C$23=0,"NO DEALS",IF('Historical Score'!$F$23="","NO RATE",IF('Historical Score'!$H$23<=Controls!$B$29,"GREEN",IF('Historical Score'!$H$23>Controls!$B$30,"RED","YELLOW")))) | G55: ='Historical Score'!$C$23 | H55: ='Historical Score'!$G$23
B56: Seasoned deals behind the primary cohort | C56: =IF('Historical Score'!$C$37="NO",0,'Historical Score'!$C$30) | D56: =Controls!$B$26 | E56: =Controls!$B$24 | F56: =IF(C56>=D56,"GREEN",IF(C56>=E56,"YELLOW","RED"))
B59: D. DECISION (cash-flow layer, on the requested offer)
B60: Red flags | C60: =COUNTIF(F38:F45,"RED")+COUNTIF(F38:F45,"KNOCKOUT") | D60: Knockouts | E60: =COUNTIF(F38:F45,"KNOCKOUT")
B61: Decline if red flags >= (Controls) | C61: 2 | D61: Minimum fund $ | E61: 10000
B62: DECISION | C62: =IF(C24=0,"",IF(OR(E60>0,IF(ISNUMBER(C73),C73,0)<E61),"DECLINE",IF(OR(B6="",B6=0),"",IF(C60>=C61,"DECLINE",IF(COUNTIF(F38:F45,"GREEN")=SUMPRODUCT(--(F38:F45<>"")),"APPROVE","CONDITIONAL")))))
B64: E. DEAL QUALITY & MAXIMUM OFFER at the sizing line | F64: Exisiting Green Line
B65: Score (G=1, Y=0.5, R=0) | C65: =COUNTIF(F38:F45,"GREEN")+0.5*COUNTIF(F38:F45,"YELLOW")
B66: Tier (score scaled to 7 for the bands) | C66: =IF(C24=0,"",IF(IF(SUMPRODUCT(--(F38:F45<>""))=0,0,C65*7/SUMPRODUCT(--(F38:F45<>"")))>=6.5,"Strong",IF(IF(SUMPRODUCT(--(F38:F45<>""))=0,0,C65*7/SUMPRODUCT(--(F38:F45<>"")))>=5,"Solid",IF(IF(SUMPRODUCT(--(F38:F45<>""))=0,0,C65*7/SUMPRODUCT(--(F38:F45<>"")))>=3.5,"Moderate","Weak"))))
B67: Max daily by SP% sizing line | C67: =IF(C24=0,"",H39*C24/$K$9) | F67: =IF(C24=0,"",D39*C24/$K$9)
B68: Max daily by Total LVG sizing line | C68: =IF(C24=0,"",(H38*C24-F34)/$K$9) | F68: =IF(C24=0,"",(D38*C24-F34)/$K$9)
B69: Max daily by Daily/Balance sizing line | C69: =IF(OR(C24=0,D24=0),"",H40*D24-E34) | F69: =IF(OR(C24=0,D24=0),"",D40*D24-E34)
B70: MAX DAILY (weakest link) | C70: =IF(C24=0,"",MAX(0,MIN(C67:C69))) | F70: =IF(C24=0,"",MAX(0,MIN(F67:F69))) | G70: {=IF(F70="","",IF(F70=0,"no clean room",INDEX({"SP% holdback";"Total LVG";"Daily/Balance"},MATCH(F70,F67:F69,0))&" is the limit"))}
B71: Weekly / monthly equivalent | C71: =IF(OR(C70="",C70=0),"",C70*5) | D71: =IF(OR(C70="",C70=0),"",C70*$K$9)
B72: Term (daily pmts) / factor from bands | C72: {=IF(OR(C70="",C70=0,C65=""),"",MAX(20,MIN(INDEX(Controls!$B$5:$B$8,MATCH(IF(SUMPRODUCT(--(F38:F45<>""))=0,0,C65*7/SUMPRODUCT(--(F38:F45<>""))),Controls!$A$5:$A$8,1)),FLOOR(Controls!$B$9*$K$9,5),FLOOR(H41*C24*D72/C70,5))))} | D72: {=IF(OR(C65="",C24=0),"",INDEX(Controls!$C$5:$C$8,MATCH(IF(SUMPRODUCT(--(F38:F45<>""))=0,0,C65*7/SUMPRODUCT(--(F38:F45<>""))),Controls!$A$5:$A$8,1)))} | F72: {=IF(OR(F70="",F70=0,C65=""),"",MAX(20,MIN(INDEX(Controls!$B$5:$B$8,MATCH(IF(SUMPRODUCT(--(F38:F45<>""))=0,0,C65*7/SUMPRODUCT(--(F38:F45<>""))),Controls!$A$5:$A$8,1)),FLOOR(Controls!$B$9*$K$9,5),FLOOR(D41*C24*D72/F70,5))))}
B73: MAX FUND at the sizing line | C73: =IF(COUNTIF(F42:F45,"KNOCKOUT")>0,"-",IF(OR(C70="",C70=0,C72="",D72=""),"",FLOOR(C70*C72/D72,500))) | D73: =IF(C73="-","KNOCKOUT on the merchant - do not fund.",IF(C73="","","payback "&TEXT(C73*D72,"$#,##0")&" over "&C72&" daily pmts ("&TEXT(C72/5,"0")&" wks)")) | F73: =IF(COUNTIF(F42:F45,"KNOCKOUT")>0,"-",IF(OR(F70="",F70=0,F72=""),"",FLOOR(F70*F72/D72,500)))
B75: F. FINAL OFFER
B76: FINAL DECISION | C76: =IF(C24=0,"",IF(OR(C73="-",C73="",C78="",C78=0,C78<E61,COUNTIF(F42:F45,"RED")+COUNTIF(F42:F45,"KNOCKOUT")+COUNTIF($C$87:$C$90,"RED")>=C61),"DECLINE",IF(OR(COUNTIF($C$87:$C$90,"YELLOW")>0,COUNTIF(F42:F45,"YELLOW")>0,C84="Negative"),"CONDITIONAL","APPROVE")))
B77: Cash flow only | C77: =F73
B78: RECOMMENDED FUND | C78: =IF($K$14="","",C73)
B79: Factor | C79: =IF(OR(C78="",C78="-"),"",D72)
B80: Term (weeks) | C80: =IF(OR(C78="",C78="-"),"",C72/5)
B81: Term (daily pmts) | C81: =IF(OR(C78="",C78="-"),"",C72)
B82: Weekly payment | C82: =IF(OR(C78="",C78="-"),"",C78*D72/C72*5)
B83: Daily payment | C83: =IF(OR(C78="",C78="-"),"",C78*D72/C72)
B84: HOUSE-BOOK OUTCOME | C84: ='Historical Score'!$C$34
B86: RE-CHECK AT FINAL OFFER
B87: Holdback | C87: =IF(D87="","",IF(D87>=G39,"KNOCKOUT",IF(D87<=D39,"GREEN",IF(D87>=E39,"RED","YELLOW")))) | D87: =IF($C$83="","",$C$83*$K$9/C24)
B88: Total LVG | C88: =IF(D88="","",IF(D88>=G38,"KNOCKOUT",IF(D88<=D38,"GREEN",IF(D88>=E38,"RED","YELLOW")))) | D88: =IF($C$83="","",(E34+$C$83)*$K$9/C24)
B89: Daily/balance | C89: =IF(D89="","",IF(D89>=G40,"KNOCKOUT",IF(D89<=D40,"GREEN",IF(D89>=E40,"RED","YELLOW")))) | D89: =IF(OR($C$83="",D24=0),"",(E34+$C$83)/D24)
B90: Fund/revenue | C90: =IF(D90="","",IF(D90>=G41,"KNOCKOUT",IF(D90<=D41,"GREEN",IF(D90>=E41,"RED","YELLOW")))) | D90: =IF(OR(C78="",C78="-"),"",C78/C24)

Sheet Historical Score
A1: HISTORICAL SCORE
A4: DEAL BEING MATCHED
B5: New deal or renewal | C5: =IF(Deal!$K$14="","",Deal!$K$14)
B6: Position (Deal C42) | C6: =IF(Deal!$C$42="","",Deal!$C$42)
B7: Industry | C7: =IF(Deal!$K$13="","",Deal!$K$13)
B8: ISO | C8: =IF(Deal!$K$12="","",Deal!$K$12)
B10: Seasoned-book principal lost rate | C10: =IF($F$21="",0,$F$21)
B11: Seasoned-book return on funded | C11: =IF($G$21="",0,$G$21)
B13: Cohort | C13: Seasoned deals | D13: Funded $ (seasoned) | E13: Meets min? | F13: Principal lost rate | G13: Return on funded | H13: Index | K13: req NR | L13: req ISO | M13: req Ind | N13: req Pos | O13: <- tier definition: 1 = must match, 0 = ignore
B14: New/renewal + ISO + industry | C14: =SUMPRODUCT('Historical Data'!$AP$2:$AP$1068*('Historical Data'!$AR$2:$AR$1068*$K14+(1-$K14))*('Historical Data'!$AT$2:$AT$1068*$L14+(1-$L14))*('Historical Data'!$AS$2:$AS$1068*$M14+(1-$M14))*('Historical Data'!$AQ$2:$AQ$1068*$N14+(1-$N14))) | D14: =SUMPRODUCT('Historical Data'!$AP$2:$AP$1068*('Historical Data'!$AR$2:$AR$1068*$K14+(1-$K14))*('Historical Data'!$AT$2:$AT$1068*$L14+(1-$L14))*('Historical Data'!$AS$2:$AS$1068*$M14+(1-$M14))*('Historical Data'!$AQ$2:$AQ$1068*$N14+(1-$N14))*'Historical Data'!$N$2:$N$1068) | E14: =IF(AND(C14>=Controls!$B$24,D14>=Controls!$B$25),"Yes","No") | F14: =IF(D14=0,"",SUMPRODUCT('Historical Data'!$AP$2:$AP$1068*('Historical Data'!$AR$2:$AR$1068*$K14+(1-$K14))*('Historical Data'!$AT$2:$AT$1068*$L14+(1-$L14))*('Historical Data'!$AS$2:$AS$1068*$M14+(1-$M14))*('Historical Data'!$AQ$2:$AQ$1068*$N14+(1-$N14))*'Historical Data'!$AK$2:$AK$1068)/D14) | G14: =IF(D14=0,"",SUMPRODUCT('Historical Data'!$AP$2:$AP$1068*('Historical Data'!$AR$2:$AR$1068*$K14+(1-$K14))*('Historical Data'!$AT$2:$AT$1068*$L14+(1-$L14))*('Historical Data'!$AS$2:$AS$1068*$M14+(1-$M14))*('Historical Data'!$AQ$2:$AQ$1068*$N14+(1-$N14))*'Historical Data'!$AJ$2:$AJ$1068)/D14) | H14: =IF(OR(F14="",$C$10=0),"",F14/$C$10) | K14: 1 | L14: 1 | M14: 1 | N14: 0
B15: New/renewal + industry + position | C15: =SUMPRODUCT('Historical Data'!$AP$2:$AP$1068*('Historical Data'!$AR$2:$AR$1068*$K15+(1-$K15))*('Historical Data'!$AT$2:$AT$1068*$L15+(1-$L15))*('Historical Data'!$AS$2:$AS$1068*$M15+(1-$M15))*('Historical Data'!$AQ$2:$AQ$1068*$N15+(1-$N15))) | D15: =SUMPRODUCT('Historical Data'!$AP$2:$AP$1068*('Historical Data'!$AR$2:$AR$1068*$K15+(1-$K15))*('Historical Data'!$AT$2:$AT$1068*$L15+(1-$L15))*('Historical Data'!$AS$2:$AS$1068*$M15+(1-$M15))*('Historical Data'!$AQ$2:$AQ$1068*$N15+(1-$N15))*'Historical Data'!$N$2:$N$1068) | E15: =IF(AND(C15>=Controls!$B$24,D15>=Controls!$B$25),"Yes","No") | F15: =IF(D15=0,"",SUMPRODUCT('Historical Data'!$AP$2:$AP$1068*('Historical Data'!$AR$2:$AR$1068*$K15+(1-$K15))*('Historical Data'!$AT$2:$AT$1068*$L15+(1-$L15))*('Historical Data'!$AS$2:$AS$1068*$M15+(1-$M15))*('Historical Data'!$AQ$2:$AQ$1068*$N15+(1-$N15))*'Historical Data'!$AK$2:$AK$1068)/D15) | G15: =IF(D15=0,"",SUMPRODUCT('Historical Data'!$AP$2:$AP$1068*('Historical Data'!$AR$2:$AR$1068*$K15+(1-$K15))*('Historical Data'!$AT$2:$AT$1068*$L15+(1-$L15))*('Historical Data'!$AS$2:$AS$1068*$M15+(1-$M15))*('Historical Data'!$AQ$2:$AQ$1068*$N15+(1-$N15))*'Historical Data'!$AJ$2:$AJ$1068)/D15) | H15: =IF(OR(F15="",$C$10=0),"",F15/$C$10) | K15: 1 | L15: 0 | M15: 1 | N15: 1
B16: New/renewal + ISO + position | C16: =SUMPRODUCT('Historical Data'!$AP$2:$AP$1068*('Historical Data'!$AR$2:$AR$1068*$K16+(1-$K16))*('Historical Data'!$AT$2:$AT$1068*$L16+(1-$L16))*('Historical Data'!$AS$2:$AS$1068*$M16+(1-$M16))*('Historical Data'!$AQ$2:$AQ$1068*$N16+(1-$N16))) | D16: =SUMPRODUCT('Historical Data'!$AP$2:$AP$1068*('Historical Data'!$AR$2:$AR$1068*$K16+(1-$K16))*('Historical Data'!$AT$2:$AT$1068*$L16+(1-$L16))*('Historical Data'!$AS$2:$AS$1068*$M16+(1-$M16))*('Historical Data'!$AQ$2:$AQ$1068*$N16+(1-$N16))*'Historical Data'!$N$2:$N$1068) | E16: =IF(AND(C16>=Controls!$B$24,D16>=Controls!$B$25),"Yes","No") | F16: =IF(D16=0,"",SUMPRODUCT('Historical Data'!$AP$2:$AP$1068*('Historical Data'!$AR$2:$AR$1068*$K16+(1-$K16))*('Historical Data'!$AT$2:$AT$1068*$L16+(1-$L16))*('Historical Data'!$AS$2:$AS$1068*$M16+(1-$M16))*('Historical Data'!$AQ$2:$AQ$1068*$N16+(1-$N16))*'Historical Data'!$AK$2:$AK$1068)/D16) | G16: =IF(D16=0,"",SUMPRODUCT('Historical Data'!$AP$2:$AP$1068*('Historical Data'!$AR$2:$AR$1068*$K16+(1-$K16))*('Historical Data'!$AT$2:$AT$1068*$L16+(1-$L16))*('Historical Data'!$AS$2:$AS$1068*$M16+(1-$M16))*('Historical Data'!$AQ$2:$AQ$1068*$N16+(1-$N16))*'Historical Data'!$AJ$2:$AJ$1068)/D16) | H16: =IF(OR(F16="",$C$10=0),"",F16/$C$10) | K16: 1 | L16: 1 | M16: 0 | N16: 1
B17: New/renewal + industry | C17: =SUMPRODUCT('Historical Data'!$AP$2:$AP$1068*('Historical Data'!$AR$2:$AR$1068*$K17+(1-$K17))*('Historical Data'!$AT$2:$AT$1068*$L17+(1-$L17))*('Historical Data'!$AS$2:$AS$1068*$M17+(1-$M17))*('Historical Data'!$AQ$2:$AQ$1068*$N17+(1-$N17))) | D17: =SUMPRODUCT('Historical Data'!$AP$2:$AP$1068*('Historical Data'!$AR$2:$AR$1068*$K17+(1-$K17))*('Historical Data'!$AT$2:$AT$1068*$L17+(1-$L17))*('Historical Data'!$AS$2:$AS$1068*$M17+(1-$M17))*('Historical Data'!$AQ$2:$AQ$1068*$N17+(1-$N17))*'Historical Data'!$N$2:$N$1068) | E17: =IF(AND(C17>=Controls!$B$24,D17>=Controls!$B$25),"Yes","No") | F17: =IF(D17=0,"",SUMPRODUCT('Historical Data'!$AP$2:$AP$1068*('Historical Data'!$AR$2:$AR$1068*$K17+(1-$K17))*('Historical Data'!$AT$2:$AT$1068*$L17+(1-$L17))*('Historical Data'!$AS$2:$AS$1068*$M17+(1-$M17))*('Historical Data'!$AQ$2:$AQ$1068*$N17+(1-$N17))*'Historical Data'!$AK$2:$AK$1068)/D17) | G17: =IF(D17=0,"",SUMPRODUCT('Historical Data'!$AP$2:$AP$1068*('Historical Data'!$AR$2:$AR$1068*$K17+(1-$K17))*('Historical Data'!$AT$2:$AT$1068*$L17+(1-$L17))*('Historical Data'!$AS$2:$AS$1068*$M17+(1-$M17))*('Historical Data'!$AQ$2:$AQ$1068*$N17+(1-$N17))*'Historical Data'!$AJ$2:$AJ$1068)/D17) | H17: =IF(OR(F17="",$C$10=0),"",F17/$C$10) | K17: 1 | L17: 0 | M17: 1 | N17: 0
B18: New/renewal + ISO | C18: =SUMPRODUCT('Historical Data'!$AP$2:$AP$1068*('Historical Data'!$AR$2:$AR$1068*$K18+(1-$K18))*('Historical Data'!$AT$2:$AT$1068*$L18+(1-$L18))*('Historical Data'!$AS$2:$AS$1068*$M18+(1-$M18))*('Historical Data'!$AQ$2:$AQ$1068*$N18+(1-$N18))) | D18: =SUMPRODUCT('Historical Data'!$AP$2:$AP$1068*('Historical Data'!$AR$2:$AR$1068*$K18+(1-$K18))*('Historical Data'!$AT$2:$AT$1068*$L18+(1-$L18))*('Historical Data'!$AS$2:$AS$1068*$M18+(1-$M18))*('Historical Data'!$AQ$2:$AQ$1068*$N18+(1-$N18))*'Historical Data'!$N$2:$N$1068) | E18: =IF(AND(C18>=Controls!$B$24,D18>=Controls!$B$25),"Yes","No") | F18: =IF(D18=0,"",SUMPRODUCT('Historical Data'!$AP$2:$AP$1068*('Historical Data'!$AR$2:$AR$1068*$K18+(1-$K18))*('Historical Data'!$AT$2:$AT$1068*$L18+(1-$L18))*('Historical Data'!$AS$2:$AS$1068*$M18+(1-$M18))*('Historical Data'!$AQ$2:$AQ$1068*$N18+(1-$N18))*'Historical Data'!$AK$2:$AK$1068)/D18) | G18: =IF(D18=0,"",SUMPRODUCT('Historical Data'!$AP$2:$AP$1068*('Historical Data'!$AR$2:$AR$1068*$K18+(1-$K18))*('Historical Data'!$AT$2:$AT$1068*$L18+(1-$L18))*('Historical Data'!$AS$2:$AS$1068*$M18+(1-$M18))*('Historical Data'!$AQ$2:$AQ$1068*$N18+(1-$N18))*'Historical Data'!$AJ$2:$AJ$1068)/D18) | H18: =IF(OR(F18="",$C$10=0),"",F18/$C$10) | K18: 1 | L18: 1 | M18: 0 | N18: 0
B19: New/renewal + position | C19: =SUMPRODUCT('Historical Data'!$AP$2:$AP$1068*('Historical Data'!$AR$2:$AR$1068*$K19+(1-$K19))*('Historical Data'!$AT$2:$AT$1068*$L19+(1-$L19))*('Historical Data'!$AS$2:$AS$1068*$M19+(1-$M19))*('Historical Data'!$AQ$2:$AQ$1068*$N19+(1-$N19))) | D19: =SUMPRODUCT('Historical Data'!$AP$2:$AP$1068*('Historical Data'!$AR$2:$AR$1068*$K19+(1-$K19))*('Historical Data'!$AT$2:$AT$1068*$L19+(1-$L19))*('Historical Data'!$AS$2:$AS$1068*$M19+(1-$M19))*('Historical Data'!$AQ$2:$AQ$1068*$N19+(1-$N19))*'Historical Data'!$N$2:$N$1068) | E19: =IF(AND(C19>=Controls!$B$24,D19>=Controls!$B$25),"Yes","No") | F19: =IF(D19=0,"",SUMPRODUCT('Historical Data'!$AP$2:$AP$1068*('Historical Data'!$AR$2:$AR$1068*$K19+(1-$K19))*('Historical Data'!$AT$2:$AT$1068*$L19+(1-$L19))*('Historical Data'!$AS$2:$AS$1068*$M19+(1-$M19))*('Historical Data'!$AQ$2:$AQ$1068*$N19+(1-$N19))*'Historical Data'!$AK$2:$AK$1068)/D19) | G19: =IF(D19=0,"",SUMPRODUCT('Historical Data'!$AP$2:$AP$1068*('Historical Data'!$AR$2:$AR$1068*$K19+(1-$K19))*('Historical Data'!$AT$2:$AT$1068*$L19+(1-$L19))*('Historical Data'!$AS$2:$AS$1068*$M19+(1-$M19))*('Historical Data'!$AQ$2:$AQ$1068*$N19+(1-$N19))*'Historical Data'!$AJ$2:$AJ$1068)/D19) | H19: =IF(OR(F19="",$C$10=0),"",F19/$C$10) | K19: 1 | L19: 0 | M19: 0 | N19: 1
B20: New/renewal only | C20: =SUMPRODUCT('Historical Data'!$AP$2:$AP$1068*('Historical Data'!$AR$2:$AR$1068*$K20+(1-$K20))*('Historical Data'!$AT$2:$AT$1068*$L20+(1-$L20))*('Historical Data'!$AS$2:$AS$1068*$M20+(1-$M20))*('Historical Data'!$AQ$2:$AQ$1068*$N20+(1-$N20))) | D20: =SUMPRODUCT('Historical Data'!$AP$2:$AP$1068*('Historical Data'!$AR$2:$AR$1068*$K20+(1-$K20))*('Historical Data'!$AT$2:$AT$1068*$L20+(1-$L20))*('Historical Data'!$AS$2:$AS$1068*$M20+(1-$M20))*('Historical Data'!$AQ$2:$AQ$1068*$N20+(1-$N20))*'Historical Data'!$N$2:$N$1068) | E20: =IF(AND(C20>=Controls!$B$24,D20>=Controls!$B$25),"Yes","No") | F20: =IF(D20=0,"",SUMPRODUCT('Historical Data'!$AP$2:$AP$1068*('Historical Data'!$AR$2:$AR$1068*$K20+(1-$K20))*('Historical Data'!$AT$2:$AT$1068*$L20+(1-$L20))*('Historical Data'!$AS$2:$AS$1068*$M20+(1-$M20))*('Historical Data'!$AQ$2:$AQ$1068*$N20+(1-$N20))*'Historical Data'!$AK$2:$AK$1068)/D20) | G20: =IF(D20=0,"",SUMPRODUCT('Historical Data'!$AP$2:$AP$1068*('Historical Data'!$AR$2:$AR$1068*$K20+(1-$K20))*('Historical Data'!$AT$2:$AT$1068*$L20+(1-$L20))*('Historical Data'!$AS$2:$AS$1068*$M20+(1-$M20))*('Historical Data'!$AQ$2:$AQ$1068*$N20+(1-$N20))*'Historical Data'!$AJ$2:$AJ$1068)/D20) | H20: =IF(OR(F20="",$C$10=0),"",F20/$C$10) | K20: 1 | L20: 0 | M20: 0 | N20: 0
B21: Whole seasoned book | C21: =SUMPRODUCT('Historical Data'!$AP$2:$AP$1068*('Historical Data'!$AR$2:$AR$1068*$K21+(1-$K21))*('Historical Data'!$AT$2:$AT$1068*$L21+(1-$L21))*('Historical Data'!$AS$2:$AS$1068*$M21+(1-$M21))*('Historical Data'!$AQ$2:$AQ$1068*$N21+(1-$N21))) | D21: =SUMPRODUCT('Historical Data'!$AP$2:$AP$1068*('Historical Data'!$AR$2:$AR$1068*$K21+(1-$K21))*('Historical Data'!$AT$2:$AT$1068*$L21+(1-$L21))*('Historical Data'!$AS$2:$AS$1068*$M21+(1-$M21))*('Historical Data'!$AQ$2:$AQ$1068*$N21+(1-$N21))*'Historical Data'!$N$2:$N$1068) | E21: =IF(AND(C21>=Controls!$B$24,D21>=Controls!$B$25),"Yes","No") | F21: =IF(D21=0,"",SUMPRODUCT('Historical Data'!$AP$2:$AP$1068*('Historical Data'!$AR$2:$AR$1068*$K21+(1-$K21))*('Historical Data'!$AT$2:$AT$1068*$L21+(1-$L21))*('Historical Data'!$AS$2:$AS$1068*$M21+(1-$M21))*('Historical Data'!$AQ$2:$AQ$1068*$N21+(1-$N21))*'Historical Data'!$AK$2:$AK$1068)/D21) | G21: =IF(D21=0,"",SUMPRODUCT('Historical Data'!$AP$2:$AP$1068*('Historical Data'!$AR$2:$AR$1068*$K21+(1-$K21))*('Historical Data'!$AT$2:$AT$1068*$L21+(1-$L21))*('Historical Data'!$AS$2:$AS$1068*$M21+(1-$M21))*('Historical Data'!$AQ$2:$AQ$1068*$N21+(1-$N21))*'Historical Data'!$AJ$2:$AJ$1068)/D21) | H21: =IF(OR(F21="",$C$10=0),"",F21/$C$10) | K21: 0 | L21: 0 | M21: 0 | N21: 0
B22: SINGLE-DIMENSION EVIDENCE | I22: |PLR - book|
B23: Position only | C23: =SUMPRODUCT('Historical Data'!$AQ$2:$AQ$1068*'Historical Data'!$AP$2:$AP$1068) | D23: =SUMPRODUCT('Historical Data'!$AQ$2:$AQ$1068*'Historical Data'!$AP$2:$AP$1068*'Historical Data'!$N$2:$N$1068) | E23: =IF(AND(C23>=Controls!$B$24,D23>=Controls!$B$25),"Yes","No") | F23: =IF(D23=0,"",SUMPRODUCT('Historical Data'!$AQ$2:$AQ$1068*'Historical Data'!$AP$2:$AP$1068*'Historical Data'!$AK$2:$AK$1068)/D23) | G23: =IF(D23=0,"",SUMPRODUCT('Historical Data'!$AQ$2:$AQ$1068*'Historical Data'!$AP$2:$AP$1068*'Historical Data'!$AJ$2:$AJ$1068)/D23) | H23: =IF(OR(F23="",$C$10=0),"",F23/$C$10) | I23: =IF(F23="",0,ABS(F23-$C$10))
B24: New/renewal only | C24: =SUMPRODUCT('Historical Data'!$AR$2:$AR$1068*'Historical Data'!$AP$2:$AP$1068) | D24: =SUMPRODUCT('Historical Data'!$AR$2:$AR$1068*'Historical Data'!$AP$2:$AP$1068*'Historical Data'!$N$2:$N$1068) | E24: =IF(AND(C24>=Controls!$B$24,D24>=Controls!$B$25),"Yes","No") | F24: =IF(D24=0,"",SUMPRODUCT('Historical Data'!$AR$2:$AR$1068*'Historical Data'!$AP$2:$AP$1068*'Historical Data'!$AK$2:$AK$1068)/D24) | G24: =IF(D24=0,"",SUMPRODUCT('Historical Data'!$AR$2:$AR$1068*'Historical Data'!$AP$2:$AP$1068*'Historical Data'!$AJ$2:$AJ$1068)/D24) | H24: =IF(OR(F24="",$C$10=0),"",F24/$C$10) | I24: =IF(F24="",0,ABS(F24-$C$10))
B25: Industry only | C25: =SUMPRODUCT('Historical Data'!$AS$2:$AS$1068*'Historical Data'!$AP$2:$AP$1068) | D25: =SUMPRODUCT('Historical Data'!$AS$2:$AS$1068*'Historical Data'!$AP$2:$AP$1068*'Historical Data'!$N$2:$N$1068) | E25: =IF(AND(C25>=Controls!$B$24,D25>=Controls!$B$25),"Yes","No") | F25: =IF(D25=0,"",SUMPRODUCT('Historical Data'!$AS$2:$AS$1068*'Historical Data'!$AP$2:$AP$1068*'Historical Data'!$AK$2:$AK$1068)/D25) | G25: =IF(D25=0,"",SUMPRODUCT('Historical Data'!$AS$2:$AS$1068*'Historical Data'!$AP$2:$AP$1068*'Historical Data'!$AJ$2:$AJ$1068)/D25) | H25: =IF(OR(F25="",$C$10=0),"",F25/$C$10) | I25: =IF(F25="",0,ABS(F25-$C$10))
B26: ISO only | C26: =SUMPRODUCT('Historical Data'!$AT$2:$AT$1068*'Historical Data'!$AP$2:$AP$1068) | D26: =SUMPRODUCT('Historical Data'!$AT$2:$AT$1068*'Historical Data'!$AP$2:$AP$1068*'Historical Data'!$N$2:$N$1068) | E26: =IF(AND(C26>=Controls!$B$24,D26>=Controls!$B$25),"Yes","No") | F26: =IF(D26=0,"",SUMPRODUCT('Historical Data'!$AT$2:$AT$1068*'Historical Data'!$AP$2:$AP$1068*'Historical Data'!$AK$2:$AK$1068)/D26) | G26: =IF(D26=0,"",SUMPRODUCT('Historical Data'!$AT$2:$AT$1068*'Historical Data'!$AP$2:$AP$1068*'Historical Data'!$AJ$2:$AJ$1068)/D26) | H26: =IF(OR(F26="",$C$10=0),"",F26/$C$10) | I26: =IF(F26="",0,ABS(F26-$C$10))
A28: RESULT
B29: Primary cohort (lowest row that meets both minimums) | C29: =IF($D$29="","- no deal entered -",INDEX($B$14:$B$21,$D$29)) | D29: =IF($C$5="","",MATCH("Yes",$E$14:$E$21,0)) | E29: row # (read by Historical Data) | K29: =IF($D$29="","",INDEX(K$14:K$21,$D$29)) | L29: =IF($D$29="","",INDEX(L$14:L$21,$D$29)) | M29: =IF($D$29="","",INDEX(M$14:M$21,$D$29)) | N29: =IF($D$29="","",INDEX(N$14:N$21,$D$29)) | O29: <- flags of the selected tier (read by Historical Data BA)
B30: Seasoned deals in it | C30: =IF($C$37="NO","",INDEX($C$14:$C$21,$D$29)) | D30: =COUNTA($B$14:$B$21) | E30: fallback row # (whole seasoned book)
B31: Principal lost rate | C31: =IF($C$37="NO","",INDEX($F$14:$F$21,$D$29))
B32: Return on funded | C32: =IF($C$37="NO","",INDEX($G$14:$G$21,$D$29))
B33: Index (PLR / book PLR) | C33: =IF($C$37="NO","",INDEX($H$14:$H$21,$D$29))
B34: HOUSE-BOOK OUTCOME | C34: =IF(OR($C$37="NO",$C$33=""),"Neutral",IF($C$33<=Controls!$B$29,"Supportive",IF($C$33>Controls!$B$30,"Negative","Neutral")))
B35: Sizing flex applied | C35: =IF($C$34="Supportive",Controls!$B$31,IF($C$34="Negative",-Controls!$B$32,0))
B36: Largest-impact variable | C36: {=IF(MAX($I$23:$I$26)=0,"none rated",_xlfn.XLOOKUP(MAX($I$23:$I$26),$I$23:$I$26,$B$23:$B$26))}
B37: HAS EVIDENCE? | C37: =IF(OR($D$29="",$D$29=$D$30),"NO","YES") | D37: <- every guard downstream reads this, not a hard-coded row number

Sheet Comparable Deals
A1: COMPARABLE DEALS
A4: Contract ID | B4: DBA | C4: Status | D4: Funded | E4: Position | F4: Industry | G4: ISO | H4: New/renewal | I4: Factor | J4: Advance | K4: Collected | L4: % paid | M4: Net cash | N4: Principal lost | O4: Term (bd) | P4: Age (bd) | Q4: Days on book | R4: Seasoned | S4: Default | T4: Open | U4: In primary cohort
A5: ='Historical Data'!A2 | B5: ='Historical Data'!B2 | C5: ='Historical Data'!D2 | D5: ='Historical Data'!E2 | E5: ='Historical Data'!G2 | F5: ='Historical Data'!Y2 | G5: ='Historical Data'!K2 | H5: ='Historical Data'!L2 | I5: ='Historical Data'!M2 | J5: ='Historical Data'!N2 | K5: ='Historical Data'!Q2 | L5: ='Historical Data'!S2 | M5: ='Historical Data'!AJ2 | N5: ='Historical Data'!AK2 | O5: ='Historical Data'!AA2 | P5: ='Historical Data'!AB2 | Q5: ='Historical Data'!AN2 | R5: ='Historical Data'!AC2 | S5: ='Historical Data'!AE2 | T5: ='Historical Data'!AH2 | U5: ='Historical Data'!BA2
A6: ='Historical Data'!A3 | B6: ='Historical Data'!B3 | C6: ='Historical Data'!D3 | D6: ='Historical Data'!E3 | E6: ='Historical Data'!G3 | F6: ='Historical Data'!Y3 | G6: ='Historical Data'!K3 | H6: ='Historical Data'!L3 | I6: ='Historical Data'!M3 | J6: ='Historical Data'!N3 | K6: ='Historical Data'!Q3 | L6: ='Historical Data'!S3 | M6: ='Historical Data'!AJ3 | N6: ='Historical Data'!AK3 | O6: ='Historical Data'!AA3 | P6: ='Historical Data'!AB3 | Q6: ='Historical Data'!AN3 | R6: ='Historical Data'!AC3 | S6: ='Historical Data'!AE3 | T6: ='Historical Data'!AH3 | U6: ='Historical Data'!BA3
A7: ='Historical Data'!A4 | B7: ='Historical Data'!B4 | C7: ='Historical Data'!D4 | D7: ='Historical Data'!E4 | E7: ='Historical Data'!G4 | F7: ='Historical Data'!Y4 | G7: ='Historical Data'!K4 | H7: ='Historical Data'!L4 | I7: ='Historical Data'!M4 | J7: ='Historical Data'!N4 | K7: ='Historical Data'!Q4 | L7: ='Historical Data'!S4 | M7: ='Historical Data'!AJ4 | N7: ='Historical Data'!AK4 | O7: ='Historical Data'!AA4 | P7: ='Historical Data'!AB4 | Q7: ='Historical Data'!AN4 | R7: ='Historical Data'!AC4 | S7: ='Historical Data'!AE4 | T7: ='Historical Data'!AH4 | U7: ='Historical Data'!BA4
A8: ='Historical Data'!A5 | B8: ='Historical Data'!B5 | C8: ='Historical Data'!D5 | D8: ='Historical Data'!E5 | E8: ='Historical Data'!G5 | F8: ='Historical Data'!Y5 | G8: ='Historical Data'!K5 | H8: ='Historical Data'!L5 | I8: ='Historical Data'!M5 | J8: ='Historical Data'!N5 | K8: ='Historical Data'!Q5 | L8: ='Historical Data'!S5 | M8: ='Historical Data'!AJ5 | N8: ='Historical Data'!AK5 | O8: ='Historical Data'!AA5 | P8: ='Historical Data'!AB5 | Q8: ='Historical Data'!AN5 | R8: ='Historical Data'!AC5 | S8: ='Historical Data'!AE5 | T8: ='Historical Data'!AH5 | U8: ='Historical Data'!BA5
A9: ='Historical Data'!A6 | B9: ='Historical Data'!B6 | C9: ='Historical Data'!D6 | D9: ='Historical Data'!E6 | E9: ='Historical Data'!G6 | F9: ='Historical Data'!Y6 | G9: ='Historical Data'!K6 | H9: ='Historical Data'!L6 | I9: ='Historical Data'!M6 | J9: ='Historical Data'!N6 | K9: ='Historical Data'!Q6 | L9: ='Historical Data'!S6 | M9: ='Historical Data'!AJ6 | N9: ='Historical Data'!AK6 | O9: ='Historical Data'!AA6 | P9: ='Historical Data'!AB6 | Q9: ='Historical Data'!AN6 | R9: ='Historical Data'!AC6 | S9: ='Historical Data'!AE6 | T9: ='Historical Data'!AH6 | U9: ='Historical Data'!BA6
A10: ='Historical Data'!A7 | B10: ='Historical Data'!B7 | C10: ='Historical Data'!D7 | D10: ='Historical Data'!E7 | E10: ='Historical Data'!G7 | F10: ='Historical Data'!Y7 | G10: ='Historical Data'!K7 | H10: ='Historical Data'!L7 | I10: ='Historical Data'!M7 | J10: ='Historical Data'!N7 | K10: ='Historical Data'!Q7 | L10: ='Historical Data'!S7 | M10: ='Historical Data'!AJ7 | N10: ='Historical Data'!AK7 | O10: ='Historical Data'!AA7 | P10: ='Historical Data'!AB7 | Q10: ='Historical Data'!AN7 | R10: ='Historical Data'!AC7 | S10: ='Historical Data'!AE7 | T10: ='Historical Data'!AH7 | U10: ='Historical Data'!BA7
A11: ='Historical Data'!A8 | B11: ='Historical Data'!B8 | C11: ='Historical Data'!D8 | D11: ='Historical Data'!E8 | E11: ='Historical Data'!G8 | F11: ='Historical Data'!Y8 | G11: ='Historical Data'!K8 | H11: ='Historical Data'!L8 | I11: ='Historical Data'!M8 | J11: ='Historical Data'!N8 | K11: ='Historical Data'!Q8 | L11: ='Historical Data'!S8 | M11: ='Historical Data'!AJ8 | N11: ='Historical Data'!AK8 | O11: ='Historical Data'!AA8 | P11: ='Historical Data'!AB8 | Q11: ='Historical Data'!AN8 | R11: ='Historical Data'!AC8 | S11: ='Historical Data'!AE8 | T11: ='Historical Data'!AH8 | U11: ='Historical Data'!BA8
A12: ='Historical Data'!A9 | B12: ='Historical Data'!B9 | C12: ='Historical Data'!D9 | D12: ='Historical Data'!E9 | E12: ='Historical Data'!G9 | F12: ='Historical Data'!Y9 | G12: ='Historical Data'!K9 | H12: ='Historical Data'!L9 | I12: ='Historical Data'!M9 | J12: ='Historical Data'!N9 | K12: ='Historical Data'!Q9 | L12: ='Historical Data'!S9 | M12: ='Historical Data'!AJ9 | N12: ='Historical Data'!AK9 | O12: ='Historical Data'!AA9 | P12: ='Historical Data'!AB9 | Q12: ='Historical Data'!AN9 | R12: ='Historical Data'!AC9 | S12: ='Historical Data'!AE9 | T12: ='Historical Data'!AH9 | U12: ='Historical Data'!BA9
A13: ='Historical Data'!A10 | B13: ='Historical Data'!B10 | C13: ='Historical Data'!D10 | D13: ='Historical Data'!E10 | E13: ='Historical Data'!G10 | F13: ='Historical Data'!Y10 | G13: ='Historical Data'!K10 | H13: ='Historical Data'!L10 | I13: ='Historical Data'!M10 | J13: ='Historical Data'!N10 | K13: ='Historical Data'!Q10 | L13: ='Historical Data'!S10 | M13: ='Historical Data'!AJ10 | N13: ='Historical Data'!AK10 | O13: ='Historical Data'!AA10 | P13: ='Historical Data'!AB10 | Q13: ='Historical Data'!AN10 | R13: ='Historical Data'!AC10 | S13: ='Historical Data'!AE10 | T13: ='Historical Data'!AH10 | U13: ='Historical Data'!BA10
A14: ='Historical Data'!A11 | B14: ='Historical Data'!B11 | C14: ='Historical Data'!D11 | D14: ='Historical Data'!E11 | E14: ='Historical Data'!G11 | F14: ='Historical Data'!Y11 | G14: ='Historical Data'!K11 | H14: ='Historical Data'!L11 | I14: ='Historical Data'!M11 | J14: ='Historical Data'!N11 | K14: ='Historical Data'!Q11 | L14: ='Historical Data'!S11 | M14: ='Historical Data'!AJ11 | N14: ='Historical Data'!AK11 | O14: ='Historical Data'!AA11 | P14: ='Historical Data'!AB11 | Q14: ='Historical Data'!AN11 | R14: ='Historical Data'!AC11 | S14: ='Historical Data'!AE11 | T14: ='Historical Data'!AH11 | U14: ='Historical Data'!BA11
A15: ='Historical Data'!A12 | B15: ='Historical Data'!B12 | C15: ='Historical Data'!D12 | D15: ='Historical Data'!E12 | E15: ='Historical Data'!G12 | F15: ='Historical Data'!Y12 | G15: ='Historical Data'!K12 | H15: ='Historical Data'!L12 | I15: ='Historical Data'!M12 | J15: ='Historical Data'!N12 | K15: ='Historical Data'!Q12 | L15: ='Historical Data'!S12 | M15: ='Historical Data'!AJ12 | N15: ='Historical Data'!AK12 | O15: ='Historical Data'!AA12 | P15: ='Historical Data'!AB12 | Q15: ='Historical Data'!AN12 | R15: ='Historical Data'!AC12 | S15: ='Historical Data'!AE12 | T15: ='Historical Data'!AH12 | U15: ='Historical Data'!BA12
A16: ='Historical Data'!A13 | B16: ='Historical Data'!B13 | C16: ='Historical Data'!D13 | D16: ='Historical Data'!E13 | E16: ='Historical Data'!G13 | F16: ='Historical Data'!Y13 | G16: ='Historical Data'!K13 | H16: ='Historical Data'!L13 | I16: ='Historical Data'!M13 | J16: ='Historical Data'!N13 | K16: ='Historical Data'!Q13 | L16: ='Historical Data'!S13 | M16: ='Historical Data'!AJ13 | N16: ='Historical Data'!AK13 | O16: ='Historical Data'!AA13 | P16: ='Historical Data'!AB13 | Q16: ='Historical Data'!AN13 | R16: ='Historical Data'!AC13 | S16: ='Historical Data'!AE13 | T16: ='Historical Data'!AH13 | U16: ='Historical Data'!BA13
... A1071: ='Historical Data'!A1068 | B1071: ='Historical Data'!B1068 | C1071: ='Historical Data'!D1068 | D1071: ='Historical Data'!E1068 | E1071: ='Historical Data'!G1068 | F1071: ='Historical Data'!Y1068 | G1071: ='Historical Data'!K1068 | H1071: ='Historical Data'!L1068 | I1071: ='Historical Data'!M1068 | J1071: ='Historical Data'!N1068 | K1071: ='Historical Data'!Q1068 | L1071: ='Historical Data'!S1068 | M1071: ='Historical Data'!AJ1068 | N1071: ='Historical Data'!AK1068 | O1071: ='Historical Data'!AA1068 | P1071: ='Historical Data'!AB1068 | Q1071: ='Historical Data'!AN1068 | R1071: ='Historical Data'!AC1068 | S1071: ='Historical Data'!AE1068 | T1071: ='Historical Data'!AH1068 | U1071: ='Historical Data'!BA1068

Sheet Historical Data
A1: Contract ID | B1: DBA | C1: Legal name | D1: Status | E1: Start date | F1: Last active | G1: Position | H1: SIC | I1: SIC2 | J1: State | K1: ISO | L1: New or renewal | M1: Factor | N1: Advance | O1: Commission | P1: Payback | Q1: Collected | R1: Balance | S1: % paid | T1: Exp dur (raw) | U1: NSF count | V1: Avg rev/mo | W1: Holdback % | X1: Biz start | Y1: Industry | Z1: Pay frequency | AA1: Term (bus. days) | AB1: Age at as-of (bus. days) | AC1: Seasoned | AD1: In window | AE1: Default | AF1: Resolved | AG1: Closed family | AH1: Open | AI1: Status valid | AJ1: Net cash | AK1: Principal lost | AL1: Adv / revenue | AM1: Has revenue | AN1: Days on book (bus.) | AO1: Renewal | AP1: Eligible (seasoned & in window) | AQ1: m: position | AR1: m: new/renewal | AS1: m: industry | AT1: m: ISO | AU1: (retired - combos now defined by the flag table on Historical Score) | BA1: In primary cohort
A2: 5674142980 | B2: The rustic charm bar and grill | C2: The rustic charm LLC | D2: Legal | E2: 45616 | F2: 46118 | G2: 1 | H2: 5813 | I2: 58 | J2: CO | K2: GREYSTONE | L2: New Deal | M2: 1.49 | N2: 15000 | O2: 2100 | P2: 22350 | Q2: 16835.64 | R2: 5514.36 | S2: 0.75327248 | T2: 2.754 | U2: 5 | V2: 50000 | W2: 0.05 | X2: 44701 | Y2: =IF(I2="","No SIC",IFERROR(VLOOKUP(I2,Ref!$A$2:$B$65,2,FALSE()),"Unclassified")) | Z2: =IF(T2="","",IF(T2<12,"Daily","Weekly")) | AA2: =IF(T2="",0,IF(T2<12,T2*Controls!$B$13,T2*5)) | AB2: =IF(E2="",0,NETWORKDAYS(E2,Controls!$B$20,Ref!$K$2:$K$42)) | AC2: =IF(OR(AF2=1,AND(AA2>0,AB2>=Controls!$B$23*AA2)),1,0) | AD2: =IF(AND(E2<>"",E2>=Controls!$B$21,E2<=Controls!$B$22),1,0) | AE2: =IF(IFERROR(VLOOKUP(D2,Controls!$A$36:$E$46,2,FALSE()),"No")="Yes",1,0) | AF2: =IF(IFERROR(VLOOKUP(D2,Controls!$A$36:$E$46,3,FALSE()),"No")="Yes",1,0) | AG2: =IF(IFERROR(VLOOKUP(D2,Controls!$A$36:$E$46,4,FALSE()),"No")="Yes",1,0) | AH2: =IF(IFERROR(VLOOKUP(D2,Controls!$A$36:$E$46,5,FALSE()),"No")="Yes",1,0) | AI2: =IF(ISNUMBER(MATCH(D2,Controls!$A$36:$A$46,0)),1,0) | AJ2: =Q2-N2 | AK2: =IF(AE2=1,MAX(0,N2-Q2),0) | AL2: =IF(OR(V2="",V2=0),0,N2/V2) | AM2: =IF(OR(V2="",V2=0),0,1) | AN2: =IF(OR(E2="",F2=""),0,NETWORKDAYS(E2,F2,Ref!$K$2:$K$42)) | AO2: =IF(L2="Renewal",1,0) | AP2: =AC2*AD2 | AQ2: =IF(AND(G2<>"",'Historical Score'!$C$6<>""),IF(G2='Historical Score'!$C$6,1,0),0) | AR2: =IF(AND(L2<>"",'Historical Score'!$C$5<>""),IF(L2='Historical Score'!$C$5,1,0),0) | AS2: =IF(AND(Y2<>"",'Historical Score'!$C$7<>""),IF(Y2='Historical Score'!$C$7,1,0),0) | AT2: =IF(AND(K2<>"",'Historical Score'!$C$8<>""),IF(K2='Historical Score'!$C$8,1,0),0) | BA2: =IF(AD2=1,(AR2*'Historical Score'!$K$29+1-'Historical Score'!$K$29)*(AT2*'Historical Score'!$L$29+1-'Historical Score'!$L$29)*(AS2*'Historical Score'!$M$29+1-'Historical Score'!$M$29)*(AQ2*'Historical Score'!$N$29+1-'Historical Score'!$N$29),0)
A3: 5674143732 | B3: GUADALUPE CASTANEDA | C3: GUADALUPE CASTANEDA | D3: Written-Off | E3: 45625 | F3: 45786 | G3: 3 | H3: 1442 | I3: 14 | J3: CA | K3: BFA 3 | L3: New Deal | M3: 1.49 | N3: 5000 | O3: 700 | P3: 7450 | Q3: 6305.98 | R3: 1144.02 | S3: 0.84644027 | T3: 2.623 | U3: 24 | V3: 100000 | W3: 0.12 | X3: 34575 | Y3: =IF(I3="","No SIC",IFERROR(VLOOKUP(I3,Ref!$A$2:$B$65,2,FALSE()),"Unclassified")) | Z3: =IF(T3="","",IF(T3<12,"Daily","Weekly")) | AA3: =IF(T3="",0,IF(T3<12,T3*Controls!$B$13,T3*5)) | AB3: =IF(E3="",0,NETWORKDAYS(E3,Controls!$B$20,Ref!$K$2:$K$42)) | AC3: =IF(OR(AF3=1,AND(AA3>0,AB3>=Controls!$B$23*AA3)),1,0) | AD3: =IF(AND(E3<>"",E3>=Controls!$B$21,E3<=Controls!$B$22),1,0) | AE3: =IF(IFERROR(VLOOKUP(D3,Controls!$A$36:$E$46,2,FALSE()),"No")="Yes",1,0) | AF3: =IF(IFERROR(VLOOKUP(D3,Controls!$A$36:$E$46,3,FALSE()),"No")="Yes",1,0) | AG3: =IF(IFERROR(VLOOKUP(D3,Controls!$A$36:$E$46,4,FALSE()),"No")="Yes",1,0) | AH3: =IF(IFERROR(VLOOKUP(D3,Controls!$A$36:$E$46,5,FALSE()),"No")="Yes",1,0) | AI3: =IF(ISNUMBER(MATCH(D3,Controls!$A$36:$A$46,0)),1,0) | AJ3: =Q3-N3 | AK3: =IF(AE3=1,MAX(0,N3-Q3),0) | AL3: =IF(OR(V3="",V3=0),0,N3/V3) | AM3: =IF(OR(V3="",V3=0),0,1) | AN3: =IF(OR(E3="",F3=""),0,NETWORKDAYS(E3,F3,Ref!$K$2:$K$42)) | AO3: =IF(L3="Renewal",1,0) | AP3: =AC3*AD3 | AQ3: =IF(AND(G3<>"",'Historical Score'!$C$6<>""),IF(G3='Historical Score'!$C$6,1,0),0) | AR3: =IF(AND(L3<>"",'Historical Score'!$C$5<>""),IF(L3='Historical Score'!$C$5,1,0),0) | AS3: =IF(AND(Y3<>"",'Historical Score'!$C$7<>""),IF(Y3='Historical Score'!$C$7,1,0),0) | AT3: =IF(AND(K3<>"",'Historical Score'!$C$8<>""),IF(K3='Historical Score'!$C$8,1,0),0) | BA3: =IF(AD3=1,(AR3*'Historical Score'!$K$29+1-'Historical Score'!$K$29)*(AT3*'Historical Score'!$L$29+1-'Historical Score'!$L$29)*(AS3*'Historical Score'!$M$29+1-'Historical Score'!$M$29)*(AQ3*'Historical Score'!$N$29+1-'Historical Score'!$N$29),0)
A4: 5674144092 | B4: DALE JOHNSON SOLE MBR | C4: LEVEL 4 TRANSPORT LLC | D4: Legal | E4: 45630 | F4: 45666 | G4: 2 | H4: 4213 | I4: 42 | J4: CA | K4: Liberty Bell Capital | L4: New Deal | M4: 1.49 | N4: 10000 | O4: 0 | P4: 14900 | Q4: 2421.25 | R4: 12478.75 | S4: 0.1625 | T4: 2.623 | U4: 5 | V4: 60000 | W4: 0.07 | X4: 43873 | Y4: =IF(I4="","No SIC",IFERROR(VLOOKUP(I4,Ref!$A$2:$B$65,2,FALSE()),"Unclassified")) | Z4: =IF(T4="","",IF(T4<12,"Daily","Weekly")) | AA4: =IF(T4="",0,IF(T4<12,T4*Controls!$B$13,T4*5)) | AB4: =IF(E4="",0,NETWORKDAYS(E4,Controls!$B$20,Ref!$K$2:$K$42)) | AC4: =IF(OR(AF4=1,AND(AA4>0,AB4>=Controls!$B$23*AA4)),1,0) | AD4: =IF(AND(E4<>"",E4>=Controls!$B$21,E4<=Controls!$B$22),1,0) | AE4: =IF(IFERROR(VLOOKUP(D4,Controls!$A$36:$E$46,2,FALSE()),"No")="Yes",1,0) | AF4: =IF(IFERROR(VLOOKUP(D4,Controls!$A$36:$E$46,3,FALSE()),"No")="Yes",1,0) | AG4: =IF(IFERROR(VLOOKUP(D4,Controls!$A$36:$E$46,4,FALSE()),"No")="Yes",1,0) | AH4: =IF(IFERROR(VLOOKUP(D4,Controls!$A$36:$E$46,5,FALSE()),"No")="Yes",1,0) | AI4: =IF(ISNUMBER(MATCH(D4,Controls!$A$36:$A$46,0)),1,0) | AJ4: =Q4-N4 | AK4: =IF(AE4=1,MAX(0,N4-Q4),0) | AL4: =IF(OR(V4="",V4=0),0,N4/V4) | AM4: =IF(OR(V4="",V4=0),0,1) | AN4: =IF(OR(E4="",F4=""),0,NETWORKDAYS(E4,F4,Ref!$K$2:$K$42)) | AO4: =IF(L4="Renewal",1,0) | AP4: =AC4*AD4 | AQ4: =IF(AND(G4<>"",'Historical Score'!$C$6<>""),IF(G4='Historical Score'!$C$6,1,0),0) | AR4: =IF(AND(L4<>"",'Historical Score'!$C$5<>""),IF(L4='Historical Score'!$C$5,1,0),0) | AS4: =IF(AND(Y4<>"",'Historical Score'!$C$7<>""),IF(Y4='Historical Score'!$C$7,1,0),0) | AT4: =IF(AND(K4<>"",'Historical Score'!$C$8<>""),IF(K4='Historical Score'!$C$8,1,0),0) | BA4: =IF(AD4=1,(AR4*'Historical Score'!$K$29+1-'Historical Score'!$K$29)*(AT4*'Historical Score'!$L$29+1-'Historical Score'!$L$29)*(AS4*'Historical Score'!$M$29+1-'Historical Score'!$M$29)*(AQ4*'Historical Score'!$N$29+1-'Historical Score'!$N$29),0)
A5: 5674144406 | B5: Lupotec | C5: LUPOTEC INC | D5: Legal | E5: 45632 | F5: 45666 | G5: 2 | H5: 2821 | I5: 28 | J5: CA | K5: Fidelity Funding | L5: New Deal | M5: 1.49 | N5: 20000 | O5: 0 | P5: 29800 | Q5: 3140 | R5: 26660 | S5: 0.10536913 | T5: 3.279 | U5: 6 | V5: 80000 | W5: 0.09 | X5: 44539 | Y5: =IF(I5="","No SIC",IFERROR(VLOOKUP(I5,Ref!$A$2:$B$65,2,FALSE()),"Unclassified")) | Z5: =IF(T5="","",IF(T5<12,"Daily","Weekly")) | AA5: =IF(T5="",0,IF(T5<12,T5*Controls!$B$13,T5*5)) | AB5: =IF(E5="",0,NETWORKDAYS(E5,Controls!$B$20,Ref!$K$2:$K$42)) | AC5: =IF(OR(AF5=1,AND(AA5>0,AB5>=Controls!$B$23*AA5)),1,0) | AD5: =IF(AND(E5<>"",E5>=Controls!$B$21,E5<=Controls!$B$22),1,0) | AE5: =IF(IFERROR(VLOOKUP(D5,Controls!$A$36:$E$46,2,FALSE()),"No")="Yes",1,0) | AF5: =IF(IFERROR(VLOOKUP(D5,Controls!$A$36:$E$46,3,FALSE()),"No")="Yes",1,0) | AG5: =IF(IFERROR(VLOOKUP(D5,Controls!$A$36:$E$46,4,FALSE()),"No")="Yes",1,0) | AH5: =IF(IFERROR(VLOOKUP(D5,Controls!$A$36:$E$46,5,FALSE()),"No")="Yes",1,0) | AI5: =IF(ISNUMBER(MATCH(D5,Controls!$A$36:$A$46,0)),1,0) | AJ5: =Q5-N5 | AK5: =IF(AE5=1,MAX(0,N5-Q5),0) | AL5: =IF(OR(V5="",V5=0),0,N5/V5) | AM5: =IF(OR(V5="",V5=0),0,1) | AN5: =IF(OR(E5="",F5=""),0,NETWORKDAYS(E5,F5,Ref!$K$2:$K$42)) | AO5: =IF(L5="Renewal",1,0) | AP5: =AC5*AD5 | AQ5: =IF(AND(G5<>"",'Historical Score'!$C$6<>""),IF(G5='Historical Score'!$C$6,1,0),0) | AR5: =IF(AND(L5<>"",'Historical Score'!$C$5<>""),IF(L5='Historical Score'!$C$5,1,0),0) | AS5: =IF(AND(Y5<>"",'Historical Score'!$C$7<>""),IF(Y5='Historical Score'!$C$7,1,0),0) | AT5: =IF(AND(K5<>"",'Historical Score'!$C$8<>""),IF(K5='Historical Score'!$C$8,1,0),0) | BA5: =IF(AD5=1,(AR5*'Historical Score'!$K$29+1-'Historical Score'!$K$29)*(AT5*'Historical Score'!$L$29+1-'Historical Score'!$L$29)*(AS5*'Historical Score'!$M$29+1-'Historical Score'!$M$29)*(AQ5*'Historical Score'!$N$29+1-'Historical Score'!$N$29),0)
A6: 5674144409 | B6: AWK ENGINEERING & TRADING LLC | C6: AWK ENGINEERING & TRADING LLC | D6: Legal | E6: 45632 | F6: 45707 | G6: 3 | H6: 8711 | I6: 87 | J6: CA | K6: J Capital Solutions | L6: New Deal | M6: 1.49 | N6: 6000 | O6: 840 | P6: 8940 | Q6: 2136.24 | R6: 6803.76 | S6: 0.23895302 | T6: 3.705 | U6: 12 | V6: 20000 | W6: 0.04 | X6: 44471 | Y6: =IF(I6="","No SIC",IFERROR(VLOOKUP(I6,Ref!$A$2:$B$65,2,FALSE()),"Unclassified")) | Z6: =IF(T6="","",IF(T6<12,"Daily","Weekly")) | AA6: =IF(T6="",0,IF(T6<12,T6*Controls!$B$13,T6*5)) | AB6: =IF(E6="",0,NETWORKDAYS(E6,Controls!$B$20,Ref!$K$2:$K$42)) | AC6: =IF(OR(AF6=1,AND(AA6>0,AB6>=Controls!$B$23*AA6)),1,0) | AD6: =IF(AND(E6<>"",E6>=Controls!$B$21,E6<=Controls!$B$22),1,0) | AE6: =IF(IFERROR(VLOOKUP(D6,Controls!$A$36:$E$46,2,FALSE()),"No")="Yes",1,0) | AF6: =IF(IFERROR(VLOOKUP(D6,Controls!$A$36:$E$46,3,FALSE()),"No")="Yes",1,0) | AG6: =IF(IFERROR(VLOOKUP(D6,Controls!$A$36:$E$46,4,FALSE()),"No")="Yes",1,0) | AH6: =IF(IFERROR(VLOOKUP(D6,Controls!$A$36:$E$46,5,FALSE()),"No")="Yes",1,0) | AI6: =IF(ISNUMBER(MATCH(D6,Controls!$A$36:$A$46,0)),1,0) | AJ6: =Q6-N6 | AK6: =IF(AE6=1,MAX(0,N6-Q6),0) | AL6: =IF(OR(V6="",V6=0),0,N6/V6) | AM6: =IF(OR(V6="",V6=0),0,1) | AN6: =IF(OR(E6="",F6=""),0,NETWORKDAYS(E6,F6,Ref!$K$2:$K$42)) | AO6: =IF(L6="Renewal",1,0) | AP6: =AC6*AD6 | AQ6: =IF(AND(G6<>"",'Historical Score'!$C$6<>""),IF(G6='Historical Score'!$C$6,1,0),0) | AR6: =IF(AND(L6<>"",'Historical Score'!$C$5<>""),IF(L6='Historical Score'!$C$5,1,0),0) | AS6: =IF(AND(Y6<>"",'Historical Score'!$C$7<>""),IF(Y6='Historical Score'!$C$7,1,0),0) | AT6: =IF(AND(K6<>"",'Historical Score'!$C$8<>""),IF(K6='Historical Score'!$C$8,1,0),0) | BA6: =IF(AD6=1,(AR6*'Historical Score'!$K$29+1-'Historical Score'!$K$29)*(AT6*'Historical Score'!$L$29+1-'Historical Score'!$L$29)*(AS6*'Historical Score'!$M$29+1-'Historical Score'!$M$29)*(AQ6*'Historical Score'!$N$29+1-'Historical Score'!$N$29),0)
A7: 5674145076 | B7: GLOBAL RESEARCH CONSULTANTS, LLC | C7: GLOBAL RESEARCH CONSULTANTS, LLC | D7: Closed | E7: 45638 | F7: 45755 | G7: 2 | H7: 8748 | I7: 87 | J7: GA | K7: Secure Capital Solutions 7 | L7: New Deal | M7: 1.49 | N7: 5000 | O7: 700 | P7: 7450 | Q7: 7450 | R7: 0 | S7: 1 | T7: 2.538 | U7: 0 | V7: 100000 | W7: 0.09 | X7: 44305 | Y7: =IF(I7="","No SIC",IFERROR(VLOOKUP(I7,Ref!$A$2:$B$65,2,FALSE()),"Unclassified")) | Z7: =IF(T7="","",IF(T7<12,"Daily","Weekly")) | AA7: =IF(T7="",0,IF(T7<12,T7*Controls!$B$13,T7*5)) | AB7: =IF(E7="",0,NETWORKDAYS(E7,Controls!$B$20,Ref!$K$2:$K$42)) | AC7: =IF(OR(AF7=1,AND(AA7>0,AB7>=Controls!$B$23*AA7)),1,0) | AD7: =IF(AND(E7<>"",E7>=Controls!$B$21,E7<=Controls!$B$22),1,0) | AE7: =IF(IFERROR(VLOOKUP(D7,Controls!$A$36:$E$46,2,FALSE()),"No")="Yes",1,0) | AF7: =IF(IFERROR(VLOOKUP(D7,Controls!$A$36:$E$46,3,FALSE()),"No")="Yes",1,0) | AG7: =IF(IFERROR(VLOOKUP(D7,Controls!$A$36:$E$46,4,FALSE()),"No")="Yes",1,0) | AH7: =IF(IFERROR(VLOOKUP(D7,Controls!$A$36:$E$46,5,FALSE()),"No")="Yes",1,0) | AI7: =IF(ISNUMBER(MATCH(D7,Controls!$A$36:$A$46,0)),1,0) | AJ7: =Q7-N7 | AK7: =IF(AE7=1,MAX(0,N7-Q7),0) | AL7: =IF(OR(V7="",V7=0),0,N7/V7) | AM7: =IF(OR(V7="",V7=0),0,1) | AN7: =IF(OR(E7="",F7=""),0,NETWORKDAYS(E7,F7,Ref!$K$2:$K$42)) | AO7: =IF(L7="Renewal",1,0) | AP7: =AC7*AD7 | AQ7: =IF(AND(G7<>"",'Historical Score'!$C$6<>""),IF(G7='Historical Score'!$C$6,1,0),0) | AR7: =IF(AND(L7<>"",'Historical Score'!$C$5<>""),IF(L7='Historical Score'!$C$5,1,0),0) | AS7: =IF(AND(Y7<>"",'Historical Score'!$C$7<>""),IF(Y7='Historical Score'!$C$7,1,0),0) | AT7: =IF(AND(K7<>"",'Historical Score'!$C$8<>""),IF(K7='Historical Score'!$C$8,1,0),0) | BA7: =IF(AD7=1,(AR7*'Historical Score'!$K$29+1-'Historical Score'!$K$29)*(AT7*'Historical Score'!$L$29+1-'Historical Score'!$L$29)*(AS7*'Historical Score'!$M$29+1-'Historical Score'!$M$29)*(AQ7*'Historical Score'!$N$29+1-'Historical Score'!$N$29),0)
A8: 5674146645 | B8: ELIZABETH CONVENIENT STORE & HAIR BRAIDING | C8: ELIZABETH CONVENIENT STORE & HAIR BRAIDING LLC | D8: Closed | E8: 45660 | F8: 45702 | G8: 5 | H8: 5411 | I8: 54 | J8: AZ | K8: ELITE FUNDING PARTNERS LLC 6 | L8: Renewal | M8: 1.4575 | N8: 4000 | O8: 560 | P8: 5830 | Q8: 5830 | R8: 0 | S8: 1 | T8: 1.967 | U8: 2 | V8: 250000 | W8: 0.04 | X8: 41745 | Y8: =IF(I8="","No SIC",IFERROR(VLOOKUP(I8,Ref!$A$2:$B$65,2,FALSE()),"Unclassified")) | Z8: =IF(T8="","",IF(T8<12,"Daily","Weekly")) | AA8: =IF(T8="",0,IF(T8<12,T8*Controls!$B$13,T8*5)) | AB8: =IF(E8="",0,NETWORKDAYS(E8,Controls!$B$20,Ref!$K$2:$K$42)) | AC8: =IF(OR(AF8=1,AND(AA8>0,AB8>=Controls!$B$23*AA8)),1,0) | AD8: =IF(AND(E8<>"",E8>=Controls!$B$21,E8<=Controls!$B$22),1,0) | AE8: =IF(IFERROR(VLOOKUP(D8,Controls!$A$36:$E$46,2,FALSE()),"No")="Yes",1,0) | AF8: =IF(IFERROR(VLOOKUP(D8,Controls!$A$36:$E$46,3,FALSE()),"No")="Yes",1,0) | AG8: =IF(IFERROR(VLOOKUP(D8,Controls!$A$36:$E$46,4,FALSE()),"No")="Yes",1,0) | AH8: =IF(IFERROR(VLOOKUP(D8,Controls!$A$36:$E$46,5,FALSE()),"No")="Yes",1,0) | AI8: =IF(ISNUMBER(MATCH(D8,Controls!$A$36:$A$46,0)),1,0) | AJ8: =Q8-N8 | AK8: =IF(AE8=1,MAX(0,N8-Q8),0) | AL8: =IF(OR(V8="",V8=0),0,N8/V8) | AM8: =IF(OR(V8="",V8=0),0,1) | AN8: =IF(OR(E8="",F8=""),0,NETWORKDAYS(E8,F8,Ref!$K$2:$K$42)) | AO8: =IF(L8="Renewal",1,0) | AP8: =AC8*AD8 | AQ8: =IF(AND(G8<>"",'Historical Score'!$C$6<>""),IF(G8='Historical Score'!$C$6,1,0),0) | AR8: =IF(AND(L8<>"",'Historical Score'!$C$5<>""),IF(L8='Historical Score'!$C$5,1,0),0) | AS8: =IF(AND(Y8<>"",'Historical Score'!$C$7<>""),IF(Y8='Historical Score'!$C$7,1,0),0) | AT8: =IF(AND(K8<>"",'Historical Score'!$C$8<>""),IF(K8='Historical Score'!$C$8,1,0),0) | BA8: =IF(AD8=1,(AR8*'Historical Score'!$K$29+1-'Historical Score'!$K$29)*(AT8*'Historical Score'!$L$29+1-'Historical Score'!$L$29)*(AS8*'Historical Score'!$M$29+1-'Historical Score'!$M$29)*(AQ8*'Historical Score'!$N$29+1-'Historical Score'!$N$29),0)
A9: 5674147185 | B9: Arete Gallery Inc | C9: Arete Gallery Inc | D9: Closed | E9: 45665 | F9: 45772 | G9: 4 | H9: 8412 | I9: 84 | J9: PA | K9: Pathway Catalyst | L9: New Deal | M9: 1.49 | N9: 3500 | O9: 490 | P9: 5215 | Q9: 5215 | R9: 0 | S9: 1 | T9: 1.937 | U9: 0 | W9: 0.15 | X9: 44105 | Y9: =IF(I9="","No SIC",IFERROR(VLOOKUP(I9,Ref!$A$2:$B$65,2,FALSE()),"Unclassified")) | Z9: =IF(T9="","",IF(T9<12,"Daily","Weekly")) | AA9: =IF(T9="",0,IF(T9<12,T9*Controls!$B$13,T9*5)) | AB9: =IF(E9="",0,NETWORKDAYS(E9,Controls!$B$20,Ref!$K$2:$K$42)) | AC9: =IF(OR(AF9=1,AND(AA9>0,AB9>=Controls!$B$23*AA9)),1,0) | AD9: =IF(AND(E9<>"",E9>=Controls!$B$21,E9<=Controls!$B$22),1,0) | AE9: =IF(IFERROR(VLOOKUP(D9,Controls!$A$36:$E$46,2,FALSE()),"No")="Yes",1,0) | AF9: =IF(IFERROR(VLOOKUP(D9,Controls!$A$36:$E$46,3,FALSE()),"No")="Yes",1,0) | AG9: =IF(IFERROR(VLOOKUP(D9,Controls!$A$36:$E$46,4,FALSE()),"No")="Yes",1,0) | AH9: =IF(IFERROR(VLOOKUP(D9,Controls!$A$36:$E$46,5,FALSE()),"No")="Yes",1,0) | AI9: =IF(ISNUMBER(MATCH(D9,Controls!$A$36:$A$46,0)),1,0) | AJ9: =Q9-N9 | AK9: =IF(AE9=1,MAX(0,N9-Q9),0) | AL9: =IF(OR(V9="",V9=0),0,N9/V9) | AM9: =IF(OR(V9="",V9=0),0,1) | AN9: =IF(OR(E9="",F9=""),0,NETWORKDAYS(E9,F9,Ref!$K$2:$K$42)) | AO9: =IF(L9="Renewal",1,0) | AP9: =AC9*AD9 | AQ9: =IF(AND(G9<>"",'Historical Score'!$C$6<>""),IF(G9='Historical Score'!$C$6,1,0),0) | AR9: =IF(AND(L9<>"",'Historical Score'!$C$5<>""),IF(L9='Historical Score'!$C$5,1,0),0) | AS9: =IF(AND(Y9<>"",'Historical Score'!$C$7<>""),IF(Y9='Historical Score'!$C$7,1,0),0) | AT9: =IF(AND(K9<>"",'Historical Score'!$C$8<>""),IF(K9='Historical Score'!$C$8,1,0),0) | BA9: =IF(AD9=1,(AR9*'Historical Score'!$K$29+1-'Historical Score'!$K$29)*(AT9*'Historical Score'!$L$29+1-'Historical Score'!$L$29)*(AS9*'Historical Score'!$M$29+1-'Historical Score'!$M$29)*(AQ9*'Historical Score'!$N$29+1-'Historical Score'!$N$29),0)
A10: 5674147188 | B10: S&E ENTERPRISE | C10: S&E ENTERPRISE LLC | D10: Closed | E10: 45666 | F10: 45722 | G10: 2 | H10: 6531 | I10: 65 | J10: RI | K10: Triumph Cap Fund | L10: New Deal | M10: 1.49 | N10: 5000 | O10: 700 | P10: 7450 | Q10: 7450 | R10: 0 | S10: 1 | T10: 2.443 | U10: 0 | W10: 0.06 | X10: 45005 | Y10: =IF(I10="","No SIC",IFERROR(VLOOKUP(I10,Ref!$A$2:$B$65,2,FALSE()),"Unclassified")) | Z10: =IF(T10="","",IF(T10<12,"Daily","Weekly")) | AA10: =IF(T10="",0,IF(T10<12,T10*Controls!$B$13,T10*5)) | AB10: =IF(E10="",0,NETWORKDAYS(E10,Controls!$B$20,Ref!$K$2:$K$42)) | AC10: =IF(OR(AF10=1,AND(AA10>0,AB10>=Controls!$B$23*AA10)),1,0) | AD10: =IF(AND(E10<>"",E10>=Controls!$B$21,E10<=Controls!$B$22),1,0) | AE10: =IF(IFERROR(VLOOKUP(D10,Controls!$A$36:$E$46,2,FALSE()),"No")="Yes",1,0) | AF10: =IF(IFERROR(VLOOKUP(D10,Controls!$A$36:$E$46,3,FALSE()),"No")="Yes",1,0) | AG10: =IF(IFERROR(VLOOKUP(D10,Controls!$A$36:$E$46,4,FALSE()),"No")="Yes",1,0) | AH10: =IF(IFERROR(VLOOKUP(D10,Controls!$A$36:$E$46,5,FALSE()),"No")="Yes",1,0) | AI10: =IF(ISNUMBER(MATCH(D10,Controls!$A$36:$A$46,0)),1,0) | AJ10: =Q10-N10 | AK10: =IF(AE10=1,MAX(0,N10-Q10),0) | AL10: =IF(OR(V10="",V10=0),0,N10/V10) | AM10: =IF(OR(V10="",V10=0),0,1) | AN10: =IF(OR(E10="",F10=""),0,NETWORKDAYS(E10,F10,Ref!$K$2:$K$42)) | AO10: =IF(L10="Renewal",1,0) | AP10: =AC10*AD10 | AQ10: =IF(AND(G10<>"",'Historical Score'!$C$6<>""),IF(G10='Historical Score'!$C$6,1,0),0) | AR10: =IF(AND(L10<>"",'Historical Score'!$C$5<>""),IF(L10='Historical Score'!$C$5,1,0),0) | AS10: =IF(AND(Y10<>"",'Historical Score'!$C$7<>""),IF(Y10='Historical Score'!$C$7,1,0),0) | AT10: =IF(AND(K10<>"",'Historical Score'!$C$8<>""),IF(K10='Historical Score'!$C$8,1,0),0) | BA10: =IF(AD10=1,(AR10*'Historical Score'!$K$29+1-'Historical Score'!$K$29)*(AT10*'Historical Score'!$L$29+1-'Historical Score'!$L$29)*(AS10*'Historical Score'!$M$29+1-'Historical Score'!$M$29)*(AQ10*'Historical Score'!$N$29+1-'Historical Score'!$N$29),0)
A11: 5674147393 | B11: Beeson Farms & Hauling LLC | C11: Beeson Farms & Hauling LLC | D11: Closed | E11: 45667 | F11: 45756 | G11: 5 | H11: 0191 | I11: 01 | J11: NC | K11: Key Capital Funding | L11: New Deal | M11: 1.49 | N11: 30000 | O11: 4200 | P11: 44700 | Q11: 44700 | R11: 0 | S11: 1 | T11: 20.19 | U11: 0 | W11: 0.05 | X11: 43579 | Y11: =IF(I11="","No SIC",IFERROR(VLOOKUP(I11,Ref!$A$2:$B$65,2,FALSE()),"Unclassified")) | Z11: =IF(T11="","",IF(T11<12,"Daily","Weekly")) | AA11: =IF(T11="",0,IF(T11<12,T11*Controls!$B$13,T11*5)) | AB11: =IF(E11="",0,NETWORKDAYS(E11,Controls!$B$20,Ref!$K$2:$K$42)) | AC11: =IF(OR(AF11=1,AND(AA11>0,AB11>=Controls!$B$23*AA11)),1,0) | AD11: =IF(AND(E11<>"",E11>=Controls!$B$21,E11<=Controls!$B$22),1,0) | AE11: =IF(IFERROR(VLOOKUP(D11,Controls!$A$36:$E$46,2,FALSE()),"No")="Yes",1,0) | AF11: =IF(IFERROR(VLOOKUP(D11,Controls!$A$36:$E$46,3,FALSE()),"No")="Yes",1,0) | AG11: =IF(IFERROR(VLOOKUP(D11,Controls!$A$36:$E$46,4,FALSE()),"No")="Yes",1,0) | AH11: =IF(IFERROR(VLOOKUP(D11,Controls!$A$36:$E$46,5,FALSE()),"No")="Yes",1,0) | AI11: =IF(ISNUMBER(MATCH(D11,Controls!$A$36:$A$46,0)),1,0) | AJ11: =Q11-N11 | AK11: =IF(AE11=1,MAX(0,N11-Q11),0) | AL11: =IF(OR(V11="",V11=0),0,N11/V11) | AM11: =IF(OR(V11="",V11=0),0,1) | AN11: =IF(OR(E11="",F11=""),0,NETWORKDAYS(E11,F11,Ref!$K$2:$K$42)) | AO11: =IF(L11="Renewal",1,0) | AP11: =AC11*AD11 | AQ11: =IF(AND(G11<>"",'Historical Score'!$C$6<>""),IF(G11='Historical Score'!$C$6,1,0),0) | AR11: =IF(AND(L11<>"",'Historical Score'!$C$5<>""),IF(L11='Historical Score'!$C$5,1,0),0) | AS11: =IF(AND(Y11<>"",'Historical Score'!$C$7<>""),IF(Y11='Historical Score'!$C$7,1,0),0) | AT11: =IF(AND(K11<>"",'Historical Score'!$C$8<>""),IF(K11='Historical Score'!$C$8,1,0),0) | BA11: =IF(AD11=1,(AR11*'Historical Score'!$K$29+1-'Historical Score'!$K$29)*(AT11*'Historical Score'!$L$29+1-'Historical Score'!$L$29)*(AS11*'Historical Score'!$M$29+1-'Historical Score'!$M$29)*(AQ11*'Historical Score'!$N$29+1-'Historical Score'!$N$29),0)
A12: 5674147441 | B12: SJ HOSPICE SERVICES | C12: SJ HOSPICE SERVICES LLC | D12: Closed | E12: 45670 | F12: 45783 | G12: 2 | H12: 8082 | I12: 80 | J12: TX | K12: ICB FUNDING | L12: New Deal | M12: 1.39 | N12: 8500 | O12: 765 | P12: 11815 | Q12: 11815 | R12: 0 | S12: 1 | T12: 2.539 | U12: 0 | W12: 0.04 | X12: 42892 | Y12: =IF(I12="","No SIC",IFERROR(VLOOKUP(I12,Ref!$A$2:$B$65,2,FALSE()),"Unclassified")) | Z12: =IF(T12="","",IF(T12<12,"Daily","Weekly")) | AA12: =IF(T12="",0,IF(T12<12,T12*Controls!$B$13,T12*5)) | AB12: =IF(E12="",0,NETWORKDAYS(E12,Controls!$B$20,Ref!$K$2:$K$42)) | AC12: =IF(OR(AF12=1,AND(AA12>0,AB12>=Controls!$B$23*AA12)),1,0) | AD12: =IF(AND(E12<>"",E12>=Controls!$B$21,E12<=Controls!$B$22),1,0) | AE12: =IF(IFERROR(VLOOKUP(D12,Controls!$A$36:$E$46,2,FALSE()),"No")="Yes",1,0) | AF12: =IF(IFERROR(VLOOKUP(D12,Controls!$A$36:$E$46,3,FALSE()),"No")="Yes",1,0) | AG12: =IF(IFERROR(VLOOKUP(D12,Controls!$A$36:$E$46,4,FALSE()),"No")="Yes",1,0) | AH12: =IF(IFERROR(VLOOKUP(D12,Controls!$A$36:$E$46,5,FALSE()),"No")="Yes",1,0) | AI12: =IF(ISNUMBER(MATCH(D12,Controls!$A$36:$A$46,0)),1,0) | AJ12: =Q12-N12 | AK12: =IF(AE12=1,MAX(0,N12-Q12),0) | AL12: =IF(OR(V12="",V12=0),0,N12/V12) | AM12: =IF(OR(V12="",V12=0),0,1) | AN12: =IF(OR(E12="",F12=""),0,NETWORKDAYS(E12,F12,Ref!$K$2:$K$42)) | AO12: =IF(L12="Renewal",1,0) | AP12: =AC12*AD12 | AQ12: =IF(AND(G12<>"",'Historical Score'!$C$6<>""),IF(G12='Historical Score'!$C$6,1,0),0) | AR12: =IF(AND(L12<>"",'Historical Score'!$C$5<>""),IF(L12='Historical Score'!$C$5,1,0),0) | AS12: =IF(AND(Y12<>"",'Historical Score'!$C$7<>""),IF(Y12='Historical Score'!$C$7,1,0),0) | AT12: =IF(AND(K12<>"",'Historical Score'!$C$8<>""),IF(K12='Historical Score'!$C$8,1,0),0) | BA12: =IF(AD12=1,(AR12*'Historical Score'!$K$29+1-'Historical Score'!$K$29)*(AT12*'Historical Score'!$L$29+1-'Historical Score'!$L$29)*(AS12*'Historical Score'!$M$29+1-'Historical Score'!$M$29)*(AQ12*'Historical Score'!$N$29+1-'Historical Score'!$N$29),0)
A13: 5674147491 | B13: ROPP JERSEY CHEESE LLC | C13: ROPP JERSEY CHEESE LLC | D13: Legal | E13: 45670 | F13: 46234 | G13: 1 | H13: 5812 | I13: 58 | J13: IL | K13: ROYAL FUNDING GROUP | L13: New Deal | M13: 1.49 | N13: 12000 | O13: 1680 | P13: 17880 | Q13: 9022 | R13: 8858 | S13: 0.50458613 | T13: 2.706 | U13: 12 | W13: 0.13 | X13: 38507 | Y13: =IF(I13="","No SIC",IFERROR(VLOOKUP(I13,Ref!$A$2:$B$65,2,FALSE()),"Unclassified")) | Z13: =IF(T13="","",IF(T13<12,"Daily","Weekly")) | AA13: =IF(T13="",0,IF(T13<12,T13*Controls!$B$13,T13*5)) | AB13: =IF(E13="",0,NETWORKDAYS(E13,Controls!$B$20,Ref!$K$2:$K$42)) | AC13: =IF(OR(AF13=1,AND(AA13>0,AB13>=Controls!$B$23*AA13)),1,0) | AD13: =IF(AND(E13<>"",E13>=Controls!$B$21,E13<=Controls!$B$22),1,0) | AE13: =IF(IFERROR(VLOOKUP(D13,Controls!$A$36:$E$46,2,FALSE()),"No")="Yes",1,0) | AF13: =IF(IFERROR(VLOOKUP(D13,Controls!$A$36:$E$46,3,FALSE()),"No")="Yes",1,0) | AG13: =IF(IFERROR(VLOOKUP(D13,Controls!$A$36:$E$46,4,FALSE()),"No")="Yes",1,0) | AH13: =IF(IFERROR(VLOOKUP(D13,Controls!$A$36:$E$46,5,FALSE()),"No")="Yes",1,0) | AI13: =IF(ISNUMBER(MATCH(D13,Controls!$A$36:$A$46,0)),1,0) | AJ13: =Q13-N13 | AK13: =IF(AE13=1,MAX(0,N13-Q13),0) | AL13: =IF(OR(V13="",V13=0),0,N13/V13) | AM13: =IF(OR(V13="",V13=0),0,1) | AN13: =IF(OR(E13="",F13=""),0,NETWORKDAYS(E13,F13,Ref!$K$2:$K$42)) | AO13: =IF(L13="Renewal",1,0) | AP13: =AC13*AD13 | AQ13: =IF(AND(G13<>"",'Historical Score'!$C$6<>""),IF(G13='Historical Score'!$C$6,1,0),0) | AR13: =IF(AND(L13<>"",'Historical Score'!$C$5<>""),IF(L13='Historical Score'!$C$5,1,0),0) | AS13: =IF(AND(Y13<>"",'Historical Score'!$C$7<>""),IF(Y13='Historical Score'!$C$7,1,0),0) | AT13: =IF(AND(K13<>"",'Historical Score'!$C$8<>""),IF(K13='Historical Score'!$C$8,1,0),0) | BA13: =IF(AD13=1,(AR13*'Historical Score'!$K$29+1-'Historical Score'!$K$29)*(AT13*'Historical Score'!$L$29+1-'Historical Score'!$L$29)*(AS13*'Historical Score'!$M$29+1-'Historical Score'!$M$29)*(AQ13*'Historical Score'!$N$29+1-'Historical Score'!$N$29),0)
A14: 5674147495 | B14: ISHI MEDICAL EQUIPMENT & SUPPLIES INC Calle Primera | C14: ISHI MEDICAL EQUIPMENT & SUPPLIES INC Calle Primera | D14: Legal | E14: 45670 | F14: 45721 | G14: 3 | H14: 5047 | I14: 50 | J14: CA | K14: Key Capital Funding | L14: New Deal | M14: 1.49 | N14: 12000 | O14: 1680 | P14: 17880 | Q14: 3184 | R14: 14696 | S14: 0.17807606 | T14: 2.951 | U14: 15 | W14: 0.09 | X14: 38507 | Y14: =IF(I14="","No SIC",IFERROR(VLOOKUP(I14,Ref!$A$2:$B$65,2,FALSE()),"Unclassified")) | Z14: =IF(T14="","",IF(T14<12,"Daily","Weekly")) | AA14: =IF(T14="",0,IF(T14<12,T14*Controls!$B$13,T14*5)) | AB14: =IF(E14="",0,NETWORKDAYS(E14,Controls!$B$20,Ref!$K$2:$K$42)) | AC14: =IF(OR(AF14=1,AND(AA14>0,AB14>=Controls!$B$23*AA14)),1,0) | AD14: =IF(AND(E14<>"",E14>=Controls!$B$21,E14<=Controls!$B$22),1,0) | AE14: =IF(IFERROR(VLOOKUP(D14,Controls!$A$36:$E$46,2,FALSE()),"No")="Yes",1,0) | AF14: =IF(IFERROR(VLOOKUP(D14,Controls!$A$36:$E$46,3,FALSE()),"No")="Yes",1,0) | AG14: =IF(IFERROR(VLOOKUP(D14,Controls!$A$36:$E$46,4,FALSE()),"No")="Yes",1,0) | AH14: =IF(IFERROR(VLOOKUP(D14,Controls!$A$36:$E$46,5,FALSE()),"No")="Yes",1,0) | AI14: =IF(ISNUMBER(MATCH(D14,Controls!$A$36:$A$46,0)),1,0) | AJ14: =Q14-N14 | AK14: =IF(AE14=1,MAX(0,N14-Q14),0) | AL14: =IF(OR(V14="",V14=0),0,N14/V14) | AM14: =IF(OR(V14="",V14=0),0,1) | AN14: =IF(OR(E14="",F14=""),0,NETWORKDAYS(E14,F14,Ref!$K$2:$K$42)) | AO14: =IF(L14="Renewal",1,0) | AP14: =AC14*AD14 | AQ14: =IF(AND(G14<>"",'Historical Score'!$C$6<>""),IF(G14='Historical Score'!$C$6,1,0),0) | AR14: =IF(AND(L14<>"",'Historical Score'!$C$5<>""),IF(L14='Historical Score'!$C$5,1,0),0) | AS14: =IF(AND(Y14<>"",'Historical Score'!$C$7<>""),IF(Y14='Historical Score'!$C$7,1,0),0) | AT14: =IF(AND(K14<>"",'Historical Score'!$C$8<>""),IF(K14='Historical Score'!$C$8,1,0),0) | BA14: =IF(AD14=1,(AR14*'Historical Score'!$K$29+1-'Historical Score'!$K$29)*(AT14*'Historical Score'!$L$29+1-'Historical Score'!$L$29)*(AS14*'Historical Score'!$M$29+1-'Historical Score'!$M$29)*(AQ14*'Historical Score'!$N$29+1-'Historical Score'!$N$29),0)
A15: 5674147827 | B15: Delta Security Services LLC | C15: Delta Security Services LLC | D15: Closed | E15: 45673 | F15: 45791 | G15: 1 | H15: 7382 | I15: 73 | J15: WA | K15: First Path Capital | L15: Renewal | M15: 1.49 | N15: 5000 | O15: 700 | P15: 7450 | Q15: 7450 | R15: 0 | S15: 1 | T15: 2.623 | U15: 0 | W15: 0.06 | Y15: =IF(I15="","No SIC",IFERROR(VLOOKUP(I15,Ref!$A$2:$B$65,2,FALSE()),"Unclassified")) | Z15: =IF(T15="","",IF(T15<12,"Daily","Weekly")) | AA15: =IF(T15="",0,IF(T15<12,T15*Controls!$B$13,T15*5)) | AB15: =IF(E15="",0,NETWORKDAYS(E15,Controls!$B$20,Ref!$K$2:$K$42)) | AC15: =IF(OR(AF15=1,AND(AA15>0,AB15>=Controls!$B$23*AA15)),1,0) | AD15: =IF(AND(E15<>"",E15>=Controls!$B$21,E15<=Controls!$B$22),1,0) | AE15: =IF(IFERROR(VLOOKUP(D15,Controls!$A$36:$E$46,2,FALSE()),"No")="Yes",1,0) | AF15: =IF(IFERROR(VLOOKUP(D15,Controls!$A$36:$E$46,3,FALSE()),"No")="Yes",1,0) | AG15: =IF(IFERROR(VLOOKUP(D15,Controls!$A$36:$E$46,4,FALSE()),"No")="Yes",1,0) | AH15: =IF(IFERROR(VLOOKUP(D15,Controls!$A$36:$E$46,5,FALSE()),"No")="Yes",1,0) | AI15: =IF(ISNUMBER(MATCH(D15,Controls!$A$36:$A$46,0)),1,0) | AJ15: =Q15-N15 | AK15: =IF(AE15=1,MAX(0,N15-Q15),0) | AL15: =IF(OR(V15="",V15=0),0,N15/V15) | AM15: =IF(OR(V15="",V15=0),0,1) | AN15: =IF(OR(E15="",F15=""),0,NETWORKDAYS(E15,F15,Ref!$K$2:$K$42)) | AO15: =IF(L15="Renewal",1,0) | AP15: =AC15*AD15 | AQ15: =IF(AND(G15<>"",'Historical Score'!$C$6<>""),IF(G15='Historical Score'!$C$6,1,0),0) | AR15: =IF(AND(L15<>"",'Historical Score'!$C$5<>""),IF(L15='Historical Score'!$C$5,1,0),0) | AS15: =IF(AND(Y15<>"",'Historical Score'!$C$7<>""),IF(Y15='Historical Score'!$C$7,1,0),0) | AT15: =IF(AND(K15<>"",'Historical Score'!$C$8<>""),IF(K15='Historical Score'!$C$8,1,0),0) | BA15: =IF(AD15=1,(AR15*'Historical Score'!$K$29+1-'Historical Score'!$K$29)*(AT15*'Historical Score'!$L$29+1-'Historical Score'!$L$29)*(AS15*'Historical Score'!$M$29+1-'Historical Score'!$M$29)*(AQ15*'Historical Score'!$N$29+1-'Historical Score'!$N$29),0)
A16: 5674148218 | B16: LTV EVENTS LLC | C16: LTV EVENTS LLC | D16: Closed | E16: 45679 | F16: 45768 | G16: 7 | H16: 7299 | I16: 72 | J16: IL | K16: Redline Capital | L16: New Deal | M16: 1.47 | N16: 4500 | O16: 630 | P16: 6615 | Q16: 6615 | R16: 0 | S16: 1 | T16: 1.928 | U16: 0 | W16: 0.083 | X16: 44256 | Y16: =IF(I16="","No SIC",IFERROR(VLOOKUP(I16,Ref!$A$2:$B$65,2,FALSE()),"Unclassified")) | Z16: =IF(T16="","",IF(T16<12,"Daily","Weekly")) | AA16: =IF(T16="",0,IF(T16<12,T16*Controls!$B$13,T16*5)) | AB16: =IF(E16="",0,NETWORKDAYS(E16,Controls!$B$20,Ref!$K$2:$K$42)) | AC16: =IF(OR(AF16=1,AND(AA16>0,AB16>=Controls!$B$23*AA16)),1,0) | AD16: =IF(AND(E16<>"",E16>=Controls!$B$21,E16<=Controls!$B$22),1,0) | AE16: =IF(IFERROR(VLOOKUP(D16,Controls!$A$36:$E$46,2,FALSE()),"No")="Yes",1,0) | AF16: =IF(IFERROR(VLOOKUP(D16,Controls!$A$36:$E$46,3,FALSE()),"No")="Yes",1,0) | AG16: =IF(IFERROR(VLOOKUP(D16,Controls!$A$36:$E$46,4,FALSE()),"No")="Yes",1,0) | AH16: =IF(IFERROR(VLOOKUP(D16,Controls!$A$36:$E$46,5,FALSE()),"No")="Yes",1,0) | AI16: =IF(ISNUMBER(MATCH(D16,Controls!$A$36:$A$46,0)),1,0) | AJ16: =Q16-N16 | AK16: =IF(AE16=1,MAX(0,N16-Q16),0) | AL16: =IF(OR(V16="",V16=0),0,N16/V16) | AM16: =IF(OR(V16="",V16=0),0,1) | AN16: =IF(OR(E16="",F16=""),0,NETWORKDAYS(E16,F16,Ref!$K$2:$K$42)) | AO16: =IF(L16="Renewal",1,0) | AP16: =AC16*AD16 | AQ16: =IF(AND(G16<>"",'Historical Score'!$C$6<>""),IF(G16='Historical Score'!$C$6,1,0),0) | AR16: =IF(AND(L16<>"",'Historical Score'!$C$5<>""),IF(L16='Historical Score'!$C$5,1,0),0) | AS16: =IF(AND(Y16<>"",'Historical Score'!$C$7<>""),IF(Y16='Historical Score'!$C$7,1,0),0) | AT16: =IF(AND(K16<>"",'Historical Score'!$C$8<>""),IF(K16='Historical Score'!$C$8,1,0),0) | BA16: =IF(AD16=1,(AR16*'Historical Score'!$K$29+1-'Historical Score'!$K$29)*(AT16*'Historical Score'!$L$29+1-'Historical Score'!$L$29)*(AS16*'Historical Score'!$M$29+1-'Historical Score'!$M$29)*(AQ16*'Historical Score'!$N$29+1-'Historical Score'!$N$29),0)
A17: 5674148220 | B17: The Tailors | C17: Jojo's Sewing Co. LLC | D17: Legal | E17: 45679 | F17: 45735 | G17: 2 | H17: 5699 | I17: 56 | J17: MI | K17: Platform Funding | L17: New Deal | M17: 1.49 | N17: 4500 | O17: 630 | P17: 6705 | Q17: 2863.14 | R17: 3841.86 | S17: 0.42701566 | T17: 2.459 | U17: 7 | W17: 0.11 | X17: 44927 | Y17: =IF(I17="","No SIC",IFERROR(VLOOKUP(I17,Ref!$A$2:$B$65,2,FALSE()),"Unclassified")) | Z17: =IF(T17="","",IF(T17<12,"Daily","Weekly")) | AA17: =IF(T17="",0,IF(T17<12,T17*Controls!$B$13,T17*5)) | AB17: =IF(E17="",0,NETWORKDAYS(E17,Controls!$B$20,Ref!$K$2:$K$42)) | AC17: =IF(OR(AF17=1,AND(AA17>0,AB17>=Controls!$B$23*AA17)),1,0) | AD17: =IF(AND(E17<>"",E17>=Controls!$B$21,E17<=Controls!$B$22),1,0) | AE17: =IF(IFERROR(VLOOKUP(D17,Controls!$A$36:$E$46,2,FALSE()),"No")="Yes",1,0) | AF17: =IF(IFERROR(VLOOKUP(D17,Controls!$A$36:$E$46,3,FALSE()),"No")="Yes",1,0) | AG17: =IF(IFERROR(VLOOKUP(D17,Controls!$A$36:$E$46,4,FALSE()),"No")="Yes",1,0) | AH17: =IF(IFERROR(VLOOKUP(D17,Controls!$A$36:$E$46,5,FALSE()),"No")="Yes",1,0) | AI17: =IF(ISNUMBER(MATCH(D17,Controls!$A$36:$A$46,0)),1,0) | AJ17: =Q17-N17 | AK17: =IF(AE17=1,MAX(0,N17-Q17),0) | AL17: =IF(OR(V17="",V17=0),0,N17/V17) | AM17: =IF(OR(V17="",V17=0),0,1) | AN17: =IF(OR(E17="",F17=""),0,NETWORKDAYS(E17,F17,Ref!$K$2:$K$42)) | AO17: =IF(L17="Renewal",1,0) | AP17: =AC17*AD17 | AQ17: =IF(AND(G17<>"",'Historical Score'!$C$6<>""),IF(G17='Historical Score'!$C$6,1,0),0) | AR17: =IF(AND(L17<>"",'Historical Score'!$C$5<>""),IF(L17='Historical Score'!$C$5,1,0),0) | AS17: =IF(AND(Y17<>"",'Historical Score'!$C$7<>""),IF(Y17='Historical Score'!$C$7,1,0),0) | AT17: =IF(AND(K17<>"",'Historical Score'!$C$8<>""),IF(K17='Historical Score'!$C$8,1,0),0) | BA17: =IF(AD17=1,(AR17*'Historical Score'!$K$29+1-'Historical Score'!$K$29)*(AT17*'Historical Score'!$L$29+1-'Historical Score'!$L$29)*(AS17*'Historical Score'!$M$29+1-'Historical Score'!$M$29)*(AQ17*'Historical Score'!$N$29+1-'Historical Score'!$N$29),0)
A18: 5674149050 | B18: Bright Future Academy | C18: Bright Future Academy | D18: Closed | E18: 45686 | F18: 45799 | G18: 4 | H18: 8351 | I18: 83 | J18: MN | K18: Key Capital Funding | L18: Renewal | M18: 1.41 | N18: 5000 | O18: 500 | P18: 7050 | Q18: 7050 | R18: 0 | S18: 1 | T18: 2.295 | U18: 4 | W18: 0.12 | X18: 43617 | Y18: =IF(I18="","No SIC",IFERROR(VLOOKUP(I18,Ref!$A$2:$B$65,2,FALSE()),"Unclassified")) | Z18: =IF(T18="","",IF(T18<12,"Daily","Weekly")) | AA18: =IF(T18="",0,IF(T18<12,T18*Controls!$B$13,T18*5)) | AB18: =IF(E18="",0,NETWORKDAYS(E18,Controls!$B$20,Ref!$K$2:$K$42)) | AC18: =IF(OR(AF18=1,AND(AA18>0,AB18>=Controls!$B$23*AA18)),1,0) | AD18: =IF(AND(E18<>"",E18>=Controls!$B$21,E18<=Controls!$B$22),1,0) | AE18: =IF(IFERROR(VLOOKUP(D18,Controls!$A$36:$E$46,2,FALSE()),"No")="Yes",1,0) | AF18: =IF(IFERROR(VLOOKUP(D18,Controls!$A$36:$E$46,3,FALSE()),"No")="Yes",1,0) | AG18: =IF(IFERROR(VLOOKUP(D18,Controls!$A$36:$E$46,4,FALSE()),"No")="Yes",1,0) | AH18: =IF(IFERROR(VLOOKUP(D18,Controls!$A$36:$E$46,5,FALSE()),"No")="Yes",1,0) | AI18: =IF(ISNUMBER(MATCH(D18,Controls!$A$36:$A$46,0)),1,0) | AJ18: =Q18-N18 | AK18: =IF(AE18=1,MAX(0,N18-Q18),0) | AL18: =IF(OR(V18="",V18=0),0,N18/V18) | AM18: =IF(OR(V18="",V18=0),0,1) | AN18: =IF(OR(E18="",F18=""),0,NETWORKDAYS(E18,F18,Ref!$K$2:$K$42)) | AO18: =IF(L18="Renewal",1,0) | AP18: =AC18*AD18 | AQ18: =IF(AND(G18<>"",'Historical Score'!$C$6<>""),IF(G18='Historical Score'!$C$6,1,0),0) | AR18: =IF(AND(L18<>"",'Historical Score'!$C$5<>""),IF(L18='Historical Score'!$C$5,1,0),0) | AS18: =IF(AND(Y18<>"",'Historical Score'!$C$7<>""),IF(Y18='Historical Score'!$C$7,1,0),0) | AT18: =IF(AND(K18<>"",'Historical Score'!$C$8<>""),IF(K18='Historical Score'!$C$8,1,0),0) | BA18: =IF(AD18=1,(AR18*'Historical Score'!$K$29+1-'Historical Score'!$K$29)*(AT18*'Historical Score'!$L$29+1-'Historical Score'!$L$29)*(AS18*'Historical Score'!$M$29+1-'Historical Score'!$M$29)*(AQ18*'Historical Score'!$N$29+1-'Historical Score'!$N$29),0)
A19: 5674149117 | B19: PRADO SALES | C19: P & F Family Construction | D19: Closed | E19: 45687 | F19: 45776 | G19: 6 | H19: 1521 | I19: 15 | J19: CA | K19: Merchant ReFi | L19: New Deal | M19: 1.49 | N19: 6000 | O19: 840 | P19: 8940 | Q19: 8940 | R19: 0 | S19: 1 | T19: 2.623 | U19: 0 | W19: 0.0835 | X19: 43739 | Y19: =IF(I19="","No SIC",IFERROR(VLOOKUP(I19,Ref!$A$2:$B$65,2,FALSE()),"Unclassified")) | Z19: =IF(T19="","",IF(T19<12,"Daily","Weekly")) | AA19: =IF(T19="",0,IF(T19<12,T19*Controls!$B$13,T19*5)) | AB19: =IF(E19="",0,NETWORKDAYS(E19,Controls!$B$20,Ref!$K$2:$K$42)) | AC19: =IF(OR(AF19=1,AND(AA19>0,AB19>=Controls!$B$23*AA19)),1,0) | AD19: =IF(AND(E19<>"",E19>=Controls!$B$21,E19<=Controls!$B$22),1,0) | AE19: =IF(IFERROR(VLOOKUP(D19,Controls!$A$36:$E$46,2,FALSE()),"No")="Yes",1,0) | AF19: =IF(IFERROR(VLOOKUP(D19,Controls!$A$36:$E$46,3,FALSE()),"No")="Yes",1,0) | AG19: =IF(IFERROR(VLOOKUP(D19,Controls!$A$36:$E$46,4,FALSE()),"No")="Yes",1,0) | AH19: =IF(IFERROR(VLOOKUP(D19,Controls!$A$36:$E$46,5,FALSE()),"No")="Yes",1,0) | AI19: =IF(ISNUMBER(MATCH(D19,Controls!$A$36:$A$46,0)),1,0) | AJ19: =Q19-N19 | AK19: =IF(AE19=1,MAX(0,N19-Q19),0) | AL19: =IF(OR(V19="",V19=0),0,N19/V19) | AM19: =IF(OR(V19="",V19=0),0,1) | AN19: =IF(OR(E19="",F19=""),0,NETWORKDAYS(E19,F19,Ref!$K$2:$K$42)) | AO19: =IF(L19="Renewal",1,0) | AP19: =AC19*AD19 | AQ19: =IF(AND(G19<>"",'Historical Score'!$C$6<>""),IF(G19='Historical Score'!$C$6,1,0),0) | AR19: =IF(AND(L19<>"",'Historical Score'!$C$5<>""),IF(L19='Historical Score'!$C$5,1,0),0) | AS19: =IF(AND(Y19<>"",'Historical Score'!$C$7<>""),IF(Y19='Historical Score'!$C$7,1,0),0) | AT19: =IF(AND(K19<>"",'Historical Score'!$C$8<>""),IF(K19='Historical Score'!$C$8,1,0),0) | BA19: =IF(AD19=1,(AR19*'Historical Score'!$K$29+1-'Historical Score'!$K$29)*(AT19*'Historical Score'!$L$29+1-'Historical Score'!$L$29)*(AS19*'Historical Score'!$M$29+1-'Historical Score'!$M$29)*(AQ19*'Historical Score'!$N$29+1-'Historical Score'!$N$29),0)
A20: 5674149282 | B20: The Garrison | C20: Garrison Restaurant & cocktail lounge llc | D20: Closed | E20: 45691 | F20: 45782 | G20: 1 | H20: 5812 | I20: 58 | J20: TX | K20: Platform Funding | L20: Renewal | M20: 1.35 | N20: 20000 | O20: 1400 | P20: 27000 | Q20: 27000 | R20: 0 | S20: 1 | T20: 2.623 | U20: 26 | W20: 0.0771 | X20: 44562 | Y20: =IF(I20="","No SIC",IFERROR(VLOOKUP(I20,Ref!$A$2:$B$65,2,FALSE()),"Unclassified")) | Z20: =IF(T20="","",IF(T20<12,"Daily","Weekly")) | AA20: =IF(T20="",0,IF(T20<12,T20*Controls!$B$13,T20*5)) | AB20: =IF(E20="",0,NETWORKDAYS(E20,Controls!$B$20,Ref!$K$2:$K$42)) | AC20: =IF(OR(AF20=1,AND(AA20>0,AB20>=Controls!$B$23*AA20)),1,0) | AD20: =IF(AND(E20<>"",E20>=Controls!$B$21,E20<=Controls!$B$22),1,0) | AE20: =IF(IFERROR(VLOOKUP(D20,Controls!$A$36:$E$46,2,FALSE()),"No")="Yes",1,0) | AF20: =IF(IFERROR(VLOOKUP(D20,Controls!$A$36:$E$46,3,FALSE()),"No")="Yes",1,0) | AG20: =IF(IFERROR(VLOOKUP(D20,Controls!$A$36:$E$46,4,FALSE()),"No")="Yes",1,0) | AH20: =IF(IFERROR(VLOOKUP(D20,Controls!$A$36:$E$46,5,FALSE()),"No")="Yes",1,0) | AI20: =IF(ISNUMBER(MATCH(D20,Controls!$A$36:$A$46,0)),1,0) | AJ20: =Q20-N20 | AK20: =IF(AE20=1,MAX(0,N20-Q20),0) | AL20: =IF(OR(V20="",V20=0),0,N20/V20) | AM20: =IF(OR(V20="",V20=0),0,1) | AN20: =IF(OR(E20="",F20=""),0,NETWORKDAYS(E20,F20,Ref!$K$2:$K$42)) | AO20: =IF(L20="Renewal",1,0) | AP20: =AC20*AD20 | AQ20: =IF(AND(G20<>"",'Historical Score'!$C$6<>""),IF(G20='Historical Score'!$C$6,1,0),0) | AR20: =IF(AND(L20<>"",'Historical Score'!$C$5<>""),IF(L20='Historical Score'!$C$5,1,0),0) | AS20: =IF(AND(Y20<>"",'Historical Score'!$C$7<>""),IF(Y20='Historical Score'!$C$7,1,0),0) | AT20: =IF(AND(K20<>"",'Historical Score'!$C$8<>""),IF(K20='Historical Score'!$C$8,1,0),0) | BA20: =IF(AD20=1,(AR20*'Historical Score'!$K$29+1-'Historical Score'!$K$29)*(AT20*'Historical Score'!$L$29+1-'Historical Score'!$L$29)*(AS20*'Historical Score'!$M$29+1-'Historical Score'!$M$29)*(AQ20*'Historical Score'!$N$29+1-'Historical Score'!$N$29),0)
A21: 5674149485 | B21: Cloud IX salon | C21: IX llc | D21: Closed | E21: 45692 | F21: 45783 | G21: 4 | H21: 7231 | I21: 72 | J21: FL | K21: GREYSTONE | L21: Renewal | M21: 1.49 | N21: 15000 | O21: 2100 | P21: 22350 | Q21: 22350 | R21: 0 | S21: 1 | T21: 2.459 | U21: 1 | W21: 0.0553 | X21: 45402 | Y21: =IF(I21="","No SIC",IFERROR(VLOOKUP(I21,Ref!$A$2:$B$65,2,FALSE()),"Unclassified")) | Z21: =IF(T21="","",IF(T21<12,"Daily","Weekly")) | AA21: =IF(T21="",0,IF(T21<12,T21*Controls!$B$13,T21*5)) | AB21: =IF(E21="",0,NETWORKDAYS(E21,Controls!$B$20,Ref!$K$2:$K$42)) | AC21: =IF(OR(AF21=1,AND(AA21>0,AB21>=Controls!$B$23*AA21)),1,0) | AD21: =IF(AND(E21<>"",E21>=Controls!$B$21,E21<=Controls!$B$22),1,0) | AE21: =IF(IFERROR(VLOOKUP(D21,Controls!$A$36:$E$46,2,FALSE()),"No")="Yes",1,0) | AF21: =IF(IFERROR(VLOOKUP(D21,Controls!$A$36:$E$46,3,FALSE()),"No")="Yes",1,0) | AG21: =IF(IFERROR(VLOOKUP(D21,Controls!$A$36:$E$46,4,FALSE()),"No")="Yes",1,0) | AH21: =IF(IFERROR(VLOOKUP(D21,Controls!$A$36:$E$46,5,FALSE()),"No")="Yes",1,0) | AI21: =IF(ISNUMBER(MATCH(D21,Controls!$A$36:$A$46,0)),1,0) | AJ21: =Q21-N21 | AK21: =IF(AE21=1,MAX(0,N21-Q21),0) | AL21: =IF(OR(V21="",V21=0),0,N21/V21) | AM21: =IF(OR(V21="",V21=0),0,1) | AN21: =IF(OR(E21="",F21=""),0,NETWORKDAYS(E21,F21,Ref!$K$2:$K$42)) | AO21: =IF(L21="Renewal",1,0) | AP21: =AC21*AD21 | AQ21: =IF(AND(G21<>"",'Historical Score'!$C$6<>""),IF(G21='Historical Score'!$C$6,1,0),0) | AR21: =IF(AND(L21<>"",'Historical Score'!$C$5<>""),IF(L21='Historical Score'!$C$5,1,0),0) | AS21: =IF(AND(Y21<>"",'Historical Score'!$C$7<>""),IF(Y21='Historical Score'!$C$7,1,0),0) | AT21: =IF(AND(K21<>"",'Historical Score'!$C$8<>""),IF(K21='Historical Score'!$C$8,1,0),0) | BA21: =IF(AD21=1,(AR21*'Historical Score'!$K$29+1-'Historical Score'!$K$29)*(AT21*'Historical Score'!$L$29+1-'Historical Score'!$L$29)*(AS21*'Historical Score'!$M$29+1-'Historical Score'!$M$29)*(AQ21*'Historical Score'!$N$29+1-'Historical Score'!$N$29),0)
A22: 5674149599 | B22: Robola Pizzeria | C22: AMC Fair Dealing | D22: Closed | E22: 45693 | F22: 45798 | G22: 6 | H22: 5812 | I22: 58 | J22: PA | K22: Splash | L22: Renewal | M22: 1.49 | N22: 5000 | O22: 700 | P22: 7450 | Q22: 7450 | R22: 0 | S22: 1 | T22: 2.459 | U22: 7 | W22: 0.12 | X22: 41030 | Y22: =IF(I22="","No SIC",IFERROR(VLOOKUP(I22,Ref!$A$2:$B$65,2,FALSE()),"Unclassified")) | Z22: =IF(T22="","",IF(T22<12,"Daily","Weekly")) | AA22: =IF(T22="",0,IF(T22<12,T22*Controls!$B$13,T22*5)) | AB22: =IF(E22="",0,NETWORKDAYS(E22,Controls!$B$20,Ref!$K$2:$K$42)) | AC22: =IF(OR(AF22=1,AND(AA22>0,AB22>=Controls!$B$23*AA22)),1,0) | AD22: =IF(AND(E22<>"",E22>=Controls!$B$21,E22<=Controls!$B$22),1,0) | AE22: =IF(IFERROR(VLOOKUP(D22,Controls!$A$36:$E$46,2,FALSE()),"No")="Yes",1,0) | AF22: =IF(IFERROR(VLOOKUP(D22,Controls!$A$36:$E$46,3,FALSE()),"No")="Yes",1,0) | AG22: =IF(IFERROR(VLOOKUP(D22,Controls!$A$36:$E$46,4,FALSE()),"No")="Yes",1,0) | AH22: =IF(IFERROR(VLOOKUP(D22,Controls!$A$36:$E$46,5,FALSE()),"No")="Yes",1,0) | AI22: =IF(ISNUMBER(MATCH(D22,Controls!$A$36:$A$46,0)),1,0) | AJ22: =Q22-N22 | AK22: =IF(AE22=1,MAX(0,N22-Q22),0) | AL22: =IF(OR(V22="",V22=0),0,N22/V22) | AM22: =IF(OR(V22="",V22=0),0,1) | AN22: =IF(OR(E22="",F22=""),0,NETWORKDAYS(E22,F22,Ref!$K$2:$K$42)) | AO22: =IF(L22="Renewal",1,0) | AP22: =AC22*AD22 | AQ22: =IF(AND(G22<>"",'Historical Score'!$C$6<>""),IF(G22='Historical Score'!$C$6,1,0),0) | AR22: =IF(AND(L22<>"",'Historical Score'!$C$5<>""),IF(L22='Historical Score'!$C$5,1,0),0) | AS22: =IF(AND(Y22<>"",'Historical Score'!$C$7<>""),IF(Y22='Historical Score'!$C$7,1,0),0) | AT22: =IF(AND(K22<>"",'Historical Score'!$C$8<>""),IF(K22='Historical Score'!$C$8,1,0),0) | BA22: =IF(AD22=1,(AR22*'Historical Score'!$K$29+1-'Historical Score'!$K$29)*(AT22*'Historical Score'!$L$29+1-'Historical Score'!$L$29)*(AS22*'Historical Score'!$M$29+1-'Historical Score'!$M$29)*(AQ22*'Historical Score'!$N$29+1-'Historical Score'!$N$29),0)
A23: 5674150031 | B23: PLLC NA | C23: Living Tree New Braunfels | D23: Closed | E23: 45698 | F23: 45775 | G23: 4 | H23: 8322 | I23: 83 | J23: TX | K23: GREYSTONE | L23: New Deal | M23: 1.49 | N23: 10000 | O23: 1400 | P23: 14900 | Q23: 14900 | R23: 0 | S23: 1 | T23: 1.967 | U23: 0 | W23: 0.0696 | X23: 43525 | Y23: =IF(I23="","No SIC",IFERROR(VLOOKUP(I23,Ref!$A$2:$B$65,2,FALSE()),"Unclassified")) | Z23: =IF(T23="","",IF(T23<12,"Daily","Weekly")) | AA23: =IF(T23="",0,IF(T23<12,T23*Controls!$B$13,T23*5)) | AB23: =IF(E23="",0,NETWORKDAYS(E23,Controls!$B$20,Ref!$K$2:$K$42)) | AC23: =IF(OR(AF23=1,AND(AA23>0,AB23>=Controls!$B$23*AA23)),1,0) | AD23: =IF(AND(E23<>"",E23>=Controls!$B$21,E23<=Controls!$B$22),1,0) | AE23: =IF(IFERROR(VLOOKUP(D23,Controls!$A$36:$E$46,2,FALSE()),"No")="Yes",1,0) | AF23: =IF(IFERROR(VLOOKUP(D23,Controls!$A$36:$E$46,3,FALSE()),"No")="Yes",1,0) | AG23: =IF(IFERROR(VLOOKUP(D23,Controls!$A$36:$E$46,4,FALSE()),"No")="Yes",1,0) | AH23: =IF(IFERROR(VLOOKUP(D23,Controls!$A$36:$E$46,5,FALSE()),"No")="Yes",1,0) | AI23: =IF(ISNUMBER(MATCH(D23,Controls!$A$36:$A$46,0)),1,0) | AJ23: =Q23-N23 | AK23: =IF(AE23=1,MAX(0,N23-Q23),0) | AL23: =IF(OR(V23="",V23=0),0,N23/V23) | AM23: =IF(OR(V23="",V23=0),0,1) | AN23: =IF(OR(E23="",F23=""),0,NETWORKDAYS(E23,F23,Ref!$K$2:$K$42)) | AO23: =IF(L23="Renewal",1,0) | AP23: =AC23*AD23 | AQ23: =IF(AND(G23<>"",'Historical Score'!$C$6<>""),IF(G23='Historical Score'!$C$6,1,0),0) | AR23: =IF(AND(L23<>"",'Historical Score'!$C$5<>""),IF(L23='Historical Score'!$C$5,1,0),0) | AS23: =IF(AND(Y23<>"",'Historical Score'!$C$7<>""),IF(Y23='Historical Score'!$C$7,1,0),0) | AT23: =IF(AND(K23<>"",'Historical Score'!$C$8<>""),IF(K23='Historical Score'!$C$8,1,0),0) | BA23: =IF(AD23=1,(AR23*'Historical Score'!$K$29+1-'Historical Score'!$K$29)*(AT23*'Historical Score'!$L$29+1-'Historical Score'!$L$29)*(AS23*'Historical Score'!$M$29+1-'Historical Score'!$M$29)*(AQ23*'Historical Score'!$N$29+1-'Historical Score'!$N$29),0)
A24: 5674150191 | B24: Miranda shine corp | C24: Miranda shine corp | D24: Closed | E24: 45700 | F24: 45772 | G24: 1 | H24: 7349 | I24: 73 | J24: MA | K24: Tip Top Capital | L24: New Deal | M24: 1.499 | N24: 5000 | O24: 700 | P24: 7495 | Q24: 7495 | R24: 9.094947e-13 | S24: 1 | T24: 2.295 | U24: 1 | W24: 0.05 | X24: 45026 | Y24: =IF(I24="","No SIC",IFERROR(VLOOKUP(I24,Ref!$A$2:$B$65,2,FALSE()),"Unclassified")) | Z24: =IF(T24="","",IF(T24<12,"Daily","Weekly")) | AA24: =IF(T24="",0,IF(T24<12,T24*Controls!$B$13,T24*5)) | AB24: =IF(E24="",0,NETWORKDAYS(E24,Controls!$B$20,Ref!$K$2:$K$42)) | AC24: =IF(OR(AF24=1,AND(AA24>0,AB24>=Controls!$B$23*AA24)),1,0) | AD24: =IF(AND(E24<>"",E24>=Controls!$B$21,E24<=Controls!$B$22),1,0) | AE24: =IF(IFERROR(VLOOKUP(D24,Controls!$A$36:$E$46,2,FALSE()),"No")="Yes",1,0) | AF24: =IF(IFERROR(VLOOKUP(D24,Controls!$A$36:$E$46,3,FALSE()),"No")="Yes",1,0) | AG24: =IF(IFERROR(VLOOKUP(D24,Controls!$A$36:$E$46,4,FALSE()),"No")="Yes",1,0) | AH24: =IF(IFERROR(VLOOKUP(D24,Controls!$A$36:$E$46,5,FALSE()),"No")="Yes",1,0) | AI24: =IF(ISNUMBER(MATCH(D24,Controls!$A$36:$A$46,0)),1,0) | AJ24: =Q24-N24 | AK24: =IF(AE24=1,MAX(0,N24-Q24),0) | AL24: =IF(OR(V24="",V24=0),0,N24/V24) | AM24: =IF(OR(V24="",V24=0),0,1) | AN24: =IF(OR(E24="",F24=""),0,NETWORKDAYS(E24,F24,Ref!$K$2:$K$42)) | AO24: =IF(L24="Renewal",1,0) | AP24: =AC24*AD24 | AQ24: =IF(AND(G24<>"",'Historical Score'!$C$6<>""),IF(G24='Historical Score'!$C$6,1,0),0) | AR24: =IF(AND(L24<>"",'Historical Score'!$C$5<>""),IF(L24='Historical Score'!$C$5,1,0),0) | AS24: =IF(AND(Y24<>"",'Historical Score'!$C$7<>""),IF(Y24='Historical Score'!$C$7,1,0),0) | AT24: =IF(AND(K24<>"",'Historical Score'!$C$8<>""),IF(K24='Historical Score'!$C$8,1,0),0) | BA24: =IF(AD24=1,(AR24*'Historical Score'!$K$29+1-'Historical Score'!$K$29)*(AT24*'Historical Score'!$L$29+1-'Historical Score'!$L$29)*(AS24*'Historical Score'!$M$29+1-'Historical Score'!$M$29)*(AQ24*'Historical Score'!$N$29+1-'Historical Score'!$N$29),0)
A25: 5674150528 | B25: Concrete Design Solutions | C25: Concrete Design Solutions | D25: Legal | E25: 45702 | F25: 45820 | G25: 3 | H25: 1611 | I25: 16 | J25: LA | K25: Splash | L25: Renewal | M25: 1.49 | N25: 22500 | O25: 3150 | P25: 33525 | Q25: 3924.41 | R25: 29600.59 | S25: 0.11705921 | T25: 28 | U25: 4 | W25: 0.1251 | X25: 39932 | Y25: =IF(I25="","No SIC",IFERROR(VLOOKUP(I25,Ref!$A$2:$B$65,2,FALSE()),"Unclassified")) | Z25: =IF(T25="","",IF(T25<12,"Daily","Weekly")) | AA25: =IF(T25="",0,IF(T25<12,T25*Controls!$B$13,T25*5)) | AB25: =IF(E25="",0,NETWORKDAYS(E25,Controls!$B$20,Ref!$K$2:$K$42)) | AC25: =IF(OR(AF25=1,AND(AA25>0,AB25>=Controls!$B$23*AA25)),1,0) | AD25: =IF(AND(E25<>"",E25>=Controls!$B$21,E25<=Controls!$B$22),1,0) | AE25: =IF(IFERROR(VLOOKUP(D25,Controls!$A$36:$E$46,2,FALSE()),"No")="Yes",1,0) | AF25: =IF(IFERROR(VLOOKUP(D25,Controls!$A$36:$E$46,3,FALSE()),"No")="Yes",1,0) | AG25: =IF(IFERROR(VLOOKUP(D25,Controls!$A$36:$E$46,4,FALSE()),"No")="Yes",1,0) | AH25: =IF(IFERROR(VLOOKUP(D25,Controls!$A$36:$E$46,5,FALSE()),"No")="Yes",1,0) | AI25: =IF(ISNUMBER(MATCH(D25,Controls!$A$36:$A$46,0)),1,0) | AJ25: =Q25-N25 | AK25: =IF(AE25=1,MAX(0,N25-Q25),0) | AL25: =IF(OR(V25="",V25=0),0,N25/V25) | AM25: =IF(OR(V25="",V25=0),0,1) | AN25: =IF(OR(E25="",F25=""),0,NETWORKDAYS(E25,F25,Ref!$K$2:$K$42)) | AO25: =IF(L25="Renewal",1,0) | AP25: =AC25*AD25 | AQ25: =IF(AND(G25<>"",'Historical Score'!$C$6<>""),IF(G25='Historical Score'!$C$6,1,0),0) | AR25: =IF(AND(L25<>"",'Historical Score'!$C$5<>""),IF(L25='Historical Score'!$C$5,1,0),0) | AS25: =IF(AND(Y25<>"",'Historical Score'!$C$7<>""),IF(Y25='Historical Score'!$C$7,1,0),0) | AT25: =IF(AND(K25<>"",'Historical Score'!$C$8<>""),IF(K25='Historical Score'!$C$8,1,0),0) | BA25: =IF(AD25=1,(AR25*'Historical Score'!$K$29+1-'Historical Score'!$K$29)*(AT25*'Historical Score'!$L$29+1-'Historical Score'!$L$29)*(AS25*'Historical Score'!$M$29+1-'Historical Score'!$M$29)*(AQ25*'Historical Score'!$N$29+1-'Historical Score'!$N$29),0)
A26: 5674150533 | B26: SIMPLY BEDLINERS & MINOR AUTO BODY REPAIR | C26: SIMPLY BEDLINERS & MINOR AUTO BODY REPAIR L.L.P. | D26: Legal | E26: 45702 | F26: 45735 | G26: 4 | H26: 7532 | I26: 75 | J26: AZ | K26: The Funding Channel | L26: Renewal | M26: 1.49 | N26: 20000 | O26: 2800 | P26: 29800 | Q26: 5962.36 | R26: 23837.64 | S26: 0.20007919 | T26: 20 | U26: 1 | W26: 0.0964 | X26: 43617 | Y26: =IF(I26="","No SIC",IFERROR(VLOOKUP(I26,Ref!$A$2:$B$65,2,FALSE()),"Unclassified")) | Z26: =IF(T26="","",IF(T26<12,"Daily","Weekly")) | AA26: =IF(T26="",0,IF(T26<12,T26*Controls!$B$13,T26*5)) | AB26: =IF(E26="",0,NETWORKDAYS(E26,Controls!$B$20,Ref!$K$2:$K$42)) | AC26: =IF(OR(AF26=1,AND(AA26>0,AB26>=Controls!$B$23*AA26)),1,0) | AD26: =IF(AND(E26<>"",E26>=Controls!$B$21,E26<=Controls!$B$22),1,0) | AE26: =IF(IFERROR(VLOOKUP(D26,Controls!$A$36:$E$46,2,FALSE()),"No")="Yes",1,0) | AF26: =IF(IFERROR(VLOOKUP(D26,Controls!$A$36:$E$46,3,FALSE()),"No")="Yes",1,0) | AG26: =IF(IFERROR(VLOOKUP(D26,Controls!$A$36:$E$46,4,FALSE()),"No")="Yes",1,0) | AH26: =IF(IFERROR(VLOOKUP(D26,Controls!$A$36:$E$46,5,FALSE()),"No")="Yes",1,0) | AI26: =IF(ISNUMBER(MATCH(D26,Controls!$A$36:$A$46,0)),1,0) | AJ26: =Q26-N26 | AK26: =IF(AE26=1,MAX(0,N26-Q26),0) | AL26: =IF(OR(V26="",V26=0),0,N26/V26) | AM26: =IF(OR(V26="",V26=0),0,1) | AN26: =IF(OR(E26="",F26=""),0,NETWORKDAYS(E26,F26,Ref!$K$2:$K$42)) | AO26: =IF(L26="Renewal",1,0) | AP26: =AC26*AD26 | AQ26: =IF(AND(G26<>"",'Historical Score'!$C$6<>""),IF(G26='Historical Score'!$C$6,1,0),0) | AR26: =IF(AND(L26<>"",'Historical Score'!$C$5<>""),IF(L26='Historical Score'!$C$5,1,0),0) | AS26: =IF(AND(Y26<>"",'Historical Score'!$C$7<>""),IF(Y26='Historical Score'!$C$7,1,0),0) | AT26: =IF(AND(K26<>"",'Historical Score'!$C$8<>""),IF(K26='Historical Score'!$C$8,1,0),0) | BA26: =IF(AD26=1,(AR26*'Historical Score'!$K$29+1-'Historical Score'!$K$29)*(AT26*'Historical Score'!$L$29+1-'Historical Score'!$L$29)*(AS26*'Historical Score'!$M$29+1-'Historical Score'!$M$29)*(AQ26*'Historical Score'!$N$29+1-'Historical Score'!$N$29),0)
A27: 5674150572 | B27: B & G Trucking LLC | C27: B & G Trucking LLC | D27: Legal | E27: 45702 | F27: 45715 | G27: 3 | H27: 4212 | I27: 42 | J27: IL | K27: Tip Top Capital | L27: New Deal | M27: 1.35 | N27: 10000 | O27: 0 | P27: 13500 | Q27: 843.2 | R27: 12656.8 | S27: 0.062459259 | T27: 2.623 | U27: 3 | W27: 0.0689 | X27: 43894 | Y27: =IF(I27="","No SIC",IFERROR(VLOOKUP(I27,Ref!$A$2:$B$65,2,FALSE()),"Unclassified")) | Z27: =IF(T27="","",IF(T27<12,"Daily","Weekly")) | AA27: =IF(T27="",0,IF(T27<12,T27*Controls!$B$13,T27*5)) | AB27: =IF(E27="",0,NETWORKDAYS(E27,Controls!$B$20,Ref!$K$2:$K$42)) | AC27: =IF(OR(AF27=1,AND(AA27>0,AB27>=Controls!$B$23*AA27)),1,0) | AD27: =IF(AND(E27<>"",E27>=Controls!$B$21,E27<=Controls!$B$22),1,0) | AE27: =IF(IFERROR(VLOOKUP(D27,Controls!$A$36:$E$46,2,FALSE()),"No")="Yes",1,0) | AF27: =IF(IFERROR(VLOOKUP(D27,Controls!$A$36:$E$46,3,FALSE()),"No")="Yes",1,0) | AG27: =IF(IFERROR(VLOOKUP(D27,Controls!$A$36:$E$46,4,FALSE()),"No")="Yes",1,0) | AH27: =IF(IFERROR(VLOOKUP(D27,Controls!$A$36:$E$46,5,FALSE()),"No")="Yes",1,0) | AI27: =IF(ISNUMBER(MATCH(D27,Controls!$A$36:$A$46,0)),1,0) | AJ27: =Q27-N27 | AK27: =IF(AE27=1,MAX(0,N27-Q27),0) | AL27: =IF(OR(V27="",V27=0),0,N27/V27) | AM27: =IF(OR(V27="",V27=0),0,1) | AN27: =IF(OR(E27="",F27=""),0,NETWORKDAYS(E27,F27,Ref!$K$2:$K$42)) | AO27: =IF(L27="Renewal",1,0) | AP27: =AC27*AD27 | AQ27: =IF(AND(G27<>"",'Historical Score'!$C$6<>""),IF(G27='Historical Score'!$C$6,1,0),0) | AR27: =IF(AND(L27<>"",'Historical Score'!$C$5<>""),IF(L27='Historical Score'!$C$5,1,0),0) | AS27: =IF(AND(Y27<>"",'Historical Score'!$C$7<>""),IF(Y27='Historical Score'!$C$7,1,0),0) | AT27: =IF(AND(K27<>"",'Historical Score'!$C$8<>""),IF(K27='Historical Score'!$C$8,1,0),0) | BA27: =IF(AD27=1,(AR27*'Historical Score'!$K$29+1-'Historical Score'!$K$29)*(AT27*'Historical Score'!$L$29+1-'Historical Score'!$L$29)*(AS27*'Historical Score'!$M$29+1-'Historical Score'!$M$29)*(AQ27*'Historical Score'!$N$29+1-'Historical Score'!$N$29),0)
A28: 5674150646 | B28: DY GARAGE DOORS | C28: DY GARAGE DOORS LLC | D28: Legal | E28: 45705 | F28: 45726 | G28: 6 | H28: 1751 | I28: 17 | J28: FL | K28: Tip Top Capital | L28: New Deal | M28: 1.49 | N28: 12000 | O28: 1440 | P28: 17880 | Q28: 2295 | R28: 15585 | S28: 0.1283557 | T28: 2.296 | U28: 5 | W28: 0.0493 | X28: 43069 | Y28: =IF(I28="","No SIC",IFERROR(VLOOKUP(I28,Ref!$A$2:$B$65,2,FALSE()),"Unclassified")) | Z28: =IF(T28="","",IF(T28<12,"Daily","Weekly")) | AA28: =IF(T28="",0,IF(T28<12,T28*Controls!$B$13,T28*5)) | AB28: =IF(E28="",0,NETWORKDAYS(E28,Controls!$B$20,Ref!$K$2:$K$42)) | AC28: =IF(OR(AF28=1,AND(AA28>0,AB28>=Controls!$B$23*AA28)),1,0) | AD28: =IF(AND(E28<>"",E28>=Controls!$B$21,E28<=Controls!$B$22),1,0) | AE28: =IF(IFERROR(VLOOKUP(D28,Controls!$A$36:$E$46,2,FALSE()),"No")="Yes",1,0) | AF28: =IF(IFERROR(VLOOKUP(D28,Controls!$A$36:$E$46,3,FALSE()),"No")="Yes",1,0) | AG28: =IF(IFERROR(VLOOKUP(D28,Controls!$A$36:$E$46,4,FALSE()),"No")="Yes",1,0) | AH28: =IF(IFERROR(VLOOKUP(D28,Controls!$A$36:$E$46,5,FALSE()),"No")="Yes",1,0) | AI28: =IF(ISNUMBER(MATCH(D28,Controls!$A$36:$A$46,0)),1,0) | AJ28: =Q28-N28 | AK28: =IF(AE28=1,MAX(0,N28-Q28),0) | AL28: =IF(OR(V28="",V28=0),0,N28/V28) | AM28: =IF(OR(V28="",V28=0),0,1) | AN28: =IF(OR(E28="",F28=""),0,NETWORKDAYS(E28,F28,Ref!$K$2:$K$42)) | AO28: =IF(L28="Renewal",1,0) | AP28: =AC28*AD28 | AQ28: =IF(AND(G28<>"",'Historical Score'!$C$6<>""),IF(G28='Historical Score'!$C$6,1,0),0) | AR28: =IF(AND(L28<>"",'Historical Score'!$C$5<>""),IF(L28='Historical Score'!$C$5,1,0),0) | AS28: =IF(AND(Y28<>"",'Historical Score'!$C$7<>""),IF(Y28='Historical Score'!$C$7,1,0),0) | AT28: =IF(AND(K28<>"",'Historical Score'!$C$8<>""),IF(K28='Historical Score'!$C$8,1,0),0) | BA28: =IF(AD28=1,(AR28*'Historical Score'!$K$29+1-'Historical Score'!$K$29)*(AT28*'Historical Score'!$L$29+1-'Historical Score'!$L$29)*(AS28*'Historical Score'!$M$29+1-'Historical Score'!$M$29)*(AQ28*'Historical Score'!$N$29+1-'Historical Score'!$N$29),0)
A29: 5674150664 | B29: Wyatts Feed and Seed | C29: Wyatts Feed and Seed | D29: Legal | E29: 45706 | F29: 45812 | G29: 3 | H29: 2048 | I29: 20 | J29: AL | K29: Pathway Catalyst | L29: Renewal | M29: 1.49 | N29: 5000 | O29: 700 | P29: 7450 | Q29: 3339 | R29: 4111 | S29: 0.44818792 | T29: 2.295 | U29: 29 | W29: 0.0566 | Y29: =IF(I29="","No SIC",IFERROR(VLOOKUP(I29,Ref!$A$2:$B$65,2,FALSE()),"Unclassified")) | Z29: =IF(T29="","",IF(T29<12,"Daily","Weekly")) | AA29: =IF(T29="",0,IF(T29<12,T29*Controls!$B$13,T29*5)) | AB29: =IF(E29="",0,NETWORKDAYS(E29,Controls!$B$20,Ref!$K$2:$K$42)) | AC29: =IF(OR(AF29=1,AND(AA29>0,AB29>=Controls!$B$23*AA29)),1,0) | AD29: =IF(AND(E29<>"",E29>=Controls!$B$21,E29<=Controls!$B$22),1,0) | AE29: =IF(IFERROR(VLOOKUP(D29,Controls!$A$36:$E$46,2,FALSE()),"No")="Yes",1,0) | AF29: =IF(IFERROR(VLOOKUP(D29,Controls!$A$36:$E$46,3,FALSE()),"No")="Yes",1,0) | AG29: =IF(IFERROR(VLOOKUP(D29,Controls!$A$36:$E$46,4,FALSE()),"No")="Yes",1,0) | AH29: =IF(IFERROR(VLOOKUP(D29,Controls!$A$36:$E$46,5,FALSE()),"No")="Yes",1,0) | AI29: =IF(ISNUMBER(MATCH(D29,Controls!$A$36:$A$46,0)),1,0) | AJ29: =Q29-N29 | AK29: =IF(AE29=1,MAX(0,N29-Q29),0) | AL29: =IF(OR(V29="",V29=0),0,N29/V29) | AM29: =IF(OR(V29="",V29=0),0,1) | AN29: =IF(OR(E29="",F29=""),0,NETWORKDAYS(E29,F29,Ref!$K$2:$K$42)) | AO29: =IF(L29="Renewal",1,0) | AP29: =AC29*AD29 | AQ29: =IF(AND(G29<>"",'Historical Score'!$C$6<>""),IF(G29='Historical Score'!$C$6,1,0),0) | AR29: =IF(AND(L29<>"",'Historical Score'!$C$5<>""),IF(L29='Historical Score'!$C$5,1,0),0) | AS29: =IF(AND(Y29<>"",'Historical Score'!$C$7<>""),IF(Y29='Historical Score'!$C$7,1,0),0) | AT29: =IF(AND(K29<>"",'Historical Score'!$C$8<>""),IF(K29='Historical Score'!$C$8,1,0),0) | BA29: =IF(AD29=1,(AR29*'Historical Score'!$K$29+1-'Historical Score'!$K$29)*(AT29*'Historical Score'!$L$29+1-'Historical Score'!$L$29)*(AS29*'Historical Score'!$M$29+1-'Historical Score'!$M$29)*(AQ29*'Historical Score'!$N$29+1-'Historical Score'!$N$29),0)
A30: 5674150667 | B30: Casteen Property Maintenance | C30: Casteen Property Maintenance | D30: Legal | E30: 45706 | F30: 45713 | G30: 4 | H30: 7349 | I30: 73 | J30: NC | K30: Tip Top Capital | L30: New Deal | M30: 1.49 | N30: 4000 | O30: 0 | P30: 5960 | Q30: 119.18 | R30: 5840.82 | S30: 0.019996644 | T30: 1.64 | U30: 3 | W30: 0.0908 | X30: 43293 | Y30: =IF(I30="","No SIC",IFERROR(VLOOKUP(I30,Ref!$A$2:$B$65,2,FALSE()),"Unclassified")) | Z30: =IF(T30="","",IF(T30<12,"Daily","Weekly")) | AA30: =IF(T30="",0,IF(T30<12,T30*Controls!$B$13,T30*5)) | AB30: =IF(E30="",0,NETWORKDAYS(E30,Controls!$B$20,Ref!$K$2:$K$42)) | AC30: =IF(OR(AF30=1,AND(AA30>0,AB30>=Controls!$B$23*AA30)),1,0) | AD30: =IF(AND(E30<>"",E30>=Controls!$B$21,E30<=Controls!$B$22),1,0) | AE30: =IF(IFERROR(VLOOKUP(D30,Controls!$A$36:$E$46,2,FALSE()),"No")="Yes",1,0) | AF30: =IF(IFERROR(VLOOKUP(D30,Controls!$A$36:$E$46,3,FALSE()),"No")="Yes",1,0) | AG30: =IF(IFERROR(VLOOKUP(D30,Controls!$A$36:$E$46,4,FALSE()),"No")="Yes",1,0) | AH30: =IF(IFERROR(VLOOKUP(D30,Controls!$A$36:$E$46,5,FALSE()),"No")="Yes",1,0) | AI30: =IF(ISNUMBER(MATCH(D30,Controls!$A$36:$A$46,0)),1,0) | AJ30: =Q30-N30 | AK30: =IF(AE30=1,MAX(0,N30-Q30),0) | AL30: =IF(OR(V30="",V30=0),0,N30/V30) | AM30: =IF(OR(V30="",V30=0),0,1) | AN30: =IF(OR(E30="",F30=""),0,NETWORKDAYS(E30,F30,Ref!$K$2:$K$42)) | AO30: =IF(L30="Renewal",1,0) | AP30: =AC30*AD30 | AQ30: =IF(AND(G30<>"",'Historical Score'!$C$6<>""),IF(G30='Historical Score'!$C$6,1,0),0) | AR30: =IF(AND(L30<>"",'Historical Score'!$C$5<>""),IF(L30='Historical Score'!$C$5,1,0),0) | AS30: =IF(AND(Y30<>"",'Historical Score'!$C$7<>""),IF(Y30='Historical Score'!$C$7,1,0),0) | AT30: =IF(AND(K30<>"",'Historical Score'!$C$8<>""),IF(K30='Historical Score'!$C$8,1,0),0) | BA30: =IF(AD30=1,(AR30*'Historical Score'!$K$29+1-'Historical Score'!$K$29)*(AT30*'Historical Score'!$L$29+1-'Historical Score'!$L$29)*(AS30*'Historical Score'!$M$29+1-'Historical Score'!$M$29)*(AQ30*'Historical Score'!$N$29+1-'Historical Score'!$N$29),0)
A31: 5674150725 | B31: Arkansas Climate Control | C31: Arkansas Climate Control | D31: Legal | E31: 45706 | F31: 45721 | G31: 2 | H31: 1711 | I31: 17 | J31: AR | K31: TRUSTFI | L31: New Deal | M31: 1.49 | N31: 8000 | O31: 0 | P31: 11920 | Q31: 681.36 | R31: 11238.64 | S31: 0.057161074 | T31: 2.295 | U31: 7 | W31: 0.1561 | X31: 45505 | Y31: =IF(I31="","No SIC",IFERROR(VLOOKUP(I31,Ref!$A$2:$B$65,2,FALSE()),"Unclassified")) | Z31: =IF(T31="","",IF(T31<12,"Daily","Weekly")) | AA31: =IF(T31="",0,IF(T31<12,T31*Controls!$B$13,T31*5)) | AB31: =IF(E31="",0,NETWORKDAYS(E31,Controls!$B$20,Ref!$K$2:$K$42)) | AC31: =IF(OR(AF31=1,AND(AA31>0,AB31>=Controls!$B$23*AA31)),1,0) | AD31: =IF(AND(E31<>"",E31>=Controls!$B$21,E31<=Controls!$B$22),1,0) | AE31: =IF(IFERROR(VLOOKUP(D31,Controls!$A$36:$E$46,2,FALSE()),"No")="Yes",1,0) | AF31: =IF(IFERROR(VLOOKUP(D31,Controls!$A$36:$E$46,3,FALSE()),"No")="Yes",1,0) | AG31: =IF(IFERROR(VLOOKUP(D31,Controls!$A$36:$E$46,4,FALSE()),"No")="Yes",1,0) | AH31: =IF(IFERROR(VLOOKUP(D31,Controls!$A$36:$E$46,5,FALSE()),"No")="Yes",1,0) | AI31: =IF(ISNUMBER(MATCH(D31,Controls!$A$36:$A$46,0)),1,0) | AJ31: =Q31-N31 | AK31: =IF(AE31=1,MAX(0,N31-Q31),0) | AL31: =IF(OR(V31="",V31=0),0,N31/V31) | AM31: =IF(OR(V31="",V31=0),0,1) | AN31: =IF(OR(E31="",F31=""),0,NETWORKDAYS(E31,F31,Ref!$K$2:$K$42)) | AO31: =IF(L31="Renewal",1,0) | AP31: =AC31*AD31 | AQ31: =IF(AND(G31<>"",'Historical Score'!$C$6<>""),IF(G31='Historical Score'!$C$6,1,0),0) | AR31: =IF(AND(L31<>"",'Historical Score'!$C$5<>""),IF(L31='Historical Score'!$C$5,1,0),0) | AS31: =IF(AND(Y31<>"",'Historical Score'!$C$7<>""),IF(Y31='Historical Score'!$C$7,1,0),0) | AT31: =IF(AND(K31<>"",'Historical Score'!$C$8<>""),IF(K31='Historical Score'!$C$8,1,0),0) | BA31: =IF(AD31=1,(AR31*'Historical Score'!$K$29+1-'Historical Score'!$K$29)*(AT31*'Historical Score'!$L$29+1-'Historical Score'!$L$29)*(AS31*'Historical Score'!$M$29+1-'Historical Score'!$M$29)*(AQ31*'Historical Score'!$N$29+1-'Historical Score'!$N$29),0)
A32: 5674150820 | B32: Brake Masters | C32: SLA BRAKE MASTERS LLC | D32: Closed | E32: 45707 | F32: 45841 | G32: 3 | H32: 7538 | I32: 75 | J32: CA | K32: Fundible | L32: New Deal | M32: 1.49 | N32: 10000 | O32: 1400 | P32: 14900 | Q32: 14900 | R32: 0 | S32: 1 | T32: 28 | U32: 0 | W32: 0.0702 | X32: 44866 | Y32: =IF(I32="","No SIC",IFERROR(VLOOKUP(I32,Ref!$A$2:$B$65,2,FALSE()),"Unclassified")) | Z32: =IF(T32="","",IF(T32<12,"Daily","Weekly")) | AA32: =IF(T32="",0,IF(T32<12,T32*Controls!$B$13,T32*5)) | AB32: =IF(E32="",0,NETWORKDAYS(E32,Controls!$B$20,Ref!$K$2:$K$42)) | AC32: =IF(OR(AF32=1,AND(AA32>0,AB32>=Controls!$B$23*AA32)),1,0) | AD32: =IF(AND(E32<>"",E32>=Controls!$B$21,E32<=Controls!$B$22),1,0) | AE32: =IF(IFERROR(VLOOKUP(D32,Controls!$A$36:$E$46,2,FALSE()),"No")="Yes",1,0) | AF32: =IF(IFERROR(VLOOKUP(D32,Controls!$A$36:$E$46,3,FALSE()),"No")="Yes",1,0) | AG32: =IF(IFERROR(VLOOKUP(D32,Controls!$A$36:$E$46,4,FALSE()),"No")="Yes",1,0) | AH32: =IF(IFERROR(VLOOKUP(D32,Controls!$A$36:$E$46,5,FALSE()),"No")="Yes",1,0) | AI32: =IF(ISNUMBER(MATCH(D32,Controls!$A$36:$A$46,0)),1,0) | AJ32: =Q32-N32 | AK32: =IF(AE32=1,MAX(0,N32-Q32),0) | AL32: =IF(OR(V32="",V32=0),0,N32/V32) | AM32: =IF(OR(V32="",V32=0),0,1) | AN32: =IF(OR(E32="",F32=""),0,NETWORKDAYS(E32,F32,Ref!$K$2:$K$42)) | AO32: =IF(L32="Renewal",1,0) | AP32: =AC32*AD32 | AQ32: =IF(AND(G32<>"",'Historical Score'!$C$6<>""),IF(G32='Historical Score'!$C$6,1,0),0) | AR32: =IF(AND(L32<>"",'Historical Score'!$C$5<>""),IF(L32='Historical Score'!$C$5,1,0),0) | AS32: =IF(AND(Y32<>"",'Historical Score'!$C$7<>""),IF(Y32='Historical Score'!$C$7,1,0),0) | AT32: =IF(AND(K32<>"",'Historical Score'!$C$8<>""),IF(K32='Historical Score'!$C$8,1,0),0) | BA32: =IF(AD32=1,(AR32*'Historical Score'!$K$29+1-'Historical Score'!$K$29)*(AT32*'Historical Score'!$L$29+1-'Historical Score'!$L$29)*(AS32*'Historical Score'!$M$29+1-'Historical Score'!$M$29)*(AQ32*'Historical Score'!$N$29+1-'Historical Score'!$N$29),0)
A33: 5674150864 | B33: Rock Hard Flooring & Land Clearing of Oklahoma | C33: AKH INVESTMENT LLC | D33: Legal | E33: 45709 | F33: 45922 | G33: 1 | H33: 1629 | I33: 16 | J33: OK | K33: PEACH STATE SOLUTIONS | L33: New Deal | M33: 1.49 | N33: 12000 | O33: 1680 | P33: 17880 | Q33: 3988.73 | R33: 13891.27 | S33: 0.22308333 | T33: 18 | U33: 6 | W33: 0.0653 | X33: 44367 | Y33: =IF(I33="","No SIC",IFERROR(VLOOKUP(I33,Ref!$A$2:$B$65,2,FALSE()),"Unclassified")) | Z33: =IF(T33="","",IF(T33<12,"Daily","Weekly")) | AA33: =IF(T33="",0,IF(T33<12,T33*Controls!$B$13,T33*5)) | AB33: =IF(E33="",0,NETWORKDAYS(E33,Controls!$B$20,Ref!$K$2:$K$42)) | AC33: =IF(OR(AF33=1,AND(AA33>0,AB33>=Controls!$B$23*AA33)),1,0) | AD33: =IF(AND(E33<>"",E33>=Controls!$B$21,E33<=Controls!$B$22),1,0) | AE33: =IF(IFERROR(VLOOKUP(D33,Controls!$A$36:$E$46,2,FALSE()),"No")="Yes",1,0) | AF33: =IF(IFERROR(VLOOKUP(D33,Controls!$A$36:$E$46,3,FALSE()),"No")="Yes",1,0) | AG33: =IF(IFERROR(VLOOKUP(D33,Controls!$A$36:$E$46,4,FALSE()),"No")="Yes",1,0) | AH33: =IF(IFERROR(VLOOKUP(D33,Controls!$A$36:$E$46,5,FALSE()),"No")="Yes",1,0) | AI33: =IF(ISNUMBER(MATCH(D33,Controls!$A$36:$A$46,0)),1,0) | AJ33: =Q33-N33 | AK33: =IF(AE33=1,MAX(0,N33-Q33),0) | AL33: =IF(OR(V33="",V33=0),0,N33/V33) | AM33: =IF(OR(V33="",V33=0),0,1) | AN33: =IF(OR(E33="",F33=""),0,NETWORKDAYS(E33,F33,Ref!$K$2:$K$42)) | AO33: =IF(L33="Renewal",1,0) | AP33: =AC33*AD33 | AQ33: =IF(AND(G33<>"",'Historical Score'!$C$6<>""),IF(G33='Historical Score'!$C$6,1,0),0) | AR33: =IF(AND(L33<>"",'Historical Score'!$C$5<>""),IF(L33='Historical Score'!$C$5,1,0),0) | AS33: =IF(AND(Y33<>"",'Historical Score'!$C$7<>""),IF(Y33='Historical Score'!$C$7,1,0),0) | AT33: =IF(AND(K33<>"",'Historical Score'!$C$8<>""),IF(K33='Historical Score'!$C$8,1,0),0) | BA33: =IF(AD33=1,(AR33*'Historical Score'!$K$29+1-'Historical Score'!$K$29)*(AT33*'Historical Score'!$L$29+1-'Historical Score'!$L$29)*(AS33*'Historical Score'!$M$29+1-'Historical Score'!$M$29)*(AQ33*'Historical Score'!$N$29+1-'Historical Score'!$N$29),0)
A34: 5674151205 | B34: CRAVE WINGS LLC | C34: CRAVE WINGS LLC | D34: Legal | E34: 45713 | F34: 46051 | G34: 4 | H34: 5812 | I34: 58 | J34: TN | K34: United Secured Capital 8 | L34: New Deal | M34: 1.49 | N34: 18000 | O34: 2520 | P34: 26820 | Q34: 23960.2 | R34: 2859.8 | S34: 0.89337062 | T34: 2.787 | U34: 0 | W34: 0.0922 | Y34: =IF(I34="","No SIC",IFERROR(VLOOKUP(I34,Ref!$A$2:$B$65,2,FALSE()),"Unclassified")) | Z34: =IF(T34="","",IF(T34<12,"Daily","Weekly")) | AA34: =IF(T34="",0,IF(T34<12,T34*Controls!$B$13,T34*5)) | AB34: =IF(E34="",0,NETWORKDAYS(E34,Controls!$B$20,Ref!$K$2:$K$42)) | AC34: =IF(OR(AF34=1,AND(AA34>0,AB34>=Controls!$B$23*AA34)),1,0) | AD34: =IF(AND(E34<>"",E34>=Controls!$B$21,E34<=Controls!$B$22),1,0) | AE34: =IF(IFERROR(VLOOKUP(D34,Controls!$A$36:$E$46,2,FALSE()),"No")="Yes",1,0) | AF34: =IF(IFERROR(VLOOKUP(D34,Controls!$A$36:$E$46,3,FALSE()),"No")="Yes",1,0) | AG34: =IF(IFERROR(VLOOKUP(D34,Controls!$A$36:$E$46,4,FALSE()),"No")="Yes",1,0) | AH34: =IF(IFERROR(VLOOKUP(D34,Controls!$A$36:$E$46,5,FALSE()),"No")="Yes",1,0) | AI34: =IF(ISNUMBER(MATCH(D34,Controls!$A$36:$A$46,0)),1,0) | AJ34: =Q34-N34 | AK34: =IF(AE34=1,MAX(0,N34-Q34),0) | AL34: =IF(OR(V34="",V34=0),0,N34/V34) | AM34: =IF(OR(V34="",V34=0),0,1) | AN34: =IF(OR(E34="",F34=""),0,NETWORKDAYS(E34,F34,Ref!$K$2:$K$42)) | AO34: =IF(L34="Renewal",1,0) | AP34: =AC34*AD34 | AQ34: =IF(AND(G34<>"",'Historical Score'!$C$6<>""),IF(G34='Historical Score'!$C$6,1,0),0) | AR34: =IF(AND(L34<>"",'Historical Score'!$C$5<>""),IF(L34='Historical Score'!$C$5,1,0),0) | AS34: =IF(AND(Y34<>"",'Historical Score'!$C$7<>""),IF(Y34='Historical Score'!$C$7,1,0),0) | AT34: =IF(AND(K34<>"",'Historical Score'!$C$8<>""),IF(K34='Historical Score'!$C$8,1,0),0) | BA34: =IF(AD34=1,(AR34*'Historical Score'!$K$29+1-'Historical Score'!$K$29)*(AT34*'Historical Score'!$L$29+1-'Historical Score'!$L$29)*(AS34*'Historical Score'!$M$29+1-'Historical Score'!$M$29)*(AQ34*'Historical Score'!$N$29+1-'Historical Score'!$N$29),0)
A35: 5674151260 | B35: NFB VENTURE SERVICES CORP | C35: NFB VENTURE SERVICES CORP | D35: Closed | E35: 45713 | F35: 45758 | G35: 2 | H35: 7549 | I35: 75 | J35: MA | K35: CARE FUNDING GROUP | L35: New Deal | M35: 1.49 | N35: 3500 | O35: 490 | P35: 5215 | Q35: 5215 | R35: 0 | S35: 1 | T35: 1.967 | U35: 0 | W35: 0.058 | X35: 45402 | Y35: =IF(I35="","No SIC",IFERROR(VLOOKUP(I35,Ref!$A$2:$B$65,2,FALSE()),"Unclassified")) | Z35: =IF(T35="","",IF(T35<12,"Daily","Weekly")) | AA35: =IF(T35="",0,IF(T35<12,T35*Controls!$B$13,T35*5)) | AB35: =IF(E35="",0,NETWORKDAYS(E35,Controls!$B$20,Ref!$K$2:$K$42)) | AC35: =IF(OR(AF35=1,AND(AA35>0,AB35>=Controls!$B$23*AA35)),1,0) | AD35: =IF(AND(E35<>"",E35>=Controls!$B$21,E35<=Controls!$B$22),1,0) | AE35: =IF(IFERROR(VLOOKUP(D35,Controls!$A$36:$E$46,2,FALSE()),"No")="Yes",1,0) | AF35: =IF(IFERROR(VLOOKUP(D35,Controls!$A$36:$E$46,3,FALSE()),"No")="Yes",1,0) | AG35: =IF(IFERROR(VLOOKUP(D35,Controls!$A$36:$E$46,4,FALSE()),"No")="Yes",1,0) | AH35: =IF(IFERROR(VLOOKUP(D35,Controls!$A$36:$E$46,5,FALSE()),"No")="Yes",1,0) | AI35: =IF(ISNUMBER(MATCH(D35,Controls!$A$36:$A$46,0)),1,0) | AJ35: =Q35-N35 | AK35: =IF(AE35=1,MAX(0,N35-Q35),0) | AL35: =IF(OR(V35="",V35=0),0,N35/V35) | AM35: =IF(OR(V35="",V35=0),0,1) | AN35: =IF(OR(E35="",F35=""),0,NETWORKDAYS(E35,F35,Ref!$K$2:$K$42)) | AO35: =IF(L35="Renewal",1,0) | AP35: =AC35*AD35 | AQ35: =IF(AND(G35<>"",'Historical Score'!$C$6<>""),IF(G35='Historical Score'!$C$6,1,0),0) | AR35: =IF(AND(L35<>"",'Historical Score'!$C$5<>""),IF(L35='Historical Score'!$C$5,1,0),0) | AS35: =IF(AND(Y35<>"",'Historical Score'!$C$7<>""),IF(Y35='Historical Score'!$C$7,1,0),0) | AT35: =IF(AND(K35<>"",'Historical Score'!$C$8<>""),IF(K35='Historical Score'!$C$8,1,0),0) | BA35: =IF(AD35=1,(AR35*'Historical Score'!$K$29+1-'Historical Score'!$K$29)*(AT35*'Historical Score'!$L$29+1-'Historical Score'!$L$29)*(AS35*'Historical Score'!$M$29+1-'Historical Score'!$M$29)*(AQ35*'Historical Score'!$N$29+1-'Historical Score'!$N$29),0)
A36: 5674151286 | B36: DEALS ON 11 LLC | C36: DEALS ON 11 LLC | D36: Closed | E36: 45714 | F36: 45797 | G36: 5 | H36: 5085 | I36: 50 | J36: AL | K36: Sky Advance | L36: New Deal | M36: 1.49 | N36: 5000 | O36: 700 | P36: 7450 | Q36: 7450 | R36: 0 | S36: 1 | T36: 1.967 | U36: 0 | W36: 0.0639 | X36: 45554 | Y36: =IF(I36="","No SIC",IFERROR(VLOOKUP(I36,Ref!$A$2:$B$65,2,FALSE()),"Unclassified")) | Z36: =IF(T36="","",IF(T36<12,"Daily","Weekly")) | AA36: =IF(T36="",0,IF(T36<12,T36*Controls!$B$13,T36*5)) | AB36: =IF(E36="",0,NETWORKDAYS(E36,Controls!$B$20,Ref!$K$2:$K$42)) | AC36: =IF(OR(AF36=1,AND(AA36>0,AB36>=Controls!$B$23*AA36)),1,0) | AD36: =IF(AND(E36<>"",E36>=Controls!$B$21,E36<=Controls!$B$22),1,0) | AE36: =IF(IFERROR(VLOOKUP(D36,Controls!$A$36:$E$46,2,FALSE()),"No")="Yes",1,0) | AF36: =IF(IFERROR(VLOOKUP(D36,Controls!$A$36:$E$46,3,FALSE()),"No")="Yes",1,0) | AG36: =IF(IFERROR(VLOOKUP(D36,Controls!$A$36:$E$46,4,FALSE()),"No")="Yes",1,0) | AH36: =IF(IFERROR(VLOOKUP(D36,Controls!$A$36:$E$46,5,FALSE()),"No")="Yes",1,0) | AI36: =IF(ISNUMBER(MATCH(D36,Controls!$A$36:$A$46,0)),1,0) | AJ36: =Q36-N36 | AK36: =IF(AE36=1,MAX(0,N36-Q36),0) | AL36: =IF(OR(V36="",V36=0),0,N36/V36) | AM36: =IF(OR(V36="",V36=0),0,1) | AN36: =IF(OR(E36="",F36=""),0,NETWORKDAYS(E36,F36,Ref!$K$2:$K$42)) | AO36: =IF(L36="Renewal",1,0) | AP36: =AC36*AD36 | AQ36: =IF(AND(G36<>"",'Historical Score'!$C$6<>""),IF(G36='Historical Score'!$C$6,1,0),0) | AR36: =IF(AND(L36<>"",'Historical Score'!$C$5<>""),IF(L36='Historical Score'!$C$5,1,0),0) | AS36: =IF(AND(Y36<>"",'Historical Score'!$C$7<>""),IF(Y36='Historical Score'!$C$7,1,0),0) | AT36: =IF(AND(K36<>"",'Historical Score'!$C$8<>""),IF(K36='Historical Score'!$C$8,1,0),0) | BA36: =IF(AD36=1,(AR36*'Historical Score'!$K$29+1-'Historical Score'!$K$29)*(AT36*'Historical Score'!$L$29+1-'Historical Score'!$L$29)*(AS36*'Historical Score'!$M$29+1-'Historical Score'!$M$29)*(AQ36*'Historical Score'!$N$29+1-'Historical Score'!$N$29),0)
A37: 5674151397 | B37: HITCHCOCK & COMPANY LLC | C37: HITCHCOCK & COMPANY LLC | D37: Closed | E37: 45714 | F37: 45846 | G37: 4 | H37: 1521 | I37: 15 | J37: ME | K37: United Secured Capital 8 | L37: New Deal | M37: 1.49 | N37: 22000 | O37: 3080 | P37: 32780 | Q37: 32780 | R37: 0 | S37: 1 | T37: 17.9 | U37: 1 | W37: 0.0326 | X37: 44044 | Y37: =IF(I37="","No SIC",IFERROR(VLOOKUP(I37,Ref!$A$2:$B$65,2,FALSE()),"Unclassified")) | Z37: =IF(T37="","",IF(T37<12,"Daily","Weekly")) | AA37: =IF(T37="",0,IF(T37<12,T37*Controls!$B$13,T37*5)) | AB37: =IF(E37="",0,NETWORKDAYS(E37,Controls!$B$20,Ref!$K$2:$K$42)) | AC37: =IF(OR(AF37=1,AND(AA37>0,AB37>=Controls!$B$23*AA37)),1,0) | AD37: =IF(AND(E37<>"",E37>=Controls!$B$21,E37<=Controls!$B$22),1,0) | AE37: =IF(IFERROR(VLOOKUP(D37,Controls!$A$36:$E$46,2,FALSE()),"No")="Yes",1,0) | AF37: =IF(IFERROR(VLOOKUP(D37,Controls!$A$36:$E$46,3,FALSE()),"No")="Yes",1,0) | AG37: =IF(IFERROR(VLOOKUP(D37,Controls!$A$36:$E$46,4,FALSE()),"No")="Yes",1,0) | AH37: =IF(IFERROR(VLOOKUP(D37,Controls!$A$36:$E$46,5,FALSE()),"No")="Yes",1,0) | AI37: =IF(ISNUMBER(MATCH(D37,Controls!$A$36:$A$46,0)),1,0) | AJ37: =Q37-N37 | AK37: =IF(AE37=1,MAX(0,N37-Q37),0) | AL37: =IF(OR(V37="",V37=0),0,N37/V37) | AM37: =IF(OR(V37="",V37=0),0,1) | AN37: =IF(OR(E37="",F37=""),0,NETWORKDAYS(E37,F37,Ref!$K$2:$K$42)) | AO37: =IF(L37="Renewal",1,0) | AP37: =AC37*AD37 | AQ37: =IF(AND(G37<>"",'Historical Score'!$C$6<>""),IF(G37='Historical Score'!$C$6,1,0),0) | AR37: =IF(AND(L37<>"",'Historical Score'!$C$5<>""),IF(L37='Historical Score'!$C$5,1,0),0) | AS37: =IF(AND(Y37<>"",'Historical Score'!$C$7<>""),IF(Y37='Historical Score'!$C$7,1,0),0) | AT37: =IF(AND(K37<>"",'Historical Score'!$C$8<>""),IF(K37='Historical Score'!$C$8,1,0),0) | BA37: =IF(AD37=1,(AR37*'Historical Score'!$K$29+1-'Historical Score'!$K$29)*(AT37*'Historical Score'!$L$29+1-'Historical Score'!$L$29)*(AS37*'Historical Score'!$M$29+1-'Historical Score'!$M$29)*(AQ37*'Historical Score'!$N$29+1-'Historical Score'!$N$29),0)
A38: 5674151553 | B38: VITELGUIDE LLC | C38: VITEL HEALTH LLC | D38: Closed | E38: 45716 | F38: 45848 | G38: 3 | H38: 8742 | I38: 87 | J38: CA | K38: ROYAL FUNDING GROUP | L38: New Deal | M38: 1.457 | N38: 17000 | O38: 2380 | P38: 24769 | Q38: 24769 | R38: 0 | S38: 1 | T38: 20 | U38: 2 | W38: 0.1247 | X38: 44417 | Y38: =IF(I38="","No SIC",IFERROR(VLOOKUP(I38,Ref!$A$2:$B$65,2,FALSE()),"Unclassified")) | Z38: =IF(T38="","",IF(T38<12,"Daily","Weekly")) | AA38: =IF(T38="",0,IF(T38<12,T38*Controls!$B$13,T38*5)) | AB38: =IF(E38="",0,NETWORKDAYS(E38,Controls!$B$20,Ref!$K$2:$K$42)) | AC38: =IF(OR(AF38=1,AND(AA38>0,AB38>=Controls!$B$23*AA38)),1,0) | AD38: =IF(AND(E38<>"",E38>=Controls!$B$21,E38<=Controls!$B$22),1,0) | AE38: =IF(IFERROR(VLOOKUP(D38,Controls!$A$36:$E$46,2,FALSE()),"No")="Yes",1,0) | AF38: =IF(IFERROR(VLOOKUP(D38,Controls!$A$36:$E$46,3,FALSE()),"No")="Yes",1,0) | AG38: =IF(IFERROR(VLOOKUP(D38,Controls!$A$36:$E$46,4,FALSE()),"No")="Yes",1,0) | AH38: =IF(IFERROR(VLOOKUP(D38,Controls!$A$36:$E$46,5,FALSE()),"No")="Yes",1,0) | AI38: =IF(ISNUMBER(MATCH(D38,Controls!$A$36:$A$46,0)),1,0) | AJ38: =Q38-N38 | AK38: =IF(AE38=1,MAX(0,N38-Q38),0) | AL38: =IF(OR(V38="",V38=0),0,N38/V38) | AM38: =IF(OR(V38="",V38=0),0,1) | AN38: =IF(OR(E38="",F38=""),0,NETWORKDAYS(E38,F38,Ref!$K$2:$K$42)) | AO38: =IF(L38="Renewal",1,0) | AP38: =AC38*AD38 | AQ38: =IF(AND(G38<>"",'Historical Score'!$C$6<>""),IF(G38='Historical Score'!$C$6,1,0),0) | AR38: =IF(AND(L38<>"",'Historical Score'!$C$5<>""),IF(L38='Historical Score'!$C$5,1,0),0) | AS38: =IF(AND(Y38<>"",'Historical Score'!$C$7<>""),IF(Y38='Historical Score'!$C$7,1,0),0) | AT38: =IF(AND(K38<>"",'Historical Score'!$C$8<>""),IF(K38='Historical Score'!$C$8,1,0),0) | BA38: =IF(AD38=1,(AR38*'Historical Score'!$K$29+1-'Historical Score'!$K$29)*(AT38*'Historical Score'!$L$29+1-'Historical Score'!$L$29)*(AS38*'Historical Score'!$M$29+1-'Historical Score'!$M$29)*(AQ38*'Historical Score'!$N$29+1-'Historical Score'!$N$29),0)
A39: 5674151571 | B39: DIAMOND GROUP LOGISTICS CO | C39: DIAMOND GROUP LOGISTICS CO | D39: Closed/NSF Unpaid | E39: 45716 | F39: 45834 | G39: 6 | H39: 4213 | I39: 42 | J39: IL | K39: Fund Max | L39: New Deal | M39: 1.499 | N39: 22000 | O39: 3080 | P39: 32978 | Q39: 32978 | R39: 0 | S39: 1 | T39: 16 | U39: 1 | W39: 0.0129 | X39: 42967 | Y39: =IF(I39="","No SIC",IFERROR(VLOOKUP(I39,Ref!$A$2:$B$65,2,FALSE()),"Unclassified")) | Z39: =IF(T39="","",IF(T39<12,"Daily","Weekly")) | AA39: =IF(T39="",0,IF(T39<12,T39*Controls!$B$13,T39*5)) | AB39: =IF(E39="",0,NETWORKDAYS(E39,Controls!$B$20,Ref!$K$2:$K$42)) | AC39: =IF(OR(AF39=1,AND(AA39>0,AB39>=Controls!$B$23*AA39)),1,0) | AD39: =IF(AND(E39<>"",E39>=Controls!$B$21,E39<=Controls!$B$22),1,0) | AE39: =IF(IFERROR(VLOOKUP(D39,Controls!$A$36:$E$46,2,FALSE()),"No")="Yes",1,0) | AF39: =IF(IFERROR(VLOOKUP(D39,Controls!$A$36:$E$46,3,FALSE()),"No")="Yes",1,0) | AG39: =IF(IFERROR(VLOOKUP(D39,Controls!$A$36:$E$46,4,FALSE()),"No")="Yes",1,0) | AH39: =IF(IFERROR(VLOOKUP(D39,Controls!$A$36:$E$46,5,FALSE()),"No")="Yes",1,0) | AI39: =IF(ISNUMBER(MATCH(D39,Controls!$A$36:$A$46,0)),1,0) | AJ39: =Q39-N39 | AK39: =IF(AE39=1,MAX(0,N39-Q39),0) | AL39: =IF(OR(V39="",V39=0),0,N39/V39) | AM39: =IF(OR(V39="",V39=0),0,1) | AN39: =IF(OR(E39="",F39=""),0,NETWORKDAYS(E39,F39,Ref!$K$2:$K$42)) | AO39: =IF(L39="Renewal",1,0) | AP39: =AC39*AD39 | AQ39: =IF(AND(G39<>"",'Historical Score'!$C$6<>""),IF(G39='Historical Score'!$C$6,1,0),0) | AR39: =IF(AND(L39<>"",'Historical Score'!$C$5<>""),IF(L39='Historical Score'!$C$5,1,0),0) | AS39: =IF(AND(Y39<>"",'Historical Score'!$C$7<>""),IF(Y39='Historical Score'!$C$7,1,0),0) | AT39: =IF(AND(K39<>"",'Historical Score'!$C$8<>""),IF(K39='Historical Score'!$C$8,1,0),0) | BA39: =IF(AD39=1,(AR39*'Historical Score'!$K$29+1-'Historical Score'!$K$29)*(AT39*'Historical Score'!$L$29+1-'Historical Score'!$L$29)*(AS39*'Historical Score'!$M$29+1-'Historical Score'!$M$29)*(AQ39*'Historical Score'!$N$29+1-'Historical Score'!$N$29),0)
A40: 5674151572 | B40: R & B HEATING & COOLING SPECIALIST | C40: R & B HEATING & COOLING | D40: In House Collection | E40: 45716 | F40: 45776 | G40: 5 | H40: 1711 | I40: 17 | J40: AZ | K40: MZ ADVANCE | L40: New Deal | M40: 1.49 | N40: 7000 | O40: 980 | P40: 10430 | Q40: 3297.57 | R40: 7132.43 | S40: 0.31616203 | T40: 1.148 | U40: 3 | W40: 0.0624 | X40: 37817 | Y40: =IF(I40="","No SIC",IFERROR(VLOOKUP(I40,Ref!$A$2:$B$65,2,FALSE()),"Unclassified")) | Z40: =IF(T40="","",IF(T40<12,"Daily","Weekly")) | AA40: =IF(T40="",0,IF(T40<12,T40*Controls!$B$13,T40*5)) | AB40: =IF(E40="",0,NETWORKDAYS(E40,Controls!$B$20,Ref!$K$2:$K$42)) | AC40: =IF(OR(AF40=1,AND(AA40>0,AB40>=Controls!$B$23*AA40)),1,0) | AD40: =IF(AND(E40<>"",E40>=Controls!$B$21,E40<=Controls!$B$22),1,0) | AE40: =IF(IFERROR(VLOOKUP(D40,Controls!$A$36:$E$46,2,FALSE()),"No")="Yes",1,0) | AF40: =IF(IFERROR(VLOOKUP(D40,Controls!$A$36:$E$46,3,FALSE()),"No")="Yes",1,0) | AG40: =IF(IFERROR(VLOOKUP(D40,Controls!$A$36:$E$46,4,FALSE()),"No")="Yes",1,0) | AH40: =IF(IFERROR(VLOOKUP(D40,Controls!$A$36:$E$46,5,FALSE()),"No")="Yes",1,0) | AI40: =IF(ISNUMBER(MATCH(D40,Controls!$A$36:$A$46,0)),1,0) | AJ40: =Q40-N40 | AK40: =IF(AE40=1,MAX(0,N40-Q40),0) | AL40: =IF(OR(V40="",V40=0),0,N40/V40) | AM40: =IF(OR(V40="",V40=0),0,1) | AN40: =IF(OR(E40="",F40=""),0,NETWORKDAYS(E40,F40,Ref!$K$2:$K$42)) | AO40: =IF(L40="Renewal",1,0) | AP40: =AC40*AD40 | AQ40: =IF(AND(G40<>"",'Historical Score'!$C$6<>""),IF(G40='Historical Score'!$C$6,1,0),0) | AR40: =IF(AND(L40<>"",'Historical Score'!$C$5<>""),IF(L40='Historical Score'!$C$5,1,0),0) | AS40: =IF(AND(Y40<>"",'Historical Score'!$C$7<>""),IF(Y40='Historical Score'!$C$7,1,0),0) | AT40: =IF(AND(K40<>"",'Historical Score'!$C$8<>""),IF(K40='Historical Score'!$C$8,1,0),0) | BA40: =IF(AD40=1,(AR40*'Historical Score'!$K$29+1-'Historical Score'!$K$29)*(AT40*'Historical Score'!$L$29+1-'Historical Score'!$L$29)*(AS40*'Historical Score'!$M$29+1-'Historical Score'!$M$29)*(AQ40*'Historical Score'!$N$29+1-'Historical Score'!$N$29),0)
A41: 5674151645 | B41: NEXT LEVEL DME | C41: LINX SOLUTIONS LLC | D41: Closed | E41: 45719 | F41: 45973 | G41: 6 | H41: 5047 | I41: 50 | J41: TN | K41: PMF | L41: New Deal | M41: 1.44 | N41: 20000 | O41: 2300 | P41: 28800 | Q41: 28800 | R41: 0 | S41: 1 | T41: 40 | U41: 0 | W41: 0.0279 | X41: 43748 | Y41: =IF(I41="","No SIC",IFERROR(VLOOKUP(I41,Ref!$A$2:$B$65,2,FALSE()),"Unclassified")) | Z41: =IF(T41="","",IF(T41<12,"Daily","Weekly")) | AA41: =IF(T41="",0,IF(T41<12,T41*Controls!$B$13,T41*5)) | AB41: =IF(E41="",0,NETWORKDAYS(E41,Controls!$B$20,Ref!$K$2:$K$42)) | AC41: =IF(OR(AF41=1,AND(AA41>0,AB41>=Controls!$B$23*AA41)),1,0) | AD41: =IF(AND(E41<>"",E41>=Controls!$B$21,E41<=Controls!$B$22),1,0) | AE41: =IF(IFERROR(VLOOKUP(D41,Controls!$A$36:$E$46,2,FALSE()),"No")="Yes",1,0) | AF41: =IF(IFERROR(VLOOKUP(D41,Controls!$A$36:$E$46,3,FALSE()),"No")="Yes",1,0) | AG41: =IF(IFERROR(VLOOKUP(D41,Controls!$A$36:$E$46,4,FALSE()),"No")="Yes",1,0) | AH41: =IF(IFERROR(VLOOKUP(D41,Controls!$A$36:$E$46,5,FALSE()),"No")="Yes",1,0) | AI41: =IF(ISNUMBER(MATCH(D41,Controls!$A$36:$A$46,0)),1,0) | AJ41: =Q41-N41 | AK41: =IF(AE41=1,MAX(0,N41-Q41),0) | AL41: =IF(OR(V41="",V41=0),0,N41/V41) | AM41: =IF(OR(V41="",V41=0),0,1) | AN41: =IF(OR(E41="",F41=""),0,NETWORKDAYS(E41,F41,Ref!$K$2:$K$42)) | AO41: =IF(L41="Renewal",1,0) | AP41: =AC41*AD41 | AQ41: =IF(AND(G41<>"",'Historical Score'!$C$6<>""),IF(G41='Historical Score'!$C$6,1,0),0) | AR41: =IF(AND(L41<>"",'Historical Score'!$C$5<>""),IF(L41='Historical Score'!$C$5,1,0),0) | AS41: =IF(AND(Y41<>"",'Historical Score'!$C$7<>""),IF(Y41='Historical Score'!$C$7,1,0),0) | AT41: =IF(AND(K41<>"",'Historical Score'!$C$8<>""),IF(K41='Historical Score'!$C$8,1,0),0) | BA41: =IF(AD41=1,(AR41*'Historical Score'!$K$29+1-'Historical Score'!$K$29)*(AT41*'Historical Score'!$L$29+1-'Historical Score'!$L$29)*(AS41*'Historical Score'!$M$29+1-'Historical Score'!$M$29)*(AQ41*'Historical Score'!$N$29+1-'Historical Score'!$N$29),0)
A42: 5674151913 | B42: S&E ENTERPRISE LLC | C42: S&E ENTERPRISE LLC | D42: Closed | E42: 45721 | F42: 45804 | G42: 2 | H42: 1751 | I42: 17 | J42: RI | K42: Triumph Cap Fund | L42: New Deal | M42: 1.49 | N42: 22000 | O42: 3080 | P42: 32780 | Q42: 32780 | R42: 0 | S42: 1 | T42: 3.607 | U42: 0 | W42: 0.1784 | X42: 45005 | Y42: =IF(I42="","No SIC",IFERROR(VLOOKUP(I42,Ref!$A$2:$B$65,2,FALSE()),"Unclassified")) | Z42: =IF(T42="","",IF(T42<12,"Daily","Weekly")) | AA42: =IF(T42="",0,IF(T42<12,T42*Controls!$B$13,T42*5)) | AB42: =IF(E42="",0,NETWORKDAYS(E42,Controls!$B$20,Ref!$K$2:$K$42)) | AC42: =IF(OR(AF42=1,AND(AA42>0,AB42>=Controls!$B$23*AA42)),1,0) | AD42: =IF(AND(E42<>"",E42>=Controls!$B$21,E42<=Controls!$B$22),1,0) | AE42: =IF(IFERROR(VLOOKUP(D42,Controls!$A$36:$E$46,2,FALSE()),"No")="Yes",1,0) | AF42: =IF(IFERROR(VLOOKUP(D42,Controls!$A$36:$E$46,3,FALSE()),"No")="Yes",1,0) | AG42: =IF(IFERROR(VLOOKUP(D42,Controls!$A$36:$E$46,4,FALSE()),"No")="Yes",1,0) | AH42: =IF(IFERROR(VLOOKUP(D42,Controls!$A$36:$E$46,5,FALSE()),"No")="Yes",1,0) | AI42: =IF(ISNUMBER(MATCH(D42,Controls!$A$36:$A$46,0)),1,0) | AJ42: =Q42-N42 | AK42: =IF(AE42=1,MAX(0,N42-Q42),0) | AL42: =IF(OR(V42="",V42=0),0,N42/V42) | AM42: =IF(OR(V42="",V42=0),0,1) | AN42: =IF(OR(E42="",F42=""),0,NETWORKDAYS(E42,F42,Ref!$K$2:$K$42)) | AO42: =IF(L42="Renewal",1,0) | AP42: =AC42*AD42 | AQ42: =IF(AND(G42<>"",'Historical Score'!$C$6<>""),IF(G42='Historical Score'!$C$6,1,0),0) | AR42: =IF(AND(L42<>"",'Historical Score'!$C$5<>""),IF(L42='Historical Score'!$C$5,1,0),0) | AS42: =IF(AND(Y42<>"",'Historical Score'!$C$7<>""),IF(Y42='Historical Score'!$C$7,1,0),0) | AT42: =IF(AND(K42<>"",'Historical Score'!$C$8<>""),IF(K42='Historical Score'!$C$8,1,0),0) | BA42: =IF(AD42=1,(AR42*'Historical Score'!$K$29+1-'Historical Score'!$K$29)*(AT42*'Historical Score'!$L$29+1-'Historical Score'!$L$29)*(AS42*'Historical Score'!$M$29+1-'Historical Score'!$M$29)*(AQ42*'Historical Score'!$N$29+1-'Historical Score'!$N$29),0)
A43: 5674151967 | B43: ANDERSON CARPENTRY CO | C43: ANDERSON CARPENTRY AND CO | D43: Closed | E43: 45722 | F43: 45813 | G43: 1 | H43: 1629 | I43: 16 | J43: FL | K43: Samson Funding | L43: New Deal | M43: 1.49 | N43: 10000 | O43: 1400 | P43: 14900 | Q43: 14900 | R43: 0 | S43: 1 | T43: 3.279 | U43: 0 | W43: 0.0981 | X43: 44977 | Y43: =IF(I43="","No SIC",IFERROR(VLOOKUP(I43,Ref!$A$2:$B$65,2,FALSE()),"Unclassified")) | Z43: =IF(T43="","",IF(T43<12,"Daily","Weekly")) | AA43: =IF(T43="",0,IF(T43<12,T43*Controls!$B$13,T43*5)) | AB43: =IF(E43="",0,NETWORKDAYS(E43,Controls!$B$20,Ref!$K$2:$K$42)) | AC43: =IF(OR(AF43=1,AND(AA43>0,AB43>=Controls!$B$23*AA43)),1,0) | AD43: =IF(AND(E43<>"",E43>=Controls!$B$21,E43<=Controls!$B$22),1,0) | AE43: =IF(IFERROR(VLOOKUP(D43,Controls!$A$36:$E$46,2,FALSE()),"No")="Yes",1,0) | AF43: =IF(IFERROR(VLOOKUP(D43,Controls!$A$36:$E$46,3,FALSE()),"No")="Yes",1,0) | AG43: =IF(IFERROR(VLOOKUP(D43,Controls!$A$36:$E$46,4,FALSE()),"No")="Yes",1,0) | AH43: =IF(IFERROR(VLOOKUP(D43,Controls!$A$36:$E$46,5,FALSE()),"No")="Yes",1,0) | AI43: =IF(ISNUMBER(MATCH(D43,Controls!$A$36:$A$46,0)),1,0) | AJ43: =Q43-N43 | AK43: =IF(AE43=1,MAX(0,N43-Q43),0) | AL43: =IF(OR(V43="",V43=0),0,N43/V43) | AM43: =IF(OR(V43="",V43=0),0,1) | AN43: =IF(OR(E43="",F43=""),0,NETWORKDAYS(E43,F43,Ref!$K$2:$K$42)) | AO43: =IF(L43="Renewal",1,0) | AP43: =AC43*AD43 | AQ43: =IF(AND(G43<>"",'Historical Score'!$C$6<>""),IF(G43='Historical Score'!$C$6,1,0),0) | AR43: =IF(AND(L43<>"",'Historical Score'!$C$5<>""),IF(L43='Historical Score'!$C$5,1,0),0) | AS43: =IF(AND(Y43<>"",'Historical Score'!$C$7<>""),IF(Y43='Historical Score'!$C$7,1,0),0) | AT43: =IF(AND(K43<>"",'Historical Score'!$C$8<>""),IF(K43='Historical Score'!$C$8,1,0),0) | BA43: =IF(AD43=1,(AR43*'Historical Score'!$K$29+1-'Historical Score'!$K$29)*(AT43*'Historical Score'!$L$29+1-'Historical Score'!$L$29)*(AS43*'Historical Score'!$M$29+1-'Historical Score'!$M$29)*(AQ43*'Historical Score'!$N$29+1-'Historical Score'!$N$29),0)
A44: 5674152037 | B44: COOPER PRINTING | C44: COOPER PRINTING | D44: Closed | E44: 45722 | F44: 45821 | G44: 4 | H44: 5699 | I44: 56 | J44: MS | K44: Platform Funding | L44: Renewal | M44: 1.47 | N44: 4000 | O44: 520 | P44: 5880 | Q44: 5880 | R44: 0 | S44: 1 | T44: 2.295 | U44: 0 | W44: 0.1421 | X44: 44350 | Y44: =IF(I44="","No SIC",IFERROR(VLOOKUP(I44,Ref!$A$2:$B$65,2,FALSE()),"Unclassified")) | Z44: =IF(T44="","",IF(T44<12,"Daily","Weekly")) | AA44: =IF(T44="",0,IF(T44<12,T44*Controls!$B$13,T44*5)) | AB44: =IF(E44="",0,NETWORKDAYS(E44,Controls!$B$20,Ref!$K$2:$K$42)) | AC44: =IF(OR(AF44=1,AND(AA44>0,AB44>=Controls!$B$23*AA44)),1,0) | AD44: =IF(AND(E44<>"",E44>=Controls!$B$21,E44<=Controls!$B$22),1,0) | AE44: =IF(IFERROR(VLOOKUP(D44,Controls!$A$36:$E$46,2,FALSE()),"No")="Yes",1,0) | AF44: =IF(IFERROR(VLOOKUP(D44,Controls!$A$36:$E$46,3,FALSE()),"No")="Yes",1,0) | AG44: =IF(IFERROR(VLOOKUP(D44,Controls!$A$36:$E$46,4,FALSE()),"No")="Yes",1,0) | AH44: =IF(IFERROR(VLOOKUP(D44,Controls!$A$36:$E$46,5,FALSE()),"No")="Yes",1,0) | AI44: =IF(ISNUMBER(MATCH(D44,Controls!$A$36:$A$46,0)),1,0) | AJ44: =Q44-N44 | AK44: =IF(AE44=1,MAX(0,N44-Q44),0) | AL44: =IF(OR(V44="",V44=0),0,N44/V44) | AM44: =IF(OR(V44="",V44=0),0,1) | AN44: =IF(OR(E44="",F44=""),0,NETWORKDAYS(E44,F44,Ref!$K$2:$K$42)) | AO44: =IF(L44="Renewal",1,0) | AP44: =AC44*AD44 | AQ44: =IF(AND(G44<>"",'Historical Score'!$C$6<>""),IF(G44='Historical Score'!$C$6,1,0),0) | AR44: =IF(AND(L44<>"",'Historical Score'!$C$5<>""),IF(L44='Historical Score'!$C$5,1,0),0) | AS44: =IF(AND(Y44<>"",'Historical Score'!$C$7<>""),IF(Y44='Historical Score'!$C$7,1,0),0) | AT44: =IF(AND(K44<>"",'Historical Score'!$C$8<>""),IF(K44='Historical Score'!$C$8,1,0),0) | BA44: =IF(AD44=1,(AR44*'Historical Score'!$K$29+1-'Historical Score'!$K$29)*(AT44*'Historical Score'!$L$29+1-'Historical Score'!$L$29)*(AS44*'Historical Score'!$M$29+1-'Historical Score'!$M$29)*(AQ44*'Historical Score'!$N$29+1-'Historical Score'!$N$29),0)
A45: 5674152412 | B45: Anzar Deliveries | C45: Anzar Deliveries LLC | D45: Closed | E45: 45728 | F45: 45772 | G45: 6 | H45: 4213 | I45: 42 | J45: CA | K45: Business Fund USA 4 | L45: New Deal | M45: 1.39 | N45: 5500 | O45: 495 | P45: 7645 | Q45: 7645 | R45: -9.094947e-13 | S45: 1 | T45: 2.295 | U45: 1 | W45: 0.06 | Y45: =IF(I45="","No SIC",IFERROR(VLOOKUP(I45,Ref!$A$2:$B$65,2,FALSE()),"Unclassified")) | Z45: =IF(T45="","",IF(T45<12,"Daily","Weekly")) | AA45: =IF(T45="",0,IF(T45<12,T45*Controls!$B$13,T45*5)) | AB45: =IF(E45="",0,NETWORKDAYS(E45,Controls!$B$20,Ref!$K$2:$K$42)) | AC45: =IF(OR(AF45=1,AND(AA45>0,AB45>=Controls!$B$23*AA45)),1,0) | AD45: =IF(AND(E45<>"",E45>=Controls!$B$21,E45<=Controls!$B$22),1,0) | AE45: =IF(IFERROR(VLOOKUP(D45,Controls!$A$36:$E$46,2,FALSE()),"No")="Yes",1,0) | AF45: =IF(IFERROR(VLOOKUP(D45,Controls!$A$36:$E$46,3,FALSE()),"No")="Yes",1,0) | AG45: =IF(IFERROR(VLOOKUP(D45,Controls!$A$36:$E$46,4,FALSE()),"No")="Yes",1,0) | AH45: =IF(IFERROR(VLOOKUP(D45,Controls!$A$36:$E$46,5,FALSE()),"No")="Yes",1,0) | AI45: =IF(ISNUMBER(MATCH(D45,Controls!$A$36:$A$46,0)),1,0) | AJ45: =Q45-N45 | AK45: =IF(AE45=1,MAX(0,N45-Q45),0) | AL45: =IF(OR(V45="",V45=0),0,N45/V45) | AM45: =IF(OR(V45="",V45=0),0,1) | AN45: =IF(OR(E45="",F45=""),0,NETWORKDAYS(E45,F45,Ref!$K$2:$K$42)) | AO45: =IF(L45="Renewal",1,0) | AP45: =AC45*AD45 | AQ45: =IF(AND(G45<>"",'Historical Score'!$C$6<>""),IF(G45='Historical Score'!$C$6,1,0),0) | AR45: =IF(AND(L45<>"",'Historical Score'!$C$5<>""),IF(L45='Historical Score'!$C$5,1,0),0) | AS45: =IF(AND(Y45<>"",'Historical Score'!$C$7<>""),IF(Y45='Historical Score'!$C$7,1,0),0) | AT45: =IF(AND(K45<>"",'Historical Score'!$C$8<>""),IF(K45='Historical Score'!$C$8,1,0),0) | BA45: =IF(AD45=1,(AR45*'Historical Score'!$K$29+1-'Historical Score'!$K$29)*(AT45*'Historical Score'!$L$29+1-'Historical Score'!$L$29)*(AS45*'Historical Score'!$M$29+1-'Historical Score'!$M$29)*(AQ45*'Historical Score'!$N$29+1-'Historical Score'!$N$29),0)
A46: 5674152422 | B46: Care & Wellness Solutions | C46: Care & Wellness Solutions LLC | D46: Written-Off | E46: 45728 | F46: 45961 | G46: 2 | H46: 8049 | I46: 80 | J46: VA | K46: Klendify | L46: New Deal | M46: 1.49 | N46: 3000 | O46: 420 | P46: 4470 | Q46: 3622.86 | R46: 847.14 | S46: 0.81048322 | T46: 2.623 | U46: 45 | W46: 0.0472 | X46: 44902 | Y46: =IF(I46="","No SIC",IFERROR(VLOOKUP(I46,Ref!$A$2:$B$65,2,FALSE()),"Unclassified")) | Z46: =IF(T46="","",IF(T46<12,"Daily","Weekly")) | AA46: =IF(T46="",0,IF(T46<12,T46*Controls!$B$13,T46*5)) | AB46: =IF(E46="",0,NETWORKDAYS(E46,Controls!$B$20,Ref!$K$2:$K$42)) | AC46: =IF(OR(AF46=1,AND(AA46>0,AB46>=Controls!$B$23*AA46)),1,0) | AD46: =IF(AND(E46<>"",E46>=Controls!$B$21,E46<=Controls!$B$22),1,0) | AE46: =IF(IFERROR(VLOOKUP(D46,Controls!$A$36:$E$46,2,FALSE()),"No")="Yes",1,0) | AF46: =IF(IFERROR(VLOOKUP(D46,Controls!$A$36:$E$46,3,FALSE()),"No")="Yes",1,0) | AG46: =IF(IFERROR(VLOOKUP(D46,Controls!$A$36:$E$46,4,FALSE()),"No")="Yes",1,0) | AH46: =IF(IFERROR(VLOOKUP(D46,Controls!$A$36:$E$46,5,FALSE()),"No")="Yes",1,0) | AI46: =IF(ISNUMBER(MATCH(D46,Controls!$A$36:$A$46,0)),1,0) | AJ46: =Q46-N46 | AK46: =IF(AE46=1,MAX(0,N46-Q46),0) | AL46: =IF(OR(V46="",V46=0),0,N46/V46) | AM46: =IF(OR(V46="",V46=0),0,1) | AN46: =IF(OR(E46="",F46=""),0,NETWORKDAYS(E46,F46,Ref!$K$2:$K$42)) | AO46: =IF(L46="Renewal",1,0) | AP46: =AC46*AD46 | AQ46: =IF(AND(G46<>"",'Historical Score'!$C$6<>""),IF(G46='Historical Score'!$C$6,1,0),0) | AR46: =IF(AND(L46<>"",'Historical Score'!$C$5<>""),IF(L46='Historical Score'!$C$5,1,0),0) | AS46: =IF(AND(Y46<>"",'Historical Score'!$C$7<>""),IF(Y46='Historical Score'!$C$7,1,0),0) | AT46: =IF(AND(K46<>"",'Historical Score'!$C$8<>""),IF(K46='Historical Score'!$C$8,1,0),0) | BA46: =IF(AD46=1,(AR46*'Historical Score'!$K$29+1-'Historical Score'!$K$29)*(AT46*'Historical Score'!$L$29+1-'Historical Score'!$L$29)*(AS46*'Historical Score'!$M$29+1-'Historical Score'!$M$29)*(AQ46*'Historical Score'!$N$29+1-'Historical Score'!$N$29),0)
A47: 5674152426 | B47: Pro car care group | C47: Pro car care group | D47: Legal | E47: 45728 | F47: 45789 | G47: 5 | H47: 7539 | I47: 75 | J47: FL | K47: One Box Funding | L47: New Deal | M47: 1.49 | N47: 5000 | O47: 700 | P47: 7450 | Q47: 3374.5 | R47: 4075.5 | S47: 0.45295302 | T47: 2.459 | U47: 9 | W47: 0.031 | X47: 44460 | Y47: =IF(I47="","No SIC",IFERROR(VLOOKUP(I47,Ref!$A$2:$B$65,2,FALSE()),"Unclassified")) | Z47: =IF(T47="","",IF(T47<12,"Daily","Weekly")) | AA47: =IF(T47="",0,IF(T47<12,T47*Controls!$B$13,T47*5)) | AB47: =IF(E47="",0,NETWORKDAYS(E47,Controls!$B$20,Ref!$K$2:$K$42)) | AC47: =IF(OR(AF47=1,AND(AA47>0,AB47>=Controls!$B$23*AA47)),1,0) | AD47: =IF(AND(E47<>"",E47>=Controls!$B$21,E47<=Controls!$B$22),1,0) | AE47: =IF(IFERROR(VLOOKUP(D47,Controls!$A$36:$E$46,2,FALSE()),"No")="Yes",1,0) | AF47: =IF(IFERROR(VLOOKUP(D47,Controls!$A$36:$E$46,3,FALSE()),"No")="Yes",1,0) | AG47: =IF(IFERROR(VLOOKUP(D47,Controls!$A$36:$E$46,4,FALSE()),"No")="Yes",1,0) | AH47: =IF(IFERROR(VLOOKUP(D47,Controls!$A$36:$E$46,5,FALSE()),"No")="Yes",1,0) | AI47: =IF(ISNUMBER(MATCH(D47,Controls!$A$36:$A$46,0)),1,0) | AJ47: =Q47-N47 | AK47: =IF(AE47=1,MAX(0,N47-Q47),0) | AL47: =IF(OR(V47="",V47=0),0,N47/V47) | AM47: =IF(OR(V47="",V47=0),0,1) | AN47: =IF(OR(E47="",F47=""),0,NETWORKDAYS(E47,F47,Ref!$K$2:$K$42)) | AO47: =IF(L47="Renewal",1,0) | AP47: =AC47*AD47 | AQ47: =IF(AND(G47<>"",'Historical Score'!$C$6<>""),IF(G47='Historical Score'!$C$6,1,0),0) | AR47: =IF(AND(L47<>"",'Historical Score'!$C$5<>""),IF(L47='Historical Score'!$C$5,1,0),0) | AS47: =IF(AND(Y47<>"",'Historical Score'!$C$7<>""),IF(Y47='Historical Score'!$C$7,1,0),0) | AT47: =IF(AND(K47<>"",'Historical Score'!$C$8<>""),IF(K47='Historical Score'!$C$8,1,0),0) | BA47: =IF(AD47=1,(AR47*'Historical Score'!$K$29+1-'Historical Score'!$K$29)*(AT47*'Historical Score'!$L$29+1-'Historical Score'!$L$29)*(AS47*'Historical Score'!$M$29+1-'Historical Score'!$M$29)*(AQ47*'Historical Score'!$N$29+1-'Historical Score'!$N$29),0)
A48: 5674152928 | B48: Valla Park Financial | C48: Valla Park Financial | D48: Legal | E48: 45735 | F48: 45770 | G48: 1 | H48: 3799 | I48: 37 | J48: GA | K48: FIFTH VENTURE | L48: New Deal | M48: 1.49 | N48: 5000 | O48: 700 | P48: 7450 | Q48: 2830.24 | R48: 4619.76 | S48: 0.37989799 | T48: 1.64 | U48: 6 | W48: 0.1106 | X48: 44139 | Y48: =IF(I48="","No SIC",IFERROR(VLOOKUP(I48,Ref!$A$2:$B$65,2,FALSE()),"Unclassified")) | Z48: =IF(T48="","",IF(T48<12,"Daily","Weekly")) | AA48: =IF(T48="",0,IF(T48<12,T48*Controls!$B$13,T48*5)) | AB48: =IF(E48="",0,NETWORKDAYS(E48,Controls!$B$20,Ref!$K$2:$K$42)) | AC48: =IF(OR(AF48=1,AND(AA48>0,AB48>=Controls!$B$23*AA48)),1,0) | AD48: =IF(AND(E48<>"",E48>=Controls!$B$21,E48<=Controls!$B$22),1,0) | AE48: =IF(IFERROR(VLOOKUP(D48,Controls!$A$36:$E$46,2,FALSE()),"No")="Yes",1,0) | AF48: =IF(IFERROR(VLOOKUP(D48,Controls!$A$36:$E$46,3,FALSE()),"No")="Yes",1,0) | AG48: =IF(IFERROR(VLOOKUP(D48,Controls!$A$36:$E$46,4,FALSE()),"No")="Yes",1,0) | AH48: =IF(IFERROR(VLOOKUP(D48,Controls!$A$36:$E$46,5,FALSE()),"No")="Yes",1,0) | AI48: =IF(ISNUMBER(MATCH(D48,Controls!$A$36:$A$46,0)),1,0) | AJ48: =Q48-N48 | AK48: =IF(AE48=1,MAX(0,N48-Q48),0) | AL48: =IF(OR(V48="",V48=0),0,N48/V48) | AM48: =IF(OR(V48="",V48=0),0,1) | AN48: =IF(OR(E48="",F48=""),0,NETWORKDAYS(E48,F48,Ref!$K$2:$K$42)) | AO48: =IF(L48="Renewal",1,0) | AP48: =AC48*AD48 | AQ48: =IF(AND(G48<>"",'Historical Score'!$C$6<>""),IF(G48='Historical Score'!$C$6,1,0),0) | AR48: =IF(AND(L48<>"",'Historical Score'!$C$5<>""),IF(L48='Historical Score'!$C$5,1,0),0) | AS48: =IF(AND(Y48<>"",'Historical Score'!$C$7<>""),IF(Y48='Historical Score'!$C$7,1,0),0) | AT48: =IF(AND(K48<>"",'Historical Score'!$C$8<>""),IF(K48='Historical Score'!$C$8,1,0),0) | BA48: =IF(AD48=1,(AR48*'Historical Score'!$K$29+1-'Historical Score'!$K$29)*(AT48*'Historical Score'!$L$29+1-'Historical Score'!$L$29)*(AS48*'Historical Score'!$M$29+1-'Historical Score'!$M$29)*(AQ48*'Historical Score'!$N$29+1-'Historical Score'!$N$29),0)
A49: 5674153028 | B49: IDENTITY ATL LLC | C49: IDENTITY ATL LLC | D49: Closed | E49: 45736 | F49: 45771 | G49: 6 | H49: 5399 | I49: 53 | J49: GA | K49: ROYAL FUNDING GROUP | L49: Renewal | M49: 1.49 | N49: 3500 | O49: 490 | P49: 5215 | Q49: 5215 | R49: 0 | S49: 1 | T49: 2.293 | U49: 2 | W49: 0.0421 | X49: 44490 | Y49: =IF(I49="","No SIC",IFERROR(VLOOKUP(I49,Ref!$A$2:$B$65,2,FALSE()),"Unclassified")) | Z49: =IF(T49="","",IF(T49<12,"Daily","Weekly")) | AA49: =IF(T49="",0,IF(T49<12,T49*Controls!$B$13,T49*5)) | AB49: =IF(E49="",0,NETWORKDAYS(E49,Controls!$B$20,Ref!$K$2:$K$42)) | AC49: =IF(OR(AF49=1,AND(AA49>0,AB49>=Controls!$B$23*AA49)),1,0) | AD49: =IF(AND(E49<>"",E49>=Controls!$B$21,E49<=Controls!$B$22),1,0) | AE49: =IF(IFERROR(VLOOKUP(D49,Controls!$A$36:$E$46,2,FALSE()),"No")="Yes",1,0) | AF49: =IF(IFERROR(VLOOKUP(D49,Controls!$A$36:$E$46,3,FALSE()),"No")="Yes",1,0) | AG49: =IF(IFERROR(VLOOKUP(D49,Controls!$A$36:$E$46,4,FALSE()),"No")="Yes",1,0) | AH49: =IF(IFERROR(VLOOKUP(D49,Controls!$A$36:$E$46,5,FALSE()),"No")="Yes",1,0) | AI49: =IF(ISNUMBER(MATCH(D49,Controls!$A$36:$A$46,0)),1,0) | AJ49: =Q49-N49 | AK49: =IF(AE49=1,MAX(0,N49-Q49),0) | AL49: =IF(OR(V49="",V49=0),0,N49/V49) | AM49: =IF(OR(V49="",V49=0),0,1) | AN49: =IF(OR(E49="",F49=""),0,NETWORKDAYS(E49,F49,Ref!$K$2:$K$42)) | AO49: =IF(L49="Renewal",1,0) | AP49: =AC49*AD49 | AQ49: =IF(AND(G49<>"",'Historical Score'!$C$6<>""),IF(G49='Historical Score'!$C$6,1,0),0) | AR49: =IF(AND(L49<>"",'Historical Score'!$C$5<>""),IF(L49='Historical Score'!$C$5,1,0),0) | AS49: =IF(AND(Y49<>"",'Historical Score'!$C$7<>""),IF(Y49='Historical Score'!$C$7,1,0),0) | AT49: =IF(AND(K49<>"",'Historical Score'!$C$8<>""),IF(K49='Historical Score'!$C$8,1,0),0) | BA49: =IF(AD49=1,(AR49*'Historical Score'!$K$29+1-'Historical Score'!$K$29)*(AT49*'Historical Score'!$L$29+1-'Historical Score'!$L$29)*(AS49*'Historical Score'!$M$29+1-'Historical Score'!$M$29)*(AQ49*'Historical Score'!$N$29+1-'Historical Score'!$N$29),0)
A50: 5674153205 | B50: JACKS PEST MGMT LLC | C50: JACKS PEST MGMT LLC | D50: Closed | E50: 45737 | F50: 45790 | G50: 3 | H50: 7342 | I50: 73 | J50: MT | K50: Samson Funding | L50: New Deal | M50: 1.49 | N50: 4500 | O50: 630 | P50: 6705 | Q50: 6705 | R50: 0 | S50: 1 | T50: 2.131 | U50: 0 | W50: 0.1991 | X50: 45280 | Y50: =IF(I50="","No SIC",IFERROR(VLOOKUP(I50,Ref!$A$2:$B$65,2,FALSE()),"Unclassified")) | Z50: =IF(T50="","",IF(T50<12,"Daily","Weekly")) | AA50: =IF(T50="",0,IF(T50<12,T50*Controls!$B$13,T50*5)) | AB50: =IF(E50="",0,NETWORKDAYS(E50,Controls!$B$20,Ref!$K$2:$K$42)) | AC50: =IF(OR(AF50=1,AND(AA50>0,AB50>=Controls!$B$23*AA50)),1,0) | AD50: =IF(AND(E50<>"",E50>=Controls!$B$21,E50<=Controls!$B$22),1,0) | AE50: =IF(IFERROR(VLOOKUP(D50,Controls!$A$36:$E$46,2,FALSE()),"No")="Yes",1,0) | AF50: =IF(IFERROR(VLOOKUP(D50,Controls!$A$36:$E$46,3,FALSE()),"No")="Yes",1,0) | AG50: =IF(IFERROR(VLOOKUP(D50,Controls!$A$36:$E$46,4,FALSE()),"No")="Yes",1,0) | AH50: =IF(IFERROR(VLOOKUP(D50,Controls!$A$36:$E$46,5,FALSE()),"No")="Yes",1,0) | AI50: =IF(ISNUMBER(MATCH(D50,Controls!$A$36:$A$46,0)),1,0) | AJ50: =Q50-N50 | AK50: =IF(AE50=1,MAX(0,N50-Q50),0) | AL50: =IF(OR(V50="",V50=0),0,N50/V50) | AM50: =IF(OR(V50="",V50=0),0,1) | AN50: =IF(OR(E50="",F50=""),0,NETWORKDAYS(E50,F50,Ref!$K$2:$K$42)) | AO50: =IF(L50="Renewal",1,0) | AP50: =AC50*AD50 | AQ50: =IF(AND(G50<>"",'Historical Score'!$C$6<>""),IF(G50='Historical Score'!$C$6,1,0),0) | AR50: =IF(AND(L50<>"",'Historical Score'!$C$5<>""),IF(L50='Historical Score'!$C$5,1,0),0) | AS50: =IF(AND(Y50<>"",'Historical Score'!$C$7<>""),IF(Y50='Historical Score'!$C$7,1,0),0) | AT50: =IF(AND(K50<>"",'Historical Score'!$C$8<>""),IF(K50='Historical Score'!$C$8,1,0),0) | BA50: =IF(AD50=1,(AR50*'Historical Score'!$K$29+1-'Historical Score'!$K$29)*(AT50*'Historical Score'!$L$29+1-'Historical Score'!$L$29)*(AS50*'Historical Score'!$M$29+1-'Historical Score'!$M$29)*(AQ50*'Historical Score'!$N$29+1-'Historical Score'!$N$29),0)
A51: 5674153335 | B51: Stones by crowne | C51: Stones by crowne | D51: Legal | E51: 45741 | F51: 46234 | G51: 1 | H51: 3281 | I51: 32 | J51: MA | K51: Premium Capital (AMRK) | L51: Renewal | M51: 1.49 | N51: 7500 | O51: 1050 | P51: 11175 | Q51: 9601.04 | R51: 1573.96 | S51: 0.85915347 | T51: 17 | U51: 6 | W51: 0.0497 | X51: 44896 | Y51: =IF(I51="","No SIC",IFERROR(VLOOKUP(I51,Ref!$A$2:$B$65,2,FALSE()),"Unclassified")) | Z51: =IF(T51="","",IF(T51<12,"Daily","Weekly")) | AA51: =IF(T51="",0,IF(T51<12,T51*Controls!$B$13,T51*5)) | AB51: =IF(E51="",0,NETWORKDAYS(E51,Controls!$B$20,Ref!$K$2:$K$42)) | AC51: =IF(OR(AF51=1,AND(AA51>0,AB51>=Controls!$B$23*AA51)),1,0) | AD51: =IF(AND(E51<>"",E51>=Controls!$B$21,E51<=Controls!$B$22),1,0) | AE51: =IF(IFERROR(VLOOKUP(D51,Controls!$A$36:$E$46,2,FALSE()),"No")="Yes",1,0) | AF51: =IF(IFERROR(VLOOKUP(D51,Controls!$A$36:$E$46,3,FALSE()),"No")="Yes",1,0) | AG51: =IF(IFERROR(VLOOKUP(D51,Controls!$A$36:$E$46,4,FALSE()),"No")="Yes",1,0) | AH51: =IF(IFERROR(VLOOKUP(D51,Controls!$A$36:$E$46,5,FALSE()),"No")="Yes",1,0) | AI51: =IF(ISNUMBER(MATCH(D51,Controls!$A$36:$A$46,0)),1,0) | AJ51: =Q51-N51 | AK51: =IF(AE51=1,MAX(0,N51-Q51),0) | AL51: =IF(OR(V51="",V51=0),0,N51/V51) | AM51: =IF(OR(V51="",V51=0),0,1) | AN51: =IF(OR(E51="",F51=""),0,NETWORKDAYS(E51,F51,Ref!$K$2:$K$42)) | AO51: =IF(L51="Renewal",1,0) | AP51: =AC51*AD51 | AQ51: =IF(AND(G51<>"",'Historical Score'!$C$6<>""),IF(G51='Historical Score'!$C$6,1,0),0) | AR51: =IF(AND(L51<>"",'Historical Score'!$C$5<>""),IF(L51='Historical Score'!$C$5,1,0),0) | AS51: =IF(AND(Y51<>"",'Historical Score'!$C$7<>""),IF(Y51='Historical Score'!$C$7,1,0),0) | AT51: =IF(AND(K51<>"",'Historical Score'!$C$8<>""),IF(K51='Historical Score'!$C$8,1,0),0) | BA51: =IF(AD51=1,(AR51*'Historical Score'!$K$29+1-'Historical Score'!$K$29)*(AT51*'Historical Score'!$L$29+1-'Historical Score'!$L$29)*(AS51*'Historical Score'!$M$29+1-'Historical Score'!$M$29)*(AQ51*'Historical Score'!$N$29+1-'Historical Score'!$N$29),0)
A52: 5674153342 | B52: CORNERSTONE GROWTH SOLUTIONS, LLC | C52: CORNERSTONE GROWTH SOLUTIONS, LLC | D52: Closed | E52: 45742 | F52: 45831 | G52: 1 | H52: 8742 | I52: 87 | J52: TX | K52: Westwood | L52: New Deal | M52: 1.49 | N52: 8000 | O52: 1120 | P52: 11920 | Q52: 11920 | R52: 0 | S52: 1 | T52: 1.967 | U52: 2 | W52: 0.0307 | X52: 40909 | Y52: =IF(I52="","No SIC",IFERROR(VLOOKUP(I52,Ref!$A$2:$B$65,2,FALSE()),"Unclassified")) | Z52: =IF(T52="","",IF(T52<12,"Daily","Weekly")) | AA52: =IF(T52="",0,IF(T52<12,T52*Controls!$B$13,T52*5)) | AB52: =IF(E52="",0,NETWORKDAYS(E52,Controls!$B$20,Ref!$K$2:$K$42)) | AC52: =IF(OR(AF52=1,AND(AA52>0,AB52>=Controls!$B$23*AA52)),1,0) | AD52: =IF(AND(E52<>"",E52>=Controls!$B$21,E52<=Controls!$B$22),1,0) | AE52: =IF(IFERROR(VLOOKUP(D52,Controls!$A$36:$E$46,2,FALSE()),"No")="Yes",1,0) | AF52: =IF(IFERROR(VLOOKUP(D52,Controls!$A$36:$E$46,3,FALSE()),"No")="Yes",1,0) | AG52: =IF(IFERROR(VLOOKUP(D52,Controls!$A$36:$E$46,4,FALSE()),"No")="Yes",1,0) | AH52: =IF(IFERROR(VLOOKUP(D52,Controls!$A$36:$E$46,5,FALSE()),"No")="Yes",1,0) | AI52: =IF(ISNUMBER(MATCH(D52,Controls!$A$36:$A$46,0)),1,0) | AJ52: =Q52-N52 | AK52: =IF(AE52=1,MAX(0,N52-Q52),0) | AL52: =IF(OR(V52="",V52=0),0,N52/V52) | AM52: =IF(OR(V52="",V52=0),0,1) | AN52: =IF(OR(E52="",F52=""),0,NETWORKDAYS(E52,F52,Ref!$K$2:$K$42)) | AO52: =IF(L52="Renewal",1,0) | AP52: =AC52*AD52 | AQ52: =IF(AND(G52<>"",'Historical Score'!$C$6<>""),IF(G52='Historical Score'!$C$6,1,0),0) | AR52: =IF(AND(L52<>"",'Historical Score'!$C$5<>""),IF(L52='Historical Score'!$C$5,1,0),0) | AS52: =IF(AND(Y52<>"",'Historical Score'!$C$7<>""),IF(Y52='Historical Score'!$C$7,1,0),0) | AT52: =IF(AND(K52<>"",'Historical Score'!$C$8<>""),IF(K52='Historical Score'!$C$8,1,0),0) | BA52: =IF(AD52=1,(AR52*'Historical Score'!$K$29+1-'Historical Score'!$K$29)*(AT52*'Historical Score'!$L$29+1-'Historical Score'!$L$29)*(AS52*'Historical Score'!$M$29+1-'Historical Score'!$M$29)*(AQ52*'Historical Score'!$N$29+1-'Historical Score'!$N$29),0)
A53: 5674153395 | B53: Happy Daiquiri llc | C53: Happy Daiquiri llc | D53: Legal | E53: 45741 | F53: 45889 | G53: 6 | H53: 5812 | I53: 58 | J53: TX | K53: Vanguard Equities | L53: New Deal | M53: 1.49 | N53: 3000 | O53: 420 | P53: 4470 | Q53: 2475.22 | R53: 1994.78 | S53: 0.55374049 | T53: 1.967 | U53: 34 | W53: 0.1093 | X53: 43819 | Y53: =IF(I53="","No SIC",IFERROR(VLOOKUP(I53,Ref!$A$2:$B$65,2,FALSE()),"Unclassified")) | Z53: =IF(T53="","",IF(T53<12,"Daily","Weekly")) | AA53: =IF(T53="",0,IF(T53<12,T53*Controls!$B$13,T53*5)) | AB53: =IF(E53="",0,NETWORKDAYS(E53,Controls!$B$20,Ref!$K$2:$K$42)) | AC53: =IF(OR(AF53=1,AND(AA53>0,AB53>=Controls!$B$23*AA53)),1,0) | AD53: =IF(AND(E53<>"",E53>=Controls!$B$21,E53<=Controls!$B$22),1,0) | AE53: =IF(IFERROR(VLOOKUP(D53,Controls!$A$36:$E$46,2,FALSE()),"No")="Yes",1,0) | AF53: =IF(IFERROR(VLOOKUP(D53,Controls!$A$36:$E$46,3,FALSE()),"No")="Yes",1,0) | AG53: =IF(IFERROR(VLOOKUP(D53,Controls!$A$36:$E$46,4,FALSE()),"No")="Yes",1,0) | AH53: =IF(IFERROR(VLOOKUP(D53,Controls!$A$36:$E$46,5,FALSE()),"No")="Yes",1,0) | AI53: =IF(ISNUMBER(MATCH(D53,Controls!$A$36:$A$46,0)),1,0) | AJ53: =Q53-N53 | AK53: =IF(AE53=1,MAX(0,N53-Q53),0) | AL53: =IF(OR(V53="",V53=0),0,N53/V53) | AM53: =IF(OR(V53="",V53=0),0,1) | AN53: =IF(OR(E53="",F53=""),0,NETWORKDAYS(E53,F53,Ref!$K$2:$K$42)) | AO53: =IF(L53="Renewal",1,0) | AP53: =AC53*AD53 | AQ53: =IF(AND(G53<>"",'Historical Score'!$C$6<>""),IF(G53='Historical Score'!$C$6,1,0),0) | AR53: =IF(AND(L53<>"",'Historical Score'!$C$5<>""),IF(L53='Historical Score'!$C$5,1,0),0) | AS53: =IF(AND(Y53<>"",'Historical Score'!$C$7<>""),IF(Y53='Historical Score'!$C$7,1,0),0) | AT53: =IF(AND(K53<>"",'Historical Score'!$C$8<>""),IF(K53='Historical Score'!$C$8,1,0),0) | BA53: =IF(AD53=1,(AR53*'Historical Score'!$K$29+1-'Historical Score'!$K$29)*(AT53*'Historical Score'!$L$29+1-'Historical Score'!$L$29)*(AS53*'Historical Score'!$M$29+1-'Historical Score'!$M$29)*(AQ53*'Historical Score'!$N$29+1-'Historical Score'!$N$29),0)
A54: 5674153450 | B54: Journey Homecare Services | C54: Journey Homecare Services | D54: Legal | E54: 45742 | F54: 46112 | G54: 3 | H54: 8051 | I54: 80 | J54: NC | K54: Vanguard Equities | L54: New Deal | M54: 1.49 | N54: 5000 | O54: 700 | P54: 7450 | Q54: 3293.97 | R54: 4156.03 | S54: 0.44214362 | T54: 2.131 | U54: 20 | W54: 0.1172 | Y54: =IF(I54="","No SIC",IFERROR(VLOOKUP(I54,Ref!$A$2:$B$65,2,FALSE()),"Unclassified")) | Z54: =IF(T54="","",IF(T54<12,"Daily","Weekly")) | AA54: =IF(T54="",0,IF(T54<12,T54*Controls!$B$13,T54*5)) | AB54: =IF(E54="",0,NETWORKDAYS(E54,Controls!$B$20,Ref!$K$2:$K$42)) | AC54: =IF(OR(AF54=1,AND(AA54>0,AB54>=Controls!$B$23*AA54)),1,0) | AD54: =IF(AND(E54<>"",E54>=Controls!$B$21,E54<=Controls!$B$22),1,0) | AE54: =IF(IFERROR(VLOOKUP(D54,Controls!$A$36:$E$46,2,FALSE()),"No")="Yes",1,0) | AF54: =IF(IFERROR(VLOOKUP(D54,Controls!$A$36:$E$46,3,FALSE()),"No")="Yes",1,0) | AG54: =IF(IFERROR(VLOOKUP(D54,Controls!$A$36:$E$46,4,FALSE()),"No")="Yes",1,0) | AH54: =IF(IFERROR(VLOOKUP(D54,Controls!$A$36:$E$46,5,FALSE()),"No")="Yes",1,0) | AI54: =IF(ISNUMBER(MATCH(D54,Controls!$A$36:$A$46,0)),1,0) | AJ54: =Q54-N54 | AK54: =IF(AE54=1,MAX(0,N54-Q54),0) | AL54: =IF(OR(V54="",V54=0),0,N54/V54) | AM54: =IF(OR(V54="",V54=0),0,1) | AN54: =IF(OR(E54="",F54=""),0,NETWORKDAYS(E54,F54,Ref!$K$2:$K$42)) | AO54: =IF(L54="Renewal",1,0) | AP54: =AC54*AD54 | AQ54: =IF(AND(G54<>"",'Historical Score'!$C$6<>""),IF(G54='Historical Score'!$C$6,1,0),0) | AR54: =IF(AND(L54<>"",'Historical Score'!$C$5<>""),IF(L54='Historical Score'!$C$5,1,0),0) | AS54: =IF(AND(Y54<>"",'Historical Score'!$C$7<>""),IF(Y54='Historical Score'!$C$7,1,0),0) | AT54: =IF(AND(K54<>"",'Historical Score'!$C$8<>""),IF(K54='Historical Score'!$C$8,1,0),0) | BA54: =IF(AD54=1,(AR54*'Historical Score'!$K$29+1-'Historical Score'!$K$29)*(AT54*'Historical Score'!$L$29+1-'Historical Score'!$L$29)*(AS54*'Historical Score'!$M$29+1-'Historical Score'!$M$29)*(AQ54*'Historical Score'!$N$29+1-'Historical Score'!$N$29),0)
A55: 5674153597 | B55: Anthony's RV Rentals | C55: Anthony's RV Rentals | D55: Legal | E55: 45743 | F55: 45866 | G55: 2 | H55: 7519 | I55: 75 | J55: MI | K55: Platform Funding | L55: Renewal | M55: 1.49 | N55: 15000 | O55: 0 | P55: 22350 | Q55: 6115.1 | R55: 16234.9 | S55: 0.27360626 | T55: 2.459 | U55: 8 | W55: 0.1567 | X55: 43617 | Y55: =IF(I55="","No SIC",IFERROR(VLOOKUP(I55,Ref!$A$2:$B$65,2,FALSE()),"Unclassified")) | Z55: =IF(T55="","",IF(T55<12,"Daily","Weekly")) | AA55: =IF(T55="",0,IF(T55<12,T55*Controls!$B$13,T55*5)) | AB55: =IF(E55="",0,NETWORKDAYS(E55,Controls!$B$20,Ref!$K$2:$K$42)) | AC55: =IF(OR(AF55=1,AND(AA55>0,AB55>=Controls!$B$23*AA55)),1,0) | AD55: =IF(AND(E55<>"",E55>=Controls!$B$21,E55<=Controls!$B$22),1,0) | AE55: =IF(IFERROR(VLOOKUP(D55,Controls!$A$36:$E$46,2,FALSE()),"No")="Yes",1,0) | AF55: =IF(IFERROR(VLOOKUP(D55,Controls!$A$36:$E$46,3,FALSE()),"No")="Yes",1,0) | AG55: =IF(IFERROR(VLOOKUP(D55,Controls!$A$36:$E$46,4,FALSE()),"No")="Yes",1,0) | AH55: =IF(IFERROR(VLOOKUP(D55,Controls!$A$36:$E$46,5,FALSE()),"No")="Yes",1,0) | AI55: =IF(ISNUMBER(MATCH(D55,Controls!$A$36:$A$46,0)),1,0) | AJ55: =Q55-N55 | AK55: =IF(AE55=1,MAX(0,N55-Q55),0) | AL55: =IF(OR(V55="",V55=0),0,N55/V55) | AM55: =IF(OR(V55="",V55=0),0,1) | AN55: =IF(OR(E55="",F55=""),0,NETWORKDAYS(E55,F55,Ref!$K$2:$K$42)) | AO55: =IF(L55="Renewal",1,0) | AP55: =AC55*AD55 | AQ55: =IF(AND(G55<>"",'Historical Score'!$C$6<>""),IF(G55='Historical Score'!$C$6,1,0),0) | AR55: =IF(AND(L55<>"",'Historical Score'!$C$5<>""),IF(L55='Historical Score'!$C$5,1,0),0) | AS55: =IF(AND(Y55<>"",'Historical Score'!$C$7<>""),IF(Y55='Historical Score'!$C$7,1,0),0) | AT55: =IF(AND(K55<>"",'Historical Score'!$C$8<>""),IF(K55='Historical Score'!$C$8,1,0),0) | BA55: =IF(AD55=1,(AR55*'Historical Score'!$K$29+1-'Historical Score'!$K$29)*(AT55*'Historical Score'!$L$29+1-'Historical Score'!$L$29)*(AS55*'Historical Score'!$M$29+1-'Historical Score'!$M$29)*(AQ55*'Historical Score'!$N$29+1-'Historical Score'!$N$29),0)
A56: 5674153862 | B56: W.H.S Humble & Associates LLC | C56: W.H.S Humble & Associates LLC | D56: Legal | E56: 45747 | F56: 45807 | G56: 6 | H56: 7291 | I56: 72 | J56: CA | K56: ROYAL FUNDING GROUP | L56: New Deal | M56: 1.499 | N56: 6500 | O56: 910 | P56: 9743.5 | Q56: 4178.4 | R56: 5565.1 | S56: 0.42883974 | T56: 2.295 | U56: 15 | W56: 0.0831 | X56: 44846 | Y56: =IF(I56="","No SIC",IFERROR(VLOOKUP(I56,Ref!$A$2:$B$65,2,FALSE()),"Unclassified")) | Z56: =IF(T56="","",IF(T56<12,"Daily","Weekly")) | AA56: =IF(T56="",0,IF(T56<12,T56*Controls!$B$13,T56*5)) | AB56: =IF(E56="",0,NETWORKDAYS(E56,Controls!$B$20,Ref!$K$2:$K$42)) | AC56: =IF(OR(AF56=1,AND(AA56>0,AB56>=Controls!$B$23*AA56)),1,0) | AD56: =IF(AND(E56<>"",E56>=Controls!$B$21,E56<=Controls!$B$22),1,0) | AE56: =IF(IFERROR(VLOOKUP(D56,Controls!$A$36:$E$46,2,FALSE()),"No")="Yes",1,0) | AF56: =IF(IFERROR(VLOOKUP(D56,Controls!$A$36:$E$46,3,FALSE()),"No")="Yes",1,0) | AG56: =IF(IFERROR(VLOOKUP(D56,Controls!$A$36:$E$46,4,FALSE()),"No")="Yes",1,0) | AH56: =IF(IFERROR(VLOOKUP(D56,Controls!$A$36:$E$46,5,FALSE()),"No")="Yes",1,0) | AI56: =IF(ISNUMBER(MATCH(D56,Controls!$A$36:$A$46,0)),1,0) | AJ56: =Q56-N56 | AK56: =IF(AE56=1,MAX(0,N56-Q56),0) | AL56: =IF(OR(V56="",V56=0),0,N56/V56) | AM56: =IF(OR(V56="",V56=0),0,1) | AN56: =IF(OR(E56="",F56=""),0,NETWORKDAYS(E56,F56,Ref!$K$2:$K$42)) | AO56: =IF(L56="Renewal",1,0) | AP56: =AC56*AD56 | AQ56: =IF(AND(G56<>"",'Historical Score'!$C$6<>""),IF(G56='Historical Score'!$C$6,1,0),0) | AR56: =IF(AND(L56<>"",'Historical Score'!$C$5<>""),IF(L56='Historical Score'!$C$5,1,0),0) | AS56: =IF(AND(Y56<>"",'Historical Score'!$C$7<>""),IF(Y56='Historical Score'!$C$7,1,0),0) | AT56: =IF(AND(K56<>"",'Historical Score'!$C$8<>""),IF(K56='Historical Score'!$C$8,1,0),0) | BA56: =IF(AD56=1,(AR56*'Historical Score'!$K$29+1-'Historical Score'!$K$29)*(AT56*'Historical Score'!$L$29+1-'Historical Score'!$L$29)*(AS56*'Historical Score'!$M$29+1-'Historical Score'!$M$29)*(AQ56*'Historical Score'!$N$29+1-'Historical Score'!$N$29),0)
A57: 5674153904 | B57: RANDY ROBBINS AGENCY LLC | C57: RANDY ROBBINS AGENCY LLC | D57: Closed | E57: 45748 | F57: 45883 | G57: 1 | H57: 6411 | I57: 64 | J57: OK | K57: United Secured Capital 8 | L57: New Deal | M57: 1.49 | N57: 10000 | O57: 1400 | P57: 14900 | Q57: 14900 | R57: 0 | S57: 1 | T57: 3.115 | U57: 0 | W57: 0.121 | X57: 41821 | Y57: =IF(I57="","No SIC",IFERROR(VLOOKUP(I57,Ref!$A$2:$B$65,2,FALSE()),"Unclassified")) | Z57: =IF(T57="","",IF(T57<12,"Daily","Weekly")) | AA57: =IF(T57="",0,IF(T57<12,T57*Controls!$B$13,T57*5)) | AB57: =IF(E57="",0,NETWORKDAYS(E57,Controls!$B$20,Ref!$K$2:$K$42)) | AC57: =IF(OR(AF57=1,AND(AA57>0,AB57>=Controls!$B$23*AA57)),1,0) | AD57: =IF(AND(E57<>"",E57>=Controls!$B$21,E57<=Controls!$B$22),1,0) | AE57: =IF(IFERROR(VLOOKUP(D57,Controls!$A$36:$E$46,2,FALSE()),"No")="Yes",1,0) | AF57: =IF(IFERROR(VLOOKUP(D57,Controls!$A$36:$E$46,3,FALSE()),"No")="Yes",1,0) | AG57: =IF(IFERROR(VLOOKUP(D57,Controls!$A$36:$E$46,4,FALSE()),"No")="Yes",1,0) | AH57: =IF(IFERROR(VLOOKUP(D57,Controls!$A$36:$E$46,5,FALSE()),"No")="Yes",1,0) | AI57: =IF(ISNUMBER(MATCH(D57,Controls!$A$36:$A$46,0)),1,0) | AJ57: =Q57-N57 | AK57: =IF(AE57=1,MAX(0,N57-Q57),0) | AL57: =IF(OR(V57="",V57=0),0,N57/V57) | AM57: =IF(OR(V57="",V57=0),0,1) | AN57: =IF(OR(E57="",F57=""),0,NETWORKDAYS(E57,F57,Ref!$K$2:$K$42)) | AO57: =IF(L57="Renewal",1,0) | AP57: =AC57*AD57 | AQ57: =IF(AND(G57<>"",'Historical Score'!$C$6<>""),IF(G57='Historical Score'!$C$6,1,0),0) | AR57: =IF(AND(L57<>"",'Historical Score'!$C$5<>""),IF(L57='Historical Score'!$C$5,1,0),0) | AS57: =IF(AND(Y57<>"",'Historical Score'!$C$7<>""),IF(Y57='Historical Score'!$C$7,1,0),0) | AT57: =IF(AND(K57<>"",'Historical Score'!$C$8<>""),IF(K57='Historical Score'!$C$8,1,0),0) | BA57: =IF(AD57=1,(AR57*'Historical Score'!$K$29+1-'Historical Score'!$K$29)*(AT57*'Historical Score'!$L$29+1-'Historical Score'!$L$29)*(AS57*'Historical Score'!$M$29+1-'Historical Score'!$M$29)*(AQ57*'Historical Score'!$N$29+1-'Historical Score'!$N$29),0)
A58: 5674153985 | B58: CAREFOCUS CORPORATION | C58: CAREFOCUS CORPORATION | D58: Closed | E58: 45749 | F58: 45888 | G58: 4 | H58: 8082 | I58: 80 | J58: MN | K58: United Secured Capital 8 | L58: New Deal | M58: 1.49 | N58: 20000 | O58: 2800 | P58: 29800 | Q58: 29800 | R58: 0 | S58: 1 | T58: 16 | U58: 1 | W58: 0.016 | Y58: =IF(I58="","No SIC",IFERROR(VLOOKUP(I58,Ref!$A$2:$B$65,2,FALSE()),"Unclassified")) | Z58: =IF(T58="","",IF(T58<12,"Daily","Weekly")) | AA58: =IF(T58="",0,IF(T58<12,T58*Controls!$B$13,T58*5)) | AB58: =IF(E58="",0,NETWORKDAYS(E58,Controls!$B$20,Ref!$K$2:$K$42)) | AC58: =IF(OR(AF58=1,AND(AA58>0,AB58>=Controls!$B$23*AA58)),1,0) | AD58: =IF(AND(E58<>"",E58>=Controls!$B$21,E58<=Controls!$B$22),1,0) | AE58: =IF(IFERROR(VLOOKUP(D58,Controls!$A$36:$E$46,2,FALSE()),"No")="Yes",1,0) | AF58: =IF(IFERROR(VLOOKUP(D58,Controls!$A$36:$E$46,3,FALSE()),"No")="Yes",1,0) | AG58: =IF(IFERROR(VLOOKUP(D58,Controls!$A$36:$E$46,4,FALSE()),"No")="Yes",1,0) | AH58: =IF(IFERROR(VLOOKUP(D58,Controls!$A$36:$E$46,5,FALSE()),"No")="Yes",1,0) | AI58: =IF(ISNUMBER(MATCH(D58,Controls!$A$36:$A$46,0)),1,0) | AJ58: =Q58-N58 | AK58: =IF(AE58=1,MAX(0,N58-Q58),0) | AL58: =IF(OR(V58="",V58=0),0,N58/V58) | AM58: =IF(OR(V58="",V58=0),0,1) | AN58: =IF(OR(E58="",F58=""),0,NETWORKDAYS(E58,F58,Ref!$K$2:$K$42)) | AO58: =IF(L58="Renewal",1,0) | AP58: =AC58*AD58 | AQ58: =IF(AND(G58<>"",'Historical Score'!$C$6<>""),IF(G58='Historical Score'!$C$6,1,0),0) | AR58: =IF(AND(L58<>"",'Historical Score'!$C$5<>""),IF(L58='Historical Score'!$C$5,1,0),0) | AS58: =IF(AND(Y58<>"",'Historical Score'!$C$7<>""),IF(Y58='Historical Score'!$C$7,1,0),0) | AT58: =IF(AND(K58<>"",'Historical Score'!$C$8<>""),IF(K58='Historical Score'!$C$8,1,0),0) | BA58: =IF(AD58=1,(AR58*'Historical Score'!$K$29+1-'Historical Score'!$K$29)*(AT58*'Historical Score'!$L$29+1-'Historical Score'!$L$29)*(AS58*'Historical Score'!$M$29+1-'Historical Score'!$M$29)*(AQ58*'Historical Score'!$N$29+1-'Historical Score'!$N$29),0)
A59: 5674154010 | B59: G Force Fiber Optics | C59: G Force Fiber Optics | D59: Legal | E59: 45749 | F59: 45755 | G59: 4 | H59: 3357 | I59: 33 | J59: TX | K59: United Secured Capital 8 | L59: New Deal | M59: 1.49 | N59: 20000 | O59: 0 | P59: 29800 | Q59: 0 | R59: 29800 | S59: 0 | T59: 16 | U59: 1 | W59: 0.0467 | X59: 43831 | Y59: =IF(I59="","No SIC",IFERROR(VLOOKUP(I59,Ref!$A$2:$B$65,2,FALSE()),"Unclassified")) | Z59: =IF(T59="","",IF(T59<12,"Daily","Weekly")) | AA59: =IF(T59="",0,IF(T59<12,T59*Controls!$B$13,T59*5)) | AB59: =IF(E59="",0,NETWORKDAYS(E59,Controls!$B$20,Ref!$K$2:$K$42)) | AC59: =IF(OR(AF59=1,AND(AA59>0,AB59>=Controls!$B$23*AA59)),1,0) | AD59: =IF(AND(E59<>"",E59>=Controls!$B$21,E59<=Controls!$B$22),1,0) | AE59: =IF(IFERROR(VLOOKUP(D59,Controls!$A$36:$E$46,2,FALSE()),"No")="Yes",1,0) | AF59: =IF(IFERROR(VLOOKUP(D59,Controls!$A$36:$E$46,3,FALSE()),"No")="Yes",1,0) | AG59: =IF(IFERROR(VLOOKUP(D59,Controls!$A$36:$E$46,4,FALSE()),"No")="Yes",1,0) | AH59: =IF(IFERROR(VLOOKUP(D59,Controls!$A$36:$E$46,5,FALSE()),"No")="Yes",1,0) | AI59: =IF(ISNUMBER(MATCH(D59,Controls!$A$36:$A$46,0)),1,0) | AJ59: =Q59-N59 | AK59: =IF(AE59=1,MAX(0,N59-Q59),0) | AL59: =IF(OR(V59="",V59=0),0,N59/V59) | AM59: =IF(OR(V59="",V59=0),0,1) | AN59: =IF(OR(E59="",F59=""),0,NETWORKDAYS(E59,F59,Ref!$K$2:$K$42)) | AO59: =IF(L59="Renewal",1,0) | AP59: =AC59*AD59 | AQ59: =IF(AND(G59<>"",'Historical Score'!$C$6<>""),IF(G59='Historical Score'!$C$6,1,0),0) | AR59: =IF(AND(L59<>"",'Historical Score'!$C$5<>""),IF(L59='Historical Score'!$C$5,1,0),0) | AS59: =IF(AND(Y59<>"",'Historical Score'!$C$7<>""),IF(Y59='Historical Score'!$C$7,1,0),0) | AT59: =IF(AND(K59<>"",'Historical Score'!$C$8<>""),IF(K59='Historical Score'!$C$8,1,0),0) | BA59: =IF(AD59=1,(AR59*'Historical Score'!$K$29+1-'Historical Score'!$K$29)*(AT59*'Historical Score'!$L$29+1-'Historical Score'!$L$29)*(AS59*'Historical Score'!$M$29+1-'Historical Score'!$M$29)*(AQ59*'Historical Score'!$N$29+1-'Historical Score'!$N$29),0)
A60: 5674154070 | B60: HDP SERVICES | C60: HDP SERVICES | D60: Legal | E60: 45749 | F60: 45995 | G60: 2 | H60: 7538 | I60: 75 | J60: AL | K60: Secure Capital Solutions 7 | L60: New Deal | M60: 1.49 | N60: 15000 | O60: 2100 | P60: 22350 | Q60: 12342.36 | R60: 10007.64 | S60: 0.55223087 | T60: 2.951 | U60: 8 | W60: 0.0757 | X60: 43497 | Y60: =IF(I60="","No SIC",IFERROR(VLOOKUP(I60,Ref!$A$2:$B$65,2,FALSE()),"Unclassified")) | Z60: =IF(T60="","",IF(T60<12,"Daily","Weekly")) | AA60: =IF(T60="",0,IF(T60<12,T60*Controls!$B$13,T60*5)) | AB60: =IF(E60="",0,NETWORKDAYS(E60,Controls!$B$20,Ref!$K$2:$K$42)) | AC60: =IF(OR(AF60=1,AND(AA60>0,AB60>=Controls!$B$23*AA60)),1,0) | AD60: =IF(AND(E60<>"",E60>=Controls!$B$21,E60<=Controls!$B$22),1,0) | AE60: =IF(IFERROR(VLOOKUP(D60,Controls!$A$36:$E$46,2,FALSE()),"No")="Yes",1,0) | AF60: =IF(IFERROR(VLOOKUP(D60,Controls!$A$36:$E$46,3,FALSE()),"No")="Yes",1,0) | AG60: =IF(IFERROR(VLOOKUP(D60,Controls!$A$36:$E$46,4,FALSE()),"No")="Yes",1,0) | AH60: =IF(IFERROR(VLOOKUP(D60,Controls!$A$36:$E$46,5,FALSE()),"No")="Yes",1,0) | AI60: =IF(ISNUMBER(MATCH(D60,Controls!$A$36:$A$46,0)),1,0) | AJ60: =Q60-N60 | AK60: =IF(AE60=1,MAX(0,N60-Q60),0) | AL60: =IF(OR(V60="",V60=0),0,N60/V60) | AM60: =IF(OR(V60="",V60=0),0,1) | AN60: =IF(OR(E60="",F60=""),0,NETWORKDAYS(E60,F60,Ref!$K$2:$K$42)) | AO60: =IF(L60="Renewal",1,0) | AP60: =AC60*AD60 | AQ60: =IF(AND(G60<>"",'Historical Score'!$C$6<>""),IF(G60='Historical Score'!$C$6,1,0),0) | AR60: =IF(AND(L60<>"",'Historical Score'!$C$5<>""),IF(L60='Historical Score'!$C$5,1,0),0) | AS60: =IF(AND(Y60<>"",'Historical Score'!$C$7<>""),IF(Y60='Historical Score'!$C$7,1,0),0) | AT60: =IF(AND(K60<>"",'Historical Score'!$C$8<>""),IF(K60='Historical Score'!$C$8,1,0),0) | BA60: =IF(AD60=1,(AR60*'Historical Score'!$K$29+1-'Historical Score'!$K$29)*(AT60*'Historical Score'!$L$29+1-'Historical Score'!$L$29)*(AS60*'Historical Score'!$M$29+1-'Historical Score'!$M$29)*(AQ60*'Historical Score'!$N$29+1-'Historical Score'!$N$29),0)
A61: 5674154093 | B61: Alba Italian Kitchen | C61: Tirupati Enterprises Limited | D61: Written-Off | E61: 45750 | F61: 45995 | G61: 5 | H61: 5812 | I61: 58 | J61: IL | K61: United Secured Capital 8 | L61: New Deal | M61: 1.49 | N61: 15000 | O61: 2100 | P61: 22350 | Q61: 16988.01 | R61: 5361.99 | S61: 0.76008993 | T61: 2.951 | U61: 17 | W61: 0.1195 | X61: 45342 | Y61: =IF(I61="","No SIC",IFERROR(VLOOKUP(I61,Ref!$A$2:$B$65,2,FALSE()),"Unclassified")) | Z61: =IF(T61="","",IF(T61<12,"Daily","Weekly")) | AA61: =IF(T61="",0,IF(T61<12,T61*Controls!$B$13,T61*5)) | AB61: =IF(E61="",0,NETWORKDAYS(E61,Controls!$B$20,Ref!$K$2:$K$42)) | AC61: =IF(OR(AF61=1,AND(AA61>0,AB61>=Controls!$B$23*AA61)),1,0) | AD61: =IF(AND(E61<>"",E61>=Controls!$B$21,E61<=Controls!$B$22),1,0) | AE61: =IF(IFERROR(VLOOKUP(D61,Controls!$A$36:$E$46,2,FALSE()),"No")="Yes",1,0) | AF61: =IF(IFERROR(VLOOKUP(D61,Controls!$A$36:$E$46,3,FALSE()),"No")="Yes",1,0) | AG61: =IF(IFERROR(VLOOKUP(D61,Controls!$A$36:$E$46,4,FALSE()),"No")="Yes",1,0) | AH61: =IF(IFERROR(VLOOKUP(D61,Controls!$A$36:$E$46,5,FALSE()),"No")="Yes",1,0) | AI61: =IF(ISNUMBER(MATCH(D61,Controls!$A$36:$A$46,0)),1,0) | AJ61: =Q61-N61 | AK61: =IF(AE61=1,MAX(0,N61-Q61),0) | AL61: =IF(OR(V61="",V61=0),0,N61/V61) | AM61: =IF(OR(V61="",V61=0),0,1) | AN61: =IF(OR(E61="",F61=""),0,NETWORKDAYS(E61,F61,Ref!$K$2:$K$42)) | AO61: =IF(L61="Renewal",1,0) | AP61: =AC61*AD61 | AQ61: =IF(AND(G61<>"",'Historical Score'!$C$6<>""),IF(G61='Historical Score'!$C$6,1,0),0) | AR61: =IF(AND(L61<>"",'Historical Score'!$C$5<>""),IF(L61='Historical Score'!$C$5,1,0),0) | AS61: =IF(AND(Y61<>"",'Historical Score'!$C$7<>""),IF(Y61='Historical Score'!$C$7,1,0),0) | AT61: =IF(AND(K61<>"",'Historical Score'!$C$8<>""),IF(K61='Historical Score'!$C$8,1,0),0) | BA61: =IF(AD61=1,(AR61*'Historical Score'!$K$29+1-'Historical Score'!$K$29)*(AT61*'Historical Score'!$L$29+1-'Historical Score'!$L$29)*(AS61*'Historical Score'!$M$29+1-'Historical Score'!$M$29)*(AQ61*'Historical Score'!$N$29+1-'Historical Score'!$N$29),0)
A62: 5674154267 | B62: MMMJ INVESTMENTS, LLC | C62: MMMJ INVESTMENTS, LLC | D62: Legal | E62: 45751 | F62: 45908 | G62: 4 | H62: 5812 | I62: 58 | J62: GA | K62: United Secured Capital 8 | L62: New Deal | M62: 1.43 | N62: 18000 | O62: 1980 | P62: 25740 | Q62: 13437.35 | R62: 12302.65 | S62: 0.52204157 | T62: 2.951 | U62: 20 | W62: 0.2026 | Y62: =IF(I62="","No SIC",IFERROR(VLOOKUP(I62,Ref!$A$2:$B$65,2,FALSE()),"Unclassified")) | Z62: =IF(T62="","",IF(T62<12,"Daily","Weekly")) | AA62: =IF(T62="",0,IF(T62<12,T62*Controls!$B$13,T62*5)) | AB62: =IF(E62="",0,NETWORKDAYS(E62,Controls!$B$20,Ref!$K$2:$K$42)) | AC62: =IF(OR(AF62=1,AND(AA62>0,AB62>=Controls!$B$23*AA62)),1,0) | AD62: =IF(AND(E62<>"",E62>=Controls!$B$21,E62<=Controls!$B$22),1,0) | AE62: =IF(IFERROR(VLOOKUP(D62,Controls!$A$36:$E$46,2,FALSE()),"No")="Yes",1,0) | AF62: =IF(IFERROR(VLOOKUP(D62,Controls!$A$36:$E$46,3,FALSE()),"No")="Yes",1,0) | AG62: =IF(IFERROR(VLOOKUP(D62,Controls!$A$36:$E$46,4,FALSE()),"No")="Yes",1,0) | AH62: =IF(IFERROR(VLOOKUP(D62,Controls!$A$36:$E$46,5,FALSE()),"No")="Yes",1,0) | AI62: =IF(ISNUMBER(MATCH(D62,Controls!$A$36:$A$46,0)),1,0) | AJ62: =Q62-N62 | AK62: =IF(AE62=1,MAX(0,N62-Q62),0) | AL62: =IF(OR(V62="",V62=0),0,N62/V62) | AM62: =IF(OR(V62="",V62=0),0,1) | AN62: =IF(OR(E62="",F62=""),0,NETWORKDAYS(E62,F62,Ref!$K$2:$K$42)) | AO62: =IF(L62="Renewal",1,0) | AP62: =AC62*AD62 | AQ62: =IF(AND(G62<>"",'Historical Score'!$C$6<>""),IF(G62='Historical Score'!$C$6,1,0),0) | AR62: =IF(AND(L62<>"",'Historical Score'!$C$5<>""),IF(L62='Historical Score'!$C$5,1,0),0) | AS62: =IF(AND(Y62<>"",'Historical Score'!$C$7<>""),IF(Y62='Historical Score'!$C$7,1,0),0) | AT62: =IF(AND(K62<>"",'Historical Score'!$C$8<>""),IF(K62='Historical Score'!$C$8,1,0),0) | BA62: =IF(AD62=1,(AR62*'Historical Score'!$K$29+1-'Historical Score'!$K$29)*(AT62*'Historical Score'!$L$29+1-'Historical Score'!$L$29)*(AS62*'Historical Score'!$M$29+1-'Historical Score'!$M$29)*(AQ62*'Historical Score'!$N$29+1-'Historical Score'!$N$29),0)
A63: 5674154332 | B63: Smith and Webster II Oral Springs LLC | C63: SMITH AND WEBSTER RESTAURANT CORAL SPRINGS | D63: Closed | E63: 45751 | F63: 45946 | G63: 4 | H63: 5812 | I63: 58 | J63: FL | K63: Fidelity Funding | L63: New Deal | M63: 1.49 | N63: 33000 | O63: 4620 | P63: 49170 | Q63: 49170 | R63: 0 | S63: 1 | T63: 20 | U63: 11 | W63: 0.0981 | X63: 45198 | Y63: =IF(I63="","No SIC",IFERROR(VLOOKUP(I63,Ref!$A$2:$B$65,2,FALSE()),"Unclassified")) | Z63: =IF(T63="","",IF(T63<12,"Daily","Weekly")) | AA63: =IF(T63="",0,IF(T63<12,T63*Controls!$B$13,T63*5)) | AB63: =IF(E63="",0,NETWORKDAYS(E63,Controls!$B$20,Ref!$K$2:$K$42)) | AC63: =IF(OR(AF63=1,AND(AA63>0,AB63>=Controls!$B$23*AA63)),1,0) | AD63: =IF(AND(E63<>"",E63>=Controls!$B$21,E63<=Controls!$B$22),1,0) | AE63: =IF(IFERROR(VLOOKUP(D63,Controls!$A$36:$E$46,2,FALSE()),"No")="Yes",1,0) | AF63: =IF(IFERROR(VLOOKUP(D63,Controls!$A$36:$E$46,3,FALSE()),"No")="Yes",1,0) | AG63: =IF(IFERROR(VLOOKUP(D63,Controls!$A$36:$E$46,4,FALSE()),"No")="Yes",1,0) | AH63: =IF(IFERROR(VLOOKUP(D63,Controls!$A$36:$E$46,5,FALSE()),"No")="Yes",1,0) | AI63: =IF(ISNUMBER(MATCH(D63,Controls!$A$36:$A$46,0)),1,0) | AJ63: =Q63-N63 | AK63: =IF(AE63=1,MAX(0,N63-Q63),0) | AL63: =IF(OR(V63="",V63=0),0,N63/V63) | AM63: =IF(OR(V63="",V63=0),0,1) | AN63: =IF(OR(E63="",F63=""),0,NETWORKDAYS(E63,F63,Ref!$K$2:$K$42)) | AO63: =IF(L63="Renewal",1,0) | AP63: =AC63*AD63 | AQ63: =IF(AND(G63<>"",'Historical Score'!$C$6<>""),IF(G63='Historical Score'!$C$6,1,0),0) | AR63: =IF(AND(L63<>"",'Historical Score'!$C$5<>""),IF(L63='Historical Score'!$C$5,1,0),0) | AS63: =IF(AND(Y63<>"",'Historical Score'!$C$7<>""),IF(Y63='Historical Score'!$C$7,1,0),0) | AT63: =IF(AND(K63<>"",'Historical Score'!$C$8<>""),IF(K63='Historical Score'!$C$8,1,0),0) | BA63: =IF(AD63=1,(AR63*'Historical Score'!$K$29+1-'Historical Score'!$K$29)*(AT63*'Historical Score'!$L$29+1-'Historical Score'!$L$29)*(AS63*'Historical Score'!$M$29+1-'Historical Score'!$M$29)*(AQ63*'Historical Score'!$N$29+1-'Historical Score'!$N$29),0)
A64: 5674154422 | B64: BUSHCO CONTRACTING | C64: BUSHCO CONTRACTING | D64: Legal | E64: 45754 | F64: 45786 | G64: 2 | H64: 1521 | I64: 15 | J64: CA | K64: GREYSTONE | L64: New Deal | M64: 1.49 | N64: 14000 | O64: 1680 | P64: 20860 | Q64: 2318.06 | R64: 18541.94 | S64: 0.11112464 | T64: 18 | U64: 3 | W64: 0.089 | Y64: =IF(I64="","No SIC",IFERROR(VLOOKUP(I64,Ref!$A$2:$B$65,2,FALSE()),"Unclassified")) | Z64: =IF(T64="","",IF(T64<12,"Daily","Weekly")) | AA64: =IF(T64="",0,IF(T64<12,T64*Controls!$B$13,T64*5)) | AB64: =IF(E64="",0,NETWORKDAYS(E64,Controls!$B$20,Ref!$K$2:$K$42)) | AC64: =IF(OR(AF64=1,AND(AA64>0,AB64>=Controls!$B$23*AA64)),1,0) | AD64: =IF(AND(E64<>"",E64>=Controls!$B$21,E64<=Controls!$B$22),1,0) | AE64: =IF(IFERROR(VLOOKUP(D64,Controls!$A$36:$E$46,2,FALSE()),"No")="Yes",1,0) | AF64: =IF(IFERROR(VLOOKUP(D64,Controls!$A$36:$E$46,3,FALSE()),"No")="Yes",1,0) | AG64: =IF(IFERROR(VLOOKUP(D64,Controls!$A$36:$E$46,4,FALSE()),"No")="Yes",1,0) | AH64: =IF(IFERROR(VLOOKUP(D64,Controls!$A$36:$E$46,5,FALSE()),"No")="Yes",1,0) | AI64: =IF(ISNUMBER(MATCH(D64,Controls!$A$36:$A$46,0)),1,0) | AJ64: =Q64-N64 | AK64: =IF(AE64=1,MAX(0,N64-Q64),0) | AL64: =IF(OR(V64="",V64=0),0,N64/V64) | AM64: =IF(OR(V64="",V64=0),0,1) | AN64: =IF(OR(E64="",F64=""),0,NETWORKDAYS(E64,F64,Ref!$K$2:$K$42)) | AO64: =IF(L64="Renewal",1,0) | AP64: =AC64*AD64 | AQ64: =IF(AND(G64<>"",'Historical Score'!$C$6<>""),IF(G64='Historical Score'!$C$6,1,0),0) | AR64: =IF(AND(L64<>"",'Historical Score'!$C$5<>""),IF(L64='Historical Score'!$C$5,1,0),0) | AS64: =IF(AND(Y64<>"",'Historical Score'!$C$7<>""),IF(Y64='Historical Score'!$C$7,1,0),0) | AT64: =IF(AND(K64<>"",'Historical Score'!$C$8<>""),IF(K64='Historical Score'!$C$8,1,0),0) | BA64: =IF(AD64=1,(AR64*'Historical Score'!$K$29+1-'Historical Score'!$K$29)*(AT64*'Historical Score'!$L$29+1-'Historical Score'!$L$29)*(AS64*'Historical Score'!$M$29+1-'Historical Score'!$M$29)*(AQ64*'Historical Score'!$N$29+1-'Historical Score'!$N$29),0)
A65: 5674154426 | B65: Zuniga Flowers | C65: Zuniga Flowers | D65: Closed | E65: 45754 | F65: 45911 | G65: 3 | H65: 5992 | I65: 59 | J65: CA | K65: Premium Capital (AMRK) | L65: Renewal | M65: 1.5 | N65: 3000 | O65: 420 | P65: 4500 | Q65: 4500 | R65: 0 | S65: 1 | T65: 2.295 | U65: 15 | W65: 0.1024 | X65: 42678 | Y65: =IF(I65="","No SIC",IFERROR(VLOOKUP(I65,Ref!$A$2:$B$65,2,FALSE()),"Unclassified")) | Z65: =IF(T65="","",IF(T65<12,"Daily","Weekly")) | AA65: =IF(T65="",0,IF(T65<12,T65*Controls!$B$13,T65*5)) | AB65: =IF(E65="",0,NETWORKDAYS(E65,Controls!$B$20,Ref!$K$2:$K$42)) | AC65: =IF(OR(AF65=1,AND(AA65>0,AB65>=Controls!$B$23*AA65)),1,0) | AD65: =IF(AND(E65<>"",E65>=Controls!$B$21,E65<=Controls!$B$22),1,0) | AE65: =IF(IFERROR(VLOOKUP(D65,Controls!$A$36:$E$46,2,FALSE()),"No")="Yes",1,0) | AF65: =IF(IFERROR(VLOOKUP(D65,Controls!$A$36:$E$46,3,FALSE()),"No")="Yes",1,0) | AG65: =IF(IFERROR(VLOOKUP(D65,Controls!$A$36:$E$46,4,FALSE()),"No")="Yes",1,0) | AH65: =IF(IFERROR(VLOOKUP(D65,Controls!$A$36:$E$46,5,FALSE()),"No")="Yes",1,0) | AI65: =IF(ISNUMBER(MATCH(D65,Controls!$A$36:$A$46,0)),1,0) | AJ65: =Q65-N65 | AK65: =IF(AE65=1,MAX(0,N65-Q65),0) | AL65: =IF(OR(V65="",V65=0),0,N65/V65) | AM65: =IF(OR(V65="",V65=0),0,1) | AN65: =IF(OR(E65="",F65=""),0,NETWORKDAYS(E65,F65,Ref!$K$2:$K$42)) | AO65: =IF(L65="Renewal",1,0) | AP65: =AC65*AD65 | AQ65: =IF(AND(G65<>"",'Historical Score'!$C$6<>""),IF(G65='Historical Score'!$C$6,1,0),0) | AR65: =IF(AND(L65<>"",'Historical Score'!$C$5<>""),IF(L65='Historical Score'!$C$5,1,0),0) | AS65: =IF(AND(Y65<>"",'Historical Score'!$C$7<>""),IF(Y65='Historical Score'!$C$7,1,0),0) | AT65: =IF(AND(K65<>"",'Historical Score'!$C$8<>""),IF(K65='Historical Score'!$C$8,1,0),0) | BA65: =IF(AD65=1,(AR65*'Historical Score'!$K$29+1-'Historical Score'!$K$29)*(AT65*'Historical Score'!$L$29+1-'Historical Score'!$L$29)*(AS65*'Historical Score'!$M$29+1-'Historical Score'!$M$29)*(AQ65*'Historical Score'!$N$29+1-'Historical Score'!$N$29),0)
A66: 5674154477 | B66: Fast Line Delivery | C66: Fast Line Delivery LLC | D66: Closed | E66: 45755 | F66: 45820 | G66: 3 | H66: 4215 | I66: 42 | J66: FL | K66: Diamond Bar Funding | L66: New Deal | M66: 1.49 | N66: 6000 | O66: 840 | P66: 8940 | Q66: 8940 | R66: 0 | S66: 1 | T66: 2.623 | U66: 2 | W66: 0.0501 | X66: 44673 | Y66: =IF(I66="","No SIC",IFERROR(VLOOKUP(I66,Ref!$A$2:$B$65,2,FALSE()),"Unclassified")) | Z66: =IF(T66="","",IF(T66<12,"Daily","Weekly")) | AA66: =IF(T66="",0,IF(T66<12,T66*Controls!$B$13,T66*5)) | AB66: =IF(E66="",0,NETWORKDAYS(E66,Controls!$B$20,Ref!$K$2:$K$42)) | AC66: =IF(OR(AF66=1,AND(AA66>0,AB66>=Controls!$B$23*AA66)),1,0) | AD66: =IF(AND(E66<>"",E66>=Controls!$B$21,E66<=Controls!$B$22),1,0) | AE66: =IF(IFERROR(VLOOKUP(D66,Controls!$A$36:$E$46,2,FALSE()),"No")="Yes",1,0) | AF66: =IF(IFERROR(VLOOKUP(D66,Controls!$A$36:$E$46,3,FALSE()),"No")="Yes",1,0) | AG66: =IF(IFERROR(VLOOKUP(D66,Controls!$A$36:$E$46,4,FALSE()),"No")="Yes",1,0) | AH66: =IF(IFERROR(VLOOKUP(D66,Controls!$A$36:$E$46,5,FALSE()),"No")="Yes",1,0) | AI66: =IF(ISNUMBER(MATCH(D66,Controls!$A$36:$A$46,0)),1,0) | AJ66: =Q66-N66 | AK66: =IF(AE66=1,MAX(0,N66-Q66),0) | AL66: =IF(OR(V66="",V66=0),0,N66/V66) | AM66: =IF(OR(V66="",V66=0),0,1) | AN66: =IF(OR(E66="",F66=""),0,NETWORKDAYS(E66,F66,Ref!$K$2:$K$42)) | AO66: =IF(L66="Renewal",1,0) | AP66: =AC66*AD66 | AQ66: =IF(AND(G66<>"",'Historical Score'!$C$6<>""),IF(G66='Historical Score'!$C$6,1,0),0) | AR66: =IF(AND(L66<>"",'Historical Score'!$C$5<>""),IF(L66='Historical Score'!$C$5,1,0),0) | AS66: =IF(AND(Y66<>"",'Historical Score'!$C$7<>""),IF(Y66='Historical Score'!$C$7,1,0),0) | AT66: =IF(AND(K66<>"",'Historical Score'!$C$8<>""),IF(K66='Historical Score'!$C$8,1,0),0) | BA66: =IF(AD66=1,(AR66*'Historical Score'!$K$29+1-'Historical Score'!$K$29)*(AT66*'Historical Score'!$L$29+1-'Historical Score'!$L$29)*(AS66*'Historical Score'!$M$29+1-'Historical Score'!$M$29)*(AQ66*'Historical Score'!$N$29+1-'Historical Score'!$N$29),0)
A67: 5674154563 | B67: R K HOSTEL | C67: DIESTRO INC | D67: Closed | E67: 45756 | F67: 45895 | G67: 2 | H67: 7011 | I67: 70 | J67: CA | K67: PMF | L67: New Deal | M67: 1.4 | N67: 40000 | O67: 3800 | P67: 56000 | Q67: 56000 | R67: 0 | S67: 1 | T67: 36 | U67: 0 | W67: 0.0793 | X67: 37622 | Y67: =IF(I67="","No SIC",IFERROR(VLOOKUP(I67,Ref!$A$2:$B$65,2,FALSE()),"Unclassified")) | Z67: =IF(T67="","",IF(T67<12,"Daily","Weekly")) | AA67: =IF(T67="",0,IF(T67<12,T67*Controls!$B$13,T67*5)) | AB67: =IF(E67="",0,NETWORKDAYS(E67,Controls!$B$20,Ref!$K$2:$K$42)) | AC67: =IF(OR(AF67=1,AND(AA67>0,AB67>=Controls!$B$23*AA67)),1,0) | AD67: =IF(AND(E67<>"",E67>=Controls!$B$21,E67<=Controls!$B$22),1,0) | AE67: =IF(IFERROR(VLOOKUP(D67,Controls!$A$36:$E$46,2,FALSE()),"No")="Yes",1,0) | AF67: =IF(IFERROR(VLOOKUP(D67,Controls!$A$36:$E$46,3,FALSE()),"No")="Yes",1,0) | AG67: =IF(IFERROR(VLOOKUP(D67,Controls!$A$36:$E$46,4,FALSE()),"No")="Yes",1,0) | AH67: =IF(IFERROR(VLOOKUP(D67,Controls!$A$36:$E$46,5,FALSE()),"No")="Yes",1,0) | AI67: =IF(ISNUMBER(MATCH(D67,Controls!$A$36:$A$46,0)),1,0) | AJ67: =Q67-N67 | AK67: =IF(AE67=1,MAX(0,N67-Q67),0) | AL67: =IF(OR(V67="",V67=0),0,N67/V67) | AM67: =IF(OR(V67="",V67=0),0,1) | AN67: =IF(OR(E67="",F67=""),0,NETWORKDAYS(E67,F67,Ref!$K$2:$K$42)) | AO67: =IF(L67="Renewal",1,0) | AP67: =AC67*AD67 | AQ67: =IF(AND(G67<>"",'Historical Score'!$C$6<>""),IF(G67='Historical Score'!$C$6,1,0),0) | AR67: =IF(AND(L67<>"",'Historical Score'!$C$5<>""),IF(L67='Historical Score'!$C$5,1,0),0) | AS67: =IF(AND(Y67<>"",'Historical Score'!$C$7<>""),IF(Y67='Historical Score'!$C$7,1,0),0) | AT67: =IF(AND(K67<>"",'Historical Score'!$C$8<>""),IF(K67='Historical Score'!$C$8,1,0),0) | BA67: =IF(AD67=1,(AR67*'Historical Score'!$K$29+1-'Historical Score'!$K$29)*(AT67*'Historical Score'!$L$29+1-'Historical Score'!$L$29)*(AS67*'Historical Score'!$M$29+1-'Historical Score'!$M$29)*(AQ67*'Historical Score'!$N$29+1-'Historical Score'!$N$29),0)
A68: 5674154668 | B68: BEESON FARMS & HAULING LLC | C68: BEESON FARMS & HAULING LLC | D68: Legal | E68: 45756 | F68: 45926 | G68: 5 | H68: 4212 | I68: 42 | J68: NC | K68: Key Capital Funding | L68: New Deal | M68: 1.49 | N68: 40000 | O68: 5600 | P68: 59600 | Q68: 41149.26 | R68: 18450.74 | S68: 0.69042383 | T68: 24 | U68: 10 | W68: 0.0561 | X68: 43579 | Y68: =IF(I68="","No SIC",IFERROR(VLOOKUP(I68,Ref!$A$2:$B$65,2,FALSE()),"Unclassified")) | Z68: =IF(T68="","",IF(T68<12,"Daily","Weekly")) | AA68: =IF(T68="",0,IF(T68<12,T68*Controls!$B$13,T68*5)) | AB68: =IF(E68="",0,NETWORKDAYS(E68,Controls!$B$20,Ref!$K$2:$K$42)) | AC68: =IF(OR(AF68=1,AND(AA68>0,AB68>=Controls!$B$23*AA68)),1,0) | AD68: =IF(AND(E68<>"",E68>=Controls!$B$21,E68<=Controls!$B$22),1,0) | AE68: =IF(IFERROR(VLOOKUP(D68,Controls!$A$36:$E$46,2,FALSE()),"No")="Yes",1,0) | AF68: =IF(IFERROR(VLOOKUP(D68,Controls!$A$36:$E$46,3,FALSE()),"No")="Yes",1,0) | AG68: =IF(IFERROR(VLOOKUP(D68,Controls!$A$36:$E$46,4,FALSE()),"No")="Yes",1,0) | AH68: =IF(IFERROR(VLOOKUP(D68,Controls!$A$36:$E$46,5,FALSE()),"No")="Yes",1,0) | AI68: =IF(ISNUMBER(MATCH(D68,Controls!$A$36:$A$46,0)),1,0) | AJ68: =Q68-N68 | AK68: =IF(AE68=1,MAX(0,N68-Q68),0) | AL68: =IF(OR(V68="",V68=0),0,N68/V68) | AM68: =IF(OR(V68="",V68=0),0,1) | AN68: =IF(OR(E68="",F68=""),0,NETWORKDAYS(E68,F68,Ref!$K$2:$K$42)) | AO68: =IF(L68="Renewal",1,0) | AP68: =AC68*AD68 | AQ68: =IF(AND(G68<>"",'Historical Score'!$C$6<>""),IF(G68='Historical Score'!$C$6,1,0),0) | AR68: =IF(AND(L68<>"",'Historical Score'!$C$5<>""),IF(L68='Historical Score'!$C$5,1,0),0) | AS68: =IF(AND(Y68<>"",'Historical Score'!$C$7<>""),IF(Y68='Historical Score'!$C$7,1,0),0) | AT68: =IF(AND(K68<>"",'Historical Score'!$C$8<>""),IF(K68='Historical Score'!$C$8,1,0),0) | BA68: =IF(AD68=1,(AR68*'Historical Score'!$K$29+1-'Historical Score'!$K$29)*(AT68*'Historical Score'!$L$29+1-'Historical Score'!$L$29)*(AS68*'Historical Score'!$M$29+1-'Historical Score'!$M$29)*(AQ68*'Historical Score'!$N$29+1-'Historical Score'!$N$29),0)
A69: 5674154700 | B69: LRT SALES LLC | C69: LRT SALES LLC | D69: Closed | E69: 45757 | F69: 45938 | G69: 1 | H69: 1796 | I69: 17 | J69: TX | K69: PMF | L69: New Deal | M69: 1.43 | N69: 20000 | O69: 2200 | P69: 28600 | Q69: 28600 | R69: 0 | S69: 1 | T69: 26 | U69: 0 | W69: 0.1056 | X69: 40963 | Y69: =IF(I69="","No SIC",IFERROR(VLOOKUP(I69,Ref!$A$2:$B$65,2,FALSE()),"Unclassified")) | Z69: =IF(T69="","",IF(T69<12,"Daily","Weekly")) | AA69: =IF(T69="",0,IF(T69<12,T69*Controls!$B$13,T69*5)) | AB69: =IF(E69="",0,NETWORKDAYS(E69,Controls!$B$20,Ref!$K$2:$K$42)) | AC69: =IF(OR(AF69=1,AND(AA69>0,AB69>=Controls!$B$23*AA69)),1,0) | AD69: =IF(AND(E69<>"",E69>=Controls!$B$21,E69<=Controls!$B$22),1,0) | AE69: =IF(IFERROR(VLOOKUP(D69,Controls!$A$36:$E$46,2,FALSE()),"No")="Yes",1,0) | AF69: =IF(IFERROR(VLOOKUP(D69,Controls!$A$36:$E$46,3,FALSE()),"No")="Yes",1,0) | AG69: =IF(IFERROR(VLOOKUP(D69,Controls!$A$36:$E$46,4,FALSE()),"No")="Yes",1,0) | AH69: =IF(IFERROR(VLOOKUP(D69,Controls!$A$36:$E$46,5,FALSE()),"No")="Yes",1,0) | AI69: =IF(ISNUMBER(MATCH(D69,Controls!$A$36:$A$46,0)),1,0) | AJ69: =Q69-N69 | AK69: =IF(AE69=1,MAX(0,N69-Q69),0) | AL69: =IF(OR(V69="",V69=0),0,N69/V69) | AM69: =IF(OR(V69="",V69=0),0,1) | AN69: =IF(OR(E69="",F69=""),0,NETWORKDAYS(E69,F69,Ref!$K$2:$K$42)) | AO69: =IF(L69="Renewal",1,0) | AP69: =AC69*AD69 | AQ69: =IF(AND(G69<>"",'Historical Score'!$C$6<>""),IF(G69='Historical Score'!$C$6,1,0),0) | AR69: =IF(AND(L69<>"",'Historical Score'!$C$5<>""),IF(L69='Historical Score'!$C$5,1,0),0) | AS69: =IF(AND(Y69<>"",'Historical Score'!$C$7<>""),IF(Y69='Historical Score'!$C$7,1,0),0) | AT69: =IF(AND(K69<>"",'Historical Score'!$C$8<>""),IF(K69='Historical Score'!$C$8,1,0),0) | BA69: =IF(AD69=1,(AR69*'Historical Score'!$K$29+1-'Historical Score'!$K$29)*(AT69*'Historical Score'!$L$29+1-'Historical Score'!$L$29)*(AS69*'Historical Score'!$M$29+1-'Historical Score'!$M$29)*(AQ69*'Historical Score'!$N$29+1-'Historical Score'!$N$29),0)
A70: 5674154793 | B70: Charlie's Electric LLC | C70: Charlie's Electric LLC | D70: Closed | E70: 45757 | F70: 45860 | G70: 7 | H70: 1731 | I70: 17 | J70: OH | K70: Vanguard Equities | L70: New Deal | M70: 1.49 | N70: 4000 | O70: 560 | P70: 5960 | Q70: 5960 | R70: 0 | S70: 1 | T70: 2.295 | U70: 0 | W70: 0.0424 | Y70: =IF(I70="","No SIC",IFERROR(VLOOKUP(I70,Ref!$A$2:$B$65,2,FALSE()),"Unclassified")) | Z70: =IF(T70="","",IF(T70<12,"Daily","Weekly")) | AA70: =IF(T70="",0,IF(T70<12,T70*Controls!$B$13,T70*5)) | AB70: =IF(E70="",0,NETWORKDAYS(E70,Controls!$B$20,Ref!$K$2:$K$42)) | AC70: =IF(OR(AF70=1,AND(AA70>0,AB70>=Controls!$B$23*AA70)),1,0) | AD70: =IF(AND(E70<>"",E70>=Controls!$B$21,E70<=Controls!$B$22),1,0) | AE70: =IF(IFERROR(VLOOKUP(D70,Controls!$A$36:$E$46,2,FALSE()),"No")="Yes",1,0) | AF70: =IF(IFERROR(VLOOKUP(D70,Controls!$A$36:$E$46,3,FALSE()),"No")="Yes",1,0) | AG70: =IF(IFERROR(VLOOKUP(D70,Controls!$A$36:$E$46,4,FALSE()),"No")="Yes",1,0) | AH70: =IF(IFERROR(VLOOKUP(D70,Controls!$A$36:$E$46,5,FALSE()),"No")="Yes",1,0) | AI70: =IF(ISNUMBER(MATCH(D70,Controls!$A$36:$A$46,0)),1,0) | AJ70: =Q70-N70 | AK70: =IF(AE70=1,MAX(0,N70-Q70),0) | AL70: =IF(OR(V70="",V70=0),0,N70/V70) | AM70: =IF(OR(V70="",V70=0),0,1) | AN70: =IF(OR(E70="",F70=""),0,NETWORKDAYS(E70,F70,Ref!$K$2:$K$42)) | AO70: =IF(L70="Renewal",1,0) | AP70: =AC70*AD70 | AQ70: =IF(AND(G70<>"",'Historical Score'!$C$6<>""),IF(G70='Historical Score'!$C$6,1,0),0) | AR70: =IF(AND(L70<>"",'Historical Score'!$C$5<>""),IF(L70='Historical Score'!$C$5,1,0),0) | AS70: =IF(AND(Y70<>"",'Historical Score'!$C$7<>""),IF(Y70='Historical Score'!$C$7,1,0),0) | AT70: =IF(AND(K70<>"",'Historical Score'!$C$8<>""),IF(K70='Historical Score'!$C$8,1,0),0) | BA70: =IF(AD70=1,(AR70*'Historical Score'!$K$29+1-'Historical Score'!$K$29)*(AT70*'Historical Score'!$L$29+1-'Historical Score'!$L$29)*(AS70*'Historical Score'!$M$29+1-'Historical Score'!$M$29)*(AQ70*'Historical Score'!$N$29+1-'Historical Score'!$N$29),0)
A71: 5674154803 | B71: BLUE SKY DESIGNER LANSCAPE | C71: BLUE SKY DESIGNER LANDSCAPE LLC | D71: Legal | E71: 45757 | F71: 45939 | G71: 2 | H71: 0782 | I71: 07 | J71: AZ | K71: Platform Funding | L71: New Deal | M71: 1.45 | N71: 30000 | O71: 4200 | P71: 43500 | Q71: 10251.74 | R71: 33248.26 | S71: 0.23567218 | T71: 28 | U71: 7 | W71: 0.1161 | X71: 44206 | Y71: =IF(I71="","No SIC",IFERROR(VLOOKUP(I71,Ref!$A$2:$B$65,2,FALSE()),"Unclassified")) | Z71: =IF(T71="","",IF(T71<12,"Daily","Weekly")) | AA71: =IF(T71="",0,IF(T71<12,T71*Controls!$B$13,T71*5)) | AB71: =IF(E71="",0,NETWORKDAYS(E71,Controls!$B$20,Ref!$K$2:$K$42)) | AC71: =IF(OR(AF71=1,AND(AA71>0,AB71>=Controls!$B$23*AA71)),1,0) | AD71: =IF(AND(E71<>"",E71>=Controls!$B$21,E71<=Controls!$B$22),1,0) | AE71: =IF(IFERROR(VLOOKUP(D71,Controls!$A$36:$E$46,2,FALSE()),"No")="Yes",1,0) | AF71: =IF(IFERROR(VLOOKUP(D71,Controls!$A$36:$E$46,3,FALSE()),"No")="Yes",1,0) | AG71: =IF(IFERROR(VLOOKUP(D71,Controls!$A$36:$E$46,4,FALSE()),"No")="Yes",1,0) | AH71: =IF(IFERROR(VLOOKUP(D71,Controls!$A$36:$E$46,5,FALSE()),"No")="Yes",1,0) | AI71: =IF(ISNUMBER(MATCH(D71,Controls!$A$36:$A$46,0)),1,0) | AJ71: =Q71-N71 | AK71: =IF(AE71=1,MAX(0,N71-Q71),0) | AL71: =IF(OR(V71="",V71=0),0,N71/V71) | AM71: =IF(OR(V71="",V71=0),0,1) | AN71: =IF(OR(E71="",F71=""),0,NETWORKDAYS(E71,F71,Ref!$K$2:$K$42)) | AO71: =IF(L71="Renewal",1,0) | AP71: =AC71*AD71 | AQ71: =IF(AND(G71<>"",'Historical Score'!$C$6<>""),IF(G71='Historical Score'!$C$6,1,0),0) | AR71: =IF(AND(L71<>"",'Historical Score'!$C$5<>""),IF(L71='Historical Score'!$C$5,1,0),0) | AS71: =IF(AND(Y71<>"",'Historical Score'!$C$7<>""),IF(Y71='Historical Score'!$C$7,1,0),0) | AT71: =IF(AND(K71<>"",'Historical Score'!$C$8<>""),IF(K71='Historical Score'!$C$8,1,0),0) | BA71: =IF(AD71=1,(AR71*'Historical Score'!$K$29+1-'Historical Score'!$K$29)*(AT71*'Historical Score'!$L$29+1-'Historical Score'!$L$29)*(AS71*'Historical Score'!$M$29+1-'Historical Score'!$M$29)*(AQ71*'Historical Score'!$N$29+1-'Historical Score'!$N$29),0)
A72: 5674154834 | B72: Doughboyz Pizzeria LLC | C72: Doughboyz Pizzeria LLC | D72: Legal | E72: 45757 | F72: 45925 | G72: 1 | H72: 5812 | I72: 58 | J72: KS | K72: Vanguard Equities | L72: New Deal | M72: 1.499 | N72: 8000 | O72: 1120 | P72: 11992 | Q72: 9597.06 | R72: 2394.94 | S72: 0.80028853 | T72: 15 | U72: 5 | W72: 0.3947 | Y72: =IF(I72="","No SIC",IFERROR(VLOOKUP(I72,Ref!$A$2:$B$65,2,FALSE()),"Unclassified")) | Z72: =IF(T72="","",IF(T72<12,"Daily","Weekly")) | AA72: =IF(T72="",0,IF(T72<12,T72*Controls!$B$13,T72*5)) | AB72: =IF(E72="",0,NETWORKDAYS(E72,Controls!$B$20,Ref!$K$2:$K$42)) | AC72: =IF(OR(AF72=1,AND(AA72>0,AB72>=Controls!$B$23*AA72)),1,0) | AD72: =IF(AND(E72<>"",E72>=Controls!$B$21,E72<=Controls!$B$22),1,0) | AE72: =IF(IFERROR(VLOOKUP(D72,Controls!$A$36:$E$46,2,FALSE()),"No")="Yes",1,0) | AF72: =IF(IFERROR(VLOOKUP(D72,Controls!$A$36:$E$46,3,FALSE()),"No")="Yes",1,0) | AG72: =IF(IFERROR(VLOOKUP(D72,Controls!$A$36:$E$46,4,FALSE()),"No")="Yes",1,0) | AH72: =IF(IFERROR(VLOOKUP(D72,Controls!$A$36:$E$46,5,FALSE()),"No")="Yes",1,0) | AI72: =IF(ISNUMBER(MATCH(D72,Controls!$A$36:$A$46,0)),1,0) | AJ72: =Q72-N72 | AK72: =IF(AE72=1,MAX(0,N72-Q72),0) | AL72: =IF(OR(V72="",V72=0),0,N72/V72) | AM72: =IF(OR(V72="",V72=0),0,1) | AN72: =IF(OR(E72="",F72=""),0,NETWORKDAYS(E72,F72,Ref!$K$2:$K$42)) | AO72: =IF(L72="Renewal",1,0) | AP72: =AC72*AD72 | AQ72: =IF(AND(G72<>"",'Historical Score'!$C$6<>""),IF(G72='Historical Score'!$C$6,1,0),0) | AR72: =IF(AND(L72<>"",'Historical Score'!$C$5<>""),IF(L72='Historical Score'!$C$5,1,0),0) | AS72: =IF(AND(Y72<>"",'Historical Score'!$C$7<>""),IF(Y72='Historical Score'!$C$7,1,0),0) | AT72: =IF(AND(K72<>"",'Historical Score'!$C$8<>""),IF(K72='Historical Score'!$C$8,1,0),0) | BA72: =IF(AD72=1,(AR72*'Historical Score'!$K$29+1-'Historical Score'!$K$29)*(AT72*'Historical Score'!$L$29+1-'Historical Score'!$L$29)*(AS72*'Historical Score'!$M$29+1-'Historical Score'!$M$29)*(AQ72*'Historical Score'!$N$29+1-'Historical Score'!$N$29),0)
A73: 5674154843 | B73: K&S ENGINEERS INC | C73: K&S ENGINEERS INC | D73: Closed | E73: 45757 | F73: 45952 | G73: 1 | H73: 8711 | I73: 87 | J73: IN | K73: Fidelity Funding | L73: New Deal | M73: 1.35 | N73: 70000 | O73: 4900 | P73: 94500 | Q73: 94500 | R73: 0 | S73: 1 | T73: 4.262 | U73: 5 | W73: 0.0418 | X73: 30864 | Y73: =IF(I73="","No SIC",IFERROR(VLOOKUP(I73,Ref!$A$2:$B$65,2,FALSE()),"Unclassified")) | Z73: =IF(T73="","",IF(T73<12,"Daily","Weekly")) | AA73: =IF(T73="",0,IF(T73<12,T73*Controls!$B$13,T73*5)) | AB73: =IF(E73="",0,NETWORKDAYS(E73,Controls!$B$20,Ref!$K$2:$K$42)) | AC73: =IF(OR(AF73=1,AND(AA73>0,AB73>=Controls!$B$23*AA73)),1,0) | AD73: =IF(AND(E73<>"",E73>=Controls!$B$21,E73<=Controls!$B$22),1,0) | AE73: =IF(IFERROR(VLOOKUP(D73,Controls!$A$36:$E$46,2,FALSE()),"No")="Yes",1,0) | AF73: =IF(IFERROR(VLOOKUP(D73,Controls!$A$36:$E$46,3,FALSE()),"No")="Yes",1,0) | AG73: =IF(IFERROR(VLOOKUP(D73,Controls!$A$36:$E$46,4,FALSE()),"No")="Yes",1,0) | AH73: =IF(IFERROR(VLOOKUP(D73,Controls!$A$36:$E$46,5,FALSE()),"No")="Yes",1,0) | AI73: =IF(ISNUMBER(MATCH(D73,Controls!$A$36:$A$46,0)),1,0) | AJ73: =Q73-N73 | AK73: =IF(AE73=1,MAX(0,N73-Q73),0) | AL73: =IF(OR(V73="",V73=0),0,N73/V73) | AM73: =IF(OR(V73="",V73=0),0,1) | AN73: =IF(OR(E73="",F73=""),0,NETWORKDAYS(E73,F73,Ref!$K$2:$K$42)) | AO73: =IF(L73="Renewal",1,0) | AP73: =AC73*AD73 | AQ73: =IF(AND(G73<>"",'Historical Score'!$C$6<>""),IF(G73='Historical Score'!$C$6,1,0),0) | AR73: =IF(AND(L73<>"",'Historical Score'!$C$5<>""),IF(L73='Historical Score'!$C$5,1,0),0) | AS73: =IF(AND(Y73<>"",'Historical Score'!$C$7<>""),IF(Y73='Historical Score'!$C$7,1,0),0) | AT73: =IF(AND(K73<>"",'Historical Score'!$C$8<>""),IF(K73='Historical Score'!$C$8,1,0),0) | BA73: =IF(AD73=1,(AR73*'Historical Score'!$K$29+1-'Historical Score'!$K$29)*(AT73*'Historical Score'!$L$29+1-'Historical Score'!$L$29)*(AS73*'Historical Score'!$M$29+1-'Historical Score'!$M$29)*(AQ73*'Historical Score'!$N$29+1-'Historical Score'!$N$29),0)
A74: 5674154901 | B74: Tree valley landscaping | C74: Tree valley landscaping | D74: Closed | E74: 45758 | F74: 45862 | G74: 1 | H74: 0783 | I74: 07 | J74: TX | K74: Platform Funding | L74: New Deal | M74: 1.45 | N74: 5000 | O74: 600 | P74: 7250 | Q74: 7250 | R74: 0 | S74: 1 | T74: 1.967 | U74: 7 | W74: 0.06 | X74: 42954 | Y74: =IF(I74="","No SIC",IFERROR(VLOOKUP(I74,Ref!$A$2:$B$65,2,FALSE()),"Unclassified")) | Z74: =IF(T74="","",IF(T74<12,"Daily","Weekly")) | AA74: =IF(T74="",0,IF(T74<12,T74*Controls!$B$13,T74*5)) | AB74: =IF(E74="",0,NETWORKDAYS(E74,Controls!$B$20,Ref!$K$2:$K$42)) | AC74: =IF(OR(AF74=1,AND(AA74>0,AB74>=Controls!$B$23*AA74)),1,0) | AD74: =IF(AND(E74<>"",E74>=Controls!$B$21,E74<=Controls!$B$22),1,0) | AE74: =IF(IFERROR(VLOOKUP(D74,Controls!$A$36:$E$46,2,FALSE()),"No")="Yes",1,0) | AF74: =IF(IFERROR(VLOOKUP(D74,Controls!$A$36:$E$46,3,FALSE()),"No")="Yes",1,0) | AG74: =IF(IFERROR(VLOOKUP(D74,Controls!$A$36:$E$46,4,FALSE()),"No")="Yes",1,0) | AH74: =IF(IFERROR(VLOOKUP(D74,Controls!$A$36:$E$46,5,FALSE()),"No")="Yes",1,0) | AI74: =IF(ISNUMBER(MATCH(D74,Controls!$A$36:$A$46,0)),1,0) | AJ74: =Q74-N74 | AK74: =IF(AE74=1,MAX(0,N74-Q74),0) | AL74: =IF(OR(V74="",V74=0),0,N74/V74) | AM74: =IF(OR(V74="",V74=0),0,1) | AN74: =IF(OR(E74="",F74=""),0,NETWORKDAYS(E74,F74,Ref!$K$2:$K$42)) | AO74: =IF(L74="Renewal",1,0) | AP74: =AC74*AD74 | AQ74: =IF(AND(G74<>"",'Historical Score'!$C$6<>""),IF(G74='Historical Score'!$C$6,1,0),0) | AR74: =IF(AND(L74<>"",'Historical Score'!$C$5<>""),IF(L74='Historical Score'!$C$5,1,0),0) | AS74: =IF(AND(Y74<>"",'Historical Score'!$C$7<>""),IF(Y74='Historical Score'!$C$7,1,0),0) | AT74: =IF(AND(K74<>"",'Historical Score'!$C$8<>""),IF(K74='Historical Score'!$C$8,1,0),0) | BA74: =IF(AD74=1,(AR74*'Historical Score'!$K$29+1-'Historical Score'!$K$29)*(AT74*'Historical Score'!$L$29+1-'Historical Score'!$L$29)*(AS74*'Historical Score'!$M$29+1-'Historical Score'!$M$29)*(AQ74*'Historical Score'!$N$29+1-'Historical Score'!$N$29),0)
A75: 5674154923 | B75: The Container Girls | C75: Containers 4 Sale, LLC | D75: Legal | E75: 45758 | F75: 46038 | G75: 1 | H75: 3412 | I75: 34 | J75: UT | K75: FC ADVANCE | L75: New Deal | M75: 1.49 | N75: 20000 | O75: 0 | P75: 29800 | Q75: 20003.4 | R75: 9796.6 | S75: 0.67125503 | T75: 18 | U75: 1 | W75: 0.0923 | X75: 44044 | Y75: =IF(I75="","No SIC",IFERROR(VLOOKUP(I75,Ref!$A$2:$B$65,2,FALSE()),"Unclassified")) | Z75: =IF(T75="","",IF(T75<12,"Daily","Weekly")) | AA75: =IF(T75="",0,IF(T75<12,T75*Controls!$B$13,T75*5)) | AB75: =IF(E75="",0,NETWORKDAYS(E75,Controls!$B$20,Ref!$K$2:$K$42)) | AC75: =IF(OR(AF75=1,AND(AA75>0,AB75>=Controls!$B$23*AA75)),1,0) | AD75: =IF(AND(E75<>"",E75>=Controls!$B$21,E75<=Controls!$B$22),1,0) | AE75: =IF(IFERROR(VLOOKUP(D75,Controls!$A$36:$E$46,2,FALSE()),"No")="Yes",1,0) | AF75: =IF(IFERROR(VLOOKUP(D75,Controls!$A$36:$E$46,3,FALSE()),"No")="Yes",1,0) | AG75: =IF(IFERROR(VLOOKUP(D75,Controls!$A$36:$E$46,4,FALSE()),"No")="Yes",1,0) | AH75: =IF(IFERROR(VLOOKUP(D75,Controls!$A$36:$E$46,5,FALSE()),"No")="Yes",1,0) | AI75: =IF(ISNUMBER(MATCH(D75,Controls!$A$36:$A$46,0)),1,0) | AJ75: =Q75-N75 | AK75: =IF(AE75=1,MAX(0,N75-Q75),0) | AL75: =IF(OR(V75="",V75=0),0,N75/V75) | AM75: =IF(OR(V75="",V75=0),0,1) | AN75: =IF(OR(E75="",F75=""),0,NETWORKDAYS(E75,F75,Ref!$K$2:$K$42)) | AO75: =IF(L75="Renewal",1,0) | AP75: =AC75*AD75 | AQ75: =IF(AND(G75<>"",'Historical Score'!$C$6<>""),IF(G75='Historical Score'!$C$6,1,0),0) | AR75: =IF(AND(L75<>"",'Historical Score'!$C$5<>""),IF(L75='Historical Score'!$C$5,1,0),0) | AS75: =IF(AND(Y75<>"",'Historical Score'!$C$7<>""),IF(Y75='Historical Score'!$C$7,1,0),0) | AT75: =IF(AND(K75<>"",'Historical Score'!$C$8<>""),IF(K75='Historical Score'!$C$8,1,0),0) | BA75: =IF(AD75=1,(AR75*'Historical Score'!$K$29+1-'Historical Score'!$K$29)*(AT75*'Historical Score'!$L$29+1-'Historical Score'!$L$29)*(AS75*'Historical Score'!$M$29+1-'Historical Score'!$M$29)*(AQ75*'Historical Score'!$N$29+1-'Historical Score'!$N$29),0)
A76: 5674154953 | B76: NFB Venture services Corp | C76: NFB Venture services Corp | D76: Closed/NSF Unpaid | E76: 45758 | F76: 46007 | G76: 2 | H76: 7542 | I76: 75 | J76: MA | K76: CARE FUNDING GROUP | L76: Renewal | M76: 1.49 | N76: 7000 | O76: 980 | P76: 10430 | Q76: 10430 | R76: 0 | S76: 1 | T76: 1.967 | U76: 15 | W76: 0.1159 | X76: 45402 | Y76: =IF(I76="","No SIC",IFERROR(VLOOKUP(I76,Ref!$A$2:$B$65,2,FALSE()),"Unclassified")) | Z76: =IF(T76="","",IF(T76<12,"Daily","Weekly")) | AA76: =IF(T76="",0,IF(T76<12,T76*Controls!$B$13,T76*5)) | AB76: =IF(E76="",0,NETWORKDAYS(E76,Controls!$B$20,Ref!$K$2:$K$42)) | AC76: =IF(OR(AF76=1,AND(AA76>0,AB76>=Controls!$B$23*AA76)),1,0) | AD76: =IF(AND(E76<>"",E76>=Controls!$B$21,E76<=Controls!$B$22),1,0) | AE76: =IF(IFERROR(VLOOKUP(D76,Controls!$A$36:$E$46,2,FALSE()),"No")="Yes",1,0) | AF76: =IF(IFERROR(VLOOKUP(D76,Controls!$A$36:$E$46,3,FALSE()),"No")="Yes",1,0) | AG76: =IF(IFERROR(VLOOKUP(D76,Controls!$A$36:$E$46,4,FALSE()),"No")="Yes",1,0) | AH76: =IF(IFERROR(VLOOKUP(D76,Controls!$A$36:$E$46,5,FALSE()),"No")="Yes",1,0) | AI76: =IF(ISNUMBER(MATCH(D76,Controls!$A$36:$A$46,0)),1,0) | AJ76: =Q76-N76 | AK76: =IF(AE76=1,MAX(0,N76-Q76),0) | AL76: =IF(OR(V76="",V76=0),0,N76/V76) | AM76: =IF(OR(V76="",V76=0),0,1) | AN76: =IF(OR(E76="",F76=""),0,NETWORKDAYS(E76,F76,Ref!$K$2:$K$42)) | AO76: =IF(L76="Renewal",1,0) | AP76: =AC76*AD76 | AQ76: =IF(AND(G76<>"",'Historical Score'!$C$6<>""),IF(G76='Historical Score'!$C$6,1,0),0) | AR76: =IF(AND(L76<>"",'Historical Score'!$C$5<>""),IF(L76='Historical Score'!$C$5,1,0),0) | AS76: =IF(AND(Y76<>"",'Historical Score'!$C$7<>""),IF(Y76='Historical Score'!$C$7,1,0),0) | AT76: =IF(AND(K76<>"",'Historical Score'!$C$8<>""),IF(K76='Historical Score'!$C$8,1,0),0) | BA76: =IF(AD76=1,(AR76*'Historical Score'!$K$29+1-'Historical Score'!$K$29)*(AT76*'Historical Score'!$L$29+1-'Historical Score'!$L$29)*(AS76*'Historical Score'!$M$29+1-'Historical Score'!$M$29)*(AQ76*'Historical Score'!$N$29+1-'Historical Score'!$N$29),0)
A77: 5674154958 | B77: LTV EVENTS LLC | C77: LTV EVENTS LLC | D77: Closed | E77: 45758 | F77: 45825 | G77: 7 | H77: 7299 | I77: 72 | J77: IL | K77: Redline Capital | L77: New Deal | M77: 1.49 | N77: 10000 | O77: 1400 | P77: 14900 | Q77: 14900 | R77: 0 | S77: 1 | T77: 2.459 | U77: 0 | W77: 0.1466 | X77: 44256 | Y77: =IF(I77="","No SIC",IFERROR(VLOOKUP(I77,Ref!$A$2:$B$65,2,FALSE()),"Unclassified")) | Z77: =IF(T77="","",IF(T77<12,"Daily","Weekly")) | AA77: =IF(T77="",0,IF(T77<12,T77*Controls!$B$13,T77*5)) | AB77: =IF(E77="",0,NETWORKDAYS(E77,Controls!$B$20,Ref!$K$2:$K$42)) | AC77: =IF(OR(AF77=1,AND(AA77>0,AB77>=Controls!$B$23*AA77)),1,0) | AD77: =IF(AND(E77<>"",E77>=Controls!$B$21,E77<=Controls!$B$22),1,0) | AE77: =IF(IFERROR(VLOOKUP(D77,Controls!$A$36:$E$46,2,FALSE()),"No")="Yes",1,0) | AF77: =IF(IFERROR(VLOOKUP(D77,Controls!$A$36:$E$46,3,FALSE()),"No")="Yes",1,0) | AG77: =IF(IFERROR(VLOOKUP(D77,Controls!$A$36:$E$46,4,FALSE()),"No")="Yes",1,0) | AH77: =IF(IFERROR(VLOOKUP(D77,Controls!$A$36:$E$46,5,FALSE()),"No")="Yes",1,0) | AI77: =IF(ISNUMBER(MATCH(D77,Controls!$A$36:$A$46,0)),1,0) | AJ77: =Q77-N77 | AK77: =IF(AE77=1,MAX(0,N77-Q77),0) | AL77: =IF(OR(V77="",V77=0),0,N77/V77) | AM77: =IF(OR(V77="",V77=0),0,1) | AN77: =IF(OR(E77="",F77=""),0,NETWORKDAYS(E77,F77,Ref!$K$2:$K$42)) | AO77: =IF(L77="Renewal",1,0) | AP77: =AC77*AD77 | AQ77: =IF(AND(G77<>"",'Historical Score'!$C$6<>""),IF(G77='Historical Score'!$C$6,1,0),0) | AR77: =IF(AND(L77<>"",'Historical Score'!$C$5<>""),IF(L77='Historical Score'!$C$5,1,0),0) | AS77: =IF(AND(Y77<>"",'Historical Score'!$C$7<>""),IF(Y77='Historical Score'!$C$7,1,0),0) | AT77: =IF(AND(K77<>"",'Historical Score'!$C$8<>""),IF(K77='Historical Score'!$C$8,1,0),0) | BA77: =IF(AD77=1,(AR77*'Historical Score'!$K$29+1-'Historical Score'!$K$29)*(AT77*'Historical Score'!$L$29+1-'Historical Score'!$L$29)*(AS77*'Historical Score'!$M$29+1-'Historical Score'!$M$29)*(AQ77*'Historical Score'!$N$29+1-'Historical Score'!$N$29),0)
A78: 5674154965 | B78: Umart | C78: Fareed Inc | D78: Legal | E78: 45758 | F78: 45784 | G78: 2 | H78: 5541 | I78: 55 | J78: FL | K78: Fundible | L78: New Deal | M78: 1.49 | N78: 5000 | O78: 700 | P78: 7450 | Q78: 1118.07 | R78: 6331.93 | S78: 0.15007651 | T78: 1.967 | U78: 9 | X78: 45170 | Y78: =IF(I78="","No SIC",IFERROR(VLOOKUP(I78,Ref!$A$2:$B$65,2,FALSE()),"Unclassified")) | Z78: =IF(T78="","",IF(T78<12,"Daily","Weekly")) | AA78: =IF(T78="",0,IF(T78<12,T78*Controls!$B$13,T78*5)) | AB78: =IF(E78="",0,NETWORKDAYS(E78,Controls!$B$20,Ref!$K$2:$K$42)) | AC78: =IF(OR(AF78=1,AND(AA78>0,AB78>=Controls!$B$23*AA78)),1,0) | AD78: =IF(AND(E78<>"",E78>=Controls!$B$21,E78<=Controls!$B$22),1,0) | AE78: =IF(IFERROR(VLOOKUP(D78,Controls!$A$36:$E$46,2,FALSE()),"No")="Yes",1,0) | AF78: =IF(IFERROR(VLOOKUP(D78,Controls!$A$36:$E$46,3,FALSE()),"No")="Yes",1,0) | AG78: =IF(IFERROR(VLOOKUP(D78,Controls!$A$36:$E$46,4,FALSE()),"No")="Yes",1,0) | AH78: =IF(IFERROR(VLOOKUP(D78,Controls!$A$36:$E$46,5,FALSE()),"No")="Yes",1,0) | AI78: =IF(ISNUMBER(MATCH(D78,Controls!$A$36:$A$46,0)),1,0) | AJ78: =Q78-N78 | AK78: =IF(AE78=1,MAX(0,N78-Q78),0) | AL78: =IF(OR(V78="",V78=0),0,N78/V78) | AM78: =IF(OR(V78="",V78=0),0,1) | AN78: =IF(OR(E78="",F78=""),0,NETWORKDAYS(E78,F78,Ref!$K$2:$K$42)) | AO78: =IF(L78="Renewal",1,0) | AP78: =AC78*AD78 | AQ78: =IF(AND(G78<>"",'Historical Score'!$C$6<>""),IF(G78='Historical Score'!$C$6,1,0),0) | AR78: =IF(AND(L78<>"",'Historical Score'!$C$5<>""),IF(L78='Historical Score'!$C$5,1,0),0) | AS78: =IF(AND(Y78<>"",'Historical Score'!$C$7<>""),IF(Y78='Historical Score'!$C$7,1,0),0) | AT78: =IF(AND(K78<>"",'Historical Score'!$C$8<>""),IF(K78='Historical Score'!$C$8,1,0),0) | BA78: =IF(AD78=1,(AR78*'Historical Score'!$K$29+1-'Historical Score'!$K$29)*(AT78*'Historical Score'!$L$29+1-'Historical Score'!$L$29)*(AS78*'Historical Score'!$M$29+1-'Historical Score'!$M$29)*(AQ78*'Historical Score'!$N$29+1-'Historical Score'!$N$29),0)
A79: 5674155038 | B79: So Baltimore, LLC | C79: So Baltimore, LLC | D79: Closed | E79: 45762 | F79: 45869 | G79: 5 | H79: 5812 | I79: 58 | J79: MD | K79: Llama Loan | L79: New Deal | M79: 1.43 | N79: 10000 | O79: 1100 | P79: 14300 | Q79: 14300 | R79: 0 | S79: 1 | T79: 2.295 | U79: 0 | W79: 0.0756 | X79: 44378 | Y79: =IF(I79="","No SIC",IFERROR(VLOOKUP(I79,Ref!$A$2:$B$65,2,FALSE()),"Unclassified")) | Z79: =IF(T79="","",IF(T79<12,"Daily","Weekly")) | AA79: =IF(T79="",0,IF(T79<12,T79*Controls!$B$13,T79*5)) | AB79: =IF(E79="",0,NETWORKDAYS(E79,Controls!$B$20,Ref!$K$2:$K$42)) | AC79: =IF(OR(AF79=1,AND(AA79>0,AB79>=Controls!$B$23*AA79)),1,0) | AD79: =IF(AND(E79<>"",E79>=Controls!$B$21,E79<=Controls!$B$22),1,0) | AE79: =IF(IFERROR(VLOOKUP(D79,Controls!$A$36:$E$46,2,FALSE()),"No")="Yes",1,0) | AF79: =IF(IFERROR(VLOOKUP(D79,Controls!$A$36:$E$46,3,FALSE()),"No")="Yes",1,0) | AG79: =IF(IFERROR(VLOOKUP(D79,Controls!$A$36:$E$46,4,FALSE()),"No")="Yes",1,0) | AH79: =IF(IFERROR(VLOOKUP(D79,Controls!$A$36:$E$46,5,FALSE()),"No")="Yes",1,0) | AI79: =IF(ISNUMBER(MATCH(D79,Controls!$A$36:$A$46,0)),1,0) | AJ79: =Q79-N79 | AK79: =IF(AE79=1,MAX(0,N79-Q79),0) | AL79: =IF(OR(V79="",V79=0),0,N79/V79) | AM79: =IF(OR(V79="",V79=0),0,1) | AN79: =IF(OR(E79="",F79=""),0,NETWORKDAYS(E79,F79,Ref!$K$2:$K$42)) | AO79: =IF(L79="Renewal",1,0) | AP79: =AC79*AD79 | AQ79: =IF(AND(G79<>"",'Historical Score'!$C$6<>""),IF(G79='Historical Score'!$C$6,1,0),0) | AR79: =IF(AND(L79<>"",'Historical Score'!$C$5<>""),IF(L79='Historical Score'!$C$5,1,0),0) | AS79: =IF(AND(Y79<>"",'Historical Score'!$C$7<>""),IF(Y79='Historical Score'!$C$7,1,0),0) | AT79: =IF(AND(K79<>"",'Historical Score'!$C$8<>""),IF(K79='Historical Score'!$C$8,1,0),0) | BA79: =IF(AD79=1,(AR79*'Historical Score'!$K$29+1-'Historical Score'!$K$29)*(AT79*'Historical Score'!$L$29+1-'Historical Score'!$L$29)*(AS79*'Historical Score'!$M$29+1-'Historical Score'!$M$29)*(AQ79*'Historical Score'!$N$29+1-'Historical Score'!$N$29),0)
A80: 5674155151 | B80: Bental electric | C80: Bental electric | D80: Legal | E80: 45763 | F80: 45866 | G80: 4 | H80: 1731 | I80: 17 | J80: CA | K80: Fund Your Bizz | L80: New Deal | M80: 1.49 | N80: 10000 | O80: 0 | P80: 14900 | Q80: 6411.72 | R80: 8488.28 | S80: 0.43031678 | T80: 2.131 | U80: 24 | W80: 0.0531 | X80: 38081 | Y80: =IF(I80="","No SIC",IFERROR(VLOOKUP(I80,Ref!$A$2:$B$65,2,FALSE()),"Unclassified")) | Z80: =IF(T80="","",IF(T80<12,"Daily","Weekly")) | AA80: =IF(T80="",0,IF(T80<12,T80*Controls!$B$13,T80*5)) | AB80: =IF(E80="",0,NETWORKDAYS(E80,Controls!$B$20,Ref!$K$2:$K$42)) | AC80: =IF(OR(AF80=1,AND(AA80>0,AB80>=Controls!$B$23*AA80)),1,0) | AD80: =IF(AND(E80<>"",E80>=Controls!$B$21,E80<=Controls!$B$22),1,0) | AE80: =IF(IFERROR(VLOOKUP(D80,Controls!$A$36:$E$46,2,FALSE()),"No")="Yes",1,0) | AF80: =IF(IFERROR(VLOOKUP(D80,Controls!$A$36:$E$46,3,FALSE()),"No")="Yes",1,0) | AG80: =IF(IFERROR(VLOOKUP(D80,Controls!$A$36:$E$46,4,FALSE()),"No")="Yes",1,0) | AH80: =IF(IFERROR(VLOOKUP(D80,Controls!$A$36:$E$46,5,FALSE()),"No")="Yes",1,0) | AI80: =IF(ISNUMBER(MATCH(D80,Controls!$A$36:$A$46,0)),1,0) | AJ80: =Q80-N80 | AK80: =IF(AE80=1,MAX(0,N80-Q80),0) | AL80: =IF(OR(V80="",V80=0),0,N80/V80) | AM80: =IF(OR(V80="",V80=0),0,1) | AN80: =IF(OR(E80="",F80=""),0,NETWORKDAYS(E80,F80,Ref!$K$2:$K$42)) | AO80: =IF(L80="Renewal",1,0) | AP80: =AC80*AD80 | AQ80: =IF(AND(G80<>"",'Historical Score'!$C$6<>""),IF(G80='Historical Score'!$C$6,1,0),0) | AR80: =IF(AND(L80<>"",'Historical Score'!$C$5<>""),IF(L80='Historical Score'!$C$5,1,0),0) | AS80: =IF(AND(Y80<>"",'Historical Score'!$C$7<>""),IF(Y80='Historical Score'!$C$7,1,0),0) | AT80: =IF(AND(K80<>"",'Historical Score'!$C$8<>""),IF(K80='Historical Score'!$C$8,1,0),0) | BA80: =IF(AD80=1,(AR80*'Historical Score'!$K$29+1-'Historical Score'!$K$29)*(AT80*'Historical Score'!$L$29+1-'Historical Score'!$L$29)*(AS80*'Historical Score'!$M$29+1-'Historical Score'!$M$29)*(AQ80*'Historical Score'!$N$29+1-'Historical Score'!$N$29),0)
A81: 5674155206 | B81: Grappling Zone | C81: Grappling Zone | D81: Legal | E81: 45764 | F81: 45839 | G81: 1 | H81: 7991 | I81: 79 | J81: TX | K81: Westwood | L81: New Deal | M81: 1.49 | N81: 20000 | O81: 2800 | P81: 29800 | Q81: 9188.58 | R81: 20611.42 | S81: 0.30834161 | T81: 3.934 | U81: 14 | W81: 0.2302 | Y81: =IF(I81="","No SIC",IFERROR(VLOOKUP(I81,Ref!$A$2:$B$65,2,FALSE()),"Unclassified")) | Z81: =IF(T81="","",IF(T81<12,"Daily","Weekly")) | AA81: =IF(T81="",0,IF(T81<12,T81*Controls!$B$13,T81*5)) | AB81: =IF(E81="",0,NETWORKDAYS(E81,Controls!$B$20,Ref!$K$2:$K$42)) | AC81: =IF(OR(AF81=1,AND(AA81>0,AB81>=Controls!$B$23*AA81)),1,0) | AD81: =IF(AND(E81<>"",E81>=Controls!$B$21,E81<=Controls!$B$22),1,0) | AE81: =IF(IFERROR(VLOOKUP(D81,Controls!$A$36:$E$46,2,FALSE()),"No")="Yes",1,0) | AF81: =IF(IFERROR(VLOOKUP(D81,Controls!$A$36:$E$46,3,FALSE()),"No")="Yes",1,0) | AG81: =IF(IFERROR(VLOOKUP(D81,Controls!$A$36:$E$46,4,FALSE()),"No")="Yes",1,0) | AH81: =IF(IFERROR(VLOOKUP(D81,Controls!$A$36:$E$46,5,FALSE()),"No")="Yes",1,0) | AI81: =IF(ISNUMBER(MATCH(D81,Controls!$A$36:$A$46,0)),1,0) | AJ81: =Q81-N81 | AK81: =IF(AE81=1,MAX(0,N81-Q81),0) | AL81: =IF(OR(V81="",V81=0),0,N81/V81) | AM81: =IF(OR(V81="",V81=0),0,1) | AN81: =IF(OR(E81="",F81=""),0,NETWORKDAYS(E81,F81,Ref!$K$2:$K$42)) | AO81: =IF(L81="Renewal",1,0) | AP81: =AC81*AD81 | AQ81: =IF(AND(G81<>"",'Historical Score'!$C$6<>""),IF(G81='Historical Score'!$C$6,1,0),0) | AR81: =IF(AND(L81<>"",'Historical Score'!$C$5<>""),IF(L81='Historical Score'!$C$5,1,0),0) | AS81: =IF(AND(Y81<>"",'Historical Score'!$C$7<>""),IF(Y81='Historical Score'!$C$7,1,0),0) | AT81: =IF(AND(K81<>"",'Historical Score'!$C$8<>""),IF(K81='Historical Score'!$C$8,1,0),0) | BA81: =IF(AD81=1,(AR81*'Historical Score'!$K$29+1-'Historical Score'!$K$29)*(AT81*'Historical Score'!$L$29+1-'Historical Score'!$L$29)*(AS81*'Historical Score'!$M$29+1-'Historical Score'!$M$29)*(AQ81*'Historical Score'!$N$29+1-'Historical Score'!$N$29),0)
A82: 5674155271 | B82: M EASY LOGISTICS LLC | C82: M EASY LOGISTICS LLC | D82: Written-Off | E82: 45765 | F82: 45894 | G82: 3 | H82: 4212 | I82: 42 | J82: NJ | K82: PMF | L82: New Deal | M82: 1.49 | N82: 8000 | O82: 1120 | P82: 11920 | Q82: 11224.71 | R82: 695.29 | S82: 0.9416703 | T82: 1.967 | U82: 9 | W82: 0.0494 | X82: 43466 | Y82: =IF(I82="","No SIC",IFERROR(VLOOKUP(I82,Ref!$A$2:$B$65,2,FALSE()),"Unclassified")) | Z82: =IF(T82="","",IF(T82<12,"Daily","Weekly")) | AA82: =IF(T82="",0,IF(T82<12,T82*Controls!$B$13,T82*5)) | AB82: =IF(E82="",0,NETWORKDAYS(E82,Controls!$B$20,Ref!$K$2:$K$42)) | AC82: =IF(OR(AF82=1,AND(AA82>0,AB82>=Controls!$B$23*AA82)),1,0) | AD82: =IF(AND(E82<>"",E82>=Controls!$B$21,E82<=Controls!$B$22),1,0) | AE82: =IF(IFERROR(VLOOKUP(D82,Controls!$A$36:$E$46,2,FALSE()),"No")="Yes",1,0) | AF82: =IF(IFERROR(VLOOKUP(D82,Controls!$A$36:$E$46,3,FALSE()),"No")="Yes",1,0) | AG82: =IF(IFERROR(VLOOKUP(D82,Controls!$A$36:$E$46,4,FALSE()),"No")="Yes",1,0) | AH82: =IF(IFERROR(VLOOKUP(D82,Controls!$A$36:$E$46,5,FALSE()),"No")="Yes",1,0) | AI82: =IF(ISNUMBER(MATCH(D82,Controls!$A$36:$A$46,0)),1,0) | AJ82: =Q82-N82 | AK82: =IF(AE82=1,MAX(0,N82-Q82),0) | AL82: =IF(OR(V82="",V82=0),0,N82/V82) | AM82: =IF(OR(V82="",V82=0),0,1) | AN82: =IF(OR(E82="",F82=""),0,NETWORKDAYS(E82,F82,Ref!$K$2:$K$42)) | AO82: =IF(L82="Renewal",1,0) | AP82: =AC82*AD82 | AQ82: =IF(AND(G82<>"",'Historical Score'!$C$6<>""),IF(G82='Historical Score'!$C$6,1,0),0) | AR82: =IF(AND(L82<>"",'Historical Score'!$C$5<>""),IF(L82='Historical Score'!$C$5,1,0),0) | AS82: =IF(AND(Y82<>"",'Historical Score'!$C$7<>""),IF(Y82='Historical Score'!$C$7,1,0),0) | AT82: =IF(AND(K82<>"",'Historical Score'!$C$8<>""),IF(K82='Historical Score'!$C$8,1,0),0) | BA82: =IF(AD82=1,(AR82*'Historical Score'!$K$29+1-'Historical Score'!$K$29)*(AT82*'Historical Score'!$L$29+1-'Historical Score'!$L$29)*(AS82*'Historical Score'!$M$29+1-'Historical Score'!$M$29)*(AQ82*'Historical Score'!$N$29+1-'Historical Score'!$N$29),0)
