Workbook

Sheet README
B2: ASPIRE COMBINED UNDERWRITING MODEL - cash-flow engine + house-book evidence (v1)
B4: HOW TO RUN A DEAL (everything happens on the Deal sheet)
B5: 1. Section A: requested fund, factor, term, frequency (optional - the engine sizes an offer from bank data even if blank).
B6: 2. Section B: up to 12 months of true revenue, average daily balance, negative days, NSFs - newest month first.
B7: 3. Existing positions: funder, funded $, payment, frequency, start date. Monthly-frequency debt = leverage only, not a position.
B8: 4. DEAL PROFILE (right of the bank data): ISO, industry (SIC major group), state, new deal or renewal, credit score. Position is automatic; override only if you know better.
B9: 5. Read Section F at the bottom: final decision, fund, factor, term, payment, frequency, modifier, comparables, confidence, stipulations and the written conclusion.
B10: 6. Decision Summary has the full 20-item output; Comparable Deals lists every house-book deal behind it by Contract ID; Historical Score shows all seven tiers and the credibility math.
B12: THE THREE LAYERS
B13: Layer 1 - Deal sheet sections A-E: the original cash-flow tool. Seven metrics plus credit score, green/yellow/red/knockout, score, cash-flow maximum daily payment (weakest of holdback, total leverage, daily-debt-to-balance green lines), term band, factor band, cash-flow max fund. Thresholds live on Controls.
B14: Layer 2 - Historical Data + Historical Score: 1,067 house-book deals, seasoned = age >= 1.25 x contracted term at the as-of date. Seven matching tiers (new/renewal + industry + position ... down to the seasoned book). Primary cohort = first tier with >= 10 seasoned deals and >= $150k seasoned funded. Credibility Z = n/(n+30). Blended lost rate = Z x cohort + (1-Z) x book. Relative index = blended / book -> modifier level (Controls table). Confidence High / Medium / Low; Low caps the modifier at one step from neutral.
B15: Layer 3 - Offer Engine + Decision Summary: adjusted fund = MIN(cash-flow max x multiplier, cash-flow max daily x adjusted term / adjusted factor). Term shortens by bands, factor rises by approved tiers, frequency may switch to weekly. All four offer-side metrics are recomputed and must stay off red. Decision = DECLINE / MANUAL REVIEW / CONDITIONAL / APPROVE.
... B30: CONVERSIONS: money with 5 and 21.655 (weekly / 5 = daily; monthly / 21.655 = daily); time with 4.331 (weeks / 4.331 = months). MoneyBadger uses 4 and 21.

Sheet Deal
B1: UNDERWRITING TOOL
B2: DECISION | C2: =C52 -> CONDITIONAL | D2: =IF(C52="","",C50&" red flag(s) vs limit "&C51&" | "&COUNTIF(F38:F45,"GREEN")&"G / "&COUNTIF(F38:F45,"YELLOW")&"Y / "&COUNTIF(F38:F45,"RED")&"R | score "&TEXT(C55,"0.0")&"/"&D55&" = "&C56&" | FINAL (with house book): "&IF(C67="","-",C67)) -> 0 red flag(s) vs limit 2 | 5G / 3Y / 0R | score 6.5/8 = Solid | FINAL (with house book): CONDITIONAL
B4: A. OFFER | J4: MONEYBADGER CROSS-CHECK
B5: Fund $ | C5: Factor | D5: =IF($E$6="Weekly","Term (weeks)","Term (daily pmts)") -> Term (weeks) | E5: Freq | F5: Fee % | J5: Metric | K5: This tool | L5: MoneyBadger | M5: Diff
B6: 75000 | C6: 1.49 | D6: 30 | E6: Weekly | F6: =Controls!$B$15 -> 0.05 | J6: =IF($E$6="Weekly","Weekly remittance","Daily remittance") -> Weekly remittance | K6: =IF(OR($E$6="",C8="",C24=0),"",IF($E$6="Weekly",D8,C8)) -> 3725 | L6: =IF(OR(L7="",C24=0),"",L7*C24/IF($E$6="Weekly",$L$8,$L$9)) -> 3725.4125 | M6: =IF(OR(K6="",L6=""),"",L6-K6) -> 0.4125
B7: Payback | C7: Daily $ | D7: Weekly $ | E7: Monthly $ | F7: Term (mo) | G7: Net $ | J7: Holdback % | K7: =IF(OR(D8="",C24=0),"",E8/C24) -> 0.13500397 | L7: =IF(OR($E$6="",C8="",C24=0),"",ROUND(IF($E$6="Weekly",D8*$L$8,C8*$L$9)/C24*100,2)/100) -> 0.1247 | M7: =IF(OR(K7="",L7=""),"",L7-K7) -> -0.010303975
B8: =IF(OR(B6="",C6=""),"",B6*C6) -> 111750 | C8: =IF(OR(B8="",D6="",D6=0),"",IF(E6="Weekly",(B8/D6)/5,B8/D6)) -> 745 | D8: =IF(C8="","",C8*5) -> 3725 | E8: =IF(C8="","",C8*$K$9) -> 16132.975 | F8: =IF(OR(D6="",D6=0),"",IF(E6="Weekly",D6,D6/5)/($K$9/5)) -> 6.9268067 | G8: =IF(B6="","",B6-(B6*F6)) -> 71250 | J8: Weeks / month | K8: =Controls!$B$28 -> 4.331 | L8: =Controls!$B$30 -> 4 | M8: =IF(OR(K8="",L8=""),"",L8-K8) -> -0.331
J9: Days / month | K9: =Controls!$B$29 -> 21.655 | L9: =Controls!$B$31 -> 21 | M9: =IF(OR(K9="",L9=""),"",L9-K9) -> -0.655
B10: B. BANK DATA (up to 12 months)
B11: Month - NEWEST FIRST | C11: True rev $ | D11: Avg daily bal $ | E11: Neg days | F11: NSFs | G11: MoM % | J11: DEAL PROFILE (house-book match inputs)
B12: Jul | C12: 124000 | D12: 9200 | E12: 0 | F12: 0 | G12: =IF(OR(C12="",C13=""),"",(C12-C13)/C13) -> 0.050847458 | J12: ISO | K12: United Secured Capital 8 | L12: =IF(K12="","",COUNTIF('Historical Data'!$K$2:$K$1068,K12)&" deals in book") -> 175 deals in book
B13: Jun | C13: 118000 | D13: 8100 | E13: 1 | F13: 0 | G13: =IF(OR(C13="",C14=""),"",(C13-C14)/C14) -> -0.024793388 | J13: Industry (SIC major group) | K13: General Building Contractors | L13: =IF(K13="","",COUNTIF('Historical Data'!$Y$2:$Y$1068,K13)&" deals in book") -> 121 deals in book
B14: May | C14: 121000 | D14: 9800 | E14: 0 | F14: 1 | G14: =IF(OR(C14="",C15=""),"",(C14-C15)/C15) -> 0.052173913 | J14: State | K14: TX | L14: =IF(K14="","",COUNTIF('Historical Data'!$J$2:$J$1068,K14)&" deals in book") -> 197 deals in book
B15: Apr | C15: 115000 | D15: 8900 | E15: 0 | F15: 0 | G15: =IF(OR(C15="",C16=""),"",(C15-C16)/C16) | J15: New deal or renewal | K15: New Deal | L15: =IF(K15="","REQUIRED for history match","")
G16: =IF(OR(C16="",C17=""),"",(C16-C17)/C17) | J16: Credit score (FICO) | K16: 640 | L16: =IF(K16="","not scored",IF(K16>=Controls!$B$12,"GREEN",IF(K16>=Controls!$C$12,"YELLOW","RED"))) -> YELLOW
G17: =IF(OR(C17="",C18=""),"",(C17-C18)/C18) | J17: Proposed position (auto) | K17: =IF(C42="","",C42) -> 2 | L17: auto: positions incl. new
G18: =IF(OR(C18="",C19=""),"",(C18-C19)/C19) | J18: Position override (optional) | L18: =IF(K18="","",IF(K18<>K17,"override in use",""))
G19: =IF(OR(C19="",C20=""),"",(C19-C20)/C20)
G20: =IF(OR(C20="",C21=""),"",(C20-C21)/C21)
G21: =IF(OR(C21="",C22=""),"",(C21-C22)/C22)
G22: =IF(OR(C22="",C23=""),"",(C22-C23)/C23)
B24: AVG / TOTAL (months entered) | C24: =IF(COUNT(C12:C23)=0,0,AVERAGE(C12:C23)) -> 119500 | D24: =IF(COUNT(D12:D23)=0,0,AVERAGE(D12:D23)) -> 9000 | E24: =SUM(E12:E23) -> 1 | F24: =SUM(F12:F23) -> 1 | G24: =IFERROR(AVERAGE(G12:G22),"") -> 0.026075994
B26: EXISTING POSITIONS (freq Monthly = leverage only, NOT a position)
B27: Funder | C27: Funded $ | D27: Payment | E27: Freq | F27: Daily equiv | G27: Start Date | H27: Est Term | I27: Est term (mo) | J27: Mo. remaining
B28: Fox Funding | C28: 60000 | D28: 2500 | E28: Weekly | F28: =IF(D28<>"",IF(E28="Daily",D28,IF(E28="Weekly",D28/5,D28/$K$9)),IF(C28="","",C28*Controls!$B$33/(Controls!$B$23*$K$9))) -> 500 | H28: =IF(OR(C28="",D28=""),"",ROUND(C28*Controls!$B$33/D28,0)) -> 35 | I28: =IF(H28="","",H28/IF(E28="Daily",$K$9,IF(E28="Weekly",$K$9/5,1))) -> 8.0812745 | J28: =IF(OR(I28="",G28=""),"",MAX(0,I28-(TODAY()-G28)/Controls!$B$32))
E29: Weekly | F29: =IF(D29<>"",IF(E29="Daily",D29,IF(E29="Weekly",D29/5,D29/$K$9)),IF(C29="","",C29*Controls!$B$33/(Controls!$B$23*$K$9))) | H29: =IF(OR(C29="",D29=""),"",ROUND(C29*Controls!$B$33/D29,0)) | I29: =IF(H29="","",H29/IF(E29="Daily",$K$9,IF(E29="Weekly",$K$9/5,1))) | J29: =IF(OR(I29="",G29=""),"",MAX(0,I29-(TODAY()-G29)/Controls!$B$32))
E30: Weekly | F30: =IF(D30<>"",IF(E30="Daily",D30,IF(E30="Weekly",D30/5,D30/$K$9)),IF(C30="","",C30*Controls!$B$33/(Controls!$B$23*$K$9))) | H30: =IF(OR(C30="",D30=""),"",ROUND(C30*Controls!$B$33/D30,0)) | I30: =IF(H30="","",H30/IF(E30="Daily",$K$9,IF(E30="Weekly",$K$9/5,1))) | J30: =IF(OR(I30="",G30=""),"",MAX(0,I30-(TODAY()-G30)/Controls!$B$32))
E31: Weekly | F31: =IF(D31<>"",IF(E31="Daily",D31,IF(E31="Weekly",D31/5,D31/$K$9)),IF(C31="","",C31*Controls!$B$33/(Controls!$B$23*$K$9))) | H31: =IF(OR(C31="",D31=""),"",ROUND(C31*Controls!$B$33/D31,0)) | I31: =IF(H31="","",H31/IF(E31="Daily",$K$9,IF(E31="Weekly",$K$9/5,1))) | J31: =IF(OR(I31="",G31=""),"",MAX(0,I31-(TODAY()-G31)/Controls!$B$32))
E32: Weekly | F32: =IF(D32<>"",IF(E32="Daily",D32,IF(E32="Weekly",D32/5,D32/$K$9)),IF(C32="","",C32*Controls!$B$33/(Controls!$B$23*$K$9))) | H32: =IF(OR(C32="",D32=""),"",ROUND(C32*Controls!$B$33/D32,0)) | I32: =IF(H32="","",H32/IF(E32="Daily",$K$9,IF(E32="Weekly",$K$9/5,1))) | J32: =IF(OR(I32="",G32=""),"",MAX(0,I32-(TODAY()-G32)/Controls!$B$32))
E33: Weekly | F33: =IF(D33<>"",IF(E33="Daily",D33,IF(E33="Weekly",D33/5,D33/$K$9)),IF(C33="","",C33*Controls!$B$33/(Controls!$B$23*$K$9))) | H33: =IF(OR(C33="",D33=""),"",ROUND(C33*Controls!$B$33/D33,0)) | I33: =IF(H33="","",H33/IF(E33="Daily",$K$9,IF(E33="Weekly",$K$9/5,1))) | J33: =IF(OR(I33="",G33=""),"",MAX(0,I33-(TODAY()-G33)/Controls!$B$32))
B34: Positions (excl. Monthly) | C34: =SUMPRODUCT(((C28:C33<>"")+(D28:D33<>"")>0)*(E28:E33<>"Monthly")) -> 1 | D34: Total existing daily | E34: =SUM(F28:F33) -> 500 | F34: =E34*$K$9 -> 10827.5 | G34: /month
B36: C. METRICS
B37: Metric | C37: Value | D37: Green | E37: Red | F37: Status | G37: Knockout
B38: Total LVG (all debt / rev) | C38: =IF(C24=0,"",(E34+IF(C8="",0,C8))*$K$9/C24) -> 0.22561067 | D38: =Controls!$B$5 -> 0.3 | E38: =Controls!$C$5 -> 0.45 | F38: =IF(C38="","",IF(C38>=G38,"KNOCKOUT",IF(C38<=D38,"GREEN",IF(C38>=E38,"RED","YELLOW")))) -> GREEN | G38: =Controls!$D$5 -> 0.55
B39: New holdback SP% | C39: =IF(OR(C24=0,E8=""),"",E8/C24) -> 0.13500397 | D39: =Controls!$B$6 -> 0.18 | E39: =Controls!$C$6 -> 0.25 | F39: =IF(C39="","",IF(C39>=G39,"KNOCKOUT",IF(C39<=D39,"GREEN",IF(C39>=E39,"RED","YELLOW")))) -> GREEN | G39: =Controls!$D$6 -> 0.35
B40: Daily debt / balance | C40: =IF(D24=0,"",(E34+IF(C8="",0,C8))/D24) -> 0.13833333 | D40: =Controls!$B$7 -> 0.18 | E40: =Controls!$C$7 -> 0.3 | F40: =IF(C40="","",IF(C40>=G40,"KNOCKOUT",IF(C40<=D40,"GREEN",IF(C40>=E40,"RED","YELLOW")))) -> GREEN | G40: =Controls!$D$7 -> 0.35
B41: Fund / revenue | C41: =IF(OR(C24=0,B6=""),"",B6/C24) -> 0.62761506 | D41: =Controls!$B$8 -> 0.6 | E41: =Controls!$C$8 -> 0.9 | F41: =IF(C41="","",IF(C41>=G41,"KNOCKOUT",IF(C41<=D41,"GREEN",IF(C41>=E41,"RED","YELLOW")))) -> YELLOW | G41: =Controls!$D$8 -> 1.25
B42: # positions (incl. new) | C42: =IF(C24=0,"",C34+1) -> 2 | D42: =Controls!$B$9 -> 2 | E42: =Controls!$C$9 -> 5 | F42: =IF(C42="","",IF(C42>=G42,"KNOCKOUT",IF(C42<=D42,"GREEN",IF(C42>=E42,"RED","YELLOW")))) -> GREEN | G42: =Controls!$D$9 -> 6
B43: Revenue trend (avg MoM) | C43: =G24 -> 0.026075994 | D43: =Controls!$B$10 -> -0.05 | E43: =Controls!$C$10 -> -0.15 | F43: =IF(C24=0,"",IF(NOT(ISNUMBER(C43)),"YELLOW",IF(C43<=G43,"KNOCKOUT",IF(C43>=D43,"GREEN",IF(C43<=E43,"RED","YELLOW"))))) -> GREEN | G43: =Controls!$D$10 -> -0.3
B44: Neg days + NSFs (total) | C44: =E24+F24 -> 2 | D44: =Controls!$B$11 -> 1 | E44: =Controls!$C$11 -> 6 | F44: =IF(C44="","",IF(C44>=G44,"KNOCKOUT",IF(C44<=D44,"GREEN",IF(C44>=E44,"RED","YELLOW")))) -> YELLOW | G44: =Controls!$D$11 -> 10
B45: Credit score (FICO) | C45: =IF(K16="","",K16) -> 640 | D45: =Controls!$B$12 -> 650 | E45: =Controls!$C$12 -> 630 | F45: =IF(C45="","",IF(AND(G45<>0,C45<=G45),"KNOCKOUT",IF(C45>=D45,"GREEN",IF(C45<E45,"RED","YELLOW")))) -> YELLOW | G45: =Controls!$D$12 -> 0
B46: Existing leverage (before new) | C46: =IF(C24=0,"",F34/C24) -> 0.090606695 | D46: - | E46: - | F46: INFO
B47: Balance / revenue | C47: =IF(C24=0,"",D24/C24) -> 0.075313808 | D47: - | E47: - | F47: INFO
B49: D. DECISION (cash-flow layer, on the requested offer)
B50: Red flags | C50: =COUNTIF(F38:F45,"RED")+COUNTIF(F38:F45,"KNOCKOUT") -> 0 | D50: Knockouts | E50: =COUNTIF(F38:F45,"KNOCKOUT") -> 0
B51: Decline if red flags >= (Controls) | C51: =Controls!$B$13 -> 2 | D51: Minimum fund $ | E51: =Controls!$B$14 -> 20000
B52: DECISION | C52: =IF(C24=0,"",IF(OR(E50>0,IF(ISNUMBER(C63),C63,0)<E51),"DECLINE",IF(OR(B6="",B6=0),"",IF(C50>=C51,"DECLINE",IF(COUNTIF(F38:F45,"GREEN")=D55,"APPROVE","CONDITIONAL"))))) -> CONDITIONAL | D52: =IF(C52="DECLINE",IF(E50>0,"KNOCKOUT: "&INDEX(B38:B45,MATCH("KNOCKOUT",F38:F45,0))&" is past its knockout line.",IF(C50>=C51,"Red flags reached the threshold.","Recommended fund "&IF(ISNUMBER(C63),TEXT(C63,"$#,##0"),"$0")&" is below your minimum "&TEXT(E51,"$#,##0")&".")),IF(C52="APPROVE","All "&D55&" decision metrics green.",IF(C52="","Enter offer + bank data.","Fundable but not clean - review yellows/reds above."))) -> Fundable but not clean - review yellows/reds above.
B54: E. DEAL QUALITY & CASH-FLOW MAXIMUM OFFER (bank data alone)
B55: Score (G=1, Y=0.5, R=0) | C55: =COUNTIF(F38:F45,"GREEN")+0.5*COUNTIF(F38:F45,"YELLOW") -> 6.5 | D55: =SUMPRODUCT(--(F38:F45<>"")) -> 8 | E55: scored metrics
B56: Tier (score scaled to 7 for the bands) | C56: =IF(C24=0,"",IF(D57>=Controls!$B$25,"Strong",IF(D57>=Controls!$C$25,"Solid",IF(D57>=Controls!$D$25,"Moderate","Weak")))) -> Solid
B57: Max daily by SP% green | C57: =IF(C24=0,"",D39*C24/$K$9) -> 993.30409 | D57: =IF(D55=0,0,C55*7/D55) -> 5.6875 | E57: scaled score /7
B58: Max daily by Total LVG green | C58: =IF(C24=0,"",(D38*C24-F34)/$K$9) -> 1155.5068
B59: Max daily by Daily/Balance green | C59: =IF(OR(C24=0,D24=0),"",D40*D24-E34) -> 1120
B60: CASH-FLOW MAX DAILY (weakest link) | C60: =IF(C24=0,"",MAX(0,MIN(C57:C59))) -> 993.30409 | D60: =IF(C60="","",IF(C60=0,"no clean room - existing debt is over a green line",INDEX({"SP% holdback";"Total LVG";"Daily/Balance"},MATCH(C60,C57:C59,0))&" is the limit")) -> SP% holdback is the limit
B61: Weekly / monthly equivalent | C61: =IF(OR(C60="",C60=0),"",C60*5) -> 4966.5204 | D61: =IF(OR(C60="",C60=0),"",C60*$K$9) -> 21510
B62: Term (daily pmts) / factor from bands | C62: =IF(OR(C60="",C60=0,C55=""),"",MAX(20,MIN(INDEX(Controls!$B$19:$B$22,MATCH(D57,Controls!$A$19:$A$22,1)),FLOOR(Controls!$B$23*$K$9,5),FLOOR(D41*C24*D62/C60,5)))) -> 100 | D62: =IF(OR(C55="",C24=0),"",INDEX(Controls!$C$19:$C$22,MATCH(D57,Controls!$A$19:$A$22,1))) -> 1.45
B63: CASH-FLOW MAX FUND | C63: =IF(COUNTIF(F42:F45,"KNOCKOUT")>0,"-",IF(OR(C60="",C60=0,C62="",D62=""),"",FLOOR(C60*C62/D62,500))) -> 68500 | D63: =IF(C63="-","KNOCKOUT on the merchant - do not fund.",IF(C63="","","payback "&TEXT(C63*D62,"$#,##0")&" over "&C62&" daily pmts ("&TEXT(C62/5,"0")&" wks) - this is the ceiling; see F below")) -> payback $99,325 over 100 daily pmts (20 wks) - this is the ceiling; see F below
B65: F. FINAL OFFER = cash-flow maximum x house-book evidence (full detail on Decision Summary)
B66: Item | C66: Value | D66: Detail
B67: FINAL DECISION | C67: ='Decision Summary'!$C$5 -> CONDITIONAL | D67: ='Decision Summary'!$D$5 -> Yellows/reds remain, evidence is negative, or conditional stips apply - see below.
B68: Recommended fund | C68: ='Decision Summary'!$C$6 -> 54500 | D68: ='Decision Summary'!$D$6 -> cash-flow max $68,500 -> 80% used (requested $75,000)
B69: Factor | C69: ='Decision Summary'!$C$7 -> 1.49 | D69: ='Decision Summary'!$D$7 -> base 1.45 -> raised one approved tier by history
B70: Term | C70: ='Decision Summary'!$C$8 -> 20 | D70: ='Decision Summary'!$D$8 -> weeks (4.6 months; base 100 daily pmts)
B71: Payment | C71: ='Decision Summary'!$C$9 -> 4060.25 | D71: ='Decision Summary'!$D$9 -> per week; daily-equivalent $812.05, monthly $17,585; payback $81,205, net $51,775
B72: Frequency | C72: ='Decision Summary'!$C$10 -> Weekly | D72: ='Decision Summary'!$D$10 -> As proposed on the Deal sheet
B73: Holdback % at final offer | C73: ='Decision Summary'!$C$11 -> 0.14715433 | D73: ='Decision Summary'!$D$11 -> GREEN (green line 18%)
B74: Historical modifier | C74: ='Decision Summary'!$C$16 -> Mild negative | D74: ='Decision Summary'!$D$16 -> relative index 1.27 (1.00 = seasoned book); fund x 0.80, term step -1, factor step 1
B75: Comparable deals (seasoned / all) | C75: ='Decision Summary'!$C$19 -> 23 / 27 | D75: ='Decision Summary'!$D$19 -> T1: new/renewal + industry + position
B76: Cohort principal lost rate | C76: ='Decision Summary'!$C$21 -> 0.34000684 | D76: ='Decision Summary'!$D$21 -> vs seasoned book 21.1%; blended (credibility-weighted) 26.7%; collected on defaults 29%
B77: Confidence | C77: ='Decision Summary'!$C$18 -> Medium | D77: ='Decision Summary'!$D$18 -> Z = 0.43; open share 4%; primary tier 1
B78: Stipulations | C78: ='Decision Summary'!$C$26 -> DataMerch, UCC search, positions / payoff letters; No-stacking covenant with default-to-daily; Bank login verification (Plaid/DecisionLogic); Landlord/lease letter;
B79: Underwriter's conclusion | C79: ='Decision Summary'!$C$30 -> Cash flow supports up to $68,500 (SP% holdback is the limit, 100 daily pmts @ 1.45). The recommendation is $54,500 (80% of the maximum) at 1.49 over 20 weeks, $4,060/week, because the primary comparable cohort (T1: new/renewal + industry + position) holds 23 / 27 seasoned deals with a principal lost rate of 34.0% against 21.1% for the seasoned book; at credibility 0.43 that blends to 26.7% (index 1.27), which is mild negative. Confidence is medium. ISO United Secured Capital 8: 109 seasoned deals, lost 26.5% vs 21.1% book, Z 0.78 -> weaker than book. Industry General Building Contractors: 82 seasoned deals, lost 32.5% vs 21.1% book, Z 0.73 -> weaker than book. State TX: 118 seasoned deals, lost 13.0% vs 21.1% book - informational only, not used in the offer. Conditional stips: No-stacking covenant with default-to-daily; Bank login verification (Plaid/DecisionLogic); Landlord/lease letter;
B80: Layer 1 (sections A-E) is the safety ceiling. Section F never exceeds C63, never removes a knockout and never turns a green metric red - see Checks. Thresholds live on Controls.

Sheet Decision Summary
B1: DECISION SUMMARY
B2: Everything an underwriter needs to sign or override. Cash flow sets the ceiling (Layer 1); house-book evidence sets how much of it to use (Layers 2-3).
B4: Item | C4: Value | D4: Detail
B5: DECISION | C5: =IF(Deal!$C$24=0,"",IF(OR(Deal!$C$63="-",Deal!$C$63="",'Offer Engine'!$D$8="",'Offer Engine'!$D$8=0,'Offer Engine'!$D$8<Controls!$B$14,'Offer Engine'!$D$40>=Controls!$B$13),"DECLINE",IF(C28<>"","MANUAL REVIEW",IF(OR(COUNTIF('Offer Engine'!$E$26:$E$33,"YELLOW")+COUNTIF('Offer Engine'!$E$26:$E$33,"RED")>0,'Offer Engine'!$C$10>=4,C31>0),"CONDITIONAL","APPROVE")))) -> CONDITIONAL | D5: =IF(C5="","Enter bank data + deal profile.",IF(C5="DECLINE",IF(COUNTIF(Deal!$F$42:$F$45,"KNOCKOUT")>0,"Merchant knockout: "&INDEX(Deal!$B$42:$B$45,MATCH("KNOCKOUT",Deal!$F$42:$F$45,0))&".",IF(OR('Offer Engine'!$D$8="",'Offer Engine'!$D$8=0),"No clean room under the green lines.",IF('Offer Engine'!$D$8<Controls!$B$14,"Adjusted fund "&TEXT('Offer Engine'!$D$8,"$#,##0")&" is below the minimum "&TEXT(Controls!$B$14,"$#,##0")&".","Red flags at the adjusted offer reached the limit."))),IF(C5="MANUAL REVIEW","Triggers: "&C28,IF(C5="APPROVE","All metrics green at the adjusted offer; evidence neutral or better; standard stips only.","Yellows/reds remain, evidence is negative, or conditional stips apply - see below.")))) -> Yellows/reds remain, evidence is negative, or conditional stips apply - see below.
B6: Recommended funding amount | C6: ='Offer Engine'!$D$8 -> 54500 | D6: =IF(OR(C6="",C6="-"),"",IF(ISNUMBER(Deal!$C$63),"cash-flow max "&TEXT(Deal!$C$63,"$#,##0")&" -> "&TEXT(C6/Deal!$C$63,"0%")&" used (requested "&IF(Deal!$B$6="","n/a",TEXT(Deal!$B$6,"$#,##0"))&")","")) -> cash-flow max $68,500 -> 80% used (requested $75,000)
B7: Recommended factor rate | C7: ='Offer Engine'!$D$7 -> 1.49 | D7: =IF(C7="","","base "&TEXT('Offer Engine'!$C$7,"0.00")&IF('Offer Engine'!$D$7>'Offer Engine'!$C$7," -> raised one approved tier by history","")) -> base 1.45 -> raised one approved tier by history
B8: Recommended term | C8: ='Offer Engine'!$D$17 -> 20 | D8: =IF(C8="","",IF('Offer Engine'!$D$16="Weekly","weeks","daily payments")&" ("&TEXT('Offer Engine'!$D$22,"0.0")&" months; base "&'Offer Engine'!$C$6&" daily pmts"&IF('Offer Engine'!$D$6<'Offer Engine'!$C$6,", shortened by history","")&")") -> weeks (4.6 months; base 100 daily pmts)
B9: Payment | C9: ='Offer Engine'!$D$18 -> 4060.25 | D9: =IF(C9="","","per "&IF('Offer Engine'!$D$16="Weekly","week","business day")&"; daily-equivalent "&TEXT('Offer Engine'!$D$9,"$#,##0.00")&", monthly "&TEXT('Offer Engine'!$D$19,"$#,##0")&"; payback "&TEXT('Offer Engine'!$D$20,"$#,##0")&", net "&TEXT('Offer Engine'!$D$21,"$#,##0")) -> per week; daily-equivalent $812.05, monthly $17,585; payback $81,205, net $51,775
B10: Daily or weekly | C10: ='Offer Engine'!$D$16 -> Weekly | D10: =IF('Offer Engine'!$C$14="Weekly","Weekly required by the historical modifier","As proposed on the Deal sheet") -> As proposed on the Deal sheet
B11: Holdback % | C11: ='Offer Engine'!$D$27 -> 0.14715433 | D11: =IF(C11="","",'Offer Engine'!$E$27&" (green line "&TEXT(Controls!$B$6,"0%")&")") -> GREEN (green line 18%)
B12: Total leverage (all debt / revenue) | C12: ='Offer Engine'!$D$26 -> 0.23776103 | D12: =IF(C12="","",'Offer Engine'!$E$26&" (green line "&TEXT(Controls!$B$5,"0%")&")") -> GREEN (green line 30%)
B13: Funding-to-revenue | C13: ='Offer Engine'!$D$29 -> 0.45606695 | D13: =IF(C13="","",'Offer Engine'!$E$29&" (green line "&TEXT(Controls!$B$8,"0.00")&"x)") -> GREEN (green line 0.60x)
B14: Daily debt-to-balance | C14: ='Offer Engine'!$D$28 -> 0.14578333 | D14: =IF(C14="","",'Offer Engine'!$E$28&" (green line "&TEXT(Controls!$B$7,"0%")&")") -> GREEN (green line 18%)
B15: Number of positions (incl. new) | C15: =Deal!$C$42 -> 2 | D15: =IF(C15="","",Deal!$F$42&IF(Deal!$K$18<>""," (position override "&Deal!$K$18&" used for matching)","")) -> GREEN
B16: Historical risk modifier | C16: ='Historical Score'!$C$43 -> Mild negative | D16: =IF(C16="","","relative index "&TEXT('Historical Score'!$C$39,"0.00")&" (1.00 = seasoned book); fund x "&TEXT('Offer Engine'!$D$11,"0.00")&", term step "&'Offer Engine'!$D$12&", factor step "&'Offer Engine'!$D$13&IF('Historical Score'!$C$42<>'Historical Score'!$C$40,"; capped by Low confidence","")) -> relative index 1.27 (1.00 = seasoned book); fund x 0.80, term step -1, factor step 1
B17: Cash-flow risk score | C17: =Deal!$C$55 -> 6.5 | D17: =IF(C17="","","of "&Deal!$D$55&" scored metrics = "&Deal!$C$56&" (scaled "&TEXT(Deal!$D$57,"0.0")&"/7 for pricing bands)") -> of 8 scored metrics = Solid (scaled 5.7/7 for pricing bands)
B18: Overall confidence in the historical evidence | C18: ='Historical Score'!$C$41 -> Medium | D18: ="Z = "&TEXT('Historical Score'!$C$37,"0.00")&"; open share "&IF('Historical Score'!$C$34="","n/a",TEXT('Historical Score'!$C$34,"0%"))&"; "&IF('Historical Score'!$C$29=7,"no specific cohort met the minimums","primary tier "&'Historical Score'!$C$29) -> Z = 0.43; open share 4%; primary tier 1
B19: Number of comparable deals (seasoned / all matches) | C19: ='Historical Score'!$C$31 -> 23 / 27 | D19: ='Historical Score'!$C$30 -> T1: new/renewal + industry + position
B20: Percentage of comparable deals seasoned | C20: ='Historical Score'!$C$32 -> 0.85185185 | D20: ="unseasoned deals are listed on Comparable Deals but never rated" -> unseasoned deals are listed on Comparable Deals but never rated
B21: Comparable-cohort principal lost rate | C21: ='Historical Score'!$C$33 -> 0.34000684 | D21: =IF(C21="","too few seasoned deals to show a rate","vs seasoned book "&TEXT('Historical Score'!$C$10,"0.0%")&"; blended (credibility-weighted) "&TEXT('Historical Score'!$C$38,"0.0%")&"; collected on defaults "&IF('Historical Score'!$C$36="","n/a",TEXT('Historical Score'!$C$36,"0%"))) -> vs seasoned book 21.1%; blended (credibility-weighted) 26.7%; collected on defaults 29%
B22: Comparable-cohort return on funded capital | C22: ='Historical Score'!$C$35 -> -0.11893978 | D22: =IF(C22="","","seasoned deals only; open deals in the cohort depress this figure") -> seasoned deals only; open deals in the cohort depress this figure
B23: Largest historical impact | C23: ='Historical Score'!$C$44 -> Industry only | D23: ='Historical Score'!$C$45 -> 29.4% vs 21.1% book (82 seasoned deals)
B24: Metric that limited the offer | C24: =IF(Deal!$D$60="","",Deal!$D$60) -> SP% holdback is the limit | D24: =IF(Deal!$C$60="","",IF(Deal!$C$60=0,"existing debt already exceeds a green line",IF(Deal!$C$62=FLOOR(Deal!$D$41*Deal!$C$24*Deal!$D$62/Deal!$C$60,5),"term also capped by the fund/revenue green line","term set by the score band"))) -> term also capped by the fund/revenue green line
B25: ISO / industry / state / position evidence | C25: ='Historical Score'!$C$46 -> ISO United Secured Capital 8: 109 seasoned deals, lost 26.5% vs 21.1% book, Z 0.78 -> weaker than book | D25: ='Historical Score'!$C$47&" | "&'Historical Score'!$C$48&" | "&'Historical Score'!$C$49&IF('Historical Score'!$C$50="No",""," | CONFLICT: "&'Historical Score'!$C$50) -> Industry General Building Contractors: 82 seasoned deals, lost 32.5% vs 21.1% book, Z 0.73 -> weaker than book | State TX: 118 seasoned deals, lost 13.0% vs 21.1% book - informational only, not used in the offer | Position 2: 145 seasoned deals, lost 23.6% vs 21.1% book
B26: Required stipulations | C26: =C27&IF(D26="","","; "&D26) -> DataMerch, UCC search, positions / payoff letters; No-stacking covenant with default-to-daily; Bank login verification (Plaid/DecisionLogic); Landlord/lease letter; | D26: =IF(AND(Controls!$B$91="Y",'Offer Engine'!$C$10>=4),"No-stacking covenant with default-to-daily; ","")&IF(AND(Controls!$B$92="Y",Deal!$F$44<>"GREEN",Deal!$F$44<>""),"Bank login verification (Plaid/DecisionLogic); ","")&IF(AND(Controls!$B$93="Y",Deal!$C$34>=2),"Payoff/balance letter for each existing position; ","")&IF(AND(Controls!$B$94="Y",Deal!$F$45<>"GREEN",Deal!$F$45<>""),"Landlord/lease letter; ","")&IF(AND(Controls!$B$95="Y",'Historical Score'!$C$41="Low"),"Underwriter review of historical evidence; ","")&IF(AND(Controls!$B$96="Y",'Offer Engine'!$C$14="Weekly"),"Weekly remittance only; ","")&IF(AND(Controls!$B$97="Y",Deal!$K$15="Renewal"),"Prior-contract payoff and renewal history; ","") -> No-stacking covenant with default-to-daily; Bank login verification (Plaid/DecisionLogic); Landlord/lease letter;
B27: Standard stipulations | C27: =IF(Controls!$B$90="Y",Controls!$A$90,"") -> DataMerch, UCC search, positions / payoff letters | D27: ="always required" -> always required
B28: Manual-review triggers fired | C28: =IF(AND(Controls!$B$79="Y",'Offer Engine'!$C$15="Y"),"Severe historical modifier; ","")&IF(AND(Controls!$B$80="Y",'Historical Score'!$C$41="Low",COUNTIF('Offer Engine'!$E$26:$E$33,"RED")>0),"Low confidence with a RED metric; ","")&IF(AND(Controls!$B$81="Y",Deal!$F$45="RED",COUNTIF('Offer Engine'!$E$26:$E$32,"RED")>0),"Credit RED plus another RED; ","")&IF(AND(Controls!$B$82="Y",ISNUMBER(Deal!$C$42),IF(ISNUMBER(Deal!$C$42),Deal!$C$42,0)>=Controls!$C$82),"Positions incl. new at/above "&Controls!$C$82&"; ","")&IF(AND(Controls!$B$83="Y",Deal!$K$15="New Deal",ISNUMBER('Historical Score'!$C$6),IF(ISNUMBER('Historical Score'!$C$6),'Historical Score'!$C$6,0)>=Controls!$C$83,OR(Deal!$K$13="General Building Contractors",Deal!$K$13="Special Trade Contractors",Deal!$K$13="Heavy Construction")),"New 3rd+ position construction deal; ","")&IF(AND(Controls!$B$84="Y",OR(AND(Deal!$K$12<>"",COUNTIF('Historical Data'!$K$2:$K$1068,Deal!$K$12)=0),AND(Deal!$K$13<>"",COUNTIF('Historical Data'!$Y$2:$Y$1068,Deal!$K$13)=0))),"ISO or industry not in house book; ","")&IF(AND(Controls!$B$85="Y",ISNUMBER('Offer Engine'!$D$8),IF(ISNUMBER('Offer Engine'!$D$8),'Offer Engine'!$D$8,0)<Controls!$B$14,IF(ISNUMBER('Offer Engine'!$D$8),'Offer Engine'!$D$8,0)>0),"Adjusted fund below minimum; ","")&IF(AND(Controls!$B$86="Y",ISNUMBER('Historical Score'!$C$34),IF(ISNUMBER('Historical Score'!$C$34),'Historical Score'!$C$34,0)>Controls!$B$43),"Cohort open share high; ","") | D28: ="blank = none" -> blank = none
B29: Main risks / positive factors | C29: =IF(COUNTIF(Deal!$F$38:$F$45,"RED")+COUNTIF(Deal!$F$38:$F$45,"KNOCKOUT")=0,"Risks: none red on the requested offer","Risks: "&IF(Deal!$F$38="RED","total leverage; ","")&IF(Deal!$F$39="RED","holdback; ","")&IF(Deal!$F$40="RED","daily debt/balance; ","")&IF(Deal!$F$41="RED","fund/revenue; ","")&IF(Deal!$F$42="RED","positions; ","")&IF(Deal!$F$43="RED","revenue trend; ","")&IF(Deal!$F$44="RED","neg days/NSFs; ","")&IF(Deal!$F$45="RED","credit; ","")&IF(COUNTIF(Deal!$F$38:$F$45,"KNOCKOUT")>0,"KNOCKOUT present",""))&IF('Offer Engine'!$C$10>=4," | history: "&'Historical Score'!$C$43,"") -> Risks: none red on the requested offer | history: Mild negative | D29: ="Positives: "&IF(COUNTIF(Deal!$F$38:$F$45,"GREEN")=0,"none green",IF(Deal!$F$38="GREEN","leverage; ","")&IF(Deal!$F$39="GREEN","holdback; ","")&IF(Deal!$F$40="GREEN","daily debt/balance; ","")&IF(Deal!$F$41="GREEN","fund/revenue; ","")&IF(Deal!$F$42="GREEN","positions; ","")&IF(Deal!$F$43="GREEN","revenue trend; ","")&IF(Deal!$F$44="GREEN","clean neg days/NSFs; ","")&IF(Deal!$F$45="GREEN","credit; ",""))&IF('Offer Engine'!$C$10<=2,"history: "&'Historical Score'!$C$43,"")&IF(Deal!$K$15="Renewal"," | renewal (strongest surviving positive in the book)","") -> Positives: leverage; holdback; daily debt/balance; positions; revenue trend;
B30: Underwriter's conclusion | C30: =IF(Deal!$C$24=0,"Enter bank data.",IF(Deal!$C$63="-","Do not fund: "&INDEX(Deal!$B$42:$B$45,MATCH("KNOCKOUT",Deal!$F$42:$F$45,0))&" is past its knockout line; history cannot override a knockout.",IF(OR(Deal!$C$63="",Deal!$C$63=0),"Cash flow leaves no clean room under the green lines - "&Deal!$D$60&".","Cash flow supports up to "&TEXT(Deal!$C$63,"$#,##0")&" ("&Deal!$D$60&", "&Deal!$C$62&" daily pmts @ "&TEXT(Deal!$D$62,"0.00")&"). "&IF(C5="DECLINE","The deal is declined: "&D5&" For reference, ","The recommendation is "&TEXT(C6,"$#,##0")&" ("&TEXT(C6/Deal!$C$63,"0%")&" of the maximum) at "&TEXT(C7,"0.00")&" over "&TEXT(C8,"0")&IF(C10="Weekly"," weeks"," daily payments")&", "&TEXT(C9,"$#,##0")&IF(C10="Weekly","/week","/day")&", because ")&"the primary comparable cohort ("&'Historical Score'!$C$30&") holds "&'Historical Score'!$C$31&" seasoned deals with a principal lost rate of "&IF('Historical Score'!$C$33="","n/a",TEXT('Historical Score'!$C$33,"0.0%"))&" against "&TEXT('Historical Score'!$C$10,"0.0%")&" for the seasoned book; at credibility "&TEXT('Historical Score'!$C$37,"0.00")&" that blends to "&TEXT('Historical Score'!$C$38,"0.0%")&" (index "&TEXT('Historical Score'!$C$39,"0.00")&"), which is "&LOWER('Historical Score'!$C$43)&IF('Historical Score'!$C$42<>'Historical Score'!$C$40," after the low-confidence cap","")&". Confidence is "&LOWER('Historical Score'!$C$41)&". "&IF(Deal!$K$15="Renewal","Renewal status is the strongest surviving positive in the book. ","")&'Historical Score'!$C$46&". "&'Historical Score'!$C$47&". "&'Historical Score'!$C$48&". "&IF(C28<>"","Sent to manual review: "&C28,"")&IF(D26<>""," Conditional stips: "&D26,"")))) -> Cash flow supports up to $68,500 (SP% holdback is the limit, 100 daily pmts @ 1.45). The recommendation is $54,500 (80% of the maximum) at 1.49 over 20 weeks, $4,060/week, because the primary comparable cohort (T1: new/renewal + industry + position) holds 23 / 27 seasoned deals with a principal lost rate of 34.0% against 21.1% for the seasoned book; at credibility 0.43 that blends to 26.7% (index 1.27), which is mild negative. Confidence is medium. ISO United Secured Capital 8: 109 seasoned deals, lost 26.5% vs 21.1% book, Z 0.78 -> weaker than book. Industry General Building Contractors: 82 seasoned deals, lost 32.5% vs 21.1% book, Z 0.73 -> weaker than book. State TX: 118 seasoned deals, lost 13.0% vs 21.1% book - informational only, not used in the offer. Conditional stips: No-stacking covenant with default-to-daily; Bank login verification (Plaid/DecisionLogic); Landlord/lease letter;
B31: Risk-based conditional stips (drive CONDITIONAL) | C31: =IF(AND(Controls!$B$91="Y",'Offer Engine'!$C$10>=4),1,0)+IF(AND(Controls!$B$92="Y",Deal!$F$44<>"GREEN",Deal!$F$44<>""),1,0)+IF(AND(Controls!$B$94="Y",Deal!$F$45<>"GREEN",Deal!$F$45<>""),1,0)+IF(AND(Controls!$B$95="Y",'Historical Score'!$C$41="Low"),1,0)+IF(AND(Controls!$B$96="Y",'Offer Engine'!$C$14="Weekly"),1,0) -> 3 | D31: ="documentary stips (payoff letters, renewal history) do not by themselves make a deal CONDITIONAL" -> documentary stips (payoff letters, renewal history) do not by themselves make a deal CONDITIONAL

Sheet Offer Engine
B1: OFFER ENGINE - base cash-flow offer, historical adjustment, adjusted offer
B2: Adjusted fund = MIN(base fund x multiplier, cash-flow max daily x adjusted term / adjusted factor). The second term keeps the daily payment at or below the cash-flow maximum even when the term is shortened.
B4: Item | C4: Base (cash flow only) | D4: Adjusted (with history) | E4: Status | F4: How
B5: Cash-flow max daily payment | C5: =Deal!$C$60 -> 993.30409 | D5: =Deal!$C$60 -> 993.30409 | F5: Deal C60 - weakest of holdback / total LVG / daily-debt-to-balance green lines
B6: Term (daily payments) | C6: =Deal!$C$62 -> 100 | D6: =IF(OR(C6="",C8="-"),"",MAX(20,MIN(C6,INDEX(Controls!$B$19:$B$22,MAX(1,MATCH(Deal!$D$57,Controls!$A$19:$A$22,1)+C12))))) -> 100 | F6: Base band term; step moves down the Controls band table
B7: Factor | C7: =Deal!$D$62 -> 1.45 | D7: =IF(C7="","",INDEX(Controls!$B$24:$D$24,MIN(3,MAX(1,MATCH(C7,Controls!$B$24:$D$24,0)+C13)))) -> 1.49 | F7: Next approved tier, never above 1.49
B8: Fund $ | C8: =Deal!$C$63 -> 68500 | D8: =IF(C8="-","-",IF(OR(C8="",D6="",D7=""),"",MAX(0,FLOOR(MIN(C8*C11,C5*D6/D7),500)))) -> 54500 | F8: Never above the base fund
B9: Daily payment | C9: =IF(OR(C8="",C8="-"),"",C8*C7/C6) -> 993.25 | D9: =IF(OR(D8="",D8="-",D8=0),"",D8*D7/D6) -> 812.05 | F9: fund x factor / term
B10: Historical modifier level (after confidence cap) | C10: ='Historical Score'!$C$42 -> 4 | D10: ='Historical Score'!$C$42 -> 4 | F10: 1 strong positive .. 3 neutral .. 6 severe
B11: Fund multiplier | C11: =INDEX(Controls!$C$54:$C$59,C10) -> 0.8 | D11: =INDEX(Controls!$C$54:$C$59,C10) -> 0.8 | F11: Controls modifier table
B12: Term step (bands) | C12: =INDEX(Controls!$D$54:$D$59,C10) -> -1 | D12: =INDEX(Controls!$D$54:$D$59,C10) -> -1
B13: Factor step (tiers) | C13: =INDEX(Controls!$E$54:$E$59,C10) -> 1 | D13: =INDEX(Controls!$E$54:$E$59,C10) -> 1
B14: Frequency rule | C14: =INDEX(Controls!$F$54:$F$59,C10) -> As proposed | D14: =INDEX(Controls!$F$54:$F$59,C10) -> As proposed
B15: Manual review flag from modifier | C15: =INDEX(Controls!$G$54:$G$59,C10) -> N | D15: =INDEX(Controls!$G$54:$G$59,C10) -> N
B16: Frequency (final) | C16: =IF(Deal!$E$6="","Daily",Deal!$E$6) -> Weekly | D16: =IF(C14="Weekly","Weekly",IF(Deal!$E$6="","Daily",Deal!$E$6)) -> Weekly | F16: Proposed frequency unless the modifier requires weekly
B17: Term in final units (weeks or daily pmts) | C17: =IF(OR(C6="",C8="-"),"",IF(C16="Weekly",C6/5,C6)) -> 20 | D17: =IF(OR(D6="",D8="-"),"",IF(D16="Weekly",D6/5,D6)) -> 20
B18: Payment in final units | C18: =IF(C9="","",IF(C16="Weekly",C9*5,C9)) -> 4966.25 | D18: =IF(D9="","",IF(D16="Weekly",D9*5,D9)) -> 4060.25
B19: Monthly payment | C19: =IF(C9="","",C9*Controls!$B$29) -> 21508.829 | D19: =IF(D9="","",D9*Controls!$B$29) -> 17584.943
B20: Payback | C20: =IF(OR(C8="",C8="-"),"",C8*C7) -> 99325 | D20: =IF(OR(D8="",D8="-"),"",D8*D7) -> 81205
B21: Net disbursed (after fee) | C21: =IF(OR(C8="",C8="-"),"",C8*(1-Controls!$B$15)) -> 65075 | D21: =IF(OR(D8="",D8="-"),"",D8*(1-Controls!$B$15)) -> 51775
B22: Term (months) | C22: =IF(C6="","",C6/Controls!$B$29) -> 4.6178712 | D22: =IF(D6="","",D6/Controls!$B$29) -> 4.6178712
B24: METRICS RE-CHECKED AT EACH OFFER (must stay off RED / KNOCKOUT)
B25: Metric | C25: Base offer | D25: Adjusted offer | E25: Status (adjusted) | F25: Green / Red / Knockout
B26: Total LVG (all debt / rev) | C26: =IF(OR(Deal!$C$24=0,C9=""),"",(Deal!$E$34+C9)*Controls!$B$29/Deal!$C$24) -> 0.27059689 | D26: =IF(OR(Deal!$C$24=0,D9=""),"",(Deal!$E$34+D9)*Controls!$B$29/Deal!$C$24) -> 0.23776103 | E26: =IF(D26="","",IF(D26>=Controls!$D$5,"KNOCKOUT",IF(D26<=Controls!$B$5,"GREEN",IF(D26>=Controls!$C$5,"RED","YELLOW")))) -> GREEN | F26: =TEXT(Controls!$B$5,"0.0%")&" / "&TEXT(Controls!$C$5,"0.0%")&" / "&TEXT(Controls!$D$5,"0.0%") -> 30.0% / 45.0% / 55.0%
B27: New holdback SP% | C27: =IF(OR(Deal!$C$24=0,C9=""),"",C9*Controls!$B$29/Deal!$C$24) -> 0.1799902 | D27: =IF(OR(Deal!$C$24=0,D9=""),"",D9*Controls!$B$29/Deal!$C$24) -> 0.14715433 | E27: =IF(D27="","",IF(D27>=Controls!$D$6,"KNOCKOUT",IF(D27<=Controls!$B$6,"GREEN",IF(D27>=Controls!$C$6,"RED","YELLOW")))) -> GREEN | F27: =TEXT(Controls!$B$6,"0.0%")&" / "&TEXT(Controls!$C$6,"0.0%")&" / "&TEXT(Controls!$D$6,"0.0%") -> 18.0% / 25.0% / 35.0%
B28: Daily debt / balance | C28: =IF(OR(Deal!$D$24=0,C9=""),"",(Deal!$E$34+C9)/Deal!$D$24) -> 0.16591667 | D28: =IF(OR(Deal!$D$24=0,D9=""),"",(Deal!$E$34+D9)/Deal!$D$24) -> 0.14578333 | E28: =IF(D28="","",IF(D28>=Controls!$D$7,"KNOCKOUT",IF(D28<=Controls!$B$7,"GREEN",IF(D28>=Controls!$C$7,"RED","YELLOW")))) -> GREEN | F28: =TEXT(Controls!$B$7,"0.0%")&" / "&TEXT(Controls!$C$7,"0.0%")&" / "&TEXT(Controls!$D$7,"0.0%") -> 18.0% / 30.0% / 35.0%
B29: Fund / revenue | C29: =IF(OR(Deal!$C$24=0,C8="",C8="-"),"",C8/Deal!$C$24) -> 0.57322176 | D29: =IF(OR(Deal!$C$24=0,D8="",D8="-"),"",D8/Deal!$C$24) -> 0.45606695 | E29: =IF(D29="","",IF(D29>=Controls!$D$8,"KNOCKOUT",IF(D29<=Controls!$B$8,"GREEN",IF(D29>=Controls!$C$8,"RED","YELLOW")))) -> GREEN | F29: =TEXT(Controls!$B$8,"0.00")&" / "&TEXT(Controls!$C$8,"0.00")&" / "&TEXT(Controls!$D$8,"0.00") -> 0.60 / 0.90 / 1.25
B30: # positions (incl. new) | C30: =Deal!$C$42 -> 2 | D30: =Deal!$C$42 -> 2 | E30: =Deal!$F$42 -> GREEN | F30: merchant-side metric - unchanged by the offer
B31: Revenue trend (avg MoM) | C31: =Deal!$C$43 -> 0.026075994 | D31: =Deal!$C$43 -> 0.026075994 | E31: =Deal!$F$43 -> GREEN | F31: merchant-side metric - unchanged by the offer
B32: Neg days + NSFs (total) | C32: =Deal!$C$44 -> 2 | D32: =Deal!$C$44 -> 2 | E32: =Deal!$F$44 -> YELLOW | F32: merchant-side metric - unchanged by the offer
B33: Credit score (FICO) | C33: =Deal!$C$45 -> 640 | D33: =Deal!$C$45 -> 640 | E33: =Deal!$F$45 -> YELLOW | F33: merchant-side metric - unchanged by the offer
B35: SAFETY PROOF
B36: Adjusted fund <= cash-flow max fund | D36: =IF(OR(D8="",D8="-",C8="",C8="-"),"OK",IF(D8<=C8,"OK","FAIL")) -> OK
B37: Adjusted daily payment <= cash-flow max daily | D37: =IF(OR(D9="",C5=""),"OK",IF(D9<=C5+0.005,"OK","FAIL")) -> OK
B38: No offer-side metric RED or KNOCKOUT at adjusted offer | D38: =IF(COUNTIF(E26:E29,"RED")+COUNTIF(E26:E29,"KNOCKOUT")=0,"OK","FAIL") -> OK
B39: Merchant knockouts untouched (history cannot remove them) | D39: =IF(COUNTIF(Deal!$F$42:$F$45,"KNOCKOUT")>0,IF(D8="-","OK","FAIL"),"OK") -> OK
B40: Red flags at adjusted offer (offer-side + merchant-side) | D40: =COUNTIF(E26:E33,"RED")+COUNTIF(E26:E33,"KNOCKOUT") -> 0

Sheet Historical Score
A1: HISTORICAL SCORE - comparable cohorts, credibility and the risk modifier
A2: Rates use SEASONED deals only (age >= seasoning multiple x contracted term, as of the Controls date). Unseasoned deals are counted, never rated. Blended lost rate = Z x cohort + (1-Z) x seasoned book, Z = n/(n+K).
A4: DEAL BEING MATCHED (from the Deal sheet)
B5: New deal or renewal | C5: =IF(Deal!$K$15="","",Deal!$K$15) -> New Deal
B6: Proposed position (effective) | C6: =IF(Deal!$K$18<>"",Deal!$K$18,Deal!$K$17) -> 2
B7: Industry | C7: =IF(Deal!$K$13="","",Deal!$K$13) -> General Building Contractors
B8: ISO | C8: =IF(Deal!$K$12="","",Deal!$K$12) -> United Secured Capital 8
B9: State | C9: =IF(Deal!$K$14="","",Deal!$K$14) -> TX
B10: Seasoned-book principal lost rate (baseline) | C10: =$L$20 -> 0.21059699
B11: Seasoned-book deals / funded | C11: =TEXT($E$20,"#,##0")&" / "&TEXT($G$20,"$#,##0") -> 637 / $12,563,126
A13: Tier | B13: Cohort | C13: Keys | D13: Deals (all) | E13: Seasoned | F13: % seasoned | G13: Funded $ (seasoned) | H13: Open n | I13: Open % | J13: Default n | K13: Default % | L13: Principal lost rate | M13: Collected on defaults | N13: Return on funded | O13: Avg adv/rev | P13: Avg term (bd) | Q13: Avg factor | R13: Avg deal size | S13: Avg days on book | T13: Renewal share | U13: Seasoned enough? | V13: Credibility Z | W13: Blended lost rate | X13: Relative index | Y13: Meets min | Z13: Impact vs book | AA13: Lost rate shown?
A14: 1 | B14: T1: new/renewal + industry + position | C14: NR + industry + position | D14: =SUMPRODUCT('Historical Data'!$AV$2:$AV$1068*'Historical Data'!$AD$2:$AD$1068) -> 27 | E14: =SUMPRODUCT('Historical Data'!$AV$2:$AV$1068*'Historical Data'!$AP$2:$AP$1068) -> 23 | F14: =IF(D14=0,"",E14/D14) -> 0.85185185 | G14: =SUMPRODUCT('Historical Data'!$AV$2:$AV$1068*'Historical Data'!$AP$2:$AP$1068*'Historical Data'!$N$2:$N$1068) -> 414000 | H14: =SUMPRODUCT('Historical Data'!$AV$2:$AV$1068*'Historical Data'!$AP$2:$AP$1068*'Historical Data'!$AH$2:$AH$1068) -> 1 | I14: =IF(E14=0,"",H14/E14) -> 0.043478261 | J14: =SUMPRODUCT('Historical Data'!$AV$2:$AV$1068*'Historical Data'!$AP$2:$AP$1068*'Historical Data'!$AE$2:$AE$1068) -> 11 | K14: =IF(E14=0,"",J14/E14) -> 0.47826087 | L14: =IF(OR(E14<Controls!$B$47,G14=0),"",SUMPRODUCT('Historical Data'!$AV$2:$AV$1068*'Historical Data'!$AP$2:$AP$1068*'Historical Data'!$AK$2:$AK$1068)/G14) -> 0.34000684 | M14: =IF(OR(E14<Controls!$B$47,SUMPRODUCT('Historical Data'!$AV$2:$AV$1068*'Historical Data'!$AP$2:$AP$1068*'Historical Data'!$AE$2:$AE$1068*'Historical Data'!$N$2:$N$1068)=0),"",SUMPRODUCT('Historical Data'!$AV$2:$AV$1068*'Historical Data'!$AP$2:$AP$1068*'Historical Data'!$AE$2:$AE$1068*'Historical Data'!$Q$2:$Q$1068)/SUMPRODUCT('Historical Data'!$AV$2:$AV$1068*'Historical Data'!$AP$2:$AP$1068*'Historical Data'!$AE$2:$AE$1068*'Historical Data'!$N$2:$N$1068)) -> 0.28907662 | N14: =IF(OR(E14<Controls!$B$47,G14=0),"",SUMPRODUCT('Historical Data'!$AV$2:$AV$1068*'Historical Data'!$AP$2:$AP$1068*'Historical Data'!$AJ$2:$AJ$1068)/G14) -> -0.11893978 | O14: =IF(SUMPRODUCT('Historical Data'!$AV$2:$AV$1068*'Historical Data'!$AP$2:$AP$1068*'Historical Data'!$AM$2:$AM$1068)=0,"",SUMPRODUCT('Historical Data'!$AV$2:$AV$1068*'Historical Data'!$AP$2:$AP$1068*'Historical Data'!$AM$2:$AM$1068*'Historical Data'!$AL$2:$AL$1068)/SUMPRODUCT('Historical Data'!$AV$2:$AV$1068*'Historical Data'!$AP$2:$AP$1068*'Historical Data'!$AM$2:$AM$1068)) -> 0.25325913 | P14: =IF(E14=0,"",SUMPRODUCT('Historical Data'!$AV$2:$AV$1068*'Historical Data'!$AP$2:$AP$1068*'Historical Data'!$AA$2:$AA$1068)/E14) -> 81.615058 | Q14: =IF(E14=0,"",SUMPRODUCT('Historical Data'!$AV$2:$AV$1068*'Historical Data'!$AP$2:$AP$1068*'Historical Data'!$M$2:$M$1068)/E14) -> 1.4701739 | R14: =IF(E14=0,"",G14/E14) -> 18000 | S14: =IF(E14=0,"",SUMPRODUCT('Historical Data'!$AV$2:$AV$1068*'Historical Data'!$AP$2:$AP$1068*'Historical Data'!$AN$2:$AN$1068)/E14) -> 89.521739 | T14: =IF(E14=0,"",SUMPRODUCT('Historical Data'!$AV$2:$AV$1068*'Historical Data'!$AP$2:$AP$1068*'Historical Data'!$AO$2:$AO$1068)/E14) -> 0 | U14: =IF(AND(E14>=Controls!$B$40,G14>=Controls!$B$41,IF(I14="",1,I14)<=Controls!$B$43),"Yes","No") -> Yes | V14: =IF(E14+Controls!$B$42=0,0,E14/(E14+Controls!$B$42)) -> 0.43396226 | W14: =IF(L14="",$C$10,V14*L14+(1-V14)*$C$10) -> 0.26675598 | X14: =IF(OR($C$10="",$C$10=0),"",W14/$C$10) -> 1.2666657 | Y14: =IF(AND(E14>=Controls!$B$40,G14>=Controls!$B$41),1,0) -> 1 | Z14: =IF(L14="",0,ABS(W14-$C$10)) -> 0.056158988 | AA14: =IF(L14="","No","Yes") -> Yes
A15: 2 | B15: T2: new/renewal + ISO + position | C15: NR + ISO + position | D15: =SUMPRODUCT('Historical Data'!$AW$2:$AW$1068*'Historical Data'!$AD$2:$AD$1068) -> 21 | E15: =SUMPRODUCT('Historical Data'!$AW$2:$AW$1068*'Historical Data'!$AP$2:$AP$1068) -> 19 | F15: =IF(D15=0,"",E15/D15) -> 0.9047619 | G15: =SUMPRODUCT('Historical Data'!$AW$2:$AW$1068*'Historical Data'!$AP$2:$AP$1068*'Historical Data'!$N$2:$N$1068) -> 268500 | H15: =SUMPRODUCT('Historical Data'!$AW$2:$AW$1068*'Historical Data'!$AP$2:$AP$1068*'Historical Data'!$AH$2:$AH$1068) -> 3 | I15: =IF(E15=0,"",H15/E15) -> 0.15789474 | J15: =SUMPRODUCT('Historical Data'!$AW$2:$AW$1068*'Historical Data'!$AP$2:$AP$1068*'Historical Data'!$AE$2:$AE$1068) -> 9 | K15: =IF(E15=0,"",J15/E15) -> 0.47368421 | L15: =IF(OR(E15<Controls!$B$47,G15=0),"",SUMPRODUCT('Historical Data'!$AW$2:$AW$1068*'Historical Data'!$AP$2:$AP$1068*'Historical Data'!$AK$2:$AK$1068)/G15) -> 0.26167475 | M15: =IF(OR(E15<Controls!$B$47,SUMPRODUCT('Historical Data'!$AW$2:$AW$1068*'Historical Data'!$AP$2:$AP$1068*'Historical Data'!$AE$2:$AE$1068*'Historical Data'!$N$2:$N$1068)=0),"",SUMPRODUCT('Historical Data'!$AW$2:$AW$1068*'Historical Data'!$AP$2:$AP$1068*'Historical Data'!$AE$2:$AE$1068*'Historical Data'!$Q$2:$Q$1068)/SUMPRODUCT('Historical Data'!$AW$2:$AW$1068*'Historical Data'!$AP$2:$AP$1068*'Historical Data'!$AE$2:$AE$1068*'Historical Data'!$N$2:$N$1068)) -> 0.3754696 | N15: =IF(OR(E15<Controls!$B$47,G15=0),"",SUMPRODUCT('Historical Data'!$AW$2:$AW$1068*'Historical Data'!$AP$2:$AP$1068*'Historical Data'!$AJ$2:$AJ$1068)/G15) -> -0.027364804 | O15: =IF(SUMPRODUCT('Historical Data'!$AW$2:$AW$1068*'Historical Data'!$AP$2:$AP$1068*'Historical Data'!$AM$2:$AM$1068)=0,"",SUMPRODUCT('Historical Data'!$AW$2:$AW$1068*'Historical Data'!$AP$2:$AP$1068*'Historical Data'!$AM$2:$AM$1068*'Historical Data'!$AL$2:$AL$1068)/SUMPRODUCT('Historical Data'!$AW$2:$AW$1068*'Historical Data'!$AP$2:$AP$1068*'Historical Data'!$AM$2:$AM$1068)) -> 0.40948308 | P15: =IF(E15=0,"",SUMPRODUCT('Historical Data'!$AW$2:$AW$1068*'Historical Data'!$AP$2:$AP$1068*'Historical Data'!$AA$2:$AA$1068)/E15) -> 74.38436 | Q15: =IF(E15=0,"",SUMPRODUCT('Historical Data'!$AW$2:$AW$1068*'Historical Data'!$AP$2:$AP$1068*'Historical Data'!$M$2:$M$1068)/E15) -> 1.4860526 | R15: =IF(E15=0,"",G15/E15) -> 14131.579 | S15: =IF(E15=0,"",SUMPRODUCT('Historical Data'!$AW$2:$AW$1068*'Historical Data'!$AP$2:$AP$1068*'Historical Data'!$AN$2:$AN$1068)/E15) -> 101.47368 | T15: =IF(E15=0,"",SUMPRODUCT('Historical Data'!$AW$2:$AW$1068*'Historical Data'!$AP$2:$AP$1068*'Historical Data'!$AO$2:$AO$1068)/E15) -> 0 | U15: =IF(AND(E15>=Controls!$B$40,G15>=Controls!$B$41,IF(I15="",1,I15)<=Controls!$B$43),"Yes","No") -> No | V15: =IF(E15+Controls!$B$42=0,0,E15/(E15+Controls!$B$42)) -> 0.3877551 | W15: =IF(L15="",$C$10,V15*L15+(1-V15)*$C$10) -> 0.23040265 | X15: =IF(OR($C$10="",$C$10=0),"",W15/$C$10) -> 1.0940453 | Y15: =IF(AND(E15>=Controls!$B$40,G15>=Controls!$B$41),1,0) -> 1 | Z15: =IF(L15="",0,ABS(W15-$C$10)) -> 0.01980566 | AA15: =IF(L15="","No","Yes") -> Yes
A16: 3 | B16: T3: new/renewal + industry | C16: NR + industry | D16: =SUMPRODUCT('Historical Data'!$AX$2:$AX$1068*'Historical Data'!$AD$2:$AD$1068) -> 98 | E16: =SUMPRODUCT('Historical Data'!$AX$2:$AX$1068*'Historical Data'!$AP$2:$AP$1068) -> 70 | F16: =IF(D16=0,"",E16/D16) -> 0.71428571 | G16: =SUMPRODUCT('Historical Data'!$AX$2:$AX$1068*'Historical Data'!$AP$2:$AP$1068*'Historical Data'!$N$2:$N$1068) -> 1145500 | H16: =SUMPRODUCT('Historical Data'!$AX$2:$AX$1068*'Historical Data'!$AP$2:$AP$1068*'Historical Data'!$AH$2:$AH$1068) -> 5 | I16: =IF(E16=0,"",H16/E16) -> 0.071428571 | J16: =SUMPRODUCT('Historical Data'!$AX$2:$AX$1068*'Historical Data'!$AP$2:$AP$1068*'Historical Data'!$AE$2:$AE$1068) -> 40 | K16: =IF(E16=0,"",J16/E16) -> 0.57142857 | L16: =IF(OR(E16<Controls!$B$47,G16=0),"",SUMPRODUCT('Historical Data'!$AX$2:$AX$1068*'Historical Data'!$AP$2:$AP$1068*'Historical Data'!$AK$2:$AK$1068)/G16) -> 0.3276407 | M16: =IF(OR(E16<Controls!$B$47,SUMPRODUCT('Historical Data'!$AX$2:$AX$1068*'Historical Data'!$AP$2:$AP$1068*'Historical Data'!$AE$2:$AE$1068*'Historical Data'!$N$2:$N$1068)=0),"",SUMPRODUCT('Historical Data'!$AX$2:$AX$1068*'Historical Data'!$AP$2:$AP$1068*'Historical Data'!$AE$2:$AE$1068*'Historical Data'!$Q$2:$Q$1068)/SUMPRODUCT('Historical Data'!$AX$2:$AX$1068*'Historical Data'!$AP$2:$AP$1068*'Historical Data'!$AE$2:$AE$1068*'Historical Data'!$N$2:$N$1068)) -> 0.4445203 | N16: =IF(OR(E16<Controls!$B$47,G16=0),"",SUMPRODUCT('Historical Data'!$AX$2:$AX$1068*'Historical Data'!$AP$2:$AP$1068*'Historical Data'!$AJ$2:$AJ$1068)/G16) -> -0.16574985 | O16: =IF(SUMPRODUCT('Historical Data'!$AX$2:$AX$1068*'Historical Data'!$AP$2:$AP$1068*'Historical Data'!$AM$2:$AM$1068)=0,"",SUMPRODUCT('Historical Data'!$AX$2:$AX$1068*'Historical Data'!$AP$2:$AP$1068*'Historical Data'!$AM$2:$AM$1068*'Historical Data'!$AL$2:$AL$1068)/SUMPRODUCT('Historical Data'!$AX$2:$AX$1068*'Historical Data'!$AP$2:$AP$1068*'Historical Data'!$AM$2:$AM$1068)) -> 0.28874264 | P16: =IF(E16=0,"",SUMPRODUCT('Historical Data'!$AX$2:$AX$1068*'Historical Data'!$AP$2:$AP$1068*'Historical Data'!$AA$2:$AA$1068)/E16) -> 74.471751 | Q16: =IF(E16=0,"",SUMPRODUCT('Historical Data'!$AX$2:$AX$1068*'Historical Data'!$AP$2:$AP$1068*'Historical Data'!$M$2:$M$1068)/E16) -> 1.4771764 | R16: =IF(E16=0,"",G16/E16) -> 16364.286 | S16: =IF(E16=0,"",SUMPRODUCT('Historical Data'!$AX$2:$AX$1068*'Historical Data'!$AP$2:$AP$1068*'Historical Data'!$AN$2:$AN$1068)/E16) -> 87.671429 | T16: =IF(E16=0,"",SUMPRODUCT('Historical Data'!$AX$2:$AX$1068*'Historical Data'!$AP$2:$AP$1068*'Historical Data'!$AO$2:$AO$1068)/E16) -> 0 | U16: =IF(AND(E16>=Controls!$B$40,G16>=Controls!$B$41,IF(I16="",1,I16)<=Controls!$B$43),"Yes","No") -> Yes | V16: =IF(E16+Controls!$B$42=0,0,E16/(E16+Controls!$B$42)) -> 0.7 | W16: =IF(L16="",$C$10,V16*L16+(1-V16)*$C$10) -> 0.29252759 | X16: =IF(OR($C$10="",$C$10=0),"",W16/$C$10) -> 1.3890397 | Y16: =IF(AND(E16>=Controls!$B$40,G16>=Controls!$B$41),1,0) -> 1 | Z16: =IF(L16="",0,ABS(W16-$C$10)) -> 0.081930593 | AA16: =IF(L16="","No","Yes") -> Yes
A17: 4 | B17: T4: new/renewal + ISO | C17: NR + ISO | D17: =SUMPRODUCT('Historical Data'!$AY$2:$AY$1068*'Historical Data'!$AD$2:$AD$1068) -> 135 | E17: =SUMPRODUCT('Historical Data'!$AY$2:$AY$1068*'Historical Data'!$AP$2:$AP$1068) -> 95 | F17: =IF(D17=0,"",E17/D17) -> 0.7037037 | G17: =SUMPRODUCT('Historical Data'!$AY$2:$AY$1068*'Historical Data'!$AP$2:$AP$1068*'Historical Data'!$N$2:$N$1068) -> 1608000 | H17: =SUMPRODUCT('Historical Data'!$AY$2:$AY$1068*'Historical Data'!$AP$2:$AP$1068*'Historical Data'!$AH$2:$AH$1068) -> 10 | I17: =IF(E17=0,"",H17/E17) -> 0.10526316 | J17: =SUMPRODUCT('Historical Data'!$AY$2:$AY$1068*'Historical Data'!$AP$2:$AP$1068*'Historical Data'!$AE$2:$AE$1068) -> 49 | K17: =IF(E17=0,"",J17/E17) -> 0.51578947 | L17: =IF(OR(E17<Controls!$B$47,G17=0),"",SUMPRODUCT('Historical Data'!$AY$2:$AY$1068*'Historical Data'!$AP$2:$AP$1068*'Historical Data'!$AK$2:$AK$1068)/G17) -> 0.2874518 | M17: =IF(OR(E17<Controls!$B$47,SUMPRODUCT('Historical Data'!$AY$2:$AY$1068*'Historical Data'!$AP$2:$AP$1068*'Historical Data'!$AE$2:$AE$1068*'Historical Data'!$N$2:$N$1068)=0),"",SUMPRODUCT('Historical Data'!$AY$2:$AY$1068*'Historical Data'!$AP$2:$AP$1068*'Historical Data'!$AE$2:$AE$1068*'Historical Data'!$Q$2:$Q$1068)/SUMPRODUCT('Historical Data'!$AY$2:$AY$1068*'Historical Data'!$AP$2:$AP$1068*'Historical Data'!$AE$2:$AE$1068*'Historical Data'!$N$2:$N$1068)) -> 0.46516004 | N17: =IF(OR(E17<Controls!$B$47,G17=0),"",SUMPRODUCT('Historical Data'!$AY$2:$AY$1068*'Historical Data'!$AP$2:$AP$1068*'Historical Data'!$AJ$2:$AJ$1068)/G17) -> -0.078777239 | O17: =IF(SUMPRODUCT('Historical Data'!$AY$2:$AY$1068*'Historical Data'!$AP$2:$AP$1068*'Historical Data'!$AM$2:$AM$1068)=0,"",SUMPRODUCT('Historical Data'!$AY$2:$AY$1068*'Historical Data'!$AP$2:$AP$1068*'Historical Data'!$AM$2:$AM$1068*'Historical Data'!$AL$2:$AL$1068)/SUMPRODUCT('Historical Data'!$AY$2:$AY$1068*'Historical Data'!$AP$2:$AP$1068*'Historical Data'!$AM$2:$AM$1068)) -> 0.40951816 | P17: =IF(E17=0,"",SUMPRODUCT('Historical Data'!$AY$2:$AY$1068*'Historical Data'!$AP$2:$AP$1068*'Historical Data'!$AA$2:$AA$1068)/E17) -> 70.336655 | Q17: =IF(E17=0,"",SUMPRODUCT('Historical Data'!$AY$2:$AY$1068*'Historical Data'!$AP$2:$AP$1068*'Historical Data'!$M$2:$M$1068)/E17) -> 1.4888982 | R17: =IF(E17=0,"",G17/E17) -> 16926.316 | S17: =IF(E17=0,"",SUMPRODUCT('Historical Data'!$AY$2:$AY$1068*'Historical Data'!$AP$2:$AP$1068*'Historical Data'!$AN$2:$AN$1068)/E17) -> 78.884211 | T17: =IF(E17=0,"",SUMPRODUCT('Historical Data'!$AY$2:$AY$1068*'Historical Data'!$AP$2:$AP$1068*'Historical Data'!$AO$2:$AO$1068)/E17) -> 0 | U17: =IF(AND(E17>=Controls!$B$40,G17>=Controls!$B$41,IF(I17="",1,I17)<=Controls!$B$43),"Yes","No") -> Yes | V17: =IF(E17+Controls!$B$42=0,0,E17/(E17+Controls!$B$42)) -> 0.76 | W17: =IF(L17="",$C$10,V17*L17+(1-V17)*$C$10) -> 0.26900665 | X17: =IF(OR($C$10="",$C$10=0),"",W17/$C$10) -> 1.2773527 | Y17: =IF(AND(E17>=Controls!$B$40,G17>=Controls!$B$41),1,0) -> 1 | Z17: =IF(L17="",0,ABS(W17-$C$10)) -> 0.058409655 | AA17: =IF(L17="","No","Yes") -> Yes
A18: 5 | B18: T5: new/renewal + position | C18: NR + position | D18: =SUMPRODUCT('Historical Data'!$AZ$2:$AZ$1068*'Historical Data'!$AD$2:$AD$1068) -> 187 | E18: =SUMPRODUCT('Historical Data'!$AZ$2:$AZ$1068*'Historical Data'!$AP$2:$AP$1068) -> 131 | F18: =IF(D18=0,"",E18/D18) -> 0.70053476 | G18: =SUMPRODUCT('Historical Data'!$AZ$2:$AZ$1068*'Historical Data'!$AP$2:$AP$1068*'Historical Data'!$N$2:$N$1068) -> 2313000 | H18: =SUMPRODUCT('Historical Data'!$AZ$2:$AZ$1068*'Historical Data'!$AP$2:$AP$1068*'Historical Data'!$AH$2:$AH$1068) -> 7 | I18: =IF(E18=0,"",H18/E18) -> 0.053435115 | J18: =SUMPRODUCT('Historical Data'!$AZ$2:$AZ$1068*'Historical Data'!$AP$2:$AP$1068*'Historical Data'!$AE$2:$AE$1068) -> 54 | K18: =IF(E18=0,"",J18/E18) -> 0.41221374 | L18: =IF(OR(E18<Controls!$B$47,G18=0),"",SUMPRODUCT('Historical Data'!$AZ$2:$AZ$1068*'Historical Data'!$AP$2:$AP$1068*'Historical Data'!$AK$2:$AK$1068)/G18) -> 0.23409906 | M18: =IF(OR(E18<Controls!$B$47,SUMPRODUCT('Historical Data'!$AZ$2:$AZ$1068*'Historical Data'!$AP$2:$AP$1068*'Historical Data'!$AE$2:$AE$1068*'Historical Data'!$N$2:$N$1068)=0),"",SUMPRODUCT('Historical Data'!$AZ$2:$AZ$1068*'Historical Data'!$AP$2:$AP$1068*'Historical Data'!$AE$2:$AE$1068*'Historical Data'!$Q$2:$Q$1068)/SUMPRODUCT('Historical Data'!$AZ$2:$AZ$1068*'Historical Data'!$AP$2:$AP$1068*'Historical Data'!$AE$2:$AE$1068*'Historical Data'!$N$2:$N$1068)) -> 0.3864108 | N18: =IF(OR(E18<Controls!$B$47,G18=0),"",SUMPRODUCT('Historical Data'!$AZ$2:$AZ$1068*'Historical Data'!$AP$2:$AP$1068*'Historical Data'!$AJ$2:$AJ$1068)/G18) -> 0.026429563 | O18: =IF(SUMPRODUCT('Historical Data'!$AZ$2:$AZ$1068*'Historical Data'!$AP$2:$AP$1068*'Historical Data'!$AM$2:$AM$1068)=0,"",SUMPRODUCT('Historical Data'!$AZ$2:$AZ$1068*'Historical Data'!$AP$2:$AP$1068*'Historical Data'!$AM$2:$AM$1068*'Historical Data'!$AL$2:$AL$1068)/SUMPRODUCT('Historical Data'!$AZ$2:$AZ$1068*'Historical Data'!$AP$2:$AP$1068*'Historical Data'!$AM$2:$AM$1068)) -> 0.37419578 | P18: =IF(E18=0,"",SUMPRODUCT('Historical Data'!$AZ$2:$AZ$1068*'Historical Data'!$AP$2:$AP$1068*'Historical Data'!$AA$2:$AA$1068)/E18) -> 81.369269 | Q18: =IF(E18=0,"",SUMPRODUCT('Historical Data'!$AZ$2:$AZ$1068*'Historical Data'!$AP$2:$AP$1068*'Historical Data'!$M$2:$M$1068)/E18) -> 1.4660522 | R18: =IF(E18=0,"",G18/E18) -> 17656.489 | S18: =IF(E18=0,"",SUMPRODUCT('Historical Data'!$AZ$2:$AZ$1068*'Historical Data'!$AP$2:$AP$1068*'Historical Data'!$AN$2:$AN$1068)/E18) -> 86.206107 | T18: =IF(E18=0,"",SUMPRODUCT('Historical Data'!$AZ$2:$AZ$1068*'Historical Data'!$AP$2:$AP$1068*'Historical Data'!$AO$2:$AO$1068)/E18) -> 0 | U18: =IF(AND(E18>=Controls!$B$40,G18>=Controls!$B$41,IF(I18="",1,I18)<=Controls!$B$43),"Yes","No") -> Yes | V18: =IF(E18+Controls!$B$42=0,0,E18/(E18+Controls!$B$42)) -> 0.8136646 | W18: =IF(L18="",$C$10,V18*L18+(1-V18)*$C$10) -> 0.22971979 | X18: =IF(OR($C$10="",$C$10=0),"",W18/$C$10) -> 1.0908028 | Y18: =IF(AND(E18>=Controls!$B$40,G18>=Controls!$B$41),1,0) -> 1 | Z18: =IF(L18="",0,ABS(W18-$C$10)) -> 0.019122797 | AA18: =IF(L18="","No","Yes") -> Yes
A19: 6 | B19: T6: new/renewal only | C19: NR | D19: =SUMPRODUCT('Historical Data'!$BA$2:$BA$1068*'Historical Data'!$AD$2:$AD$1068) -> 852 | E19: =SUMPRODUCT('Historical Data'!$BA$2:$BA$1068*'Historical Data'!$AP$2:$AP$1068) -> 536 | F19: =IF(D19=0,"",E19/D19) -> 0.62910798 | G19: =SUMPRODUCT('Historical Data'!$BA$2:$BA$1068*'Historical Data'!$AP$2:$AP$1068*'Historical Data'!$N$2:$N$1068) -> 10039126 | H19: =SUMPRODUCT('Historical Data'!$BA$2:$BA$1068*'Historical Data'!$AP$2:$AP$1068*'Historical Data'!$AH$2:$AH$1068) -> 34 | I19: =IF(E19=0,"",H19/E19) -> 0.063432836 | J19: =SUMPRODUCT('Historical Data'!$BA$2:$BA$1068*'Historical Data'!$AP$2:$AP$1068*'Historical Data'!$AE$2:$AE$1068) -> 243 | K19: =IF(E19=0,"",J19/E19) -> 0.45335821 | L19: =IF(OR(E19<Controls!$B$47,G19=0),"",SUMPRODUCT('Historical Data'!$BA$2:$BA$1068*'Historical Data'!$AP$2:$AP$1068*'Historical Data'!$AK$2:$AK$1068)/G19) -> 0.23461302 | M19: =IF(OR(E19<Controls!$B$47,SUMPRODUCT('Historical Data'!$BA$2:$BA$1068*'Historical Data'!$AP$2:$AP$1068*'Historical Data'!$AE$2:$AE$1068*'Historical Data'!$N$2:$N$1068)=0),"",SUMPRODUCT('Historical Data'!$BA$2:$BA$1068*'Historical Data'!$AP$2:$AP$1068*'Historical Data'!$AE$2:$AE$1068*'Historical Data'!$Q$2:$Q$1068)/SUMPRODUCT('Historical Data'!$BA$2:$BA$1068*'Historical Data'!$AP$2:$AP$1068*'Historical Data'!$AE$2:$AE$1068*'Historical Data'!$N$2:$N$1068)) -> 0.46584113 | N19: =IF(OR(E19<Controls!$B$47,G19=0),"",SUMPRODUCT('Historical Data'!$BA$2:$BA$1068*'Historical Data'!$AP$2:$AP$1068*'Historical Data'!$AJ$2:$AJ$1068)/G19) -> -0.022968255 | O19: =IF(SUMPRODUCT('Historical Data'!$BA$2:$BA$1068*'Historical Data'!$AP$2:$AP$1068*'Historical Data'!$AM$2:$AM$1068)=0,"",SUMPRODUCT('Historical Data'!$BA$2:$BA$1068*'Historical Data'!$AP$2:$AP$1068*'Historical Data'!$AM$2:$AM$1068*'Historical Data'!$AL$2:$AL$1068)/SUMPRODUCT('Historical Data'!$BA$2:$BA$1068*'Historical Data'!$AP$2:$AP$1068*'Historical Data'!$AM$2:$AM$1068)) -> 0.33980496 | P19: =IF(E19=0,"",SUMPRODUCT('Historical Data'!$BA$2:$BA$1068*'Historical Data'!$AP$2:$AP$1068*'Historical Data'!$AA$2:$AA$1068)/E19) -> 77.540864 | Q19: =IF(E19=0,"",SUMPRODUCT('Historical Data'!$BA$2:$BA$1068*'Historical Data'!$AP$2:$AP$1068*'Historical Data'!$M$2:$M$1068)/E19) -> 1.4700913 | R19: =IF(E19=0,"",G19/E19) -> 18729.713 | S19: =IF(E19=0,"",SUMPRODUCT('Historical Data'!$BA$2:$BA$1068*'Historical Data'!$AP$2:$AP$1068*'Historical Data'!$AN$2:$AN$1068)/E19) -> 86.91791 | T19: =IF(E19=0,"",SUMPRODUCT('Historical Data'!$BA$2:$BA$1068*'Historical Data'!$AP$2:$AP$1068*'Historical Data'!$AO$2:$AO$1068)/E19) -> 0 | U19: =IF(AND(E19>=Controls!$B$40,G19>=Controls!$B$41,IF(I19="",1,I19)<=Controls!$B$43),"Yes","No") -> Yes | V19: =IF(E19+Controls!$B$42=0,0,E19/(E19+Controls!$B$42)) -> 0.94699647 | W19: =IF(L19="",$C$10,V19*L19+(1-V19)*$C$10) -> 0.23334009 | X19: =IF(OR($C$10="",$C$10=0),"",W19/$C$10) -> 1.1079934 | Y19: =IF(AND(E19>=Controls!$B$40,G19>=Controls!$B$41),1,0) -> 1 | Z19: =IF(L19="",0,ABS(W19-$C$10)) -> 0.022743096 | AA19: =IF(L19="","No","Yes") -> Yes
A20: 7 | B20: T7: seasoned book (baseline) | C20: all seasoned deals in window | D20: =SUMPRODUCT('Historical Data'!$BB$2:$BB$1068*'Historical Data'!$AD$2:$AD$1068) -> 1067 | E20: =SUMPRODUCT('Historical Data'!$BB$2:$BB$1068*'Historical Data'!$AP$2:$AP$1068) -> 637 | F20: =IF(D20=0,"",E20/D20) -> 0.59700094 | G20: =SUMPRODUCT('Historical Data'!$BB$2:$BB$1068*'Historical Data'!$AP$2:$AP$1068*'Historical Data'!$N$2:$N$1068) -> 12563126 | H20: =SUMPRODUCT('Historical Data'!$BB$2:$BB$1068*'Historical Data'!$AP$2:$AP$1068*'Historical Data'!$AH$2:$AH$1068) -> 44 | I20: =IF(E20=0,"",H20/E20) -> 0.069073783 | J20: =SUMPRODUCT('Historical Data'!$BB$2:$BB$1068*'Historical Data'!$AP$2:$AP$1068*'Historical Data'!$AE$2:$AE$1068) -> 270 | K20: =IF(E20=0,"",J20/E20) -> 0.42386185 | L20: =IF(OR(E20<Controls!$B$47,G20=0),"",SUMPRODUCT('Historical Data'!$BB$2:$BB$1068*'Historical Data'!$AP$2:$AP$1068*'Historical Data'!$AK$2:$AK$1068)/G20) -> 0.21059699 | M20: =IF(OR(E20<Controls!$B$47,SUMPRODUCT('Historical Data'!$BB$2:$BB$1068*'Historical Data'!$AP$2:$AP$1068*'Historical Data'!$AE$2:$AE$1068*'Historical Data'!$N$2:$N$1068)=0),"",SUMPRODUCT('Historical Data'!$BB$2:$BB$1068*'Historical Data'!$AP$2:$AP$1068*'Historical Data'!$AE$2:$AE$1068*'Historical Data'!$Q$2:$Q$1068)/SUMPRODUCT('Historical Data'!$BB$2:$BB$1068*'Historical Data'!$AP$2:$AP$1068*'Historical Data'!$AE$2:$AE$1068*'Historical Data'!$N$2:$N$1068)) -> 0.47401722 | N20: =IF(OR(E20<Controls!$B$47,G20=0),"",SUMPRODUCT('Historical Data'!$BB$2:$BB$1068*'Historical Data'!$AP$2:$AP$1068*'Historical Data'!$AJ$2:$AJ$1068)/G20) -> 0.022259973 | O20: =IF(SUMPRODUCT('Historical Data'!$BB$2:$BB$1068*'Historical Data'!$AP$2:$AP$1068*'Historical Data'!$AM$2:$AM$1068)=0,"",SUMPRODUCT('Historical Data'!$BB$2:$BB$1068*'Historical Data'!$AP$2:$AP$1068*'Historical Data'!$AM$2:$AM$1068*'Historical Data'!$AL$2:$AL$1068)/SUMPRODUCT('Historical Data'!$BB$2:$BB$1068*'Historical Data'!$AP$2:$AP$1068*'Historical Data'!$AM$2:$AM$1068)) -> 0.36868739 | P20: =IF(E20=0,"",SUMPRODUCT('Historical Data'!$BB$2:$BB$1068*'Historical Data'!$AP$2:$AP$1068*'Historical Data'!$AA$2:$AA$1068)/E20) -> 77.431593 | Q20: =IF(E20=0,"",SUMPRODUCT('Historical Data'!$BB$2:$BB$1068*'Historical Data'!$AP$2:$AP$1068*'Historical Data'!$M$2:$M$1068)/E20) -> 1.4713822 | R20: =IF(E20=0,"",G20/E20) -> 19722.333 | S20: =IF(E20=0,"",SUMPRODUCT('Historical Data'!$BB$2:$BB$1068*'Historical Data'!$AP$2:$AP$1068*'Historical Data'!$AN$2:$AN$1068)/E20) -> 88.125589 | T20: =IF(E20=0,"",SUMPRODUCT('Historical Data'!$BB$2:$BB$1068*'Historical Data'!$AP$2:$AP$1068*'Historical Data'!$AO$2:$AO$1068)/E20) -> 0.15855573 | U20: =IF(AND(E20>=Controls!$B$40,G20>=Controls!$B$41,IF(I20="",1,I20)<=Controls!$B$43),"Yes","No") -> Yes | V20: =IF(E20+Controls!$B$42=0,0,E20/(E20+Controls!$B$42)) -> 0.95502249 | W20: =IF(L20="",$C$10,V20*L20+(1-V20)*$C$10) -> 0.21059699 | X20: =IF(OR($C$10="",$C$10=0),"",W20/$C$10) -> 1 | Y20: =IF(AND(E20>=Controls!$B$40,G20>=Controls!$B$41),1,0) -> 1 | Z20: =IF(L20="",0,ABS(W20-$C$10)) -> 0 | AA20: =IF(L20="","No","Yes") -> Yes
B21: SINGLE-DIMENSION EVIDENCE (informational + largest-impact test)
A22: S1 | B22: Position only | C22: Position only | D22: =SUMPRODUCT('Historical Data'!$AQ$2:$AQ$1068*'Historical Data'!$AD$2:$AD$1068) -> 213 | E22: =SUMPRODUCT('Historical Data'!$AQ$2:$AQ$1068*'Historical Data'!$AP$2:$AP$1068) -> 145 | F22: =IF(D22=0,"",E22/D22) -> 0.68075117 | G22: =SUMPRODUCT('Historical Data'!$AQ$2:$AQ$1068*'Historical Data'!$AP$2:$AP$1068*'Historical Data'!$N$2:$N$1068) -> 2573500 | H22: =SUMPRODUCT('Historical Data'!$AQ$2:$AQ$1068*'Historical Data'!$AP$2:$AP$1068*'Historical Data'!$AH$2:$AH$1068) -> 8 | I22: =IF(E22=0,"",H22/E22) -> 0.055172414 | J22: =SUMPRODUCT('Historical Data'!$AQ$2:$AQ$1068*'Historical Data'!$AP$2:$AP$1068*'Historical Data'!$AE$2:$AE$1068) -> 60 | K22: =IF(E22=0,"",J22/E22) -> 0.4137931 | L22: =IF(OR(E22<Controls!$B$47,G22=0),"",SUMPRODUCT('Historical Data'!$AQ$2:$AQ$1068*'Historical Data'!$AP$2:$AP$1068*'Historical Data'!$AK$2:$AK$1068)/G22) -> 0.23577655 | M22: =IF(OR(E22<Controls!$B$47,SUMPRODUCT('Historical Data'!$AQ$2:$AQ$1068*'Historical Data'!$AP$2:$AP$1068*'Historical Data'!$AE$2:$AE$1068*'Historical Data'!$N$2:$N$1068)=0),"",SUMPRODUCT('Historical Data'!$AQ$2:$AQ$1068*'Historical Data'!$AP$2:$AP$1068*'Historical Data'!$AE$2:$AE$1068*'Historical Data'!$Q$2:$Q$1068)/SUMPRODUCT('Historical Data'!$AQ$2:$AQ$1068*'Historical Data'!$AP$2:$AP$1068*'Historical Data'!$AE$2:$AE$1068*'Historical Data'!$N$2:$N$1068)) -> 0.38785392 | N22: =IF(OR(E22<Controls!$B$47,G22=0),"",SUMPRODUCT('Historical Data'!$AQ$2:$AQ$1068*'Historical Data'!$AP$2:$AP$1068*'Historical Data'!$AJ$2:$AJ$1068)/G22) -> 0.018162048 | O22: =IF(SUMPRODUCT('Historical Data'!$AQ$2:$AQ$1068*'Historical Data'!$AP$2:$AP$1068*'Historical Data'!$AM$2:$AM$1068)=0,"",SUMPRODUCT('Historical Data'!$AQ$2:$AQ$1068*'Historical Data'!$AP$2:$AP$1068*'Historical Data'!$AM$2:$AM$1068*'Historical Data'!$AL$2:$AL$1068)/SUMPRODUCT('Historical Data'!$AQ$2:$AQ$1068*'Historical Data'!$AP$2:$AP$1068*'Historical Data'!$AM$2:$AM$1068)) -> 0.40111711 | P22: =IF(E22=0,"",SUMPRODUCT('Historical Data'!$AQ$2:$AQ$1068*'Historical Data'!$AP$2:$AP$1068*'Historical Data'!$AA$2:$AA$1068)/E22) -> 80.677747 | Q22: =IF(E22=0,"",SUMPRODUCT('Historical Data'!$AQ$2:$AQ$1068*'Historical Data'!$AP$2:$AP$1068*'Historical Data'!$M$2:$M$1068)/E22) -> 1.4663506 | R22: =IF(E22=0,"",G22/E22) -> 17748.276 | S22: =IF(E22=0,"",SUMPRODUCT('Historical Data'!$AQ$2:$AQ$1068*'Historical Data'!$AP$2:$AP$1068*'Historical Data'!$AN$2:$AN$1068)/E22) -> 87.558621 | T22: =IF(E22=0,"",SUMPRODUCT('Historical Data'!$AQ$2:$AQ$1068*'Historical Data'!$AP$2:$AP$1068*'Historical Data'!$AO$2:$AO$1068)/E22) -> 0.096551724 | U22: =IF(AND(E22>=Controls!$B$40,G22>=Controls!$B$41,IF(I22="",1,I22)<=Controls!$B$43),"Yes","No") -> Yes | V22: =IF(E22+Controls!$B$42=0,0,E22/(E22+Controls!$B$42)) -> 0.82857143 | W22: =IF(L22="",$C$10,V22*L22+(1-V22)*$C$10) -> 0.23146005 | X22: =IF(OR($C$10="",$C$10=0),"",W22/$C$10) -> 1.0990663 | Y22: =IF(AND(E22>=Controls!$B$40,G22>=Controls!$B$41),1,0) -> 1 | Z22: =IF(L22="",0,ABS(W22-$C$10)) -> 0.02086306 | AA22: =IF(L22="","No","Yes") -> Yes
A23: S2 | B23: New/renewal only | C23: New/renewal only | D23: =SUMPRODUCT('Historical Data'!$AR$2:$AR$1068*'Historical Data'!$AD$2:$AD$1068) -> 852 | E23: =SUMPRODUCT('Historical Data'!$AR$2:$AR$1068*'Historical Data'!$AP$2:$AP$1068) -> 536 | F23: =IF(D23=0,"",E23/D23) -> 0.62910798 | G23: =SUMPRODUCT('Historical Data'!$AR$2:$AR$1068*'Historical Data'!$AP$2:$AP$1068*'Historical Data'!$N$2:$N$1068) -> 10039126 | H23: =SUMPRODUCT('Historical Data'!$AR$2:$AR$1068*'Historical Data'!$AP$2:$AP$1068*'Historical Data'!$AH$2:$AH$1068) -> 34 | I23: =IF(E23=0,"",H23/E23) -> 0.063432836 | J23: =SUMPRODUCT('Historical Data'!$AR$2:$AR$1068*'Historical Data'!$AP$2:$AP$1068*'Historical Data'!$AE$2:$AE$1068) -> 243 | K23: =IF(E23=0,"",J23/E23) -> 0.45335821 | L23: =IF(OR(E23<Controls!$B$47,G23=0),"",SUMPRODUCT('Historical Data'!$AR$2:$AR$1068*'Historical Data'!$AP$2:$AP$1068*'Historical Data'!$AK$2:$AK$1068)/G23) -> 0.23461302 | M23: =IF(OR(E23<Controls!$B$47,SUMPRODUCT('Historical Data'!$AR$2:$AR$1068*'Historical Data'!$AP$2:$AP$1068*'Historical Data'!$AE$2:$AE$1068*'Historical Data'!$N$2:$N$1068)=0),"",SUMPRODUCT('Historical Data'!$AR$2:$AR$1068*'Historical Data'!$AP$2:$AP$1068*'Historical Data'!$AE$2:$AE$1068*'Historical Data'!$Q$2:$Q$1068)/SUMPRODUCT('Historical Data'!$AR$2:$AR$1068*'Historical Data'!$AP$2:$AP$1068*'Historical Data'!$AE$2:$AE$1068*'Historical Data'!$N$2:$N$1068)) -> 0.46584113 | N23: =IF(OR(E23<Controls!$B$47,G23=0),"",SUMPRODUCT('Historical Data'!$AR$2:$AR$1068*'Historical Data'!$AP$2:$AP$1068*'Historical Data'!$AJ$2:$AJ$1068)/G23) -> -0.022968255 | O23: =IF(SUMPRODUCT('Historical Data'!$AR$2:$AR$1068*'Historical Data'!$AP$2:$AP$1068*'Historical Data'!$AM$2:$AM$1068)=0,"",SUMPRODUCT('Historical Data'!$AR$2:$AR$1068*'Historical Data'!$AP$2:$AP$1068*'Historical Data'!$AM$2:$AM$1068*'Historical Data'!$AL$2:$AL$1068)/SUMPRODUCT('Historical Data'!$AR$2:$AR$1068*'Historical Data'!$AP$2:$AP$1068*'Historical Data'!$AM$2:$AM$1068)) -> 0.33980496 | P23: =IF(E23=0,"",SUMPRODUCT('Historical Data'!$AR$2:$AR$1068*'Historical Data'!$AP$2:$AP$1068*'Historical Data'!$AA$2:$AA$1068)/E23) -> 77.540864 | Q23: =IF(E23=0,"",SUMPRODUCT('Historical Data'!$AR$2:$AR$1068*'Historical Data'!$AP$2:$AP$1068*'Historical Data'!$M$2:$M$1068)/E23) -> 1.4700913 | R23: =IF(E23=0,"",G23/E23) -> 18729.713 | S23: =IF(E23=0,"",SUMPRODUCT('Historical Data'!$AR$2:$AR$1068*'Historical Data'!$AP$2:$AP$1068*'Historical Data'!$AN$2:$AN$1068)/E23) -> 86.91791 | T23: =IF(E23=0,"",SUMPRODUCT('Historical Data'!$AR$2:$AR$1068*'Historical Data'!$AP$2:$AP$1068*'Historical Data'!$AO$2:$AO$1068)/E23) -> 0 | U23: =IF(AND(E23>=Controls!$B$40,G23>=Controls!$B$41,IF(I23="",1,I23)<=Controls!$B$43),"Yes","No") -> Yes | V23: =IF(E23+Controls!$B$42=0,0,E23/(E23+Controls!$B$42)) -> 0.94699647 | W23: =IF(L23="",$C$10,V23*L23+(1-V23)*$C$10) -> 0.23334009 | X23: =IF(OR($C$10="",$C$10=0),"",W23/$C$10) -> 1.1079934 | Y23: =IF(AND(E23>=Controls!$B$40,G23>=Controls!$B$41),1,0) -> 1 | Z23: =IF(L23="",0,ABS(W23-$C$10)) -> 0.022743096 | AA23: =IF(L23="","No","Yes") -> Yes
A24: S3 | B24: Industry only | C24: Industry only | D24: =SUMPRODUCT('Historical Data'!$AS$2:$AS$1068*'Historical Data'!$AD$2:$AD$1068) -> 121 | E24: =SUMPRODUCT('Historical Data'!$AS$2:$AS$1068*'Historical Data'!$AP$2:$AP$1068) -> 82 | F24: =IF(D24=0,"",E24/D24) -> 0.67768595 | G24: =SUMPRODUCT('Historical Data'!$AS$2:$AS$1068*'Historical Data'!$AP$2:$AP$1068*'Historical Data'!$N$2:$N$1068) -> 1390000 | H24: =SUMPRODUCT('Historical Data'!$AS$2:$AS$1068*'Historical Data'!$AP$2:$AP$1068*'Historical Data'!$AH$2:$AH$1068) -> 6 | I24: =IF(E24=0,"",H24/E24) -> 0.073170732 | J24: =SUMPRODUCT('Historical Data'!$AS$2:$AS$1068*'Historical Data'!$AP$2:$AP$1068*'Historical Data'!$AE$2:$AE$1068) -> 45 | K24: =IF(E24=0,"",J24/E24) -> 0.54878049 | L24: =IF(OR(E24<Controls!$B$47,G24=0),"",SUMPRODUCT('Historical Data'!$AS$2:$AS$1068*'Historical Data'!$AP$2:$AP$1068*'Historical Data'!$AK$2:$AK$1068)/G24) -> 0.32495211 | M24: =IF(OR(E24<Controls!$B$47,SUMPRODUCT('Historical Data'!$AS$2:$AS$1068*'Historical Data'!$AP$2:$AP$1068*'Historical Data'!$AE$2:$AE$1068*'Historical Data'!$N$2:$N$1068)=0),"",SUMPRODUCT('Historical Data'!$AS$2:$AS$1068*'Historical Data'!$AP$2:$AP$1068*'Historical Data'!$AE$2:$AE$1068*'Historical Data'!$Q$2:$Q$1068)/SUMPRODUCT('Historical Data'!$AS$2:$AS$1068*'Historical Data'!$AP$2:$AP$1068*'Historical Data'!$AE$2:$AE$1068*'Historical Data'!$N$2:$N$1068)) -> 0.42236899 | N24: =IF(OR(E24<Controls!$B$47,G24=0),"",SUMPRODUCT('Historical Data'!$AS$2:$AS$1068*'Historical Data'!$AP$2:$AP$1068*'Historical Data'!$AJ$2:$AJ$1068)/G24) -> -0.14483546 | O24: =IF(SUMPRODUCT('Historical Data'!$AS$2:$AS$1068*'Historical Data'!$AP$2:$AP$1068*'Historical Data'!$AM$2:$AM$1068)=0,"",SUMPRODUCT('Historical Data'!$AS$2:$AS$1068*'Historical Data'!$AP$2:$AP$1068*'Historical Data'!$AM$2:$AM$1068*'Historical Data'!$AL$2:$AL$1068)/SUMPRODUCT('Historical Data'!$AS$2:$AS$1068*'Historical Data'!$AP$2:$AP$1068*'Historical Data'!$AM$2:$AM$1068)) -> 0.30229906 | P24: =IF(E24=0,"",SUMPRODUCT('Historical Data'!$AS$2:$AS$1068*'Historical Data'!$AP$2:$AP$1068*'Historical Data'!$AA$2:$AA$1068)/E24) -> 74.604584 | Q24: =IF(E24=0,"",SUMPRODUCT('Historical Data'!$AS$2:$AS$1068*'Historical Data'!$AP$2:$AP$1068*'Historical Data'!$M$2:$M$1068)/E24) -> 1.4783823 | R24: =IF(E24=0,"",G24/E24) -> 16951.22 | S24: =IF(E24=0,"",SUMPRODUCT('Historical Data'!$AS$2:$AS$1068*'Historical Data'!$AP$2:$AP$1068*'Historical Data'!$AN$2:$AN$1068)/E24) -> 86.182927 | T24: =IF(E24=0,"",SUMPRODUCT('Historical Data'!$AS$2:$AS$1068*'Historical Data'!$AP$2:$AP$1068*'Historical Data'!$AO$2:$AO$1068)/E24) -> 0.14634146 | U24: =IF(AND(E24>=Controls!$B$40,G24>=Controls!$B$41,IF(I24="",1,I24)<=Controls!$B$43),"Yes","No") -> Yes | V24: =IF(E24+Controls!$B$42=0,0,E24/(E24+Controls!$B$42)) -> 0.73214286 | W24: =IF(L24="",$C$10,V24*L24+(1-V24)*$C$10) -> 0.29432127 | X24: =IF(OR($C$10="",$C$10=0),"",W24/$C$10) -> 1.3975569 | Y24: =IF(AND(E24>=Controls!$B$40,G24>=Controls!$B$41),1,0) -> 1 | Z24: =IF(L24="",0,ABS(W24-$C$10)) -> 0.08372428 | AA24: =IF(L24="","No","Yes") -> Yes
A25: S4 | B25: ISO only | C25: ISO only | D25: =SUMPRODUCT('Historical Data'!$AT$2:$AT$1068*'Historical Data'!$AD$2:$AD$1068) -> 175 | E25: =SUMPRODUCT('Historical Data'!$AT$2:$AT$1068*'Historical Data'!$AP$2:$AP$1068) -> 109 | F25: =IF(D25=0,"",E25/D25) -> 0.62285714 | G25: =SUMPRODUCT('Historical Data'!$AT$2:$AT$1068*'Historical Data'!$AP$2:$AP$1068*'Historical Data'!$N$2:$N$1068) -> 2007500 | H25: =SUMPRODUCT('Historical Data'!$AT$2:$AT$1068*'Historical Data'!$AP$2:$AP$1068*'Historical Data'!$AH$2:$AH$1068) -> 11 | I25: =IF(E25=0,"",H25/E25) -> 0.10091743 | J25: =SUMPRODUCT('Historical Data'!$AT$2:$AT$1068*'Historical Data'!$AP$2:$AP$1068*'Historical Data'!$AE$2:$AE$1068) -> 54 | K25: =IF(E25=0,"",J25/E25) -> 0.49541284 | L25: =IF(OR(E25<Controls!$B$47,G25=0),"",SUMPRODUCT('Historical Data'!$AT$2:$AT$1068*'Historical Data'!$AP$2:$AP$1068*'Historical Data'!$AK$2:$AK$1068)/G25) -> 0.26542797 | M25: =IF(OR(E25<Controls!$B$47,SUMPRODUCT('Historical Data'!$AT$2:$AT$1068*'Historical Data'!$AP$2:$AP$1068*'Historical Data'!$AE$2:$AE$1068*'Historical Data'!$N$2:$N$1068)=0),"",SUMPRODUCT('Historical Data'!$AT$2:$AT$1068*'Historical Data'!$AP$2:$AP$1068*'Historical Data'!$AE$2:$AE$1068*'Historical Data'!$Q$2:$Q$1068)/SUMPRODUCT('Historical Data'!$AT$2:$AT$1068*'Historical Data'!$AP$2:$AP$1068*'Historical Data'!$AE$2:$AE$1068*'Historical Data'!$N$2:$N$1068)) -> 0.46346056 | N25: =IF(OR(E25<Controls!$B$47,G25=0),"",SUMPRODUCT('Historical Data'!$AT$2:$AT$1068*'Historical Data'!$AP$2:$AP$1068*'Historical Data'!$AJ$2:$AJ$1068)/G25) -> -0.041875666 | O25: =IF(SUMPRODUCT('Historical Data'!$AT$2:$AT$1068*'Historical Data'!$AP$2:$AP$1068*'Historical Data'!$AM$2:$AM$1068)=0,"",SUMPRODUCT('Historical Data'!$AT$2:$AT$1068*'Historical Data'!$AP$2:$AP$1068*'Historical Data'!$AM$2:$AM$1068*'Historical Data'!$AL$2:$AL$1068)/SUMPRODUCT('Historical Data'!$AT$2:$AT$1068*'Historical Data'!$AP$2:$AP$1068*'Historical Data'!$AM$2:$AM$1068)) -> 0.43284826 | P25: =IF(E25=0,"",SUMPRODUCT('Historical Data'!$AT$2:$AT$1068*'Historical Data'!$AP$2:$AP$1068*'Historical Data'!$AA$2:$AA$1068)/E25) -> 71.821487 | Q25: =IF(E25=0,"",SUMPRODUCT('Historical Data'!$AT$2:$AT$1068*'Historical Data'!$AP$2:$AP$1068*'Historical Data'!$M$2:$M$1068)/E25) -> 1.4891223 | R25: =IF(E25=0,"",G25/E25) -> 18417.431 | S25: =IF(E25=0,"",SUMPRODUCT('Historical Data'!$AT$2:$AT$1068*'Historical Data'!$AP$2:$AP$1068*'Historical Data'!$AN$2:$AN$1068)/E25) -> 80.174312 | T25: =IF(E25=0,"",SUMPRODUCT('Historical Data'!$AT$2:$AT$1068*'Historical Data'!$AP$2:$AP$1068*'Historical Data'!$AO$2:$AO$1068)/E25) -> 0.12844037 | U25: =IF(AND(E25>=Controls!$B$40,G25>=Controls!$B$41,IF(I25="",1,I25)<=Controls!$B$43),"Yes","No") -> Yes | V25: =IF(E25+Controls!$B$42=0,0,E25/(E25+Controls!$B$42)) -> 0.78417266 | W25: =IF(L25="",$C$10,V25*L25+(1-V25)*$C$10) -> 0.25359395 | X25: =IF(OR($C$10="",$C$10=0),"",W25/$C$10) -> 1.204167 | Y25: =IF(AND(E25>=Controls!$B$40,G25>=Controls!$B$41),1,0) -> 1 | Z25: =IF(L25="",0,ABS(W25-$C$10)) -> 0.042996953 | AA25: =IF(L25="","No","Yes") -> Yes
A26: S5 | B26: State only (INFORMATIONAL - never in hierarchy) | C26: State only | D26: =SUMPRODUCT('Historical Data'!$AU$2:$AU$1068*'Historical Data'!$AD$2:$AD$1068) -> 197 | E26: =SUMPRODUCT('Historical Data'!$AU$2:$AU$1068*'Historical Data'!$AP$2:$AP$1068) -> 118 | F26: =IF(D26=0,"",E26/D26) -> 0.59898477 | G26: =SUMPRODUCT('Historical Data'!$AU$2:$AU$1068*'Historical Data'!$AP$2:$AP$1068*'Historical Data'!$N$2:$N$1068) -> 2456000 | H26: =SUMPRODUCT('Historical Data'!$AU$2:$AU$1068*'Historical Data'!$AP$2:$AP$1068*'Historical Data'!$AH$2:$AH$1068) -> 10 | I26: =IF(E26=0,"",H26/E26) -> 0.084745763 | J26: =SUMPRODUCT('Historical Data'!$AU$2:$AU$1068*'Historical Data'!$AP$2:$AP$1068*'Historical Data'!$AE$2:$AE$1068) -> 36 | K26: =IF(E26=0,"",J26/E26) -> 0.30508475 | L26: =IF(OR(E26<Controls!$B$47,G26=0),"",SUMPRODUCT('Historical Data'!$AU$2:$AU$1068*'Historical Data'!$AP$2:$AP$1068*'Historical Data'!$AK$2:$AK$1068)/G26) -> 0.13001329 | M26: =IF(OR(E26<Controls!$B$47,SUMPRODUCT('Historical Data'!$AU$2:$AU$1068*'Historical Data'!$AP$2:$AP$1068*'Historical Data'!$AE$2:$AE$1068*'Historical Data'!$N$2:$N$1068)=0),"",SUMPRODUCT('Historical Data'!$AU$2:$AU$1068*'Historical Data'!$AP$2:$AP$1068*'Historical Data'!$AE$2:$AE$1068*'Historical Data'!$Q$2:$Q$1068)/SUMPRODUCT('Historical Data'!$AU$2:$AU$1068*'Historical Data'!$AP$2:$AP$1068*'Historical Data'!$AE$2:$AE$1068*'Historical Data'!$N$2:$N$1068)) -> 0.60161475 | N26: =IF(OR(E26<Controls!$B$47,G26=0),"",SUMPRODUCT('Historical Data'!$AU$2:$AU$1068*'Historical Data'!$AP$2:$AP$1068*'Historical Data'!$AJ$2:$AJ$1068)/G26) -> 0.13598154 | O26: =IF(SUMPRODUCT('Historical Data'!$AU$2:$AU$1068*'Historical Data'!$AP$2:$AP$1068*'Historical Data'!$AM$2:$AM$1068)=0,"",SUMPRODUCT('Historical Data'!$AU$2:$AU$1068*'Historical Data'!$AP$2:$AP$1068*'Historical Data'!$AM$2:$AM$1068*'Historical Data'!$AL$2:$AL$1068)/SUMPRODUCT('Historical Data'!$AU$2:$AU$1068*'Historical Data'!$AP$2:$AP$1068*'Historical Data'!$AM$2:$AM$1068)) -> 0.3557282 | P26: =IF(E26=0,"",SUMPRODUCT('Historical Data'!$AU$2:$AU$1068*'Historical Data'!$AP$2:$AP$1068*'Historical Data'!$AA$2:$AA$1068)/E26) -> 85.548265 | Q26: =IF(E26=0,"",SUMPRODUCT('Historical Data'!$AU$2:$AU$1068*'Historical Data'!$AP$2:$AP$1068*'Historical Data'!$M$2:$M$1068)/E26) -> 1.4613144 | R26: =IF(E26=0,"",G26/E26) -> 20813.559 | S26: =IF(E26=0,"",SUMPRODUCT('Historical Data'!$AU$2:$AU$1068*'Historical Data'!$AP$2:$AP$1068*'Historical Data'!$AN$2:$AN$1068)/E26) -> 87.991525 | T26: =IF(E26=0,"",SUMPRODUCT('Historical Data'!$AU$2:$AU$1068*'Historical Data'!$AP$2:$AP$1068*'Historical Data'!$AO$2:$AO$1068)/E26) -> 0.1440678 | U26: =IF(AND(E26>=Controls!$B$40,G26>=Controls!$B$41,IF(I26="",1,I26)<=Controls!$B$43),"Yes","No") -> Yes | V26: =IF(E26+Controls!$B$42=0,0,E26/(E26+Controls!$B$42)) -> 0.7972973 | W26: =IF(L26="",$C$10,V26*L26+(1-V26)*$C$10) -> 0.14634782 | X26: =IF(OR($C$10="",$C$10=0),"",W26/$C$10) -> 0.69491885 | Y26: =IF(AND(E26>=Controls!$B$40,G26>=Controls!$B$41),1,0) -> 1 | Z26: =IF(L26="",0,ABS(W26-$C$10)) -> 0.064249173 | AA26: =IF(L26="","No","Yes") -> Yes
A28: RESULT
B29: Primary tier (first tier meeting the minimums) | C29: =IFERROR(MATCH(1,$Y$14:$Y$20,0),7) -> 1
B30: Primary cohort | C30: =INDEX($B$14:$B$20,$C$29) -> T1: new/renewal + industry + position
B31: Seasoned deals in primary cohort / all matches | C31: =TEXT(INDEX($E$14:$E$20,$C$29),"#,##0")&" / "&TEXT(INDEX($D$14:$D$20,$C$29),"#,##0") -> 23 / 27
B32: % of comparable deals seasoned | C32: =INDEX($F$14:$F$20,$C$29) -> 0.85185185
B33: Cohort principal lost rate (seasoned) | C33: =INDEX($L$14:$L$20,$C$29) -> 0.34000684
B34: Cohort open share | C34: =INDEX($I$14:$I$20,$C$29) -> 0.043478261
B35: Cohort return on funded capital | C35: =INDEX($N$14:$N$20,$C$29) -> -0.11893978
B36: Cohort collected on defaults | C36: =INDEX($M$14:$M$20,$C$29) -> 0.28907662
B37: Credibility Z | C37: =INDEX($V$14:$V$20,$C$29) -> 0.43396226
B38: Blended lost rate | C38: =INDEX($W$14:$W$20,$C$29) -> 0.26675598
B39: Relative index (blended / book) | C39: =INDEX($X$14:$X$20,$C$29) -> 1.2666657
B40: Modifier level from index (1 strong positive .. 6 severe) | C40: =IF(C39="",3,COUNTIF(Controls!$A$54:$A$59,"<"&C39)+1) -> 4
B41: Confidence | C41: =IF(OR($C$29=7,C37<Controls!$B$45),"Low",IF(AND(C37>=Controls!$B$44,IF(C34="",1,C34)<=Controls!$B$43),"High","Medium")) -> Medium
B42: Modifier level after confidence cap | C42: =IF(C41="Low",MIN(MAX(C40,3-Controls!$B$46),3+Controls!$B$46),C40) -> 4
B43: Modifier level name | C43: =INDEX(Controls!$B$54:$B$59,C42) -> Mild negative
B44: Largest-impact variable (position / NR / industry / ISO) | C44: =IF(MAX($Z$22:$Z$25)=0,"none - no single-dimension cohort has a rate",INDEX($B$22:$B$25,MATCH(MAX($Z$22:$Z$25),$Z$22:$Z$25,0))) -> Industry only
B45: its blended lost rate vs book | C45: =IF(MAX($Z$22:$Z$25)=0,"",TEXT(INDEX($W$22:$W$25,MATCH(MAX($Z$22:$Z$25),$Z$22:$Z$25,0)),"0.0%")&" vs "&TEXT($C$10,"0.0%")&" book ("&TEXT(INDEX($E$22:$E$25,MATCH(MAX($Z$22:$Z$25),$Z$22:$Z$25,0)),"0")&" seasoned deals)") -> 29.4% vs 21.1% book (82 seasoned deals)
B46: ISO evidence | C46: =IF($C$8="","ISO not entered",IF($E$25=0,"ISO "&$C$8&" has no seasoned deals in the book",IF($L$25="","ISO "&$C$8&": "&$E$25&" seasoned deals - too few to rate","ISO "&$C$8&": "&$E$25&" seasoned deals, lost "&TEXT($L$25,"0.0%")&" vs "&TEXT($C$10,"0.0%")&" book, Z "&TEXT($V$25,"0.00")&" -> "&IF($X$25<=Controls!$A$55,"stronger than book",IF($X$25<=Controls!$A$56,"neutral","weaker than book"))))) -> ISO United Secured Capital 8: 109 seasoned deals, lost 26.5% vs 21.1% book, Z 0.78 -> weaker than book
B47: Industry evidence | C47: =IF($C$7="","Industry not entered",IF($E$24=0,"Industry has no seasoned deals in the book",IF($L$24="","Industry "&$C$7&": "&$E$24&" seasoned deals - too few to rate","Industry "&$C$7&": "&$E$24&" seasoned deals, lost "&TEXT($L$24,"0.0%")&" vs "&TEXT($C$10,"0.0%")&" book, Z "&TEXT($V$24,"0.00")&" -> "&IF($X$24<=Controls!$A$55,"stronger than book",IF($X$24<=Controls!$A$56,"neutral","weaker than book"))))) -> Industry General Building Contractors: 82 seasoned deals, lost 32.5% vs 21.1% book, Z 0.73 -> weaker than book
B48: State evidence (informational only) | C48: =IF($C$9="","State not entered",IF($E$26=0,"State "&$C$9&" has no seasoned deals",IF($L$26="","State "&$C$9&": "&$E$26&" seasoned deals - too few to rate; not used","State "&$C$9&": "&$E$26&" seasoned deals, lost "&TEXT($L$26,"0.0%")&" vs "&TEXT($C$10,"0.0%")&" book - informational only, not used in the offer"))) -> State TX: 118 seasoned deals, lost 13.0% vs 21.1% book - informational only, not used in the offer
B49: Position evidence | C49: =IF($C$6="","Position not entered",IF($L$22="","Position "&$C$6&": "&$E$22&" seasoned deals - too few to rate","Position "&$C$6&": "&$E$22&" seasoned deals, lost "&TEXT($L$22,"0.0%")&" vs "&TEXT($C$10,"0.0%")&" book")) -> Position 2: 145 seasoned deals, lost 23.6% vs 21.1% book
B50: Conflicting signals? (ISO and industry on opposite sides of neutral) | C50: =IF(OR($L$24="",$L$25=""),"No",IF(OR(AND($X$24<Controls!$A$55,$X$25>Controls!$A$56),AND($X$25<Controls!$A$55,$X$24>Controls!$A$56)),"YES - review both cohorts","No")) -> No
B51: Warnings | C51: =IF($C$29=7,"No cohort met the minimums - book baseline used; ","")&IF(INDEX($U$14:$U$20,$C$29)="No","Primary cohort not seasoned-enough (count, dollars or open share); ","")&IF(C41="Low","Low confidence - modifier capped; ","")&IF(C33<Controls!$B$43,"","Cohort open share high; ") -> Cohort open share high;

Sheet Comparable Deals
A1: COMPARABLE DEALS - every house-book deal in the primary cohort (seasoned and unseasoned), inspect by Contract ID
A2: ="Primary cohort: "&'Historical Score'!$C$30&" | "&'Historical Score'!$C$31&" seasoned / all | only the first 400 are listed" -> Primary cohort: T1: new/renewal + industry + position | 23 / 27 seasoned / all | only the first 400 are listed
A3: Similarity tier 1 = closest (matches NR + industry + position). Deals shown with Seasoned = 0 are counted but excluded from every rate.
A4: # | B4: Contract ID | C4: DBA | D4: Status | E4: Funded | F4: Position | G4: Industry | H4: ISO | I4: State | J4: New/renewal | K4: Factor | L4: Advance | M4: Collected | N4: % paid | O4: Net cash | P4: Principal lost | Q4: Term (bd) | R4: Age (bd) | S4: Days on book | T4: Seasoned | U4: Default | V4: Open | W4: Similarity tier | X4: Why included
A5: 1 | B5: =IFERROR(INDEX('Historical Data'!$A$2:$A$1068,MATCH($A5,'Historical Data'!$BE$2:$BE$1068,0)),"") -> 5674154422 | C5: =IFERROR(INDEX('Historical Data'!$B$2:$B$1068,MATCH($A5,'Historical Data'!$BE$2:$BE$1068,0)),"") -> BUSHCO CONTRACTING | D5: =IFERROR(INDEX('Historical Data'!$D$2:$D$1068,MATCH($A5,'Historical Data'!$BE$2:$BE$1068,0)),"") -> Legal | E5: =IFERROR(INDEX('Historical Data'!$E$2:$E$1068,MATCH($A5,'Historical Data'!$BE$2:$BE$1068,0)),"") -> 45754 | F5: =IFERROR(INDEX('Historical Data'!$G$2:$G$1068,MATCH($A5,'Historical Data'!$BE$2:$BE$1068,0)),"") -> 2 | G5: =IFERROR(INDEX('Historical Data'!$Y$2:$Y$1068,MATCH($A5,'Historical Data'!$BE$2:$BE$1068,0)),"") -> General Building Contractors | H5: =IFERROR(INDEX('Historical Data'!$K$2:$K$1068,MATCH($A5,'Historical Data'!$BE$2:$BE$1068,0)),"") -> GREYSTONE | I5: =IFERROR(INDEX('Historical Data'!$J$2:$J$1068,MATCH($A5,'Historical Data'!$BE$2:$BE$1068,0)),"") -> CA | J5: =IFERROR(INDEX('Historical Data'!$L$2:$L$1068,MATCH($A5,'Historical Data'!$BE$2:$BE$1068,0)),"") -> New Deal | K5: =IFERROR(INDEX('Historical Data'!$M$2:$M$1068,MATCH($A5,'Historical Data'!$BE$2:$BE$1068,0)),"") -> 1.49 | L5: =IFERROR(INDEX('Historical Data'!$N$2:$N$1068,MATCH($A5,'Historical Data'!$BE$2:$BE$1068,0)),"") -> 14000 | M5: =IFERROR(INDEX('Historical Data'!$Q$2:$Q$1068,MATCH($A5,'Historical Data'!$BE$2:$BE$1068,0)),"") -> 2318.06 | N5: =IFERROR(INDEX('Historical Data'!$S$2:$S$1068,MATCH($A5,'Historical Data'!$BE$2:$BE$1068,0)),"") -> 0.11112464 | O5: =IFERROR(INDEX('Historical Data'!$AJ$2:$AJ$1068,MATCH($A5,'Historical Data'!$BE$2:$BE$1068,0)),"") -> -11681.94 | P5: =IFERROR(INDEX('Historical Data'!$AK$2:$AK$1068,MATCH($A5,'Historical Data'!$BE$2:$BE$1068,0)),"") -> 11681.94 | Q5: =IFERROR(INDEX('Historical Data'!$AA$2:$AA$1068,MATCH($A5,'Historical Data'!$BE$2:$BE$1068,0)),"") -> 90 | R5: =IFERROR(INDEX('Historical Data'!$AB$2:$AB$1068,MATCH($A5,'Historical Data'!$BE$2:$BE$1068,0)),"") -> 349 | S5: =IFERROR(INDEX('Historical Data'!$AN$2:$AN$1068,MATCH($A5,'Historical Data'!$BE$2:$BE$1068,0)),"") -> 25 | T5: =IFERROR(INDEX('Historical Data'!$AC$2:$AC$1068,MATCH($A5,'Historical Data'!$BE$2:$BE$1068,0)),"") -> 1 | U5: =IFERROR(INDEX('Historical Data'!$AE$2:$AE$1068,MATCH($A5,'Historical Data'!$BE$2:$BE$1068,0)),"") -> 1 | V5: =IFERROR(INDEX('Historical Data'!$AH$2:$AH$1068,MATCH($A5,'Historical Data'!$BE$2:$BE$1068,0)),"") -> 0 | W5: =IFERROR(INDEX('Historical Data'!$BC$2:$BC$1068,MATCH($A5,'Historical Data'!$BE$2:$BE$1068,0)),"") -> 1 | X5: =IF(B5="","",IF(W5=1,"NR + industry + position",IF(W5=2,"NR + ISO + position",IF(W5=3,"NR + industry",IF(W5=4,"NR + ISO",IF(W5=5,"NR + position",IF(W5=6,"NR only","book baseline"))))))&" ["&IF(T5=1,"seasoned","unseasoned")&IF(U5=1,", defaulted","")&IF(V5=1,", open","")&"]") -> NR + industry + position [seasoned, defaulted]
A6: 2 | B6: =IFERROR(INDEX('Historical Data'!$A$2:$A$1068,MATCH($A6,'Historical Data'!$BE$2:$BE$1068,0)),"") -> 5674160797 | C6: =IFERROR(INDEX('Historical Data'!$B$2:$B$1068,MATCH($A6,'Historical Data'!$BE$2:$BE$1068,0)),"") -> MACS CUSTOM INSTALLS | D6: =IFERROR(INDEX('Historical Data'!$D$2:$D$1068,MATCH($A6,'Historical Data'!$BE$2:$BE$1068,0)),"") -> At-Risk | E6: =IFERROR(INDEX('Historical Data'!$E$2:$E$1068,MATCH($A6,'Historical Data'!$BE$2:$BE$1068,0)),"") -> 45838 | F6: =IFERROR(INDEX('Historical Data'!$G$2:$G$1068,MATCH($A6,'Historical Data'!$BE$2:$BE$1068,0)),"") -> 2 | G6: =IFERROR(INDEX('Historical Data'!$Y$2:$Y$1068,MATCH($A6,'Historical Data'!$BE$2:$BE$1068,0)),"") -> General Building Contractors | H6: =IFERROR(INDEX('Historical Data'!$K$2:$K$1068,MATCH($A6,'Historical Data'!$BE$2:$BE$1068,0)),"") -> Shield Funding | I6: =IFERROR(INDEX('Historical Data'!$J$2:$J$1068,MATCH($A6,'Historical Data'!$BE$2:$BE$1068,0)),"") -> SC | J6: =IFERROR(INDEX('Historical Data'!$L$2:$L$1068,MATCH($A6,'Historical Data'!$BE$2:$BE$1068,0)),"") -> New Deal | K6: =IFERROR(INDEX('Historical Data'!$M$2:$M$1068,MATCH($A6,'Historical Data'!$BE$2:$BE$1068,0)),"") -> 1.49 | L6: =IFERROR(INDEX('Historical Data'!$N$2:$N$1068,MATCH($A6,'Historical Data'!$BE$2:$BE$1068,0)),"") -> 10000 | M6: =IFERROR(INDEX('Historical Data'!$Q$2:$Q$1068,MATCH($A6,'Historical Data'!$BE$2:$BE$1068,0)),"") -> 8473.92 | N6: =IFERROR(INDEX('Historical Data'!$S$2:$S$1068,MATCH($A6,'Historical Data'!$BE$2:$BE$1068,0)),"") -> 0.56871946 | O6: =IFERROR(INDEX('Historical Data'!$AJ$2:$AJ$1068,MATCH($A6,'Historical Data'!$BE$2:$BE$1068,0)),"") -> -1526.08 | P6: =IFERROR(INDEX('Historical Data'!$AK$2:$AK$1068,MATCH($A6,'Historical Data'!$BE$2:$BE$1068,0)),"") -> 1526.08 | Q6: =IFERROR(INDEX('Historical Data'!$AA$2:$AA$1068,MATCH($A6,'Historical Data'!$BE$2:$BE$1068,0)),"") -> 56.801065 | R6: =IFERROR(INDEX('Historical Data'!$AB$2:$AB$1068,MATCH($A6,'Historical Data'!$BE$2:$BE$1068,0)),"") -> 291 | S6: =IFERROR(INDEX('Historical Data'!$AN$2:$AN$1068,MATCH($A6,'Historical Data'!$BE$2:$BE$1068,0)),"") -> 221 | T6: =IFERROR(INDEX('Historical Data'!$AC$2:$AC$1068,MATCH($A6,'Historical Data'!$BE$2:$BE$1068,0)),"") -> 1 | U6: =IFERROR(INDEX('Historical Data'!$AE$2:$AE$1068,MATCH($A6,'Historical Data'!$BE$2:$BE$1068,0)),"") -> 1 | V6: =IFERROR(INDEX('Historical Data'!$AH$2:$AH$1068,MATCH($A6,'Historical Data'!$BE$2:$BE$1068,0)),"") -> 0 | W6: =IFERROR(INDEX('Historical Data'!$BC$2:$BC$1068,MATCH($A6,'Historical Data'!$BE$2:$BE$1068,0)),"") -> 1 | X6: =IF(B6="","",IF(W6=1,"NR + industry + position",IF(W6=2,"NR + ISO + position",IF(W6=3,"NR + industry",IF(W6=4,"NR + ISO",IF(W6=5,"NR + position",IF(W6=6,"NR only","book baseline"))))))&" ["&IF(T6=1,"seasoned","unseasoned")&IF(U6=1,", defaulted","")&IF(V6=1,", open","")&"]") -> NR + industry + position [seasoned, defaulted]
A7: 3 | B7: =IFERROR(INDEX('Historical Data'!$A$2:$A$1068,MATCH($A7,'Historical Data'!$BE$2:$BE$1068,0)),"") -> 5674162609 | C7: =IFERROR(INDEX('Historical Data'!$B$2:$B$1068,MATCH($A7,'Historical Data'!$BE$2:$BE$1068,0)),"") -> Ribeiro General Construction Corp | D7: =IFERROR(INDEX('Historical Data'!$D$2:$D$1068,MATCH($A7,'Historical Data'!$BE$2:$BE$1068,0)),"") -> Closed | E7: =IFERROR(INDEX('Historical Data'!$E$2:$E$1068,MATCH($A7,'Historical Data'!$BE$2:$BE$1068,0)),"") -> 45863 | F7: =IFERROR(INDEX('Historical Data'!$G$2:$G$1068,MATCH($A7,'Historical Data'!$BE$2:$BE$1068,0)),"") -> 2 | G7: =IFERROR(INDEX('Historical Data'!$Y$2:$Y$1068,MATCH($A7,'Historical Data'!$BE$2:$BE$1068,0)),"") -> General Building Contractors | H7: =IFERROR(INDEX('Historical Data'!$K$2:$K$1068,MATCH($A7,'Historical Data'!$BE$2:$BE$1068,0)),"") -> NY Tribeca Group | I7: =IFERROR(INDEX('Historical Data'!$J$2:$J$1068,MATCH($A7,'Historical Data'!$BE$2:$BE$1068,0)),"") -> MA | J7: =IFERROR(INDEX('Historical Data'!$L$2:$L$1068,MATCH($A7,'Historical Data'!$BE$2:$BE$1068,0)),"") -> New Deal | K7: =IFERROR(INDEX('Historical Data'!$M$2:$M$1068,MATCH($A7,'Historical Data'!$BE$2:$BE$1068,0)),"") -> 1.35 | L7: =IFERROR(INDEX('Historical Data'!$N$2:$N$1068,MATCH($A7,'Historical Data'!$BE$2:$BE$1068,0)),"") -> 10000 | M7: =IFERROR(INDEX('Historical Data'!$Q$2:$Q$1068,MATCH($A7,'Historical Data'!$BE$2:$BE$1068,0)),"") -> 13500 | N7: =IFERROR(INDEX('Historical Data'!$S$2:$S$1068,MATCH($A7,'Historical Data'!$BE$2:$BE$1068,0)),"") -> 1 | O7: =IFERROR(INDEX('Historical Data'!$AJ$2:$AJ$1068,MATCH($A7,'Historical Data'!$BE$2:$BE$1068,0)),"") -> 3500 | P7: =IFERROR(INDEX('Historical Data'!$AK$2:$AK$1068,MATCH($A7,'Historical Data'!$BE$2:$BE$1068,0)),"") -> 0 | Q7: =IFERROR(INDEX('Historical Data'!$AA$2:$AA$1068,MATCH($A7,'Historical Data'!$BE$2:$BE$1068,0)),"") -> 42.595385 | R7: =IFERROR(INDEX('Historical Data'!$AB$2:$AB$1068,MATCH($A7,'Historical Data'!$BE$2:$BE$1068,0)),"") -> 273 | S7: =IFERROR(INDEX('Historical Data'!$AN$2:$AN$1068,MATCH($A7,'Historical Data'!$BE$2:$BE$1068,0)),"") -> 72 | T7: =IFERROR(INDEX('Historical Data'!$AC$2:$AC$1068,MATCH($A7,'Historical Data'!$BE$2:$BE$1068,0)),"") -> 1 | U7: =IFERROR(INDEX('Historical Data'!$AE$2:$AE$1068,MATCH($A7,'Historical Data'!$BE$2:$BE$1068,0)),"") -> 0 | V7: =IFERROR(INDEX('Historical Data'!$AH$2:$AH$1068,MATCH($A7,'Historical Data'!$BE$2:$BE$1068,0)),"") -> 0 | W7: =IFERROR(INDEX('Historical Data'!$BC$2:$BC$1068,MATCH($A7,'Historical Data'!$BE$2:$BE$1068,0)),"") -> 1 | X7: =IF(B7="","",IF(W7=1,"NR + industry + position",IF(W7=2,"NR + ISO + position",IF(W7=3,"NR + industry",IF(W7=4,"NR + ISO",IF(W7=5,"NR + position",IF(W7=6,"NR only","book baseline"))))))&" ["&IF(T7=1,"seasoned","unseasoned")&IF(U7=1,", defaulted","")&IF(V7=1,", open","")&"]") -> NR + industry + position [seasoned]
A8: 4 | B8: =IFERROR(INDEX('Historical Data'!$A$2:$A$1068,MATCH($A8,'Historical Data'!$BE$2:$BE$1068,0)),"") -> 5674162983 | C8: =IFERROR(INDEX('Historical Data'!$B$2:$B$1068,MATCH($A8,'Historical Data'!$BE$2:$BE$1068,0)),"") -> ON SITE REPAIR SERVICES LLC | D8: =IFERROR(INDEX('Historical Data'!$D$2:$D$1068,MATCH($A8,'Historical Data'!$BE$2:$BE$1068,0)),"") -> Closed | E8: =IFERROR(INDEX('Historical Data'!$E$2:$E$1068,MATCH($A8,'Historical Data'!$BE$2:$BE$1068,0)),"") -> 45869 | F8: =IFERROR(INDEX('Historical Data'!$G$2:$G$1068,MATCH($A8,'Historical Data'!$BE$2:$BE$1068,0)),"") -> 2 | G8: =IFERROR(INDEX('Historical Data'!$Y$2:$Y$1068,MATCH($A8,'Historical Data'!$BE$2:$BE$1068,0)),"") -> General Building Contractors | H8: =IFERROR(INDEX('Historical Data'!$K$2:$K$1068,MATCH($A8,'Historical Data'!$BE$2:$BE$1068,0)),"") -> Ballicci | I8: =IFERROR(INDEX('Historical Data'!$J$2:$J$1068,MATCH($A8,'Historical Data'!$BE$2:$BE$1068,0)),"") -> TX | J8: =IFERROR(INDEX('Historical Data'!$L$2:$L$1068,MATCH($A8,'Historical Data'!$BE$2:$BE$1068,0)),"") -> New Deal | K8: =IFERROR(INDEX('Historical Data'!$M$2:$M$1068,MATCH($A8,'Historical Data'!$BE$2:$BE$1068,0)),"") -> 1.49 | L8: =IFERROR(INDEX('Historical Data'!$N$2:$N$1068,MATCH($A8,'Historical Data'!$BE$2:$BE$1068,0)),"") -> 15000 | M8: =IFERROR(INDEX('Historical Data'!$Q$2:$Q$1068,MATCH($A8,'Historical Data'!$BE$2:$BE$1068,0)),"") -> 22350 | N8: =IFERROR(INDEX('Historical Data'!$S$2:$S$1068,MATCH($A8,'Historical Data'!$BE$2:$BE$1068,0)),"") -> 1 | O8: =IFERROR(INDEX('Historical Data'!$AJ$2:$AJ$1068,MATCH($A8,'Historical Data'!$BE$2:$BE$1068,0)),"") -> 7350 | P8: =IFERROR(INDEX('Historical Data'!$AK$2:$AK$1068,MATCH($A8,'Historical Data'!$BE$2:$BE$1068,0)),"") -> 0 | Q8: =IFERROR(INDEX('Historical Data'!$AA$2:$AA$1068,MATCH($A8,'Historical Data'!$BE$2:$BE$1068,0)),"") -> 60.352485 | R8: =IFERROR(INDEX('Historical Data'!$AB$2:$AB$1068,MATCH($A8,'Historical Data'!$BE$2:$BE$1068,0)),"") -> 269 | S8: =IFERROR(INDEX('Historical Data'!$AN$2:$AN$1068,MATCH($A8,'Historical Data'!$BE$2:$BE$1068,0)),"") -> 86 | T8: =IFERROR(INDEX('Historical Data'!$AC$2:$AC$1068,MATCH($A8,'Historical Data'!$BE$2:$BE$1068,0)),"") -> 1 | U8: =IFERROR(INDEX('Historical Data'!$AE$2:$AE$1068,MATCH($A8,'Historical Data'!$BE$2:$BE$1068,0)),"") -> 0 | V8: =IFERROR(INDEX('Historical Data'!$AH$2:$AH$1068,MATCH($A8,'Historical Data'!$BE$2:$BE$1068,0)),"") -> 0 | W8: =IFERROR(INDEX('Historical Data'!$BC$2:$BC$1068,MATCH($A8,'Historical Data'!$BE$2:$BE$1068,0)),"") -> 1 | X8: =IF(B8="","",IF(W8=1,"NR + industry + position",IF(W8=2,"NR + ISO + position",IF(W8=3,"NR + industry",IF(W8=4,"NR + ISO",IF(W8=5,"NR + position",IF(W8=6,"NR only","book baseline"))))))&" ["&IF(T8=1,"seasoned","unseasoned")&IF(U8=1,", defaulted","")&IF(V8=1,", open","")&"]") -> NR + industry + position [seasoned]
A9: 5 | B9: =IFERROR(INDEX('Historical Data'!$A$2:$A$1068,MATCH($A9,'Historical Data'!$BE$2:$BE$1068,0)),"") -> 5674163296 | C9: =IFERROR(INDEX('Historical Data'!$B$2:$B$1068,MATCH($A9,'Historical Data'!$BE$2:$BE$1068,0)),"") -> parker construction company | D9: =IFERROR(INDEX('Historical Data'!$D$2:$D$1068,MATCH($A9,'Historical Data'!$BE$2:$BE$1068,0)),"") -> Legal | E9: =IFERROR(INDEX('Historical Data'!$E$2:$E$1068,MATCH($A9,'Historical Data'!$BE$2:$BE$1068,0)),"") -> 45874 | F9: =IFERROR(INDEX('Historical Data'!$G$2:$G$1068,MATCH($A9,'Historical Data'!$BE$2:$BE$1068,0)),"") -> 2 | G9: =IFERROR(INDEX('Historical Data'!$Y$2:$Y$1068,MATCH($A9,'Historical Data'!$BE$2:$BE$1068,0)),"") -> General Building Contractors | H9: =IFERROR(INDEX('Historical Data'!$K$2:$K$1068,MATCH($A9,'Historical Data'!$BE$2:$BE$1068,0)),"") -> Springville Partners | I9: =IFERROR(INDEX('Historical Data'!$J$2:$J$1068,MATCH($A9,'Historical Data'!$BE$2:$BE$1068,0)),"") -> TN | J9: =IFERROR(INDEX('Historical Data'!$L$2:$L$1068,MATCH($A9,'Historical Data'!$BE$2:$BE$1068,0)),"") -> New Deal | K9: =IFERROR(INDEX('Historical Data'!$M$2:$M$1068,MATCH($A9,'Historical Data'!$BE$2:$BE$1068,0)),"") -> 1.499 | L9: =IFERROR(INDEX('Historical Data'!$N$2:$N$1068,MATCH($A9,'Historical Data'!$BE$2:$BE$1068,0)),"") -> 20000 | M9: =IFERROR(INDEX('Historical Data'!$Q$2:$Q$1068,MATCH($A9,'Historical Data'!$BE$2:$BE$1068,0)),"") -> 3350.52 | N9: =IFERROR(INDEX('Historical Data'!$S$2:$S$1068,MATCH($A9,'Historical Data'!$BE$2:$BE$1068,0)),"") -> 0.11175851 | O9: =IFERROR(INDEX('Historical Data'!$AJ$2:$AJ$1068,MATCH($A9,'Historical Data'!$BE$2:$BE$1068,0)),"") -> -16649.48 | P9: =IFERROR(INDEX('Historical Data'!$AK$2:$AK$1068,MATCH($A9,'Historical Data'!$BE$2:$BE$1068,0)),"") -> 16649.48 | Q9: =IFERROR(INDEX('Historical Data'!$AA$2:$AA$1068,MATCH($A9,'Historical Data'!$BE$2:$BE$1068,0)),"") -> 56.801065 | R9: =IFERROR(INDEX('Historical Data'!$AB$2:$AB$1068,MATCH($A9,'Historical Data'!$BE$2:$BE$1068,0)),"") -> 266 | S9: =IFERROR(INDEX('Historical Data'!$AN$2:$AN$1068,MATCH($A9,'Historical Data'!$BE$2:$BE$1068,0)),"") -> 12 | T9: =IFERROR(INDEX('Historical Data'!$AC$2:$AC$1068,MATCH($A9,'Historical Data'!$BE$2:$BE$1068,0)),"") -> 1 | U9: =IFERROR(INDEX('Historical Data'!$AE$2:$AE$1068,MATCH($A9,'Historical Data'!$BE$2:$BE$1068,0)),"") -> 1 | V9: =IFERROR(INDEX('Historical Data'!$AH$2:$AH$1068,MATCH($A9,'Historical Data'!$BE$2:$BE$1068,0)),"") -> 0 | W9: =IFERROR(INDEX('Historical Data'!$BC$2:$BC$1068,MATCH($A9,'Historical Data'!$BE$2:$BE$1068,0)),"") -> 1 | X9: =IF(B9="","",IF(W9=1,"NR + industry + position",IF(W9=2,"NR + ISO + position",IF(W9=3,"NR + industry",IF(W9=4,"NR + ISO",IF(W9=5,"NR + position",IF(W9=6,"NR only","book baseline"))))))&" ["&IF(T9=1,"seasoned","unseasoned")&IF(U9=1,", defaulted","")&IF(V9=1,", open","")&"]") -> NR + industry + position [seasoned, defaulted]
A10: 6 | B10: =IFERROR(INDEX('Historical Data'!$A$2:$A$1068,MATCH($A10,'Historical Data'!$BE$2:$BE$1068,0)),"") -> 5674163929 | C10: =IFERROR(INDEX('Historical Data'!$B$2:$B$1068,MATCH($A10,'Historical Data'!$BE$2:$BE$1068,0)),"") -> EXCELLENCE HOME SERVICES LLC | D10: =IFERROR(INDEX('Historical Data'!$D$2:$D$1068,MATCH($A10,'Historical Data'!$BE$2:$BE$1068,0)),"") -> Closed | E10: =IFERROR(INDEX('Historical Data'!$E$2:$E$1068,MATCH($A10,'Historical Data'!$BE$2:$BE$1068,0)),"") -> 45882 | F10: =IFERROR(INDEX('Historical Data'!$G$2:$G$1068,MATCH($A10,'Historical Data'!$BE$2:$BE$1068,0)),"") -> 2 | G10: =IFERROR(INDEX('Historical Data'!$Y$2:$Y$1068,MATCH($A10,'Historical Data'!$BE$2:$BE$1068,0)),"") -> General Building Contractors | H10: =IFERROR(INDEX('Historical Data'!$K$2:$K$1068,MATCH($A10,'Historical Data'!$BE$2:$BE$1068,0)),"") -> The Funding Channel | I10: =IFERROR(INDEX('Historical Data'!$J$2:$J$1068,MATCH($A10,'Historical Data'!$BE$2:$BE$1068,0)),"") -> FL | J10: =IFERROR(INDEX('Historical Data'!$L$2:$L$1068,MATCH($A10,'Historical Data'!$BE$2:$BE$1068,0)),"") -> New Deal | K10: =IFERROR(INDEX('Historical Data'!$M$2:$M$1068,MATCH($A10,'Historical Data'!$BE$2:$BE$1068,0)),"") -> 1.49 | L10: =IFERROR(INDEX('Historical Data'!$N$2:$N$1068,MATCH($A10,'Historical Data'!$BE$2:$BE$1068,0)),"") -> 15000 | M10: =IFERROR(INDEX('Historical Data'!$Q$2:$Q$1068,MATCH($A10,'Historical Data'!$BE$2:$BE$1068,0)),"") -> 22350 | N10: =IFERROR(INDEX('Historical Data'!$S$2:$S$1068,MATCH($A10,'Historical Data'!$BE$2:$BE$1068,0)),"") -> 1 | O10: =IFERROR(INDEX('Historical Data'!$AJ$2:$AJ$1068,MATCH($A10,'Historical Data'!$BE$2:$BE$1068,0)),"") -> 7350 | P10: =IFERROR(INDEX('Historical Data'!$AK$2:$AK$1068,MATCH($A10,'Historical Data'!$BE$2:$BE$1068,0)),"") -> 0 | Q10: =IFERROR(INDEX('Historical Data'!$AA$2:$AA$1068,MATCH($A10,'Historical Data'!$BE$2:$BE$1068,0)),"") -> 75 | R10: =IFERROR(INDEX('Historical Data'!$AB$2:$AB$1068,MATCH($A10,'Historical Data'!$BE$2:$BE$1068,0)),"") -> 260 | S10: =IFERROR(INDEX('Historical Data'!$AN$2:$AN$1068,MATCH($A10,'Historical Data'!$BE$2:$BE$1068,0)),"") -> 73 | T10: =IFERROR(INDEX('Historical Data'!$AC$2:$AC$1068,MATCH($A10,'Historical Data'!$BE$2:$BE$1068,0)),"") -> 1 | U10: =IFERROR(INDEX('Historical Data'!$AE$2:$AE$1068,MATCH($A10,'Historical Data'!$BE$2:$BE$1068,0)),"") -> 0 | V10: =IFERROR(INDEX('Historical Data'!$AH$2:$AH$1068,MATCH($A10,'Historical Data'!$BE$2:$BE$1068,0)),"") -> 0 | W10: =IFERROR(INDEX('Historical Data'!$BC$2:$BC$1068,MATCH($A10,'Historical Data'!$BE$2:$BE$1068,0)),"") -> 1 | X10: =IF(B10="","",IF(W10=1,"NR + industry + position",IF(W10=2,"NR + ISO + position",IF(W10=3,"NR + industry",IF(W10=4,"NR + ISO",IF(W10=5,"NR + position",IF(W10=6,"NR only","book baseline"))))))&" ["&IF(T10=1,"seasoned","unseasoned")&IF(U10=1,", defaulted","")&IF(V10=1,", open","")&"]") -> NR + industry + position [seasoned]
A11: 7 | B11: =IFERROR(INDEX('Historical Data'!$A$2:$A$1068,MATCH($A11,'Historical Data'!$BE$2:$BE$1068,0)),"") -> 5674164817 | C11: =IFERROR(INDEX('Historical Data'!$B$2:$B$1068,MATCH($A11,'Historical Data'!$BE$2:$BE$1068,0)),"") -> JAMES CORVIN | D11: =IFERROR(INDEX('Historical Data'!$D$2:$D$1068,MATCH($A11,'Historical Data'!$BE$2:$BE$1068,0)),"") -> Legal | E11: =IFERROR(INDEX('Historical Data'!$E$2:$E$1068,MATCH($A11,'Historical Data'!$BE$2:$BE$1068,0)),"") -> 45895 | F11: =IFERROR(INDEX('Historical Data'!$G$2:$G$1068,MATCH($A11,'Historical Data'!$BE$2:$BE$1068,0)),"") -> 2 | G11: =IFERROR(INDEX('Historical Data'!$Y$2:$Y$1068,MATCH($A11,'Historical Data'!$BE$2:$BE$1068,0)),"") -> General Building Contractors | H11: =IFERROR(INDEX('Historical Data'!$K$2:$K$1068,MATCH($A11,'Historical Data'!$BE$2:$BE$1068,0)),"") -> PMF | I11: =IFERROR(INDEX('Historical Data'!$J$2:$J$1068,MATCH($A11,'Historical Data'!$BE$2:$BE$1068,0)),"") -> VA | J11: =IFERROR(INDEX('Historical Data'!$L$2:$L$1068,MATCH($A11,'Historical Data'!$BE$2:$BE$1068,0)),"") -> New Deal | K11: =IFERROR(INDEX('Historical Data'!$M$2:$M$1068,MATCH($A11,'Historical Data'!$BE$2:$BE$1068,0)),"") -> 1.49 | L11: =IFERROR(INDEX('Historical Data'!$N$2:$N$1068,MATCH($A11,'Historical Data'!$BE$2:$BE$1068,0)),"") -> 75000 | M11: =IFERROR(INDEX('Historical Data'!$Q$2:$Q$1068,MATCH($A11,'Historical Data'!$BE$2:$BE$1068,0)),"") -> 27953.45 | N11: =IFERROR(INDEX('Historical Data'!$S$2:$S$1068,MATCH($A11,'Historical Data'!$BE$2:$BE$1068,0)),"") -> 0.25014273 | O11: =IFERROR(INDEX('Historical Data'!$AJ$2:$AJ$1068,MATCH($A11,'Historical Data'!$BE$2:$BE$1068,0)),"") -> -47046.55 | P11: =IFERROR(INDEX('Historical Data'!$AK$2:$AK$1068,MATCH($A11,'Historical Data'!$BE$2:$BE$1068,0)),"") -> 47046.55 | Q11: =IFERROR(INDEX('Historical Data'!$AA$2:$AA$1068,MATCH($A11,'Historical Data'!$BE$2:$BE$1068,0)),"") -> 140 | R11: =IFERROR(INDEX('Historical Data'!$AB$2:$AB$1068,MATCH($A11,'Historical Data'!$BE$2:$BE$1068,0)),"") -> 251 | S11: =IFERROR(INDEX('Historical Data'!$AN$2:$AN$1068,MATCH($A11,'Historical Data'!$BE$2:$BE$1068,0)),"") -> 38 | T11: =IFERROR(INDEX('Historical Data'!$AC$2:$AC$1068,MATCH($A11,'Historical Data'!$BE$2:$BE$1068,0)),"") -> 1 | U11: =IFERROR(INDEX('Historical Data'!$AE$2:$AE$1068,MATCH($A11,'Historical Data'!$BE$2:$BE$1068,0)),"") -> 1 | V11: =IFERROR(INDEX('Historical Data'!$AH$2:$AH$1068,MATCH($A11,'Historical Data'!$BE$2:$BE$1068,0)),"") -> 0 | W11: =IFERROR(INDEX('Historical Data'!$BC$2:$BC$1068,MATCH($A11,'Historical Data'!$BE$2:$BE$1068,0)),"") -> 1 | X11: =IF(B11="","",IF(W11=1,"NR + industry + position",IF(W11=2,"NR + ISO + position",IF(W11=3,"NR + industry",IF(W11=4,"NR + ISO",IF(W11=5,"NR + position",IF(W11=6,"NR only","book baseline"))))))&" ["&IF(T11=1,"seasoned","unseasoned")&IF(U11=1,", defaulted","")&IF(V11=1,", open","")&"]") -> NR + industry + position [seasoned, defaulted]
A12: 8 | B12: =IFERROR(INDEX('Historical Data'!$A$2:$A$1068,MATCH($A12,'Historical Data'!$BE$2:$BE$1068,0)),"") -> 5674165849 | C12: =IFERROR(INDEX('Historical Data'!$B$2:$B$1068,MATCH($A12,'Historical Data'!$BE$2:$BE$1068,0)),"") -> BD Home Group Inc | D12: =IFERROR(INDEX('Historical Data'!$D$2:$D$1068,MATCH($A12,'Historical Data'!$BE$2:$BE$1068,0)),"") -> Legal | E12: =IFERROR(INDEX('Historical Data'!$E$2:$E$1068,MATCH($A12,'Historical Data'!$BE$2:$BE$1068,0)),"") -> 45908 | F12: =IFERROR(INDEX('Historical Data'!$G$2:$G$1068,MATCH($A12,'Historical Data'!$BE$2:$BE$1068,0)),"") -> 2 | G12: =IFERROR(INDEX('Historical Data'!$Y$2:$Y$1068,MATCH($A12,'Historical Data'!$BE$2:$BE$1068,0)),"") -> General Building Contractors | H12: =IFERROR(INDEX('Historical Data'!$K$2:$K$1068,MATCH($A12,'Historical Data'!$BE$2:$BE$1068,0)),"") -> Tech Consulting Pro LLC D/B/A: Nationwide Advance | I12: =IFERROR(INDEX('Historical Data'!$J$2:$J$1068,MATCH($A12,'Historical Data'!$BE$2:$BE$1068,0)),"") -> CA | J12: =IFERROR(INDEX('Historical Data'!$L$2:$L$1068,MATCH($A12,'Historical Data'!$BE$2:$BE$1068,0)),"") -> New Deal | K12: =IFERROR(INDEX('Historical Data'!$M$2:$M$1068,MATCH($A12,'Historical Data'!$BE$2:$BE$1068,0)),"") -> 1.499 | L12: =IFERROR(INDEX('Historical Data'!$N$2:$N$1068,MATCH($A12,'Historical Data'!$BE$2:$BE$1068,0)),"") -> 16000 | M12: =IFERROR(INDEX('Historical Data'!$Q$2:$Q$1068,MATCH($A12,'Historical Data'!$BE$2:$BE$1068,0)),"") -> 866.4 | N12: =IFERROR(INDEX('Historical Data'!$S$2:$S$1068,MATCH($A12,'Historical Data'!$BE$2:$BE$1068,0)),"") -> 0.036124083 | O12: =IFERROR(INDEX('Historical Data'!$AJ$2:$AJ$1068,MATCH($A12,'Historical Data'!$BE$2:$BE$1068,0)),"") -> -15133.6 | P12: =IFERROR(INDEX('Historical Data'!$AK$2:$AK$1068,MATCH($A12,'Historical Data'!$BE$2:$BE$1068,0)),"") -> 15133.6 | Q12: =IFERROR(INDEX('Historical Data'!$AA$2:$AA$1068,MATCH($A12,'Historical Data'!$BE$2:$BE$1068,0)),"") -> 39.043965 | R12: =IFERROR(INDEX('Historical Data'!$AB$2:$AB$1068,MATCH($A12,'Historical Data'!$BE$2:$BE$1068,0)),"") -> 243 | S12: =IFERROR(INDEX('Historical Data'!$AN$2:$AN$1068,MATCH($A12,'Historical Data'!$BE$2:$BE$1068,0)),"") -> 184 | T12: =IFERROR(INDEX('Historical Data'!$AC$2:$AC$1068,MATCH($A12,'Historical Data'!$BE$2:$BE$1068,0)),"") -> 1 | U12: =IFERROR(INDEX('Historical Data'!$AE$2:$AE$1068,MATCH($A12,'Historical Data'!$BE$2:$BE$1068,0)),"") -> 1 | V12: =IFERROR(INDEX('Historical Data'!$AH$2:$AH$1068,MATCH($A12,'Historical Data'!$BE$2:$BE$1068,0)),"") -> 0 | W12: =IFERROR(INDEX('Historical Data'!$BC$2:$BC$1068,MATCH($A12,'Historical Data'!$BE$2:$BE$1068,0)),"") -> 1 | X12: =IF(B12="","",IF(W12=1,"NR + industry + position",IF(W12=2,"NR + ISO + position",IF(W12=3,"NR + industry",IF(W12=4,"NR + ISO",IF(W12=5,"NR + position",IF(W12=6,"NR only","book baseline"))))))&" ["&IF(T12=1,"seasoned","unseasoned")&IF(U12=1,", defaulted","")&IF(V12=1,", open","")&"]") -> NR + industry + position [seasoned, defaulted]
A13: 9 | B13: =IFERROR(INDEX('Historical Data'!$A$2:$A$1068,MATCH($A13,'Historical Data'!$BE$2:$BE$1068,0)),"") -> 5674166066 | C13: =IFERROR(INDEX('Historical Data'!$B$2:$B$1068,MATCH($A13,'Historical Data'!$BE$2:$BE$1068,0)),"") -> CC REMODELING SERVICES INC | D13: =IFERROR(INDEX('Historical Data'!$D$2:$D$1068,MATCH($A13,'Historical Data'!$BE$2:$BE$1068,0)),"") -> Closed | E13: =IFERROR(INDEX('Historical Data'!$E$2:$E$1068,MATCH($A13,'Historical Data'!$BE$2:$BE$1068,0)),"") -> 45910 | F13: =IFERROR(INDEX('Historical Data'!$G$2:$G$1068,MATCH($A13,'Historical Data'!$BE$2:$BE$1068,0)),"") -> 2 | G13: =IFERROR(INDEX('Historical Data'!$Y$2:$Y$1068,MATCH($A13,'Historical Data'!$BE$2:$BE$1068,0)),"") -> General Building Contractors | H13: =IFERROR(INDEX('Historical Data'!$K$2:$K$1068,MATCH($A13,'Historical Data'!$BE$2:$BE$1068,0)),"") -> biz advance now | I13: =IFERROR(INDEX('Historical Data'!$J$2:$J$1068,MATCH($A13,'Historical Data'!$BE$2:$BE$1068,0)),"") -> TN | J13: =IFERROR(INDEX('Historical Data'!$L$2:$L$1068,MATCH($A13,'Historical Data'!$BE$2:$BE$1068,0)),"") -> New Deal | K13: =IFERROR(INDEX('Historical Data'!$M$2:$M$1068,MATCH($A13,'Historical Data'!$BE$2:$BE$1068,0)),"") -> 1.499 | L13: =IFERROR(INDEX('Historical Data'!$N$2:$N$1068,MATCH($A13,'Historical Data'!$BE$2:$BE$1068,0)),"") -> 15000 | M13: =IFERROR(INDEX('Historical Data'!$Q$2:$Q$1068,MATCH($A13,'Historical Data'!$BE$2:$BE$1068,0)),"") -> 22485 | N13: =IFERROR(INDEX('Historical Data'!$S$2:$S$1068,MATCH($A13,'Historical Data'!$BE$2:$BE$1068,0)),"") -> 1 | O13: =IFERROR(INDEX('Historical Data'!$AJ$2:$AJ$1068,MATCH($A13,'Historical Data'!$BE$2:$BE$1068,0)),"") -> 7485 | P13: =IFERROR(INDEX('Historical Data'!$AK$2:$AK$1068,MATCH($A13,'Historical Data'!$BE$2:$BE$1068,0)),"") -> 0 | Q13: =IFERROR(INDEX('Historical Data'!$AA$2:$AA$1068,MATCH($A13,'Historical Data'!$BE$2:$BE$1068,0)),"") -> 56.801065 | R13: =IFERROR(INDEX('Historical Data'!$AB$2:$AB$1068,MATCH($A13,'Historical Data'!$BE$2:$BE$1068,0)),"") -> 241 | S13: =IFERROR(INDEX('Historical Data'!$AN$2:$AN$1068,MATCH($A13,'Historical Data'!$BE$2:$BE$1068,0)),"") -> 82 | T13: =IFERROR(INDEX('Historical Data'!$AC$2:$AC$1068,MATCH($A13,'Historical Data'!$BE$2:$BE$1068,0)),"") -> 1 | U13: =IFERROR(INDEX('Historical Data'!$AE$2:$AE$1068,MATCH($A13,'Historical Data'!$BE$2:$BE$1068,0)),"") -> 0 | V13: =IFERROR(INDEX('Historical Data'!$AH$2:$AH$1068,MATCH($A13,'Historical Data'!$BE$2:$BE$1068,0)),"") -> 0 | W13: =IFERROR(INDEX('Historical Data'!$BC$2:$BC$1068,MATCH($A13,'Historical Data'!$BE$2:$BE$1068,0)),"") -> 1 | X13: =IF(B13="","",IF(W13=1,"NR + industry + position",IF(W13=2,"NR + ISO + position",IF(W13=3,"NR + industry",IF(W13=4,"NR + ISO",IF(W13=5,"NR + position",IF(W13=6,"NR only","book baseline"))))))&" ["&IF(T13=1,"seasoned","unseasoned")&IF(U13=1,", defaulted","")&IF(V13=1,", open","")&"]") -> NR + industry + position [seasoned]
A14: 10 | B14: =IFERROR(INDEX('Historical Data'!$A$2:$A$1068,MATCH($A14,'Historical Data'!$BE$2:$BE$1068,0)),"") -> 5674166825 | C14: =IFERROR(INDEX('Historical Data'!$B$2:$B$1068,MATCH($A14,'Historical Data'!$BE$2:$BE$1068,0)),"") -> ALPHA 3 MASONRY & REMODEL | D14: =IFERROR(INDEX('Historical Data'!$D$2:$D$1068,MATCH($A14,'Historical Data'!$BE$2:$BE$1068,0)),"") -> Closed | E14: =IFERROR(INDEX('Historical Data'!$E$2:$E$1068,MATCH($A14,'Historical Data'!$BE$2:$BE$1068,0)),"") -> 45917 | F14: =IFERROR(INDEX('Historical Data'!$G$2:$G$1068,MATCH($A14,'Historical Data'!$BE$2:$BE$1068,0)),"") -> 2 | G14: =IFERROR(INDEX('Historical Data'!$Y$2:$Y$1068,MATCH($A14,'Historical Data'!$BE$2:$BE$1068,0)),"") -> General Building Contractors | H14: =IFERROR(INDEX('Historical Data'!$K$2:$K$1068,MATCH($A14,'Historical Data'!$BE$2:$BE$1068,0)),"") -> FIMACAP INC | I14: =IFERROR(INDEX('Historical Data'!$J$2:$J$1068,MATCH($A14,'Historical Data'!$BE$2:$BE$1068,0)),"") -> AZ | J14: =IFERROR(INDEX('Historical Data'!$L$2:$L$1068,MATCH($A14,'Historical Data'!$BE$2:$BE$1068,0)),"") -> New Deal | K14: =IFERROR(INDEX('Historical Data'!$M$2:$M$1068,MATCH($A14,'Historical Data'!$BE$2:$BE$1068,0)),"") -> 1.35 | L14: =IFERROR(INDEX('Historical Data'!$N$2:$N$1068,MATCH($A14,'Historical Data'!$BE$2:$BE$1068,0)),"") -> 20000 | M14: =IFERROR(INDEX('Historical Data'!$Q$2:$Q$1068,MATCH($A14,'Historical Data'!$BE$2:$BE$1068,0)),"") -> 27000 | N14: =IFERROR(INDEX('Historical Data'!$S$2:$S$1068,MATCH($A14,'Historical Data'!$BE$2:$BE$1068,0)),"") -> 1 | O14: =IFERROR(INDEX('Historical Data'!$AJ$2:$AJ$1068,MATCH($A14,'Historical Data'!$BE$2:$BE$1068,0)),"") -> 7000 | P14: =IFERROR(INDEX('Historical Data'!$AK$2:$AK$1068,MATCH($A14,'Historical Data'!$BE$2:$BE$1068,0)),"") -> 0 | Q14: =IFERROR(INDEX('Historical Data'!$AA$2:$AA$1068,MATCH($A14,'Historical Data'!$BE$2:$BE$1068,0)),"") -> 110 | R14: =IFERROR(INDEX('Historical Data'!$AB$2:$AB$1068,MATCH($A14,'Historical Data'!$BE$2:$BE$1068,0)),"") -> 236 | S14: =IFERROR(INDEX('Historical Data'!$AN$2:$AN$1068,MATCH($A14,'Historical Data'!$BE$2:$BE$1068,0)),"") -> 110 | T14: =IFERROR(INDEX('Historical Data'!$AC$2:$AC$1068,MATCH($A14,'Historical Data'!$BE$2:$BE$1068,0)),"") -> 1 | U14: =IFERROR(INDEX('Historical Data'!$AE$2:$AE$1068,MATCH($A14,'Historical Data'!$BE$2:$BE$1068,0)),"") -> 0 | V14: =IFERROR(INDEX('Historical Data'!$AH$2:$AH$1068,MATCH($A14,'Historical Data'!$BE$2:$BE$1068,0)),"") -> 0 | W14: =IFERROR(INDEX('Historical Data'!$BC$2:$BC$1068,MATCH($A14,'Historical Data'!$BE$2:$BE$1068,0)),"") -> 1 | X14: =IF(B14="","",IF(W14=1,"NR + industry + position",IF(W14=2,"NR + ISO + position",IF(W14=3,"NR + industry",IF(W14=4,"NR + ISO",IF(W14=5,"NR + position",IF(W14=6,"NR only","book baseline"))))))&" ["&IF(T14=1,"seasoned","unseasoned")&IF(U14=1,", defaulted","")&IF(V14=1,", open","")&"]") -> NR + industry + position [seasoned]
A15: 11 | B15: =IFERROR(INDEX('Historical Data'!$A$2:$A$1068,MATCH($A15,'Historical Data'!$BE$2:$BE$1068,0)),"") -> 5674167409 | C15: =IFERROR(INDEX('Historical Data'!$B$2:$B$1068,MATCH($A15,'Historical Data'!$BE$2:$BE$1068,0)),"") -> Cincinnati Home Remodelation LLC | D15: =IFERROR(INDEX('Historical Data'!$D$2:$D$1068,MATCH($A15,'Historical Data'!$BE$2:$BE$1068,0)),"") -> Legal | E15: =IFERROR(INDEX('Historical Data'!$E$2:$E$1068,MATCH($A15,'Historical Data'!$BE$2:$BE$1068,0)),"") -> 45926 | F15: =IFERROR(INDEX('Historical Data'!$G$2:$G$1068,MATCH($A15,'Historical Data'!$BE$2:$BE$1068,0)),"") -> 2 | G15: =IFERROR(INDEX('Historical Data'!$Y$2:$Y$1068,MATCH($A15,'Historical Data'!$BE$2:$BE$1068,0)),"") -> General Building Contractors | H15: =IFERROR(INDEX('Historical Data'!$K$2:$K$1068,MATCH($A15,'Historical Data'!$BE$2:$BE$1068,0)),"") -> United Secured Capital 8 | I15: =IFERROR(INDEX('Historical Data'!$J$2:$J$1068,MATCH($A15,'Historical Data'!$BE$2:$BE$1068,0)),"") -> OH | J15: =IFERROR(INDEX('Historical Data'!$L$2:$L$1068,MATCH($A15,'Historical Data'!$BE$2:$BE$1068,0)),"") -> New Deal | K15: =IFERROR(INDEX('Historical Data'!$M$2:$M$1068,MATCH($A15,'Historical Data'!$BE$2:$BE$1068,0)),"") -> 1.499 | L15: =IFERROR(INDEX('Historical Data'!$N$2:$N$1068,MATCH($A15,'Historical Data'!$BE$2:$BE$1068,0)),"") -> 7000 | M15: =IFERROR(INDEX('Historical Data'!$Q$2:$Q$1068,MATCH($A15,'Historical Data'!$BE$2:$BE$1068,0)),"") -> 3913.5 | N15: =IFERROR(INDEX('Historical Data'!$S$2:$S$1068,MATCH($A15,'Historical Data'!$BE$2:$BE$1068,0)),"") -> 0.37296293 | O15: =IFERROR(INDEX('Historical Data'!$AJ$2:$AJ$1068,MATCH($A15,'Historical Data'!$BE$2:$BE$1068,0)),"") -> -3086.5 | P15: =IFERROR(INDEX('Historical Data'!$AK$2:$AK$1068,MATCH($A15,'Historical Data'!$BE$2:$BE$1068,0)),"") -> 3086.5 | Q15: =IFERROR(INDEX('Historical Data'!$AA$2:$AA$1068,MATCH($A15,'Historical Data'!$BE$2:$BE$1068,0)),"") -> 56.801065 | R15: =IFERROR(INDEX('Historical Data'!$AB$2:$AB$1068,MATCH($A15,'Historical Data'!$BE$2:$BE$1068,0)),"") -> 229 | S15: =IFERROR(INDEX('Historical Data'!$AN$2:$AN$1068,MATCH($A15,'Historical Data'!$BE$2:$BE$1068,0)),"") -> 54 | T15: =IFERROR(INDEX('Historical Data'!$AC$2:$AC$1068,MATCH($A15,'Historical Data'!$BE$2:$BE$1068,0)),"") -> 1 | U15: =IFERROR(INDEX('Historical Data'!$AE$2:$AE$1068,MATCH($A15,'Historical Data'!$BE$2:$BE$1068,0)),"") -> 1 | V15: =IFERROR(INDEX('Historical Data'!$AH$2:$AH$1068,MATCH($A15,'Historical Data'!$BE$2:$BE$1068,0)),"") -> 0 | W15: =IFERROR(INDEX('Historical Data'!$BC$2:$BC$1068,MATCH($A15,'Historical Data'!$BE$2:$BE$1068,0)),"") -> 1 | X15: =IF(B15="","",IF(W15=1,"NR + industry + position",IF(W15=2,"NR + ISO + position",IF(W15=3,"NR + industry",IF(W15=4,"NR + ISO",IF(W15=5,"NR + position",IF(W15=6,"NR only","book baseline"))))))&" ["&IF(T15=1,"seasoned","unseasoned")&IF(U15=1,", defaulted","")&IF(V15=1,", open","")&"]") -> NR + industry + position [seasoned, defaulted]
A16: 12 | B16: =IFERROR(INDEX('Historical Data'!$A$2:$A$1068,MATCH($A16,'Historical Data'!$BE$2:$BE$1068,0)),"") -> 5674169346 | C16: =IFERROR(INDEX('Historical Data'!$B$2:$B$1068,MATCH($A16,'Historical Data'!$BE$2:$BE$1068,0)),"") -> Robs Flooring LLC | D16: =IFERROR(INDEX('Historical Data'!$D$2:$D$1068,MATCH($A16,'Historical Data'!$BE$2:$BE$1068,0)),"") -> In House Collection | E16: =IFERROR(INDEX('Historical Data'!$E$2:$E$1068,MATCH($A16,'Historical Data'!$BE$2:$BE$1068,0)),"") -> 45958 | F16: =IFERROR(INDEX('Historical Data'!$G$2:$G$1068,MATCH($A16,'Historical Data'!$BE$2:$BE$1068,0)),"") -> 2 | G16: =IFERROR(INDEX('Historical Data'!$Y$2:$Y$1068,MATCH($A16,'Historical Data'!$BE$2:$BE$1068,0)),"") -> General Building Contractors | H16: =IFERROR(INDEX('Historical Data'!$K$2:$K$1068,MATCH($A16,'Historical Data'!$BE$2:$BE$1068,0)),"") -> Llama Loan | I16: =IFERROR(INDEX('Historical Data'!$J$2:$J$1068,MATCH($A16,'Historical Data'!$BE$2:$BE$1068,0)),"") -> MI | J16: =IFERROR(INDEX('Historical Data'!$L$2:$L$1068,MATCH($A16,'Historical Data'!$BE$2:$BE$1068,0)),"") -> New Deal | K16: =IFERROR(INDEX('Historical Data'!$M$2:$M$1068,MATCH($A16,'Historical Data'!$BE$2:$BE$1068,0)),"") -> 1.45 | L16: =IFERROR(INDEX('Historical Data'!$N$2:$N$1068,MATCH($A16,'Historical Data'!$BE$2:$BE$1068,0)),"") -> 3500 | M16: =IFERROR(INDEX('Historical Data'!$Q$2:$Q$1068,MATCH($A16,'Historical Data'!$BE$2:$BE$1068,0)),"") -> 2067.06 | N16: =IFERROR(INDEX('Historical Data'!$S$2:$S$1068,MATCH($A16,'Historical Data'!$BE$2:$BE$1068,0)),"") -> 0.40730246 | O16: =IFERROR(INDEX('Historical Data'!$AJ$2:$AJ$1068,MATCH($A16,'Historical Data'!$BE$2:$BE$1068,0)),"") -> -1432.94 | P16: =IFERROR(INDEX('Historical Data'!$AK$2:$AK$1068,MATCH($A16,'Historical Data'!$BE$2:$BE$1068,0)),"") -> 1432.94 | Q16: =IFERROR(INDEX('Historical Data'!$AA$2:$AA$1068,MATCH($A16,'Historical Data'!$BE$2:$BE$1068,0)),"") -> 80 | R16: =IFERROR(INDEX('Historical Data'!$AB$2:$AB$1068,MATCH($A16,'Historical Data'!$BE$2:$BE$1068,0)),"") -> 208 | S16: =IFERROR(INDEX('Historical Data'!$AN$2:$AN$1068,MATCH($A16,'Historical Data'!$BE$2:$BE$1068,0)),"") -> 201 | T16: =IFERROR(INDEX('Historical Data'!$AC$2:$AC$1068,MATCH($A16,'Historical Data'!$BE$2:$BE$1068,0)),"") -> 1 | U16: =IFERROR(INDEX('Historical Data'!$AE$2:$AE$1068,MATCH($A16,'Historical Data'!$BE$2:$BE$1068,0)),"") -> 1 | V16: =IFERROR(INDEX('Historical Data'!$AH$2:$AH$1068,MATCH($A16,'Historical Data'!$BE$2:$BE$1068,0)),"") -> 0 | W16: =IFERROR(INDEX('Historical Data'!$BC$2:$BC$1068,MATCH($A16,'Historical Data'!$BE$2:$BE$1068,0)),"") -> 1 | X16: =IF(B16="","",IF(W16=1,"NR + industry + position",IF(W16=2,"NR + ISO + position",IF(W16=3,"NR + industry",IF(W16=4,"NR + ISO",IF(W16=5,"NR + position",IF(W16=6,"NR only","book baseline"))))))&" ["&IF(T16=1,"seasoned","unseasoned")&IF(U16=1,", defaulted","")&IF(V16=1,", open","")&"]") -> NR + industry + position [seasoned, defaulted]
... A404: 400 | B404: =IFERROR(INDEX('Historical Data'!$A$2:$A$1068,MATCH($A404,'Historical Data'!$BE$2:$BE$1068,0)),"") | C404: =IFERROR(INDEX('Historical Data'!$B$2:$B$1068,MATCH($A404,'Historical Data'!$BE$2:$BE$1068,0)),"") | D404: =IFERROR(INDEX('Historical Data'!$D$2:$D$1068,MATCH($A404,'Historical Data'!$BE$2:$BE$1068,0)),"") | E404: =IFERROR(INDEX('Historical Data'!$E$2:$E$1068,MATCH($A404,'Historical Data'!$BE$2:$BE$1068,0)),"") | F404: =IFERROR(INDEX('Historical Data'!$G$2:$G$1068,MATCH($A404,'Historical Data'!$BE$2:$BE$1068,0)),"") | G404: =IFERROR(INDEX('Historical Data'!$Y$2:$Y$1068,MATCH($A404,'Historical Data'!$BE$2:$BE$1068,0)),"") | H404: =IFERROR(INDEX('Historical Data'!$K$2:$K$1068,MATCH($A404,'Historical Data'!$BE$2:$BE$1068,0)),"") | I404: =IFERROR(INDEX('Historical Data'!$J$2:$J$1068,MATCH($A404,'Historical Data'!$BE$2:$BE$1068,0)),"") | J404: =IFERROR(INDEX('Historical Data'!$L$2:$L$1068,MATCH($A404,'Historical Data'!$BE$2:$BE$1068,0)),"") | K404: =IFERROR(INDEX('Historical Data'!$M$2:$M$1068,MATCH($A404,'Historical Data'!$BE$2:$BE$1068,0)),"") | L404: =IFERROR(INDEX('Historical Data'!$N$2:$N$1068,MATCH($A404,'Historical Data'!$BE$2:$BE$1068,0)),"") | M404: =IFERROR(INDEX('Historical Data'!$Q$2:$Q$1068,MATCH($A404,'Historical Data'!$BE$2:$BE$1068,0)),"") | N404: =IFERROR(INDEX('Historical Data'!$S$2:$S$1068,MATCH($A404,'Historical Data'!$BE$2:$BE$1068,0)),"") | O404: =IFERROR(INDEX('Historical Data'!$AJ$2:$AJ$1068,MATCH($A404,'Historical Data'!$BE$2:$BE$1068,0)),"") | P404: =IFERROR(INDEX('Historical Data'!$AK$2:$AK$1068,MATCH($A404,'Historical Data'!$BE$2:$BE$1068,0)),"") | Q404: =IFERROR(INDEX('Historical Data'!$AA$2:$AA$1068,MATCH($A404,'Historical Data'!$BE$2:$BE$1068,0)),"") | R404: =IFERROR(INDEX('Historical Data'!$AB$2:$AB$1068,MATCH($A404,'Historical Data'!$BE$2:$BE$1068,0)),"") | S404: =IFERROR(INDEX('Historical Data'!$AN$2:$AN$1068,MATCH($A404,'Historical Data'!$BE$2:$BE$1068,0)),"") | T404: =IFERROR(INDEX('Historical Data'!$AC$2:$AC$1068,MATCH($A404,'Historical Data'!$BE$2:$BE$1068,0)),"") | U404: =IFERROR(INDEX('Historical Data'!$AE$2:$AE$1068,MATCH($A404,'Historical Data'!$BE$2:$BE$1068,0)),"") | V404: =IFERROR(INDEX('Historical Data'!$AH$2:$AH$1068,MATCH($A404,'Historical Data'!$BE$2:$BE$1068,0)),"") | W404: =IFERROR(INDEX('Historical Data'!$BC$2:$BC$1068,MATCH($A404,'Historical Data'!$BE$2:$BE$1068,0)),"") | X404: =IF(B404="","",IF(W404=1,"NR + industry + position",IF(W404=2,"NR + ISO + position",IF(W404=3,"NR + industry",IF(W404=4,"NR + ISO",IF(W404=5,"NR + position",IF(W404=6,"NR only","book baseline"))))))&" ["&IF(T404=1,"seasoned","unseasoned")&IF(U404=1,", defaulted","")&IF(V404=1,", open","")&"]")

Sheet Historical Data
A1: Contract ID | B1: DBA | C1: Legal name | D1: Status | E1: Start date | F1: Last active | G1: Position | H1: SIC | I1: SIC2 | J1: State | K1: ISO | L1: New or renewal | M1: Factor | N1: Advance | O1: Commission | P1: Payback | Q1: Collected | R1: Balance | S1: % paid | T1: Exp dur (raw) | U1: NSF count | V1: Avg rev/mo | W1: Holdback % | X1: Biz start | Y1: Industry | Z1: Pay frequency | AA1: Term (bus. days) | AB1: Age at as-of (bus. days) | AC1: Seasoned | AD1: In window | AE1: Default | AF1: Resolved | AG1: Closed family | AH1: Open | AI1: Status valid | AJ1: Net cash | AK1: Principal lost | AL1: Adv / revenue | AM1: Has revenue | AN1: Days on book (bus.) | AO1: Renewal | AP1: Eligible (seasoned & in window) | AQ1: m: position | AR1: m: new/renewal | AS1: m: industry | AT1: m: ISO | AU1: m: state | AV1: T1 NR+Ind+Pos | AW1: T2 NR+ISO+Pos | AX1: T3 NR+Ind | AY1: T4 NR+ISO | AZ1: T5 NR+Pos | BA1: T6 NR | BB1: T7 Book | BC1: Best tier | BD1: In primary cohort | BE1: Seq
A2: 5674142980 | B2: The rustic charm bar and grill | C2: The rustic charm LLC | D2: Legal | E2: 45616 | F2: 46118 | G2: 1 | H2: 5813 | I2: 58 | J2: CO | K2: GREYSTONE | L2: New Deal | M2: 1.49 | N2: 15000 | O2: 2100 | P2: 22350 | Q2: 16835.64 | R2: 5514.36 | S2: 0.75327248 | T2: 2.754 | U2: 5 | W2: 0.05 | X2: 44701 | Y2: =IF(I2="","No SIC",IFERROR(VLOOKUP(I2,Ref!$A$2:$B$65,2,FALSE()),"Unclassified")) -> Eating & Drinking Places | Z2: =IF(T2="","",IF(T2<12,"Daily","Weekly")) -> Daily | AA2: =IF(T2="",0,IF(T2<12,T2*Controls!$B$29,T2*5)) -> 59.63787 | AB2: =IF(E2="",0,NETWORKDAYS(E2,Controls!$B$36,Ref!$K$2:$K$42)) -> 442 | AC2: =IF(AND(AA2>0,AB2>=Controls!$B$39*AA2),1,0) -> 1 | AD2: =IF(AND(E2<>"",E2>=Controls!$B$37,E2<=Controls!$B$38),1,0) -> 1 | AE2: =IF(IFERROR(VLOOKUP(D2,Controls!$A$64:$E$74,2,FALSE()),"No")="Yes",1,0) -> 1 | AF2: =IF(IFERROR(VLOOKUP(D2,Controls!$A$64:$E$74,3,FALSE()),"No")="Yes",1,0) -> 0 | AG2: =IF(IFERROR(VLOOKUP(D2,Controls!$A$64:$E$74,4,FALSE()),"No")="Yes",1,0) -> 0 | AH2: =IF(IFERROR(VLOOKUP(D2,Controls!$A$64:$E$74,5,FALSE()),"No")="Yes",1,0) -> 0 | AI2: =IF(ISNUMBER(MATCH(D2,Controls!$A$64:$A$74,0)),1,0) -> 1 | AJ2: =Q2-N2 -> 1835.64 | AK2: =IF(AE2=1,MAX(0,N2-Q2),0) -> 0 | AL2: =IF(OR(V2="",V2=0),0,N2/V2) -> 0 | AM2: =IF(OR(V2="",V2=0),0,1) -> 0 | AN2: =IF(OR(E2="",F2=""),0,NETWORKDAYS(E2,F2,Ref!$K$2:$K$42)) -> 343 | AO2: =IF(L2="Renewal",1,0) -> 0 | AP2: =AC2*AD2 -> 1 | AQ2: =IF(AND(G2<>"",'Historical Score'!$C$6<>""),IF(G2='Historical Score'!$C$6,1,0),0) -> 0 | AR2: =IF(AND(L2<>"",'Historical Score'!$C$5<>""),IF(L2='Historical Score'!$C$5,1,0),0) -> 1 | AS2: =IF(AND(Y2<>"",'Historical Score'!$C$7<>""),IF(Y2='Historical Score'!$C$7,1,0),0) -> 0 | AT2: =IF(AND(K2<>"",'Historical Score'!$C$8<>""),IF(K2='Historical Score'!$C$8,1,0),0) -> 0 | AU2: =IF(AND(J2<>"",'Historical Score'!$C$9<>""),IF(J2='Historical Score'!$C$9,1,0),0) -> 0 | AV2: =AR2*AS2*AQ2 -> 0 | AW2: =AR2*AT2*AQ2 -> 0 | AX2: =AR2*AS2 -> 0 | AY2: =AR2*AT2 -> 0 | AZ2: =AR2*AQ2 -> 0 | BA2: =AR2 -> 1 | BB2: =1 -> 1 | BC2: =IF(AV2=1,1,IF(AW2=1,2,IF(AX2=1,3,IF(AY2=1,4,IF(AZ2=1,5,IF(BA2=1,6,7)))))) -> 6 | BD2: =IF(AD2=1,CHOOSE('Historical Score'!$C$29,AV2,AW2,AX2,AY2,AZ2,BA2,BB2),0) -> 0 | BE2: =IF(BD2=1,COUNTIF($BD$2:BD2,1),"")
A3: 5674143732 | B3: GUADALUPE CASTANEDA | C3: GUADALUPE CASTANEDA | D3: Written-Off | E3: 45625 | F3: 45786 | G3: 3 | H3: 1442 | I3: 14 | J3: CA | K3: BFA 3 | L3: New Deal | M3: 1.49 | N3: 5000 | O3: 700 | P3: 7450 | Q3: 6305.98 | R3: 1144.02 | S3: 0.84644027 | T3: 2.623 | U3: 24 | W3: 0.12 | X3: 34575 | Y3: =IF(I3="","No SIC",IFERROR(VLOOKUP(I3,Ref!$A$2:$B$65,2,FALSE()),"Unclassified")) -> Nonmetallic Minerals Mining | Z3: =IF(T3="","",IF(T3<12,"Daily","Weekly")) -> Daily | AA3: =IF(T3="",0,IF(T3<12,T3*Controls!$B$29,T3*5)) -> 56.801065 | AB3: =IF(E3="",0,NETWORKDAYS(E3,Controls!$B$36,Ref!$K$2:$K$42)) -> 436 | AC3: =IF(AND(AA3>0,AB3>=Controls!$B$39*AA3),1,0) -> 1 | AD3: =IF(AND(E3<>"",E3>=Controls!$B$37,E3<=Controls!$B$38),1,0) -> 1 | AE3: =IF(IFERROR(VLOOKUP(D3,Controls!$A$64:$E$74,2,FALSE()),"No")="Yes",1,0) -> 1 | AF3: =IF(IFERROR(VLOOKUP(D3,Controls!$A$64:$E$74,3,FALSE()),"No")="Yes",1,0) -> 1 | AG3: =IF(IFERROR(VLOOKUP(D3,Controls!$A$64:$E$74,4,FALSE()),"No")="Yes",1,0) -> 0 | AH3: =IF(IFERROR(VLOOKUP(D3,Controls!$A$64:$E$74,5,FALSE()),"No")="Yes",1,0) -> 0 | AI3: =IF(ISNUMBER(MATCH(D3,Controls!$A$64:$A$74,0)),1,0) -> 1 | AJ3: =Q3-N3 -> 1305.98 | AK3: =IF(AE3=1,MAX(0,N3-Q3),0) -> 0 | AL3: =IF(OR(V3="",V3=0),0,N3/V3) -> 0 | AM3: =IF(OR(V3="",V3=0),0,1) -> 0 | AN3: =IF(OR(E3="",F3=""),0,NETWORKDAYS(E3,F3,Ref!$K$2:$K$42)) -> 112 | AO3: =IF(L3="Renewal",1,0) -> 0 | AP3: =AC3*AD3 -> 1 | AQ3: =IF(AND(G3<>"",'Historical Score'!$C$6<>""),IF(G3='Historical Score'!$C$6,1,0),0) -> 0 | AR3: =IF(AND(L3<>"",'Historical Score'!$C$5<>""),IF(L3='Historical Score'!$C$5,1,0),0) -> 1 | AS3: =IF(AND(Y3<>"",'Historical Score'!$C$7<>""),IF(Y3='Historical Score'!$C$7,1,0),0) -> 0 | AT3: =IF(AND(K3<>"",'Historical Score'!$C$8<>""),IF(K3='Historical Score'!$C$8,1,0),0) -> 0 | AU3: =IF(AND(J3<>"",'Historical Score'!$C$9<>""),IF(J3='Historical Score'!$C$9,1,0),0) -> 0 | AV3: =AR3*AS3*AQ3 -> 0 | AW3: =AR3*AT3*AQ3 -> 0 | AX3: =AR3*AS3 -> 0 | AY3: =AR3*AT3 -> 0 | AZ3: =AR3*AQ3 -> 0 | BA3: =AR3 -> 1 | BB3: =1 -> 1 | BC3: =IF(AV3=1,1,IF(AW3=1,2,IF(AX3=1,3,IF(AY3=1,4,IF(AZ3=1,5,IF(BA3=1,6,7)))))) -> 6 | BD3: =IF(AD3=1,CHOOSE('Historical Score'!$C$29,AV3,AW3,AX3,AY3,AZ3,BA3,BB3),0) -> 0 | BE3: =IF(BD3=1,COUNTIF($BD$2:BD3,1),"")
A4: 5674144092 | B4: DALE JOHNSON SOLE MBR | C4: LEVEL 4 TRANSPORT LLC | D4: Legal | E4: 45630 | F4: 45666 | G4: 2 | H4: 4213 | I4: 42 | J4: CA | K4: Liberty Bell Capital | L4: New Deal | M4: 1.49 | N4: 10000 | O4: 0 | P4: 14900 | Q4: 2421.25 | R4: 12478.75 | S4: 0.1625 | T4: 2.623 | U4: 5 | W4: 0.07 | X4: 43873 | Y4: =IF(I4="","No SIC",IFERROR(VLOOKUP(I4,Ref!$A$2:$B$65,2,FALSE()),"Unclassified")) -> Trucking & Warehousing | Z4: =IF(T4="","",IF(T4<12,"Daily","Weekly")) -> Daily | AA4: =IF(T4="",0,IF(T4<12,T4*Controls!$B$29,T4*5)) -> 56.801065 | AB4: =IF(E4="",0,NETWORKDAYS(E4,Controls!$B$36,Ref!$K$2:$K$42)) -> 433 | AC4: =IF(AND(AA4>0,AB4>=Controls!$B$39*AA4),1,0) -> 1 | AD4: =IF(AND(E4<>"",E4>=Controls!$B$37,E4<=Controls!$B$38),1,0) -> 1 | AE4: =IF(IFERROR(VLOOKUP(D4,Controls!$A$64:$E$74,2,FALSE()),"No")="Yes",1,0) -> 1 | AF4: =IF(IFERROR(VLOOKUP(D4,Controls!$A$64:$E$74,3,FALSE()),"No")="Yes",1,0) -> 0 | AG4: =IF(IFERROR(VLOOKUP(D4,Controls!$A$64:$E$74,4,FALSE()),"No")="Yes",1,0) -> 0 | AH4: =IF(IFERROR(VLOOKUP(D4,Controls!$A$64:$E$74,5,FALSE()),"No")="Yes",1,0) -> 0 | AI4: =IF(ISNUMBER(MATCH(D4,Controls!$A$64:$A$74,0)),1,0) -> 1 | AJ4: =Q4-N4 -> -7578.75 | AK4: =IF(AE4=1,MAX(0,N4-Q4),0) -> 7578.75 | AL4: =IF(OR(V4="",V4=0),0,N4/V4) -> 0 | AM4: =IF(OR(V4="",V4=0),0,1) -> 0 | AN4: =IF(OR(E4="",F4=""),0,NETWORKDAYS(E4,F4,Ref!$K$2:$K$42)) -> 25 | AO4: =IF(L4="Renewal",1,0) -> 0 | AP4: =AC4*AD4 -> 1 | AQ4: =IF(AND(G4<>"",'Historical Score'!$C$6<>""),IF(G4='Historical Score'!$C$6,1,0),0) -> 1 | AR4: =IF(AND(L4<>"",'Historical Score'!$C$5<>""),IF(L4='Historical Score'!$C$5,1,0),0) -> 1 | AS4: =IF(AND(Y4<>"",'Historical Score'!$C$7<>""),IF(Y4='Historical Score'!$C$7,1,0),0) -> 0 | AT4: =IF(AND(K4<>"",'Historical Score'!$C$8<>""),IF(K4='Historical Score'!$C$8,1,0),0) -> 0 | AU4: =IF(AND(J4<>"",'Historical Score'!$C$9<>""),IF(J4='Historical Score'!$C$9,1,0),0) -> 0 | AV4: =AR4*AS4*AQ4 -> 0 | AW4: =AR4*AT4*AQ4 -> 0 | AX4: =AR4*AS4 -> 0 | AY4: =AR4*AT4 -> 0 | AZ4: =AR4*AQ4 -> 1 | BA4: =AR4 -> 1 | BB4: =1 -> 1 | BC4: =IF(AV4=1,1,IF(AW4=1,2,IF(AX4=1,3,IF(AY4=1,4,IF(AZ4=1,5,IF(BA4=1,6,7)))))) -> 5 | BD4: =IF(AD4=1,CHOOSE('Historical Score'!$C$29,AV4,AW4,AX4,AY4,AZ4,BA4,BB4),0) -> 0 | BE4: =IF(BD4=1,COUNTIF($BD$2:BD4,1),"")
A5: 5674144406 | B5: Lupotec | C5: LUPOTEC INC | D5: Legal | E5: 45632 | F5: 45666 | G5: 2 | H5: 2821 | I5: 28 | J5: CA | K5: Fidelity Funding | L5: New Deal | M5: 1.49 | N5: 20000 | O5: 0 | P5: 29800 | Q5: 3140 | R5: 26660 | S5: 0.10536913 | T5: 3.279 | U5: 6 | W5: 0.09 | X5: 44539 | Y5: =IF(I5="","No SIC",IFERROR(VLOOKUP(I5,Ref!$A$2:$B$65,2,FALSE()),"Unclassified")) -> Chemicals & Allied Products | Z5: =IF(T5="","",IF(T5<12,"Daily","Weekly")) -> Daily | AA5: =IF(T5="",0,IF(T5<12,T5*Controls!$B$29,T5*5)) -> 71.006745 | AB5: =IF(E5="",0,NETWORKDAYS(E5,Controls!$B$36,Ref!$K$2:$K$42)) -> 431 | AC5: =IF(AND(AA5>0,AB5>=Controls!$B$39*AA5),1,0) -> 1 | AD5: =IF(AND(E5<>"",E5>=Controls!$B$37,E5<=Controls!$B$38),1,0) -> 1 | AE5: =IF(IFERROR(VLOOKUP(D5,Controls!$A$64:$E$74,2,FALSE()),"No")="Yes",1,0) -> 1 | AF5: =IF(IFERROR(VLOOKUP(D5,Controls!$A$64:$E$74,3,FALSE()),"No")="Yes",1,0) -> 0 | AG5: =IF(IFERROR(VLOOKUP(D5,Controls!$A$64:$E$74,4,FALSE()),"No")="Yes",1,0) -> 0 | AH5: =IF(IFERROR(VLOOKUP(D5,Controls!$A$64:$E$74,5,FALSE()),"No")="Yes",1,0) -> 0 | AI5: =IF(ISNUMBER(MATCH(D5,Controls!$A$64:$A$74,0)),1,0) -> 1 | AJ5: =Q5-N5 -> -16860 | AK5: =IF(AE5=1,MAX(0,N5-Q5),0) -> 16860 | AL5: =IF(OR(V5="",V5=0),0,N5/V5) -> 0 | AM5: =IF(OR(V5="",V5=0),0,1) -> 0 | AN5: =IF(OR(E5="",F5=""),0,NETWORKDAYS(E5,F5,Ref!$K$2:$K$42)) -> 23 | AO5: =IF(L5="Renewal",1,0) -> 0 | AP5: =AC5*AD5 -> 1 | AQ5: =IF(AND(G5<>"",'Historical Score'!$C$6<>""),IF(G5='Historical Score'!$C$6,1,0),0) -> 1 | AR5: =IF(AND(L5<>"",'Historical Score'!$C$5<>""),IF(L5='Historical Score'!$C$5,1,0),0) -> 1 | AS5: =IF(AND(Y5<>"",'Historical Score'!$C$7<>""),IF(Y5='Historical Score'!$C$7,1,0),0) -> 0 | AT5: =IF(AND(K5<>"",'Historical Score'!$C$8<>""),IF(K5='Historical Score'!$C$8,1,0),0) -> 0 | AU5: =IF(AND(J5<>"",'Historical Score'!$C$9<>""),IF(J5='Historical Score'!$C$9,1,0),0) -> 0 | AV5: =AR5*AS5*AQ5 -> 0 | AW5: =AR5*AT5*AQ5 -> 0 | AX5: =AR5*AS5 -> 0 | AY5: =AR5*AT5 -> 0 | AZ5: =AR5*AQ5 -> 1 | BA5: =AR5 -> 1 | BB5: =1 -> 1 | BC5: =IF(AV5=1,1,IF(AW5=1,2,IF(AX5=1,3,IF(AY5=1,4,IF(AZ5=1,5,IF(BA5=1,6,7)))))) -> 5 | BD5: =IF(AD5=1,CHOOSE('Historical Score'!$C$29,AV5,AW5,AX5,AY5,AZ5,BA5,BB5),0) -> 0 | BE5: =IF(BD5=1,COUNTIF($BD$2:BD5,1),"")
A6: 5674144409 | B6: AWK ENGINEERING & TRADING LLC | C6: AWK ENGINEERING & TRADING LLC | D6: Legal | E6: 45632 | F6: 45707 | G6: 3 | H6: 8711 | I6: 87 | J6: CA | K6: J Capital Solutions | L6: New Deal | M6: 1.49 | N6: 6000 | O6: 840 | P6: 8940 | Q6: 2136.24 | R6: 6803.76 | S6: 0.23895302 | T6: 3.705 | U6: 12 | W6: 0.04 | X6: 44471 | Y6: =IF(I6="","No SIC",IFERROR(VLOOKUP(I6,Ref!$A$2:$B$65,2,FALSE()),"Unclassified")) -> Engineering, Accounting & Management | Z6: =IF(T6="","",IF(T6<12,"Daily","Weekly")) -> Daily | AA6: =IF(T6="",0,IF(T6<12,T6*Controls!$B$29,T6*5)) -> 80.231775 | AB6: =IF(E6="",0,NETWORKDAYS(E6,Controls!$B$36,Ref!$K$2:$K$42)) -> 431 | AC6: =IF(AND(AA6>0,AB6>=Controls!$B$39*AA6),1,0) -> 1 | AD6: =IF(AND(E6<>"",E6>=Controls!$B$37,E6<=Controls!$B$38),1,0) -> 1 | AE6: =IF(IFERROR(VLOOKUP(D6,Controls!$A$64:$E$74,2,FALSE()),"No")="Yes",1,0) -> 1 | AF6: =IF(IFERROR(VLOOKUP(D6,Controls!$A$64:$E$74,3,FALSE()),"No")="Yes",1,0) -> 0 | AG6: =IF(IFERROR(VLOOKUP(D6,Controls!$A$64:$E$74,4,FALSE()),"No")="Yes",1,0) -> 0 | AH6: =IF(IFERROR(VLOOKUP(D6,Controls!$A$64:$E$74,5,FALSE()),"No")="Yes",1,0) -> 0 | AI6: =IF(ISNUMBER(MATCH(D6,Controls!$A$64:$A$74,0)),1,0) -> 1 | AJ6: =Q6-N6 -> -3863.76 | AK6: =IF(AE6=1,MAX(0,N6-Q6),0) -> 3863.76 | AL6: =IF(OR(V6="",V6=0),0,N6/V6) -> 0 | AM6: =IF(OR(V6="",V6=0),0,1) -> 0 | AN6: =IF(OR(E6="",F6=""),0,NETWORKDAYS(E6,F6,Ref!$K$2:$K$42)) -> 50 | AO6: =IF(L6="Renewal",1,0) -> 0 | AP6: =AC6*AD6 -> 1 | AQ6: =IF(AND(G6<>"",'Historical Score'!$C$6<>""),IF(G6='Historical Score'!$C$6,1,0),0) -> 0 | AR6: =IF(AND(L6<>"",'Historical Score'!$C$5<>""),IF(L6='Historical Score'!$C$5,1,0),0) -> 1 | AS6: =IF(AND(Y6<>"",'Historical Score'!$C$7<>""),IF(Y6='Historical Score'!$C$7,1,0),0) -> 0 | AT6: =IF(AND(K6<>"",'Historical Score'!$C$8<>""),IF(K6='Historical Score'!$C$8,1,0),0) -> 0 | AU6: =IF(AND(J6<>"",'Historical Score'!$C$9<>""),IF(J6='Historical Score'!$C$9,1,0),0) -> 0 | AV6: =AR6*AS6*AQ6 -> 0 | AW6: =AR6*AT6*AQ6 -> 0 | AX6: =AR6*AS6 -> 0 | AY6: =AR6*AT6 -> 0 | AZ6: =AR6*AQ6 -> 0 | BA6: =AR6 -> 1 | BB6: =1 -> 1 | BC6: =IF(AV6=1,1,IF(AW6=1,2,IF(AX6=1,3,IF(AY6=1,4,IF(AZ6=1,5,IF(BA6=1,6,7)))))) -> 6 | BD6: =IF(AD6=1,CHOOSE('Historical Score'!$C$29,AV6,AW6,AX6,AY6,AZ6,BA6,BB6),0) -> 0 | BE6: =IF(BD6=1,COUNTIF($BD$2:BD6,1),"")
A7: 5674145076 | B7: GLOBAL RESEARCH CONSULTANTS, LLC | C7: GLOBAL RESEARCH CONSULTANTS, LLC | D7: Closed | E7: 45638 | F7: 45755 | G7: 2 | H7: 8748 | I7: 87 | J7: GA | K7: Secure Capital Solutions 7 | L7: New Deal | M7: 1.49 | N7: 5000 | O7: 700 | P7: 7450 | Q7: 7450 | R7: 0 | S7: 1 | T7: 2.538 | U7: 0 | W7: 0.09 | Y7: =IF(I7="","No SIC",IFERROR(VLOOKUP(I7,Ref!$A$2:$B$65,2,FALSE()),"Unclassified")) -> Engineering, Accounting & Management | Z7: =IF(T7="","",IF(T7<12,"Daily","Weekly")) -> Daily | AA7: =IF(T7="",0,IF(T7<12,T7*Controls!$B$29,T7*5)) -> 54.96039 | AB7: =IF(E7="",0,NETWORKDAYS(E7,Controls!$B$36,Ref!$K$2:$K$42)) -> 427 | AC7: =IF(AND(AA7>0,AB7>=Controls!$B$39*AA7),1,0) -> 1 | AD7: =IF(AND(E7<>"",E7>=Controls!$B$37,E7<=Controls!$B$38),1,0) -> 1 | AE7: =IF(IFERROR(VLOOKUP(D7,Controls!$A$64:$E$74,2,FALSE()),"No")="Yes",1,0) -> 0 | AF7: =IF(IFERROR(VLOOKUP(D7,Controls!$A$64:$E$74,3,FALSE()),"No")="Yes",1,0) -> 1 | AG7: =IF(IFERROR(VLOOKUP(D7,Controls!$A$64:$E$74,4,FALSE()),"No")="Yes",1,0) -> 1 | AH7: =IF(IFERROR(VLOOKUP(D7,Controls!$A$64:$E$74,5,FALSE()),"No")="Yes",1,0) -> 0 | AI7: =IF(ISNUMBER(MATCH(D7,Controls!$A$64:$A$74,0)),1,0) -> 1 | AJ7: =Q7-N7 -> 2450 | AK7: =IF(AE7=1,MAX(0,N7-Q7),0) -> 0 | AL7: =IF(OR(V7="",V7=0),0,N7/V7) -> 0 | AM7: =IF(OR(V7="",V7=0),0,1) -> 0 | AN7: =IF(OR(E7="",F7=""),0,NETWORKDAYS(E7,F7,Ref!$K$2:$K$42)) -> 80 | AO7: =IF(L7="Renewal",1,0) -> 0 | AP7: =AC7*AD7 -> 1 | AQ7: =IF(AND(G7<>"",'Historical Score'!$C$6<>""),IF(G7='Historical Score'!$C$6,1,0),0) -> 1 | AR7: =IF(AND(L7<>"",'Historical Score'!$C$5<>""),IF(L7='Historical Score'!$C$5,1,0),0) -> 1 | AS7: =IF(AND(Y7<>"",'Historical Score'!$C$7<>""),IF(Y7='Historical Score'!$C$7,1,0),0) -> 0 | AT7: =IF(AND(K7<>"",'Historical Score'!$C$8<>""),IF(K7='Historical Score'!$C$8,1,0),0) -> 0 | AU7: =IF(AND(J7<>"",'Historical Score'!$C$9<>""),IF(J7='Historical Score'!$C$9,1,0),0) -> 0 | AV7: =AR7*AS7*AQ7 -> 0 | AW7: =AR7*AT7*AQ7 -> 0 | AX7: =AR7*AS7 -> 0 | AY7: =AR7*AT7 -> 0 | AZ7: =AR7*AQ7 -> 1 | BA7: =AR7 -> 1 | BB7: =1 -> 1 | BC7: =IF(AV7=1,1,IF(AW7=1,2,IF(AX7=1,3,IF(AY7=1,4,IF(AZ7=1,5,IF(BA7=1,6,7)))))) -> 5 | BD7: =IF(AD7=1,CHOOSE('Historical Score'!$C$29,AV7,AW7,AX7,AY7,AZ7,BA7,BB7),0) -> 0 | BE7: =IF(BD7=1,COUNTIF($BD$2:BD7,1),"")
A8: 5674146645 | B8: ELIZABETH CONVENIENT STORE & HAIR BRAIDING | C8: ELIZABETH CONVENIENT STORE & HAIR BRAIDING LLC | D8: Closed | E8: 45660 | F8: 45702 | G8: 5 | H8: 5411 | I8: 54 | J8: AZ | K8: ELITE FUNDING PARTNERS LLC 6 | L8: Renewal | M8: 1.4575 | N8: 4000 | O8: 560 | P8: 5830 | Q8: 5830 | R8: 0 | S8: 1 | T8: 1.967 | U8: 2 | W8: 0.04 | X8: 41745 | Y8: =IF(I8="","No SIC",IFERROR(VLOOKUP(I8,Ref!$A$2:$B$65,2,FALSE()),"Unclassified")) -> Food Stores | Z8: =IF(T8="","",IF(T8<12,"Daily","Weekly")) -> Daily | AA8: =IF(T8="",0,IF(T8<12,T8*Controls!$B$29,T8*5)) -> 42.595385 | AB8: =IF(E8="",0,NETWORKDAYS(E8,Controls!$B$36,Ref!$K$2:$K$42)) -> 413 | AC8: =IF(AND(AA8>0,AB8>=Controls!$B$39*AA8),1,0) -> 1 | AD8: =IF(AND(E8<>"",E8>=Controls!$B$37,E8<=Controls!$B$38),1,0) -> 1 | AE8: =IF(IFERROR(VLOOKUP(D8,Controls!$A$64:$E$74,2,FALSE()),"No")="Yes",1,0) -> 0 | AF8: =IF(IFERROR(VLOOKUP(D8,Controls!$A$64:$E$74,3,FALSE()),"No")="Yes",1,0) -> 1 | AG8: =IF(IFERROR(VLOOKUP(D8,Controls!$A$64:$E$74,4,FALSE()),"No")="Yes",1,0) -> 1 | AH8: =IF(IFERROR(VLOOKUP(D8,Controls!$A$64:$E$74,5,FALSE()),"No")="Yes",1,0) -> 0 | AI8: =IF(ISNUMBER(MATCH(D8,Controls!$A$64:$A$74,0)),1,0) -> 1 | AJ8: =Q8-N8 -> 1830 | AK8: =IF(AE8=1,MAX(0,N8-Q8),0) -> 0 | AL8: =IF(OR(V8="",V8=0),0,N8/V8) -> 0 | AM8: =IF(OR(V8="",V8=0),0,1) -> 0 | AN8: =IF(OR(E8="",F8=""),0,NETWORKDAYS(E8,F8,Ref!$K$2:$K$42)) -> 30 | AO8: =IF(L8="Renewal",1,0) -> 1 | AP8: =AC8*AD8 -> 1 | AQ8: =IF(AND(G8<>"",'Historical Score'!$C$6<>""),IF(G8='Historical Score'!$C$6,1,0),0) -> 0 | AR8: =IF(AND(L8<>"",'Historical Score'!$C$5<>""),IF(L8='Historical Score'!$C$5,1,0),0) -> 0 | AS8: =IF(AND(Y8<>"",'Historical Score'!$C$7<>""),IF(Y8='Historical Score'!$C$7,1,0),0) -> 0 | AT8: =IF(AND(K8<>"",'Historical Score'!$C$8<>""),IF(K8='Historical Score'!$C$8,1,0),0) -> 0 | AU8: =IF(AND(J8<>"",'Historical Score'!$C$9<>""),IF(J8='Historical Score'!$C$9,1,0),0) -> 0 | AV8: =AR8*AS8*AQ8 -> 0 | AW8: =AR8*AT8*AQ8 -> 0 | AX8: =AR8*AS8 -> 0 | AY8: =AR8*AT8 -> 0 | AZ8: =AR8*AQ8 -> 0 | BA8: =AR8 -> 0 | BB8: =1 -> 1 | BC8: =IF(AV8=1,1,IF(AW8=1,2,IF(AX8=1,3,IF(AY8=1,4,IF(AZ8=1,5,IF(BA8=1,6,7)))))) -> 7 | BD8: =IF(AD8=1,CHOOSE('Historical Score'!$C$29,AV8,AW8,AX8,AY8,AZ8,BA8,BB8),0) -> 0 | BE8: =IF(BD8=1,COUNTIF($BD$2:BD8,1),"")
A9: 5674147185 | B9: Arete Gallery Inc | C9: Arete Gallery Inc | D9: Closed | E9: 45665 | F9: 45772 | G9: 4 | H9: 8412 | I9: 84 | J9: PA | K9: Pathway Catalyst | L9: New Deal | M9: 1.49 | N9: 3500 | O9: 490 | P9: 5215 | Q9: 5215 | R9: 0 | S9: 1 | T9: 1.937 | U9: 0 | W9: 0.15 | X9: 44105 | Y9: =IF(I9="","No SIC",IFERROR(VLOOKUP(I9,Ref!$A$2:$B$65,2,FALSE()),"Unclassified")) -> Museums & Botanical Gardens | Z9: =IF(T9="","",IF(T9<12,"Daily","Weekly")) -> Daily | AA9: =IF(T9="",0,IF(T9<12,T9*Controls!$B$29,T9*5)) -> 41.945735 | AB9: =IF(E9="",0,NETWORKDAYS(E9,Controls!$B$36,Ref!$K$2:$K$42)) -> 410 | AC9: =IF(AND(AA9>0,AB9>=Controls!$B$39*AA9),1,0) -> 1 | AD9: =IF(AND(E9<>"",E9>=Controls!$B$37,E9<=Controls!$B$38),1,0) -> 1 | AE9: =IF(IFERROR(VLOOKUP(D9,Controls!$A$64:$E$74,2,FALSE()),"No")="Yes",1,0) -> 0 | AF9: =IF(IFERROR(VLOOKUP(D9,Controls!$A$64:$E$74,3,FALSE()),"No")="Yes",1,0) -> 1 | AG9: =IF(IFERROR(VLOOKUP(D9,Controls!$A$64:$E$74,4,FALSE()),"No")="Yes",1,0) -> 1 | AH9: =IF(IFERROR(VLOOKUP(D9,Controls!$A$64:$E$74,5,FALSE()),"No")="Yes",1,0) -> 0 | AI9: =IF(ISNUMBER(MATCH(D9,Controls!$A$64:$A$74,0)),1,0) -> 1 | AJ9: =Q9-N9 -> 1715 | AK9: =IF(AE9=1,MAX(0,N9-Q9),0) -> 0 | AL9: =IF(OR(V9="",V9=0),0,N9/V9) -> 0 | AM9: =IF(OR(V9="",V9=0),0,1) -> 0 | AN9: =IF(OR(E9="",F9=""),0,NETWORKDAYS(E9,F9,Ref!$K$2:$K$42)) -> 76 | AO9: =IF(L9="Renewal",1,0) -> 0 | AP9: =AC9*AD9 -> 1 | AQ9: =IF(AND(G9<>"",'Historical Score'!$C$6<>""),IF(G9='Historical Score'!$C$6,1,0),0) -> 0 | AR9: =IF(AND(L9<>"",'Historical Score'!$C$5<>""),IF(L9='Historical Score'!$C$5,1,0),0) -> 1 | AS9: =IF(AND(Y9<>"",'Historical Score'!$C$7<>""),IF(Y9='Historical Score'!$C$7,1,0),0) -> 0 | AT9: =IF(AND(K9<>"",'Historical Score'!$C$8<>""),IF(K9='Historical Score'!$C$8,1,0),0) -> 0 | AU9: =IF(AND(J9<>"",'Historical Score'!$C$9<>""),IF(J9='Historical Score'!$C$9,1,0),0) -> 0 | AV9: =AR9*AS9*AQ9 -> 0 | AW9: =AR9*AT9*AQ9 -> 0 | AX9: =AR9*AS9 -> 0 | AY9: =AR9*AT9 -> 0 | AZ9: =AR9*AQ9 -> 0 | BA9: =AR9 -> 1 | BB9: =1 -> 1 | BC9: =IF(AV9=1,1,IF(AW9=1,2,IF(AX9=1,3,IF(AY9=1,4,IF(AZ9=1,5,IF(BA9=1,6,7)))))) -> 6 | BD9: =IF(AD9=1,CHOOSE('Historical Score'!$C$29,AV9,AW9,AX9,AY9,AZ9,BA9,BB9),0) -> 0 | BE9: =IF(BD9=1,COUNTIF($BD$2:BD9,1),"")
A10: 5674147188 | B10: S&E ENTERPRISE | C10: S&E ENTERPRISE LLC | D10: Closed | E10: 45666 | F10: 45722 | G10: 2 | H10: 6531 | I10: 65 | J10: RI | K10: Triumph Cap Fund | L10: New Deal | M10: 1.49 | N10: 5000 | O10: 700 | P10: 7450 | Q10: 7450 | R10: 0 | S10: 1 | T10: 2.443 | U10: 0 | W10: 0.06 | X10: 45005 | Y10: =IF(I10="","No SIC",IFERROR(VLOOKUP(I10,Ref!$A$2:$B$65,2,FALSE()),"Unclassified")) -> Real Estate | Z10: =IF(T10="","",IF(T10<12,"Daily","Weekly")) -> Daily | AA10: =IF(T10="",0,IF(T10<12,T10*Controls!$B$29,T10*5)) -> 52.903165 | AB10: =IF(E10="",0,NETWORKDAYS(E10,Controls!$B$36,Ref!$K$2:$K$42)) -> 409 | AC10: =IF(AND(AA10>0,AB10>=Controls!$B$39*AA10),1,0) -> 1 | AD10: =IF(AND(E10<>"",E10>=Controls!$B$37,E10<=Controls!$B$38),1,0) -> 1 | AE10: =IF(IFERROR(VLOOKUP(D10,Controls!$A$64:$E$74,2,FALSE()),"No")="Yes",1,0) -> 0 | AF10: =IF(IFERROR(VLOOKUP(D10,Controls!$A$64:$E$74,3,FALSE()),"No")="Yes",1,0) -> 1 | AG10: =IF(IFERROR(VLOOKUP(D10,Controls!$A$64:$E$74,4,FALSE()),"No")="Yes",1,0) -> 1 | AH10: =IF(IFERROR(VLOOKUP(D10,Controls!$A$64:$E$74,5,FALSE()),"No")="Yes",1,0) -> 0 | AI10: =IF(ISNUMBER(MATCH(D10,Controls!$A$64:$A$74,0)),1,0) -> 1 | AJ10: =Q10-N10 -> 2450 | AK10: =IF(AE10=1,MAX(0,N10-Q10),0) -> 0 | AL10: =IF(OR(V10="",V10=0),0,N10/V10) -> 0 | AM10: =IF(OR(V10="",V10=0),0,1) -> 0 | AN10: =IF(OR(E10="",F10=""),0,NETWORKDAYS(E10,F10,Ref!$K$2:$K$42)) -> 39 | AO10: =IF(L10="Renewal",1,0) -> 0 | AP10: =AC10*AD10 -> 1 | AQ10: =IF(AND(G10<>"",'Historical Score'!$C$6<>""),IF(G10='Historical Score'!$C$6,1,0),0) -> 1 | AR10: =IF(AND(L10<>"",'Historical Score'!$C$5<>""),IF(L10='Historical Score'!$C$5,1,0),0) -> 1 | AS10: =IF(AND(Y10<>"",'Historical Score'!$C$7<>""),IF(Y10='Historical Score'!$C$7,1,0),0) -> 0 | AT10: =IF(AND(K10<>"",'Historical Score'!$C$8<>""),IF(K10='Historical Score'!$C$8,1,0),0) -> 0 | AU10: =IF(AND(J10<>"",'Historical Score'!$C$9<>""),IF(J10='Historical Score'!$C$9,1,0),0) -> 0 | AV10: =AR10*AS10*AQ10 -> 0 | AW10: =AR10*AT10*AQ10 -> 0 | AX10: =AR10*AS10 -> 0 | AY10: =AR10*AT10 -> 0 | AZ10: =AR10*AQ10 -> 1 | BA10: =AR10 -> 1 | BB10: =1 -> 1 | BC10: =IF(AV10=1,1,IF(AW10=1,2,IF(AX10=1,3,IF(AY10=1,4,IF(AZ10=1,5,IF(BA10=1,6,7)))))) -> 5 | BD10: =IF(AD10=1,CHOOSE('Historical Score'!$C$29,AV10,AW10,AX10,AY10,AZ10,BA10,BB10),0) -> 0 | BE10: =IF(BD10=1,COUNTIF($BD$2:BD10,1),"")
A11: 5674147393 | B11: Beeson Farms & Hauling LLC | C11: Beeson Farms & Hauling LLC | D11: Closed | E11: 45667 | F11: 45756 | G11: 5 | H11: 0191 | I11: 01 | J11: NC | K11: Key Capital Funding | L11: New Deal | M11: 1.49 | N11: 30000 | O11: 4200 | P11: 44700 | Q11: 44700 | R11: 0 | S11: 1 | T11: 20.19 | U11: 0 | W11: 0.05 | X11: 43579 | Y11: =IF(I11="","No SIC",IFERROR(VLOOKUP(I11,Ref!$A$2:$B$65,2,FALSE()),"Unclassified")) -> Agricultural Production - Crops | Z11: =IF(T11="","",IF(T11<12,"Daily","Weekly")) -> Weekly | AA11: =IF(T11="",0,IF(T11<12,T11*Controls!$B$29,T11*5)) -> 100.95 | AB11: =IF(E11="",0,NETWORKDAYS(E11,Controls!$B$36,Ref!$K$2:$K$42)) -> 408 | AC11: =IF(AND(AA11>0,AB11>=Controls!$B$39*AA11),1,0) -> 1 | AD11: =IF(AND(E11<>"",E11>=Controls!$B$37,E11<=Controls!$B$38),1,0) -> 1 | AE11: =IF(IFERROR(VLOOKUP(D11,Controls!$A$64:$E$74,2,FALSE()),"No")="Yes",1,0) -> 0 | AF11: =IF(IFERROR(VLOOKUP(D11,Controls!$A$64:$E$74,3,FALSE()),"No")="Yes",1,0) -> 1 | AG11: =IF(IFERROR(VLOOKUP(D11,Controls!$A$64:$E$74,4,FALSE()),"No")="Yes",1,0) -> 1 | AH11: =IF(IFERROR(VLOOKUP(D11,Controls!$A$64:$E$74,5,FALSE()),"No")="Yes",1,0) -> 0 | AI11: =IF(ISNUMBER(MATCH(D11,Controls!$A$64:$A$74,0)),1,0) -> 1 | AJ11: =Q11-N11 -> 14700 | AK11: =IF(AE11=1,MAX(0,N11-Q11),0) -> 0 | AL11: =IF(OR(V11="",V11=0),0,N11/V11) -> 0 | AM11: =IF(OR(V11="",V11=0),0,1) -> 0 | AN11: =IF(OR(E11="",F11=""),0,NETWORKDAYS(E11,F11,Ref!$K$2:$K$42)) -> 62 | AO11: =IF(L11="Renewal",1,0) -> 0 | AP11: =AC11*AD11 -> 1 | AQ11: =IF(AND(G11<>"",'Historical Score'!$C$6<>""),IF(G11='Historical Score'!$C$6,1,0),0) -> 0 | AR11: =IF(AND(L11<>"",'Historical Score'!$C$5<>""),IF(L11='Historical Score'!$C$5,1,0),0) -> 1 | AS11: =IF(AND(Y11<>"",'Historical Score'!$C$7<>""),IF(Y11='Historical Score'!$C$7,1,0),0) -> 0 | AT11: =IF(AND(K11<>"",'Historical Score'!$C$8<>""),IF(K11='Historical Score'!$C$8,1,0),0) -> 0 | AU11: =IF(AND(J11<>"",'Historical Score'!$C$9<>""),IF(J11='Historical Score'!$C$9,1,0),0) -> 0 | AV11: =AR11*AS11*AQ11 -> 0 | AW11: =AR11*AT11*AQ11 -> 0 | AX11: =AR11*AS11 -> 0 | AY11: =AR11*AT11 -> 0 | AZ11: =AR11*AQ11 -> 0 | BA11: =AR11 -> 1 | BB11: =1 -> 1 | BC11: =IF(AV11=1,1,IF(AW11=1,2,IF(AX11=1,3,IF(AY11=1,4,IF(AZ11=1,5,IF(BA11=1,6,7)))))) -> 6 | BD11: =IF(AD11=1,CHOOSE('Historical Score'!$C$29,AV11,AW11,AX11,AY11,AZ11,BA11,BB11),0) -> 0 | BE11: =IF(BD11=1,COUNTIF($BD$2:BD11,1),"")
A12: 5674147441 | B12: SJ HOSPICE SERVICES | C12: SJ HOSPICE SERVICES LLC | D12: Closed | E12: 45670 | F12: 45783 | G12: 2 | H12: 8082 | I12: 80 | J12: TX | K12: ICB FUNDING | L12: New Deal | M12: 1.39 | N12: 8500 | O12: 765 | P12: 11815 | Q12: 11815 | R12: 0 | S12: 1 | T12: 2.539 | U12: 0 | W12: 0.04 | X12: 42892 | Y12: =IF(I12="","No SIC",IFERROR(VLOOKUP(I12,Ref!$A$2:$B$65,2,FALSE()),"Unclassified")) -> Health Services | Z12: =IF(T12="","",IF(T12<12,"Daily","Weekly")) -> Daily | AA12: =IF(T12="",0,IF(T12<12,T12*Controls!$B$29,T12*5)) -> 54.982045 | AB12: =IF(E12="",0,NETWORKDAYS(E12,Controls!$B$36,Ref!$K$2:$K$42)) -> 407 | AC12: =IF(AND(AA12>0,AB12>=Controls!$B$39*AA12),1,0) -> 1 | AD12: =IF(AND(E12<>"",E12>=Controls!$B$37,E12<=Controls!$B$38),1,0) -> 1 | AE12: =IF(IFERROR(VLOOKUP(D12,Controls!$A$64:$E$74,2,FALSE()),"No")="Yes",1,0) -> 0 | AF12: =IF(IFERROR(VLOOKUP(D12,Controls!$A$64:$E$74,3,FALSE()),"No")="Yes",1,0) -> 1 | AG12: =IF(IFERROR(VLOOKUP(D12,Controls!$A$64:$E$74,4,FALSE()),"No")="Yes",1,0) -> 1 | AH12: =IF(IFERROR(VLOOKUP(D12,Controls!$A$64:$E$74,5,FALSE()),"No")="Yes",1,0) -> 0 | AI12: =IF(ISNUMBER(MATCH(D12,Controls!$A$64:$A$74,0)),1,0) -> 1 | AJ12: =Q12-N12 -> 3315 | AK12: =IF(AE12=1,MAX(0,N12-Q12),0) -> 0 | AL12: =IF(OR(V12="",V12=0),0,N12/V12) -> 0 | AM12: =IF(OR(V12="",V12=0),0,1) -> 0 | AN12: =IF(OR(E12="",F12=""),0,NETWORKDAYS(E12,F12,Ref!$K$2:$K$42)) -> 80 | AO12: =IF(L12="Renewal",1,0) -> 0 | AP12: =AC12*AD12 -> 1 | AQ12: =IF(AND(G12<>"",'Historical Score'!$C$6<>""),IF(G12='Historical Score'!$C$6,1,0),0) -> 1 | AR12: =IF(AND(L12<>"",'Historical Score'!$C$5<>""),IF(L12='Historical Score'!$C$5,1,0),0) -> 1 | AS12: =IF(AND(Y12<>"",'Historical Score'!$C$7<>""),IF(Y12='Historical Score'!$C$7,1,0),0) -> 0 | AT12: =IF(AND(K12<>"",'Historical Score'!$C$8<>""),IF(K12='Historical Score'!$C$8,1,0),0) -> 0 | AU12: =IF(AND(J12<>"",'Historical Score'!$C$9<>""),IF(J12='Historical Score'!$C$9,1,0),0) -> 1 | AV12: =AR12*AS12*AQ12 -> 0 | AW12: =AR12*AT12*AQ12 -> 0 | AX12: =AR12*AS12 -> 0 | AY12: =AR12*AT12 -> 0 | AZ12: =AR12*AQ12 -> 1 | BA12: =AR12 -> 1 | BB12: =1 -> 1 | BC12: =IF(AV12=1,1,IF(AW12=1,2,IF(AX12=1,3,IF(AY12=1,4,IF(AZ12=1,5,IF(BA12=1,6,7)))))) -> 5 | BD12: =IF(AD12=1,CHOOSE('Historical Score'!$C$29,AV12,AW12,AX12,AY12,AZ12,BA12,BB12),0) -> 0 | BE12: =IF(BD12=1,COUNTIF($BD$2:BD12,1),"")
A13: 5674147491 | B13: ROPP JERSEY CHEESE LLC | C13: ROPP JERSEY CHEESE LLC | D13: Legal | E13: 45670 | F13: 46234 | G13: 1 | H13: 5812 | I13: 58 | J13: IL | K13: ROYAL FUNDING GROUP | L13: New Deal | M13: 1.49 | N13: 12000 | O13: 1680 | P13: 17880 | Q13: 9022 | R13: 8858 | S13: 0.50458613 | T13: 2.706 | U13: 12 | W13: 0.13 | X13: 38507 | Y13: =IF(I13="","No SIC",IFERROR(VLOOKUP(I13,Ref!$A$2:$B$65,2,FALSE()),"Unclassified")) -> Eating & Drinking Places | Z13: =IF(T13="","",IF(T13<12,"Daily","Weekly")) -> Daily | AA13: =IF(T13="",0,IF(T13<12,T13*Controls!$B$29,T13*5)) -> 58.59843 | AB13: =IF(E13="",0,NETWORKDAYS(E13,Controls!$B$36,Ref!$K$2:$K$42)) -> 407 | AC13: =IF(AND(AA13>0,AB13>=Controls!$B$39*AA13),1,0) -> 1 | AD13: =IF(AND(E13<>"",E13>=Controls!$B$37,E13<=Controls!$B$38),1,0) -> 1 | AE13: =IF(IFERROR(VLOOKUP(D13,Controls!$A$64:$E$74,2,FALSE()),"No")="Yes",1,0) -> 1 | AF13: =IF(IFERROR(VLOOKUP(D13,Controls!$A$64:$E$74,3,FALSE()),"No")="Yes",1,0) -> 0 | AG13: =IF(IFERROR(VLOOKUP(D13,Controls!$A$64:$E$74,4,FALSE()),"No")="Yes",1,0) -> 0 | AH13: =IF(IFERROR(VLOOKUP(D13,Controls!$A$64:$E$74,5,FALSE()),"No")="Yes",1,0) -> 0 | AI13: =IF(ISNUMBER(MATCH(D13,Controls!$A$64:$A$74,0)),1,0) -> 1 | AJ13: =Q13-N13 -> -2978 | AK13: =IF(AE13=1,MAX(0,N13-Q13),0) -> 2978 | AL13: =IF(OR(V13="",V13=0),0,N13/V13) -> 0 | AM13: =IF(OR(V13="",V13=0),0,1) -> 0 | AN13: =IF(OR(E13="",F13=""),0,NETWORKDAYS(E13,F13,Ref!$K$2:$K$42)) -> 390 | AO13: =IF(L13="Renewal",1,0) -> 0 | AP13: =AC13*AD13 -> 1 | AQ13: =IF(AND(G13<>"",'Historical Score'!$C$6<>""),IF(G13='Historical Score'!$C$6,1,0),0) -> 0 | AR13: =IF(AND(L13<>"",'Historical Score'!$C$5<>""),IF(L13='Historical Score'!$C$5,1,0),0) -> 1 | AS13: =IF(AND(Y13<>"",'Historical Score'!$C$7<>""),IF(Y13='Historical Score'!$C$7,1,0),0) -> 0 | AT13: =IF(AND(K13<>"",'Historical Score'!$C$8<>""),IF(K13='Historical Score'!$C$8,1,0),0) -> 0 | AU13: =IF(AND(J13<>"",'Historical Score'!$C$9<>""),IF(J13='Historical Score'!$C$9,1,0),0) -> 0 | AV13: =AR13*AS13*AQ13 -> 0 | AW13: =AR13*AT13*AQ13 -> 0 | AX13: =AR13*AS13 -> 0 | AY13: =AR13*AT13 -> 0 | AZ13: =AR13*AQ13 -> 0 | BA13: =AR13 -> 1 | BB13: =1 -> 1 | BC13: =IF(AV13=1,1,IF(AW13=1,2,IF(AX13=1,3,IF(AY13=1,4,IF(AZ13=1,5,IF(BA13=1,6,7)))))) -> 6 | BD13: =IF(AD13=1,CHOOSE('Historical Score'!$C$29,AV13,AW13,AX13,AY13,AZ13,BA13,BB13),0) -> 0 | BE13: =IF(BD13=1,COUNTIF($BD$2:BD13,1),"")
A14: 5674147495 | B14: ISHI MEDICAL EQUIPMENT & SUPPLIES INC Calle Primera | C14: ISHI MEDICAL EQUIPMENT & SUPPLIES INC Calle Primera | D14: Legal | E14: 45670 | F14: 45721 | G14: 3 | H14: 5047 | I14: 50 | J14: CA | K14: Key Capital Funding | L14: New Deal | M14: 1.49 | N14: 12000 | O14: 1680 | P14: 17880 | Q14: 3184 | R14: 14696 | S14: 0.17807606 | T14: 2.951 | U14: 15 | W14: 0.09 | X14: 38507 | Y14: =IF(I14="","No SIC",IFERROR(VLOOKUP(I14,Ref!$A$2:$B$65,2,FALSE()),"Unclassified")) -> Wholesale Trade - Durable Goods | Z14: =IF(T14="","",IF(T14<12,"Daily","Weekly")) -> Daily | AA14: =IF(T14="",0,IF(T14<12,T14*Controls!$B$29,T14*5)) -> 63.903905 | AB14: =IF(E14="",0,NETWORKDAYS(E14,Controls!$B$36,Ref!$K$2:$K$42)) -> 407 | AC14: =IF(AND(AA14>0,AB14>=Controls!$B$39*AA14),1,0) -> 1 | AD14: =IF(AND(E14<>"",E14>=Controls!$B$37,E14<=Controls!$B$38),1,0) -> 1 | AE14: =IF(IFERROR(VLOOKUP(D14,Controls!$A$64:$E$74,2,FALSE()),"No")="Yes",1,0) -> 1 | AF14: =IF(IFERROR(VLOOKUP(D14,Controls!$A$64:$E$74,3,FALSE()),"No")="Yes",1,0) -> 0 | AG14: =IF(IFERROR(VLOOKUP(D14,Controls!$A$64:$E$74,4,FALSE()),"No")="Yes",1,0) -> 0 | AH14: =IF(IFERROR(VLOOKUP(D14,Controls!$A$64:$E$74,5,FALSE()),"No")="Yes",1,0) -> 0 | AI14: =IF(ISNUMBER(MATCH(D14,Controls!$A$64:$A$74,0)),1,0) -> 1 | AJ14: =Q14-N14 -> -8816 | AK14: =IF(AE14=1,MAX(0,N14-Q14),0) -> 8816 | AL14: =IF(OR(V14="",V14=0),0,N14/V14) -> 0 | AM14: =IF(OR(V14="",V14=0),0,1) -> 0 | AN14: =IF(OR(E14="",F14=""),0,NETWORKDAYS(E14,F14,Ref!$K$2:$K$42)) -> 36 | AO14: =IF(L14="Renewal",1,0) -> 0 | AP14: =AC14*AD14 -> 1 | AQ14: =IF(AND(G14<>"",'Historical Score'!$C$6<>""),IF(G14='Historical Score'!$C$6,1,0),0) -> 0 | AR14: =IF(AND(L14<>"",'Historical Score'!$C$5<>""),IF(L14='Historical Score'!$C$5,1,0),0) -> 1 | AS14: =IF(AND(Y14<>"",'Historical Score'!$C$7<>""),IF(Y14='Historical Score'!$C$7,1,0),0) -> 0 | AT14: =IF(AND(K14<>"",'Historical Score'!$C$8<>""),IF(K14='Historical Score'!$C$8,1,0),0) -> 0 | AU14: =IF(AND(J14<>"",'Historical Score'!$C$9<>""),IF(J14='Historical Score'!$C$9,1,0),0) -> 0 | AV14: =AR14*AS14*AQ14 -> 0 | AW14: =AR14*AT14*AQ14 -> 0 | AX14: =AR14*AS14 -> 0 | AY14: =AR14*AT14 -> 0 | AZ14: =AR14*AQ14 -> 0 | BA14: =AR14 -> 1 | BB14: =1 -> 1 | BC14: =IF(AV14=1,1,IF(AW14=1,2,IF(AX14=1,3,IF(AY14=1,4,IF(AZ14=1,5,IF(BA14=1,6,7)))))) -> 6 | BD14: =IF(AD14=1,CHOOSE('Historical Score'!$C$29,AV14,AW14,AX14,AY14,AZ14,BA14,BB14),0) -> 0 | BE14: =IF(BD14=1,COUNTIF($BD$2:BD14,1),"")
A15: 5674147827 | B15: Delta Security Services LLC | C15: Delta Security Services LLC | D15: Closed | E15: 45673 | F15: 45791 | G15: 1 | H15: 7382 | I15: 73 | J15: WA | K15: First Path Capital | L15: Renewal | M15: 1.49 | N15: 5000 | O15: 700 | P15: 7450 | Q15: 7450 | R15: 0 | S15: 1 | T15: 2.623 | U15: 0 | W15: 0.06 | Y15: =IF(I15="","No SIC",IFERROR(VLOOKUP(I15,Ref!$A$2:$B$65,2,FALSE()),"Unclassified")) -> Business Services | Z15: =IF(T15="","",IF(T15<12,"Daily","Weekly")) -> Daily | AA15: =IF(T15="",0,IF(T15<12,T15*Controls!$B$29,T15*5)) -> 56.801065 | AB15: =IF(E15="",0,NETWORKDAYS(E15,Controls!$B$36,Ref!$K$2:$K$42)) -> 404 | AC15: =IF(AND(AA15>0,AB15>=Controls!$B$39*AA15),1,0) -> 1 | AD15: =IF(AND(E15<>"",E15>=Controls!$B$37,E15<=Controls!$B$38),1,0) -> 1 | AE15: =IF(IFERROR(VLOOKUP(D15,Controls!$A$64:$E$74,2,FALSE()),"No")="Yes",1,0) -> 0 | AF15: =IF(IFERROR(VLOOKUP(D15,Controls!$A$64:$E$74,3,FALSE()),"No")="Yes",1,0) -> 1 | AG15: =IF(IFERROR(VLOOKUP(D15,Controls!$A$64:$E$74,4,FALSE()),"No")="Yes",1,0) -> 1 | AH15: =IF(IFERROR(VLOOKUP(D15,Controls!$A$64:$E$74,5,FALSE()),"No")="Yes",1,0) -> 0 | AI15: =IF(ISNUMBER(MATCH(D15,Controls!$A$64:$A$74,0)),1,0) -> 1 | AJ15: =Q15-N15 -> 2450 | AK15: =IF(AE15=1,MAX(0,N15-Q15),0) -> 0 | AL15: =IF(OR(V15="",V15=0),0,N15/V15) -> 0 | AM15: =IF(OR(V15="",V15=0),0,1) -> 0 | AN15: =IF(OR(E15="",F15=""),0,NETWORKDAYS(E15,F15,Ref!$K$2:$K$42)) -> 83 | AO15: =IF(L15="Renewal",1,0) -> 1 | AP15: =AC15*AD15 -> 1 | AQ15: =IF(AND(G15<>"",'Historical Score'!$C$6<>""),IF(G15='Historical Score'!$C$6,1,0),0) -> 0 | AR15: =IF(AND(L15<>"",'Historical Score'!$C$5<>""),IF(L15='Historical Score'!$C$5,1,0),0) -> 0 | AS15: =IF(AND(Y15<>"",'Historical Score'!$C$7<>""),IF(Y15='Historical Score'!$C$7,1,0),0) -> 0 | AT15: =IF(AND(K15<>"",'Historical Score'!$C$8<>""),IF(K15='Historical Score'!$C$8,1,0),0) -> 0 | AU15: =IF(AND(J15<>"",'Historical Score'!$C$9<>""),IF(J15='Historical Score'!$C$9,1,0),0) -> 0 | AV15: =AR15*AS15*AQ15 -> 0 | AW15: =AR15*AT15*AQ15 -> 0 | AX15: =AR15*AS15 -> 0 | AY15: =AR15*AT15 -> 0 | AZ15: =AR15*AQ15 -> 0 | BA15: =AR15 -> 0 | BB15: =1 -> 1 | BC15: =IF(AV15=1,1,IF(AW15=1,2,IF(AX15=1,3,IF(AY15=1,4,IF(AZ15=1,5,IF(BA15=1,6,7)))))) -> 7 | BD15: =IF(AD15=1,CHOOSE('Historical Score'!$C$29,AV15,AW15,AX15,AY15,AZ15,BA15,BB15),0) -> 0 | BE15: =IF(BD15=1,COUNTIF($BD$2:BD15,1),"")
A16: 5674148218 | B16: LTV EVENTS LLC | C16: LTV EVENTS LLC | D16: Closed | E16: 45679 | F16: 45768 | G16: 7 | H16: 7299 | I16: 72 | J16: IL | K16: Redline Capital | L16: New Deal | M16: 1.47 | N16: 4500 | O16: 630 | P16: 6615 | Q16: 6615 | R16: 0 | S16: 1 | T16: 1.928 | U16: 0 | W16: 0.083 | X16: 44256 | Y16: =IF(I16="","No SIC",IFERROR(VLOOKUP(I16,Ref!$A$2:$B$65,2,FALSE()),"Unclassified")) -> Personal Services | Z16: =IF(T16="","",IF(T16<12,"Daily","Weekly")) -> Daily | AA16: =IF(T16="",0,IF(T16<12,T16*Controls!$B$29,T16*5)) -> 41.75084 | AB16: =IF(E16="",0,NETWORKDAYS(E16,Controls!$B$36,Ref!$K$2:$K$42)) -> 401 | AC16: =IF(AND(AA16>0,AB16>=Controls!$B$39*AA16),1,0) -> 1 | AD16: =IF(AND(E16<>"",E16>=Controls!$B$37,E16<=Controls!$B$38),1,0) -> 1 | AE16: =IF(IFERROR(VLOOKUP(D16,Controls!$A$64:$E$74,2,FALSE()),"No")="Yes",1,0) -> 0 | AF16: =IF(IFERROR(VLOOKUP(D16,Controls!$A$64:$E$74,3,FALSE()),"No")="Yes",1,0) -> 1 | AG16: =IF(IFERROR(VLOOKUP(D16,Controls!$A$64:$E$74,4,FALSE()),"No")="Yes",1,0) -> 1 | AH16: =IF(IFERROR(VLOOKUP(D16,Controls!$A$64:$E$74,5,FALSE()),"No")="Yes",1,0) -> 0 | AI16: =IF(ISNUMBER(MATCH(D16,Controls!$A$64:$A$74,0)),1,0) -> 1 | AJ16: =Q16-N16 -> 2115 | AK16: =IF(AE16=1,MAX(0,N16-Q16),0) -> 0 | AL16: =IF(OR(V16="",V16=0),0,N16/V16) -> 0 | AM16: =IF(OR(V16="",V16=0),0,1) -> 0 | AN16: =IF(OR(E16="",F16=""),0,NETWORKDAYS(E16,F16,Ref!$K$2:$K$42)) -> 63 | AO16: =IF(L16="Renewal",1,0) -> 0 | AP16: =AC16*AD16 -> 1 | AQ16: =IF(AND(G16<>"",'Historical Score'!$C$6<>""),IF(G16='Historical Score'!$C$6,1,0),0) -> 0 | AR16: =IF(AND(L16<>"",'Historical Score'!$C$5<>""),IF(L16='Historical Score'!$C$5,1,0),0) -> 1 | AS16: =IF(AND(Y16<>"",'Historical Score'!$C$7<>""),IF(Y16='Historical Score'!$C$7,1,0),0) -> 0 | AT16: =IF(AND(K16<>"",'Historical Score'!$C$8<>""),IF(K16='Historical Score'!$C$8,1,0),0) -> 0 | AU16: =IF(AND(J16<>"",'Historical Score'!$C$9<>""),IF(J16='Historical Score'!$C$9,1,0),0) -> 0 | AV16: =AR16*AS16*AQ16 -> 0 | AW16: =AR16*AT16*AQ16 -> 0 | AX16: =AR16*AS16 -> 0 | AY16: =AR16*AT16 -> 0 | AZ16: =AR16*AQ16 -> 0 | BA16: =AR16 -> 1 | BB16: =1 -> 1 | BC16: =IF(AV16=1,1,IF(AW16=1,2,IF(AX16=1,3,IF(AY16=1,4,IF(AZ16=1,5,IF(BA16=1,6,7)))))) -> 6 | BD16: =IF(AD16=1,CHOOSE('Historical Score'!$C$29,AV16,AW16,AX16,AY16,AZ16,BA16,BB16),0) -> 0 | BE16: =IF(BD16=1,COUNTIF($BD$2:BD16,1),"")
A17: 5674148220 | B17: The Tailors | C17: Jojo's Sewing Co. LLC | D17: Legal | E17: 45679 | F17: 45735 | G17: 2 | H17: 5699 | I17: 56 | J17: MI | K17: Platform Funding | L17: New Deal | M17: 1.49 | N17: 4500 | O17: 630 | P17: 6705 | Q17: 2863.14 | R17: 3841.86 | S17: 0.42701566 | T17: 2.459 | U17: 7 | W17: 0.11 | X17: 44927 | Y17: =IF(I17="","No SIC",IFERROR(VLOOKUP(I17,Ref!$A$2:$B$65,2,FALSE()),"Unclassified")) -> Apparel & Accessory Stores | Z17: =IF(T17="","",IF(T17<12,"Daily","Weekly")) -> Daily | AA17: =IF(T17="",0,IF(T17<12,T17*Controls!$B$29,T17*5)) -> 53.249645 | AB17: =IF(E17="",0,NETWORKDAYS(E17,Controls!$B$36,Ref!$K$2:$K$42)) -> 401 | AC17: =IF(AND(AA17>0,AB17>=Controls!$B$39*AA17),1,0) -> 1 | AD17: =IF(AND(E17<>"",E17>=Controls!$B$37,E17<=Controls!$B$38),1,0) -> 1 | AE17: =IF(IFERROR(VLOOKUP(D17,Controls!$A$64:$E$74,2,FALSE()),"No")="Yes",1,0) -> 1 | AF17: =IF(IFERROR(VLOOKUP(D17,Controls!$A$64:$E$74,3,FALSE()),"No")="Yes",1,0) -> 0 | AG17: =IF(IFERROR(VLOOKUP(D17,Controls!$A$64:$E$74,4,FALSE()),"No")="Yes",1,0) -> 0 | AH17: =IF(IFERROR(VLOOKUP(D17,Controls!$A$64:$E$74,5,FALSE()),"No")="Yes",1,0) -> 0 | AI17: =IF(ISNUMBER(MATCH(D17,Controls!$A$64:$A$74,0)),1,0) -> 1 | AJ17: =Q17-N17 -> -1636.86 | AK17: =IF(AE17=1,MAX(0,N17-Q17),0) -> 1636.86 | AL17: =IF(OR(V17="",V17=0),0,N17/V17) -> 0 | AM17: =IF(OR(V17="",V17=0),0,1) -> 0 | AN17: =IF(OR(E17="",F17=""),0,NETWORKDAYS(E17,F17,Ref!$K$2:$K$42)) -> 40 | AO17: =IF(L17="Renewal",1,0) -> 0 | AP17: =AC17*AD17 -> 1 | AQ17: =IF(AND(G17<>"",'Historical Score'!$C$6<>""),IF(G17='Historical Score'!$C$6,1,0),0) -> 1 | AR17: =IF(AND(L17<>"",'Historical Score'!$C$5<>""),IF(L17='Historical Score'!$C$5,1,0),0) -> 1 | AS17: =IF(AND(Y17<>"",'Historical Score'!$C$7<>""),IF(Y17='Historical Score'!$C$7,1,0),0) -> 0 | AT17: =IF(AND(K17<>"",'Historical Score'!$C$8<>""),IF(K17='Historical Score'!$C$8,1,0),0) -> 0 | AU17: =IF(AND(J17<>"",'Historical Score'!$C$9<>""),IF(J17='Historical Score'!$C$9,1,0),0) -> 0 | AV17: =AR17*AS17*AQ17 -> 0 | AW17: =AR17*AT17*AQ17 -> 0 | AX17: =AR17*AS17 -> 0 | AY17: =AR17*AT17 -> 0 | AZ17: =AR17*AQ17 -> 1 | BA17: =AR17 -> 1 | BB17: =1 -> 1 | BC17: =IF(AV17=1,1,IF(AW17=1,2,IF(AX17=1,3,IF(AY17=1,4,IF(AZ17=1,5,IF(BA17=1,6,7)))))) -> 5 | BD17: =IF(AD17=1,CHOOSE('Historical Score'!$C$29,AV17,AW17,AX17,AY17,AZ17,BA17,BB17),0) -> 0 | BE17: =IF(BD17=1,COUNTIF($BD$2:BD17,1),"")
A18: 5674149050 | B18: Bright Future Academy | C18: Bright Future Academy | D18: Closed | E18: 45686 | F18: 45799 | G18: 4 | H18: 8351 | I18: 83 | J18: MN | K18: Key Capital Funding | L18: Renewal | M18: 1.41 | N18: 5000 | O18: 500 | P18: 7050 | Q18: 7050 | R18: 0 | S18: 1 | T18: 2.295 | U18: 4 | W18: 0.12 | X18: 43617 | Y18: =IF(I18="","No SIC",IFERROR(VLOOKUP(I18,Ref!$A$2:$B$65,2,FALSE()),"Unclassified")) -> Social Services | Z18: =IF(T18="","",IF(T18<12,"Daily","Weekly")) -> Daily | AA18: =IF(T18="",0,IF(T18<12,T18*Controls!$B$29,T18*5)) -> 49.698225 | AB18: =IF(E18="",0,NETWORKDAYS(E18,Controls!$B$36,Ref!$K$2:$K$42)) -> 396 | AC18: =IF(AND(AA18>0,AB18>=Controls!$B$39*AA18),1,0) -> 1 | AD18: =IF(AND(E18<>"",E18>=Controls!$B$37,E18<=Controls!$B$38),1,0) -> 1 | AE18: =IF(IFERROR(VLOOKUP(D18,Controls!$A$64:$E$74,2,FALSE()),"No")="Yes",1,0) -> 0 | AF18: =IF(IFERROR(VLOOKUP(D18,Controls!$A$64:$E$74,3,FALSE()),"No")="Yes",1,0) -> 1 | AG18: =IF(IFERROR(VLOOKUP(D18,Controls!$A$64:$E$74,4,FALSE()),"No")="Yes",1,0) -> 1 | AH18: =IF(IFERROR(VLOOKUP(D18,Controls!$A$64:$E$74,5,FALSE()),"No")="Yes",1,0) -> 0 | AI18: =IF(ISNUMBER(MATCH(D18,Controls!$A$64:$A$74,0)),1,0) -> 1 | AJ18: =Q18-N18 -> 2050 | AK18: =IF(AE18=1,MAX(0,N18-Q18),0) -> 0 | AL18: =IF(OR(V18="",V18=0),0,N18/V18) -> 0 | AM18: =IF(OR(V18="",V18=0),0,1) -> 0 | AN18: =IF(OR(E18="",F18=""),0,NETWORKDAYS(E18,F18,Ref!$K$2:$K$42)) -> 81 | AO18: =IF(L18="Renewal",1,0) -> 1 | AP18: =AC18*AD18 -> 1 | AQ18: =IF(AND(G18<>"",'Historical Score'!$C$6<>""),IF(G18='Historical Score'!$C$6,1,0),0) -> 0 | AR18: =IF(AND(L18<>"",'Historical Score'!$C$5<>""),IF(L18='Historical Score'!$C$5,1,0),0) -> 0 | AS18: =IF(AND(Y18<>"",'Historical Score'!$C$7<>""),IF(Y18='Historical Score'!$C$7,1,0),0) -> 0 | AT18: =IF(AND(K18<>"",'Historical Score'!$C$8<>""),IF(K18='Historical Score'!$C$8,1,0),0) -> 0 | AU18: =IF(AND(J18<>"",'Historical Score'!$C$9<>""),IF(J18='Historical Score'!$C$9,1,0),0) -> 0 | AV18: =AR18*AS18*AQ18 -> 0 | AW18: =AR18*AT18*AQ18 -> 0 | AX18: =AR18*AS18 -> 0 | AY18: =AR18*AT18 -> 0 | AZ18: =AR18*AQ18 -> 0 | BA18: =AR18 -> 0 | BB18: =1 -> 1 | BC18: =IF(AV18=1,1,IF(AW18=1,2,IF(AX18=1,3,IF(AY18=1,4,IF(AZ18=1,5,IF(BA18=1,6,7)))))) -> 7 | BD18: =IF(AD18=1,CHOOSE('Historical Score'!$C$29,AV18,AW18,AX18,AY18,AZ18,BA18,BB18),0) -> 0 | BE18: =IF(BD18=1,COUNTIF($BD$2:BD18,1),"")
A19: 5674149117 | B19: PRADO SALES | C19: P & F Family Construction | D19: Closed | E19: 45687 | F19: 45776 | G19: 6 | H19: 1521 | I19: 15 | J19: CA | K19: Merchant ReFi | L19: New Deal | M19: 1.49 | N19: 6000 | O19: 840 | P19: 8940 | Q19: 8940 | R19: 0 | S19: 1 | T19: 2.623 | U19: 0 | W19: 0.0835 | X19: 43739 | Y19: =IF(I19="","No SIC",IFERROR(VLOOKUP(I19,Ref!$A$2:$B$65,2,FALSE()),"Unclassified")) -> General Building Contractors | Z19: =IF(T19="","",IF(T19<12,"Daily","Weekly")) -> Daily | AA19: =IF(T19="",0,IF(T19<12,T19*Controls!$B$29,T19*5)) -> 56.801065 | AB19: =IF(E19="",0,NETWORKDAYS(E19,Controls!$B$36,Ref!$K$2:$K$42)) -> 395 | AC19: =IF(AND(AA19>0,AB19>=Controls!$B$39*AA19),1,0) -> 1 | AD19: =IF(AND(E19<>"",E19>=Controls!$B$37,E19<=Controls!$B$38),1,0) -> 1 | AE19: =IF(IFERROR(VLOOKUP(D19,Controls!$A$64:$E$74,2,FALSE()),"No")="Yes",1,0) -> 0 | AF19: =IF(IFERROR(VLOOKUP(D19,Controls!$A$64:$E$74,3,FALSE()),"No")="Yes",1,0) -> 1 | AG19: =IF(IFERROR(VLOOKUP(D19,Controls!$A$64:$E$74,4,FALSE()),"No")="Yes",1,0) -> 1 | AH19: =IF(IFERROR(VLOOKUP(D19,Controls!$A$64:$E$74,5,FALSE()),"No")="Yes",1,0) -> 0 | AI19: =IF(ISNUMBER(MATCH(D19,Controls!$A$64:$A$74,0)),1,0) -> 1 | AJ19: =Q19-N19 -> 2940 | AK19: =IF(AE19=1,MAX(0,N19-Q19),0) -> 0 | AL19: =IF(OR(V19="",V19=0),0,N19/V19) -> 0 | AM19: =IF(OR(V19="",V19=0),0,1) -> 0 | AN19: =IF(OR(E19="",F19=""),0,NETWORKDAYS(E19,F19,Ref!$K$2:$K$42)) -> 63 | AO19: =IF(L19="Renewal",1,0) -> 0 | AP19: =AC19*AD19 -> 1 | AQ19: =IF(AND(G19<>"",'Historical Score'!$C$6<>""),IF(G19='Historical Score'!$C$6,1,0),0) -> 0 | AR19: =IF(AND(L19<>"",'Historical Score'!$C$5<>""),IF(L19='Historical Score'!$C$5,1,0),0) -> 1 | AS19: =IF(AND(Y19<>"",'Historical Score'!$C$7<>""),IF(Y19='Historical Score'!$C$7,1,0),0) -> 1 | AT19: =IF(AND(K19<>"",'Historical Score'!$C$8<>""),IF(K19='Historical Score'!$C$8,1,0),0) -> 0 | AU19: =IF(AND(J19<>"",'Historical Score'!$C$9<>""),IF(J19='Historical Score'!$C$9,1,0),0) -> 0 | AV19: =AR19*AS19*AQ19 -> 0 | AW19: =AR19*AT19*AQ19 -> 0 | AX19: =AR19*AS19 -> 1 | AY19: =AR19*AT19 -> 0 | AZ19: =AR19*AQ19 -> 0 | BA19: =AR19 -> 1 | BB19: =1 -> 1 | BC19: =IF(AV19=1,1,IF(AW19=1,2,IF(AX19=1,3,IF(AY19=1,4,IF(AZ19=1,5,IF(BA19=1,6,7)))))) -> 3 | BD19: =IF(AD19=1,CHOOSE('Historical Score'!$C$29,AV19,AW19,AX19,AY19,AZ19,BA19,BB19),0) -> 0 | BE19: =IF(BD19=1,COUNTIF($BD$2:BD19,1),"")
A20: 5674149282 | B20: The Garrison | C20: Garrison Restaurant & cocktail lounge llc | D20: Closed | E20: 45691 | F20: 45782 | G20: 1 | H20: 5812 | I20: 58 | J20: TX | K20: Platform Funding | L20: Renewal | M20: 1.35 | N20: 20000 | O20: 1400 | P20: 27000 | Q20: 27000 | R20: 0 | S20: 1 | T20: 2.623 | U20: 26 | W20: 0.0771 | X20: 44562 | Y20: =IF(I20="","No SIC",IFERROR(VLOOKUP(I20,Ref!$A$2:$B$65,2,FALSE()),"Unclassified")) -> Eating & Drinking Places | Z20: =IF(T20="","",IF(T20<12,"Daily","Weekly")) -> Daily | AA20: =IF(T20="",0,IF(T20<12,T20*Controls!$B$29,T20*5)) -> 56.801065 | AB20: =IF(E20="",0,NETWORKDAYS(E20,Controls!$B$36,Ref!$K$2:$K$42)) -> 393 | AC20: =IF(AND(AA20>0,AB20>=Controls!$B$39*AA20),1,0) -> 1 | AD20: =IF(AND(E20<>"",E20>=Controls!$B$37,E20<=Controls!$B$38),1,0) -> 1 | AE20: =IF(IFERROR(VLOOKUP(D20,Controls!$A$64:$E$74,2,FALSE()),"No")="Yes",1,0) -> 0 | AF20: =IF(IFERROR(VLOOKUP(D20,Controls!$A$64:$E$74,3,FALSE()),"No")="Yes",1,0) -> 1 | AG20: =IF(IFERROR(VLOOKUP(D20,Controls!$A$64:$E$74,4,FALSE()),"No")="Yes",1,0) -> 1 | AH20: =IF(IFERROR(VLOOKUP(D20,Controls!$A$64:$E$74,5,FALSE()),"No")="Yes",1,0) -> 0 | AI20: =IF(ISNUMBER(MATCH(D20,Controls!$A$64:$A$74,0)),1,0) -> 1 | AJ20: =Q20-N20 -> 7000 | AK20: =IF(AE20=1,MAX(0,N20-Q20),0) -> 0 | AL20: =IF(OR(V20="",V20=0),0,N20/V20) -> 0 | AM20: =IF(OR(V20="",V20=0),0,1) -> 0 | AN20: =IF(OR(E20="",F20=""),0,NETWORKDAYS(E20,F20,Ref!$K$2:$K$42)) -> 65 | AO20: =IF(L20="Renewal",1,0) -> 1 | AP20: =AC20*AD20 -> 1 | AQ20: =IF(AND(G20<>"",'Historical Score'!$C$6<>""),IF(G20='Historical Score'!$C$6,1,0),0) -> 0 | AR20: =IF(AND(L20<>"",'Historical Score'!$C$5<>""),IF(L20='Historical Score'!$C$5,1,0),0) -> 0 | AS20: =IF(AND(Y20<>"",'Historical Score'!$C$7<>""),IF(Y20='Historical Score'!$C$7,1,0),0) -> 0 | AT20: =IF(AND(K20<>"",'Historical Score'!$C$8<>""),IF(K20='Historical Score'!$C$8,1,0),0) -> 0 | AU20: =IF(AND(J20<>"",'Historical Score'!$C$9<>""),IF(J20='Historical Score'!$C$9,1,0),0) -> 1 | AV20: =AR20*AS20*AQ20 -> 0 | AW20: =AR20*AT20*AQ20 -> 0 | AX20: =AR20*AS20 -> 0 | AY20: =AR20*AT20 -> 0 | AZ20: =AR20*AQ20 -> 0 | BA20: =AR20 -> 0 | BB20: =1 -> 1 | BC20: =IF(AV20=1,1,IF(AW20=1,2,IF(AX20=1,3,IF(AY20=1,4,IF(AZ20=1,5,IF(BA20=1,6,7)))))) -> 7 | BD20: =IF(AD20=1,CHOOSE('Historical Score'!$C$29,AV20,AW20,AX20,AY20,AZ20,BA20,BB20),0) -> 0 | BE20: =IF(BD20=1,COUNTIF($BD$2:BD20,1),"")
A21: 5674149485 | B21: Cloud IX salon | C21: IX llc | D21: Closed | E21: 45692 | F21: 45783 | G21: 4 | H21: 7231 | I21: 72 | J21: FL | K21: GREYSTONE | L21: Renewal | M21: 1.49 | N21: 15000 | O21: 2100 | P21: 22350 | Q21: 22350 | R21: 0 | S21: 1 | T21: 2.459 | U21: 1 | W21: 0.0553 | X21: 45402 | Y21: =IF(I21="","No SIC",IFERROR(VLOOKUP(I21,Ref!$A$2:$B$65,2,FALSE()),"Unclassified")) -> Personal Services | Z21: =IF(T21="","",IF(T21<12,"Daily","Weekly")) -> Daily | AA21: =IF(T21="",0,IF(T21<12,T21*Controls!$B$29,T21*5)) -> 53.249645 | AB21: =IF(E21="",0,NETWORKDAYS(E21,Controls!$B$36,Ref!$K$2:$K$42)) -> 392 | AC21: =IF(AND(AA21>0,AB21>=Controls!$B$39*AA21),1,0) -> 1 | AD21: =IF(AND(E21<>"",E21>=Controls!$B$37,E21<=Controls!$B$38),1,0) -> 1 | AE21: =IF(IFERROR(VLOOKUP(D21,Controls!$A$64:$E$74,2,FALSE()),"No")="Yes",1,0) -> 0 | AF21: =IF(IFERROR(VLOOKUP(D21,Controls!$A$64:$E$74,3,FALSE()),"No")="Yes",1,0) -> 1 | AG21: =IF(IFERROR(VLOOKUP(D21,Controls!$A$64:$E$74,4,FALSE()),"No")="Yes",1,0) -> 1 | AH21: =IF(IFERROR(VLOOKUP(D21,Controls!$A$64:$E$74,5,FALSE()),"No")="Yes",1,0) -> 0 | AI21: =IF(ISNUMBER(MATCH(D21,Controls!$A$64:$A$74,0)),1,0) -> 1 | AJ21: =Q21-N21 -> 7350 | AK21: =IF(AE21=1,MAX(0,N21-Q21),0) -> 0 | AL21: =IF(OR(V21="",V21=0),0,N21/V21) -> 0 | AM21: =IF(OR(V21="",V21=0),0,1) -> 0 | AN21: =IF(OR(E21="",F21=""),0,NETWORKDAYS(E21,F21,Ref!$K$2:$K$42)) -> 65 | AO21: =IF(L21="Renewal",1,0) -> 1 | AP21: =AC21*AD21 -> 1 | AQ21: =IF(AND(G21<>"",'Historical Score'!$C$6<>""),IF(G21='Historical Score'!$C$6,1,0),0) -> 0 | AR21: =IF(AND(L21<>"",'Historical Score'!$C$5<>""),IF(L21='Historical Score'!$C$5,1,0),0) -> 0 | AS21: =IF(AND(Y21<>"",'Historical Score'!$C$7<>""),IF(Y21='Historical Score'!$C$7,1,0),0) -> 0 | AT21: =IF(AND(K21<>"",'Historical Score'!$C$8<>""),IF(K21='Historical Score'!$C$8,1,0),0) -> 0 | AU21: =IF(AND(J21<>"",'Historical Score'!$C$9<>""),IF(J21='Historical Score'!$C$9,1,0),0) -> 0 | AV21: =AR21*AS21*AQ21 -> 0 | AW21: =AR21*AT21*AQ21 -> 0 | AX21: =AR21*AS21 -> 0 | AY21: =AR21*AT21 -> 0 | AZ21: =AR21*AQ21 -> 0 | BA21: =AR21 -> 0 | BB21: =1 -> 1 | BC21: =IF(AV21=1,1,IF(AW21=1,2,IF(AX21=1,3,IF(AY21=1,4,IF(AZ21=1,5,IF(BA21=1,6,7)))))) -> 7 | BD21: =IF(AD21=1,CHOOSE('Historical Score'!$C$29,AV21,AW21,AX21,AY21,AZ21,BA21,BB21),0) -> 0 | BE21: =IF(BD21=1,COUNTIF($BD$2:BD21,1),"")
A22: 5674149599 | B22: Robola Pizzeria | C22: AMC Fair Dealing | D22: Closed | E22: 45693 | F22: 45798 | G22: 6 | H22: 5812 | I22: 58 | J22: PA | K22: Splash | L22: Renewal | M22: 1.49 | N22: 5000 | O22: 700 | P22: 7450 | Q22: 7450 | R22: 0 | S22: 1 | T22: 2.459 | U22: 7 | W22: 0.12 | X22: 41030 | Y22: =IF(I22="","No SIC",IFERROR(VLOOKUP(I22,Ref!$A$2:$B$65,2,FALSE()),"Unclassified")) -> Eating & Drinking Places | Z22: =IF(T22="","",IF(T22<12,"Daily","Weekly")) -> Daily | AA22: =IF(T22="",0,IF(T22<12,T22*Controls!$B$29,T22*5)) -> 53.249645 | AB22: =IF(E22="",0,NETWORKDAYS(E22,Controls!$B$36,Ref!$K$2:$K$42)) -> 391 | AC22: =IF(AND(AA22>0,AB22>=Controls!$B$39*AA22),1,0) -> 1 | AD22: =IF(AND(E22<>"",E22>=Controls!$B$37,E22<=Controls!$B$38),1,0) -> 1 | AE22: =IF(IFERROR(VLOOKUP(D22,Controls!$A$64:$E$74,2,FALSE()),"No")="Yes",1,0) -> 0 | AF22: =IF(IFERROR(VLOOKUP(D22,Controls!$A$64:$E$74,3,FALSE()),"No")="Yes",1,0) -> 1 | AG22: =IF(IFERROR(VLOOKUP(D22,Controls!$A$64:$E$74,4,FALSE()),"No")="Yes",1,0) -> 1 | AH22: =IF(IFERROR(VLOOKUP(D22,Controls!$A$64:$E$74,5,FALSE()),"No")="Yes",1,0) -> 0 | AI22: =IF(ISNUMBER(MATCH(D22,Controls!$A$64:$A$74,0)),1,0) -> 1 | AJ22: =Q22-N22 -> 2450 | AK22: =IF(AE22=1,MAX(0,N22-Q22),0) -> 0 | AL22: =IF(OR(V22="",V22=0),0,N22/V22) -> 0 | AM22: =IF(OR(V22="",V22=0),0,1) -> 0 | AN22: =IF(OR(E22="",F22=""),0,NETWORKDAYS(E22,F22,Ref!$K$2:$K$42)) -> 75 | AO22: =IF(L22="Renewal",1,0) -> 1 | AP22: =AC22*AD22 -> 1 | AQ22: =IF(AND(G22<>"",'Historical Score'!$C$6<>""),IF(G22='Historical Score'!$C$6,1,0),0) -> 0 | AR22: =IF(AND(L22<>"",'Historical Score'!$C$5<>""),IF(L22='Historical Score'!$C$5,1,0),0) -> 0 | AS22: =IF(AND(Y22<>"",'Historical Score'!$C$7<>""),IF(Y22='Historical Score'!$C$7,1,0),0) -> 0 | AT22: =IF(AND(K22<>"",'Historical Score'!$C$8<>""),IF(K22='Historical Score'!$C$8,1,0),0) -> 0 | AU22: =IF(AND(J22<>"",'Historical Score'!$C$9<>""),IF(J22='Historical Score'!$C$9,1,0),0) -> 0 | AV22: =AR22*AS22*AQ22 -> 0 | AW22: =AR22*AT22*AQ22 -> 0 | AX22: =AR22*AS22 -> 0 | AY22: =AR22*AT22 -> 0 | AZ22: =AR22*AQ22 -> 0 | BA22: =AR22 -> 0 | BB22: =1 -> 1 | BC22: =IF(AV22=1,1,IF(AW22=1,2,IF(AX22=1,3,IF(AY22=1,4,IF(AZ22=1,5,IF(BA22=1,6,7)))))) -> 7 | BD22: =IF(AD22=1,CHOOSE('Historical Score'!$C$29,AV22,AW22,AX22,AY22,AZ22,BA22,BB22),0) -> 0 | BE22: =IF(BD22=1,COUNTIF($BD$2:BD22,1),"")
A23: 5674150031 | B23: PLLC NA | C23: Living Tree New Braunfels | D23: Closed | E23: 45698 | F23: 45775 | G23: 4 | H23: 8322 | I23: 83 | J23: TX | K23: GREYSTONE | L23: New Deal | M23: 1.49 | N23: 10000 | O23: 1400 | P23: 14900 | Q23: 14900 | R23: 0 | S23: 1 | T23: 1.967 | U23: 0 | W23: 0.0696 | X23: 43525 | Y23: =IF(I23="","No SIC",IFERROR(VLOOKUP(I23,Ref!$A$2:$B$65,2,FALSE()),"Unclassified")) -> Social Services | Z23: =IF(T23="","",IF(T23<12,"Daily","Weekly")) -> Daily | AA23: =IF(T23="",0,IF(T23<12,T23*Controls!$B$29,T23*5)) -> 42.595385 | AB23: =IF(E23="",0,NETWORKDAYS(E23,Controls!$B$36,Ref!$K$2:$K$42)) -> 388 | AC23: =IF(AND(AA23>0,AB23>=Controls!$B$39*AA23),1,0) -> 1 | AD23: =IF(AND(E23<>"",E23>=Controls!$B$37,E23<=Controls!$B$38),1,0) -> 1 | AE23: =IF(IFERROR(VLOOKUP(D23,Controls!$A$64:$E$74,2,FALSE()),"No")="Yes",1,0) -> 0 | AF23: =IF(IFERROR(VLOOKUP(D23,Controls!$A$64:$E$74,3,FALSE()),"No")="Yes",1,0) -> 1 | AG23: =IF(IFERROR(VLOOKUP(D23,Controls!$A$64:$E$74,4,FALSE()),"No")="Yes",1,0) -> 1 | AH23: =IF(IFERROR(VLOOKUP(D23,Controls!$A$64:$E$74,5,FALSE()),"No")="Yes",1,0) -> 0 | AI23: =IF(ISNUMBER(MATCH(D23,Controls!$A$64:$A$74,0)),1,0) -> 1 | AJ23: =Q23-N23 -> 4900 | AK23: =IF(AE23=1,MAX(0,N23-Q23),0) -> 0 | AL23: =IF(OR(V23="",V23=0),0,N23/V23) -> 0 | AM23: =IF(OR(V23="",V23=0),0,1) -> 0 | AN23: =IF(OR(E23="",F23=""),0,NETWORKDAYS(E23,F23,Ref!$K$2:$K$42)) -> 55 | AO23: =IF(L23="Renewal",1,0) -> 0 | AP23: =AC23*AD23 -> 1 | AQ23: =IF(AND(G23<>"",'Historical Score'!$C$6<>""),IF(G23='Historical Score'!$C$6,1,0),0) -> 0 | AR23: =IF(AND(L23<>"",'Historical Score'!$C$5<>""),IF(L23='Historical Score'!$C$5,1,0),0) -> 1 | AS23: =IF(AND(Y23<>"",'Historical Score'!$C$7<>""),IF(Y23='Historical Score'!$C$7,1,0),0) -> 0 | AT23: =IF(AND(K23<>"",'Historical Score'!$C$8<>""),IF(K23='Historical Score'!$C$8,1,0),0) -> 0 | AU23: =IF(AND(J23<>"",'Historical Score'!$C$9<>""),IF(J23='Historical Score'!$C$9,1,0),0) -> 1 | AV23: =AR23*AS23*AQ23 -> 0 | AW23: =AR23*AT23*AQ23 -> 0 | AX23: =AR23*AS23 -> 0 | AY23: =AR23*AT23 -> 0 | AZ23: =AR23*AQ23 -> 0 | BA23: =AR23 -> 1 | BB23: =1 -> 1 | BC23: =IF(AV23=1,1,IF(AW23=1,2,IF(AX23=1,3,IF(AY23=1,4,IF(AZ23=1,5,IF(BA23=1,6,7)))))) -> 6 | BD23: =IF(AD23=1,CHOOSE('Historical Score'!$C$29,AV23,AW23,AX23,AY23,AZ23,BA23,BB23),0) -> 0 | BE23: =IF(BD23=1,COUNTIF($BD$2:BD23,1),"")
A24: 5674150191 | B24: Miranda shine corp | C24: Miranda shine corp | D24: Closed | E24: 45700 | F24: 45772 | G24: 1 | H24: 7349 | I24: 73 | J24: MA | K24: Tip Top Capital | L24: New Deal | M24: 1.499 | N24: 5000 | O24: 700 | P24: 7495 | Q24: 7495 | R24: 9.094947e-13 | S24: 1 | T24: 2.295 | U24: 1 | W24: 0.05 | X24: 45026 | Y24: =IF(I24="","No SIC",IFERROR(VLOOKUP(I24,Ref!$A$2:$B$65,2,FALSE()),"Unclassified")) -> Business Services | Z24: =IF(T24="","",IF(T24<12,"Daily","Weekly")) -> Daily | AA24: =IF(T24="",0,IF(T24<12,T24*Controls!$B$29,T24*5)) -> 49.698225 | AB24: =IF(E24="",0,NETWORKDAYS(E24,Controls!$B$36,Ref!$K$2:$K$42)) -> 386 | AC24: =IF(AND(AA24>0,AB24>=Controls!$B$39*AA24),1,0) -> 1 | AD24: =IF(AND(E24<>"",E24>=Controls!$B$37,E24<=Controls!$B$38),1,0) -> 1 | AE24: =IF(IFERROR(VLOOKUP(D24,Controls!$A$64:$E$74,2,FALSE()),"No")="Yes",1,0) -> 0 | AF24: =IF(IFERROR(VLOOKUP(D24,Controls!$A$64:$E$74,3,FALSE()),"No")="Yes",1,0) -> 1 | AG24: =IF(IFERROR(VLOOKUP(D24,Controls!$A$64:$E$74,4,FALSE()),"No")="Yes",1,0) -> 1 | AH24: =IF(IFERROR(VLOOKUP(D24,Controls!$A$64:$E$74,5,FALSE()),"No")="Yes",1,0) -> 0 | AI24: =IF(ISNUMBER(MATCH(D24,Controls!$A$64:$A$74,0)),1,0) -> 1 | AJ24: =Q24-N24 -> 2495 | AK24: =IF(AE24=1,MAX(0,N24-Q24),0) -> 0 | AL24: =IF(OR(V24="",V24=0),0,N24/V24) -> 0 | AM24: =IF(OR(V24="",V24=0),0,1) -> 0 | AN24: =IF(OR(E24="",F24=""),0,NETWORKDAYS(E24,F24,Ref!$K$2:$K$42)) -> 52 | AO24: =IF(L24="Renewal",1,0) -> 0 | AP24: =AC24*AD24 -> 1 | AQ24: =IF(AND(G24<>"",'Historical Score'!$C$6<>""),IF(G24='Historical Score'!$C$6,1,0),0) -> 0 | AR24: =IF(AND(L24<>"",'Historical Score'!$C$5<>""),IF(L24='Historical Score'!$C$5,1,0),0) -> 1 | AS24: =IF(AND(Y24<>"",'Historical Score'!$C$7<>""),IF(Y24='Historical Score'!$C$7,1,0),0) -> 0 | AT24: =IF(AND(K24<>"",'Historical Score'!$C$8<>""),IF(K24='Historical Score'!$C$8,1,0),0) -> 0 | AU24: =IF(AND(J24<>"",'Historical Score'!$C$9<>""),IF(J24='Historical Score'!$C$9,1,0),0) -> 0 | AV24: =AR24*AS24*AQ24 -> 0 | AW24: =AR24*AT24*AQ24 -> 0 | AX24: =AR24*AS24 -> 0 | AY24: =AR24*AT24 -> 0 | AZ24: =AR24*AQ24 -> 0 | BA24: =AR24 -> 1 | BB24: =1 -> 1 | BC24: =IF(AV24=1,1,IF(AW24=1,2,IF(AX24=1,3,IF(AY24=1,4,IF(AZ24=1,5,IF(BA24=1,6,7)))))) -> 6 | BD24: =IF(AD24=1,CHOOSE('Historical Score'!$C$29,AV24,AW24,AX24,AY24,AZ24,BA24,BB24),0) -> 0 | BE24: =IF(BD24=1,COUNTIF($BD$2:BD24,1),"")
A25: 5674150528 | B25: Concrete Design Solutions | C25: Concrete Design Solutions | D25: Legal | E25: 45702 | F25: 45820 | G25: 3 | H25: 1611 | I25: 16 | J25: LA | K25: Splash | L25: Renewal | M25: 1.49 | N25: 22500 | O25: 3150 | P25: 33525 | Q25: 3924.41 | R25: 29600.59 | S25: 0.11705921 | T25: 28 | U25: 4 | W25: 0.1251 | X25: 39932 | Y25: =IF(I25="","No SIC",IFERROR(VLOOKUP(I25,Ref!$A$2:$B$65,2,FALSE()),"Unclassified")) -> Heavy Construction | Z25: =IF(T25="","",IF(T25<12,"Daily","Weekly")) -> Weekly | AA25: =IF(T25="",0,IF(T25<12,T25*Controls!$B$29,T25*5)) -> 140 | AB25: =IF(E25="",0,NETWORKDAYS(E25,Controls!$B$36,Ref!$K$2:$K$42)) -> 384 | AC25: =IF(AND(AA25>0,AB25>=Controls!$B$39*AA25),1,0) -> 1 | AD25: =IF(AND(E25<>"",E25>=Controls!$B$37,E25<=Controls!$B$38),1,0) -> 1 | AE25: =IF(IFERROR(VLOOKUP(D25,Controls!$A$64:$E$74,2,FALSE()),"No")="Yes",1,0) -> 1 | AF25: =IF(IFERROR(VLOOKUP(D25,Controls!$A$64:$E$74,3,FALSE()),"No")="Yes",1,0) -> 0 | AG25: =IF(IFERROR(VLOOKUP(D25,Controls!$A$64:$E$74,4,FALSE()),"No")="Yes",1,0) -> 0 | AH25: =IF(IFERROR(VLOOKUP(D25,Controls!$A$64:$E$74,5,FALSE()),"No")="Yes",1,0) -> 0 | AI25: =IF(ISNUMBER(MATCH(D25,Controls!$A$64:$A$74,0)),1,0) -> 1 | AJ25: =Q25-N25 -> -18575.59 | AK25: =IF(AE25=1,MAX(0,N25-Q25),0) -> 18575.59 | AL25: =IF(OR(V25="",V25=0),0,N25/V25) -> 0 | AM25: =IF(OR(V25="",V25=0),0,1) -> 0 | AN25: =IF(OR(E25="",F25=""),0,NETWORKDAYS(E25,F25,Ref!$K$2:$K$42)) -> 83 | AO25: =IF(L25="Renewal",1,0) -> 1 | AP25: =AC25*AD25 -> 1 | AQ25: =IF(AND(G25<>"",'Historical Score'!$C$6<>""),IF(G25='Historical Score'!$C$6,1,0),0) -> 0 | AR25: =IF(AND(L25<>"",'Historical Score'!$C$5<>""),IF(L25='Historical Score'!$C$5,1,0),0) -> 0 | AS25: =IF(AND(Y25<>"",'Historical Score'!$C$7<>""),IF(Y25='Historical Score'!$C$7,1,0),0) -> 0 | AT25: =IF(AND(K25<>"",'Historical Score'!$C$8<>""),IF(K25='Historical Score'!$C$8,1,0),0) -> 0 | AU25: =IF(AND(J25<>"",'Historical Score'!$C$9<>""),IF(J25='Historical Score'!$C$9,1,0),0) -> 0 | AV25: =AR25*AS25*AQ25 -> 0 | AW25: =AR25*AT25*AQ25 -> 0 | AX25: =AR25*AS25 -> 0 | AY25: =AR25*AT25 -> 0 | AZ25: =AR25*AQ25 -> 0 | BA25: =AR25 -> 0 | BB25: =1 -> 1 | BC25: =IF(AV25=1,1,IF(AW25=1,2,IF(AX25=1,3,IF(AY25=1,4,IF(AZ25=1,5,IF(BA25=1,6,7)))))) -> 7 | BD25: =IF(AD25=1,CHOOSE('Historical Score'!$C$29,AV25,AW25,AX25,AY25,AZ25,BA25,BB25),0) -> 0 | BE25: =IF(BD25=1,COUNTIF($BD$2:BD25,1),"")
A26: 5674150533 | B26: SIMPLY BEDLINERS & MINOR AUTO BODY REPAIR | C26: SIMPLY BEDLINERS & MINOR AUTO BODY REPAIR L.L.P. | D26: Legal | E26: 45702 | F26: 45735 | G26: 4 | H26: 7532 | I26: 75 | J26: AZ | K26: The Funding Channel | L26: Renewal | M26: 1.49 | N26: 20000 | O26: 2800 | P26: 29800 | Q26: 5962.36 | R26: 23837.64 | S26: 0.20007919 | T26: 20 | U26: 1 | W26: 0.0964 | X26: 43617 | Y26: =IF(I26="","No SIC",IFERROR(VLOOKUP(I26,Ref!$A$2:$B$65,2,FALSE()),"Unclassified")) -> Auto Repair & Services | Z26: =IF(T26="","",IF(T26<12,"Daily","Weekly")) -> Weekly | AA26: =IF(T26="",0,IF(T26<12,T26*Controls!$B$29,T26*5)) -> 100 | AB26: =IF(E26="",0,NETWORKDAYS(E26,Controls!$B$36,Ref!$K$2:$K$42)) -> 384 | AC26: =IF(AND(AA26>0,AB26>=Controls!$B$39*AA26),1,0) -> 1 | AD26: =IF(AND(E26<>"",E26>=Controls!$B$37,E26<=Controls!$B$38),1,0) -> 1 | AE26: =IF(IFERROR(VLOOKUP(D26,Controls!$A$64:$E$74,2,FALSE()),"No")="Yes",1,0) -> 1 | AF26: =IF(IFERROR(VLOOKUP(D26,Controls!$A$64:$E$74,3,FALSE()),"No")="Yes",1,0) -> 0 | AG26: =IF(IFERROR(VLOOKUP(D26,Controls!$A$64:$E$74,4,FALSE()),"No")="Yes",1,0) -> 0 | AH26: =IF(IFERROR(VLOOKUP(D26,Controls!$A$64:$E$74,5,FALSE()),"No")="Yes",1,0) -> 0 | AI26: =IF(ISNUMBER(MATCH(D26,Controls!$A$64:$A$74,0)),1,0) -> 1 | AJ26: =Q26-N26 -> -14037.64 | AK26: =IF(AE26=1,MAX(0,N26-Q26),0) -> 14037.64 | AL26: =IF(OR(V26="",V26=0),0,N26/V26) -> 0 | AM26: =IF(OR(V26="",V26=0),0,1) -> 0 | AN26: =IF(OR(E26="",F26=""),0,NETWORKDAYS(E26,F26,Ref!$K$2:$K$42)) -> 23 | AO26: =IF(L26="Renewal",1,0) -> 1 | AP26: =AC26*AD26 -> 1 | AQ26: =IF(AND(G26<>"",'Historical Score'!$C$6<>""),IF(G26='Historical Score'!$C$6,1,0),0) -> 0 | AR26: =IF(AND(L26<>"",'Historical Score'!$C$5<>""),IF(L26='Historical Score'!$C$5,1,0),0) -> 0 | AS26: =IF(AND(Y26<>"",'Historical Score'!$C$7<>""),IF(Y26='Historical Score'!$C$7,1,0),0) -> 0 | AT26: =IF(AND(K26<>"",'Historical Score'!$C$8<>""),IF(K26='Historical Score'!$C$8,1,0),0) -> 0 | AU26: =IF(AND(J26<>"",'Historical Score'!$C$9<>""),IF(J26='Historical Score'!$C$9,1,0),0) -> 0 | AV26: =AR26*AS26*AQ26 -> 0 | AW26: =AR26*AT26*AQ26 -> 0 | AX26: =AR26*AS26 -> 0 | AY26: =AR26*AT26 -> 0 | AZ26: =AR26*AQ26 -> 0 | BA26: =AR26 -> 0 | BB26: =1 -> 1 | BC26: =IF(AV26=1,1,IF(AW26=1,2,IF(AX26=1,3,IF(AY26=1,4,IF(AZ26=1,5,IF(BA26=1,6,7)))))) -> 7 | BD26: =IF(AD26=1,CHOOSE('Historical Score'!$C$29,AV26,AW26,AX26,AY26,AZ26,BA26,BB26),0) -> 0 | BE26: =IF(BD26=1,COUNTIF($BD$2:BD26,1),"")
A27: 5674150572 | B27: B & G Trucking LLC | C27: B & G Trucking LLC | D27: Legal | E27: 45702 | F27: 45715 | G27: 3 | H27: 4212 | I27: 42 | J27: IL | K27: Tip Top Capital | L27: New Deal | M27: 1.35 | N27: 10000 | O27: 0 | P27: 13500 | Q27: 843.2 | R27: 12656.8 | S27: 0.062459259 | T27: 2.623 | U27: 3 | W27: 0.0689 | X27: 43894 | Y27: =IF(I27="","No SIC",IFERROR(VLOOKUP(I27,Ref!$A$2:$B$65,2,FALSE()),"Unclassified")) -> Trucking & Warehousing | Z27: =IF(T27="","",IF(T27<12,"Daily","Weekly")) -> Daily | AA27: =IF(T27="",0,IF(T27<12,T27*Controls!$B$29,T27*5)) -> 56.801065 | AB27: =IF(E27="",0,NETWORKDAYS(E27,Controls!$B$36,Ref!$K$2:$K$42)) -> 384 | AC27: =IF(AND(AA27>0,AB27>=Controls!$B$39*AA27),1,0) -> 1 | AD27: =IF(AND(E27<>"",E27>=Controls!$B$37,E27<=Controls!$B$38),1,0) -> 1 | AE27: =IF(IFERROR(VLOOKUP(D27,Controls!$A$64:$E$74,2,FALSE()),"No")="Yes",1,0) -> 1 | AF27: =IF(IFERROR(VLOOKUP(D27,Controls!$A$64:$E$74,3,FALSE()),"No")="Yes",1,0) -> 0 | AG27: =IF(IFERROR(VLOOKUP(D27,Controls!$A$64:$E$74,4,FALSE()),"No")="Yes",1,0) -> 0 | AH27: =IF(IFERROR(VLOOKUP(D27,Controls!$A$64:$E$74,5,FALSE()),"No")="Yes",1,0) -> 0 | AI27: =IF(ISNUMBER(MATCH(D27,Controls!$A$64:$A$74,0)),1,0) -> 1 | AJ27: =Q27-N27 -> -9156.8 | AK27: =IF(AE27=1,MAX(0,N27-Q27),0) -> 9156.8 | AL27: =IF(OR(V27="",V27=0),0,N27/V27) -> 0 | AM27: =IF(OR(V27="",V27=0),0,1) -> 0 | AN27: =IF(OR(E27="",F27=""),0,NETWORKDAYS(E27,F27,Ref!$K$2:$K$42)) -> 9 | AO27: =IF(L27="Renewal",1,0) -> 0 | AP27: =AC27*AD27 -> 1 | AQ27: =IF(AND(G27<>"",'Historical Score'!$C$6<>""),IF(G27='Historical Score'!$C$6,1,0),0) -> 0 | AR27: =IF(AND(L27<>"",'Historical Score'!$C$5<>""),IF(L27='Historical Score'!$C$5,1,0),0) -> 1 | AS27: =IF(AND(Y27<>"",'Historical Score'!$C$7<>""),IF(Y27='Historical Score'!$C$7,1,0),0) -> 0 | AT27: =IF(AND(K27<>"",'Historical Score'!$C$8<>""),IF(K27='Historical Score'!$C$8,1,0),0) -> 0 | AU27: =IF(AND(J27<>"",'Historical Score'!$C$9<>""),IF(J27='Historical Score'!$C$9,1,0),0) -> 0 | AV27: =AR27*AS27*AQ27 -> 0 | AW27: =AR27*AT27*AQ27 -> 0 | AX27: =AR27*AS27 -> 0 | AY27: =AR27*AT27 -> 0 | AZ27: =AR27*AQ27 -> 0 | BA27: =AR27 -> 1 | BB27: =1 -> 1 | BC27: =IF(AV27=1,1,IF(AW27=1,2,IF(AX27=1,3,IF(AY27=1,4,IF(AZ27=1,5,IF(BA27=1,6,7)))))) -> 6 | BD27: =IF(AD27=1,CHOOSE('Historical Score'!$C$29,AV27,AW27,AX27,AY27,AZ27,BA27,BB27),0) -> 0 | BE27: =IF(BD27=1,COUNTIF($BD$2:BD27,1),"")
A28: 5674150646 | B28: DY GARAGE DOORS | C28: DY GARAGE DOORS LLC | D28: Legal | E28: 45705 | F28: 45726 | G28: 6 | H28: 1751 | I28: 17 | J28: FL | K28: Tip Top Capital | L28: New Deal | M28: 1.49 | N28: 12000 | O28: 1440 | P28: 17880 | Q28: 2295 | R28: 15585 | S28: 0.1283557 | T28: 2.296 | U28: 5 | W28: 0.0493 | X28: 43069 | Y28: =IF(I28="","No SIC",IFERROR(VLOOKUP(I28,Ref!$A$2:$B$65,2,FALSE()),"Unclassified")) -> Special Trade Contractors | Z28: =IF(T28="","",IF(T28<12,"Daily","Weekly")) -> Daily | AA28: =IF(T28="",0,IF(T28<12,T28*Controls!$B$29,T28*5)) -> 49.71988 | AB28: =IF(E28="",0,NETWORKDAYS(E28,Controls!$B$36,Ref!$K$2:$K$42)) -> 383 | AC28: =IF(AND(AA28>0,AB28>=Controls!$B$39*AA28),1,0) -> 1 | AD28: =IF(AND(E28<>"",E28>=Controls!$B$37,E28<=Controls!$B$38),1,0) -> 1 | AE28: =IF(IFERROR(VLOOKUP(D28,Controls!$A$64:$E$74,2,FALSE()),"No")="Yes",1,0) -> 1 | AF28: =IF(IFERROR(VLOOKUP(D28,Controls!$A$64:$E$74,3,FALSE()),"No")="Yes",1,0) -> 0 | AG28: =IF(IFERROR(VLOOKUP(D28,Controls!$A$64:$E$74,4,FALSE()),"No")="Yes",1,0) -> 0 | AH28: =IF(IFERROR(VLOOKUP(D28,Controls!$A$64:$E$74,5,FALSE()),"No")="Yes",1,0) -> 0 | AI28: =IF(ISNUMBER(MATCH(D28,Controls!$A$64:$A$74,0)),1,0) -> 1 | AJ28: =Q28-N28 -> -9705 | AK28: =IF(AE28=1,MAX(0,N28-Q28),0) -> 9705 | AL28: =IF(OR(V28="",V28=0),0,N28/V28) -> 0 | AM28: =IF(OR(V28="",V28=0),0,1) -> 0 | AN28: =IF(OR(E28="",F28=""),0,NETWORKDAYS(E28,F28,Ref!$K$2:$K$42)) -> 15 | AO28: =IF(L28="Renewal",1,0) -> 0 | AP28: =AC28*AD28 -> 1 | AQ28: =IF(AND(G28<>"",'Historical Score'!$C$6<>""),IF(G28='Historical Score'!$C$6,1,0),0) -> 0 | AR28: =IF(AND(L28<>"",'Historical Score'!$C$5<>""),IF(L28='Historical Score'!$C$5,1,0),0) -> 1 | AS28: =IF(AND(Y28<>"",'Historical Score'!$C$7<>""),IF(Y28='Historical Score'!$C$7,1,0),0) -> 0 | AT28: =IF(AND(K28<>"",'Historical Score'!$C$8<>""),IF(K28='Historical Score'!$C$8,1,0),0) -> 0 | AU28: =IF(AND(J28<>"",'Historical Score'!$C$9<>""),IF(J28='Historical Score'!$C$9,1,0),0) -> 0 | AV28: =AR28*AS28*AQ28 -> 0 | AW28: =AR28*AT28*AQ28 -> 0 | AX28: =AR28*AS28 -> 0 | AY28: =AR28*AT28 -> 0 | AZ28: =AR28*AQ28 -> 0 | BA28: =AR28 -> 1 | BB28: =1 -> 1 | BC28: =IF(AV28=1,1,IF(AW28=1,2,IF(AX28=1,3,IF(AY28=1,4,IF(AZ28=1,5,IF(BA28=1,6,7)))))) -> 6 | BD28: =IF(AD28=1,CHOOSE('Historical Score'!$C$29,AV28,AW28,AX28,AY28,AZ28,BA28,BB28),0) -> 0 | BE28: =IF(BD28=1,COUNTIF($BD$2:BD28,1),"")
A29: 5674150664 | B29: Wyatts Feed and Seed | C29: Wyatts Feed and Seed | D29: Legal | E29: 45706 | F29: 45812 | G29: 3 | H29: 2048 | I29: 20 | J29: AL | K29: Pathway Catalyst | L29: Renewal | M29: 1.49 | N29: 5000 | O29: 700 | P29: 7450 | Q29: 3339 | R29: 4111 | S29: 0.44818792 | T29: 2.295 | U29: 29 | W29: 0.0566 | Y29: =IF(I29="","No SIC",IFERROR(VLOOKUP(I29,Ref!$A$2:$B$65,2,FALSE()),"Unclassified")) -> Food & Kindred Products | Z29: =IF(T29="","",IF(T29<12,"Daily","Weekly")) -> Daily | AA29: =IF(T29="",0,IF(T29<12,T29*Controls!$B$29,T29*5)) -> 49.698225 | AB29: =IF(E29="",0,NETWORKDAYS(E29,Controls!$B$36,Ref!$K$2:$K$42)) -> 383 | AC29: =IF(AND(AA29>0,AB29>=Controls!$B$39*AA29),1,0) -> 1 | AD29: =IF(AND(E29<>"",E29>=Controls!$B$37,E29<=Controls!$B$38),1,0) -> 1 | AE29: =IF(IFERROR(VLOOKUP(D29,Controls!$A$64:$E$74,2,FALSE()),"No")="Yes",1,0) -> 1 | AF29: =IF(IFERROR(VLOOKUP(D29,Controls!$A$64:$E$74,3,FALSE()),"No")="Yes",1,0) -> 0 | AG29: =IF(IFERROR(VLOOKUP(D29,Controls!$A$64:$E$74,4,FALSE()),"No")="Yes",1,0) -> 0 | AH29: =IF(IFERROR(VLOOKUP(D29,Controls!$A$64:$E$74,5,FALSE()),"No")="Yes",1,0) -> 0 | AI29: =IF(ISNUMBER(MATCH(D29,Controls!$A$64:$A$74,0)),1,0) -> 1 | AJ29: =Q29-N29 -> -1661 | AK29: =IF(AE29=1,MAX(0,N29-Q29),0) -> 1661 | AL29: =IF(OR(V29="",V29=0),0,N29/V29) -> 0 | AM29: =IF(OR(V29="",V29=0),0,1) -> 0 | AN29: =IF(OR(E29="",F29=""),0,NETWORKDAYS(E29,F29,Ref!$K$2:$K$42)) -> 76 | AO29: =IF(L29="Renewal",1,0) -> 1 | AP29: =AC29*AD29 -> 1 | AQ29: =IF(AND(G29<>"",'Historical Score'!$C$6<>""),IF(G29='Historical Score'!$C$6,1,0),0) -> 0 | AR29: =IF(AND(L29<>"",'Historical Score'!$C$5<>""),IF(L29='Historical Score'!$C$5,1,0),0) -> 0 | AS29: =IF(AND(Y29<>"",'Historical Score'!$C$7<>""),IF(Y29='Historical Score'!$C$7,1,0),0) -> 0 | AT29: =IF(AND(K29<>"",'Historical Score'!$C$8<>""),IF(K29='Historical Score'!$C$8,1,0),0) -> 0 | AU29: =IF(AND(J29<>"",'Historical Score'!$C$9<>""),IF(J29='Historical Score'!$C$9,1,0),0) -> 0 | AV29: =AR29*AS29*AQ29 -> 0 | AW29: =AR29*AT29*AQ29 -> 0 | AX29: =AR29*AS29 -> 0 | AY29: =AR29*AT29 -> 0 | AZ29: =AR29*AQ29 -> 0 | BA29: =AR29 -> 0 | BB29: =1 -> 1 | BC29: =IF(AV29=1,1,IF(AW29=1,2,IF(AX29=1,3,IF(AY29=1,4,IF(AZ29=1,5,IF(BA29=1,6,7)))))) -> 7 | BD29: =IF(AD29=1,CHOOSE('Historical Score'!$C$29,AV29,AW29,AX29,AY29,AZ29,BA29,BB29),0) -> 0 | BE29: =IF(BD29=1,COUNTIF($BD$2:BD29,1),"")
A30: 5674150667 | B30: Casteen Property Maintenance | C30: Casteen Property Maintenance | D30: Legal | E30: 45706 | F30: 45713 | G30: 4 | H30: 7349 | I30: 73 | J30: NC | K30: Tip Top Capital | L30: New Deal | M30: 1.49 | N30: 4000 | O30: 0 | P30: 5960 | Q30: 119.18 | R30: 5840.82 | S30: 0.019996644 | T30: 1.64 | U30: 3 | W30: 0.0908 | X30: 43293 | Y30: =IF(I30="","No SIC",IFERROR(VLOOKUP(I30,Ref!$A$2:$B$65,2,FALSE()),"Unclassified")) -> Business Services | Z30: =IF(T30="","",IF(T30<12,"Daily","Weekly")) -> Daily | AA30: =IF(T30="",0,IF(T30<12,T30*Controls!$B$29,T30*5)) -> 35.5142 | AB30: =IF(E30="",0,NETWORKDAYS(E30,Controls!$B$36,Ref!$K$2:$K$42)) -> 383 | AC30: =IF(AND(AA30>0,AB30>=Controls!$B$39*AA30),1,0) -> 1 | AD30: =IF(AND(E30<>"",E30>=Controls!$B$37,E30<=Controls!$B$38),1,0) -> 1 | AE30: =IF(IFERROR(VLOOKUP(D30,Controls!$A$64:$E$74,2,FALSE()),"No")="Yes",1,0) -> 1 | AF30: =IF(IFERROR(VLOOKUP(D30,Controls!$A$64:$E$74,3,FALSE()),"No")="Yes",1,0) -> 0 | AG30: =IF(IFERROR(VLOOKUP(D30,Controls!$A$64:$E$74,4,FALSE()),"No")="Yes",1,0) -> 0 | AH30: =IF(IFERROR(VLOOKUP(D30,Controls!$A$64:$E$74,5,FALSE()),"No")="Yes",1,0) -> 0 | AI30: =IF(ISNUMBER(MATCH(D30,Controls!$A$64:$A$74,0)),1,0) -> 1 | AJ30: =Q30-N30 -> -3880.82 | AK30: =IF(AE30=1,MAX(0,N30-Q30),0) -> 3880.82 | AL30: =IF(OR(V30="",V30=0),0,N30/V30) -> 0 | AM30: =IF(OR(V30="",V30=0),0,1) -> 0 | AN30: =IF(OR(E30="",F30=""),0,NETWORKDAYS(E30,F30,Ref!$K$2:$K$42)) -> 6 | AO30: =IF(L30="Renewal",1,0) -> 0 | AP30: =AC30*AD30 -> 1 | AQ30: =IF(AND(G30<>"",'Historical Score'!$C$6<>""),IF(G30='Historical Score'!$C$6,1,0),0) -> 0 | AR30: =IF(AND(L30<>"",'Historical Score'!$C$5<>""),IF(L30='Historical Score'!$C$5,1,0),0) -> 1 | AS30: =IF(AND(Y30<>"",'Historical Score'!$C$7<>""),IF(Y30='Historical Score'!$C$7,1,0),0) -> 0 | AT30: =IF(AND(K30<>"",'Historical Score'!$C$8<>""),IF(K30='Historical Score'!$C$8,1,0),0) -> 0 | AU30: =IF(AND(J30<>"",'Historical Score'!$C$9<>""),IF(J30='Historical Score'!$C$9,1,0),0) -> 0 | AV30: =AR30*AS30*AQ30 -> 0 | AW30: =AR30*AT30*AQ30 -> 0 | AX30: =AR30*AS30 -> 0 | AY30: =AR30*AT30 -> 0 | AZ30: =AR30*AQ30 -> 0 | BA30: =AR30 -> 1 | BB30: =1 -> 1 | BC30: =IF(AV30=1,1,IF(AW30=1,2,IF(AX30=1,3,IF(AY30=1,4,IF(AZ30=1,5,IF(BA30=1,6,7)))))) -> 6 | BD30: =IF(AD30=1,CHOOSE('Historical Score'!$C$29,AV30,AW30,AX30,AY30,AZ30,BA30,BB30),0) -> 0 | BE30: =IF(BD30=1,COUNTIF($BD$2:BD30,1),"")
A31: 5674150725 | B31: Arkansas Climate Control | C31: Arkansas Climate Control | D31: Legal | E31: 45706 | F31: 45721 | G31: 2 | H31: 1711 | I31: 17 | J31: AR | K31: TRUSTFI | L31: New Deal | M31: 1.49 | N31: 8000 | O31: 0 | P31: 11920 | Q31: 681.36 | R31: 11238.64 | S31: 0.057161074 | T31: 2.295 | U31: 7 | W31: 0.1561 | X31: 45505 | Y31: =IF(I31="","No SIC",IFERROR(VLOOKUP(I31,Ref!$A$2:$B$65,2,FALSE()),"Unclassified")) -> Special Trade Contractors | Z31: =IF(T31="","",IF(T31<12,"Daily","Weekly")) -> Daily | AA31: =IF(T31="",0,IF(T31<12,T31*Controls!$B$29,T31*5)) -> 49.698225 | AB31: =IF(E31="",0,NETWORKDAYS(E31,Controls!$B$36,Ref!$K$2:$K$42)) -> 383 | AC31: =IF(AND(AA31>0,AB31>=Controls!$B$39*AA31),1,0) -> 1 | AD31: =IF(AND(E31<>"",E31>=Controls!$B$37,E31<=Controls!$B$38),1,0) -> 1 | AE31: =IF(IFERROR(VLOOKUP(D31,Controls!$A$64:$E$74,2,FALSE()),"No")="Yes",1,0) -> 1 | AF31: =IF(IFERROR(VLOOKUP(D31,Controls!$A$64:$E$74,3,FALSE()),"No")="Yes",1,0) -> 0 | AG31: =IF(IFERROR(VLOOKUP(D31,Controls!$A$64:$E$74,4,FALSE()),"No")="Yes",1,0) -> 0 | AH31: =IF(IFERROR(VLOOKUP(D31,Controls!$A$64:$E$74,5,FALSE()),"No")="Yes",1,0) -> 0 | AI31: =IF(ISNUMBER(MATCH(D31,Controls!$A$64:$A$74,0)),1,0) -> 1 | AJ31: =Q31-N31 -> -7318.64 | AK31: =IF(AE31=1,MAX(0,N31-Q31),0) -> 7318.64 | AL31: =IF(OR(V31="",V31=0),0,N31/V31) -> 0 | AM31: =IF(OR(V31="",V31=0),0,1) -> 0 | AN31: =IF(OR(E31="",F31=""),0,NETWORKDAYS(E31,F31,Ref!$K$2:$K$42)) -> 12 | AO31: =IF(L31="Renewal",1,0) -> 0 | AP31: =AC31*AD31 -> 1 | AQ31: =IF(AND(G31<>"",'Historical Score'!$C$6<>""),IF(G31='Historical Score'!$C$6,1,0),0) -> 1 | AR31: =IF(AND(L31<>"",'Historical Score'!$C$5<>""),IF(L31='Historical Score'!$C$5,1,0),0) -> 1 | AS31: =IF(AND(Y31<>"",'Historical Score'!$C$7<>""),IF(Y31='Historical Score'!$C$7,1,0),0) -> 0 | AT31: =IF(AND(K31<>"",'Historical Score'!$C$8<>""),IF(K31='Historical Score'!$C$8,1,0),0) -> 0 | AU31: =IF(AND(J31<>"",'Historical Score'!$C$9<>""),IF(J31='Historical Score'!$C$9,1,0),0) -> 0 | AV31: =AR31*AS31*AQ31 -> 0 | AW31: =AR31*AT31*AQ31 -> 0 | AX31: =AR31*AS31 -> 0 | AY31: =AR31*AT31 -> 0 | AZ31: =AR31*AQ31 -> 1 | BA31: =AR31 -> 1 | BB31: =1 -> 1 | BC31: =IF(AV31=1,1,IF(AW31=1,2,IF(AX31=1,3,IF(AY31=1,4,IF(AZ31=1,5,IF(BA31=1,6,7)))))) -> 5 | BD31: =IF(AD31=1,CHOOSE('Historical Score'!$C$29,AV31,AW31,AX31,AY31,AZ31,BA31,BB31),0) -> 0 | BE31: =IF(BD31=1,COUNTIF($BD$2:BD31,1),"")
A32: 5674150820 | B32: Brake Masters | C32: SLA BRAKE MASTERS LLC | D32: Closed | E32: 45707 | F32: 45841 | G32: 3 | H32: 7538 | I32: 75 | J32: CA | K32: Fundible | L32: New Deal | M32: 1.49 | N32: 10000 | O32: 1400 | P32: 14900 | Q32: 14900 | R32: 0 | S32: 1 | T32: 28 | U32: 0 | W32: 0.0702 | X32: 44866 | Y32: =IF(I32="","No SIC",IFERROR(VLOOKUP(I32,Ref!$A$2:$B$65,2,FALSE()),"Unclassified")) -> Auto Repair & Services | Z32: =IF(T32="","",IF(T32<12,"Daily","Weekly")) -> Weekly | AA32: =IF(T32="",0,IF(T32<12,T32*Controls!$B$29,T32*5)) -> 140 | AB32: =IF(E32="",0,NETWORKDAYS(E32,Controls!$B$36,Ref!$K$2:$K$42)) -> 382 | AC32: =IF(AND(AA32>0,AB32>=Controls!$B$39*AA32),1,0) -> 1 | AD32: =IF(AND(E32<>"",E32>=Controls!$B$37,E32<=Controls!$B$38),1,0) -> 1 | AE32: =IF(IFERROR(VLOOKUP(D32,Controls!$A$64:$E$74,2,FALSE()),"No")="Yes",1,0) -> 0 | AF32: =IF(IFERROR(VLOOKUP(D32,Controls!$A$64:$E$74,3,FALSE()),"No")="Yes",1,0) -> 1 | AG32: =IF(IFERROR(VLOOKUP(D32,Controls!$A$64:$E$74,4,FALSE()),"No")="Yes",1,0) -> 1 | AH32: =IF(IFERROR(VLOOKUP(D32,Controls!$A$64:$E$74,5,FALSE()),"No")="Yes",1,0) -> 0 | AI32: =IF(ISNUMBER(MATCH(D32,Controls!$A$64:$A$74,0)),1,0) -> 1 | AJ32: =Q32-N32 -> 4900 | AK32: =IF(AE32=1,MAX(0,N32-Q32),0) -> 0 | AL32: =IF(OR(V32="",V32=0),0,N32/V32) -> 0 | AM32: =IF(OR(V32="",V32=0),0,1) -> 0 | AN32: =IF(OR(E32="",F32=""),0,NETWORKDAYS(E32,F32,Ref!$K$2:$K$42)) -> 95 | AO32: =IF(L32="Renewal",1,0) -> 0 | AP32: =AC32*AD32 -> 1 | AQ32: =IF(AND(G32<>"",'Historical Score'!$C$6<>""),IF(G32='Historical Score'!$C$6,1,0),0) -> 0 | AR32: =IF(AND(L32<>"",'Historical Score'!$C$5<>""),IF(L32='Historical Score'!$C$5,1,0),0) -> 1 | AS32: =IF(AND(Y32<>"",'Historical Score'!$C$7<>""),IF(Y32='Historical Score'!$C$7,1,0),0) -> 0 | AT32: =IF(AND(K32<>"",'Historical Score'!$C$8<>""),IF(K32='Historical Score'!$C$8,1,0),0) -> 0 | AU32: =IF(AND(J32<>"",'Historical Score'!$C$9<>""),IF(J32='Historical Score'!$C$9,1,0),0) -> 0 | AV32: =AR32*AS32*AQ32 -> 0 | AW32: =AR32*AT32*AQ32 -> 0 | AX32: =AR32*AS32 -> 0 | AY32: =AR32*AT32 -> 0 | AZ32: =AR32*AQ32 -> 0 | BA32: =AR32 -> 1 | BB32: =1 -> 1 | BC32: =IF(AV32=1,1,IF(AW32=1,2,IF(AX32=1,3,IF(AY32=1,4,IF(AZ32=1,5,IF(BA32=1,6,7)))))) -> 6 | BD32: =IF(AD32=1,CHOOSE('Historical Score'!$C$29,AV32,AW32,AX32,AY32,AZ32,BA32,BB32),0) -> 0 | BE32: =IF(BD32=1,COUNTIF($BD$2:BD32,1),"")
A33: 5674150864 | B33: Rock Hard Flooring & Land Clearing of Oklahoma | C33: AKH INVESTMENT LLC | D33: Legal | E33: 45709 | F33: 45922 | G33: 1 | H33: 1629 | I33: 16 | J33: OK | K33: PEACH STATE SOLUTIONS | L33: New Deal | M33: 1.49 | N33: 12000 | O33: 1680 | P33: 17880 | Q33: 3988.73 | R33: 13891.27 | S33: 0.22308333 | T33: 18 | U33: 6 | W33: 0.0653 | X33: 44367 | Y33: =IF(I33="","No SIC",IFERROR(VLOOKUP(I33,Ref!$A$2:$B$65,2,FALSE()),"Unclassified")) -> Heavy Construction | Z33: =IF(T33="","",IF(T33<12,"Daily","Weekly")) -> Weekly | AA33: =IF(T33="",0,IF(T33<12,T33*Controls!$B$29,T33*5)) -> 90 | AB33: =IF(E33="",0,NETWORKDAYS(E33,Controls!$B$36,Ref!$K$2:$K$42)) -> 380 | AC33: =IF(AND(AA33>0,AB33>=Controls!$B$39*AA33),1,0) -> 1 | AD33: =IF(AND(E33<>"",E33>=Controls!$B$37,E33<=Controls!$B$38),1,0) -> 1 | AE33: =IF(IFERROR(VLOOKUP(D33,Controls!$A$64:$E$74,2,FALSE()),"No")="Yes",1,0) -> 1 | AF33: =IF(IFERROR(VLOOKUP(D33,Controls!$A$64:$E$74,3,FALSE()),"No")="Yes",1,0) -> 0 | AG33: =IF(IFERROR(VLOOKUP(D33,Controls!$A$64:$E$74,4,FALSE()),"No")="Yes",1,0) -> 0 | AH33: =IF(IFERROR(VLOOKUP(D33,Controls!$A$64:$E$74,5,FALSE()),"No")="Yes",1,0) -> 0 | AI33: =IF(ISNUMBER(MATCH(D33,Controls!$A$64:$A$74,0)),1,0) -> 1 | AJ33: =Q33-N33 -> -8011.27 | AK33: =IF(AE33=1,MAX(0,N33-Q33),0) -> 8011.27 | AL33: =IF(OR(V33="",V33=0),0,N33/V33) -> 0 | AM33: =IF(OR(V33="",V33=0),0,1) -> 0 | AN33: =IF(OR(E33="",F33=""),0,NETWORKDAYS(E33,F33,Ref!$K$2:$K$42)) -> 148 | AO33: =IF(L33="Renewal",1,0) -> 0 | AP33: =AC33*AD33 -> 1 | AQ33: =IF(AND(G33<>"",'Historical Score'!$C$6<>""),IF(G33='Historical Score'!$C$6,1,0),0) -> 0 | AR33: =IF(AND(L33<>"",'Historical Score'!$C$5<>""),IF(L33='Historical Score'!$C$5,1,0),0) -> 1 | AS33: =IF(AND(Y33<>"",'Historical Score'!$C$7<>""),IF(Y33='Historical Score'!$C$7,1,0),0) -> 0 | AT33: =IF(AND(K33<>"",'Historical Score'!$C$8<>""),IF(K33='Historical Score'!$C$8,1,0),0) -> 0 | AU33: =IF(AND(J33<>"",'Historical Score'!$C$9<>""),IF(J33='Historical Score'!$C$9,1,0),0) -> 0 | AV33: =AR33*AS33*AQ33 -> 0 | AW33: =AR33*AT33*AQ33 -> 0 | AX33: =AR33*AS33 -> 0 | AY33: =AR33*AT33 -> 0 | AZ33: =AR33*AQ33 -> 0 | BA33: =AR33 -> 1 | BB33: =1 -> 1 | BC33: =IF(AV33=1,1,IF(AW33=1,2,IF(AX33=1,3,IF(AY33=1,4,IF(AZ33=1,5,IF(BA33=1,6,7)))))) -> 6 | BD33: =IF(AD33=1,CHOOSE('Historical Score'!$C$29,AV33,AW33,AX33,AY33,AZ33,BA33,BB33),0) -> 0 | BE33: =IF(BD33=1,COUNTIF($BD$2:BD33,1),"")
A34: 5674151205 | B34: CRAVE WINGS LLC | C34: CRAVE WINGS LLC | D34: Legal | E34: 45713 | F34: 46051 | G34: 4 | H34: 5812 | I34: 58 | J34: TN | K34: United Secured Capital 8 | L34: New Deal | M34: 1.49 | N34: 18000 | O34: 2520 | P34: 26820 | Q34: 23960.2 | R34: 2859.8 | S34: 0.89337062 | T34: 2.787 | U34: 0 | W34: 0.0922 | Y34: =IF(I34="","No SIC",IFERROR(VLOOKUP(I34,Ref!$A$2:$B$65,2,FALSE()),"Unclassified")) -> Eating & Drinking Places | Z34: =IF(T34="","",IF(T34<12,"Daily","Weekly")) -> Daily | AA34: =IF(T34="",0,IF(T34<12,T34*Controls!$B$29,T34*5)) -> 60.352485 | AB34: =IF(E34="",0,NETWORKDAYS(E34,Controls!$B$36,Ref!$K$2:$K$42)) -> 378 | AC34: =IF(AND(AA34>0,AB34>=Controls!$B$39*AA34),1,0) -> 1 | AD34: =IF(AND(E34<>"",E34>=Controls!$B$37,E34<=Controls!$B$38),1,0) -> 1 | AE34: =IF(IFERROR(VLOOKUP(D34,Controls!$A$64:$E$74,2,FALSE()),"No")="Yes",1,0) -> 1 | AF34: =IF(IFERROR(VLOOKUP(D34,Controls!$A$64:$E$74,3,FALSE()),"No")="Yes",1,0) -> 0 | AG34: =IF(IFERROR(VLOOKUP(D34,Controls!$A$64:$E$74,4,FALSE()),"No")="Yes",1,0) -> 0 | AH34: =IF(IFERROR(VLOOKUP(D34,Controls!$A$64:$E$74,5,FALSE()),"No")="Yes",1,0) -> 0 | AI34: =IF(ISNUMBER(MATCH(D34,Controls!$A$64:$A$74,0)),1,0) -> 1 | AJ34: =Q34-N34 -> 5960.2 | AK34: =IF(AE34=1,MAX(0,N34-Q34),0) -> 0 | AL34: =IF(OR(V34="",V34=0),0,N34/V34) -> 0 | AM34: =IF(OR(V34="",V34=0),0,1) -> 0 | AN34: =IF(OR(E34="",F34=""),0,NETWORKDAYS(E34,F34,Ref!$K$2:$K$42)) -> 233 | AO34: =IF(L34="Renewal",1,0) -> 0 | AP34: =AC34*AD34 -> 1 | AQ34: =IF(AND(G34<>"",'Historical Score'!$C$6<>""),IF(G34='Historical Score'!$C$6,1,0),0) -> 0 | AR34: =IF(AND(L34<>"",'Historical Score'!$C$5<>""),IF(L34='Historical Score'!$C$5,1,0),0) -> 1 | AS34: =IF(AND(Y34<>"",'Historical Score'!$C$7<>""),IF(Y34='Historical Score'!$C$7,1,0),0) -> 0 | AT34: =IF(AND(K34<>"",'Historical Score'!$C$8<>""),IF(K34='Historical Score'!$C$8,1,0),0) -> 1 | AU34: =IF(AND(J34<>"",'Historical Score'!$C$9<>""),IF(J34='Historical Score'!$C$9,1,0),0) -> 0 | AV34: =AR34*AS34*AQ34 -> 0 | AW34: =AR34*AT34*AQ34 -> 0 | AX34: =AR34*AS34 -> 0 | AY34: =AR34*AT34 -> 1 | AZ34: =AR34*AQ34 -> 0 | BA34: =AR34 -> 1 | BB34: =1 -> 1 | BC34: =IF(AV34=1,1,IF(AW34=1,2,IF(AX34=1,3,IF(AY34=1,4,IF(AZ34=1,5,IF(BA34=1,6,7)))))) -> 4 | BD34: =IF(AD34=1,CHOOSE('Historical Score'!$C$29,AV34,AW34,AX34,AY34,AZ34,BA34,BB34),0) -> 0 | BE34: =IF(BD34=1,COUNTIF($BD$2:BD34,1),"")
